{
  "app_name": "Missive",
  "app_slug": "missive",
  "search_term": "Find the official pricing page URL for Missive (missive.com). Only provide the exact URL to the pricing page, not a summary of pricing information.",
  "timestamp": 1744695507.3726354,
  "response_text": [
    "https://missiveapp.com/pricing"
  ],
  "citations": [],
  "extracted_content": [
    {
      "url": "https://missiveapp.com/pricing",
      "is_accessible": true,
      "content": "Pay-for-what-you-use pricing\n----------------------------\n\nTry Missive risk-free for 30 days. No credit card required.\n\nBilled yearly\n\n20% off\n\nStarter\n\n$\n\n14\n\nper user/month\n\nBilled yearly\n\nFor teams with simple needs\n\nEmail,\u00a0SMS, social accounts\n\nTeam spaces and inboxes\n\nConversations and tasks\n\nSOC 2 Type II compliance\n\nProductive\n\n$\n\n24\n\nper user/month\n\nBilled yearly\n\nFor teams with workflow needs\n\nEverything in\n\nStarter\n\nplus\n\nIntegrations with external tools\n\nRules & automations\n\nBasic analytics & reporting\n\nAPI access\n\nBusiness\n\n$\n\n36\n\nper user/month\n\nBilled yearly\n\nFor teams with advanced needs\n\nEverything in\n\nProductive\n\nplus\n\nSAML and SSO\n\nIP restriction\n\nAdvanced analytics & reporting\n\nPersonalized team onboarding\n\n![Image 1: The picture of Philppe-Antoine lehoux, CEO at Missive](https://cdn.prod.website-files.com/66c7823b4706f4a0a95d2d31/67857bbe614f1a9b98134764_img-PhilLehoux.jpg)\n\n\"As a small team ourselves, we believe in accessible pricing. Your local car repair shop probably uses Missive. So does a fancy tech company like Maple. We want everyone to be able to enjoy their inbox. Not just the Fortune guys.\"\n--------------------------------------------------------------------------------------------------------------------------------\n\n**Philippe Lehoux**\n\n**\u00b7**\n\nCEO at Missive\n\nStarter\n\nProductive\n\nBusiness\n\nWorkspace\n\nUsers\n\nUp to 5 users\n\nUp to 50 users\n\nUnlimited\n\nKey features\n\nSOC 2 Type II\n\nAudited security policies & procedures\n\nRules\n\nAutomate your workflows\n\n**AI automations (Requires AI key)**\n\nSupercharge your workflows with AI\n\nIntegrations\n\nChatGPT, Pipedrive, Trello and more\n\nAnalytics\n\nMeasure key performance metrics\n\nBasics\n\nAdvanced\n\nAPI access\n\nPost content to Missive\n\nSAML Single Sign-On\n\nOkta, Azure AD, etc.\n\nIP restrictions\n\nSecure access by location\n\nPersonalized Onboarding\n\nLive sessions with our experts\n\nYearly plan\n\nView all plan features\n\nTeam Inboxes\n\nPersonal Inboxes\n\nAliases\n\nMultiple signatures\n\nLabels\n\nSnooze\n\nSend later / Undo send\n\nAuto CC / BCC\n\nUnlimited email import history\n\nEditing with AI\n\nInternal threads\n\nCollaborative drafting\n\nAssignment\n\nInternal read statuses\n\nTeam spaces\n\nInternal chat\n\nTeam signatures\n\nAudit trail\n\nShared contact books\n\nContact syncing (Gmail, Office 365)\n\nCalendar syncing (Gmail, Office 365)\n\nDue dates\n\nEmail referencing\n\nAssigned by\n\nMultiple assignees\n\nFiltering and sorting\n\nCalendar view\n\nCanned responses\n\nRules\n\nAuto-assignment\n\nAuto-follow ups\n\nInstant AI drafts\n\nAI Rules and automations\n\nTranslate to any language\n\nSummarize conversations\n\nTurn an idea into an email\n\nDesign your own prompts\n\nGmail & Google workspace\n\nOutlook\n\nIMAP\n\nWhatsapp\n\nMessenger\n\nInstagram\n\nSMS via Twilio\n\nVideo Chat via Twilio\n\nChatGPT, OpenAI\n\nDropbox, Google Drive\n\nZoom, Google Meet, etc.\n\nAsana, ClickUp, Trello, etc.\n\nHubspot, Salesforce, etc.\n\nAPI Access\n\nCompany-wide analytics\n\nSLA reports\n\nTeam performance reports\n\nUser performance reports\n\nFilter by labels and more\n\nAnalytics exports\n\nRoles and permissions\n\nSOC 2 Type II Certified\n\nGDPR Ready\n\nSAML Single Sign-On\n\nIP restrictions\n\nWorkspace\n\nUsers\n\nUp to 5\n\nKey features\n\nSOC 2\n\nAudited security policies & procedures\n\nRules\n\nAutomate your workflows\n\n**Al Automations (Requires key)**\n\nSupercharge your workflows with AI\n\nIntegrations\n\nChatGPT, Pipedrive, Trello and more\n\nAnalytics\n\nMeasure key performance metrics\n\nAPI access\n\nPost content to Missive\n\nSAML Single Sign-On\n\nOkta, Azure AD, etc.\n\nIP restrictions\n\nSecure access by location\n\nPersonalized Onboarding\n\nLive sessions with our experts\n\nWorkspace\n\nUsers\n\nUp to 50\n\nKey features\n\nSOC 2\n\nAudited security policies & procedures\n\nRules\n\nAutomate your workflows\n\n**Al Automations (Requires key)**\n\nSupercharge your workflows with AI\n\nIntegrations\n\nChatGPT, Pipedrive, Trello and more\n\nAnalytics\n\nMeasure key performance metrics\n\nBasic\n\nAPI access\n\nPost content to Missive\n\nSAML Single Sign-On\n\nOkta, Azure AD, etc.\n\nIP restrictions\n\nSecure access by location\n\nPersonalized Onboarding\n\nLive sessions with our experts\n\nWorkspace\n\nUsers\n\nUnlimited\n\nKey features\n\nSOC 2\n\nAudited security policies & procedures\n\nRules\n\nAutomate your workflows\n\n**Al Automations (Requires key)**\n\nSupercharge your workflows with AI\n\nIntegrations\n\nChatGPT, Pipedrive, Trello and more\n\nAnalytics\n\nMeasure key performance metrics\n\nAdvanced\n\nAPI access\n\nPost content to Missive\n\nSAML Single Sign-On\n\nOkta, Azure AD, etc.\n\nIP restrictions\n\nSecure access by location\n\nPersonalized Onboarding\n\nLive sessions with our experts\n\nFrequently asked questions\n--------------------------\n\nCan I try Missive first?\n\nYes! Everyone starts on Missive\u2019s free plan so they can test out features and functionality, to make sure there is a good fit. No credit card is required.\n\nCan I import more than one account?\n\nYes, Missive supports connecting multiple accounts (email, SMS, WhatsApp, etc.). Each user can have up to 10 personal accounts and 5 shared accounts. For example, an organization with 10 users can have up to 50 shared accounts, and an organization with 100 users can have up to 500 shared accounts. Additional shared accounts can be purchased.\n\nWill my personal emails be shared with my coworkers?\n\nNo, your coworkers will never see your personal emails by default. You can choose to grant them access to your account or invite them on a per-conversation basis.\n\nWhat devices do you support?\n\nMissive is primarily a web app, accessible from any web browser.  \nWe also offer mobile apps (iOS and Android) and desktop apps (macOS and Windows). Visit our [download page.](https://missiveapp.com/download)\n\nCan you help migrate my existing system?\n\nIf you're migrating from Google Workspace or Outlook, the process will be straightforward \u2014 see [here](https://missiveapp.com/faq/change-imap-server). For migrations from platforms like Front, we've created a simple guide, which you can find [here](https://missiveapp.com/faq/migrate-from-front).\n\nOur team is always happy to assist and ensure you get the most out of Missive. Don\u2019t hesitate to reach out!\n\nCan I add or remove users later?\n\nYes \u2014 Admins can add more users to the team. You can also remove individual team users from your plan through Admin controls. For Yearly plans, you will continue to pay for the removed user until the end of the billing period, but if you add a new team member, the seat will be re-assigned to them.\n\nWhat happens if we cancel our subscription?\n\nAfter canceling your plan, you will retain access to all features until the end of your current billing cycle. Once the billing cycle ends, your content will remain available in read-only mode.\n\nStill have more questions?\n\nWe would love to help \u2014 Visit [our help center](https://missiveapp.com/help) or simply [email us.](mailto:contact@missiveapp.com?subject=Inquiry%20regarding%20Missive%20app)\n\nWe also [host a bi-weekly demo](https://calendly.com/luis-missive/missive-the-team-inbox?back=1&month=2024-10) where we share tips and tricks for getting the most out of Missive and discover how it can help improve your team collaboration and communication.\n\nWe love building for small businesses\n-------------------------------------\n\n4.8\n\n500+ reviews\n\nAcross G2, Capterra and TrustPilot\n\nWe live in our inboxes.  \nLet\u2019s make email enjoyable.\n-----------------------------------------------------\n\nTry us out for free, invite a few people to get a feel, and upgrade when you\u2019re ready.\n\n4.8 \u2192 Over 500 reviews\n\nTry Missive risk-free for 30 days with your whole team. Unlock unlimited integrations, advanced security, custom rules, and more when you upgrade.",
      "error": null,
      "pricing_data": {
        "app_id": "missive",
        "app_name": "Missive",
        "app_slug": "missive",
        "pricing_url": "https://missiveapp.com/pricing",
        "source_url": null,
        "all_pricing_urls": [
          "https://missiveapp.com/pricing"
        ],
        "price_model_type": [
          "PriceModelType.SUBSCRIPTION"
        ],
        "has_free_tier": true,
        "has_free_trial": true,
        "free_trial_period_days": 30,
        "currency": "USD",
        "is_pricing_public": true,
        "pricing_page_accessible": true,
        "pricing_notes": "Annual billing offers a 20% discount compared to monthly billing.",
        "pricing_tiers": [
          {
            "tier_name": "Starter",
            "tier_description": "For teams with simple needs",
            "monthly_price": 14.0,
            "annual_price": 168.0,
            "annual_discount_percentage": 20.0,
            "setup_fee": null,
            "features": [
              "Email, SMS, social accounts",
              "Team spaces and inboxes",
              "Conversations and tasks",
              "SOC 2 Type II compliance"
            ],
            "limits": {
              "users": 5,
              "storage": "unlimited",
              "operations": "unlimited",
              "api_calls": "unlimited",
              "integrations": "unlimited",
              "custom_limits": null
            }
          },
          {
            "tier_name": "Productive",
            "tier_description": "For teams with workflow needs",
            "monthly_price": 24.0,
            "annual_price": 288.0,
            "annual_discount_percentage": 20.0,
            "setup_fee": null,
            "features": [
              "Everything in Starter",
              "Integrations with external tools",
              "Rules & automations",
              "Basic analytics & reporting",
              "API access"
            ],
            "limits": {
              "users": 50,
              "storage": "unlimited",
              "operations": "unlimited",
              "api_calls": "unlimited",
              "integrations": "unlimited",
              "custom_limits": null
            }
          },
          {
            "tier_name": "Business",
            "tier_description": "For teams with advanced needs",
            "monthly_price": 36.0,
            "annual_price": 432.0,
            "annual_discount_percentage": 20.0,
            "setup_fee": null,
            "features": [
              "Everything in Productive",
              "SAML and SSO",
              "IP restriction",
              "Advanced analytics & reporting",
              "Personalized team onboarding"
            ],
            "limits": {
              "users": "unlimited",
              "storage": "unlimited",
              "operations": "unlimited",
              "api_calls": "unlimited",
              "integrations": "unlimited",
              "custom_limits": null
            }
          }
        ],
        "usage_based_pricing": null,
        "ai_specific_pricing": {
          "has_token_based_pricing": false,
          "input_token_price": null,
          "output_token_price": null,
          "models_pricing": null,
          "has_inference_pricing": false,
          "has_fine_tuning_pricing": false,
          "has_training_pricing": false,
          "ai_addon_available": true
        },
        "promotional_offers": null,
        "additional_fees": [
          {
            "fee_name": "Additional shared accounts",
            "fee_amount": null,
            "fee_description": "Can be purchased for organizations exceeding the default shared account limits."
          }
        ],
        "extraction_timestamp": "2025-04-15T01:38:41.340942",
        "schema_validated": true,
        "confidence_score": 100,
        "extraction_error": false,
        "json_repaired": false
      },
      "pricing_analyzed": true
    }
  ],
  "results_directory": "pricing_results\\missive\\20250415_013841"
}