{
  "app_name": "Reamaze",
  "app_slug": "reamaze",
  "search_term": "Find the official pricing page URL for Reamaze (reamaze.com). Only provide the exact URL to the pricing page, not a summary of pricing information.",
  "timestamp": 1744726266.0280735,
  "response_text": [
    "The official URL to the Reamaze pricing page is: https://www.reamaze.com/pricing  "
  ],
  "citations": [],
  "extracted_content": [
    {
      "url": "https://www.reamaze.com/pricing",
      "is_accessible": true,
      "content": "The world's best helpdesk fits all team sizes\n---------------------------------------------\n\nNo Contracts. No Obligations. No Credit Card Needed.\n\nStart your trial now and choose your Plan later. See below for Pricing details.\n\nMonthly\n\nAnnually (Save 10%)\n\nBasic\n\n$29\n\nper Team Member per Month\n\n$29 $26 .10\n\nper Team Member per Month  \nbilled Annually\n\n*   Unlimited Email Inboxes\n*   Live Chat\n*   Social Media Channels\n*   Public/Internal FAQ\n*   Workflow Automation (Macros)\n*   Response Templates\n*   Website Integration\n*   Chatbots\n*   Cues (Proactive Messages)\n*   Basic Reporting\n*   Customer Intents\n\nPro\n\n$49\n\nper Team Member per Month\n\n$49 $44 .10\n\nper Team Member per Month  \nbilled Annually\n\n*   All of the features in Basic\n*   Manage Multiple Brands in one Account\n*   Live View of Site Visitors\n*   Advanced Reporting\n*   SMS and Voice Channels\n*   Custom Hosted Domain\n*   Customizable Email Appearance\n*   Status Page\n\n**Our most popular plan**\n\nPlus\n\n$69\n\nper Team Member per Month\n\n$69 $62 .10\n\nper Team Member per Month  \nbilled Annually\n\n*   All of the features in Pro\n*   Peek (Live Screensharing)\n*   Departments (Staff Groups)\n*   Staff Performance Reporting\n*   Staff Shifts and Vacation Days\n*   Customizable Staff Roles\n*   Customer Satisfaction Ratings\n*   In-Chat Video Calls\n*   Optional Classic Chat Mode \\*\n*   FAQ Article Edit History\n\nEmail Inboxes\n\nUnlimited\n\nUnlimited\n\nUnlimited\n\nSocial Channels\n\nUnlimited\n\nUnlimited\n\nUnlimited\n\nBrands\n\n1\n\nUnlimited\n\nUnlimited\n\nLive Chat\n\nCues (Proactive Messages)\n\nWelcome Bot\n\nOrder Bot\n\nCustom Bots\n\nLive View of Site Visitors\n\nPeek (Live Screensharing)\n\nOptional Classic Chat Mode\n\nLive Video Calls\n\nPublic & Internal FAQ\n\nCustom Domain\n\nStatus Page\n\nFAQ Edit History\n\nArticle Feedback\n\nResponse Templates\n\nWorkflows\n\nWelcome Bot\n\nOrder Bot\n\nCustom Bots\n\nCustomer Intent\n\nDepartments\n\nRoles\n\nPerformance Reporting\n\nShifts & Vacation Days\n\nConversations\n\nMessages\n\nEcommerce Integrations\n\nWorkflows\n\nTags\n\nStaff Performance\n\nStarter\n\nJust starting up? Get all of the features in Basic for unlimited team members. Limited to 500 Responded Conversations per month.\n\n$59\n\nFlat Rate per Month\n\nEnterprise\n\nRe:amaze Enterprise is a helpdesk platform for high-volume and fast-growing businesses.\n\n[Contact us](https://www.reamaze.com/pricing#) to learn more about how our white-glove service can help your business scale to your customers' needs.\n\nStart your trial now and choose your Plan later. See above for Pricing details.\n\nWhether you\u2019re building the **ecommerce** store of your dreams or the next big **SaaS**, Re:amaze can help you deliver awesome, personable customer support experiences.\n--------------------------------------------------------------------------------------------------------------------------------\n\nBusinesses who love their customers love us. **Hear what they have to say**.\n\n![Image 1](https://cdn.reamaze.com/assets/site/testimonials/mike-55f94c92b9cba5126c8be8c73cb33830f1b13fc233eb6f7046ff5bd9d396a466.jpg)\n\nMike\n\nCodeity\n\n> Once we started using Reamaze **we found our solution to customer support**. We now have a fully integrated and mobile solution to engaging with our customers in realtime.\n\n![Image 2](https://cdn.reamaze.com/assets/site/testimonials/jeff_jen-db11e86cf68a491ff279368aaaf884e223039fee71f4a56866dc68b25aa6565a.jpg)\n\nJen & Jeff\n\nPipsnacks\n\n> Reamaze has made customer service so much more efficient! We are able to view the customer's order number, items ordered and order history - without ever having to leave the customer's message. It has made response time faster and information exchange shorter, which makes our employees and customers happy!\n\n![Image 3](https://cdn.reamaze.com/assets/site/testimonials/Dusty-7e31b036394873d159679431fc2a870ddac23c7c00dd5761a1fe24414a754028.jpg)\n\nDustin\n\nPilot and Captain\n\n> We're a group of designers and illustrators, **not customer service experts**. Reamaze has let us bridge that gap and offer top notch service and response through **a simple, intuitive system**.\n\n![Image 4](https://cdn.reamaze.com/assets/site/testimonials/jeana-b5355b3b9a67b1fa27d538afb7d26c41b24d96b557311e5e277c0bf1677b6606.jpg)\n\nJeana\n\nArt of Skin Care\n\n> Prior to utilizing Re:amaze, we interacted with one or two customers per week on our live chat. **Now we help 60 to 80 clients per week. That\u2019s a remarkable difference.**\n\n#### How does the 14-day free trial work?\n\nAfter you signup you get access to all the features in the Re:amaze. You'll be up and running in under 5 minutes and you can play with Re:amaze to your heart's content. You will not be billed unless you choose to continue with us.\n\n#### Will I love Re:amaze?\n\nYes. We're so sure you'll love Re:amaze that if you're not happy after your 14 day trial, we'll help you look for an alternative. Just [ping us any time](mailto:support@reamaze.com) and we'd be happy to chat.\n\n#### Do I have to sign a contract?\n\nNo. You pay for Re:amaze month-to-month and you can cancel at any time. There are no cancellation fees or other nasty pitfalls awaiting.\n\n#### Do I have to install anything to use Re:amaze?\n\nNo. You and your whole team can access Re:amaze 24/7 from any computer or mobile device with a modern browser. Your experience with Re:amaze may be enhanced with caffeine.\n\nLet's get started\n-----------------\n\nStart with the 14 Days Free Trial, then you will be able to pick a plan in your account settings.\n\nUp and running in 5 minutes or less.\n\nNo adult supervision required. No credit card required.\n\nStill unsure?\n-------------\n\nContact our support team to get more details. We're happy to simplify things even more.\n\nJoin thousands of teams using Reamaze to impress customers.\n\nFind out how with a free account.",
      "error": null,
      "pricing_data": {
        "app_id": "reamaze",
        "app_name": "Reamaze",
        "app_slug": "reamaze",
        "pricing_url": "https://www.reamaze.com/pricing",
        "source_url": "https://www.reamaze.com/pricing",
        "all_pricing_urls": [
          "https://www.reamaze.com/pricing"
        ],
        "price_model_type": [
          "PriceModelType.SUBSCRIPTION",
          "PriceModelType.QUOTE_BASED",
          "PriceModelType.FREE_TIER"
        ],
        "has_free_tier": false,
        "has_free_trial": true,
        "free_trial_period_days": 14,
        "currency": "USD",
        "is_pricing_public": true,
        "pricing_page_accessible": true,
        "pricing_notes": "Pricing is based on per team member per month for most plans, with a flat rate for the Starter plan and custom pricing for Enterprise.",
        "pricing_tiers": [
          {
            "tier_name": "Basic",
            "tier_description": null,
            "monthly_price": 29.0,
            "annual_price": 26.1,
            "annual_discount_percentage": 10.0,
            "setup_fee": null,
            "features": [
              "Unlimited Email Inboxes",
              "Live Chat",
              "Social Media Channels",
              "Public/Internal FAQ",
              "Workflow Automation (Macros)",
              "Response Templates",
              "Website Integration",
              "Chatbots",
              "Cues (Proactive Messages)",
              "Basic Reporting",
              "Customer Intents"
            ],
            "limits": {
              "users": "unlimited",
              "storage": "unlimited",
              "operations": "unlimited",
              "api_calls": "unlimited",
              "integrations": "unlimited",
              "custom_limits": null
            }
          },
          {
            "tier_name": "Pro",
            "tier_description": "Our most popular plan",
            "monthly_price": 49.0,
            "annual_price": 44.1,
            "annual_discount_percentage": 10.0,
            "setup_fee": null,
            "features": [
              "All of the features in Basic",
              "Manage Multiple Brands in one Account",
              "Live View of Site Visitors",
              "Advanced Reporting",
              "SMS and Voice Channels",
              "Custom Hosted Domain",
              "Customizable Email Appearance",
              "Status Page"
            ],
            "limits": {
              "users": "unlimited",
              "storage": "unlimited",
              "operations": "unlimited",
              "api_calls": "unlimited",
              "integrations": "unlimited",
              "custom_limits": null
            }
          },
          {
            "tier_name": "Plus",
            "tier_description": null,
            "monthly_price": 69.0,
            "annual_price": 62.1,
            "annual_discount_percentage": 10.0,
            "setup_fee": null,
            "features": [
              "All of the features in Pro",
              "Peek (Live Screensharing)",
              "Departments (Staff Groups)",
              "Staff Performance Reporting",
              "Staff Shifts and Vacation Days",
              "Customizable Staff Roles",
              "Customer Satisfaction Ratings",
              "In-Chat Video Calls",
              "Optional Classic Chat Mode",
              "FAQ Article Edit History"
            ],
            "limits": {
              "users": "unlimited",
              "storage": "unlimited",
              "operations": "unlimited",
              "api_calls": "unlimited",
              "integrations": "unlimited",
              "custom_limits": null
            }
          },
          {
            "tier_name": "Starter",
            "tier_description": "Just starting up? Get all of the features in Basic for unlimited team members. Limited to 500 Responded Conversations per month.",
            "monthly_price": 59.0,
            "annual_price": null,
            "annual_discount_percentage": null,
            "setup_fee": null,
            "features": [
              "All features in Basic"
            ],
            "limits": {
              "users": "unlimited",
              "storage": "unlimited",
              "operations": 500,
              "api_calls": "unlimited",
              "integrations": "unlimited",
              "custom_limits": null
            }
          },
          {
            "tier_name": "Enterprise",
            "tier_description": "Re:amaze Enterprise is a helpdesk platform for high-volume and fast-growing businesses.",
            "monthly_price": null,
            "annual_price": null,
            "annual_discount_percentage": null,
            "setup_fee": null,
            "features": [
              "Custom white-glove service"
            ],
            "limits": null
          }
        ],
        "usage_based_pricing": null,
        "ai_specific_pricing": null,
        "promotional_offers": null,
        "additional_fees": null,
        "extraction_timestamp": "2025-04-15T10:11:15.239507",
        "schema_validated": true,
        "confidence_score": 100,
        "extraction_error": false,
        "json_repaired": false
      },
      "pricing_analyzed": true
    }
  ],
  "results_directory": "pricing_results\\reamaze\\20250415_101115"
}