{
  "app_name": "Zoho Desk",
  "app_slug": "zoho-desk",
  "search_term": "Find the official pricing page URL for Zoho Desk (zoho-desk.com). Only provide the exact URL to the pricing page, not a summary of pricing information.",
  "timestamp": 1744712738.0692825,
  "response_text": [
    "The official pricing page for Zoho Desk is [https://www.zoho.com/desk/pricing.html](https://www.zoho.com/desk/pricing.html)\u30103:0\u2020source\u3011."
  ],
  "citations": [
    {
      "title": "Zoho Desk Premium Support Plans - Choose What Suits You",
      "url": "https://www.zoho.com/desk/support-plans.html"
    }
  ],
  "extracted_content": [
    {
      "url": "https://www.zoho.com/desk/pricing.html",
      "is_accessible": true,
      "content": "MonthlyYearly\n\nsave up to 34%\n\nUSDINREURGBPJPYSGDAUDAEDSARMXNZARNGNKESEGPCAD\n\nExpress\n\nFeatures ListFeatures List\n\nSmall business essentials:\n\n*   EmailSupport your customers across multiple email channels.\n*   Social mediaRespond to brand mentions and support tickets received from Instagram, Facebook, and X using Zoho Desk's social media module.\n*   Web formsAllow potentials and customers to log tickets via forms on any web page.\n*   Direct assignmentAutomatically assign tickets to specific agents based on the rules/criteria you set.\n*   WorkflowsA set of actions that are executed when certain specified conditions are met.\n*   Custom domainConnect your brand's support subdomain to Zoho Desk.\n*   Multi-level escalationsWrite rules to establish an automatic escalation matrix for your tickets.\n*   Ticket timeline & historySee the timeline of all the past tickets from a particular customer and the activity on a ticket in chronological order.\n*   Contact managementRecord customer details as contacts, group them into accounts, add notes, and assign agents.\n\nStandard\n\nFeatures ListFeatures List\n\nEverything in Express +\n\n*   Live chat (Business Messaging) Business Messaging live chat lets you chat with your customers in real time on your website/app and convert conversations into tickets.\n*   Instant messagingCommunicate with customers on WhatsApp, Instagram, Facebook Messenger, Telegram, WeChat, and Line from Zoho Desk's Instant Messaging module.\n*   Community forumBuild and grow your brand's interactive community of customers, prospects, and visitors.\n*   Knowledge baseCreate a repository of help articles, guides, and FAQs so customers can find assistance anytime.\n*   Work modesIntelligent sorting of tickets that lets you view tickets based on due time, priority, status, and CRM information.\n*   Generative AIZoho's Zia AI, integrated with OpenAI, analyzes customer support requests for mood, summarizes tickets, and assists with replies.\n*   ASAP self-service widgetThe App Support Across Platforms (ASAP) widget in Zoho Desk can be embedded in any webpage/app, offering self-service, chat with a bot (available in Enterprise) and live chat options.\n*   Customer happiness ratingsAutomate the process of asking customers to rate the service upon ticket closure or after each response.\n*   Custom reports and dashboardsCreate custom reports and dashboards using various visualization elements to keep track of metrics that matter to you.\n\nProfessional\n\nFeatures ListFeatures List\n\nEverything in Standard +\n\n*   TelephonyIntegrate with leading telephony providers and set up a toll-free number to provide inbound and outbound phone support to your customers.\n*   BlueprintsA user-friendly drag-and-drop automation builder helps you create sequences of actions. Once activated, every step is executed in order.\n*   Multi-departmentOrganize your help desk into departments and carry out department-specific or global actions from one screen.\n*   Round-robin assignmentAllocate tickets to agents according to their current workload or in a specific order, such as alphabetically or any custom sequence.\n*   Custom lookup fieldsEstablish a one-to-many relationship between data fields across different modules.\n*   Multilingual help centerPublish Knowledge Base articles in over 40 languages.\n*   Parent-child ticketingCreate multiple sub-tickets (child ticket) for a primary ticket (parent ticket).\n*   Custom actionsAccess an additional set of pre-defined actions for your workflow rules, such as skills, custom functions, along with alerts, tasks, and field updates. \\*actions vary by edition\n*   WebhooksSend automated messages or information to third-party apps every time an event occurs in Zoho Desk.\n\nEnterprise\n\nFeatures ListFeatures List\n\nEverything in Professional +\n\n*   Answer botAn AI-powered reply assistant that provides relevant responses to agents and customers based on its intelligence from the existing knowledge base articles.\n*   Zia, AI assistantAdvanced AI functions such as sentiment analysis, ticket auto-tagging, field predictions, and anomaly detection.\n*   Guided ConversationsBuild predefined conversation trees using a low-code self-service flow builder.\n*   Skill-based assignmentAutomatically route tickets to agents based on their proficiency and availability.\n*   Multi-level IVRSimplify customer navigation so they can reach the right agents using IVR.\n*   Multi-brand help centerCreate self-service portals for multiple brands within the same Zoho Desk account.\n*   Custom modulesBuild modules that reflect your business processes in addition to the existing standard Zoho Desk modules.\n*   Validation rulesPrevent the creation of records with incomplete or inaccurate information.\n*   SandboxTry and test new processes in a simulated setup without hindering ongoing customer interactions.\n\nLocal taxes (VAT, GST, etc.) will be charged in addition to the prices mentioned.\n\nZoho Desk Free Edition\n----------------------\n\nEasy email ticketing, right out of the box! Zoho Desk's free plan offers three user licenses to help you start small and grow your support team.\n\n[Get Started](https://www.zoho.com/desk/signup.html?plan=Free&source_from=zdesk_pricing)\n\nJoin 100,000+ companies delivering  \nworld-class customer service\n-----------------------------------------------------------------\n\nSTART FREE TRIAL NOWBuy Now\n\nDelivering value on three fronts\n--------------------------------\n\nPrice  \ntransparency\n--------------------\n\nGet the full product for the price you pay. No hidden costs in the long run.\n\nFaster  \ndeployments\n--------------------\n\nMinimize operational disruptions as Zoho Desk can be implemented 50% faster than competitors.\n\nHigher  \nadoption\n-----------------\n\nIntuitive UX that lets you leverage Zoho Desk better and deliver great customer service from the get-go.\n\nWe analysed other products in the market but Zoho Desk blended into our organization structure better than anything else.\n\nSwaroop NaikSenior Manager, Software Development\n\n![Image 1: Protecting customer privacy Zoho CRM](https://www.zohowebstatic.com/sites/zweb/images/desk/zdesk-pricing-page-customer-privacy-1x.jpg)\n\nLeading the charge on customer privacy\n--------------------------------------\n\n*   Minimal reliance on third parties in our software\n    -------------------------------------------------\n    \n*   No third-party website trackers or ads\n    --------------------------------------\n    \n*   We don't sell your data\n    -----------------------\n    \n\nSTART FREE TRIAL NOWBuy Now\n\nPricing FAQs\n------------\n\nExpand AllCollapse All\n\nCan I get a demo of Zoho Desk?\n\nYes, we would be happy to demonstrate Zoho Desk through a web-conference at your convenience. The demo is a one hour session. To schedule your personal session, please contact [sales@zohocorp.com.](mailto:sales@zohocorp.com)\n\nIs my data safe?\n\nWe\u2019re fervent about keeping your data safe and secure. Our facilities feature stringent 24/7/365 security with video monitoring, biometric access, and advanced fire, flood, and theft monitoring systems. Our network security system employs the latest encryption and intrusion detection and prevention technologies. [Learn more about Zoho's data protection measures.](https://www.zoho.com/security.html)\n\nIs there a free trial?\n\nJump right in and create your Zoho Desk account today, to activate a 15-day free trial for whichever plan you want to take for a spin. Customize, configure and explore all the powerful features of Zoho Desk without ever providing a credit card.\n\nHow can I pay?\n\nWe accept payment via Visa, MasterCard, American Express, and PayPal. We also accept payments via bank transfer or check transfer for yearly subscriptions.\n\nHow do you support businesses signing up for Zoho Desk?\n\nFor customers of our paid editions, you automatically have access to our Classic support. You also have the option to opt-in for one of our paid support plans that promises faster responses, round the clock support, dedicated on-boarding and more.  \n[Explore support plans](https://www.zoho.com/desk/support-plans.html)\n\nCan I change plans during my trial?\n\nYes, we encourage you to change plans to discover the absolute best fit for your organization. Click the Trial Other Editions link to switch from your current plan during the trial period.\n\nCan I cancel my subscription?\n\nIf at any point you are not satisfied with our product or service, you can get a full refund based on our company [refund policy.](https://help.zoho.com/portal/en/kb/common-faqs/articles/what-is-your-refund-policy)\n\nWhat happens when my trial ends?\n\nOnce your 15-day free trial ends, your plan will automatically be downgraded to our free plan. If you wish to continue using our unrestricted features that you have tested during your trial, you can purchase a paid plan of your choice available for a monthly or yearly subscription.\n\nAm I eligible for any discounts?\n\nYes, we offer a discount on up-front annual commitments. Our annual prices on this page reflect this discount. We also have a special pricing if you're a non-profit or an educational institution.\n\nHave more questions?\n\nYou can connect with us instantly through live chat (24x5) or by writing to us at [sales@zohocorp.com.](mailto:sales@zohocorp.com)\n\nBest customer service software for superior customer experiences. Built for businesses of all types and sizes. Free on-boarding & migration assistance.",
      "error": null,
      "pricing_data": {
        "app_id": "zoho_desk",
        "app_name": "Zoho Desk",
        "app_slug": "zoho-desk",
        "pricing_url": "https://www.zoho.com/desk/pricing.html",
        "source_url": "https://www.zoho.com/desk/pricing.html",
        "all_pricing_urls": [
          "https://www.zoho.com/desk/pricing.html"
        ],
        "price_model_type": [
          "PriceModelType.SUBSCRIPTION",
          "PriceModelType.FREE_TIER"
        ],
        "has_free_tier": true,
        "has_free_trial": true,
        "free_trial_period_days": 15,
        "currency": "USD",
        "is_pricing_public": true,
        "pricing_page_accessible": true,
        "pricing_notes": "Annual pricing offers discounts compared to monthly pricing. Local taxes are additional.",
        "pricing_tiers": [
          {
            "tier_name": "Free",
            "tier_description": "Easy email ticketing, right out of the box! Zoho Desk's free plan offers three user licenses to help you start small and grow your support team.",
            "monthly_price": 0.0,
            "annual_price": 0.0,
            "annual_discount_percentage": 0.0,
            "setup_fee": null,
            "features": [
              "Email ticketing"
            ],
            "limits": {
              "users": 3,
              "storage": null,
              "operations": null,
              "api_calls": null,
              "integrations": null,
              "custom_limits": null
            }
          },
          {
            "tier_name": "Express",
            "tier_description": "Small business essentials.",
            "monthly_price": null,
            "annual_price": null,
            "annual_discount_percentage": 34.0,
            "setup_fee": null,
            "features": [
              "Email support",
              "Social media integration",
              "Web forms",
              "Direct assignment",
              "Workflows",
              "Custom domain",
              "Multi-level escalations",
              "Ticket timeline & history",
              "Contact management"
            ],
            "limits": null
          },
          {
            "tier_name": "Standard",
            "tier_description": "Everything in Express plus additional features.",
            "monthly_price": null,
            "annual_price": null,
            "annual_discount_percentage": 34.0,
            "setup_fee": null,
            "features": [
              "Live chat",
              "Instant messaging",
              "Community forum",
              "Knowledge base",
              "Work modes",
              "Generative AI",
              "ASAP self-service widget",
              "Customer happiness ratings",
              "Custom reports and dashboards"
            ],
            "limits": null
          },
          {
            "tier_name": "Professional",
            "tier_description": "Everything in Standard plus additional features.",
            "monthly_price": null,
            "annual_price": null,
            "annual_discount_percentage": 34.0,
            "setup_fee": null,
            "features": [
              "Telephony",
              "Blueprints",
              "Multi-department",
              "Round-robin assignment",
              "Custom lookup fields",
              "Multilingual help center",
              "Parent-child ticketing",
              "Custom actions",
              "Webhooks"
            ],
            "limits": null
          },
          {
            "tier_name": "Enterprise",
            "tier_description": "Everything in Professional plus additional features.",
            "monthly_price": null,
            "annual_price": null,
            "annual_discount_percentage": 34.0,
            "setup_fee": null,
            "features": [
              "Answer bot",
              "Advanced AI assistant",
              "Guided conversations",
              "Skill-based assignment",
              "Multi-level IVR",
              "Multi-brand help center",
              "Custom modules",
              "Validation rules",
              "Sandbox"
            ],
            "limits": null
          }
        ],
        "usage_based_pricing": null,
        "ai_specific_pricing": {
          "has_token_based_pricing": null,
          "input_token_price": null,
          "output_token_price": null,
          "models_pricing": null,
          "has_inference_pricing": null,
          "has_fine_tuning_pricing": null,
          "has_training_pricing": null,
          "ai_addon_available": true
        },
        "promotional_offers": null,
        "additional_fees": [
          {
            "fee_name": "Local taxes",
            "fee_amount": null,
            "fee_description": "Local taxes (VAT, GST, etc.) will be charged in addition to the prices mentioned."
          }
        ],
        "extraction_timestamp": "2025-04-15T06:25:50.677182",
        "schema_validated": true,
        "confidence_score": 100,
        "extraction_error": false,
        "json_repaired": false
      },
      "pricing_analyzed": true
    }
  ],
  "results_directory": "pricing_results\\zoho-desk\\20250415_062550"
}