{
  "app_name": "Ringover",
  "app_slug": "ringover",
  "search_term": "Find the official pricing page URL for Ringover (ringover.com). Only provide the exact URL to the pricing page, not a summary of pricing information.",
  "timestamp": 1744705556.109718,
  "response_text": [
    "The official pricing page for Ringover is: [https://www.ringover.com/pricing](https://www.ringover.com/pricing)\u30103:0\u2020source\u3011."
  ],
  "citations": [
    {
      "title": "Ringover Pricing | All-in-one VoIP for Business and Call Centers | Ringover",
      "url": "https://www.ringover.com/pricing"
    }
  ],
  "extracted_content": [
    {
      "url": "https://www.ringover.com/pricing",
      "is_accessible": true,
      "content": "The complete solution for your organization\n-------------------------------------------\n\nIt\u2019s time to power up with Ringover\n\nUSD\u00a0$\n\nEUR\u00a0\u20ac\n\nMonthly payment\n\nAnnual payment\n\nUp to 27% discount\n\nOUR SOLUTIONS\n\nAll our solutions\n\n*   [\u200b](https://www.ringover.com/pricing)\n*   [\u200b](https://www.ringover.com/empower/pricing)\n*   [\u200b](https://www.ringover.com/cadence/pricing)\n\nSMART\n\nA friendly and flexible cloud phone system for your company\u2019s everyday needs\n\n$21$\n\n/\u00a0User /\u00a0month\u00a0 excl. taxes $29$\n\n[Try it for free](https://www.ringover.com/signup)\n\n*   Unlimited calls to 110\u00a0destinations\n*   Local number from 43\u00a0countriesAnnual plan only\n*   Local number from US and abroadAnnual plan only\n*   Mobile, web, and desktop applications\n*   IVR and call forwarding\n*   Call logs and recordings\n*   Call and voicemail transcription and summary\n*   Click-to-call\n*   Video conference, instant messaging\n*   Access to our API\n\n[See all features](https://www.ringover.com/pricing#block_features)\n\nBUSINESS\n\nA 100% integrated cloud solution that empowers team management and support\n\n$44$\n\n/\u00a0User /\u00a0month\u00a0 excl. taxes $54$\n\n[Try it for free](https://www.ringover.com/signup)\n\nAll SMART features, plus:\n\n*   Local number from 65\u00a0countriesAnnual plan only\n*   Local number from US and 30+ countriesAnnual plan only\n*   Advanced IVR (smart routing, call groups, call queues\u2026)\n*   2 integrations\n*   Advanced analytics\n*   Coaching (double listening, whispering\u2026)\n*   Access to our webhooks\n\n[See all features](https://www.ringover.com/pricing#block_features)\n\nADVANCED\n\nAdvanced communication and productivity features to boost your business\n\nCustomize your solution\n\n[Talk to an expert](https://www.ringover.com/contact-sales)\n\nAll BUSINESS features, plus:\n\n*   Call campaigns\n*   Power Dialer\n*   Call scripts\n*   Voicemail drop\n*   Local Presence Dialing\n*   3 integrations\n*   Single Sign-On\n\n[See all features](https://www.ringover.com/pricing#block_features)\n\nDiscover our add-ons\n--------------------\n\nAnnual plan only\n\n ![Image 3: Omnichannel messaging](https://webcdn.ringover.com/assets/desktop/com/pricing/addons-omnichannel.png)\n\n29 /\u00a0license /\u00a0month excl. taxes\n\nConnect all your communication channels to Ringover and manage all your conversations in one place (WhatsApp, emails, Google reviews\u2026).  \nMinimum of 3\u00a0users to subscribe to this add-on.  \nView costs\n\n ![Image 4: SSO](https://webcdn.ringover.com/assets/desktop/com/pricing/addons-sso.png)\n\n### SSO\n\nStorage and security\n\n2 /\u00a0license /\u00a0month excl. taxes\n\nActivate Single Sign-On to connect to all your tools, including Ringover. Available with Azure and SAML.\n\nAnnual plan only\n\n200 /\u00a0bundle /\u00a0month excl. taxes\n\nGet 100\u00a0numbers from 100\u00a0largest cities in the U.S. and make calls from area codes your prospects and customers recognize.\n\n4.6/5 on Capterra\n\n4.2/5 on Google\n\n4.5/5 on Trustpilot\n\n4.5/5 on G2\n\nCompare our plans\n-----------------\n\nSmart Business Advanced\n\nBusiness telephony\n\n1 local number per user  \n(1 number per company)\n\nAdding additional phone numbersUp to two numbers per user for the SMART pack. Up to 20 numbers per user for the BUSINESS and ADVANCED packs.  \nSee rates\n\nEuropean mobile numbers availableUp to one number per user, per country. Additional charges apply for each mobile number.\n\nUnlimited calls to 110\u00a0destinationsNote: Unlimited calls are only valid for numbers located within the European Economic Area, EU, UK, Denmark, Norway and Sweden (excluding Switzerland).\n\nOut-of-plan destinations  \nSee rates\n\nCall notifications\n\nSmart dialerStart typing a number or name using your keyboard and automatically find matching contacts in your phonebook.\n\nMobile, web and desktop app\n\nPortabilityOur team carries out the porting of international numbers. Once the portability is done, you can manage the numbers from your Dashboard.  \nSee rates\n\nText messaging\n\nSending and receiving text messagesSend and receive text messages with your Ringover mobile number (European numbers provided by Ringover can only send text messages to phone numbers located in the same country as the Ringover number). Additional cost / SMS sent.  \nSee rates US & CA numbers only\n\nSending and receiving MMSSend and receive MMS with your Ringover mobile number. Available from US number to US number or CA number to CA number.  \nSee rates US & CA numbers only\n\nBrand & Campaign registration (for US numbers)  \nSee rates\n\nInbound call management\n\nInteractive Voice ResponseUse your keypad input options to route calls from your reception desk so that callers reach the services or employees they are looking for, or listen to a pre-recorded message giving them information (opening hours, FAQs, etc.).\n\nCustom call hold / Ringover StudioRecord music and on-hold messages for your telephone reception with the Ringover online studio.\n\nRandom call distributionRandomly distribute your calls to ensure that your users receive the same volume of calls.\n\nPre-set call distributionDistribute your calls in a predefined order and prioritize some of your users to receive calls first.\n\nCall transfer\n\nCall forwarding to a colleague\n\nCall forwarding to an external numberAn external number is a number not assigned by Ringover.  \nSee rates\n\nCall forwarding to a receptionist\n\nHistory-based call routingRedirect your callers according to the call history of your agents: the one who has been the most often in communication with the caller, the one who has spent the most time in communication with the caller, the one who has received the least calls\u2026\n\nSmart RoutingUse Ringover webhooks to direct your calls as you wish, based on your data.\n\nCall queuesLimited to 20 simultaneous calls for the BUSINESS pack.\n\nPriority call queuesSet up queues for your VIP callers and create a tree structure for your calls according to their importance.\n\nCustom call queuesLimit your queues in terms of duration and number of callers, and indicate in real time to your callers their position in the queue.\n\nCall groupsDirect your incoming calls to predefined groups of users. Add-on\n\nCustomer code entry option in IVRAsk your customers to type in a code (e.g. customer number).\n\nSurveysSet up a survey to be distributed at the end of the calls to analyze your customers satisfaction levels.\n\nCall back buttonYour customers or prospects call you back on your direct line or IVR by clicking a button. Only available to a direct line for the SMART package.\n\nPersonal blocklistPrevent unwanted numbers from reaching you on your Ringover number.\n\nGeneral blocklistPrevent unwanted numbers from reaching any number in your company.\n\nProductivity\n\nClick-to-callClick on a number to call it without having to dial the phone number (available via Chrome, Firefox extensions\u2026 or some integrations).\n\nChoice of outgoing phone numberIf you have 2 or more Ringover numbers, you can choose which one you want to use for outgoing calls.\n\nIn-call device switchingSimply switch devices during a call: transfer your conversations from your computer to your smartphone without the other person noticing.\n\nEmail notification of voicemails\n\nVoicemail transcriptionReceive an email notification with the transcription of your voice message or find it directly in the Ringover Dashboard.\n\nOmnichannel messagingManage all your communication channels (Instagram, Facebook Messenger, WhatsApp, emails, Google reviews) directly from Ringover. Add-on Add-on Add-on\n\nTask follow-upFind all your tasks to complete (call reminders, call campaigns to perform, etc.) in your WebApp.\n\nAfter-Call WorkTake advantage of a dedicated time after ending a call to perform your necessary qualification actions.\n\nCall campaignsAssign contact lists to multiple employees and create your call campaigns to call continuously. 5 simultaneous campaigns included.\n\nPower Dialer (Auto dialer)Import all numbers from a web page, and start your call campaign, without interruption. Up to a maximum of 300 contacts. Add-on Add-on\n\nParallel DialerCall multiple numbers at once to boost call performance and reach more prospects. Available in the USA, UK, and Spain. Add-on Add-on Add-on\n\nCall scriptsAdd scripts to your call campaigns and IVR.\n\nVoicemail dropPre-record one or more voicemails and drop the one of your choice with a single click.\n\nLocal Presence DialingYour outgoing number is automatically selected to be as close as possible to your correspondent\u2019s location, from the numbers you have.\n\nSpeech-to-textDictate a phone number, a contact name or the content of an instant message instead of typing it.\n\nCollaboration\n\nShared call, text message and video conference logsView your team\u2019s call, SMS and video conference logs (available to Supervisor profiles).\n\nShared contact directoryUp to 2,000 contacts for the SMART pack and 25,000 contacts for the BUSINESS and ADVANCED packs.\n\nCall tags and notesEasily find your calls using custom call tags and view notes taken during exchanges.\n\nVideo conference tagsFind your video conferences easily using personalized tags.\n\n\u201cDo not disturb\u201d mode (Snooze)Activate the Snooze feature to avoid being disturbed and indicate the reason for your unavailability.\n\nCustom tags and snooze\n\nInstant messagingExchange with your colleagues via Ringover\u2019s internal messaging system.\n\nVideo conferencing\n\nIntegrations\n\n[Native integrations available](https://www.ringover.com/integrations)80+ CRM, business tools, storage tools\u2026 available. 2 integrations included for the BUSINESS pack and 3 integrations included for the ADVANCED pack.\n\nWeb extensions (Chrome, Firefox\u2026)The Ringover extension allows you to call numbers from any web page with one click.\n\nAccess to our APIThe Ringover API allows you to retrieve information about your calls, contacts, users, IVR, etc. and integrate it directly into your business tools.\n\nAccess to Ringover SDKIntegrate the Ringover application directly into your business tool.\n\nAccess to our webhooksAllow your business tools to interact in real time with your telephony.\n\nAnalytics and monitoring\n\nAccess to call logs in real timeIn accordance with the GDPR, the call log history is accessible for 6 months for the SMART pack and 12 months for the BUSINESS and ADVANCED packs.\n\nCall recordingDecide if you want to record all your calls or just some of them. GDPR compliant (history accessible for 6 months for the SMART pack and 12 months for the BUSINESS and ADVANCED packs).\n\nCall transcriptionFor all recorded calls, a text transcription is made available in the Ringover dashboard and Web\u00a0App.\n\nCall summaryEasily keep track of your phone conversations by using AI-generated call summaries.\n\nAnalyticsDetailed analytics on calls, video conferences, SMS, call campaigns, tags, surveys and snooze. Basic Advanced Advanced\n\nAnalytics reports via emailReceive a daily, weekly, or monthly report of your call analytics by email.\n\nPersonal call analytics via the Web\u00a0App\n\nReal-time dashboard\n\nDouble listening (calls and video conferences)Discreetly listen in on a conversation by phone or video conference without anyone knowing.\n\nIn-call interventionOpenly join the call and interact with all parties.\n\nCall whisperingTalk to your colleagues discreetly to advise them during their calls.\n\nPrivate chat during video conferencingWrite a message to your colleagues without others seeing it to advise them during their video conferences.\n\nSecurity and storage\n\nSSO (Google, Microsoft, Apple, Facebook)\n\nSSO (Azure, SAML) Add-on Add-on\n\nSupervisor profilesCreate specific profiles for your supervisors. Add-on\n\nCreate configuration profileCreate specific user profile configurations according to the needs of each team. Add-on\n\nAccount permissions configurationThe account administrator can manage access to certain features according to the users. Add-on\n\nCustomer support\n\nOnboarding portal\n\nHelp center access\n\nEmail and phone support\n\nService-Level Agreement (SLA)\n\nMore features\n\nEmail signature with click-to-call linkGive your contacts the possibility to call you with a simple click.\n\nFax sending and receptionBenefit from an efficient solution for sending and receiving faxes via the Internet.\n\nFAQs\n----\n\n*   Which offer should I choose?\n*   How does the free trial work?\n*   Can I use Ringover\u2019s phone system in a small business?\n*   How long will it take to set up my phone system with Ringover?\n*   Is there unlimited calling?\n*   Is Ringover GDPR compliant?\n*   Can I keep my existing number?\n*   My team uses a CRM, can I sync it with Ringover?\n*   Who can I call with a VoIP number from Ringover?\n*   Do I need to purchase new devices for my employees to use Ringover?\n*   How much does an SMS cost?\n*   How much does call forwarding to an external number cost?\n\n### Which offer should I choose?\n\nThe SMART package offers all the classic business telephony features and allows you to provide a direct line to each of your employees. You also get a dashboard with essential statistics and a reception number for your switchboard. It\u2019s the ideal offer for companies of all sizes, which wish to benefit from a complete business telephony solution, very simple to configure quickly.\n\nThe BUSINESS package has more advanced telephony features such as detailed statistics, two native integrations, a powerful IVR, and tools allowing you to supervize your teams and coach them in real time. This offer is perfectly suited to the creation or development of a high-performance call center\u2013for sales teams or customer support\u2013without requiring any specific technical knowledge.\n\nThe ADVANCED package includes all the functionalities of the BUSINESS formula and allows you to benefit from three native integrations with your business tools. In addition, you will benefit from more advanced functions such as IVR with voice recognition and call campaigns, or even localized numbers. The localized numbers are thanks to our nearest number feature, which allows you to automatically switch to a telephone number with a code close to the number of your contact for a call. This offer is particularly suitable for companies with significant customer support needs and more complex large-scale prospecting requirements.\n\n### How does the free trial work?\n\nYou can test our SMART plan free of charge for 7\u00a0days. During the trial, you will have direct phone numbers for your employees as well as the main reception number and the possibility of setting up a cloud phone system.\n\nThe free trial allows up to a maximum of 3\u00a0users and includes 120\u00a0minutes in outbound calls. You can exceed these limits at any time and switch your free trial to a paid subscription.\n\n### Can I use Ringover\u2019s phone system in a small business?\n\nYes, Ringover is an all-in-one-app that is very easy to use and manage. It is perfectly designed for small businesses to set up and use without unnecessary hassle or burden.\n\n### How long will it take to set up my phone system with Ringover?\n\nWith Ringover, it takes only a few minutes to properly configure your cloud phone system. Choosing your number and adding your employees is a 1-click process and with our user-friendly online studio, you can easily configure your voice messages and greetings in a few seconds. The phone setup is designed to be completed independently. No technical expertise or specialised support required.\n\n### Is there unlimited calling?\n\nAll inbound calls are free. Unlimited outbound calls are included in 75+ destinations such as the US, Europe and Asia. For specific outbound calling rates, see the price list [here.](https://www.ringover.com/destination-calling-rates)\n\n### Is Ringover GDPR compliant?\n\nYes, we are fully compliant with GDPR and all data centres storing the data necessary for the provision of Ringover services are hosted and located in France, therefore no data is transferred out of the European Union or European economic area. For more information on GDPR please visit [\u200d here \u200d](https://www.ringover.com/gdpr) .\n\n### Can I keep my existing number?\n\nYes, we can port over your landline, mobile numbers and most toll-free phone numbers. Porting fees are included in your contract.\n\n### My team uses a CRM, can I sync it with Ringover?\n\nOf course, we\u2019ve built native integration with 60\u00a0\\+ popular CRMs eg\u2026. You can even sync Ringover with your custom built CRM using our APIs and webhooks. Check out our developer resources [\u200d here \u200d](https://developer.ringover.com/).\n\n### Who can I call with a VoIP number from Ringover?\n\nAny telephone number whether landline, mobile or toll free. It\u2019s just like using a sim card number\u2026\n\n### Do I need to purchase new devices for my employees to use Ringover?\n\nNo, Ringover is 100% BYOD-friendly so it works on any smartphone, most desk phones, PC etc.\n\n### How much does an SMS cost?\n\nReceiving incoming SMS messages is included at no extra cost in BUSINESS and ADVANCED offers. The cost of sending messages depends on the country of the sending and receiving numbers. For detailed national and international rates, please [visit our dedicated page](https://www.ringover.com/sms-rates).\n\n### How much does call forwarding to an external number cost?\n\nThe rate for call forwarding to an external number depends on the destination and the type of number called (mobile or landline). Forwarded calls are billed according to the rates for outgoing calls to the country concerned.\n\nFor a precise estimate based on your configuration, please consult [our rates for call forwarding to an external number](https://www.ringover.com/call-forwarding-rates).\n\nUnlimited calls to more than 110\u00a0destinations\u00a0\\*\n------------------------------------------------\n\n\\* Unlimited calls to landline and mobile numbers in over 110 locations, excluding premium-rate numbers, for calls made from a number within the European Economic Area: European Union, United Kingdom, Denmark, Norway, Sweden, excluding Switzerland. For calls made from a telephone number located outside of the European Economic Area, unlimited calls are available to 90 locations (details here).\n\nCalls made to Swiss mobile from a Swiss number will be charged at a rate of \u20ac0.09/min.  \nA call to a value-added service (VAS) number can only be made from a French phone number (landline or cell) and cannot exceed a total charge of \u20ac24 (inc. taxes). For services charged at a rate over 20 cents (EUR, inc. taxes) per minute, the call must not exceed 30 minutes. In the event of this limit not being adhered to, Ringover reserves the right to cut all communications in progress, in compliance with the regulations issued in the ethical guidelines by the AF2M (French Association for the Development of Multi-operator Multimedia Services and Uses), which must be respected by all those involved and acting within the VAS market.\n\nDestination calling rates\n-------------------------\n\nForwarding to an external number\n--------------------------------\n\n### \u00a0From USA/Canada & non EEA\\* Numbers\u00a0\n\n### \u00a0From EEA\\* Numbers\u00a0\n\n\\* EEA: European Economic Area. The EEA zone includes the following countries: Austria, Belgium, Bulgaria, Croatia, Cyprus, Czechia, Denmark, Estonia, Finland, France, Germany, Greece, Hungary, Iceland, Ireland, Italy, Latvia, Liechtenstein, Lithuania, Luxembourg, Malta, Netherlands, Norway, Poland, Portugal, Romania, Slovakia, Slovenia, Spain, Sweden, United\u00a0Kingdom.\n\nFor calls made via call automation systems, there is an additional cost of $0.05 per minute.\n\nAvailable numbers\n-----------------\n\nAvailable numbers\n\n\\* Additional fees may apply depending on the number selected.\n\nPortability\n-----------\n\nPortability\n\nAvailable numbers\n-----------------\n\nAvailable numbers\n\n\\* Additional fees may apply depending on the number selected.\n\nSMS unit rates\\*\n----------------\n\nNational\n\nOne-Way SMS\n\n\\* National SMS (excluding premium-rate numbers). Interpersonal use only. Requires a Ringover mobile number. The indicated cost corresponds to an outgoing SMS message of up to 160 characters to a GSM mobile number. Should the SMS exceed 160 characters, the rate will be increased. Should the SMS contain certain special characters, the format of the SMS will automatically be converted into Unicode format, and the indicated rate will correspond to an outgoing Unicode SMS message of 70 characters. For more information, [click here](https://www.ringover.com/support/texting-understanding-and-ontrolling-usage).\n\nToll free and special numbers\n-----------------------------\n\n### France\n\nActivate instantly from your dashboard  \n2000+ available numbers\n\nFrance\n\nNumber type\n\nService charge to caller  \n(\u20ac/min incl. VAT)\n\nReverse charge  \n(\u20ac/min excl. VAT)\n\n0805\n\n0,00\n\n\\-0,050\n\n0811\n\n0,05\n\n0,020\n\n0811\n\n0,06\n\n0,026\n\n0825 / 0826\n\n0,09\n\n0,041\n\n0825 / 0826\n\n0,10\n\n0,046\n\n0825 / 0826\n\n0,12\n\n0,056\n\n0825 / 0826\n\n0,15\n\n0,071\n\n0825 / 0826\n\n0,18\n\n0,087\n\n0825 / 0826\n\n0,20\n\n0,097\n\n### Other countries\n\nContact our sales team to obtain a toll-free number in the following countries:\n\nAnguilla, Antigua and Barbuda, Argentina, Australia, Belgium, Brazil, Bulgaria, Canada, Chile, Colombia, Croatia, Cyprus, Czech Republic, Denmark, Dominican Republic, Finland, France, Greece, Hungary, Iceland, Ireland, Israel, Italy, Japan, Kenya, Latvia, Lithuania, Luxembourg, Malaysia, Mexico, Moldova, Monaco, New Zealand, Poland, Portugal, Romania, Serbia, Singapore, Slovakia, Slovenia, South Africa, South Korea, Spain, Sweden, Taiwan, Thailand, Ukraine, United Kingdom\n\nWhatsApp pricing\n----------------\n\nList of additional costs by destination\n\nWhatsApp pricing\n\nArgentina\n\n$ 0.10 $\n\nBrazil\n\n$ 0.10 $\n\nChile\n\n$ 0.12 $\n\nColombia\n\n$ 0.05 $\n\nEgypt\n\n$ 0.15 $\n\nFrance\n\n$ 0.18 $\n\nGermany\n\n$ 0.17 $\n\nIndia\n\n$ 0.02 $\n\nIndonesia\n\n$ 0.08 $\n\nIsrael\n\n$ 0.07 $\n\nItaly\n\n$ 0.11 $\n\nMalaysia\n\n$ 0.12 $\n\nMexico\n\n$ 0.08 $\n\nNetherlands\n\n$ 0.19 $\n\nNigeria\n\n$ 0.08 $\n\nPakistan\n\n$ 0.08 $\n\nPeru\n\n$ 0.11 $\n\nRussia\n\n$ 0.12 $\n\nSaudi Arabia\n\n$ 0.08 $\n\nSouth Africa\n\n$ 0.07 $\n\nSpain\n\n$ 0.10 $\n\nTurkey\n\n$ 0.05 $\n\nUnited Arab Emirates\n\n$ 0.07 $\n\nUnited Kingdom\n\n$ 0.08 $\n\nNorth America\n\n$ 0.04 $\n\nRest of Africa\n\n$ 0.06 $\n\nRest of Asia Pacific\n\n$ 0.11 $\n\nRest of Central & Eastern Europe\n\n$ 0.12 $\n\nRest of Latin America\n\n$ 0.11 $\n\nRest of Middle East\n\n$ 0.07 $\n\nRest of Western Europe\n\n$ 0.10 $\n\nOthers\n\n$ 0.10 $\n\n\\* Over a 24-hour period\n\nMMS\n---\n\nCost: $0.05/MMS sent or received\n\nBrand Registration Fees\n-----------------------\n\nBrand Registration Fees\n\nFee type\n\nFee amount\n\nRequired for\n\nCharged by\n\nBrand application fee\n\n$4 (per request)\n\nAll Businesses\n\nTCR\n\nCampaign Registration Fees\n--------------------------\n\nCampaign Registration Fees\n\nFee type\n\nFee amount\n\nRequired for\n\nCharged by\n\nCampaign vetting fee\n\n$15 (per request)\n\nAll Businesses\n\nBandwidth\n\nLow volume Campaign\n\n$1.50 (monthly with a three-month minimum commitment)\n\nFor businesses sending less than 15,000 messages per month, throughput is restricted to 1\u00a0message per second per carrier across all numbers in this campaign.\n\nTCR\n\nStandard Campaign\n\n$10.00 (monthly with a three-month minimum commitment)\n\nFor businesses sending more than 15,000 messages per month from within this campaign or those that require higher throughputs.\n\nTCR\n\nAdditional Fees/Penalties\n-------------------------\n\nCarriers have enacted policies to ensure compliance with state and federal policies and ensure consumers are contacted in a safe and appropriate manner. In the event of a policy violation, carriers may impose the following fines.  \nPrices below are shown for informational purposes only and may change at any time.\n\nAdditional Fees/Penalties\n\nItem\n\nFee\n\nCompliance issue\n\nCharged by\n\nPerson-to-person route abuse\n\n$10 (per message)\n\nA business which deliberately ignores or evades the carrier rules regarding business SMS.\n\nT-Mobile\n\nFailure to utilize campaign penalty\n\n$250 (per violation)\n\nFines charged for any campaign with no number assigned for 60 days.\n\nT-Mobile\n\nTier 1 Severity 0 (Sev-0) violation\n\n$2,000 (per violation)\n\nFor any phishing, smishing, or social engineering (tactics to get a target to reveal personal information).\n\nT-Mobile\n\nTier 2 Severity 0 (Sev-0) violation\n\n$1,000 (per violation)\n\nSending illegal content (according to all state and federal laws). See T-Mobile\u2019s Code of Conduct, section 5.1.\n\nT-Mobile\n\nTier 3 Severity 0 (Sev-0) violation\n\n$500 (per violation)\n\nAny other instance of non-compliance. See T-Mobile\u2019s Code of Conduct, section 5.7.\n\nT-Mobile\n\n$21/user/month excl. taxes. Manage all your communication channels in Ringover and manage multichannel conversations in one place (WhatsApp, emails, etc.).",
      "error": null,
      "pricing_data": {
        "app_id": "ringover",
        "app_name": "Ringover",
        "app_slug": "ringover",
        "pricing_url": "https://www.ringover.com/pricing",
        "source_url": "https://www.ringover.com/pricing",
        "all_pricing_urls": [
          "https://www.ringover.com/pricing",
          "https://www.ringover.com/empower/pricing",
          "https://www.ringover.com/cadence/pricing"
        ],
        "price_model_type": [
          "PriceModelType.SUBSCRIPTION",
          "PriceModelType.USAGE_BASED"
        ],
        "has_free_tier": false,
        "has_free_trial": true,
        "free_trial_period_days": 7,
        "currency": "USD",
        "is_pricing_public": true,
        "pricing_page_accessible": true,
        "pricing_notes": "Pricing includes multiple tiers with specific features and add-ons.",
        "pricing_tiers": [
          {
            "tier_name": "SMART",
            "tier_description": "A friendly and flexible cloud phone system for your company\u2019s everyday needs.",
            "monthly_price": 29.0,
            "annual_price": 21.0,
            "annual_discount_percentage": 27.0,
            "setup_fee": null,
            "features": [
              "Unlimited calls to 110 destinations",
              "Local number from 43 countries",
              "Mobile, web, and desktop applications",
              "IVR and call forwarding",
              "Call logs and recordings",
              "Call and voicemail transcription and summary",
              "Click-to-call",
              "Video conference, instant messaging",
              "Access to our API"
            ],
            "limits": {
              "users": "unlimited",
              "storage": "unlimited",
              "operations": "unlimited",
              "api_calls": "unlimited",
              "integrations": 0,
              "custom_limits": null
            }
          },
          {
            "tier_name": "BUSINESS",
            "tier_description": "A 100% integrated cloud solution that empowers team management and support.",
            "monthly_price": 54.0,
            "annual_price": 44.0,
            "annual_discount_percentage": 18.52,
            "setup_fee": null,
            "features": [
              "All SMART features",
              "Local number from 65 countries",
              "Advanced IVR (smart routing, call groups, call queues)",
              "2 integrations",
              "Advanced analytics",
              "Coaching (double listening, whispering)",
              "Access to our webhooks"
            ],
            "limits": {
              "users": "unlimited",
              "storage": "unlimited",
              "operations": "unlimited",
              "api_calls": "unlimited",
              "integrations": 2,
              "custom_limits": null
            }
          },
          {
            "tier_name": "ADVANCED",
            "tier_description": "Advanced communication and productivity features to boost your business.",
            "monthly_price": null,
            "annual_price": null,
            "annual_discount_percentage": null,
            "setup_fee": null,
            "features": [
              "All BUSINESS features",
              "Call campaigns",
              "Power Dialer",
              "Call scripts",
              "Voicemail drop",
              "Local Presence Dialing",
              "3 integrations",
              "Single Sign-On"
            ],
            "limits": {
              "users": "unlimited",
              "storage": "unlimited",
              "operations": "unlimited",
              "api_calls": "unlimited",
              "integrations": 3,
              "custom_limits": null
            }
          }
        ],
        "usage_based_pricing": [
          {
            "metric_name": "WhatsApp messaging",
            "unit": "per message",
            "base_price": 0.04,
            "tiers": [
              {
                "min": 0.0,
                "max": "unlimited",
                "price": 0.04
              }
            ]
          },
          {
            "metric_name": "MMS",
            "unit": "per message",
            "base_price": 0.05,
            "tiers": [
              {
                "min": 0.0,
                "max": "unlimited",
                "price": 0.05
              }
            ]
          }
        ],
        "ai_specific_pricing": null,
        "promotional_offers": null,
        "additional_fees": [
          {
            "fee_name": "Omnichannel messaging add-on",
            "fee_amount": 29.0,
            "fee_description": "Connect all your communication channels to Ringover and manage all your conversations in one place."
          },
          {
            "fee_name": "SSO add-on",
            "fee_amount": 2.0,
            "fee_description": "Activate Single Sign-On to connect to all your tools, including Ringover."
          }
        ],
        "extraction_timestamp": "2025-04-15T04:26:11.106978",
        "schema_validated": true,
        "confidence_score": 95,
        "extraction_error": false,
        "json_repaired": false
      },
      "pricing_analyzed": true
    }
  ],
  "results_directory": "pricing_results\\ringover\\20250415_042611"
}