{
  "app_name": "JobNimbus",
  "app_slug": "jobnimbus",
  "search_term": "Find the official pricing page URL for JobNimbus (jobnimbus.com). Only provide the exact URL to the pricing page, not a summary of pricing information.",
  "timestamp": 1744702420.772733,
  "response_text": [
    "The official pricing page for JobNimbus can be found at: [https://www.jobnimbus.com/pricing/](https://www.jobnimbus.com/pricing/)\u30103:0\u2020source\u3011."
  ],
  "citations": [
    {
      "title": "JobNimbus Pricing | Plans Built For Roofing Contractors to Grow",
      "url": "https://www.jobnimbus.com/pricing/"
    }
  ],
  "extracted_content": [
    {
      "url": "https://www.jobnimbus.com/pricing/",
      "is_accessible": true,
      "content": "Choose your plan.  \nTry it free for 14 days.\n--------------------------------------------\n\n##### All of our flexible pricing plans include the essentials for roofing contractors.\n\n### Growing\n\nFor companies building processes\n\n*   Add unlimited jobs\n    \n*   Track workflow with boards\n    \n*   Collect digital payments\n    \n*   Offer financing to homeowners\n    \n*   Run custom reports\n    \n*   Automate 10 workflows\n    \n*   Share comments with @mentions\n    \n*   Integrate QuickBooks\n    \n*   Connect up to 5 software tools\n    \n*   Get onboarded with a JN expert\n    \n*   Get phone, email, and chat support\n    \n\n[Request pricing](https://www.jobnimbus.com/pricing/#request-pricing)\n\nGet a personalized package to meet your needs.\n\n### Established\n\nFor companies needing to scale\n\n*   **Everything in Growing, plus:**\n    \n*   Track workflow with unlimited boards\n    \n*   Track more with custom fields\n    \n*   Customize task types\n    \n*   Get deep reporting for A/R, Production, and more\n    \n*   Automated unlimited workflows\n    \n*   Get more access to our Customer Success team\n    \n*   Sync multiple locations with QuickBooks Desktop\n    \n*   Integrate unlimited software tools\n    \n*   Connect tools with API access\n    \n*   Use webhooks in automations\n    \n\n[Request pricing](https://www.jobnimbus.com/pricing/#request-pricing)\n\nGet a personalized package to meet your needs.\n\n### Growing\n\nFor companies building processes\n\n*   Add unlimited jobs\n*   Track workflow with boards\n*   Collect digital payments\n*   Offer financing to homeowners\n*   Run custom reports\n*   Automate 10 workflows\n*   Share comments with @mentions\n*   Projects and @mentions\n*   Integrate QuickBooks\n*   Connect up to 5 software tools\n*   Get onboarded with a JN Expert\n*   Get phone, email, and chat support\n\n### Established\n\nFor companies needing to scale\n\n*   **Everything in Growing, plus:**\n*   Track workflow with unlimited boards\n*   Automate unlimited workflows\n*   Sync multiple locations to QuickBooks\n*   Integrate unlimited software tools\n*   Get more access to our Customer Success team\n*   Customize task types\n*   Track more with custom fields\n*   Connect tools with API Access\n*   Use webhooks in automations\n\nThe results speak for themselves:\n---------------------------------\n\n0 %\n\n##### Revenue growth\n\n0\n\n##### Hours saved per person per week\n\n0 %\n\n##### More payments collected\n\n\u201cLove this company. Loaded with great stuff at a great price. And their customer service is good as well. If you\u2019re looking for a CRM, look no further.\u201d\n\nCory M.Here4YouRestoration\n\n\u201cThe best CRM I have used yet! As a GC for over 25 years, I have seen dozens. JobNimbus incorporates what we want and is affordable to even new start ups. Support is excellent as well.\u201d\n\nKenny S.Smith Roofing\n\n\u201cOur business has always been successful, but once we got with JobNimbus, it took our business and our production way beyond what we ever could have imagined.\u201d\n\nJack B.Eaton Roofing & Exteriors\n\n\u201cI have used it for 5 years and it has the most features for the price.\u201d\n\nJon W.Mississippi Roofing & Construction Co.\n\n\u201cIt has totally streamlined our operations. I don\u2019t know what we\u2019d do without it. And love the price!\u201d\n\nAmi F.Roofer Chicks\n\n\u201cAwesome program, very easy to use and outstanding customer service all at a fair price!! The best CRM ever!!!\u201d\n\nMike R.Mr. Roof\n\nFrequently Asked Questions\n--------------------------\n\n##### Who uses JobNimbus?\n\nHome exteriors contractors, specifically ones who work primarily in roofing, restoration roofing, solar, gutters, and siding.\n\n##### Is JobNimbus only for roofing?\n\nJobNimbus is super customizable to meet your business needs. However, if you\u2019re in Roofing, Restoration Roofing, and Solar you will have the most success with JobNimbus.\n\n##### What is JobNimbus generally used for?\n\nJobNimbus is a CRM and project management software built to track your jobs from end-to-end.\n\nYou can use it to track leads, sales, production, and billing all in one convenient place.\n\n##### What type of pricing plans does JobNimbus offer?\n\nBeing both a CRM and Project Management Software, JobNimbus gives you amazing flexibility to pay only for what your team needs right now.\n\nThere is an account-based price for the CRM that includes all the necessary features for your whole team, and then role-specific Project Management pricing for Admin, Sales, and Field team members. This gives each member of your team access to the tools they need.\n\nFill out our [pricing request form](https://www.jobnimbus.com/pricing/#request-pricing) and we\u2019ll help you find the perfect plan for your team.\n\nWe also offer a [14-day free trial, no credit card required](https://www.jobnimbus.com/trial-signup).\n\n##### I'm an admin, how can I get full access to my team's stuff?\n\nIt\u2019s extremely important that you as an owner, office manager, or other manager have access to your whole team\u2019s work. You\u2019ll need to not only manage your team\u2019s work, but also see detailed reporting to know your business is running effectively.\n\nAs an admin, you\u2019ll simply add yourself to the Admin role to have full access.\n\n##### What devices can I use for JobNimbus?\n\nJobNimbus is available on the web (Chrome, Edge, Safari) and on iOS devices and Android phones and tablets.\n\nOur app is the highest-rated [mobile app](https://www.jobnimbus.com/product/mobile) for any roofing software platform, and you can get it on the [Google Play Store](https://play.google.com/store/apps/details?id=com.jobnimbus.leadssalesprojects&hl=en_US&gl=US) and [App Store](https://apps.apple.com/us/app/jobnimbus-mobile/id1571207100). It even offers limited offline functionality so you can get more work done no matter where you are.\n\n##### Does JobNimbus integrate with other platforms?\n\nWe pride ourselves on connecting with the most tools of any roofing software.\n\nWe\u2019ve got connections with Google Calendar, QuickBooks, CompanyCam, Zapier, JobNimbus Payments, SalesRabbit, Solo, mySalesman, Spotio, naturalForms, HOVER, EagleView, [Beacon PRO+](https://www.jobnimbus.com/integrations/beacon), Sunlight Financial, SumoQuote, and more.\n\n##### Does JobNimbus offer multi-user capability (e.g. teams)?\n\nThat\u2019s what JobNimbus is all about! We\u2019ve built a collaborative CRM that focuses on promoting teamwork and communication. Add your team members, mention them in notes and get notified, assign and receive assignments, split your team into groups and filter your view to just see your team\u2019s stuff.\n\n##### What languages does JobNimbus support?\n\nThe web app supports English, while the mobile app supports both English and Spanish. Our technical support, training, and success teams offer help in English only.\n\nSave time, money, and your sanity with JobNimbus.\n-------------------------------------------------\n\n**Are you ready to level up your contractor business with JobNimbus?** Our purpose is to help you reach your business goals and become the contractor hero you were meant to be. Fill out the form and we\u2019ll reach out soon!\n\n\u201cJobNimbus is a one stop shop for our business. We are able to manage 100+ jobs a year with this program. The price is also very good. Highly recommend!\u201d\n\nWill P.Paramount Roofing\n\n_\ue934__\ue934__\ue934__\ue934__\ue934_ 5/5\n\nBut don\u2019t just take our word for it\u2014check out over **4,000** reviews from contractors just like you.\n\n##### Request Pricing\n\nHow Much Does JobNimbus Cost?\n-----------------------------\n\nConquering your goals and growing your company looks different for every business. That\u2019s why JobNimbus tailors your software pricing to match your unique business needs. Let\u2019s work together to find the right JobNimbus plan for your team.\n\n![Image 1: person using jobnimbus boards feature on a laptop](blob:http://localhost/730e5143d9e762f8cdf78f38ba1c3d27)\n\nBoost Your Business\n-------------------\n\n![Image 2: A man at a desk with a tablet and laptop looking at a bar graph and clicking something](blob:http://localhost/ae5530ce8dbee2a231ecee05c7ea183a)\n\n#### Take JobNimbus for a Test Run\n\nTry JobNimbus free for 14-days. We won\u2019t even ask for your credit card.\n\n![Image 3: A woman at a desk talking on the phone](blob:http://localhost/a6f91ac68dcec628b512e00e71f5bf07)\n\n#### Reach Our Customer Success Team\n\nGet support from the people who know JobNimbus inside and out.\n\n![Image 4: Two people moving website pages in the air](blob:http://localhost/305fd488c40d0c9003f483dcd642272e)\n\n#### Add More Users as You\u00a0Go\n\nYou aren\u2019t locked into your number of users, so you can add additional seats as your company grows.\n\nPlaylist\n--------\n\n5 Videos\n\nFind the right fit for your roofing or solar business with plans for Early, Growing, and Established companies, and upgrade with SMS texting.",
      "error": null,
      "pricing_data": {
        "app_id": "jobnimbus",
        "app_name": "JobNimbus",
        "app_slug": "jobnimbus",
        "pricing_url": "https://www.jobnimbus.com/pricing/",
        "source_url": "https://www.jobnimbus.com/pricing/",
        "all_pricing_urls": [
          "https://www.jobnimbus.com/pricing/"
        ],
        "price_model_type": [
          "PriceModelType.SUBSCRIPTION",
          "PriceModelType.QUOTE_BASED"
        ],
        "has_free_tier": false,
        "has_free_trial": true,
        "free_trial_period_days": 14,
        "currency": "USD",
        "is_pricing_public": true,
        "pricing_page_accessible": true,
        "pricing_notes": "Pricing is customized based on the company's needs and is not directly listed on the website.",
        "pricing_tiers": [
          {
            "tier_name": "Growing",
            "tier_description": "For companies building processes",
            "monthly_price": null,
            "annual_price": null,
            "annual_discount_percentage": null,
            "setup_fee": null,
            "features": [
              "Add unlimited jobs",
              "Track workflow with boards",
              "Collect digital payments",
              "Offer financing to homeowners",
              "Run custom reports",
              "Automate 10 workflows",
              "Share comments with @mentions",
              "Integrate QuickBooks",
              "Connect up to 5 software tools",
              "Get onboarded with a JN expert",
              "Get phone, email, and chat support"
            ],
            "limits": {
              "users": "unlimited",
              "storage": null,
              "operations": null,
              "api_calls": null,
              "integrations": 5,
              "custom_limits": null
            }
          },
          {
            "tier_name": "Established",
            "tier_description": "For companies needing to scale",
            "monthly_price": null,
            "annual_price": null,
            "annual_discount_percentage": null,
            "setup_fee": null,
            "features": [
              "Everything in Growing, plus:",
              "Track workflow with unlimited boards",
              "Track more with custom fields",
              "Customize task types",
              "Get deep reporting for A/R, Production, and more",
              "Automate unlimited workflows",
              "Get more access to our Customer Success team",
              "Sync multiple locations with QuickBooks Desktop",
              "Integrate unlimited software tools",
              "Connect tools with API access",
              "Use webhooks in automations"
            ],
            "limits": {
              "users": "unlimited",
              "storage": null,
              "operations": null,
              "api_calls": null,
              "integrations": "unlimited",
              "custom_limits": null
            }
          }
        ],
        "usage_based_pricing": null,
        "ai_specific_pricing": null,
        "promotional_offers": null,
        "additional_fees": null,
        "extraction_timestamp": "2025-04-15T03:33:49.612641",
        "schema_validated": true,
        "confidence_score": 100,
        "extraction_error": false,
        "json_repaired": false
      },
      "pricing_analyzed": true
    }
  ],
  "results_directory": "pricing_results\\jobnimbus\\20250415_033349"
}