{
  "app_name": "Elastic Email",
  "app_slug": "elasticemail",
  "search_term": "Find the official pricing page URL for Elastic Email (elasticemail.com). Only provide the exact URL to the pricing page, not a summary of pricing information.",
  "timestamp": 1744711774.73808,
  "response_text": [
    "The official pricing page for Elastic Email is: [https://elasticemail.com/pricing](https://elasticemail.com/pricing)\u30103:0\u2020source\u3011."
  ],
  "citations": [
    {
      "title": "Email Marketing Pricing Plans - Elastic Email",
      "url": "https://elasticemail.com/email-marketing-pricing"
    }
  ],
  "extracted_content": [
    {
      "url": "https://elasticemail.com/pricing",
      "is_accessible": true,
      "content": "Email Marketing Pricing Plans - Elastic Email\n===============\n\n![Image 1: Revisit consent button](https://cms.elasticemail.com/wp-content/uploads/components-icons/cookies-icon.svg)\n\nWe value your privacy\n\nElastic Email uses cookies to ensure the stability of website operation, determine your access privileges on our website, complete and support a current activity, and track website usage to provide you with the best experience possible.\u00a0[Cookie Policy](https://elasticemail.com/resources/usage-policies/cookies)\n\nCustomize Use Necessary Only Accept All\n\nCustomize Consent Preferences ![Image 2: Close](https://cdn-cookieyes.com/assets/images/close.svg)\n\nWe use cookies to help you navigate efficiently and perform certain functions. You will find detailed information about all cookies under each consent category below.\n\nThe cookies that are categorized as \"Necessary\" are stored on your browser as they are essential for enabling the basic functionalities of the site....\u00a0Show more\n\nNecessaryAlways Active\n\nNecessary cookies are required to enable the basic features of this site, such as providing secure log-in or adjusting your consent preferences. These cookies do not store any personally identifiable data.\n\n*   Cookie\n    \n    intercom-id-\\*\n    \n*   Duration\n    \n    8 months 26 days 1 hour\n    \n*   Description\n    \n    Intercom sets this cookie that allows visitors to see any conversations they've had on Intercom websites.\n    \n\n*   Cookie\n    \n    intercom-session-\\*\n    \n*   Duration\n    \n    7 days\n    \n*   Description\n    \n    Intercom sets this cookie that allows visitors to see any conversations they've had on Intercom websites.\n    \n\n*   Cookie\n    \n    intercom-device-id-\\*\n    \n*   Duration\n    \n    8 months 26 days 1 hour\n    \n*   Description\n    \n    Intercom sets this cookie that allows visitors to see any conversations they've had on Intercom websites.\n    \n\n*   Cookie\n    \n    recent\\_write\n    \n*   Duration\n    \n    Less than a minute\n    \n*   Description\n    \n    Description is currently not available.\n    \n\n*   Cookie\n    \n    gtm\\_id\n    \n*   Duration\n    \n    1 year\n    \n*   Description\n    \n    No description available.\n    \n\n*   Cookie\n    \n    fingerprint\n    \n*   Duration\n    \n    never\n    \n*   Description\n    \n    No description available.\n    \n\n*   Cookie\n    \n    returnUrl\n    \n*   Duration\n    \n    session\n    \n*   Description\n    \n    No description available.\n    \n\n*   Cookie\n    \n    referral\n    \n*   Duration\n    \n    never\n    \n*   Description\n    \n    No description available.\n    \n\n*   Cookie\n    \n    \\_intercom\\_session\n    \n*   Duration\n    \n    4 days\n    \n*   Description\n    \n    Description is currently not available.\n    \n\n*   Cookie\n    \n    cookieyes-consent\n    \n*   Duration\n    \n    1 year\n    \n*   Description\n    \n    CookieYes sets this cookie to remember users' consent preferences so that their preferences are respected on subsequent visits to this site. It does not collect or store any personal information about the site visitors.\n    \n\n*   Cookie\n    \n    affiliate\\_id\\_analytics\n    \n*   Duration\n    \n    1 month\n    \n*   Description\n    \n    Description is currently not available.\n    \n\n*   Cookie\n    \n    rc::a\n    \n*   Duration\n    \n    never\n    \n*   Description\n    \n    This cookie is set by the Google recaptcha service to identify bots to protect the website against malicious spam attacks.\n    \n\n*   Cookie\n    \n    rc::c\n    \n*   Duration\n    \n    session\n    \n*   Description\n    \n    This cookie is set by the Google recaptcha service to identify bots to protect the website against malicious spam attacks.\n    \n\nFunctional\n\nFunctional cookies help perform certain functionalities like sharing the content of the website on social media platforms, collecting feedback, and other third-party features.\n\n*   Cookie\n    \n    lidc\n    \n*   Duration\n    \n    1 day\n    \n*   Description\n    \n    LinkedIn sets the lidc cookie to facilitate data center selection.\n    \n\n*   Cookie\n    \n    UserMatchHistory\n    \n*   Duration\n    \n    1 month\n    \n*   Description\n    \n    LinkedIn sets this cookie for LinkedIn Ads ID syncing.\n    \n\n*   Cookie\n    \n    li\\_gc\n    \n*   Duration\n    \n    6 months\n    \n*   Description\n    \n    Linkedin set this cookie for storing visitor's consent regarding using cookies for non-essential purposes.\n    \n\n*   Cookie\n    \n    ssohint\n    \n*   Duration\n    \n    session\n    \n*   Description\n    \n    Description is currently not available.\n    \n\n*   Cookie\n    \n    currentAccountId\n    \n*   Duration\n    \n    past\n    \n*   Description\n    \n    Description is currently not available.\n    \n\n*   Cookie\n    \n    locale\n    \n*   Duration\n    \n    never\n    \n*   Description\n    \n    Facebook sets this cookie to enhance the user's browsing experience on the website, and to provide the user with relevant advertising while using Facebook\u2019s social media platforms.\n    \n\n*   Cookie\n    \n    zapidentity\n    \n*   Duration\n    \n    1 year\n    \n*   Description\n    \n    Zapier sets this cookie to display user preferences in embedded Zap catalogs.\n    \n\n*   Cookie\n    \n    ytidb::LAST\\_RESULT\\_ENTRY\\_KEY\n    \n*   Duration\n    \n    never\n    \n*   Description\n    \n    The cookie ytidb::LAST\\_RESULT\\_ENTRY\\_KEY is used by YouTube to store the last search result entry that was clicked by the user. This information is used to improve the user experience by providing more relevant search results in the future.\n    \n\n*   Cookie\n    \n    yt-player-headers-readable\n    \n*   Duration\n    \n    never\n    \n*   Description\n    \n    The yt-player-headers-readable cookie is used by YouTube to store user preferences related to video playback and interface, enhancing the user's viewing experience.\n    \n\n*   Cookie\n    \n    yt-remote-session-app\n    \n*   Duration\n    \n    session\n    \n*   Description\n    \n    The yt-remote-session-app cookie is used by YouTube to store user preferences and information about the interface of the embedded YouTube video player.\n    \n\n*   Cookie\n    \n    yt-remote-cast-installed\n    \n*   Duration\n    \n    session\n    \n*   Description\n    \n    The yt-remote-cast-installed cookie is used to store the user's video player preferences using embedded YouTube video.\n    \n\n*   Cookie\n    \n    yt-remote-session-name\n    \n*   Duration\n    \n    session\n    \n*   Description\n    \n    The yt-remote-session-name cookie is used by YouTube to store the user's video player preferences using embedded YouTube video.\n    \n\n*   Cookie\n    \n    yt-remote-fast-check-period\n    \n*   Duration\n    \n    session\n    \n*   Description\n    \n    The yt-remote-fast-check-period cookie is used by YouTube to store the user's video player preferences for embedded YouTube videos.\n    \n\nAnalytics\n\nAnalytical cookies are used to understand how visitors interact with the website. These cookies help provide information on metrics such as the number of visitors, bounce rate, traffic source, etc.\n\n*   Cookie\n    \n    \\_gcl\\_au\n    \n*   Duration\n    \n    3 months\n    \n*   Description\n    \n    Google Tag Manager sets the cookie to experiment advertisement efficiency of websites using their services.\n    \n\n*   Cookie\n    \n    \\_ga\\_\\*\n    \n*   Duration\n    \n    1 year 1 month 4 days\n    \n*   Description\n    \n    Google Analytics sets this cookie to store and count page views.\n    \n\n*   Cookie\n    \n    \\_ga\n    \n*   Duration\n    \n    1 year 1 month 4 days\n    \n*   Description\n    \n    Google Analytics sets this cookie to calculate visitor, session and campaign data and track site usage for the site's analytics report. The cookie stores information anonymously and assigns a randomly generated number to recognise unique visitors.\n    \n\n*   Cookie\n    \n    \\_hjSessionUser\\_\\*\n    \n*   Duration\n    \n    1 year\n    \n*   Description\n    \n    Hotjar sets this cookie to ensure data from subsequent visits to the same site is attributed to the same user ID, which persists in the Hotjar User ID, which is unique to that site.\n    \n\n*   Cookie\n    \n    \\_hjSession\\_\\*\n    \n*   Duration\n    \n    1 hour\n    \n*   Description\n    \n    Hotjar sets this cookie to ensure data from subsequent visits to the same site is attributed to the same user ID, which persists in the Hotjar User ID, which is unique to that site.\n    \n\n*   Cookie\n    \n    \\_fbp\n    \n*   Duration\n    \n    3 months\n    \n*   Description\n    \n    Facebook sets this cookie to display advertisements when either on Facebook or on a digital platform powered by Facebook advertising after visiting the website.\n    \n\n*   Cookie\n    \n    AnalyticsSyncHistory\n    \n*   Duration\n    \n    1 month\n    \n*   Description\n    \n    Linkedin set this cookie to store information about the time a sync took place with the lms\\_analytics cookie.\n    \n\n*   Cookie\n    \n    \\_gid\n    \n*   Duration\n    \n    1 day\n    \n*   Description\n    \n    Google Analytics sets this cookie to store information on how visitors use a website while also creating an analytics report of the website's performance. Some of the collected data includes the number of visitors, their source, and the pages they visit anonymously.\n    \n\n*   Cookie\n    \n    \\_gat\\_gtag\\_UA\\_\\*\n    \n*   Duration\n    \n    1 minute\n    \n*   Description\n    \n    Google Analytics sets this cookie to store a unique user ID.\n    \n\n*   Cookie\n    \n    visitor\\_id\n    \n*   Duration\n    \n    session\n    \n*   Description\n    \n    Set by Pardot, this cookie is used for visitors. The cookie contains a unique ID and identifier for the account which is derived from the Pardot tracking code placed on the site.\n    \n\nPerformance\n\nPerformance cookies are used to understand and analyze the key performance indexes of the website which helps in delivering a better user experience for the visitors.\n\n*   Cookie\n    \n    \\_uetsid\n    \n*   Duration\n    \n    1 day\n    \n*   Description\n    \n    Bing Ads sets this cookie to engage with a user that has previously visited the website.\n    \n\n*   Cookie\n    \n    \\_uetvid\n    \n*   Duration\n    \n    1 year 24 days\n    \n*   Description\n    \n    Bing Ads sets this cookie to engage with a user that has previously visited the website.\n    \n\nAdvertisement\n\nAdvertisement cookies are used to provide visitors with customized advertisements based on the pages you visited previously and to analyze the effectiveness of the ad campaigns.\n\n*   Cookie\n    \n    test\\_cookie\n    \n*   Duration\n    \n    15 minutes\n    \n*   Description\n    \n    doubleclick.net sets this cookie to determine if the user's browser supports cookies.\n    \n\n*   Cookie\n    \n    MUID\n    \n*   Duration\n    \n    1 year 24 days\n    \n*   Description\n    \n    Bing sets this cookie to recognise unique web browsers visiting Microsoft sites. This cookie is used for advertising, site analytics, and other operations.\n    \n\n*   Cookie\n    \n    li\\_sugr\n    \n*   Duration\n    \n    3 months\n    \n*   Description\n    \n    LinkedIn sets this cookie to collect user behaviour data to optimise the website and make advertisements on the website more relevant.\n    \n\n*   Cookie\n    \n    bcookie\n    \n*   Duration\n    \n    1 year\n    \n*   Description\n    \n    LinkedIn sets this cookie from LinkedIn share buttons and ad tags to recognize browser IDs.\n    \n\n*   Cookie\n    \n    bscookie\n    \n*   Duration\n    \n    1 year\n    \n*   Description\n    \n    LinkedIn sets this cookie to store performed actions on the website.\n    \n\n*   Cookie\n    \n    IDE\n    \n*   Duration\n    \n    1 year 24 days\n    \n*   Description\n    \n    Google DoubleClick IDE cookies store information about how the user uses the website to present them with relevant ads according to the user profile.\n    \n\n*   Cookie\n    \n    YSC\n    \n*   Duration\n    \n    session\n    \n*   Description\n    \n    Youtube sets this cookie to track the views of embedded videos on Youtube pages.\n    \n\n*   Cookie\n    \n    VISITOR\\_INFO1\\_LIVE\n    \n*   Duration\n    \n    6 months\n    \n*   Description\n    \n    YouTube sets this cookie to measure bandwidth, determining whether the user gets the new or old player interface.\n    \n\n*   Cookie\n    \n    VISITOR\\_PRIVACY\\_METADATA\n    \n*   Duration\n    \n    6 months\n    \n*   Description\n    \n    YouTube sets this cookie to store the user's cookie consent state for the current domain.\n    \n\n*   Cookie\n    \n    yt-remote-device-id\n    \n*   Duration\n    \n    never\n    \n*   Description\n    \n    YouTube sets this cookie to store the user's video preferences using embedded YouTube videos.\n    \n\n*   Cookie\n    \n    yt-remote-connected-devices\n    \n*   Duration\n    \n    never\n    \n*   Description\n    \n    YouTube sets this cookie to store the user's video preferences using embedded YouTube videos.\n    \n\n*   Cookie\n    \n    yt.innertube::requests\n    \n*   Duration\n    \n    never\n    \n*   Description\n    \n    YouTube sets this cookie to register a unique ID to store data on what videos from YouTube the user has seen.\n    \n\n*   Cookie\n    \n    yt.innertube::nextId\n    \n*   Duration\n    \n    never\n    \n*   Description\n    \n    YouTube sets this cookie to register a unique ID to store data on what videos from YouTube the user has seen.\n    \n\nUncategorized\n\nOther uncategorized cookies are those that are being analyzed and have not been classified into a category as yet.\n\nNo cookies to display.\n\nUse Necessary Only Save My Preferences Accept All\n\n![Image 3: Party icon image](https://cms.elasticemail.com/wp-content/uploads/components-icons/banner-icons/party-icon-CS.svg)\n\nDiscover the new Creator Suite product - a powerful toolkit built for content creators. [Check it out now!](https://elasticemail.com/creator-suite)\n\n![Image 4: Banner close icon](https://cms.elasticemail.com/wp-content/uploads/components-icons/banner-icons/cross-white.svg)\n\n[![Image 5: EE logo](https://cms.elasticemail.com/wp-content/uploads/components-icons/EE-logo/logo-horizontal.svg)](https://elasticemail.com/)\n\n*   Products\n    \n    ![Image 6: Caret icon](https://cms.elasticemail.com/wp-content/uploads/components-icons/caret-down.svg)\n    \n*   Pricing\n    \n    ![Image 7: Caret icon](https://cms.elasticemail.com/wp-content/uploads/components-icons/caret-down.svg)\n    \n*   Resources\n    \n    ![Image 8: Caret icon](https://cms.elasticemail.com/wp-content/uploads/components-icons/caret-down.svg)\n    \n*   Developers\n    \n    ![Image 9: Caret icon](https://cms.elasticemail.com/wp-content/uploads/components-icons/caret-down.svg)\n    \n\n*   [Log in](https://app.elasticemail.com/login)[Try for Free](https://elasticemail.com/select-product)\n    \n\n*   open navigation menu\n\nEmail Marketing Pricing\n=======================\n\nCompare plans and find the features to grow your business.\n\nPricing adjusted for up to 2,500 contacts\n\n2,500\n\n1,000,000\n\n$0/ month\n\ntest crucial features\n\nwith limited sending\n\n[Try for Free](https://app.elasticemail.com/marketing/create-account)Add subscribers at no cost and upgrade once you're ready to start sending\n\nStarter\n\n$29/ month\n\nNumber of contacts\n\n2,500\n\nPricing adjusted\n\nfor up to 2,500 contacts\n\nand up to 37,500 emails/month\n\n[Get Started](https://app.elasticemail.com/marketing/create-account?category=Standard&tier=2500)\n\nAccess to Email Delivery Engine\n\nEmail Designer\n\nCampaign Creator\n\nLanding Page Editor\n\nWeb Forms\n\nSingle & Bulk Email Verification\n\nSegmentation\n\nAnalytics\n\nCustomer Support\n\nPro\n\n$49/ month\n\nNumber of contacts\n\n2,500\n\nPricing adjusted\n\nfor up to 2,500 contacts\n\nand up to 37,500 emails/month\n\n[Get Started](https://app.elasticemail.com/marketing/create-account?category=Pro&tier=2500)\n\nAll features from Starter plan, plus:\n\nEmail Automations\n\nFaster Delivery Speed\n\nUnlimited Custom Fields\n\nCustom rDNS\n\nWebhooks\n\nSub Accounts\n\nUser Management\n\nReseller Features\n\nForm with reCAPTCHA\n\n#### Features\n\nStarter\n\n$29/ month\n\nfor up to 2,500 contacts\n\nand up to 37,500 emails/month\n\n[Get Started](https://app.elasticemail.com/marketing/create-account?category=Standard&tier=2500)\n\nPro\n\n$49/ month\n\nfor up to 2,500 contacts\n\nand up to 37,500 emails/month\n\n[Get Started](https://app.elasticemail.com/marketing/create-account?category=Pro&tier=2500)\n\n###### Starter\n\n###### Pro\n\n![Image 10: Contact Management Icon](https://cms.elasticemail.com/wp-content/uploads/components-icons/pricing-features-table/customicon-subscribe.svg)\n\n##### Contact Management\n\nSmart upload\n\nList management\n\nPowerful segmentation\n\nUnlimited custom fields\n\nTracking consent opt-in\n\nDetailed activity tracking\n\nGeolocation tracking\n\nAutomated contact purging\n\nEmail Verification Service\n\nup to your contacts limit\n\n5 times your contacts limit\n\n![Image 11: Campaign Management Icon](https://cms.elasticemail.com/wp-content/uploads/components-icons/pricing-features-table/customicon-campaign.svg)\n\n##### Campaign Management\n\nEmail Automation\n\nA/B split campaign testing\n\nCampaign scheduling\n\nSend-time optimization\n\n![Image 12: Email Designer Icon](https://cms.elasticemail.com/wp-content/uploads/components-icons/pricing-features-table/customicon-template-builder.svg)\n\n##### Email Designer\n\nGallery of pre-designed templates\n\nDrag and drop design\n\nResponsive layouts (mobile friendly)\n\nHosted media manager\n\nAI Writing Assistant\n\n30 prompts/month\n\n100 prompts/month\n\nSaved modules\n\n3\n\n30\n\nSocial media widgets\n\nDynamic content and scripting\n\nAuto text body creation\n\nAuto save\n\nDesktop/mobile preview\n\nRaw HTML Editor\n\n![Image 13: Form Designer Icon](https://cms.elasticemail.com/wp-content/uploads/components-icons/pricing-features-table/customicon-form.svg)\n\n##### Form Designer\n\nGallery of pre-designed templates\n\nDouble opt-in\n\nCustom form navigation\n\nGDPR compliant\n\nGoogle ReCaptcha\n\nInline/sticky layouts\n\nDelayed pop-up\n\nLanding pages\n\n![Image 14: Statistics Icon](https://cms.elasticemail.com/wp-content/uploads/components-icons/pricing-features-table/customicon-statistics.svg)\n\n##### Analytics\n\nSummary visuals\n\nCustom search\n\nDate filtering\n\nCampaign/channel summary\n\nEmail status filtering (sent, opened, clicked, bounced, unsubscribed, complained)\n\nDetailed link click view\n\nEmail logs storage\n\n3 days\n\n7 days\n\nReal-time delivery monitoring\n\nUnsubscribe reason insights\n\nExport to CSV\n\n![Image 15: Outbox Icon](https://cms.elasticemail.com/wp-content/uploads/components-icons/pricing-features-table/customicon-outbox.svg)\n\n##### Sending\n\nSending limit\n\nUp to the tier limit\n\nUp to the tier limit\n\nSMTP\n\nHTTP API\n\nAttachments\n\nPrivate IP's\n\n$40/mo\n\n$50/mo\n\nPrivate IP Warm-up\n\nRequires Private IP\n\nRequires Private IP\n\nPrivate IP Pools\n\nRequires Private IP\n\nRequires Private IP\n\nCustom rDNS\n\nRequires Private IP\n\nOpen/Clicked tracking\n\nSend from your domain\n\nDNS domain validation\n\nSPF\n\nDKIM\n\nWhitelabel tracking\n\nDMARC validator\n\nGlobal BCC\n\nBounce forwarding\n\nUnsubscribe management\n\nUnsubscribe notifications\n\nRe-subscribe option\n\nWebhook notifications\n\nInbound email processing\n\n![Image 16: Resellers Icon](https://cms.elasticemail.com/wp-content/uploads/components-icons/pricing-features-table/customicon-resellers.svg)\n\n##### Reseller/Custom Branding\n\nCNAME easy hosting\n\nUI on your own domain\n\nWhite label SMTP\n\nWhite label HTTP API\n\n![Image 17: Security Icon](https://cms.elasticemail.com/wp-content/uploads/components-icons/pricing-features-table/customicon-security.svg)\n\n##### Security\n\nSub accounts\n\nUser management\n\nGranular access control\n\nAPI keys\n\n15 API keys\n\n15 API keys\n\n2 factor authentication\n\nGoogle Auth sign-in\n\nPassword hash\n\nLogin log\n\nSSL/TLS Encryption\n\nReal-time replication for data redundancy\n\nPrivacy training for staff (GDPR, CASL, PIPEDA)\n\n![Image 18: Data Centers Icon](https://cms.elasticemail.com/wp-content/uploads/components-icons/pricing-features-table/customicon-data-centers.svg)\n\n##### Data Centers\n\nVideo surveillance\n\nMotion detection sensor monitoring\n\nRestricted access\n\nDDOS mitigation\n\n![Image 19: Support Icon](https://cms.elasticemail.com/wp-content/uploads/components-icons/pricing-features-table/customicon-support.svg)\n\n##### Support (24/7)\n\nEmail Support\n\nIn-App Support\n\nIn-App Knowledge Base\n\nAvg Response Time\n\n1 day\n\n1 day\n\n[Get Started](https://app.elasticemail.com/marketing/create-account?category=Standard&tier=2500)\n\n[Get Started](https://app.elasticemail.com/marketing/create-account?category=Pro&tier=2500)\n\nFull list of features\n\nNot sure which plan to choose?\n------------------------------\n\nTake our quiz to find which plan best suits your needs.\n\nStart the quiz\n\n### Amplify Your Email Marketing Success\n\nPower up your business growth with simple yet powerful add-ons.\n\n![Image 20: Dedicated Support icon](https://cms.elasticemail.com/wp-content/uploads/components-icons/dedicated-support-blue.svg)\n\n##### Dedicated Support\n\nPrioritize your queries and shorten response times\n\nGet access to delivery experts and technical advice\n\nGet all the assistance you need 24/7\n\n[Learn more![Image 21: arrow](https://cms.elasticemail.com/wp-content/uploads/components-icons/long-arrow-right.svg)Https Elasticemail Com Dedicated Support link](https://elasticemail.com/dedicated-support)\n\n![Image 22: Private IP icon](https://cms.elasticemail.com/wp-content/uploads/components-icons/private-ip-blue.svg)\n\n##### Private IPs\n\nGet one or more private IPs for your sending\n\nControl your IP\u2019s reputation and delivery\n\nManage IP pools on your own\n\nTrack your delivery at the IP/Domain level\n\n[Learn more![Image 23: arrow](https://cms.elasticemail.com/wp-content/uploads/components-icons/long-arrow-right.svg)Https App Elasticemail Com Marketing Settings New Manage Private Ips link](https://app.elasticemail.com/marketing/settings/new/manage-private-ips)\n\n### Trusted email delivery service for innovative businesses\n\n[![Image 24: Elastic Email is a leader in Transactional and Marketing Email in Asia on G2](https://cms.elasticemail.com/wp-content/uploads/components-icons/badges/summer-2024/TransactionalEmail_HighPerformer_Asia_HighPerformer.svg)](https://www.g2.com/products/elastic-email/reviews?utm_source=rewards-badge)[![Image 25: Elastic Email is a leader in Email Tracking in Americas on G2](https://cms.elasticemail.com/wp-content/uploads/components-icons/badges/summer-2024/EmailTracking_HighPerformer_Americas_HighPerformer.svg)](https://www.g2.com/products/elastic-email/reviews?utm_source=rewards-badge)[![Image 26: Elastic Email is a leader in Email Marketing in EMEA on G2](https://cms.elasticemail.com/wp-content/uploads/components-icons/badges/summer-2024/EmailMarketing_HighPerformer_EMEA_HighPerformer.svg)](https://www.g2.com/products/elastic-email/reviews?utm_source=rewards-badge)[![Image 27: Elastic Email is a leader in Mid-Market on G2](https://cms.elasticemail.com/wp-content/uploads/components-icons/badges/summer-2024/EmailTracking_EasiestToDoBusinessWith_Mid-Market_EaseOfDoingBusinessWith.svg)](https://www.g2.com/products/elastic-email/reviews?utm_source=rewards-badge)[![Image 28: Elastic Email is a leader in Transactional Email, and Email Marketing and Tracking on G2](https://cms.elasticemail.com/wp-content/uploads/components-icons/badges/summer-2024/EmailTracking_HighPerformer_HighPerformer.svg)](https://www.g2.com/products/elastic-email/reviews?utm_source=rewards-badge)[![Image 29: Elastic Email is a leader in Mid-Market Transactional Email on G2](https://cms.elasticemail.com/wp-content/uploads/components-icons/badges/summer-2024/TransactionalEmail_BestEstimatedROI_Mid-Market_Roi.svg)](https://www.g2.com/products/elastic-email/reviews?utm_source=rewards-badge)[![Image 30: Elastic Email is a leader in Mid-Market Transactional Email on G2](https://cms.elasticemail.com/wp-content/uploads/components-icons/badges/summer-2024/TransactionalEmail_EasiestSetup_Mid-Market_EaseOfSetup.svg)](https://www.g2.com/products/elastic-email/reviews?utm_source=rewards-badge)[![Image 31: Users Love Elastic Email on G2](https://cms.elasticemail.com/wp-content/uploads/components-icons/badges/summer-2024/users-love-us-summer-2024.svg)](https://www.g2.com/products/elastic-email/reviews?utm_source=rewards-badge)\n\nFrequently Asked Questions\n--------------------------\n\nHow does Email Marketing pricing work? In detail!\n\n\n-----------------------------------------------------\n\n* * *\n\nI would like to try Elastic Email. How do I get started?\n\n\n------------------------------------------------------------\n\n* * *\n\nDo I need a credit card to register?\n\n\n----------------------------------------\n\n* * *\n\nWhat if I reach the limits of my plan?\n\n\n------------------------------------------\n\n* * *\n\nHow can I upgrade or downgrade?\n\n\n-----------------------------------\n\n* * *\n\nCan I use your other products while using your Email Marketing product?\n\n\n---------------------------------------------------------------------------\n\n* * *\n\nWhat payment types are accepted?\n\n\n------------------------------------\n\n* * *\n\nAre all stored contacts counted into my pricing plan?\n\n\n---------------------------------------------------------\n\n* * *\n\nHow does your customer support work? Do I have to pay extra?\n\n\n----------------------------------------------------------------\n\n* * *\n\nDo you offer onboarding help or delivery consulting?\n\n\n--------------------------------------------------------\n\n* * *\n\nIs there a way to compare or discuss your plans?\n\n\n----------------------------------------------------\n\n* * *\n\nDo you have a solution for high-volume senders? Do you offer custom/enterprise plans?\n\n\n-----------------------------------------------------------------------------------------\n\n### Ready to try Elastic Email for your business?\n\nSay goodbye to outdated email delivery tools and embrace our fresh and modern service.\n\n[Start Now](https://elasticemail.com/select-product)Instant setup. No credit card required.\n\nProduct\n\n[Email Marketing](https://elasticemail.com/marketing-features)[Email API](https://elasticemail.com/email-api)[Creator Suite](https://elasticemail.com/creator-suite)[Email Marketing Pricing](https://elasticemail.com/email-marketing-pricing)[Email API Pricing](https://elasticemail.com/email-api-pricing)[Creator Suite Pricing](https://elasticemail.com/creator-suite-pricing)[Email Verification](https://elasticemail.com/email-verification)[Integrations](https://elasticemail.com/integrations)\n\nResources\n\n[Getting Started](https://elasticemail.com/getting-started)[Help Center](https://help.elasticemail.com/)[Blog](https://elasticemail.com/blog)[Video Tutorials](https://youtube.com/@elasticemail)[Case Studies](https://elasticemail.com/blog?cat=case_studies)\n\nDevelopers\n\n[REST API Docs](https://elasticemail.com/developers/api-documentation/rest-api)[WEB API Docs (Legacy)](https://elasticemail.com/developers/api-documentation/web-api-v2)[API Libraries](https://elasticemail.com/developers/api-libraries)[Status](https://status.elasticemail.com/)\n\nCompany\n\n[About](https://elasticemail.com/about)[Careers We\u2019re hiring](https://elasticemail.com/careers)[Brand Assets](https://elasticemail.com/brand-assets)[Referral Program](https://elasticemail.com/referral-program)[Privacy & Terms](https://elasticemail.com/resources/usage-policies)[Sitemap](https://elasticemail.com/sitemap_index.xml)\n\nContact\n\n[Contact](https://elasticemail.com/contact)[Partnership](https://elasticemail.com/partnership)[Report Spam](https://elasticemail.com/report-spam)\n\n\u00a9 Elastic Email Inc. 2025\n\n[Facebook link](https://facebook.com/ElasticEmail)[X.com link](https://twitter.com/Elastic_Email)[YouTube link](https://youtube.com/@elasticemail)[LinkedIn link](https://linkedin.com/company/elastic-email)[Instagram link](https://instagram.com/elastic_email/)\n\nCheck our email marketing pricing plans and choose the right one for you. Send engaging email campaigns and get extra features. Find out more!",
      "error": null,
      "pricing_data": {
        "app_id": "elastic_email",
        "app_name": "Elastic Email",
        "app_slug": "elastic-email",
        "pricing_url": "https://elasticemail.com/pricing",
        "source_url": "https://elasticemail.com/pricing",
        "all_pricing_urls": [
          "https://elasticemail.com/pricing"
        ],
        "price_model_type": [
          "PriceModelType.SUBSCRIPTION",
          "PriceModelType.FREE_TIER"
        ],
        "has_free_tier": true,
        "has_free_trial": false,
        "free_trial_period_days": null,
        "currency": "USD",
        "is_pricing_public": true,
        "pricing_page_accessible": true,
        "pricing_notes": "Pricing is based on the number of contacts and includes a free tier for limited sending.",
        "pricing_tiers": [
          {
            "tier_name": "Free",
            "tier_description": "Test crucial features with limited sending.",
            "monthly_price": 0.0,
            "annual_price": null,
            "annual_discount_percentage": null,
            "setup_fee": null,
            "features": [
              "Limited sending"
            ],
            "limits": {
              "users": "unlimited",
              "storage": null,
              "operations": null,
              "api_calls": null,
              "integrations": null,
              "custom_limits": [
                {
                  "name": "Contacts",
                  "value": 2500
                }
              ]
            }
          },
          {
            "tier_name": "Starter",
            "tier_description": "For up to 2,500 contacts and up to 37,500 emails/month.",
            "monthly_price": 29.0,
            "annual_price": null,
            "annual_discount_percentage": null,
            "setup_fee": null,
            "features": [
              "Access to Email Delivery Engine",
              "Email Designer",
              "Campaign Creator",
              "Landing Page Editor",
              "Web Forms",
              "Single & Bulk Email Verification",
              "Segmentation",
              "Analytics",
              "Customer Support"
            ],
            "limits": {
              "users": "unlimited",
              "storage": null,
              "operations": 37500,
              "api_calls": null,
              "integrations": null,
              "custom_limits": [
                {
                  "name": "Contacts",
                  "value": 2500
                }
              ]
            }
          },
          {
            "tier_name": "Pro",
            "tier_description": "For up to 2,500 contacts and up to 37,500 emails/month.",
            "monthly_price": 49.0,
            "annual_price": null,
            "annual_discount_percentage": null,
            "setup_fee": null,
            "features": [
              "All features from Starter plan",
              "Email Automations",
              "Faster Delivery Speed",
              "Unlimited Custom Fields",
              "Custom rDNS",
              "Webhooks",
              "Sub Accounts",
              "User Management",
              "Reseller Features",
              "Form with reCAPTCHA"
            ],
            "limits": {
              "users": "unlimited",
              "storage": null,
              "operations": 37500,
              "api_calls": null,
              "integrations": null,
              "custom_limits": [
                {
                  "name": "Contacts",
                  "value": 2500
                }
              ]
            }
          }
        ],
        "usage_based_pricing": null,
        "ai_specific_pricing": null,
        "promotional_offers": null,
        "additional_fees": [
          {
            "fee_name": "Private IP",
            "fee_amount": 40.0,
            "fee_description": "Monthly fee for a private IP in the Starter plan."
          },
          {
            "fee_name": "Private IP",
            "fee_amount": 50.0,
            "fee_description": "Monthly fee for a private IP in the Pro plan."
          }
        ],
        "extraction_timestamp": "2025-04-15T06:09:56.943075",
        "schema_validated": true,
        "confidence_score": 95,
        "extraction_error": false,
        "json_repaired": false
      },
      "pricing_analyzed": true
    }
  ],
  "results_directory": "pricing_results\\elasticemail\\20250415_060957"
}