{
  "app_name": "Vtiger CRM",
  "app_slug": "vtiger",
  "search_term": "Find the official pricing page URL for Vtiger CRM (vtiger.com). Only provide the exact URL to the pricing page, not a summary of pricing information.",
  "timestamp": 1744696260.1731176,
  "response_text": [
    "The official pricing page URL for Vtiger CRM is: [https://www.vtiger.com/pricing/](https://www.vtiger.com/pricing/)\u30103:0\u2020source\u3011."
  ],
  "citations": [
    {
      "title": "Vtiger CRM Pricing - Try it for free!",
      "url": "https://www.vtiger.com/pricing/"
    }
  ],
  "extracted_content": [
    {
      "url": "https://www.vtiger.com/pricing/",
      "is_accessible": true,
      "content": "**Key Features**\n\n**< Drag sideways to see more\\>**\n\nONE PILOT\n\nFree plan - ideal for companies getting started on their CRM journey\n\nUS$5 US$0\n\nper user\n\nMax users - 10\n\nMax records - 3000\n\n##### Lead & Contact Management\n\nLeads, Contacts and Organizations\n\nOne View\n\nIdle Alerts\n\nDuplicate Prevention\n\nProfile Scoring\n\n##### Contact Engagement\n\nEmails & Phone Integration\n\nDocument Engagement\n\nZoom & Google Meet\n\n##### Internal Collaboration\n\nDirect messages, Comments and @Mentions\n\nCalendar Notifications\n\nMeeting Aide in Vtiger Buzz\n\nActions Page\n\nComments\n\n##### Marketing Automation\n\nLists and Segments\n\nEmail Campaigns\n\n1000 Emails/month\n\nEmail Campaign Reports\n\nAutoresponders\n\nConsents for compliance\n\nWeb to Lead Forms\n\nEmail Template Builder\n\nList Reports\n\nLanding Pages\n\nShort URLs\n\nFacebook Leads Ads and Google Leads Form Extension integration\n\n##### Project Management\n\nTasks & Milestones\n\nSubtasks\n\nGantt View\n\nKanban Board\n\n##### Sales Pipeline\n\nDeals and Contact Roles\n\nCustomize Sales Stages\n\nDeal Kanban View\n\nIdle Deal Alerts\n\nTime Spent in every Stage\n\n##### Sales Enablement\n\nEmail Sequences\n\nGoogle + O365 Add-ins\n\nEnrich LinkedIn Extension\n\nAppointment Pages\n\nWorkflows\n\n##### Help Desk\n\nEmail to Case\n\nFirst Response SLA\n\nResolution SLA\n\nBusiness Hours\n\n##### Mobile App\n\nReal-time Notifications\n\nActions Page\n\nBusiness Card Scanner\n\nLeads, Contacts, Deals, Quotes, Cases\n\nVoice Notes\n\n##### Storage\n\n3 GB\n\nONE GROWTH\n\nA CRM for small and medium-sized businesses\n\nMax users - 15\n\nMax records - 100,000\n\nEverything in  \n**One Pilot** plus:\n\n##### Lead Management\n\nLead Auto-assignment & Routing\n\n##### Action Center\n\nEmail tracking & real time notifications\n\n##### Salesforce Automation\n\nMultiple pipelines\n\nDeal Playbooks\n\n##### Marketing Automation\n\nCampaigns\n\n5000 Emails/month or 500 Emails/user\n\n##### Help desk\n\nOrganization matching with Email domain\n\nAgent level business hours\n\nCase satisfaction survey\n\nArticles & FAQs\n\nCustomer Portal\n\n##### Inventory Management\n\nInvoicing\n\nSales Order\n\n##### Reports & Analytics\n\nCustomizable dashboards\n\nCustom schedule reports\n\n##### Automation\n\nOpportunity creation from Email\n\nOrganization creation from Email\n\nPOPULAR\n\nONE PROFESSIONAL\n\nPowered by AI\n\nA complete CRM that gets all your teams on the same page with Customer One View.\n\nEverything in  \n**One Growth** plus:\n\n##### Salesforce Automation\n\nMultiple Pipelines\n\nProfile & Engagement Scoring\n\nLead Scoring\n\nSales Forecasting\n\nSales Quotas\n\nDeal Room\n\nCPQ (Configure, Price, Quote)\n\n##### AI\n\nPredictive AI\n\nGenerative AI\n\nNatural Language Querying\n\nChatbot\n\nPrompt Builder\n\nQuery Analytics\n\nGenerative AI Designer\n\nPrediction AI Designer\n\n##### Marketing Automation\n\n20,000 Emails/month or 2000 Emails/user\n\nUnlimited Custom Email Templates\n\nImage Storage\n\nAutoresponder Email Campaigns\n\nScheduled Email Campaigns\n\n##### Help Desk\n\nSocial Ticketing\n\nRound Robin Ticket Assignment\n\nLeast Loaded Ticket Assignment\n\nAgent Level Business Hours\n\nService Contracts\n\n##### Conversations\n\nInternal Team Collaboration\n\nLive Web Chat\n\n##### Dashboards\n\nSales Insights\n\nSupport Insights\n\nCustomizable Reports & Dashboards\n\n##### Inventory Management\n\nInvoicing\n\nVendor Management\n\nPurchase Order Management\n\nSubscriptions\n\nPayment Tracking\n\nSales Order\n\nAssets\n\n##### Project Management\n\nTask dependencies (Finish to Start)\n\nAutomated task end times (User business hours)\n\n##### LMS Portal\n\nCourses\n\nConcepts\n\nExercises\n\nQuiz\n\nQuestions\n\n##### Process Designer\n\nBusiness Process Automation\n\nRules, Conditions, and Actions\n\nWorkflows and Approvals\n\nFlowcharts\n\nTasks\n\nONE ENTERPRISE\n\nPowered by AI\n\nFully loaded enterprise grade CRM that gives you best-in-class features for a fraction of the cost of comparable options\n\nEverything in  \n**One Professional** plus:\n\n##### Contact Engagement\n\nBest Time to Contact\n\n##### Salesforce Automation\n\nMulti Currencies\n\n##### Internal Ticketing\n\nInternal Ticketing system for employees\n\nInternal ticket Insights\n\n##### Help Desk\n\nWork order management\n\n##### Project Management\n\nAutomated Time Tracking and Billing\n\nProject key metrics and analytics\n\nProject Templates\n\nNEW\n\nONE AI\n\nPowered by AI\n\nEnterprise-grade CRM with predictive and generative AI features for maximizing AI potential\n\nEverything in  \n**One Enterprise** plus:\n\n##### BUILT-IN AI\n\nPredictive AI\n\nGenerative AI\n\nNatural Language Querying\n\nVoice Assistants Integration\n\nChatbot\n\nPrompt Builder\n\nQuery Analytics\n\nGenerative AI Designer\n\nPrediction AI Designer\n\n**Booster Packs**\n\n### Customize your CRM edition with additional features\n\nAre feature limits holding you back? Use Vtiger Booster Packs add-ons and increase the limits of specific features without upgrading the plan. Pick what feature you want. Pay for the feature you use.\n\n**1-Week implementation Challenge**\n\nCRM Implementation made simple with commitment\n----------------------------------------------\n\nJoin us to launch your CRM in just one week. With our expertise and Vtiger's easy setup, we'll quickly connect you to your prospects.\n\n### Frequently Asked Questions\n\n[**What\u2019s the difference between Standard User and Single App User?**](https://www.vtiger.com/pricing/#f_q)Standard users have full access to five apps (Marketing, Sales, Help Desk, Projects and Inventory) and all modules. Single App users have complete access to one of the five apps (Marketing, Sales, Help Desk, Projects and Inventory) and read-only access to records in the other four apps.\n\n[**Can I get a demo of Vtiger CRM?**](https://www.vtiger.com/pricing/#s_q)Yes, you can request a no-obligation demo of the latest cloud version of Vtiger CRM [from here](https://vtigerecs.od1.vtiger.com/appointments/meetwithus). Our experts will walk you through product capabilities and show how you can configure Vtiger to achieve your business goals.\n\n[**Can I switch plans?**](https://www.vtiger.com/pricing/#t_q)You can change your existing plan at any point in time. You can either upgrade or downgrade the plan based on your necessity.\n\n[**Have more questions?**](https://www.vtiger.com/pricing/#four_q)You can connect with us instantly through live chat (24x7) or by reaching to us at [\\[email protected\\]](https://www.vtiger.com/cdn-cgi/l/email-protection)\n\nNot sure which plan to choose?\n\nONE GROWTH\n\nA CRM for small and medium-sized businesses\n\nMax users - 15\n\nMax records - 100,000\n\nEverything in  \n**One Pilot** plus:\n\n##### Lead Management\n\nLead Auto-assignment & Routing\n\n##### Action Center\n\nEmail tracking & real time notifications\n\n##### Salesforce Automation\n\nMultiple pipelines\n\nDeal Playbooks\n\n##### Marketing Automation\n\nCampaigns\n\n5000 Emails/month or 500 Emails/user\n\n##### Help desk\n\nOrganization matching with Email domain\n\nAgent level business hours\n\nCase satisfaction survey\n\nArticles & FAQs\n\nCustomer Portal\n\n##### Inventory Management\n\nInvoicing\n\nSales Order\n\n##### Reports & Analytics\n\nCustomizable dashboards\n\nCustom schedule reports\n\n##### Automation\n\nOpportunity creation from Email\n\nOrganization creation from Email\n\nONE ENTERPRISE\n\nPowered by AI\n\nFully loaded enterprise grade CRM that gives you best-in-class features for a fraction of the cost of comparable options\n\nEverything in  \n**One Professional** plus:\n\n##### Contact Engagement\n\nBest Time to Contact\n\n##### Salesforce Automation\n\nMulti Currencies\n\n##### Internal Ticketing\n\nInternal Ticketing system for employees\n\nInternal ticket Insights\n\n##### Help Desk\n\nWork order management\n\n##### Project Management\n\nAutomated Time Tracking and Billing\n\nProject key metrics and analytics\n\nProject Templates\n\nPOPULAR\n\nONE PROFESSIONAL\n\nPowered by AI\n\nA complete CRM that gets all your teams on the same page with Customer One View.\n\nEverything in  \n**One Growth** plus:\n\n##### Salesforce Automation\n\nMultiple Pipelines\n\nProfile & Engagement Scoring\n\nLead Scoring\n\nSales Forecasting\n\nSales Quotas\n\nDeal Room\n\nCPQ (Configure, Price, Quote)\n\n##### AI\n\nPredictive AI\n\nGenerative AI\n\nNatural Language Querying\n\nAI Prompt Builder\n\nAI Query Analytics\n\nAI Chatbot\n\nAI Bot Management\n\n##### Marketing Automation\n\n20,000 Emails/month or 2000 Emails/user\n\nUnlimited Custom Email Templates\n\nImage Storage\n\nAutoresponder Email Campaigns\n\nScheduled Email Campaigns\n\n##### Help Desk\n\nSocial Ticketing\n\nRound Robin Ticket Assignment\n\nLeast Loaded Ticket Assignment\n\nAgent Level Business Hours\n\nService Contracts\n\n##### Conversations\n\nInternal Team Collaboration\n\nLive Web Chat\n\n##### Dashboards\n\nSales Insights\n\nSupport Insights\n\nCustomizable Reports & Dashboards\n\n##### Inventory Management\n\nInvoicing\n\nVendor Management\n\nPurchase Order Management\n\nSubscriptions\n\nPayment Tracking\n\nSales Order\n\nAssets\n\n##### Project Management\n\nTask dependencies (Finish to Start)\n\nAutomated task end times (User business hours)\n\n##### LMS Portals\n\nCourses\n\nConcepts\n\nExercises\n\nQuiz\n\nQuestions\n\n##### Process Designer\n\nBusiness Process Automation\n\nRules, Conditions, and Actions\n\nWorkflows and Approvals\n\nFlowcharts\n\nTasks\n\nNEW\n\nONE AI\n\nPowered by AI\n\nEnterprise-grade CRM with predictive and generative AI features for maximizing AI potential\n\nEverything in  \n**One Enterprise** plus:\n\n##### Built-IN AI\n\nPredictive AI\n\nGenerative AI\n\nNatural Language Querying\n\nVoice Assistants Integration\n\nAI Prompt Builder\n\nAI Query Analytics\n\nAI Chatbot\n\nAI Bot Management\n\nOne PILOT\n\nFree plan - ideal for companies getting started on their CRM journey\n\nUS$ 5 US$0\n\nper user\n\nMax users - 10\n\nMax records - 3000\n\n##### Lead & Contact Management\n\nLeads, Contacts and Organizations\n\nOne View\n\nIdle Alerts\n\nDuplicate Prevention\n\nProfile Scoring\n\n##### Contact Engagement\n\nEmails & Phone Integration\n\nDocument Engagement\n\nZoom & Google Meet\n\n##### Internal Collaboration\n\nDirect messages, Comments and @Mentions\n\nCalendar Notifications\n\nMeeting Aide in Vtiger Buzz\n\nDirect messages\n\nCalendar Notifications\n\nActions Page\n\nComments\n\n##### Marketing Automation\n\nLists and Segments\n\nEmail Campaigns\n\n1000 Emails/month\n\nEmail Campaign Reports\n\nAutoresponders\n\nConsents for compliance\n\nWeb to Lead Forms\n\nEmail Template Builder\n\nList Reports\n\nLanding Pages\n\nShort URLs\n\nFacebook Leads Ads and Google Leads Form Extension integration\n\n##### Project Management\n\nTasks & Milestones\n\nSubtasks\n\nGantt View\n\nKanban Board\n\n##### Sales Pipeline\n\nDeals and Contact Roles\n\nCustomize Sales Stages\n\nDeal Kanban View\n\nIdle Deal Alerts\n\nTime Spent in every Stage\n\n##### Sales Enablement\n\nEmail Sequences\n\nGoogle + O365 Add-ins\n\nEnrich LinkedIn Extension\n\nAppointment Pages\n\nWorkflows\n\n##### Help Desk\n\nEmail to Case\n\nFirst Response SLA\n\nResolution SLA\n\nBusiness Hours\n\n##### Mobile App\n\nReal-time Notifications\n\nActions Page\n\nBusiness Card Scanner\n\nLeads, Contacts, Deals, Quotes, Cases\n\nVoice Notes\n\n##### Storage\n\n3 GB\n\n**Booster Packs**\n\n### Customize your CRM edition with additional features\n\nAre feature limits holding you back? Use Vtiger Booster Packs add-ons and increase the limits of specific features without upgrading the plan. Pick what feature you want. Pay for the feature you use.\n\n**1-Week implementation Challenge**\n\nCRM Implementation made simple with commitment\n----------------------------------------------\n\nJoin us to launch your CRM in just one week. With our expertise and Vtiger's easy setup, we'll quickly connect you to your prospects.\n\n### Frequently Asked Questions\n\n[**What\u2019s the difference between Standard User and Single App User?**](https://www.vtiger.com/pricing/#f_q)Standard users have full access to five apps (Marketing, Sales, Help Desk, Projects and Inventory) and all modules. Single App users have complete access to one of the five apps (Marketing, Sales, Help Desk, Projects and Inventory) and read-only access to records in the other four apps.\n\n[**Can I get a demo of Vtiger CRM?**](https://www.vtiger.com/pricing/#s_q)Yes, you can request a no-obligation demo of the latest cloud version of Vtiger CRM [from here](https://vtigerecs.od1.vtiger.com/appointments/meetwithus). Our experts will walk you through product capabilities and show how you can configure Vtiger to achieve your business goals.\n\n[**Can I switch plans?**](https://www.vtiger.com/pricing/#t_q)You can change your existing plan at any point in time. You can either upgrade or downgrade the plan based on your necessity.\n\n[**Have more questions?**](https://www.vtiger.com/pricing/#four_q)You can connect with us instantly through live chat (24x7) or by reaching to us at [\\[email protected\\]](https://www.vtiger.com/cdn-cgi/l/email-protection)\n\nNot sure which plan to choose?\n\nChoose the Vtiger pricing plan that's right for your business. Get started with the Free Forever edition or 15 days free trial.",
      "error": null,
      "pricing_data": {
        "app_id": "vtiger_crm",
        "app_name": "Vtiger CRM",
        "app_slug": "vtiger-crm",
        "pricing_url": "https://www.vtiger.com/pricing/",
        "source_url": "https://www.vtiger.com/pricing/",
        "all_pricing_urls": [
          "https://www.vtiger.com/pricing/"
        ],
        "price_model_type": [
          "PriceModelType.SUBSCRIPTION",
          "PriceModelType.FREE_TIER",
          "PriceModelType.USAGE_BASED"
        ],
        "has_free_tier": true,
        "has_free_trial": true,
        "free_trial_period_days": 15,
        "currency": "USD",
        "is_pricing_public": true,
        "pricing_page_accessible": true,
        "pricing_notes": "Vtiger CRM offers a free tier and booster packs for additional features.",
        "pricing_tiers": [
          {
            "tier_name": "One Pilot",
            "tier_description": "Free plan - ideal for companies getting started on their CRM journey",
            "monthly_price": 0.0,
            "annual_price": 0.0,
            "annual_discount_percentage": null,
            "setup_fee": null,
            "features": [
              "Lead & Contact Management",
              "Contact Engagement",
              "Internal Collaboration",
              "Marketing Automation",
              "Project Management",
              "Sales Pipeline",
              "Sales Enablement",
              "Help Desk",
              "Mobile App",
              "Storage"
            ],
            "limits": {
              "users": 10,
              "storage": "3GB",
              "operations": null,
              "api_calls": null,
              "integrations": null,
              "custom_limits": [
                {
                  "name": "Max records",
                  "value": 3000
                }
              ]
            }
          },
          {
            "tier_name": "One Growth",
            "tier_description": "A CRM for small and medium-sized businesses",
            "monthly_price": null,
            "annual_price": null,
            "annual_discount_percentage": null,
            "setup_fee": null,
            "features": [
              "Lead Management",
              "Action Center",
              "Salesforce Automation",
              "Marketing Automation",
              "Help Desk",
              "Inventory Management",
              "Reports & Analytics",
              "Automation"
            ],
            "limits": {
              "users": 15,
              "storage": null,
              "operations": null,
              "api_calls": null,
              "integrations": null,
              "custom_limits": [
                {
                  "name": "Max records",
                  "value": 100000
                }
              ]
            }
          },
          {
            "tier_name": "One Professional",
            "tier_description": "Powered by AI",
            "monthly_price": null,
            "annual_price": null,
            "annual_discount_percentage": null,
            "setup_fee": null,
            "features": [
              "Salesforce Automation",
              "AI",
              "Marketing Automation",
              "Help Desk",
              "Conversations",
              "Dashboards",
              "Inventory Management",
              "Project Management",
              "LMS Portal",
              "Process Designer"
            ],
            "limits": {
              "users": "unlimited",
              "storage": "unlimited",
              "operations": null,
              "api_calls": null,
              "integrations": null,
              "custom_limits": null
            }
          },
          {
            "tier_name": "One Enterprise",
            "tier_description": "Powered by AI",
            "monthly_price": null,
            "annual_price": null,
            "annual_discount_percentage": null,
            "setup_fee": null,
            "features": [
              "Contact Engagement",
              "Salesforce Automation",
              "Internal Ticketing",
              "Help Desk",
              "Project Management"
            ],
            "limits": {
              "users": "unlimited",
              "storage": "unlimited",
              "operations": null,
              "api_calls": null,
              "integrations": null,
              "custom_limits": null
            }
          },
          {
            "tier_name": "One AI",
            "tier_description": "Powered by AI",
            "monthly_price": null,
            "annual_price": null,
            "annual_discount_percentage": null,
            "setup_fee": null,
            "features": [
              "Built-in AI"
            ],
            "limits": {
              "users": "unlimited",
              "storage": "unlimited",
              "operations": null,
              "api_calls": null,
              "integrations": null,
              "custom_limits": null
            }
          }
        ],
        "usage_based_pricing": [
          {
            "metric_name": "Emails",
            "unit": "per email",
            "base_price": null,
            "tiers": [
              {
                "min": 0.0,
                "max": 1000.0,
                "price": null
              },
              {
                "min": 1001.0,
                "max": 5000.0,
                "price": null
              },
              {
                "min": 5001.0,
                "max": 20000.0,
                "price": null
              }
            ]
          }
        ],
        "ai_specific_pricing": {
          "has_token_based_pricing": false,
          "input_token_price": null,
          "output_token_price": null,
          "models_pricing": null,
          "has_inference_pricing": false,
          "has_fine_tuning_pricing": false,
          "has_training_pricing": false,
          "ai_addon_available": true
        },
        "promotional_offers": null,
        "additional_fees": [
          {
            "fee_name": "Booster Packs",
            "fee_amount": null,
            "fee_description": "Add-ons to increase feature limits without upgrading the plan"
          }
        ],
        "extraction_timestamp": "2025-04-15T01:51:11.002645",
        "schema_validated": true,
        "confidence_score": 95,
        "extraction_error": false,
        "json_repaired": false
      },
      "pricing_analyzed": true
    }
  ],
  "results_directory": "pricing_results\\vtiger\\20250415_015111"
}