{
  "app_name": "Google Slides",
  "app_slug": "google-slides",
  "search_term": "Find the official pricing page URL for Google Slides (google-slides.com). Only provide the exact URL to the pricing page, not a summary of pricing information.",
  "timestamp": 1744701602.9789371,
  "response_text": [
    "The official pricing page for Google Slides is part of Google Workspace and can be found at: [https://workspace.google.com/pricing.html](https://workspace.google.com/pricing.html)\u30103:1\u2020source\u3011."
  ],
  "citations": [
    {
      "title": "Compare Flexible Pricing Plan Options | Google Workspace",
      "url": "https://workspace.google.com/pricing"
    }
  ],
  "extracted_content": [
    {
      "url": "https://workspace.google.com/pricing",
      "is_accessible": true,
      "content": "closemenu\n\n\n\n\nSolutions\n\nProducts\n\nIndustries\n\nAI\n\nPricing\n\nResources\n\n\nAdmin console\n\nContact sales\n\nStart a trial\n\n\n\nSolutions\n\nProducts\n\nIndustries\n\nAI\n\nPricing\n\nResources\n\n\n\n\n\n\nTry Google Workspace for 14 days.\n\n\n\nBusiness Starter\n\n$7 USD\n$7\nper user / month, 1 year commitment\n\n\ninfo_outline\n\n\nOr $8.40 per user / month, when billed monthly\n\n\n\n\n\nStart a trial\n\n30 GB\n pooled storage per user*\nSecure custom business email, you@your-company.com\n\n\nGet started with AI\nGemini AI assistant in Gmail\nChat with AI in the Gemini app\n100 participant video meetings\nSecurity and management controls\nStandard Support\n\nmost popular\n\nBusiness Standard\n\n$14 USD\n$14\nper user / month, 1 year commitment\n\n\ninfo_outline\n\n\nOr $16.80 per user / month, when billed monthly\n\n\n\n\n\nStart a trial\n\n2 TB\n pooled storage per user*\nSecure custom business email, you@your-company.com\n\n\nUnlock the full power of AI\nGemini AI assistant in Gmail, Docs, Meet, and more\nChat with AI in the Gemini app + create your team of AI experts\nAI research assistant (NotebookLM Plus)\n150 participant video meetings + recording, noise cancellation\neSignature with Docs and PDFs\nAppointment booking pages\nCollaborative video creator + editor\nEmail layouts and mail merge\nSecurity and management controls\nStandard Support**\n\n\nBusiness Plus\n\n$22 USD\n$22\nper user / month, 1 year commitment\n\n\ninfo_outline\n\n\nOr $26.40 per user / month, when billed monthly\n\n\n\n\n\nStart a trial\n\n5 TB\n pooled storage per user*\nSecure custom business email, eDiscovery, retention\n\n\nUnlock the full power of AI\nGemini AI assistant in Gmail, Docs, Meet, and more\nChat with AI in the Gemini app + create your team of AI experts\nAI research assistant (NotebookLM Plus)\n500 participant video meetings + recording, attendance tracking, noise cancellation\neSignature with Docs and PDFs\nAppointment booking pages\nCollaborative video creator + editor\nEmail layouts and mail merge\nEnhanced security and management controls, including Vault and advanced endpoint management\nStandard Support**\n\n\nEnterprise\n\nContact sales for pricing\n\n\n\n\n\nContact sales\n\n5 TB\n pooled storage per user*\nSecure custom business email, eDiscovery, retention\n\n\nUnlock the full power of AI\nGemini AI assistant in Gmail, Docs, Meet, and more\nChat with AI in the Gemini app + create your team of AI experts\nAI research assistant (NotebookLM Plus)\n1000 participant video meetings + recording, attendance tracking, noise cancellation, in-domain live streaming\neSignature with Docs and PDFs\nAppointment booking pages\nCollaborative video creator + editor\nEmail layouts and mail merge\nAdvanced security, management, and compliance controls, including Vault, DLP, data regions, and enterprise endpoint management\nEnhanced Support**\n\n\n\n\n\nBusiness Starter\nBusiness Standard\nBusiness Plus\nEnterprise\n\n\n\n\nBusiness Starter\n\n$7 USD\n$7\nper user / month, 1 year commitment\n\n\ninfo_outline\n\n\nOr $8.40 per user / month, when billed monthly\n\n\n\n\n\nStart a trial\n\n30 GB\n pooled storage per user*\nSecure custom business email, you@your-company.com\n\n\nGet started with AI\nGemini AI assistant in Gmail\nChat with AI in the Gemini app\n100 participant video meetings\nSecurity and management controls\nStandard Support\n\n\n\nmost popular\n\nBusiness Standard\n\n$14 USD\n$14\nper user / month, 1 year commitment\n\n\ninfo_outline\n\n\nOr $16.80 per user / month, when billed monthly\n\n\n\n\n\nStart a trial\n\n2 TB\n pooled storage per user*\nSecure custom business email, you@your-company.com\n\n\nUnlock the full power of AI\nGemini AI assistant in Gmail, Docs, Meet, and more\nChat with AI in the Gemini app + create your team of AI experts\nAI research assistant (NotebookLM Plus)\n150 participant video meetings + recording, noise cancellation\neSignature with Docs and PDFs\nAppointment booking pages\nCollaborative video creator + editor\nEmail layouts and mail merge\nSecurity and management controls\nStandard Support**\n\n\n\n\nBusiness Plus\n\n$22 USD\n$22\nper user / month, 1 year commitment\n\n\ninfo_outline\n\n\nOr $26.40 per user / month, when billed monthly\n\n\n\n\n\nStart a trial\n\n5 TB\n pooled storage per user*\nSecure custom business email, eDiscovery, retention\n\n\nUnlock the full power of AI\nGemini AI assistant in Gmail, Docs, Meet, and more\nChat with AI in the Gemini app + create your team of AI experts\nAI research assistant (NotebookLM Plus)\n500 participant video meetings + recording, attendance tracking, noise cancellation\neSignature with Docs and PDFs\nAppointment booking pages\nCollaborative video creator + editor\nEmail layouts and mail merge\nEnhanced security and management controls, including Vault and advanced endpoint management\nStandard Support**\n\n\n\n\nEnterprise\n\nContact sales for pricing\n\n\n\n\n\nContact sales\n\n5 TB\n pooled storage per user*\nSecure custom business email, eDiscovery, retention\n\n\nUnlock the full power of AI\nGemini AI assistant in Gmail, Docs, Meet, and more\nChat with AI in the Gemini app + create your team of AI experts\nAI research assistant (NotebookLM Plus)\n1000 participant video meetings + recording, attendance tracking, noise cancellation, in-domain live streaming\neSignature with Docs and PDFs\nAppointment booking pages\nCollaborative video creator + editor\nEmail layouts and mail merge\nAdvanced security, management, and compliance controls, including Vault, DLP, data regions, and enterprise endpoint management\nEnhanced Support**\n\nBusiness Starter, Business Standard, and Business Plus plans can be purchased for a maximum of 300 users. There is no minimum or maximum user limit for Enterprise plans.\nGoogle Workspace customers may have access to additional features for a limited promotional period.\n\nGoogle Workspace provides flexible pooled storage per user that is shared across the organization. Visit our Help Center to learn more about getting additional storage for your organization.\nPaid upgrade available from Standard to Enhanced Support, or from Enhanced to Premium Support on Enterprise plansCompare plans in detail\narrow_downward\n\n\n\nGmail\n\nDrive\n\nMeet\n\nCalendar\n\nChat\n\nGemini app\n\nDocs\n\nSheets\n\nSlides\n\nVids\n\nKeep\n\nSites\n\nForms\n\nNotebookLM\n\nAppSheet\n\n\n\nStart a trialarrow_forward_ios\nBusiness Starter\n\nBusiness Starter\n\n\n\n\nStart a trial\nmost popular\nBusiness Standard\n\nBusiness Standard\n\n\n\n\nStart a trial\nBusiness Plus\n\nBusiness Plus\n\n\n\n\nStart a trial\nEnterprise\n\nEnterprise\n\n\n\n\nContact sales\n\n\nProductivity & Collaboration\n\n\n\nGmail \nBusiness emailThis feature is available for the SKUdoneThis feature is available for the SKUdoneThis feature is available for the SKUdoneThis feature is available for the SKUdone\n\n\nCustom email for your businessThis feature is available for the SKUdoneThis feature is available for the SKUdoneThis feature is available for the SKUdoneThis feature is available for the SKUdone\n\n\nPhishing and spam protection that blocks more than 99.9% of attacksThis feature is available for the SKUdoneThis feature is available for the SKUdoneThis feature is available for the SKUdoneThis feature is available for the SKUdone\n\n\nAd-free email experienceThis feature is available for the SKUdoneThis feature is available for the SKUdoneThis feature is available for the SKUdoneThis feature is available for the SKUdone\n\n\nGemini in Workspace apps\nLimitedThis feature is available for the SKUdoneThis feature is available for the SKUdoneThis feature is available for the SKUdone\n\n\nEnterprise-grade security and privacyThis feature is available for the SKUdoneThis feature is available for the SKUdoneThis feature is available for the SKUdoneThis feature is available for the SKUdone\n\n\nGemini in Gmail - find, summarize, and write emails faster with AIThis feature is available for the SKUdoneThis feature is available for the SKUdoneThis feature is available for the SKUdoneThis feature is available for the SKUdone\n\n\nGemini in Docs - tackle the blank page or polish draft documents with AIThis feature is not supported by this SKUhorizontal_ruleThis feature is available for the SKUdoneThis feature is available for the SKUdoneThis feature is available for the SKUdone\n\n\nGemini in Sheets - visualize data and surface insights faster with AIThis feature is not supported by this SKUhorizontal_ruleThis feature is available for the SKUdoneThis feature is available for the SKUdoneThis feature is available for the SKUdone\n\n\nGemini in Slides - make presentations shine with AI imagesThis feature is not supported by this SKUhorizontal_ruleThis feature is available for the SKUdoneThis feature is available for the SKUdoneThis feature is available for the SKUdone\n\n\nGemini in Vids - tell engaging stories at work with AI-powered video creationThis feature is not supported by this SKUhorizontal_ruleThis feature is available for the SKUdoneThis feature is available for the SKUdoneThis feature is available for the SKUdone\n\n\nGemini in Drive - find, summarize, and analyze files with AIThis feature is not supported by this SKUhorizontal_ruleThis feature is available for the SKUdoneThis feature is available for the SKUdoneThis feature is available for the SKUdone\n\n\nGemini in Meet - let AI summarize, translate, and take notes in meetingsThis feature is not supported by this SKUhorizontal_ruleThis feature is available for the SKUdoneThis feature is available for the SKUdoneThis feature is available for the SKUdone\n\n\nGemini in Chat - find, summarize, and translate chats with AIThis feature is not supported by this SKUhorizontal_ruleThis feature is available for the SKUdoneThis feature is available for the SKUdoneThis feature is available for the SKUdone\n\n\n\nGemini app \nAI assistant from Google\nGemini app\nGemini Advanced\nGemini Advanced\nGemini Advanced\n\n\nEnterprise-grade security and privacyThis feature is available for the SKUdoneThis feature is available for the SKUdoneThis feature is available for the SKUdoneThis feature is available for the SKUdone\n\n\nAccess Gemini app on web or mobileThis feature is available for the SKUdoneThis feature is available for the SKUdoneThis feature is available for the SKUdoneThis feature is available for the SKUdone\n\n\nGoogle\u2019s most capable AI models for complex tasksThis feature is not supported by this SKUhorizontal_ruleThis feature is available for the SKUdoneThis feature is available for the SKUdoneThis feature is available for the SKUdone\n\n\nBuild custom AI experts for any topic with GemsThis feature is not supported by this SKUhorizontal_ruleThis feature is available for the SKUdoneThis feature is available for the SKUdoneThis feature is available for the SKUdone\n\n\n\nMeet \nVideo and voice conferencing\n100 participants\n100 people\n150 participants\n150 people\n500 participants\n500 people\n1000 participants\n1000 people\n\n\nMeeting length (maximum)\n24 hours\n24 hours\n24 hours\n24 hours\n\n\nUS or international dial-in phone numbersThis feature is available for the SKUdoneThis feature is available for the SKUdoneThis feature is available for the SKUdoneThis feature is available for the SKUdone\n\n\nStudio Sound noise cancellationThis feature is not supported by this SKUhorizontal_ruleThis feature is available for the SKUdoneThis feature is available for the SKUdoneThis feature is available for the SKUdone\n\n\nAdaptive AudioThis feature is not supported by this SKUhorizontal_ruleThis feature is available for the SKUdoneThis feature is available for the SKUdoneThis feature is available for the SKUdone\n\n\nMeeting recordings saved to Google DriveThis feature is not supported by this SKUhorizontal_ruleThis feature is available for the SKUdoneThis feature is available for the SKUdoneThis feature is available for the SKUdone\n\n\n\n\nexpand_moreSee more features\n\n\n\nDrive \nSecure cloud storage\n30 GB per user\n30 GB / user\n2 TB per user\n2 TB / user\n5 TB per user\n5 TB / user\n5 TB per user with ability to request more\n5 TB / user with ability to request more\n\n\nDrive for desktopThis feature is available for the SKUdoneThis feature is available for the SKUdoneThis feature is available for the SKUdoneThis feature is available for the SKUdone\n\n\n\n\nexpand_moreSee more features\n\n\n\nChat \nTeam messagingThis feature is available for the SKUdoneThis feature is available for the SKUdoneThis feature is available for the SKUdoneThis feature is available for the SKUdone\n\n\nTurn history on or off by defaultThis feature is available for the SKUdoneThis feature is available for the SKUdoneThis feature is available for the SKUdoneThis feature is available for the SKUdone\n\n\nAuto-accept invitationsThis feature is available for the SKUdoneThis feature is available for the SKUdoneThis feature is available for the SKUdoneThis feature is available for the SKUdone\n\n\n\n\nexpand_moreSee more features\n\n\n\nCalendar \nShared calendarsThis feature is available for the SKUdoneThis feature is available for the SKUdoneThis feature is available for the SKUdoneThis feature is available for the SKUdone\n\n\nAppointment booking pagesThis feature is not supported by this SKUhorizontal_ruleThis feature is available for the SKUdoneThis feature is available for the SKUdoneThis feature is available for the SKUdone\n\n\nBrowse and reserve conference roomsThis feature is available for the SKUdoneThis feature is available for the SKUdoneThis feature is available for the SKUdoneThis feature is available for the SKUdone\n\n\n\nDocs, Sheets, Slides \nCollaborative content creationThis feature is available for the SKUdoneThis feature is available for the SKUdoneThis feature is available for the SKUdoneThis feature is available for the SKUdone\n\n\nVids AI-powered video creationThis feature is not supported by this SKUhorizontal_ruleThis feature is available for the SKUdoneThis feature is available for the SKUdoneThis feature is available for the SKUdone\n\n\nKeep Shared NotesThis feature is available for the SKUdoneThis feature is available for the SKUdoneThis feature is available for the SKUdoneThis feature is available for the SKUdone\n\n\neSignature with Docs and PDFsThis feature is not supported by this SKUhorizontal_ruleThis feature is available for the SKUdoneThis feature is available for the SKUdoneThis feature is available for the SKUdone\n\n\nSites website builderThis feature is available for the SKUdoneThis feature is available for the SKUdoneThis feature is available for the SKUdoneThis feature is available for the SKUdone\n\n\nForms survey builderThis feature is available for the SKUdoneThis feature is available for the SKUdoneThis feature is available for the SKUdoneThis feature is available for the SKUdone\n\n\nInteroperability with Office filesThis feature is available for the SKUdoneThis feature is available for the SKUdoneThis feature is available for the SKUdoneThis feature is available for the SKUdone\n\n\nEasier analysis with Smart Fill, Smart Cleanup, and AnswersThis feature is available for the SKUdoneThis feature is available for the SKUdoneThis feature is available for the SKUdoneThis feature is available for the SKUdone\n\n\nProofread to help with writing styleThis feature is not supported by this SKUhorizontal_ruleThis feature is available for the SKUdoneThis feature is available for the SKUdoneThis feature is available for the SKUdone\n\n\n\n\nexpand_moreSee more features\n\n\n\nNotebookLM \nAI research assistant\nNotebookLM\nNotebookLM Plus\nNotebookLM Plus\nNotebookLM Plus\n\n\nGenerate interactive Audio Overviews with two AI hosts\nUp to 3 per day\nUp to 20 per day\nUp to 20 per day\nUp to 20 per day\n\n\nGet 5x more notebooks, chat queries and sources per notebookThis feature is not supported by this SKUhorizontal_ruleThis feature is available for the SKUdoneThis feature is available for the SKUdoneThis feature is available for the SKUdone\n\n\nChat modes to customize style and lengthThis feature is not supported by this SKUhorizontal_ruleThis feature is available for the SKUdoneThis feature is available for the SKUdoneThis feature is available for the SKUdone\n\n\n\nAppSheet \nBuild apps without codeThis feature is available for the SKUdoneThis feature is available for the SKUdoneThis feature is available for the SKUdoneThis feature is available for the SKUdone\n\n\nSecurity & Management\n\n2-step verificationThis feature is available for the SKUdoneThis feature is available for the SKUdoneThis feature is available for the SKUdoneThis feature is available for the SKUdone\n\nGroup-based policy controlsThis feature is available for the SKUdoneThis feature is available for the SKUdoneThis feature is available for the SKUdoneThis feature is available for the SKUdone\n\nAdvanced Protection ProgramThis feature is available for the SKUdoneThis feature is available for the SKUdoneThis feature is available for the SKUdoneThis feature is available for the SKUdone\n\nEndpoint management\nFundamental\nFundamental\nAdvanced\nEnterprise\n\n\n\n\nexpand_moreSee more features\nTry Google Workspace for free\nSee why millions of businesses love and rely on Google Workspace for their business needs.\n\n\n\n\nStart a trial\n\n\nTop questions about Google Workspace pricing\n\n\n\nWhat is a user?expand_more\n\n\n\n\nHow do I buy and pay?expand_more\n\n\n\n\nWhat is the payment plan?expand_more\n\n\n\nAdd-ons sold separately.\nHardware\n\n\nGoogle Meet Hardware\nFast, reliable, easy-to-join web meetings and video conferencing services for any size meeting room.Learn more\n\nChrome Enterprise\nUnlock the business capabilities of Chrome OS, Chrome Browser, and Chrome devices, freeing IT to power your cloud workforce.Learn more\nApplications\n\n\nVoice\nAn affordable, easy-to-use business telephone solution for organizations of any size.Get Google Workspace with VoiceLearn more\n\nAppSheet\nA no-code app development platform with advanced integrations and secure governance policies.Learn more\n\n\nSign up for the Google Workspace newsletter\n\n\nEnter your emailEnter your email\n\n\nPlease enter a valid email addressPlease enter a valid email address\n\n\nRegionRegionRegionUnited States\n\n\n\n\nAfghanistan\nAlbania\nAmerican Samoa\nAndorra\nAnguilla\nAntarctica\nAntigua and Barbuda\nArgentina\nArmenia\nAruba\nAustralia\nAustria\nAzerbaijan\nBahamas\nBahrain\nBangladesh\nBarbados\nBelarus\nBelgium\nBelize\nBenin\nBermuda\nBhutan\nBolivia\nBosnia and Herzegovina\nBotswana\nBouvet Island\nBrazil\nBritish Indian Ocean Territory\nBritish Virgin Islands\nBrunei\nBulgaria\nBurkina Faso\nBurundi\nCambodia\nCameroon\nCanada\nCape Verde\nCayman Islands\nCentral African Republic\nChad\nChile\nChina\nChristmas Island\nCocos [Keeling] Islands\nColombia\nComoros\nCongo [DRC]\nCongo [Republic]\nCook Islands\nCosta Rica\nC\u00f4te d'Ivoire\nCroatia\nCyprus\nCzech Republic\nDenmark\nDjibouti\nDominica\nDominican Republic\nEcuador\nEgypt\nEl Salvador\nEquatorial Guinea\nEritrea\nEstonia\nEthiopia\nFalkland Islands [Islas Malvinas]\nFaroe Islands\nFiji\nFinland\nFrance\nFrench Guiana\nFrench Polynesia\nFrench Southern Territories\nGabon\nGambia\nGeorgia\nGermany\nGhana\nGibraltar\nGreece\nGreenland\nGrenada\nGuadeloupe\nGuam\nGuatemala\nGuinea\nGuinea-Bissau\nGuyana\nHaiti\nHeard Island and McDonald Islands\nHonduras\nHong Kong\nHungary\nIceland\nIndia\nIndonesia\nIraq\nIreland\nIsrael\nItaly\nJamaica\nJapan\nJordan\nKazakhstan\nKenya\nKiribati\nKuwait\nKyrgyzstan\nLaos\nLatvia\nLebanon\nLesotho\nLiberia\nLibya\nLiechtenstein\nLithuania\nLuxembourg\nMacau\nMacedonia [FYROM]\nMadagascar\nMalawi\nMalaysia\nMaldives\nMali\nMalta\nMarshall Islands\nMartinique\nMauritania\nMauritius\nMayotte\nMexico\nMicronesia\nMoldova\nMonaco\nMongolia\nMontserrat\nMorocco\nMozambique\nNamibia\nNauru\nNepal\nNetherlands\nNetherlands Antilles\nNew Caledonia\nNew Zealand\nNicaragua\nNiger\nNigeria\nNiue\nNorfolk Island\nNorthern Mariana Islands\nNorway\nOman\nPakistan\nPalau\nPalestine\nPanama\nPapua New Guinea\nParaguay\nPeru\nPhilippines\nPitcairn Islands\nPoland\nPortugal\nPuerto Rico\nQatar\nR\u00e9union\nRomania\nRussia\nRwanda\nSaint Helena\nSaint Kitts and Nevis\nSaint Lucia\nSaint Pierre and Miquelon\nSaint Vincent and the Grenadines\nSamoa\nSan Marino\nS\u00e3o Tom\u00e9 and Pr\u00edncipe\nSaudi Arabia\nSenegal\nSeychelles\nSierra Leone\nSingapore\nSlovakia\nSlovenia\nSolomon Islands\nSomalia\nSouth Africa\nSouth Georgia and the South Sandwich Islands\nSouth Korea\nSpain\nSri Lanka\nSuriname\nSvalbard and Jan Mayen\nSwaziland\nSweden\nSwitzerland\nTaiwan\nTajikistan\nTanzania\nThailand\nTimor-Leste\nTogo\nTokelau\nTonga\nTrinidad and Tobago\nTunisia\nTurkey\nTurkmenistan\nTurks and Caicos Islands\nTuvalu\nU.S. Outlying Islands\nU.S. Virgin Islands\nUganda\nUkraine\nUnited Arab Emirates\nUnited Kingdom\nUnited States\nUruguay\nUzbekistan\nVanuatu\nVatican City\nVenezuela\nVietnam\nWallis and Futuna\nWestern Sahara\nYemen\nZambia\nZimbabwe\n\n\n\nAlso sign me up for Google Cloud emails with news, product updates, event information, special offers, and more. (Optional and you can unsubscribe at a later time).\nI understand my personal data will be processed in accordance with Google\u2019s Privacy Policy.\n\n\nSign up\n\n\n\n\nFollow our Blog\n\n\n\n\n\n\n\nSearch this siteSearch this sitesearch\n\n\n\n\n\nIncluded applications\n\nGmail\nMeet\nChat\nCalendar\nDrive\nDocs\nSheets\nSlides\nForms\nSites\nKeep\nApps Script\n\n\n\nIncluded applicationsexpand_more\n\n\n\nSecurity and management\n\nAdmin\nEndpoint\nVault\nWork Insights\n\n\n\nSecurity and managementexpand_more\n\n\n\nSolutions\n\nNew Business\nSmall Business\nEnterprise\nRetail\nManufacturing\nProfessional Services\nTechnology\nHealthcare\nGovernment\nEducation\nNonprofits\nArtificial Intelligence\n\n\n\nSolutionsexpand_more\n\n\n\nPricing\n\nCompare pricing plans\n\n\n\nPricingexpand_more\n\n\n\nAdd-ons\n\nMeet hardware\nGoogle Voice\nAppSheet\n\n\n\nAdd-onsexpand_more\n\n\n\nResources\n\nWorking remotely\nSecurity\nCustomer Stories\nFAQs\nPartners\nMarketplace\nIntegrations\nTraining & Certification\nRefer Google Workspace\n\n\n\nResourcesexpand_more\n\n\n\nLearning and support\n\nAdmin Help\nSetup and Deployment Center\nLearning Center for Users\nForums for Admins\nGoogle Workspace Dashboard\nWhat's New in Google Workspace\nFind a Google Workspace Partner\nJoin the community of IT Admins\nPress\n\n\n\nLearning and supportexpand_more\n\n\n\nMore from Google\n\nGoogle Cloud\nGoogle Domains\nChrome Enterprise\nGoogle Business Solutions\nGoogle Ads\nBusiness Messages\nJoin User Studies\n\n\n\nMore from Googleexpand_more\n\n\nGoogleAbout GoogleGoogle ProductsPrivacyTerms\n\n\n\n\nlanguageChange Language\n\n\n\n\n\nPrivacy Policy\n\nTerms\n\nCookies management controls\n\nCompare flexible pricing options for Google Workspace with plans for businesses of all sizes.",
      "error": null,
      "pricing_data": {
        "app_id": "google_slides",
        "app_name": "Google Slides",
        "app_slug": "google-slides",
        "pricing_url": "https://workspace.google.com/pricing",
        "source_url": null,
        "all_pricing_urls": [
          "https://workspace.google.com/pricing"
        ],
        "price_model_type": [
          "PriceModelType.SUBSCRIPTION"
        ],
        "has_free_tier": false,
        "has_free_trial": true,
        "free_trial_period_days": 14,
        "currency": "USD",
        "is_pricing_public": true,
        "pricing_page_accessible": true,
        "pricing_notes": "Pricing is part of Google Workspace plans, which include Google Slides among other applications.",
        "pricing_tiers": [
          {
            "tier_name": "Business Starter",
            "tier_description": null,
            "monthly_price": 8.4,
            "annual_price": 84.0,
            "annual_discount_percentage": 16.67,
            "setup_fee": null,
            "features": [
              "30 GB pooled storage per user",
              "Secure custom business email",
              "Gemini AI assistant in Gmail",
              "Chat with AI in the Gemini app",
              "100 participant video meetings",
              "Security and management controls",
              "Standard Support"
            ],
            "limits": {
              "users": 300,
              "storage": "30GB",
              "operations": null,
              "api_calls": null,
              "integrations": null,
              "custom_limits": null
            }
          },
          {
            "tier_name": "Business Standard",
            "tier_description": null,
            "monthly_price": 16.8,
            "annual_price": 168.0,
            "annual_discount_percentage": 16.67,
            "setup_fee": null,
            "features": [
              "2 TB pooled storage per user",
              "Secure custom business email",
              "Gemini AI assistant in Gmail, Docs, Meet, and more",
              "Chat with AI in the Gemini app + create your team of AI experts",
              "AI research assistant (NotebookLM Plus)",
              "150 participant video meetings + recording, noise cancellation",
              "eSignature with Docs and PDFs",
              "Appointment booking pages",
              "Collaborative video creator + editor",
              "Email layouts and mail merge",
              "Security and management controls",
              "Standard Support"
            ],
            "limits": {
              "users": 300,
              "storage": "2TB",
              "operations": null,
              "api_calls": null,
              "integrations": null,
              "custom_limits": null
            }
          },
          {
            "tier_name": "Business Plus",
            "tier_description": null,
            "monthly_price": 26.4,
            "annual_price": 264.0,
            "annual_discount_percentage": 16.67,
            "setup_fee": null,
            "features": [
              "5 TB pooled storage per user",
              "Secure custom business email, eDiscovery, retention",
              "Gemini AI assistant in Gmail, Docs, Meet, and more",
              "Chat with AI in the Gemini app + create your team of AI experts",
              "AI research assistant (NotebookLM Plus)",
              "500 participant video meetings + recording, attendance tracking, noise cancellation",
              "eSignature with Docs and PDFs",
              "Appointment booking pages",
              "Collaborative video creator + editor",
              "Email layouts and mail merge",
              "Enhanced security and management controls, including Vault and advanced endpoint management",
              "Standard Support"
            ],
            "limits": {
              "users": 300,
              "storage": "5TB",
              "operations": null,
              "api_calls": null,
              "integrations": null,
              "custom_limits": null
            }
          },
          {
            "tier_name": "Enterprise",
            "tier_description": null,
            "monthly_price": null,
            "annual_price": null,
            "annual_discount_percentage": null,
            "setup_fee": null,
            "features": [
              "5 TB pooled storage per user",
              "Secure custom business email, eDiscovery, retention",
              "Gemini AI assistant in Gmail, Docs, Meet, and more",
              "Chat with AI in the Gemini app + create your team of AI experts",
              "AI research assistant (NotebookLM Plus)",
              "1000 participant video meetings + recording, attendance tracking, noise cancellation, in-domain live streaming",
              "eSignature with Docs and PDFs",
              "Appointment booking pages",
              "Collaborative video creator + editor",
              "Email layouts and mail merge",
              "Advanced security, management, and compliance controls, including Vault, DLP, data regions, and enterprise endpoint management",
              "Enhanced Support"
            ],
            "limits": {
              "users": "unlimited",
              "storage": "5TB",
              "operations": null,
              "api_calls": null,
              "integrations": null,
              "custom_limits": null
            }
          }
        ],
        "usage_based_pricing": null,
        "ai_specific_pricing": null,
        "promotional_offers": [
          {
            "offer_name": "Limited promotional period features",
            "offer_description": "Google Workspace customers may have access to additional features for a limited promotional period.",
            "discount_percentage": null,
            "offer_url": null,
            "valid_until": null
          }
        ],
        "additional_fees": null,
        "extraction_timestamp": "2025-04-15T03:20:22.042523",
        "schema_validated": true,
        "confidence_score": 100,
        "extraction_error": false,
        "json_repaired": false
      },
      "pricing_analyzed": true
    },
    {
      "url": "https://workspace.google.com/pricing.html",
      "is_accessible": true,
      "content": "closemenu\n\n\n\n\nSolutions\n\nProducts\n\nIndustries\n\nAI\n\nPricing\n\nResources\n\n\nAdmin console\n\nContact sales\n\nStart a trial\n\n\n\nSolutions\n\nProducts\n\nIndustries\n\nAI\n\nPricing\n\nResources\n\n\n\n\n\n\nTry Google Workspace for 14 days.\n\n\n\nGmail\n\nDrive\n\nMeet\n\nCalendar\n\nChat\n\nGemini app\n\nDocs\n\nSheets\n\nSlides\n\nVids\n\nKeep\n\nSites\n\nForms\n\nNotebookLM\n\nAppSheet\n\n\n\nBusiness Starter\n\n$7 USD\n$7\nper user / month, 1 year commitment\n\n\ninfo_outline\n\n\nOr $8.40 per user / month, when billed monthly\n\n\n\n\n\nStart a trial\n\n30 GB\n pooled storage per user*\nSecure custom business email, you@your-company.com\n\n\nGet started with AI\nGemini AI assistant in Gmail\nChat with AI in the Gemini app\n100 participant video meetings\nSecurity and management controls\nStandard Support\n\nmost popular\n\nBusiness Standard\n\n$14 USD\n$14\nper user / month, 1 year commitment\n\n\ninfo_outline\n\n\nOr $16.80 per user / month, when billed monthly\n\n\n\n\n\nStart a trial\n\n2 TB\n pooled storage per user*\nSecure custom business email, you@your-company.com\n\n\nUnlock the full power of AI\nGemini AI assistant in Gmail, Docs, Meet, and more\nChat with AI in the Gemini app + create your team of AI experts\nAI research assistant (NotebookLM Plus)\n150 participant video meetings + recording, noise cancellation\neSignature with Docs and PDFs\nAppointment booking pages\nCollaborative video creator + editor\nEmail layouts and mail merge\nSecurity and management controls\nStandard Support**\n\n\nBusiness Plus\n\n$22 USD\n$22\nper user / month, 1 year commitment\n\n\ninfo_outline\n\n\nOr $26.40 per user / month, when billed monthly\n\n\n\n\n\nStart a trial\n\n5 TB\n pooled storage per user*\nSecure custom business email, eDiscovery, retention\n\n\nUnlock the full power of AI\nGemini AI assistant in Gmail, Docs, Meet, and more\nChat with AI in the Gemini app + create your team of AI experts\nAI research assistant (NotebookLM Plus)\n500 participant video meetings + recording, attendance tracking, noise cancellation\neSignature with Docs and PDFs\nAppointment booking pages\nCollaborative video creator + editor\nEmail layouts and mail merge\nEnhanced security and management controls, including Vault and advanced endpoint management\nStandard Support**\n\n\nEnterprise\n\nContact sales for pricing\n\n\n\n\n\nContact sales\n\n5 TB\n pooled storage per user*\nSecure custom business email, eDiscovery, retention\n\n\nUnlock the full power of AI\nGemini AI assistant in Gmail, Docs, Meet, and more\nChat with AI in the Gemini app + create your team of AI experts\nAI research assistant (NotebookLM Plus)\n1000 participant video meetings + recording, attendance tracking, noise cancellation, in-domain live streaming\neSignature with Docs and PDFs\nAppointment booking pages\nCollaborative video creator + editor\nEmail layouts and mail merge\nAdvanced security, management, and compliance controls, including Vault, DLP, data regions, and enterprise endpoint management\nEnhanced Support**\n\n\n\n\n\nBusiness Starter\nBusiness Standard\nBusiness Plus\nEnterprise\n\n\n\n\nBusiness Starter\n\n$7 USD\n$7\nper user / month, 1 year commitment\n\n\ninfo_outline\n\n\nOr $8.40 per user / month, when billed monthly\n\n\n\n\n\nStart a trial\n\n30 GB\n pooled storage per user*\nSecure custom business email, you@your-company.com\n\n\nGet started with AI\nGemini AI assistant in Gmail\nChat with AI in the Gemini app\n100 participant video meetings\nSecurity and management controls\nStandard Support\n\n\n\nmost popular\n\nBusiness Standard\n\n$14 USD\n$14\nper user / month, 1 year commitment\n\n\ninfo_outline\n\n\nOr $16.80 per user / month, when billed monthly\n\n\n\n\n\nStart a trial\n\n2 TB\n pooled storage per user*\nSecure custom business email, you@your-company.com\n\n\nUnlock the full power of AI\nGemini AI assistant in Gmail, Docs, Meet, and more\nChat with AI in the Gemini app + create your team of AI experts\nAI research assistant (NotebookLM Plus)\n150 participant video meetings + recording, noise cancellation\neSignature with Docs and PDFs\nAppointment booking pages\nCollaborative video creator + editor\nEmail layouts and mail merge\nSecurity and management controls\nStandard Support**\n\n\n\n\nBusiness Plus\n\n$22 USD\n$22\nper user / month, 1 year commitment\n\n\ninfo_outline\n\n\nOr $26.40 per user / month, when billed monthly\n\n\n\n\n\nStart a trial\n\n5 TB\n pooled storage per user*\nSecure custom business email, eDiscovery, retention\n\n\nUnlock the full power of AI\nGemini AI assistant in Gmail, Docs, Meet, and more\nChat with AI in the Gemini app + create your team of AI experts\nAI research assistant (NotebookLM Plus)\n500 participant video meetings + recording, attendance tracking, noise cancellation\neSignature with Docs and PDFs\nAppointment booking pages\nCollaborative video creator + editor\nEmail layouts and mail merge\nEnhanced security and management controls, including Vault and advanced endpoint management\nStandard Support**\n\n\n\n\nEnterprise\n\nContact sales for pricing\n\n\n\n\n\nContact sales\n\n5 TB\n pooled storage per user*\nSecure custom business email, eDiscovery, retention\n\n\nUnlock the full power of AI\nGemini AI assistant in Gmail, Docs, Meet, and more\nChat with AI in the Gemini app + create your team of AI experts\nAI research assistant (NotebookLM Plus)\n1000 participant video meetings + recording, attendance tracking, noise cancellation, in-domain live streaming\neSignature with Docs and PDFs\nAppointment booking pages\nCollaborative video creator + editor\nEmail layouts and mail merge\nAdvanced security, management, and compliance controls, including Vault, DLP, data regions, and enterprise endpoint management\nEnhanced Support**\n\nBusiness Starter, Business Standard, and Business Plus plans can be purchased for a maximum of 300 users. There is no minimum or maximum user limit for Enterprise plans.\nGoogle Workspace customers may have access to additional features for a limited promotional period.\n\nGoogle Workspace provides flexible pooled storage per user that is shared across the organization. Visit our Help Center to learn more about getting additional storage for your organization.\nPaid upgrade available from Standard to Enhanced Support, or from Enhanced to Premium Support on Enterprise plansCompare plans in detail\narrow_downward\n\n\n\nStart a trialarrow_forward_ios\nBusiness Starter\n\nBusiness Starter\n\n\n\n\nStart a trial\nmost popular\nBusiness Standard\n\nBusiness Standard\n\n\n\n\nStart a trial\nBusiness Plus\n\nBusiness Plus\n\n\n\n\nStart a trial\nEnterprise\n\nEnterprise\n\n\n\n\nContact sales\n\n\nProductivity & Collaboration\n\n\n\nGmail \nBusiness emailThis feature is available for the SKUdoneThis feature is available for the SKUdoneThis feature is available for the SKUdoneThis feature is available for the SKUdone\n\n\nCustom email for your businessThis feature is available for the SKUdoneThis feature is available for the SKUdoneThis feature is available for the SKUdoneThis feature is available for the SKUdone\n\n\nPhishing and spam protection that blocks more than 99.9% of attacksThis feature is available for the SKUdoneThis feature is available for the SKUdoneThis feature is available for the SKUdoneThis feature is available for the SKUdone\n\n\nAd-free email experienceThis feature is available for the SKUdoneThis feature is available for the SKUdoneThis feature is available for the SKUdoneThis feature is available for the SKUdone\n\n\nGemini in Workspace apps\nLimitedThis feature is available for the SKUdoneThis feature is available for the SKUdoneThis feature is available for the SKUdone\n\n\nEnterprise-grade security and privacyThis feature is available for the SKUdoneThis feature is available for the SKUdoneThis feature is available for the SKUdoneThis feature is available for the SKUdone\n\n\nGemini in Gmail - find, summarize, and write emails faster with AIThis feature is available for the SKUdoneThis feature is available for the SKUdoneThis feature is available for the SKUdoneThis feature is available for the SKUdone\n\n\nGemini in Docs - tackle the blank page or polish draft documents with AIThis feature is not supported by this SKUhorizontal_ruleThis feature is available for the SKUdoneThis feature is available for the SKUdoneThis feature is available for the SKUdone\n\n\nGemini in Sheets - visualize data and surface insights faster with AIThis feature is not supported by this SKUhorizontal_ruleThis feature is available for the SKUdoneThis feature is available for the SKUdoneThis feature is available for the SKUdone\n\n\nGemini in Slides - make presentations shine with AI imagesThis feature is not supported by this SKUhorizontal_ruleThis feature is available for the SKUdoneThis feature is available for the SKUdoneThis feature is available for the SKUdone\n\n\nGemini in Vids - tell engaging stories at work with AI-powered video creationThis feature is not supported by this SKUhorizontal_ruleThis feature is available for the SKUdoneThis feature is available for the SKUdoneThis feature is available for the SKUdone\n\n\nGemini in Drive - find, summarize, and analyze files with AIThis feature is not supported by this SKUhorizontal_ruleThis feature is available for the SKUdoneThis feature is available for the SKUdoneThis feature is available for the SKUdone\n\n\nGemini in Meet - let AI summarize, translate, and take notes in meetingsThis feature is not supported by this SKUhorizontal_ruleThis feature is available for the SKUdoneThis feature is available for the SKUdoneThis feature is available for the SKUdone\n\n\nGemini in Chat - find, summarize, and translate chats with AIThis feature is not supported by this SKUhorizontal_ruleThis feature is available for the SKUdoneThis feature is available for the SKUdoneThis feature is available for the SKUdone\n\n\n\nGemini app \nAI assistant from Google\nGemini app\nGemini Advanced\nGemini Advanced\nGemini Advanced\n\n\nEnterprise-grade security and privacyThis feature is available for the SKUdoneThis feature is available for the SKUdoneThis feature is available for the SKUdoneThis feature is available for the SKUdone\n\n\nAccess Gemini app on web or mobileThis feature is available for the SKUdoneThis feature is available for the SKUdoneThis feature is available for the SKUdoneThis feature is available for the SKUdone\n\n\nGoogle\u2019s most capable AI models for complex tasksThis feature is not supported by this SKUhorizontal_ruleThis feature is available for the SKUdoneThis feature is available for the SKUdoneThis feature is available for the SKUdone\n\n\nBuild custom AI experts for any topic with GemsThis feature is not supported by this SKUhorizontal_ruleThis feature is available for the SKUdoneThis feature is available for the SKUdoneThis feature is available for the SKUdone\n\n\n\nMeet \nVideo and voice conferencing\n100 participants\n100 people\n150 participants\n150 people\n500 participants\n500 people\n1000 participants\n1000 people\n\n\nMeeting length (maximum)\n24 hours\n24 hours\n24 hours\n24 hours\n\n\nUS or international dial-in phone numbersThis feature is available for the SKUdoneThis feature is available for the SKUdoneThis feature is available for the SKUdoneThis feature is available for the SKUdone\n\n\nStudio Sound noise cancellationThis feature is not supported by this SKUhorizontal_ruleThis feature is available for the SKUdoneThis feature is available for the SKUdoneThis feature is available for the SKUdone\n\n\nAdaptive AudioThis feature is not supported by this SKUhorizontal_ruleThis feature is available for the SKUdoneThis feature is available for the SKUdoneThis feature is available for the SKUdone\n\n\nMeeting recordings saved to Google DriveThis feature is not supported by this SKUhorizontal_ruleThis feature is available for the SKUdoneThis feature is available for the SKUdoneThis feature is available for the SKUdone\n\n\n\n\nexpand_moreSee more features\n\n\n\nDrive \nSecure cloud storage\n30 GB per user\n30 GB / user\n2 TB per user\n2 TB / user\n5 TB per user\n5 TB / user\n5 TB per user with ability to request more\n5 TB / user with ability to request more\n\n\nDrive for desktopThis feature is available for the SKUdoneThis feature is available for the SKUdoneThis feature is available for the SKUdoneThis feature is available for the SKUdone\n\n\n\n\nexpand_moreSee more features\n\n\n\nChat \nTeam messagingThis feature is available for the SKUdoneThis feature is available for the SKUdoneThis feature is available for the SKUdoneThis feature is available for the SKUdone\n\n\nTurn history on or off by defaultThis feature is available for the SKUdoneThis feature is available for the SKUdoneThis feature is available for the SKUdoneThis feature is available for the SKUdone\n\n\nAuto-accept invitationsThis feature is available for the SKUdoneThis feature is available for the SKUdoneThis feature is available for the SKUdoneThis feature is available for the SKUdone\n\n\n\n\nexpand_moreSee more features\n\n\n\nCalendar \nShared calendarsThis feature is available for the SKUdoneThis feature is available for the SKUdoneThis feature is available for the SKUdoneThis feature is available for the SKUdone\n\n\nAppointment booking pagesThis feature is not supported by this SKUhorizontal_ruleThis feature is available for the SKUdoneThis feature is available for the SKUdoneThis feature is available for the SKUdone\n\n\nBrowse and reserve conference roomsThis feature is available for the SKUdoneThis feature is available for the SKUdoneThis feature is available for the SKUdoneThis feature is available for the SKUdone\n\n\n\nDocs, Sheets, Slides \nCollaborative content creationThis feature is available for the SKUdoneThis feature is available for the SKUdoneThis feature is available for the SKUdoneThis feature is available for the SKUdone\n\n\nVids AI-powered video creationThis feature is not supported by this SKUhorizontal_ruleThis feature is available for the SKUdoneThis feature is available for the SKUdoneThis feature is available for the SKUdone\n\n\nKeep Shared NotesThis feature is available for the SKUdoneThis feature is available for the SKUdoneThis feature is available for the SKUdoneThis feature is available for the SKUdone\n\n\neSignature with Docs and PDFsThis feature is not supported by this SKUhorizontal_ruleThis feature is available for the SKUdoneThis feature is available for the SKUdoneThis feature is available for the SKUdone\n\n\nSites website builderThis feature is available for the SKUdoneThis feature is available for the SKUdoneThis feature is available for the SKUdoneThis feature is available for the SKUdone\n\n\nForms survey builderThis feature is available for the SKUdoneThis feature is available for the SKUdoneThis feature is available for the SKUdoneThis feature is available for the SKUdone\n\n\nInteroperability with Office filesThis feature is available for the SKUdoneThis feature is available for the SKUdoneThis feature is available for the SKUdoneThis feature is available for the SKUdone\n\n\nEasier analysis with Smart Fill, Smart Cleanup, and AnswersThis feature is available for the SKUdoneThis feature is available for the SKUdoneThis feature is available for the SKUdoneThis feature is available for the SKUdone\n\n\nProofread to help with writing styleThis feature is not supported by this SKUhorizontal_ruleThis feature is available for the SKUdoneThis feature is available for the SKUdoneThis feature is available for the SKUdone\n\n\n\n\nexpand_moreSee more features\n\n\n\nNotebookLM \nAI research assistant\nNotebookLM\nNotebookLM Plus\nNotebookLM Plus\nNotebookLM Plus\n\n\nGenerate interactive Audio Overviews with two AI hosts\nUp to 3 per day\nUp to 20 per day\nUp to 20 per day\nUp to 20 per day\n\n\nGet 5x more notebooks, chat queries and sources per notebookThis feature is not supported by this SKUhorizontal_ruleThis feature is available for the SKUdoneThis feature is available for the SKUdoneThis feature is available for the SKUdone\n\n\nChat modes to customize style and lengthThis feature is not supported by this SKUhorizontal_ruleThis feature is available for the SKUdoneThis feature is available for the SKUdoneThis feature is available for the SKUdone\n\n\n\nAppSheet \nBuild apps without codeThis feature is available for the SKUdoneThis feature is available for the SKUdoneThis feature is available for the SKUdoneThis feature is available for the SKUdone\n\n\nSecurity & Management\n\n2-step verificationThis feature is available for the SKUdoneThis feature is available for the SKUdoneThis feature is available for the SKUdoneThis feature is available for the SKUdone\n\nGroup-based policy controlsThis feature is available for the SKUdoneThis feature is available for the SKUdoneThis feature is available for the SKUdoneThis feature is available for the SKUdone\n\nAdvanced Protection ProgramThis feature is available for the SKUdoneThis feature is available for the SKUdoneThis feature is available for the SKUdoneThis feature is available for the SKUdone\n\nEndpoint management\nFundamental\nFundamental\nAdvanced\nEnterprise\n\n\n\n\nexpand_moreSee more features\nTry Google Workspace for free\nSee why millions of businesses love and rely on Google Workspace for their business needs.\n\n\n\n\nStart a trial\n\n\nTop questions about Google Workspace pricing\n\n\n\nWhat is a user?expand_more\n\n\n\n\nHow do I buy and pay?expand_more\n\n\n\n\nWhat is the payment plan?expand_more\n\n\n\nAdd-ons sold separately.\nHardware\n\n\nGoogle Meet Hardware\nFast, reliable, easy-to-join web meetings and video conferencing services for any size meeting room.Learn more\n\nChrome Enterprise\nUnlock the business capabilities of Chrome OS, Chrome Browser, and Chrome devices, freeing IT to power your cloud workforce.Learn more\nApplications\n\n\nVoice\nAn affordable, easy-to-use business telephone solution for organizations of any size.Get Google Workspace with VoiceLearn more\n\nAppSheet\nA no-code app development platform with advanced integrations and secure governance policies.Learn more\n\n\nSign up for the Google Workspace newsletter\n\n\nEnter your emailEnter your email\n\n\nPlease enter a valid email addressPlease enter a valid email address\n\n\nRegionRegionRegionUnited States\n\n\n\n\nAfghanistan\nAlbania\nAmerican Samoa\nAndorra\nAnguilla\nAntarctica\nAntigua and Barbuda\nArgentina\nArmenia\nAruba\nAustralia\nAustria\nAzerbaijan\nBahamas\nBahrain\nBangladesh\nBarbados\nBelarus\nBelgium\nBelize\nBenin\nBermuda\nBhutan\nBolivia\nBosnia and Herzegovina\nBotswana\nBouvet Island\nBrazil\nBritish Indian Ocean Territory\nBritish Virgin Islands\nBrunei\nBulgaria\nBurkina Faso\nBurundi\nCambodia\nCameroon\nCanada\nCape Verde\nCayman Islands\nCentral African Republic\nChad\nChile\nChina\nChristmas Island\nCocos [Keeling] Islands\nColombia\nComoros\nCongo [DRC]\nCongo [Republic]\nCook Islands\nCosta Rica\nC\u00f4te d'Ivoire\nCroatia\nCyprus\nCzech Republic\nDenmark\nDjibouti\nDominica\nDominican Republic\nEcuador\nEgypt\nEl Salvador\nEquatorial Guinea\nEritrea\nEstonia\nEthiopia\nFalkland Islands [Islas Malvinas]\nFaroe Islands\nFiji\nFinland\nFrance\nFrench Guiana\nFrench Polynesia\nFrench Southern Territories\nGabon\nGambia\nGeorgia\nGermany\nGhana\nGibraltar\nGreece\nGreenland\nGrenada\nGuadeloupe\nGuam\nGuatemala\nGuinea\nGuinea-Bissau\nGuyana\nHaiti\nHeard Island and McDonald Islands\nHonduras\nHong Kong\nHungary\nIceland\nIndia\nIndonesia\nIraq\nIreland\nIsrael\nItaly\nJamaica\nJapan\nJordan\nKazakhstan\nKenya\nKiribati\nKuwait\nKyrgyzstan\nLaos\nLatvia\nLebanon\nLesotho\nLiberia\nLibya\nLiechtenstein\nLithuania\nLuxembourg\nMacau\nMacedonia [FYROM]\nMadagascar\nMalawi\nMalaysia\nMaldives\nMali\nMalta\nMarshall Islands\nMartinique\nMauritania\nMauritius\nMayotte\nMexico\nMicronesia\nMoldova\nMonaco\nMongolia\nMontserrat\nMorocco\nMozambique\nNamibia\nNauru\nNepal\nNetherlands\nNetherlands Antilles\nNew Caledonia\nNew Zealand\nNicaragua\nNiger\nNigeria\nNiue\nNorfolk Island\nNorthern Mariana Islands\nNorway\nOman\nPakistan\nPalau\nPalestine\nPanama\nPapua New Guinea\nParaguay\nPeru\nPhilippines\nPitcairn Islands\nPoland\nPortugal\nPuerto Rico\nQatar\nR\u00e9union\nRomania\nRussia\nRwanda\nSaint Helena\nSaint Kitts and Nevis\nSaint Lucia\nSaint Pierre and Miquelon\nSaint Vincent and the Grenadines\nSamoa\nSan Marino\nS\u00e3o Tom\u00e9 and Pr\u00edncipe\nSaudi Arabia\nSenegal\nSeychelles\nSierra Leone\nSingapore\nSlovakia\nSlovenia\nSolomon Islands\nSomalia\nSouth Africa\nSouth Georgia and the South Sandwich Islands\nSouth Korea\nSpain\nSri Lanka\nSuriname\nSvalbard and Jan Mayen\nSwaziland\nSweden\nSwitzerland\nTaiwan\nTajikistan\nTanzania\nThailand\nTimor-Leste\nTogo\nTokelau\nTonga\nTrinidad and Tobago\nTunisia\nTurkey\nTurkmenistan\nTurks and Caicos Islands\nTuvalu\nU.S. Outlying Islands\nU.S. Virgin Islands\nUganda\nUkraine\nUnited Arab Emirates\nUnited Kingdom\nUnited States\nUruguay\nUzbekistan\nVanuatu\nVatican City\nVenezuela\nVietnam\nWallis and Futuna\nWestern Sahara\nYemen\nZambia\nZimbabwe\n\n\n\nAlso sign me up for Google Cloud emails with news, product updates, event information, special offers, and more. (Optional and you can unsubscribe at a later time).\nI understand my personal data will be processed in accordance with Google\u2019s Privacy Policy.\n\n\nSign up\n\n\n\n\nFollow our Blog\n\n\n\n\n\n\n\nSearch this siteSearch this sitesearch\n\n\n\n\n\nIncluded applications\n\nGmail\nMeet\nChat\nCalendar\nDrive\nDocs\nSheets\nSlides\nForms\nSites\nKeep\nApps Script\n\n\n\nIncluded applicationsexpand_more\n\n\n\nSecurity and management\n\nAdmin\nEndpoint\nVault\nWork Insights\n\n\n\nSecurity and managementexpand_more\n\n\n\nSolutions\n\nNew Business\nSmall Business\nEnterprise\nRetail\nManufacturing\nProfessional Services\nTechnology\nHealthcare\nGovernment\nEducation\nNonprofits\nArtificial Intelligence\n\n\n\nSolutionsexpand_more\n\n\n\nPricing\n\nCompare pricing plans\n\n\n\nPricingexpand_more\n\n\n\nAdd-ons\n\nMeet hardware\nGoogle Voice\nAppSheet\n\n\n\nAdd-onsexpand_more\n\n\n\nResources\n\nWorking remotely\nSecurity\nCustomer Stories\nFAQs\nPartners\nMarketplace\nIntegrations\nTraining & Certification\nRefer Google Workspace\n\n\n\nResourcesexpand_more\n\n\n\nLearning and support\n\nAdmin Help\nSetup and Deployment Center\nLearning Center for Users\nForums for Admins\nGoogle Workspace Dashboard\nWhat's New in Google Workspace\nFind a Google Workspace Partner\nJoin the community of IT Admins\nPress\n\n\n\nLearning and supportexpand_more\n\n\n\nMore from Google\n\nGoogle Cloud\nGoogle Domains\nChrome Enterprise\nGoogle Business Solutions\nGoogle Ads\nBusiness Messages\nJoin User Studies\n\n\n\nMore from Googleexpand_more\n\n\nGoogleAbout GoogleGoogle ProductsPrivacyTerms\n\n\n\n\nlanguageChange Language\n\n\n\n\n\nPrivacy Policy\n\nTerms\n\nCookies management controls\n\nCompare flexible pricing options for Google Workspace with plans for businesses of all sizes.",
      "error": null,
      "pricing_data": {
        "app_id": "google_slides",
        "app_name": "Google Slides",
        "app_slug": "google-slides",
        "pricing_url": "https://workspace.google.com/pricing.html",
        "source_url": null,
        "all_pricing_urls": [
          "https://workspace.google.com/pricing.html"
        ],
        "price_model_type": [
          "PriceModelType.SUBSCRIPTION"
        ],
        "has_free_tier": false,
        "has_free_trial": true,
        "free_trial_period_days": 14,
        "currency": "USD",
        "is_pricing_public": true,
        "pricing_page_accessible": true,
        "pricing_notes": "Google Slides is part of Google Workspace, and its pricing is included in the Workspace plans.",
        "pricing_tiers": [
          {
            "tier_name": "Business Starter",
            "tier_description": null,
            "monthly_price": 8.4,
            "annual_price": 7.0,
            "annual_discount_percentage": 16.67,
            "setup_fee": null,
            "features": [
              "30 GB pooled storage per user",
              "Secure custom business email",
              "Gemini AI assistant in Gmail",
              "Chat with AI in the Gemini app",
              "100 participant video meetings",
              "Security and management controls",
              "Standard Support"
            ],
            "limits": {
              "users": 300,
              "storage": "30GB",
              "operations": null,
              "api_calls": null,
              "integrations": null,
              "custom_limits": null
            }
          },
          {
            "tier_name": "Business Standard",
            "tier_description": "Most popular",
            "monthly_price": 16.8,
            "annual_price": 14.0,
            "annual_discount_percentage": 16.67,
            "setup_fee": null,
            "features": [
              "2 TB pooled storage per user",
              "Secure custom business email",
              "Gemini AI assistant in Gmail, Docs, Meet, and more",
              "Chat with AI in the Gemini app + create your team of AI experts",
              "AI research assistant (NotebookLM Plus)",
              "150 participant video meetings + recording, noise cancellation",
              "eSignature with Docs and PDFs",
              "Appointment booking pages",
              "Collaborative video creator + editor",
              "Email layouts and mail merge",
              "Security and management controls",
              "Standard Support"
            ],
            "limits": {
              "users": 300,
              "storage": "2TB",
              "operations": null,
              "api_calls": null,
              "integrations": null,
              "custom_limits": null
            }
          },
          {
            "tier_name": "Business Plus",
            "tier_description": null,
            "monthly_price": 26.4,
            "annual_price": 22.0,
            "annual_discount_percentage": 16.67,
            "setup_fee": null,
            "features": [
              "5 TB pooled storage per user",
              "Secure custom business email, eDiscovery, retention",
              "Gemini AI assistant in Gmail, Docs, Meet, and more",
              "Chat with AI in the Gemini app + create your team of AI experts",
              "AI research assistant (NotebookLM Plus)",
              "500 participant video meetings + recording, attendance tracking, noise cancellation",
              "eSignature with Docs and PDFs",
              "Appointment booking pages",
              "Collaborative video creator + editor",
              "Email layouts and mail merge",
              "Enhanced security and management controls, including Vault and advanced endpoint management",
              "Standard Support"
            ],
            "limits": {
              "users": 300,
              "storage": "5TB",
              "operations": null,
              "api_calls": null,
              "integrations": null,
              "custom_limits": null
            }
          },
          {
            "tier_name": "Enterprise",
            "tier_description": null,
            "monthly_price": null,
            "annual_price": null,
            "annual_discount_percentage": null,
            "setup_fee": null,
            "features": [
              "5 TB pooled storage per user",
              "Secure custom business email, eDiscovery, retention",
              "Gemini AI assistant in Gmail, Docs, Meet, and more",
              "Chat with AI in the Gemini app + create your team of AI experts",
              "AI research assistant (NotebookLM Plus)",
              "1000 participant video meetings + recording, attendance tracking, noise cancellation, in-domain live streaming",
              "eSignature with Docs and PDFs",
              "Appointment booking pages",
              "Collaborative video creator + editor",
              "Email layouts and mail merge",
              "Advanced security, management, and compliance controls, including Vault, DLP, data regions, and enterprise endpoint management",
              "Enhanced Support"
            ],
            "limits": {
              "users": "unlimited",
              "storage": "5TB",
              "operations": null,
              "api_calls": null,
              "integrations": null,
              "custom_limits": null
            }
          }
        ],
        "usage_based_pricing": null,
        "ai_specific_pricing": null,
        "promotional_offers": null,
        "additional_fees": null,
        "extraction_timestamp": "2025-04-15T03:20:36.768046",
        "schema_validated": true,
        "confidence_score": 100,
        "extraction_error": false,
        "json_repaired": false
      },
      "pricing_analyzed": true
    }
  ],
  "results_directory": "pricing_results\\google-slides\\20250415_032037"
}