{
  "app_name": "SafetyCulture",
  "app_slug": "safetyculture",
  "search_term": "Find the official pricing page URL for SafetyCulture (safetyculture.com). Only provide the exact URL to the pricing page, not a summary of pricing information.",
  "timestamp": 1744688461.2072837,
  "response_text": [
    "The official pricing page for SafetyCulture can be found at: [https://safetyculture.com/pricing/](https://safetyculture.com/pricing/)\u30103:0\u2020source\u3011."
  ],
  "citations": [
    {
      "title": "Pricing | SafetyCulture",
      "url": "https://safetyculture.com/pricing/"
    }
  ],
  "extracted_content": [
    {
      "url": "https://safetyculture.com/pricing/",
      "is_accessible": true,
      "content": "Pricing\nFind the right plan for your team\n\nTeam size:\n\n1-10\n11-150\n150+\n\nBill cycle:\n\nMonthly\nAnnually (save 17%)\nFree\n\nEverything you need to get started\n\n$0\n\n/ seat / month\n\nGet started\n\nIncludes:\n\nUp to 10 free seats\n\n5 active templates, unlimited inspections\n\nAnalytics\n\nTraining\n\nTasks & issue reporting\n\nUp to 3 years of data & evidence history\n\nBest value\n\nPremium\n\nImprove safety, quality, and operations with advanced tools for growing teams\n\n$24\n\n/ seat / month\n\nStart 30 day free trial\n\nAll the benefits of \u2018Free\u2019, plus:\n\nUnlimited paid seats\n\nUnlimited active inspections templates\n\nAdvanced analytics\n\nAdvanced training\n\nPermissions & access management\n\nOut-of-the-box & custom integrations\n\nAdvanced security, including SSO & SCIM\n\nUnlimited data & evidence history\n\nEnterprise\n\nPricing & services tailored to maximize impact across large organizations\n\nCustom price\nContact sales\nAdd Lite seats to any paid plan\n\nAffordable access for occasional users, built to scale\n\nFrom\n\n$5\n\n/seat / month\n\nwhen billed annually\n\nIncludes:\n\nCreate & complete training\n\nIssues\n\nActions\n\nAssets\n\nHeads Up notifications\n\n12 inspections/year\n\nView-only analytics & reports\n\nTrusted by thousands of brands globally\n\nCompare all plan features\nFree\nGet started\nPremium\nStart free trial\n\nProcess digitization & automation\n\n\n\nWeb & mobile access\n\t\n\t\n\n\nAI template builder & library\n\t\nUp to 5 active templates\n\t\nUnlimited active templates\n\n\nDigitized inspections & checklists\n\t\n\t\n\n\nReports\n\t\nPDF, Web reports\n\t\nPDF, Word , Excel, and web reports\n\n\nApproval workflow\n\t\n-\n\t\n\n\nCustom branded reports\n\t\n-\n\t\n\n\n\nWorkplace training\n\n\n\nAI course builder & library\n\t\n\t\n\n\nIn-person training\n\t\n\t\n\n\nPerformance tracking\n\t\n\t\n\n\nEngagement tools\n\t\nEssential\n\t\nCustom\n\n\nAI course translation\n\t\n-\n\t\n\n\nRecurring courses\n\t\n-\n\t\n\n\nTraining matrix\n\t\n-\n\t\n\n\n\nOperational visibility & control\n\n\n\nTask management\n\t\n\t\n\n\nObservation & issue reporting\n\t\n\t\n\n\nAsset register\n\t\n\t\n\n\nWorkplace communication\n\t\n\t\n\n\nData & evidence history\n\t\nUp to 3 years\n\t\nUnlimited\n\n\nPre-built analytics dashboard\n\t\n30 days of data\n\t\n\n\nCustom dashboard & charts\n\t\n-\n\t\n\n\n\nUser & team management\n\n\n\nTeam size\n\t\nUp to 10 seats\n\t\nUnlimited\n\n\nAdvanced access rules\n\t\n-\n\t\n\n\nAdvanced permissions\n\t\n-\n\t\n\n\nFree guest seats\n\t\n-\n\t\n\n\nSingle sign-on (SSO) & SCIM\n\t\n-\n\t\n\n\nSeat types\n\t\nFull seat only\n\t\nGuest, Lite & Full seats\n\n\n\nApps & integrations\n\n\n\nSensors & IoT\n\t\n\t\n\n\nDirect integrations\n\t\n-\n\t\n\n\nCustom integrations\n\t\n-\n\t\n\n\n\nSupport\n\n\n\nHelp Center\n\t\n\t\n\n\nEssential support\n\t\n\t\n\n\nSafetyCulture Community\n\t\n\t\n\n\nSafetyCulture Certified Course\n\t\n\t\n\n\nPriority support\n\t\n-\n\t\n\nOnboarding services and training\t\n-\n\t\nContact sales\n\nOngoing customer success services\t\n-\n\t\nContact sales\nCompare seat types on paid plans\n\nAdd members to your team based on their needs. Our seat types are flexible and economically allow you to scale.\n\nLite seat\n\nFor occasional users who only require limited access to collaborate & contribute\n\n$5\n\n/seat / month\n\nwhen billed annually\n\nFull seat\n\nFor workers & leaders getting things done, who need unlimited access & control\n\n$24\n\n/seat / month\n\nwhen billed annually\n\nInspections\t\n12 per year\n\t\nUnlimited\n\nTraining\t\nCreate, facilitate & learn\n\t\nManage groups, publish content, create & learn\n\nTask management\t\n\t\n\nObservations & issue reporting\t\n\t\n\nAsset register\n\t\nCreate and view\n\t\nManage and create\n\nAnalytics\t\nView-only\n\t\nManage and customize\n\nWorkplace communications\t\nView only\n\t\nManage, create and view\n\nPermissions\t\n-\n\t\nHow your price is calculated\n\nChoose your plan\n\nSelect the plan that works for your team.\n\nCompare plans\n+\n\nSelect your seats\n\nAssign seat types when you invite your team.\n\nCompare seat types\n=\n\nYour price\n\nUpgrade plans and seats anytime.\n\nStart 30 day free trial\nAward-winning operation, inspection and training platform\nFrequently Asked Questions\nWhich plan is best for me?\nWhat are the main differences between the Free & Premium Plan?\nWhat\u2019s the difference between seat types and plan types?\nWhat is a seat?\nWhat happens if I cancel my plan?\nCan some of my team members be on a Free Plan and some on a Premium or Enterprise Plan?\nWho pays for our plan?\nIs there a limit to the number of users I can have under my organization?\nCan I trial Premium before I pay?\nDuring my trial, is there a limit to the number of users I can add to my plan?\nAre we able to set up invoicing payment?\nWhich currencies do you offer for billing?\u00a0\n\nProduct\n\nPricing\nBook Demo\nProduct updates\nSafetyCulture (formerly iAuditor)\n\nSupport\n\nHelp Center\nPartner support\nAPI developer documentation\nDigitize your checklist\nContact us\n\nResources\n\nChecklist library\nApp & software guides\nChecklist guides\nTopic guides\neBooks\nBlog\n\nCompany\n\nAbout\nCareers\nNews room\nBrand Partnerships\nMeet the leadership team\nEvents\nStatus\nLegal\nTerms and Conditions\nPrivacy Portal\nSecurity\n\u00a9 2025\n\nTry any plan free for 30 days, no upfront commitment. Used for more than 50+ million inspections in over 80 countries.",
      "error": null,
      "pricing_data": {
        "app_id": "safetyculture",
        "app_name": "SafetyCulture",
        "app_slug": "safetyculture",
        "pricing_url": "https://www.safetyculture.com/pricing",
        "source_url": null,
        "all_pricing_urls": [
          "https://www.safetyculture.com/pricing"
        ],
        "price_model_type": [
          "PriceModelType.SUBSCRIPTION",
          "PriceModelType.FREE_TIER",
          "PriceModelType.QUOTE_BASED"
        ],
        "has_free_tier": true,
        "has_free_trial": true,
        "free_trial_period_days": 30,
        "currency": "USD",
        "is_pricing_public": true,
        "pricing_page_accessible": true,
        "pricing_notes": "SafetyCulture offers flexible pricing based on team size and seat types, with a free tier available for small teams.",
        "pricing_tiers": [
          {
            "tier_name": "Free",
            "tier_description": "Everything you need to get started",
            "monthly_price": 0.0,
            "annual_price": 0.0,
            "annual_discount_percentage": null,
            "setup_fee": null,
            "features": [
              "Up to 10 free seats",
              "5 active templates",
              "Unlimited inspections",
              "Analytics",
              "Training",
              "Tasks & issue reporting",
              "Up to 3 years of data & evidence history"
            ],
            "limits": {
              "users": 10,
              "storage": "Up to 3 years of data & evidence history",
              "operations": "Unlimited inspections",
              "api_calls": null,
              "integrations": null,
              "custom_limits": null
            }
          },
          {
            "tier_name": "Premium",
            "tier_description": "Improve safety, quality, and operations with advanced tools for growing teams",
            "monthly_price": 24.0,
            "annual_price": null,
            "annual_discount_percentage": 17.0,
            "setup_fee": null,
            "features": [
              "Unlimited paid seats",
              "Unlimited active inspections templates",
              "Advanced analytics",
              "Advanced training",
              "Permissions & access management",
              "Out-of-the-box & custom integrations",
              "Advanced security, including SSO & SCIM",
              "Unlimited data & evidence history"
            ],
            "limits": {
              "users": "Unlimited",
              "storage": "Unlimited",
              "operations": "Unlimited inspections",
              "api_calls": null,
              "integrations": "Unlimited",
              "custom_limits": null
            }
          },
          {
            "tier_name": "Enterprise",
            "tier_description": "Pricing & services tailored to maximize impact across large organizations",
            "monthly_price": null,
            "annual_price": null,
            "annual_discount_percentage": null,
            "setup_fee": null,
            "features": [
              "Custom pricing",
              "Add Lite seats to any paid plan",
              "Affordable access for occasional users, built to scale"
            ],
            "limits": {
              "users": "Unlimited",
              "storage": "Unlimited",
              "operations": "Unlimited inspections",
              "api_calls": null,
              "integrations": "Unlimited",
              "custom_limits": null
            }
          }
        ],
        "usage_based_pricing": null,
        "ai_specific_pricing": null,
        "promotional_offers": null,
        "additional_fees": [
          {
            "fee_name": "Lite Seat",
            "fee_amount": 5.0,
            "fee_description": "For occasional users who only require limited access to collaborate & contribute"
          }
        ],
        "extraction_timestamp": "2025-04-14T23:41:22.513431",
        "schema_validated": true,
        "confidence_score": 95,
        "extraction_error": false,
        "json_repaired": false
      },
      "pricing_analyzed": true
    }
  ],
  "results_directory": "pricing_results\\safetyculture\\20250414_234122"
}