{
  "app_name": "Calendly",
  "app_slug": "calendly",
  "search_term": "Find the official pricing page URL for Calendly (calendly.com). Only provide the exact URL to the pricing page, not a summary of pricing information.",
  "timestamp": 1744719076.573242,
  "response_text": [
    "The official URL for Calendly's pricing page is https://calendly.com/pricing\u30103:0\u2020source\u3011."
  ],
  "citations": [
    {
      "title": "Pricing | Calendly",
      "url": "https://calendly.com/pricing"
    }
  ],
  "extracted_content": [
    {
      "url": "https://calendly.com/pricing\u30103:0\u2020source\u3011.",
      "is_accessible": true,
      "content": "Calendly.com\n===============\n    \n\nEnglish\n\nEnglishFran\u00e7aisEspa\u00f1olDeutschPortugu\u00eas\n\n[Talk to sales](https://calendly.com/contact)\n\n[![Image 1: Calendly logo](https://marketing-assets.calendly.com/media/logo.svg)](https://calendly.com/)\n\n*   [Product](https://calendly.com/features)\n*   [Solutions](https://calendly.com/solutions)\n*   [Enterprise](https://calendly.com/solutions/enterprise)\n*   [Pricing](https://calendly.com/pricing)\n*   [Resources](https://calendly.com/resources)\n\n*   [Log In](https://calendly.com/login)[Log In](https://calendly.com/login)\n*   [Get started](https://calendly.com/signup)\n    \n\n*   [Log In](https://calendly.com/login)[Log In](https://calendly.com/login)\n*   [Get started](https://calendly.com/signup)\n    \n\n404\n\nPage not found\n==============\n\nSorry, but the page you were looking for could not be found.\n\n[Return to homepage](https://calendly.com/)\n\nLooking to explore?\n-------------------\n\nBe sure to check out some of our resources.\n\n[![Image 2: Blog Post - LinkedIn + Calendly: Never lose a meeting opportunity](https://images.ctfassets.net/k0lk9kiuza3o/7Iik2yNomV8tl5CpBWmH3j/7c1edb77d09c285b4f23bfc6b27a12a3/OG_image__1__io.png?q=85&fm=webp) LinkedIn + Calendly: Never lose a meeting opportunity Share scheduling links instantly in LinkedIn Messaging with Calendly\u2019s updated browser extension. Read now](https://calendly.com/blog/linkedin-browser-extension)\n\n[![Image 3: blog post - Now you can vote on times to schedule events AND book the meeting, all within Calendly](https://images.ctfassets.net/k0lk9kiuza3o/7iTWOEASJA8eWMuylaSwMf/525c4f79d45b7538db4009e7873ac1e2/meeting-polls-og.png?q=85&fm=webp) Introducing Meeting Polls: Now it\u2019s even easier for everyone to find time together Now you can vote on times to schedule events AND book the meeting, all within Calendly. Read now](https://calendly.com/blog/meeting-polls)\n\n[![Image 4: Calendly etiquette: How to share your scheduling link politely](https://images.ctfassets.net/k0lk9kiuza3o/4o7hVRRc7O8uuLG58hFFiY/f5217f5a88decad2385c72cad960cd79/is-calendly-rude-og.png?q=85&fm=webp) Calendly etiquette: How to share your scheduling link politely Learn the basics of scheduling etiquette. Read now](https://calendly.com/blog/is-calendly-rude)\n\nEasy ahead\u2122\n-----------\n\nWe take the work out of connecting with others so you can accomplish more.\n\n[FEATURED #### 2024 Report: The State of Meetings See the latest data on meeting culture and productivity](https://calendly.com/resources/guides/2024-state-of-meetings-report)\n\n##### Features\n\n*   [Scheduling automation](https://calendly.com/features/scheduling)\n*   [Customizable availability](https://calendly.com/features/availability)\n*   [Mobile apps](https://calendly.com/features/mobile-apps)\n*   [Browser extensions](https://calendly.com/features/browser-extensions)\n*   [Meeting routing](https://calendly.com/features/routing)\n*   [Event Types](https://calendly.com/features/event-types)\n*   [Email & website embeds](https://calendly.com/features/embed-options)\n*   [Reminders & follow-ups](https://calendly.com/features/workflows)\n*   [Meeting polls](https://calendly.com/features/meeting-polls)\n*   [Analytics](https://calendly.com/features/analytics)\n*   [Admin management](https://calendly.com/features/admin-management)\n\n##### Integrations\n\n*   [Google ecosystem](https://calendly.com/integration?search=google)\n*   [Microsoft ecosystem](https://calendly.com/integration?search=microsoft)\n*   [Calendars](https://calendly.com/integration#calendars)\n*   [Video conferencing](https://calendly.com/integration#video-conferencing)\n*   [Payments](https://calendly.com/integration#payments)\n*   [Sales & CRM](https://calendly.com/integration#sales-and-crm)\n*   [Recruiting & ATS](https://calendly.com/integration#recruiting-and-ats)\n*   [Email messaging](https://calendly.com/integration#email-messaging)\n*   [Embed Calendly](https://calendly.com/integration#embed-calendly)\n*   [Analytics](https://calendly.com/integration#analytics)\n*   [API & connectors](https://calendly.com/integration#api-and-connectors)\n*   [Security & compliance](https://calendly.com/integration#security-and-compliance)\n\n##### Calendly\n\n*   [Pricing](https://calendly.com/pricing)\n*   [Product overview](https://calendly.com/features)\n*   [Solutions](https://calendly.com/solutions)\n*   [For individuals](https://calendly.com/solutions/individuals)\n*   [For small businesses](https://calendly.com/solutions/small-business)\n*   [For enterprise](https://calendly.com/solutions/enterprise)\n*   [Compare](https://calendly.com/compare)\n*   [Security](https://calendly.com/security)\n*   [Sign up for free](https://calendly.com/signup)\n*   [Talk to sales](https://calendly.com/contact)\n*   [Get a demo](https://calendly.com/contact/demo)\n\n##### Resources\n\n*   [Help center](https://calendly.com/help)\n*   [Resource center](https://calendly.com/resources)\n*   [Blog](https://calendly.com/blog)\n*   [Customer stories](https://calendly.com/customers)\n*   [Calendly community](https://community.calendly.com/?_ga=2.256195651.97573991.1727360292-272702306.1727360288)\n*   [Developer tools](https://developer.calendly.com/?_ga=2.256195651.97573991.1727360292-272702306.1727360288)\n*   [Release notes](https://calendly.com/release-notes)\n\n##### Company\n\n*   [About us](https://calendly.com/about)\n*   [Leadership](https://calendly.com/leadership)\n*   [Careers](https://careers.calendly.com/?_ga=2.184359022.97573991.1727360292-272702306.1727360288)\n    \n    We\u2019re hiring!\n    \n*   [Newsroom](https://calendly.com/newsroom)\n*   [Become a partner](https://calendly.com/partners/contact)\n*   [Contact us](https://calendly.com/contact-us)\n\n##### Downloads\n\n[App Store](https://apps.apple.com/app/calendly-mobile/id1451094657?pt=118425599&mt=8&ct=footer&utm_source=calendly&utm_medium=marketing_site&utm_campaign=footer&utm_content=ios&utm_term=ios&l=en-us)[Google Play](https://play.google.com/store/apps/details?id=com.calendly.app&utm_source=calendly&utm_medium=marketing_site&utm_campaign=footer&utm_content=android&utm_term=android&hl=en-us)[Chrome extension](https://chromewebstore.google.com/detail/calendly-meeting-scheduli/cbhilkcodigmigfbnphipnnmamjfkipp?utm_source=calendly&utm_medium=marketing_site&utm_campaign=footer&utm_content=chrome&utm_term=chrome&hl=en-us)[Edge extension](https://microsoftedge.microsoft.com/addons/detail/calendly-meeting-schedul/hfngfpepejakabkhocoamdlnipilcpga?utm_source=calendly&utm_medium=marketing_site&utm_campaign=footer&utm_content=edge&utm_term=edge&hl=en-us)[Firefox extension](https://addons.mozilla.org/en-US/firefox/addon/calendly-meeting-scheduling/?utm_source=calendly&utm_medium=marketing_site&utm_campaign=footer&utm_content=firefox&utm_term=firefox)[Outlook add-in](https://appsource.microsoft.com/en-us/product/office/WA104381446?utm_source=calendly&utm_medium=marketing_site&utm_campaign=footer&utm_content=outlook&utm_term=outlookaddin)\n\n[](https://twitter.com/calendly)[](https://www.facebook.com/calendly)[](https://www.instagram.com/calendly/)[](https://www.linkedin.com/company/calendly/life/lifeatcalendly/)[](https://www.youtube.com/c/Calendly)\n\nEnglish\n\nEnglishFran\u00e7aisEspa\u00f1olDeutschPortugu\u00eas\n\n[Privacy Policy](https://calendly.com/legal/privacy-notice)[Legal](https://calendly.com/legal)[Status](https://www.calendlystatus.com/)Cookie settingsCookie SettingsYour Privacy Choices\n\nCopyright Calendly 2025\n\n \n\n \n\nWe respect your personal privacy\n--------------------------------\n\nWe and our partners use cookies, pixels, and similar tracking technology (all called \u201ccookies\u201d here), including necessary cookies to provide our websites and optional cookies to collect information from you (including your clicks, cursor movements, and screen recordings on our websites) for site functionality and personalization, usage analytics, and marketing. You consent to our use of all cookies by choosing \u201cl understand\u201d or continuing to use this website. You may decline optional cookies by choosing \"Do not allow cookies\". We honor opt-out preference signals. [Click here](https://calendly.com/privacy) to read about how we use your personal data.\n\nCookie settings\n\nDo not allow cookies I understand\n\n![Image 6: Company Logo](https://cdn.cookielaw.org/logos/122ecfc3-4694-42f1-863f-2db42d1b1e68/0bcbbcf4-9b83-4684-ba59-bc913c0d5905/c21bea90-f4f1-43d1-8118-8938bbb27a9d/logo.png)\n\nPrivacy Preference Center\n-------------------------\n\nWhen you visit any website, it may store or retrieve information on your browser, mostly in the form of cookies. This information might be about you, your preferences or your device and is mostly used to make the site work as you expect it to. The information does not usually directly identify you, but it can give you a more personalized web experience. Because we respect your right to privacy, you can choose not to allow some types of cookies. Click on the different category headings to find out more and change our default settings. However, blocking some types of cookies may impact your experience of the site and the services we are able to offer.\n\nAllow All\n\n### Manage Consent Preferences\n\n#### Strictly Necessary Cookies\n\nAlways Active\n\nThese cookies are necessary for the website to function and cannot be switched off in our systems. They are usually only set in response to actions made by you which amount to a request for services, such as setting your privacy preferences, logging in or filling in forms. You can set your browser to block or alert you about these cookies, but some parts of the site will not then work. These cookies do not store any personally identifiable information.\n\nCookie Details\u200e\n\n#### Functional Cookies\n\n Functional Cookies\n\nThese cookies enable the website to provide enhanced functionality and personalisation. They may be set by us or by third party providers whose services we have added to our pages. If you do not allow these cookies then some or all of these services may not function properly.\n\nCookie Details\u200e\n\n#### Performance Cookies\n\n Performance Cookies\n\nThese cookies allow us to count visits and traffic sources so we can measure and improve the performance of our site. They help us to know which pages are the most and least popular and see how visitors move around the site. All information these cookies collect is aggregated and therefore anonymous. If you do not allow these cookies we will not know when you have visited our site, and will not be able to monitor its performance.\n\nCookie Details\u200e\n\n#### Targeting Cookies\n\n Targeting Cookies\n\nThese cookies may be set through our site by our advertising partners. They may be used by those companies to build a profile of your interests and show you relevant adverts on other sites. They do not store directly personal information, but are based on uniquely identifying your browser and internet device. If you do not allow these cookies, you will experience less targeted advertising.\n\nCookie Details\u200e\n\n### Cookie List\n\n \n\nClear\n\n checkbox label label\n\nApply Cancel\n\nConsent Leg.Interest\n\n checkbox label label\n\n checkbox label label\n\n checkbox label label\n\nReject All Confirm My Choices\n\n[![Image 7: Powered by Onetrust](https://cdn.cookielaw.org/logos/static/powered_by_logo.svg)](https://www.onetrust.com/products/cookie-consent/)\n\nFind the perfect meeting time with super easy online appointment scheduling software from Calendly, and say goodbye to phone and email tag. It's 100% free, super easy to use, and you'll love our customer service.",
      "error": null,
      "pricing_data": {
        "app_id": "calendly",
        "app_name": "Calendly",
        "app_slug": "calendly",
        "pricing_url": "https://calendly.com/pricing",
        "source_url": "https://calendly.com/pricing",
        "all_pricing_urls": [
          "https://calendly.com/pricing"
        ],
        "price_model_type": [
          "PriceModelType.SUBSCRIPTION",
          "PriceModelType.FREE_TIER"
        ],
        "has_free_tier": true,
        "has_free_trial": false,
        "free_trial_period_days": null,
        "currency": "USD",
        "is_pricing_public": true,
        "pricing_page_accessible": false,
        "pricing_notes": "The pricing page was not accessible, and detailed tier information could not be extracted.",
        "pricing_tiers": null,
        "usage_based_pricing": null,
        "ai_specific_pricing": null,
        "promotional_offers": null,
        "additional_fees": null,
        "extraction_timestamp": "2025-04-15T08:11:33.466049",
        "schema_validated": true,
        "confidence_score": 85,
        "extraction_error": false,
        "json_repaired": false
      },
      "pricing_analyzed": true
    },
    {
      "url": "https://calendly.com/pricing",
      "is_accessible": true,
      "content": "English\nTalk to sales\nProduct\nSolutions\nEnterprise\nResources\nPricing\nLog In\nGet started\nProduct\nScheduling\nSimplified booking\nCalendar connections\nAvailability controls\nMeeting routing\nReminders & follow-up\nProduct overview\nWhy choose Calendly\nAutomate scheduling\nConnect your tools\nIncrease team efficiency\nWork smarter & securely\nPlatform\nIntegrations\nMobile app\nBrowser extension\nAdmin controls\nSecurity\nAnalytics\nPick the perfect plan for your team\n\nBilled monthly\n\nBilled yearly\n\nFree\n\nFor personal use\n\nAlways free\nGet started\n\nFree features:\n\nScheduling\n\n1 event type\n\nConnect 1 calendar\n\nCustomize availability\n\nAdd video conferencing\n\nCustomize your booking page\n\nMobile apps\n\nBrowser extensions\n\nStandard\n\nFor professionals and small teams\n\n$10\n/seat/mo\nSave 16%\nGet started\n\nFree features, plus:\n\nScheduling\n\nUnlimited event types\n\nConnect multiple calendars\n\nConnect Hubspot, Mailchimp\n\nConnect Stripe, Paypal\n\nConnect with Zapier, webhooks\n\nAutomate reminders\n\n24/7 chat support\n\nTeams\nRecommended plan\n\nFor growing businesses\n\n$16\n/seat/mo\nSave 20%\nTry for free\n\nStandard features, plus:\n\nScheduling\n\nSend meetings to Salesforce\n\nShare Round-robin meetings\n\nQualify & route leads\n\nConnect Hubspot, Marketo, Pardot\n\nAdvanced admin features\n\nSecurity add-on\n\nSingle Sign-On\n\nEnterprise\n\nFor large companies\n\nStarts at\n$15k\n/yr\nTalk to sales\n\nTeams features, plus:\n\nScheduling\n\nRoute with Salesforce lookup\n\nConnect Microsoft Dynamics\n\nDedicated account support\n\nSecurity\n\nEnable SSO & SAML\n\nDomain control\n\nAudit log compliance\n\nData deletion API\n\nSecurity and legal reviews\n\nCompare features\n\n\t\nFree\nAlways free\nGet started\n\t\t\nStandard\n$10\u00a0/seat/mo\nGet started\n\t\t\nTeams\n$16\u00a0/seat/mo\nTry for free\n\t\t\nEnterprise\nContact us\nTalk to sales\nScheduling\n\t\n\nOne-on-one meeting types\n\t\n\n1\n\n\t\t\n\nUnlimited\n\n\t\t\n\nUnlimited\n\n\t\t\n\nUnlimited\n\n\n\nConnect calendars\n\t\n\n1\n\n\t\t\n\n6\n\n\t\t\n\n6\n\n\t\t\n\n6\n\n\n\nUnlimited meetings\n\t\n\t\t\n\t\t\n\t\t\n\n\nCustomize your booking link\n\t\n\t\t\n\t\t\n\t\t\n\n\nMobile app & browser extension\n\t\n\t\t\n\t\t\n\t\t\n\n\nMeeting polls and one-off meetings\n\t\n\t\t\n\t\t\n\t\t\n\n\nView contact profiles and scheduling activity\n\t\n\t\t\n\t\t\n\t\t\n\n\nMulti-person meeting types\n\t\n\n\t\t\n\nUnlimited\n\n\t\t\n\nUnlimited\n\n\t\t\n\nUnlimited\n\n\n\nRound robin meeting distribution\n\t\n\n\t\t\n\n\t\t\n\nUnlimited\n\n\t\t\n\nUnlimited\n\n\n\nShare availability from contact profiles\n\t\n\n\t\t\n\t\t\n\t\t\n\n\nBook meetings on behalf of others\n\t\n\n\t\t\n\t\t\n\t\t\n\n\nAutomate meeting reminders and follow-up\n\t\n\n\t\t\n\t\t\n\t\t\n\n\nAdd a meeting cancellation policy\n\t\n\n\t\t\n\t\t\n\t\t\n\n\nCreate forms and screen invitees based on responses\n\t\n\n\t\t\n\n\t\t\n\t\t\nIntegrations\n\t\n\nGoogle, Microsoft Teams, Outlook, and Office 365 calendar integrations\n\t\n\n1\n\n\t\t\n\t\t\n\t\t\n\n\nZoom, Google Meet, Microsoft Teams and other video conferencing tools\n\t\n\t\t\n\t\t\n\t\t\n\n\nCustom webhooks to access Calendly meeting information in real-time\n\t\n\n\t\t\n\t\t\n\t\t\n\n\nStripe and PayPal for payment collection\n\t\n\n\t\t\n\t\t\n\t\t\n\n\nHubSpot, Mailchimp, and Zapier for automations\n\t\n\n\t\t\n\t\t\n\t\t\n\n\nAdd Calendly scheduling to HubSpot, Marketo, and Pardot marketing forms\n\t\n\n\t\t\n\t\t\n\t\t\n\n\nTrack conversions and booking activity with Google Analytics and Meta Pixel\n\t\n\n\t\t\n\t\t\n\t\t\n\n\nAutomate reminder workflows with Gmail and Outlook\n\t\n\n\t\t\n\t\t\n\t\t\n\n\nSync meeting data to Marketo\n\t\n\n\t\t\n\n\t\t\n\t\t\n\n\nConnect to Salesforce CRM to keep records up to date\n\t\n\n\t\t\n\n\t\t\n\t\t\n\n\nRoute by Salesforce assignment\n\t\n\n\t\t\n\n\t\t\n\n\t\t\n\n\nRoute by HubSpot assignment\n\t\n\n\t\t\n\t\t\n\t\t\n\n\nConnect integrations for your org\n\t\n\n\t\t\n\n\t\t\n\t\t\n\n\nConnect to Microsoft Dynamics 365 and Power Automate to keep records up to date\n\t\n\n\t\t\n\n\t\t\n\n\t\t\nPersonalizations\n\t\n\nCustom branding on booking page\n\t\n\t\t\n\t\t\n\t\t\n\n\nOption to remove Calendly branding\n\t\n\n\t\t\n\t\t\n\t\t\n\n\nCustomize colors when you add Calendly to your website\n\t\n\n\t\t\n\t\t\n\t\t\n\n\nCustomize your meeting confirmation pages with preferred links\n\t\n\n\t\t\n\t\t\n\t\t\nAdmin tools\n\t\n\nTeam scheduling analytics and insights\n\t\n\n\t\t\n\t\t\n\t\t\n\n\nEnforce consistent branding for your organization\n\t\n\n\t\t\n\n\t\t\n\t\t\n\n\nOrganize teams into groups and assign admins\n\t\n\n\t\t\n\n\t\t\n\t\t\n\n\nCreate admin-managed events and assign them to your team for consistency\n\t\n\n\t\t\n\n\t\t\n\t\t\nSecurity and control\n\t\n\nData deletion for compliance\n\t\n\t\t\n\t\t\n\t\t\n\n\nData Deletion API\n\t\n\n\t\t\n\n\t\t\n\n\t\t\n\n\nSAML Single Sign-On (SSO)\n\t\n\n\t\t\n\n\t\t\n\nAdd-on\n\n\t\t\n\n\nAutomate user provisioning via SCIM\n\t\n\n\t\t\n\n\t\t\n\n\t\t\n\n\nAutomate group provisioning\n\t\n\n\t\t\n\n\t\t\n\n\t\t\n\n\nDomain control and account oversight\n\t\n\n\t\t\n\n\t\t\n\n\t\t\n\n\nSecurity and legal reviews\n\t\n\n\t\t\n\n\t\t\n\n\t\t\nBusiness Support\n\t\n\nHelp center and Calendly community access\n\t\n\t\t\n\t\t\n\t\t\n\n\n24/7 Email support\n\t\n\t\t\n\t\t\n\t\t\n\n\n24/7 Chat support\n\t\n\n\t\t\n\t\t\n\t\t\n\n\nPhone support\n\t\n\n\t\t\n\n\t\t\n\n\t\t\n\n\nDedicated account support\n\t\n\n\t\t\n\n\t\t\n\n\t\t\n\n\nDedicated account onboarding and implementation\n\t\n\n\t\t\n\n\t\t\n\n\t\t\n\n\nPersonalized account milestones and success metrics\n\t\n\n\t\t\n\n\t\t\n\n\t\t\nFrequently Asked Questions\nWhat happens at the end of my trial?\nWhich plan is best for me and my team?\nCan we try Calendly with multiple users?\nWhat does the renewal process look like?\nHow do I upgrade or downgrade?\nWe\u2019re a non-profit organization, is there special pricing available?\nWhat payment methods do you accept?\nEasy access for easy bookings\n\nShare your Calendly link right from your browser, so you can schedule meetings without the back-and-forth\n\nSign up for free\nGet a demo\nEasy ahead\u2122\n\nWe take the work out of connecting with others so you can accomplish more.\n\nFEATURED\n2024 Report: The State of Meetings\nSee the latest data on meeting culture and productivity\nFeatures\nScheduling automation\nCustomizable availability\nMobile apps\nBrowser extensions\nMeeting routing\nEvent Types\nEmail & website embeds\nReminders & follow-ups\nMeeting polls\nAnalytics\nAdmin management\nIntegrations\nGoogle ecosystem\nMicrosoft ecosystem\nCalendars\nVideo conferencing\nPayments\nSales & CRM\nRecruiting & ATS\nEmail messaging\nEmbed Calendly\nAnalytics\nAPI & connectors\nSecurity & compliance\nCalendly\nPricing\nProduct overview\nSolutions\nFor individuals\nFor small businesses\nFor enterprise\nCompare\nSecurity\nSign up for free\nTalk to sales\nGet a demo\nResources\nHelp center\nResource center\nBlog\nCustomer stories\nCalendly community\nDeveloper tools\nRelease notes\nCompany\nAbout us\nLeadership\nCareers\nWe\u2019re hiring!\nNewsroom\nBecome a partner\nContact us\nDownloads\nApp Store\nGoogle Play\nChrome extension\nEdge extension\nFirefox extension\nOutlook add-in\nEnglish\nPrivacy Policy\nLegal\nStatus\nCookie Settings\nYour Privacy Choices\nCopyright Calendly 2025\nWe respect your personal privacy\nWe and our partners use cookies, pixels, and similar tracking technology (all called \u201ccookies\u201d here), including necessary cookies to provide our websites and optional cookies to collect information from you (including your clicks, cursor movements, and screen recordings on our websites) for site functionality and personalization, usage analytics, and marketing. You consent to our use of all cookies by choosing \u201cl understand\u201d or continuing to use this website. You may decline optional cookies by choosing \"Do not allow cookies\". We honor opt-out preference signals. Click here to read about how we use your personal data.\nCookie settings\nDo not allow cookies\nI understand\n\nUse Calendly for FREE or upgrade to one of our powerful plans. Choose the right Calendly for your team, no matter how small or large.",
      "error": null,
      "pricing_data": {
        "app_id": "calendly",
        "app_name": "Calendly",
        "app_slug": "calendly",
        "pricing_url": "https://calendly.com/pricing",
        "source_url": null,
        "all_pricing_urls": [
          "https://calendly.com/pricing"
        ],
        "price_model_type": [
          "PriceModelType.SUBSCRIPTION",
          "PriceModelType.FREE_TIER"
        ],
        "has_free_tier": true,
        "has_free_trial": true,
        "free_trial_period_days": 14,
        "currency": "USD",
        "is_pricing_public": true,
        "pricing_page_accessible": true,
        "pricing_notes": "Annual billing offers discounts compared to monthly billing.",
        "pricing_tiers": [
          {
            "tier_name": "Free",
            "tier_description": "For personal use",
            "monthly_price": 0.0,
            "annual_price": 0.0,
            "annual_discount_percentage": null,
            "setup_fee": null,
            "features": [
              "Scheduling",
              "1 event type",
              "Connect 1 calendar",
              "Customize availability",
              "Add video conferencing",
              "Customize your booking page",
              "Mobile apps",
              "Browser extensions"
            ],
            "limits": {
              "users": 1,
              "storage": null,
              "operations": "unlimited",
              "api_calls": null,
              "integrations": 1,
              "custom_limits": null
            }
          },
          {
            "tier_name": "Standard",
            "tier_description": "For professionals and small teams",
            "monthly_price": 10.0,
            "annual_price": 120.0,
            "annual_discount_percentage": 16.0,
            "setup_fee": null,
            "features": [
              "Scheduling",
              "Unlimited event types",
              "Connect multiple calendars",
              "Connect Hubspot, Mailchimp",
              "Connect Stripe, Paypal",
              "Connect with Zapier, webhooks",
              "Automate reminders",
              "24/7 chat support"
            ],
            "limits": {
              "users": "unlimited",
              "storage": null,
              "operations": "unlimited",
              "api_calls": null,
              "integrations": "unlimited",
              "custom_limits": null
            }
          },
          {
            "tier_name": "Teams",
            "tier_description": "Recommended plan for growing businesses",
            "monthly_price": 16.0,
            "annual_price": 192.0,
            "annual_discount_percentage": 20.0,
            "setup_fee": null,
            "features": [
              "Standard features",
              "Send meetings to Salesforce",
              "Share Round-robin meetings",
              "Qualify & route leads",
              "Connect Hubspot, Marketo, Pardot",
              "Advanced admin features",
              "Security add-on",
              "Single Sign-On"
            ],
            "limits": {
              "users": "unlimited",
              "storage": null,
              "operations": "unlimited",
              "api_calls": null,
              "integrations": "unlimited",
              "custom_limits": null
            }
          },
          {
            "tier_name": "Enterprise",
            "tier_description": "For large companies",
            "monthly_price": null,
            "annual_price": 15000.0,
            "annual_discount_percentage": null,
            "setup_fee": null,
            "features": [
              "Teams features",
              "Route with Salesforce lookup",
              "Connect Microsoft Dynamics",
              "Dedicated account support",
              "Security",
              "Enable SSO & SAML",
              "Domain control",
              "Audit log compliance",
              "Data deletion API",
              "Security and legal reviews"
            ],
            "limits": {
              "users": "unlimited",
              "storage": null,
              "operations": "unlimited",
              "api_calls": null,
              "integrations": "unlimited",
              "custom_limits": null
            }
          }
        ],
        "usage_based_pricing": null,
        "ai_specific_pricing": null,
        "promotional_offers": null,
        "additional_fees": null,
        "extraction_timestamp": "2025-04-15T08:11:51.428987",
        "schema_validated": true,
        "confidence_score": 100,
        "extraction_error": false,
        "json_repaired": false
      },
      "pricing_analyzed": true
    }
  ],
  "results_directory": "pricing_results\\calendly\\20250415_081151"
}