{
  "app_name": "Recruiterflow",
  "app_slug": "recruiterflow",
  "search_term": "Find the official pricing page URL for Recruiterflow (recruiterflow.com). Only provide the exact URL to the pricing page, not a summary of pricing information.",
  "timestamp": 1744699072.257651,
  "response_text": [
    "The official pricing page for Recruiterflow is here: [https://recruiterflow.com/pricing](https://recruiterflow.com/pricing)\u30103:0\u2020source\u3011."
  ],
  "citations": [
    {
      "title": "Transparent Pricing for Your Growing Recruitment Needs - Recruiterflow",
      "url": "https://recruiterflow.com/pricing"
    }
  ],
  "extracted_content": [
    {
      "url": "https://recruiterflow.com/pricing",
      "is_accessible": true,
      "content": "Base\n\n$99\n---\n\n/User/Month\n\nBest suited for emerging agencies beginning their recruitment operations journey.\n\nGet Base\n\nThis plan includes\n\n*   Unlimited Jobs\n*   Unlimited Candidates and Contacts\n*   Branded Careers Page\n*   Click to Call and Texting\n*   Reports\n\nMOST POPULAR\n\nPro\n\n$109\n----\n\n/User/Month\n\nGreat for agencies aiming to streamline and scale their recruitment operations.\n\nGet Pro\n\nAll Base Plan Features, plus:\n\n*   Sourcing using Chrome Extension\n*   Access Control\n*   Custom Activity\n*   Campaign Templates\n*   Multi-Channel Email and SMS Campaigns\n*   API Access\n*   RF GPT\n\nAdvanced\n\n$129\n----\n\n/User/Month\n\nCreated for agencies requiring a complete and sophisticated recruitment operations solution.\n\nGet Advanced\n\nAll Pro Plan Features, plus:\n\n*   Recruitment Automation\n*   Sales Automation\n*   Bulk Import Using Chrome Extension\n*   Auto Disqualification\n*   Automation Templates\n*   AI-powered Candidate Matching\n*   Find Similar Candidates Using AI\n*   Custom User Teams\n\n![Image 1: graphic images](https://d30417wqrqt2r9.cloudfront.net/static/css/images/yellow-circle.png)\n\nUnlimited Jobs\n\nCustomizable Drag-and-Drop Job Pipeline\n\nJob Posting and Ads On Job Boards\n\nBranded Careers Page\n\nAdvanced Resume Parsing\\*\\*Subject to fair usage\n\nCandidate and Job Advanced Search\n\nCandidate Sourcing using Chrome Extension\n\nUnlimited Contacts and Companies\n\nCustomizable Drag-and-Drop Deal Pipeline\n\nContact, Company and Deals Advanced Search\n\nPlacement Records\n\nLead Sourcing using Chrome Extension\n\nPitch Candidates (MPC)\n\nClient Portal\n\nSubsidiary Management\u2014\n\nCustom Fields for Profiles, Jobs, Deals and Placements\n\nResume Formatting\n\nBulk Field Updates\n\nDynamic Segments\n\nGmail Plugin\n\nMobile App\n\nCustom Activity\u2014\n\nCampaign Templates\u2014\n\nAutomatic Profile Refresh\u2014\n\nAccess Control\u2014\n\nBulk Import using Chrome Extension\u2014\u2014\n\nCreate Custom User Teams\u2014\u2014\n\nAutomation Templates\u2014\u2014\n\nClick to Call\n\nTexting\n\nTwo Way Email and Calendar Sync\n\nProfile Sharing With Candidates\n\nWhatsApp Integration\n\nEmail Opt Out\n\nRingCentral Integration\n\nEmail and SMS Campaigns\u2014\n\nMulti Channel Sequences\u2014\n\nKnock Out Questions\n\nWebhooks\n\nZapier Integration\n\nAPI Access\n\nRule Based Automation\u2014\u2014\n\nDynamic Segment Based Automation\u2014\u2014\n\nJob Pipeline Based Automation\u2014\u2014\n\nAuto Disqualification\u2014\u2014\n\nSales Automation\u2014\u2014\n\nJob Pipeline Reports\n\nActivity Reports\n\nSales Reports\n\nJob Placement Reports\n\nRevenue Tracking\n\nDashboards\n\nJob Description Generator\n\nJob Pitch Generator\u2014\n\nInterview Screening Assistant\u2014\n\nRF GPT\u2014\n\nAI Powered Job to Candidate Matching\u2014\u2014\n\nFind similar Candidates Using AI\u2014\u2014\n\nChat Support\n\nEmail Support\n\nHelp Center and Knowledge Base\n\nEnd-To-End Migration Assistance\\*\\*\\*\\*One time fee involved\n\nDedicated Onboarding Specialist\u2014\u2014\n\n![Image 2: Alderson loop logo](https://d30417wqrqt2r9.cloudfront.net/static/css/images/alderson-loop-logo.png)\n\n![Image 3: Ruckus logo](https://d30417wqrqt2r9.cloudfront.net/static/css/images/ruckus-logo.png)\n\n![Image 4: Remotely logo](https://d30417wqrqt2r9.cloudfront.net/static/css/images/remotely-logo.png)\n\n![Image 5: Floodgate medical logo](https://d30417wqrqt2r9.cloudfront.net/static/css/images/floodgate-medical-logo.png)\n\n![Image 6: Damia group logo](https://d30417wqrqt2r9.cloudfront.net/static/css/images/damia-logo.png)\n\n![Image 7: user images](https://d30417wqrqt2r9.cloudfront.net/static/css/images/profile-pictures/mickey-pearson.png)\n\nMickey Pearson\n\nDirector of Operations, Salmela Talent\n\nEasy-to-learn, solid software that is active and focused in rolling out new features when they are ready and not too early.\n\n![Image 8: user images](https://d30417wqrqt2r9.cloudfront.net/static/css/images/profile-pictures/daren-thornley.png)\n\nDaren Thornley\n\nFounder, Thornley Corporate Solutions\n\nExcellent feature set. The automation of daily tasks and triggered events is a life saver.\n\n![Image 9: user images](https://d30417wqrqt2r9.cloudfront.net/static/css/images/profile-pictures/james-huntingford.png)\n\nJames Huntingford\n\nMD, Sydney James Global\n\nEase of use and customer support are a big thing for my business. I absolutely love this product.\n\n![Image 10: user images](https://d30417wqrqt2r9.cloudfront.net/static/css/images/profile-pictures/lesa-iteom.png)\n\nLesa E\n\nSr Recruiting Consultant, ITEOM Talent\n\nI'm a big fan based on the speed of the system, how easy it is to customize, and all of the automation capabilities!\n\n![Image 11: user images](https://d30417wqrqt2r9.cloudfront.net/static/css/images/profile-pictures/mike-zarner.png)\n\nMike Zarnek\n\nFounder, Z-Search\n\nLove the ease of use and how it eliminates data entry. Email sequences are incredibly helpful as well.\n\n![Image 12: user images](https://d30417wqrqt2r9.cloudfront.net/static/css/images/profile-pictures/todd-baer.png)\n\nTodd Baer\n\nPresident, Todd Baer Associates\n\nI've consolidated almost all of the software I use to use to do my job, into one easy to use package\n\n![Image 13: user images](https://d30417wqrqt2r9.cloudfront.net/static/css/images/profile-pictures/tracy-nickell.png)\n\nTracy Nickell\n\nFounder, Summit Search Consultants\n\nI envy the your recruiters who join our team because they\u2019ve never had to work with another software!\n\n![Image 14: user images](https://d30417wqrqt2r9.cloudfront.net/static/css/images/profile-pictures/melvin-suen.png)\n\nMelvin Suen\n\nPrincipal, Plus10\n\nI assessed over 8 different ATS solutions, and Recruiterflow was the top choice. The product is simply beautiful to use.\n\n![Image 15: user images](https://d30417wqrqt2r9.cloudfront.net/static/css/images/profile-pictures/amanda-daering.png)\n\nAmanda Daering\n\nCEO, Newance\n\nEasy to use as a recruiter. You can click through jobs and candidates in ways that just make sense. Support is wonderful!\n\n![Image 16: graphic images](https://d30417wqrqt2r9.cloudfront.net/static/css/images/blue-circle.png)\n\nFrequently asked questions\n--------------------------\n\n###### Can I upgrade/downgrade from one plan to another?\n\nYes you can! You can upgrade or downgrade from any plan at any time without any additional cost. You will be charged according to the new plan and change your billing cycle.\n\n###### Can I pay yearly and get a discount?\n\nYes you can. Our discounted prices are mentioned in the pricing chart.\n\n###### Can I mix annual and monthly licenses or can I pick just one?\n\nYes you can. For example, if you want to purchase 5 licenses, you can purchase 3 annual and 2 monthly licenses.\n\n###### What job boards does Recruiterflow integrate with?\n\nRecruiterflow integrates with 15+ job boards like Indeed, LinkedIn, Glassdoor, ZipRecruiter, etc. You can find the complete list of all job boards at recruiterflow.com/integrations.\n\n###### Is there a training and setup fee?\n\nNope. We will setup Recruiterflow for your needs without any additional charges. No hidden charges.\n\n###### What\u2019s an email lookup?\n\nAn email lookup is when we successfully find someone's email id through our chrome extension. This is an add-on and you can purchase lookups at $20 for 100 lookups.\n\n###### Do I need a credit card to start my trial?\n\nNo you don\u2019t. You can get started with a free trial whenever you want.\n\n###### What integrations does Recruiterflow support?\n\nWe have integrations with multiple tools ranging from document management tools, workforce management tools, productivity & collaborative tools, etc. You can find the complete list of all integrations at recruiterflow.com/integrations.\n\nCompare Recruiterflow\u2019s different plans best suited for recruiting & staffing agencies and Executive Search Firms",
      "error": null,
      "pricing_data": {
        "app_id": "recruiterflow",
        "app_name": "Recruiterflow",
        "app_slug": "recruiterflow",
        "pricing_url": null,
        "source_url": null,
        "all_pricing_urls": null,
        "price_model_type": [
          "PriceModelType.SUBSCRIPTION"
        ],
        "has_free_tier": false,
        "has_free_trial": true,
        "free_trial_period_days": null,
        "currency": "USD",
        "is_pricing_public": true,
        "pricing_page_accessible": true,
        "pricing_notes": "Annual pricing discounts are available, and plans can be mixed between annual and monthly licenses.",
        "pricing_tiers": [
          {
            "tier_name": "Base",
            "tier_description": "Best suited for emerging agencies beginning their recruitment operations journey.",
            "monthly_price": 99.0,
            "annual_price": null,
            "annual_discount_percentage": null,
            "setup_fee": null,
            "features": [
              "Unlimited Jobs",
              "Unlimited Candidates and Contacts",
              "Branded Careers Page",
              "Click to Call and Texting",
              "Reports"
            ],
            "limits": null
          },
          {
            "tier_name": "Pro",
            "tier_description": "Great for agencies aiming to streamline and scale their recruitment operations.",
            "monthly_price": 109.0,
            "annual_price": null,
            "annual_discount_percentage": null,
            "setup_fee": null,
            "features": [
              "All Base Plan Features",
              "Sourcing using Chrome Extension",
              "Access Control",
              "Custom Activity",
              "Campaign Templates",
              "Multi-Channel Email and SMS Campaigns",
              "API Access",
              "RF GPT"
            ],
            "limits": null
          },
          {
            "tier_name": "Advanced",
            "tier_description": "Created for agencies requiring a complete and sophisticated recruitment operations solution.",
            "monthly_price": 129.0,
            "annual_price": null,
            "annual_discount_percentage": null,
            "setup_fee": null,
            "features": [
              "All Pro Plan Features",
              "Recruitment Automation",
              "Sales Automation",
              "Bulk Import Using Chrome Extension",
              "Auto Disqualification",
              "Automation Templates",
              "AI-powered Candidate Matching",
              "Find Similar Candidates Using AI",
              "Custom User Teams"
            ],
            "limits": null
          }
        ],
        "usage_based_pricing": [
          {
            "metric_name": "Email Lookups",
            "unit": "per 100 lookups",
            "base_price": 20.0,
            "tiers": null
          }
        ],
        "ai_specific_pricing": {
          "has_token_based_pricing": false,
          "input_token_price": null,
          "output_token_price": null,
          "models_pricing": null,
          "has_inference_pricing": false,
          "has_fine_tuning_pricing": false,
          "has_training_pricing": false,
          "ai_addon_available": true
        },
        "promotional_offers": null,
        "additional_fees": [
          {
            "fee_name": "Email Lookup",
            "fee_amount": 20.0,
            "fee_description": "Cost for 100 email lookups using the Chrome extension."
          }
        ],
        "extraction_timestamp": "2025-04-15T02:38:05.995580",
        "schema_validated": true,
        "confidence_score": 100,
        "extraction_error": false,
        "json_repaired": false
      },
      "pricing_analyzed": true
    }
  ],
  "results_directory": "pricing_results\\recruiterflow\\20250415_023806"
}