{
  "app_name": "Launch27",
  "app_slug": "launch27",
  "search_term": "Find the official pricing page URL for Launch27 (launch27.com). Only provide the exact URL to the pricing page, not a summary of pricing information.",
  "timestamp": 1744693258.1745722,
  "response_text": [
    "The official pricing page for Launch27 can be found at: [https://www.launch27.com/pricing](https://www.launch27.com/pricing)\u30103:0\u2020source\u3011."
  ],
  "citations": [
    {
      "title": "Launch27 Maid Software Pricing | Try A 14-Day Risk-Free Trial",
      "url": "https://www.launch27.com/pricing/"
    }
  ],
  "extracted_content": [
    {
      "url": "https://www.launch27.com/pricing",
      "is_accessible": true,
      "content": "Simple pricing to scale your cleaning business\n----------------------------------------------\n\n### Innovative features that help do it RIGHT\n\nSIGN UP TODAY!\n--------------\n\nMonthly and Annual options available  \n\\-15% off Annual Subscriptions\n\nBASE\n----\n\nEverything needed to launch your housecleaning business\n\n**$75**/month\n-------------\n\n$765/year (-15%)\n\n*   Unlimited Users\n*   Unlimited Bookings\n*   Customer Database\n*   Customer Tags\n*   Customer Notes\n*   Private/Internal Note tracker\n*   Cleaner Database\n*   Cleaner Tags\n*   Basic Booking form with Launch27 Branding\n*   SSL Encryption on Booking form\n*   Client List Import Tool\n*   Data Export Manager\n*   Mobile Friendly Interface\n*   Customer Login Portal\n*   Cleaner Login Portal\n*   Office Staff Login Portal\n*   Contractor Schedule Tracker\n*   Employee Schedule Tracker\n*   Booking Manager with Filters\n*   Availabilty Manager\n*   Scheduling Conflict Prevention\n*   Payroll Manager with Revenue Split & Commission reports\n*   Customizable Rescheduling & Cancellation Policy\n*   New Booking Alerts\n*   WordPress Booking Form Integration\n*   Squarespace Booking Form Integration\n*   Wix Booking Form Integration\n*   Fullsteam Integration\n*   Facebook Booking Form Integration\n*   Customizable Coupons & Discounts\n*   Day Specific Promotions\n*   Discount Tracker\n*   Automated Email Reminders for Clients\n*   Automated Welcome Email when Customers book\n*   System Alerts\n*   Client History Tracker\n*   Client Payment Tracker\n*   Customizable Email Templates\n*   Ability to calculate tax on booking form\n*   Contact Form for commercial leads\n*   Custom Form API\n*   Free Customer Support via Chat & Email\n*   Automatic Daily Schedule Sent to Teams (Email)\n\nPRO\n---\n\nGrow your housecleaning business.\n\n**$150**/month\n--------------\n\n$1,530/year (-15%)\n\n**Everything in the Base Plan plus\u2026**\n\n*   Premium Booking form with no L27 Branding\n*   Custom CSS Editor\n*   Premium Form Designer Tool\n*   Payroll Manager with Time tracking reports\n*   Google Calendar Integration\n*   Zapier Integration\n*   Google Analytics Integration\n*   Thank you page Conversion Tracking\n*   Twilio Integration\n*   Quickbooks Integration\n*   Gift Cards\n*   Gift Card Tracker Tool\n*   Automated Text Reminders for Clients\n*   Automatic Daily Schedule Sent to Teams (SMS)\n*   Horizontal Calendar\n*   Vertical Calendar\n*   Available cleaners highlighted on calendar\n*   View bookings on Map\n*   Google Maps integration with Street View\n*   Client Feedback Tracker\n*   Automated Review Requests (Only the good ones)\n*   Employee Rating System Tracker\n*   Customizable Text Message Templates\n\nPLUS\n----\n\nFully automate and scale your housecleaning business.\n\n**$299**/month\n--------------\n\n$3,049.80/year (-15%)\n\n**Everything in the Pro Plan plus\u2026  \n**\n\n*   Customer Referral Engine\n*   Booking Invitations to Teams\n*   Automatic Pre-authorization on Credit Cards\n*   Automatic Charging on Credit Cards\n*   Mobile App Access for Cleaners\n*   Mobile App Access for Admins & Office Staff\n*   Multi-lingual App (English/Spanish)\n*   Cleaner \u201cOn the Way\u201d Alerts (available in app)\n*   Cleaner Running Late Alerts (available in app)\n*   Team Check in/out Booking Alerts (available in app)\n*   Take/Store Photos (available in app)\n*   Calendars for Multiple Locations\n*   Different Pricing/Availability Based on Location\n\n### See how Launch27 is changing lives around the world\n\n### STILL ON THE FENCE\u2026\n\n### NEED MORE INFORMATION\u2026\n\n### WANT US TO HELP YOU MAKE A DECISION?\n\nWe offer maid software pricing for cleaning, housekeeping, and maid businesses of all sizes and budgets. Try Launch27 risk-free for 14 days.",
      "error": null,
      "pricing_data": {
        "app_id": "launch27",
        "app_name": "Launch27",
        "app_slug": "launch27",
        "pricing_url": null,
        "source_url": null,
        "all_pricing_urls": null,
        "price_model_type": [
          "PriceModelType.SUBSCRIPTION"
        ],
        "has_free_tier": false,
        "has_free_trial": true,
        "free_trial_period_days": 14,
        "currency": "USD",
        "is_pricing_public": true,
        "pricing_page_accessible": true,
        "pricing_notes": "Annual subscriptions offer a 15% discount compared to monthly pricing.",
        "pricing_tiers": [
          {
            "tier_name": "Base",
            "tier_description": "Everything needed to launch your housecleaning business",
            "monthly_price": 75.0,
            "annual_price": 765.0,
            "annual_discount_percentage": 15.0,
            "setup_fee": null,
            "features": [
              "Unlimited Users",
              "Unlimited Bookings",
              "Customer Database",
              "Customer Tags",
              "Customer Notes",
              "Private/Internal Note tracker",
              "Cleaner Database",
              "Cleaner Tags",
              "Basic Booking form with Launch27 Branding",
              "SSL Encryption on Booking form",
              "Client List Import Tool",
              "Data Export Manager",
              "Mobile Friendly Interface",
              "Customer Login Portal",
              "Cleaner Login Portal",
              "Office Staff Login Portal",
              "Contractor Schedule Tracker",
              "Employee Schedule Tracker",
              "Booking Manager with Filters",
              "Availabilty Manager",
              "Scheduling Conflict Prevention",
              "Payroll Manager with Revenue Split & Commission reports",
              "Customizable Rescheduling & Cancellation Policy",
              "New Booking Alerts",
              "WordPress Booking Form Integration",
              "Squarespace Booking Form Integration",
              "Wix Booking Form Integration",
              "Fullsteam Integration",
              "Facebook Booking Form Integration",
              "Customizable Coupons & Discounts",
              "Day Specific Promotions",
              "Discount Tracker",
              "Automated Email Reminders for Clients",
              "Automated Welcome Email when Customers book",
              "System Alerts",
              "Client History Tracker",
              "Client Payment Tracker",
              "Customizable Email Templates",
              "Ability to calculate tax on booking form",
              "Contact Form for commercial leads",
              "Custom Form API",
              "Free Customer Support via Chat & Email",
              "Automatic Daily Schedule Sent to Teams (Email)"
            ],
            "limits": {
              "users": "unlimited",
              "storage": "unlimited",
              "operations": "unlimited",
              "api_calls": "unlimited",
              "integrations": "unlimited",
              "custom_limits": null
            }
          },
          {
            "tier_name": "Pro",
            "tier_description": "Grow your housecleaning business.",
            "monthly_price": 150.0,
            "annual_price": 1530.0,
            "annual_discount_percentage": 15.0,
            "setup_fee": null,
            "features": [
              "Everything in the Base Plan plus\u2026",
              "Premium Booking form with no L27 Branding",
              "Custom CSS Editor",
              "Premium Form Designer Tool",
              "Payroll Manager with Time tracking reports",
              "Google Calendar Integration",
              "Zapier Integration",
              "Google Analytics Integration",
              "Thank you page Conversion Tracking",
              "Twilio Integration",
              "Quickbooks Integration",
              "Gift Cards",
              "Gift Card Tracker Tool",
              "Automated Text Reminders for Clients",
              "Automatic Daily Schedule Sent to Teams (SMS)",
              "Horizontal Calendar",
              "Vertical Calendar",
              "Available cleaners highlighted on calendar",
              "View bookings on Map",
              "Google Maps integration with Street View",
              "Client Feedback Tracker",
              "Automated Review Requests (Only the good ones)",
              "Employee Rating System Tracker",
              "Customizable Text Message Templates"
            ],
            "limits": {
              "users": "unlimited",
              "storage": "unlimited",
              "operations": "unlimited",
              "api_calls": "unlimited",
              "integrations": "unlimited",
              "custom_limits": null
            }
          },
          {
            "tier_name": "Plus",
            "tier_description": "Fully automate and scale your housecleaning business.",
            "monthly_price": 299.0,
            "annual_price": 3049.8,
            "annual_discount_percentage": 15.0,
            "setup_fee": null,
            "features": [
              "Everything in the Pro Plan plus\u2026",
              "Customer Referral Engine",
              "Booking Invitations to Teams",
              "Automatic Pre-authorization on Credit Cards",
              "Automatic Charging on Credit Cards",
              "Mobile App Access for Cleaners",
              "Mobile App Access for Admins & Office Staff",
              "Multi-lingual App (English/Spanish)",
              "Cleaner \u201cOn the Way\u201d Alerts (available in app)",
              "Cleaner Running Late Alerts (available in app)",
              "Team Check in/out Booking Alerts (available in app)",
              "Take/Store Photos (available in app)",
              "Calendars for Multiple Locations",
              "Different Pricing/Availability Based on Location"
            ],
            "limits": {
              "users": "unlimited",
              "storage": "unlimited",
              "operations": "unlimited",
              "api_calls": "unlimited",
              "integrations": "unlimited",
              "custom_limits": null
            }
          }
        ],
        "usage_based_pricing": null,
        "ai_specific_pricing": null,
        "promotional_offers": null,
        "additional_fees": null,
        "extraction_timestamp": "2025-04-15T01:01:17.044786",
        "schema_validated": null,
        "confidence_score": null,
        "extraction_error": null,
        "json_repaired": null
      },
      "pricing_analyzed": true
    },
    {
      "url": "https://www.launch27.com/pricing/",
      "is_accessible": true,
      "content": "Simple pricing to scale your cleaning business\n----------------------------------------------\n\n### Innovative features that help do it RIGHT\n\nSIGN UP TODAY!\n--------------\n\nMonthly and Annual options available  \n\\-15% off Annual Subscriptions\n\nBASE\n----\n\nEverything needed to launch your housecleaning business\n\n**$75**/month\n-------------\n\n$765/year (-15%)\n\n*   Unlimited Users\n*   Unlimited Bookings\n*   Customer Database\n*   Customer Tags\n*   Customer Notes\n*   Private/Internal Note tracker\n*   Cleaner Database\n*   Cleaner Tags\n*   Basic Booking form with Launch27 Branding\n*   SSL Encryption on Booking form\n*   Client List Import Tool\n*   Data Export Manager\n*   Mobile Friendly Interface\n*   Customer Login Portal\n*   Cleaner Login Portal\n*   Office Staff Login Portal\n*   Contractor Schedule Tracker\n*   Employee Schedule Tracker\n*   Booking Manager with Filters\n*   Availabilty Manager\n*   Scheduling Conflict Prevention\n*   Payroll Manager with Revenue Split & Commission reports\n*   Customizable Rescheduling & Cancellation Policy\n*   New Booking Alerts\n*   WordPress Booking Form Integration\n*   Squarespace Booking Form Integration\n*   Wix Booking Form Integration\n*   Fullsteam Integration\n*   Facebook Booking Form Integration\n*   Customizable Coupons & Discounts\n*   Day Specific Promotions\n*   Discount Tracker\n*   Automated Email Reminders for Clients\n*   Automated Welcome Email when Customers book\n*   System Alerts\n*   Client History Tracker\n*   Client Payment Tracker\n*   Customizable Email Templates\n*   Ability to calculate tax on booking form\n*   Contact Form for commercial leads\n*   Custom Form API\n*   Free Customer Support via Chat & Email\n*   Automatic Daily Schedule Sent to Teams (Email)\n\nPRO\n---\n\nGrow your housecleaning business.\n\n**$150**/month\n--------------\n\n$1,530/year (-15%)\n\n**Everything in the Base Plan plus\u2026**\n\n*   Premium Booking form with no L27 Branding\n*   Custom CSS Editor\n*   Premium Form Designer Tool\n*   Payroll Manager with Time tracking reports\n*   Google Calendar Integration\n*   Zapier Integration\n*   Google Analytics Integration\n*   Thank you page Conversion Tracking\n*   Twilio Integration\n*   Quickbooks Integration\n*   Gift Cards\n*   Gift Card Tracker Tool\n*   Automated Text Reminders for Clients\n*   Automatic Daily Schedule Sent to Teams (SMS)\n*   Horizontal Calendar\n*   Vertical Calendar\n*   Available cleaners highlighted on calendar\n*   View bookings on Map\n*   Google Maps integration with Street View\n*   Client Feedback Tracker\n*   Automated Review Requests (Only the good ones)\n*   Employee Rating System Tracker\n*   Customizable Text Message Templates\n\nPLUS\n----\n\nFully automate and scale your housecleaning business.\n\n**$299**/month\n--------------\n\n$3,049.80/year (-15%)\n\n**Everything in the Pro Plan plus\u2026  \n**\n\n*   Customer Referral Engine\n*   Booking Invitations to Teams\n*   Automatic Pre-authorization on Credit Cards\n*   Automatic Charging on Credit Cards\n*   Mobile App Access for Cleaners\n*   Mobile App Access for Admins & Office Staff\n*   Multi-lingual App (English/Spanish)\n*   Cleaner \u201cOn the Way\u201d Alerts (available in app)\n*   Cleaner Running Late Alerts (available in app)\n*   Team Check in/out Booking Alerts (available in app)\n*   Take/Store Photos (available in app)\n*   Calendars for Multiple Locations\n*   Different Pricing/Availability Based on Location\n\n### See how Launch27 is changing lives around the world\n\n### STILL ON THE FENCE\u2026\n\n### NEED MORE INFORMATION\u2026\n\n### WANT US TO HELP YOU MAKE A DECISION?\n\nWe offer maid software pricing for cleaning, housekeeping, and maid businesses of all sizes and budgets. Try Launch27 risk-free for 14 days.",
      "error": null,
      "pricing_data": {
        "app_id": "launch27",
        "app_name": "Launch27",
        "app_slug": "launch27",
        "pricing_url": null,
        "source_url": null,
        "all_pricing_urls": null,
        "price_model_type": [
          "PriceModelType.SUBSCRIPTION"
        ],
        "has_free_tier": false,
        "has_free_trial": true,
        "free_trial_period_days": 14,
        "currency": "USD",
        "is_pricing_public": true,
        "pricing_page_accessible": true,
        "pricing_notes": "Annual subscriptions offer a 15% discount compared to monthly pricing.",
        "pricing_tiers": [
          {
            "tier_name": "Base",
            "tier_description": "Everything needed to launch your housecleaning business",
            "monthly_price": 75.0,
            "annual_price": 765.0,
            "annual_discount_percentage": 15.0,
            "setup_fee": null,
            "features": [
              "Unlimited Users",
              "Unlimited Bookings",
              "Customer Database",
              "Customer Tags",
              "Customer Notes",
              "Private/Internal Note tracker",
              "Cleaner Database",
              "Cleaner Tags",
              "Basic Booking form with Launch27 Branding",
              "SSL Encryption on Booking form",
              "Client List Import Tool",
              "Data Export Manager",
              "Mobile Friendly Interface",
              "Customer Login Portal",
              "Cleaner Login Portal",
              "Office Staff Login Portal",
              "Contractor Schedule Tracker",
              "Employee Schedule Tracker",
              "Booking Manager with Filters",
              "Availabilty Manager",
              "Scheduling Conflict Prevention",
              "Payroll Manager with Revenue Split & Commission reports",
              "Customizable Rescheduling & Cancellation Policy",
              "New Booking Alerts",
              "WordPress Booking Form Integration",
              "Squarespace Booking Form Integration",
              "Wix Booking Form Integration",
              "Fullsteam Integration",
              "Facebook Booking Form Integration",
              "Customizable Coupons & Discounts",
              "Day Specific Promotions",
              "Discount Tracker",
              "Automated Email Reminders for Clients",
              "Automated Welcome Email when Customers book",
              "System Alerts",
              "Client History Tracker",
              "Client Payment Tracker",
              "Customizable Email Templates",
              "Ability to calculate tax on booking form",
              "Contact Form for commercial leads",
              "Custom Form API",
              "Free Customer Support via Chat & Email",
              "Automatic Daily Schedule Sent to Teams (Email)"
            ],
            "limits": {
              "users": "unlimited",
              "storage": null,
              "operations": "unlimited",
              "api_calls": null,
              "integrations": "unlimited",
              "custom_limits": null
            }
          },
          {
            "tier_name": "Pro",
            "tier_description": "Grow your housecleaning business.",
            "monthly_price": 150.0,
            "annual_price": 1530.0,
            "annual_discount_percentage": 15.0,
            "setup_fee": null,
            "features": [
              "Everything in the Base Plan plus\u2026",
              "Premium Booking form with no L27 Branding",
              "Custom CSS Editor",
              "Premium Form Designer Tool",
              "Payroll Manager with Time tracking reports",
              "Google Calendar Integration",
              "Zapier Integration",
              "Google Analytics Integration",
              "Thank you page Conversion Tracking",
              "Twilio Integration",
              "Quickbooks Integration",
              "Gift Cards",
              "Gift Card Tracker Tool",
              "Automated Text Reminders for Clients",
              "Automatic Daily Schedule Sent to Teams (SMS)",
              "Horizontal Calendar",
              "Vertical Calendar",
              "Available cleaners highlighted on calendar",
              "View bookings on Map",
              "Google Maps integration with Street View",
              "Client Feedback Tracker",
              "Automated Review Requests (Only the good ones)",
              "Employee Rating System Tracker",
              "Customizable Text Message Templates"
            ],
            "limits": {
              "users": "unlimited",
              "storage": null,
              "operations": "unlimited",
              "api_calls": null,
              "integrations": "unlimited",
              "custom_limits": null
            }
          },
          {
            "tier_name": "Plus",
            "tier_description": "Fully automate and scale your housecleaning business.",
            "monthly_price": 299.0,
            "annual_price": 3049.8,
            "annual_discount_percentage": 15.0,
            "setup_fee": null,
            "features": [
              "Everything in the Pro Plan plus\u2026",
              "Customer Referral Engine",
              "Booking Invitations to Teams",
              "Automatic Pre-authorization on Credit Cards",
              "Automatic Charging on Credit Cards",
              "Mobile App Access for Cleaners",
              "Mobile App Access for Admins & Office Staff",
              "Multi-lingual App (English/Spanish)",
              "Cleaner \u201cOn the Way\u201d Alerts (available in app)",
              "Cleaner Running Late Alerts (available in app)",
              "Team Check in/out Booking Alerts (available in app)",
              "Take/Store Photos (available in app)",
              "Calendars for Multiple Locations",
              "Different Pricing/Availability Based on Location"
            ],
            "limits": {
              "users": "unlimited",
              "storage": null,
              "operations": "unlimited",
              "api_calls": null,
              "integrations": "unlimited",
              "custom_limits": null
            }
          }
        ],
        "usage_based_pricing": null,
        "ai_specific_pricing": null,
        "promotional_offers": null,
        "additional_fees": null,
        "extraction_timestamp": "2025-04-15T01:01:34.287406",
        "schema_validated": null,
        "confidence_score": null,
        "extraction_error": null,
        "json_repaired": null
      },
      "pricing_analyzed": true
    }
  ],
  "results_directory": "pricing_results\\launch27\\20250415_010134"
}