{
  "app_name": "Bonjoro",
  "app_slug": "bonjoro",
  "search_term": "Find the official pricing page URL for Bonjoro (bonjoro.com). Only provide the exact URL to the pricing page, not a summary of pricing information.",
  "timestamp": 1744713032.7302504,
  "response_text": [
    "The official pricing page for Bonjoro is: [https://www.bonjoro.com/plans](https://www.bonjoro.com/plans)\u30103:0\u2020source\u3011."
  ],
  "citations": [
    {
      "title": "Bonjoro Video Messaging - Plans and Pricing",
      "url": "https://www.bonjoro.com/pricing"
    }
  ],
  "extracted_content": [
    {
      "url": "https://www.bonjoro.com/pricing",
      "is_accessible": true,
      "content": "### Start your journey for free. No credit card required.\n\n##### Annual\n\nSave up to 40%\n\n##### Monthly\n\n#### FREE\n\nFree forever for entrepreneurs and startups\n\n$0\n--\n\n[Get started](http://www.bonjoro.com/c/vm-starter-yearly-2023)\n\nAll Free plans include:\n\nVideo messaging\n\nCRM integrations\n\nUnlimited screen recording\n\n![Image 1](https://img.plasmic.app/img-optimizer/v1/img?src=https%3A%2F%2Fimg.plasmic.app%2Fimg-optimizer%2Fv1%2Fimg%2F1acfe871dd9a2099a8837ae89c257759.png&q=75)\n\nEverything in Free, plus:\n\nAdd your branding\n\nCTA buttons on your videos\n\n2 message templates\n\n![Image 2](https://img.plasmic.app/img-optimizer/v1/img?src=https%3A%2F%2Fimg.plasmic.app%2Fimg-optimizer%2Fv1%2Fimg%2Fe3ee9a588b085159406513602f73b2c3.png&q=75)\n\nMOST POPULAR\n\nEverything in Starter, plus:\n\nUnlimited videos\n\nVideo scheduling\n\n5 message templates\n\n![Image 3](https://img.plasmic.app/img-optimizer/v1/img?src=https%3A%2F%2Fimg.plasmic.app%2Fimg-optimizer%2Fv1%2Fimg%2F018cecb25767798ec78fea750ccc7488.png&q=75)\n\nBEST FOR TEAMS\n\nEverything in Pro, plus:\n\n3 users included\n\nSend one-to-many videos\n\nCustom domain / CNAME\n\n![Image 4](https://img.plasmic.app/img-optimizer/v1/img?src=https%3A%2F%2Fimg.plasmic.app%2Fimg-optimizer%2Fv1%2Fimg%2Fb8636956027a24e4ea91364d929178b9.png&q=75)\n\n\\*All prices are in USD\n\nThe results of our Bonjoro video emails so far have been $16,200 extra sales within 4 weeks!\n\n![Image 5](https://img.plasmic.app/img-optimizer/v1/img?src=https%3A%2F%2Fimg.plasmic.app%2Fimg-optimizer%2Fv1%2Fimg%2F06392e3ad66fa02370d783566542b7d5.jpg&w=96&q=75)\n\nChristo Hall | Owner of Basic Bananas\n\nAnnual\n\nSave up to 40%\n\nMonthly\n\nFREE\n\nSee what recording and sharing amazing videos can do for your relationships\n\n$0\n\n[Get started](http://www.bonjoro.com/c/pricing-redirect-starter-2022-yearly)\n\nAll Free plans include:\n\nSend up to 50 videos\n\nIntegrate with your tech stack\n\nUnlimited Screen Recording\n\n![Image 6](https://img.plasmic.app/img-optimizer/v1/img?src=https%3A%2F%2Fimg.plasmic.app%2Fimg-optimizer%2Fv1%2Fimg%2Fe4b6e4374d8e6942e022e0e9772ea203.png&q=75)\n\nEverything in Free, plus:\n\nSend up to 50 videos\n\nAdd your branding\n\n3 message templates\n\n![Image 7](https://img.plasmic.app/img-optimizer/v1/img?src=https%3A%2F%2Fimg.plasmic.app%2Fimg-optimizer%2Fv1%2Fimg%2F0f0e04814bc3337b3793f8b832cc9565.png&q=75)\n\nMOST POPULAR\n\nEverything in Starter, plus:\n\nSend unlimited videos\n\nBonjoro strategy session\n\n5 message templates\n\n![Image 8](https://img.plasmic.app/img-optimizer/v1/img?src=https%3A%2F%2Fimg.plasmic.app%2Fimg-optimizer%2Fv1%2Fimg%2F5c4e00be84faf4d332d80137d26b4332.png&q=75)\n\nEverything in Pro, plus:\n\nSend 1 to many videos\n\nRemove Bonjoro badge\n\nCustom domain for your videos\n\n![Image 9](https://img.plasmic.app/img-optimizer/v1/img?src=https%3A%2F%2Fimg.plasmic.app%2Fimg-optimizer%2Fv1%2Fimg%2Fed1f3b404a36321732ceebd0f5493de9.png&q=75)\n\n\\*All prices are in USD\n\nSee all inclusions\n------------------\n\n##### Personal\n\n##### Starter\n\n##### Pro\n\n##### Grrrowth\n\nVideo messaging\n\nVideo emails included\n\n50\n\nMessage templates\n\n0\n\nVideo playlists & calendar embeds\n\nSend from desktop\n\nSend from iOS/Android App\n\nSend one to many videos\n\n\\-\n\nAdd your branding\n\n\\-\n\nRemove Bonjoro badge\n\n\\-\n\nReplies via text or video\n\nTrack your results\n\nTracking & analytics\n\nSmart-scheduling (best time to send)\n\n\\-\n\nScheduled sends (you chose the time)\n\n\\-\n\nAutomated resends\n\n\\-\n\nSend from your email address\n\nCustom domains (SSL)\n\n\\+ add-on\n\nScreen recording\n\nScreen recordings included\n\nUnlimited\n\nHD video quality\n\nVideo library\n\nDownload videos\n\nVideo time limit\n\nUnlimited\n\niOS/Android apps\n\nVideo storage\n\nUnlimited\n\nPlatform features\n\nIncluded team\n\n\\-\n\nNative CRM integrations\n\nCRM attributes\n\nZapier integrations\n\nSlack integration\n\nShopify integration\n\nVideo library & hosting\n\nWorkflows\n\nUnlimited\n\nAdvanced workflow filters\n\n\\-\n\nLanguages & Regions\n\nCustom subdomains\n\n\\-\n\nTeam inbox\n\nBest in class email delivery\n\nData exports\n\n\\-\n\nAdditional team members\n\n\\+ add on\n\nWorkspaces\n\n\\-\n\nAPI calls\n\n\\-\n\nContacts\n\nUnlimited\n\nRest API\n\n\\-\n\nCustomer support\n\nLive chat support\n\n\\-\n\n1 on 1 training\n\n\\-\n\nTeam training & setup\n\n\\-\n\nGot a bigger team? Try our Company plan\n---------------------------------------\n\nEnterprise\n\nAn account managed service, for larger teams.\n\n[Book a demo](https://calendly.com/d/447-zcj-zbz/call-with-bonjoro-best-practice-strategy-demo)\n\nUnlimited videos\n\nUnlimited video templates\n\nTeam workspaces\n\nCustom domain (SSL)\n\nIncreased Roll-up limits\n\nIncreased CSV upload limits\n\n10 users included\n\nTeam training\n\nAccount manager\n\nPayment via invoice\n\nPriority support\n\nRest API access\n\n\\*All prices are in USD\n\nUnlimited videos\n\nUnlimited video templates\n\nTeam workspaces\n\nRoll-ups (1:many videos)\n\n20 users included\n\nRemove Bonjoro badge\n\nCustom domain (SSL)\n\nRest API\n\nAccount manager\n\nPriority support\n\n\\*All prices are in USD\n\nFrequently asked questions\n--------------------------\n\nPut something extra here\n\nStart your journey for free. Upgrade when you want.\nNo credit card required.",
      "error": null,
      "pricing_data": {
        "app_id": "bonjoro",
        "app_name": "Bonjoro",
        "app_slug": "bonjoro",
        "pricing_url": "http://www.bonjoro.com/c/pricing-redirect-starter-2022-yearly",
        "source_url": "http://www.bonjoro.com/c/pricing-redirect-starter-2022-yearly",
        "all_pricing_urls": [
          "http://www.bonjoro.com/c/pricing-redirect-starter-2022-yearly"
        ],
        "price_model_type": [
          "PriceModelType.SUBSCRIPTION",
          "PriceModelType.FREE_TIER"
        ],
        "has_free_tier": true,
        "has_free_trial": false,
        "free_trial_period_days": null,
        "currency": "USD",
        "is_pricing_public": true,
        "pricing_page_accessible": true,
        "pricing_notes": "Pricing includes a free tier and multiple subscription options with features scaling by tier.",
        "pricing_tiers": [
          {
            "tier_name": "Free",
            "tier_description": "Free forever for entrepreneurs and startups",
            "monthly_price": 0.0,
            "annual_price": 0.0,
            "annual_discount_percentage": null,
            "setup_fee": null,
            "features": [
              "Video messaging",
              "CRM integrations",
              "Unlimited screen recording"
            ],
            "limits": {
              "users": "unlimited",
              "storage": "unlimited",
              "operations": "unlimited",
              "api_calls": null,
              "integrations": "unlimited",
              "custom_limits": null
            }
          },
          {
            "tier_name": "Starter",
            "tier_description": "Includes branding and CTA buttons",
            "monthly_price": null,
            "annual_price": null,
            "annual_discount_percentage": 40.0,
            "setup_fee": null,
            "features": [
              "Add your branding",
              "CTA buttons on your videos",
              "2 message templates"
            ],
            "limits": {
              "users": "unlimited",
              "storage": "unlimited",
              "operations": "unlimited",
              "api_calls": null,
              "integrations": "unlimited",
              "custom_limits": null
            }
          },
          {
            "tier_name": "Pro",
            "tier_description": "Most popular tier with unlimited videos",
            "monthly_price": null,
            "annual_price": null,
            "annual_discount_percentage": 40.0,
            "setup_fee": null,
            "features": [
              "Unlimited videos",
              "Video scheduling",
              "5 message templates"
            ],
            "limits": {
              "users": "unlimited",
              "storage": "unlimited",
              "operations": "unlimited",
              "api_calls": null,
              "integrations": "unlimited",
              "custom_limits": null
            }
          },
          {
            "tier_name": "Enterprise",
            "tier_description": "For larger teams with managed services",
            "monthly_price": null,
            "annual_price": null,
            "annual_discount_percentage": null,
            "setup_fee": null,
            "features": [
              "Unlimited videos",
              "Unlimited video templates",
              "Team workspaces",
              "Custom domain (SSL)",
              "Increased Roll-up limits",
              "Increased CSV upload limits",
              "10 users included",
              "Team training",
              "Account manager",
              "Payment via invoice",
              "Priority support",
              "Rest API access"
            ],
            "limits": {
              "users": 10,
              "storage": "unlimited",
              "operations": "unlimited",
              "api_calls": "unlimited",
              "integrations": "unlimited",
              "custom_limits": null
            }
          }
        ],
        "usage_based_pricing": null,
        "ai_specific_pricing": null,
        "promotional_offers": null,
        "additional_fees": null,
        "extraction_timestamp": "2025-04-15T06:30:44.695003",
        "schema_validated": true,
        "confidence_score": 95,
        "extraction_error": false,
        "json_repaired": false
      },
      "pricing_analyzed": true
    },
    {
      "url": "https://www.bonjoro.com/plans",
      "is_accessible": true,
      "content": "![Image 1](https://static.bonjoro.com/b8335213e019484ea4b9fa8c722771aa13df9e3d/assets/images/joro/404.png)\n\n404\n\nOops! Something went wrong\u2026\n\nSorry the page you are looking for does not exist.\n\n[Return home](https://www.bonjoro.com/home)",
      "error": null,
      "pricing_data": {
        "app_id": "bonjoro",
        "app_name": "Bonjoro",
        "app_slug": "bonjoro",
        "pricing_url": null,
        "source_url": "https://static.bonjoro.com/b8335213e019484ea4b9fa8c722771aa13df9e3d/assets/images/joro/404.png",
        "all_pricing_urls": null,
        "price_model_type": [],
        "has_free_tier": false,
        "has_free_trial": false,
        "free_trial_period_days": null,
        "currency": "USD",
        "is_pricing_public": false,
        "pricing_page_accessible": true,
        "pricing_notes": "The pricing page returned a 404 error, indicating that the detailed pricing information is not accessible.",
        "pricing_tiers": null,
        "usage_based_pricing": null,
        "ai_specific_pricing": null,
        "promotional_offers": null,
        "additional_fees": null,
        "extraction_timestamp": "2025-04-15T06:30:55.960408",
        "schema_validated": null,
        "confidence_score": null,
        "extraction_error": null,
        "json_repaired": null
      },
      "pricing_analyzed": true
    }
  ],
  "results_directory": "pricing_results\\bonjoro\\20250415_063056"
}