{
  "app_name": "FunnelCockpit",
  "app_slug": "funnelcockpit",
  "search_term": "Find the official pricing page URL for FunnelCockpit (funnelcockpit.com). Only provide the exact URL to the pricing page, not a summary of pricing information.",
  "timestamp": 1744715374.5735965,
  "response_text": [
    "The official pricing page for FunnelCockpit can be accessed here: [https://www.funnelcockpit.com/preise](https://www.funnelcockpit.com/preise)\u30103:0\u2020source\u3011."
  ],
  "citations": [
    {
      "title": "FunnelCockpit Pricing - Das kostet die All-In-One Software",
      "url": "https://funnelcockpit.com/pricing/"
    }
  ],
  "extracted_content": [
    {
      "url": "https://funnelcockpit.com/pricing/",
      "is_accessible": true,
      "content": "FunnelCockpit Pricing - Das kostet die All-In-One Software\n===============\n    \n\n[![Image 1: FunnelCockpit Logo](https://static.funnelcockpit.com/upload/uXKFHDA5mnw5uNpc6/babe7d5760f634b6d8aa07f59bcea6fe.png)](https://funnelcockpit.com/)\n\n[LOGIN](https://app.funnelcockpit.com/)\n\nBist du bereit f\u00fcr\u00a0das n\u00e4chste\u00a0Level?\n\nW\u00e4hle deinen passenden Plan und teste FunnelCockpit f\u00fcr die n\u00e4chsten 14 Tage...\n\nSpare 20%!\n\nMonatlich\n\nJ\u00e4hrlich\\- 15%\n\n![Image 2](https://static.funnelcockpit.com/upload/RBQjxJBoixoW3jkEN/83d68711e039e600e8b82b27f097f7df.png)\n\nLITE\n\n**47\u20ac** / mtl.\n\n**14-Tage f\u00fcr 1 EUR testen**\n\n5 Projekte\u00a0/ Unbegrenzt Traffic\n\nFunnelBuilder  \nSeiten-Vorlagen  \nAI Generator NEU  \nVideo Player  \nVideo Funnels  \nBlog-System  \nDSGVO-Funktionen  \nE-Mail Marketing  \n1 Mitgliederbereich  \n1 Umfrage  \n\u221e Splittests  \n1 Formular  \nWebinare  \nCRM System  \nMaustracking  \nBounce-Tool  \nTeam-Funktion  \n\n[JETZT 14 TAGE TESTEN!](https://www.digistore24.com/product/98205)\n\n![Image 3](https://static.funnelcockpit.com/upload/RBQjxJBoixoW3jkEN/fdf7a0c29f7a0d9ee133bee1ac9f4826.png)\n\n**\u2728 AM MEISTEN GENUTZT!**\n\n![Image 4](https://static.funnelcockpit.com/upload/bc99388b-a161-4e2d-ab49-2d2fb7cc2519.png)\n\nSTANDARD\n\n**97\u20ac** / mtl.\n\n**14-Tage f\u00fcr 1 EUR testen**\n\n10 Projekte\u00a0/ Unbegrenzt Traffic\n\nFunnelBuilder  \nSeiten-Vorlagen  \nAI Generator NEU  \nVideo Player  \nVideo Funnels  \nBlog-System  \nDSGVO-Funktionen  \nE-Mail Marketing  \n3 Mitgliederbereiche  \n\u221e Umfragen  \n\u221e Splittests  \n3 Formulare  \n3 Webinare  \nCRM System  \nMaustracking  \nBounce-Tool  \nTeam-Funktion  \n\n[JETZT 14 TAGE TESTEN!](https://www.digistore24.com/product/98201)\n\n![Image 5](https://static.funnelcockpit.com/upload/RBQjxJBoixoW3jkEN/fdf7a0c29f7a0d9ee133bee1ac9f4826.png)\n\n![Image 6](https://static.funnelcockpit.com/upload/9ccf34dd-e554-45fb-8191-ace207aaf162.png)\n\nBUSINESS\n\n**297\u20ac** / mtl.\n\n**14-Tage f\u00fcr 1 EUR testen**\n\nUnbegrenzt Projekte\u00a0/ Unbegrenzt Traffic\n\nFunnelBuilder  \nSeiten-Vorlagen  \nAI Generator NEU  \nVideo Player  \nVideo Funnels  \nBlog-System  \nDSGVO-Funktionen  \nE-Mail Marketing  \n\u221e Mitgliederbereiche  \n\u221e Umfragen  \n\u221e Splittests  \n\u221e Formulare  \n\u221e Webinare  \nCRM System  \nMaustracking  \nBounce-Tool  \nTeam-Funktion  \n\n[JETZT 14 TAGE TESTEN!](https://www.digistore24.com/product/98203)\n\n![Image 7](https://static.funnelcockpit.com/upload/RBQjxJBoixoW3jkEN/fdf7a0c29f7a0d9ee133bee1ac9f4826.png)\n\nF.A.Q\n\n**H\u00e4ufig gestellte Fragen**\n\n*   [ ]  Was kostet FunnelCockpit?\n    \n    FunnelCockpit bietet dir verschiedene Pl\u00e4ne an. W\u00e4hle den f\u00fcr dich Passenden aus, du kannst deinen Account auch jederzeit bequem hoch- oder runterstufen. Um dich zu \u00fcberzeugen, kannst du 14 Tage f\u00fcr nur 1 \u20ac testen!\n    \n    LITE: 47\u20ac monatlich | Standard: 97\u20ac monatlich | Business: 297\u20ac monatlich\n    \n    Hinweis: Du kannst jederzeit mit einem Mausklick zum Ende des Monats (oder innerhalb der Testwochen) k\u00fcndigen.\n    \n*   [ ]  Gibt es eine Mindestlaufzeit?\n    \n    Nein! Du kannst FunnelCockpit jederzeit zum Ende des Monats k\u00fcndigen. Dazu loggst du dich in deinen FunnelCockpit Account ein und w\u00e4hlst in deinen Kontoeinstellungen die Funktion \"K\u00fcndigen\". Die K\u00fcndigung wird automatisch durchgef\u00fchrt und du erh\u00e4ltst sofort eine Best\u00e4tigungsemail. Dein Testkonto kannst du zudem auch innerhalb der 14 Tage k\u00fcndigen.\n    \n*   [ ]  Warum ist FunnelCockpit besser?\n    \n    Mit FunnelCockpit hast du alle essentiellen Marketing-Tools in einer Oberfl\u00e4che. Das steigert deine Effizienz, M\u00f6glichkeiten und deinen Umsatz. Da wir nahtlose Anbindungen aller internen Tools erm\u00f6glichen, hast du ein leicht zu bedienendes und umfangreiches System mit 100% Kompatibilit\u00e4t. Des Weiteren bieten wir deutsche Anleitungen, Support und Funktionen mit dem R\u00fccksicht auf hier geltende Gesetze und Anforderungen.  \n      \n    F\u00fcr deine unternehmerische Zukunft kannst du dir au\u00dferdem sicher sein, dass wir unser System stets weiterentwickeln und neue Technologien und M\u00f6glichkeiten implementieren. Au\u00dferdem sind wir seit 2016 am Markt und haben bis heute keine Preiserh\u00f6hung vollzogen. Wir bieten dir einen konstant bezahlbaren Preis, ohne Abstriche zu machen. Viele FunnelCockpit User sind bereits erfolgreich, vielleicht bist du der oder die N\u00e4chste?\n    \n*   [ ]  Ben\u00f6tige ich eine spezielle Software?\n    \n    Nein! Du musst nichts installieren, FunnelCockpit kannst du bequem am PC, Laptop (MacOS & Windows usw.) und sogar auch \u00fcber dein iPhone, Smartphone und Tablet benutzen. Die einzige Voraussetzung ist eine Internetverbindung. Damit kannst du dein gesamtes Business jederzeit auch von Unterwegs aus steuern, verwalten, erstellen und analysieren.\n    \n*   [ ]  Gibt es eine WordPress Integration?\n    \n    Ja! Auch wenn du alles direkt in FunnelCockpit realisieren kannst, haben wir auf Wunsch f\u00fcr WordPress ein spezielles Plugin entwickelt, das du kostenlos herunterladen und installieren kannst. So kannst du deine erstellten Funnelseiten mit wenigen Mausklicks auf deiner Domain via WordPress einbinden. Nat\u00fcrlich ist die Anbindung f\u00fcr SEO optimiert.\n    \n*   [ ]  Erhalte ich jederzeit Support?\n    \n    Ja! Unsere Support-Mitarbeiter stehen dir jederzeit \u00fcber die Support-Funktion (Live-Chat & Support-Ticket) zur Verf\u00fcgung. Au\u00dferdem befindet sich im FunnelCockpit eine ausf\u00fchrliche Dokumentation mit Video-Anleitungen f\u00fcr jegliche Tools und Funktionen.\n    \n*   [ ]  Sind E-Mail Marketing Systeme integriert?\n    \n    Ja, FunnelCockpit bietet dir eine komplette E-Mail Marketing L\u00f6sung! Du brauchst daher keine weitere E-Mail Marketing Software. Wir haben allerdings auch Anbindungen zu Drittanbietern wie Klick-Tipp, Infusionsoft, CleverReach, GetResponse, AWeber, MailChimp, WordPress, Custom HTML und viele mehr.\n    \n*   [ ]  Ist FunnelCockpit f\u00fcr Anf\u00e4nger geeignet?\n    \n    Ja! FunnelCockpit bietet dir sogar explizit als Anf\u00e4nger unglaubliche M\u00f6glichkeiten. Du kannst Webseiten erstellen ohne Programmieren zu m\u00fcssen. Auch die enthaltenden Tools k\u00f6nnen von Anf\u00e4ngern schnell und einfach umgesetzt werden. Solltest du Fragen haben, steht dir unser Support-Team jederzeit zur Verf\u00fcgung! Au\u00dferdem erh\u00e4ltst du in deinem Cockpit zahlreiche Tutorial-Videos mit Schritt-f\u00fcr-Schritt Anleitungen.\n    \n*   [ ]  Was ist mit dem Projekt/Funnel gemeint?\n    \n    Ein Projekt wird bei uns mit einer von dir definierten Domain (oder Subdomain von uns) angelegt. In einem Projekt/Funnel k\u00f6nnen beliebig viele Seiten erstellt werden. Du kannst also Funnels, Webseiten, Blogs, Mitgliederbereiche in einem Projekt gleichzeitig verwalten.\n    \n\n**Support**\n\n[Support-Mail](https://funnelcockpit.com/cdn-cgi/l/email-protection#34474144445b46407452415a5a5158575b575f445d401a575b59 \"Support E-Mail Adresse\")  \n[Tutorial-Datenbank](https://tutorials.funnelcockpit.com/ \"Video-Tutorials\")  \n[Facebook Gruppe](https://www.facebook.com/groups/FunnelCockpit \"Unsere Facebook Gruppe\")\n\n**Weitere Services**\n\n[Certified Consultant](https://certified.funnelcockpit.com/ \"Unser Zertifizierungsprogramm\")  \n[FunnelCockpit Award](https://award.funnelcockpit.com/ \"Der 1 Million Award\")  \n[Partnerprogramm](https://funnelcockpit.com/partner/ \"Das Affiliate Programm\")\n\n**Rechtliches**\n\n[Impressum](https://funnelcockpit.com/impressum/ \"Angaben zum Seitenbetreiber\")  \n[Datenschutzerkl\u00e4rung](https://funnelcockpit.com/datenschutz/ \"DSGVO & Co\")  \n[Nutzungsbedingungen](https://funnelcockpit.com/nutzungsbedingungen/ \"Unsere Nutzungsbedingungen\")  \n[Cookies](https://funnelcockpit.com/pricing/#cookie-settings)\n\n![Image 8: DSGVO Konform](https://static.funnelcockpit.com/upload/RBQjxJBoixoW3jkEN/904d7db8ebf5f671dde7559142078d2a.png)\n\n![Image 9: SSL Verschl\u00fcsselt](https://static.funnelcockpit.com/upload/RBQjxJBoixoW3jkEN/f2049c3478ea21ab30d6afad4cc49ae8.png)\n\n![Image 10: Deutscher Serverstandort](https://static.funnelcockpit.com/upload/RBQjxJBoixoW3jkEN/f5ad64b61424860cd4bb7b34844b84b2.png)\n\n\u00a9 FunnelCockpit.com - Das Original seit 2016\n\n[\u2715](https://funnelcockpit.com/pricing/#)\n\nDu m\u00f6chtest gerne wissen, welche Kosten dir bei der Nutzung der All-In-One Software FunnelCockpit entstehen? mehr erfahren...",
      "error": null,
      "pricing_data": {
        "app_id": "funnelcockpit",
        "app_name": "FunnelCockpit",
        "app_slug": "funnelcockpit",
        "pricing_url": "https://funnelcockpit.com/pricing/",
        "source_url": "https://funnelcockpit.com/pricing/",
        "all_pricing_urls": [
          "https://funnelcockpit.com/pricing/"
        ],
        "price_model_type": [
          "PriceModelType.SUBSCRIPTION"
        ],
        "has_free_tier": false,
        "has_free_trial": true,
        "free_trial_period_days": 14,
        "currency": "EUR",
        "is_pricing_public": true,
        "pricing_page_accessible": true,
        "pricing_notes": "Pricing includes a 14-day trial for 1 EUR. Annual plans offer a discount.",
        "pricing_tiers": [
          {
            "tier_name": "LITE",
            "tier_description": null,
            "monthly_price": 47.0,
            "annual_price": null,
            "annual_discount_percentage": 15.0,
            "setup_fee": null,
            "features": [
              "FunnelBuilder",
              "Seiten-Vorlagen",
              "AI Generator NEU",
              "Video Player",
              "Video Funnels",
              "Blog-System",
              "DSGVO-Funktionen",
              "E-Mail Marketing",
              "1 Mitgliederbereich",
              "1 Umfrage",
              "\u221e Splittests",
              "1 Formular",
              "Webinare",
              "CRM System",
              "Maustracking",
              "Bounce-Tool",
              "Team-Funktion"
            ],
            "limits": {
              "users": null,
              "storage": null,
              "operations": null,
              "api_calls": null,
              "integrations": null,
              "custom_limits": [
                {
                  "name": "Projects",
                  "value": 5
                },
                {
                  "name": "Traffic",
                  "value": "unlimited"
                }
              ]
            }
          },
          {
            "tier_name": "STANDARD",
            "tier_description": "Most popular tier.",
            "monthly_price": 97.0,
            "annual_price": null,
            "annual_discount_percentage": 15.0,
            "setup_fee": null,
            "features": [
              "FunnelBuilder",
              "Seiten-Vorlagen",
              "AI Generator NEU",
              "Video Player",
              "Video Funnels",
              "Blog-System",
              "DSGVO-Funktionen",
              "E-Mail Marketing",
              "3 Mitgliederbereiche",
              "\u221e Umfragen",
              "\u221e Splittests",
              "3 Formulare",
              "3 Webinare",
              "CRM System",
              "Maustracking",
              "Bounce-Tool",
              "Team-Funktion"
            ],
            "limits": {
              "users": null,
              "storage": null,
              "operations": null,
              "api_calls": null,
              "integrations": null,
              "custom_limits": [
                {
                  "name": "Projects",
                  "value": 10
                },
                {
                  "name": "Traffic",
                  "value": "unlimited"
                }
              ]
            }
          },
          {
            "tier_name": "BUSINESS",
            "tier_description": null,
            "monthly_price": 297.0,
            "annual_price": null,
            "annual_discount_percentage": 15.0,
            "setup_fee": null,
            "features": [
              "FunnelBuilder",
              "Seiten-Vorlagen",
              "AI Generator NEU",
              "Video Player",
              "Video Funnels",
              "Blog-System",
              "DSGVO-Funktionen",
              "E-Mail Marketing",
              "\u221e Mitgliederbereiche",
              "\u221e Umfragen",
              "\u221e Splittests",
              "\u221e Formulare",
              "\u221e Webinare",
              "CRM System",
              "Maustracking",
              "Bounce-Tool",
              "Team-Funktion"
            ],
            "limits": {
              "users": null,
              "storage": null,
              "operations": null,
              "api_calls": null,
              "integrations": null,
              "custom_limits": [
                {
                  "name": "Projects",
                  "value": "unlimited"
                },
                {
                  "name": "Traffic",
                  "value": "unlimited"
                }
              ]
            }
          }
        ],
        "usage_based_pricing": null,
        "ai_specific_pricing": null,
        "promotional_offers": [
          {
            "offer_name": "Annual Discount",
            "offer_description": "Save 15% on annual plans.",
            "discount_percentage": 15.0,
            "offer_url": "https://funnelcockpit.com/pricing/",
            "valid_until": null
          }
        ],
        "additional_fees": null,
        "extraction_timestamp": "2025-04-15T07:09:42.181267",
        "schema_validated": true,
        "confidence_score": 100,
        "extraction_error": false,
        "json_repaired": false
      },
      "pricing_analyzed": true
    }
  ],
  "results_directory": "pricing_results\\funnelcockpit\\20250415_070942"
}