{
  "app_name": "MailerLite",
  "app_slug": "mailerlite",
  "search_term": "Find the official pricing page URL for MailerLite (mailerlite.com). Only provide the exact URL to the pricing page, not a summary of pricing information.",
  "timestamp": 1744722608.4533608,
  "response_text": [
    "The official pricing page for MailerLite is: [https://www.mailerlite.com/pricing](https://www.mailerlite.com/pricing)\u30103:0\u2020source\u3011."
  ],
  "citations": [
    {
      "title": "Simple, Transparent Pricing - MailerLite",
      "url": "https://www.mailerlite.com/pricing"
    }
  ],
  "extracted_content": [
    {
      "url": "https://www.mailerlite.com/pricing",
      "is_accessible": true,
      "content": "EN\nPricing\n\nWe believe pricing should be straightforward, fair and affordable for all businesses.\n\nMarketing\n\nEmail, audience & automation\n\nTransactional\n\nEmail, SMS & inbound routing\n\nAll you need to grow your business online\n\nMailerLite helps you easily create newsletters, email automations, landing pages, websites, and more. Affordable and backed by 24/7 award-winning support.\n\nHow many subscribers do you have?\n500\n500\n500K\nUse the slider above\nBilled yearly\nBilled monthly\nSave 10% by paying yearly\nUSD\nEUR\nBest value\nAdvanced\n$18.00 / month\n$216.00 billed yearly for up to 500 subscribers\nTaxes may apply, learn more.\nStart free trial\nTry premium features for 30 days \nUnlimited monthly emails\nUnlimited user seats\n24/7 Live chat & email support\nAll in Growing Business, plus\nSmart sending\nFacebook integration\nCustom HTML editor\nPromotion pop-ups\nEnhanced automations\nPreference center\nAI writing assistant\nPartner discounts\nGrowing Business\n$9.00 / month\n$108.00 billed yearly for up to 500 subscribers\nTaxes may apply, learn more.\nStart free trial\nTry premium features for 30 days \nUnlimited monthly emails\n3 user seats\n24/7 Email support\nAll in Free, plus\nSell digital products\nUnlimited templates\nDynamic emails\nCampaign auto-resend\nMultivariate testing\nUnlimited websites & blogs\nUnlimited landing pages\nUnsubscribe page builder\nFree\n$0\n\nFor up to 1,000 subscribers\n\nSign up free\nTry premium features for 30 days \n12,000 monthly emails\n1 user seat\n24/7 Email & chat support for up to 30 days\nKey features\nDrag & drop editor\nEmail automation builder\nWebsites\n10 landing pages\nComparative reporting\nSignup forms & pop-ups\nEnterprise\n\nBusinesses with over 100K subscribers.\n\nLet's talk\nUnlimited user seats\n24/7 Live chat & email support\nDedicated success manager\nDedicated IP & deliverability consultation\nOnboarding consultation and training\nAccount audit and performance improvements\nSign up free\nFull pricing plan comparison\nGet a free 30-day trial of premium features | No credit card required\nShow full comparison table\nCompare plans\nAdvanced\n$18.00 / month\n$216.00 billed yearly for up to 500 subscribers\nGrowing Business\n$9.00 / month\n$108.00 billed yearly for up to 500 subscribers\nFree\n$0\nFor up to 1,000 subscribers\nSign up free\nMonthly email sends \n\tUnlimited monthly emails\tUnlimited monthly emails\t12,000 monthly emails\nSeats \n\tUnlimited\t3 seats\t1 seats\nCustom user permissions \n\t\n\t\n\t\n\nAudiences \n\tUnlimited\tUnlimited\tUnlimited\n15% off Google Workspace \n\t\n\t\n\t\nGrow your audience\nWebsites \n\tUnlimited\tUnlimited\tLimited to 1\nLanding pages \n\tUnlimited\tUnlimited\tLimited to 10\nEmbedded forms \n\tUnlimited\tUnlimited\tUnlimited\nPop-ups \n\tUnlimited\tUnlimited\tUnlimited\nPromotion pop-ups \n\t\n\t\n\t\n\nFacebook custom audiences \n\t\n\t\n\t\n\nSegmentation \n\tUnlimited\tUnlimited\tUnlimited\nInterest groups (tags) \n\tUnlimited\tUnlimited\tUnlimited\nSubscriber management \n\t\n\t\n\t\nSend amazing email campaigns\nDrag & Drop newsletter editor \n\t\n\t\n\t\n\nRich-text newsletter editor \n\t\n\t\n\t\n\nImage library \n\t\n\t\n\t\n\nMobile-friendly newsletters \n\t\n\t\n\t\n\nNewsletter templates \n\t\n\t\n\t\n\nCreate your own newsletter template \n\t\n\t\n\t\n\nRemove MailerLite Logo \n\t\n\t\n\t\n\nEdit links in sent campaigns \n\t\n\t\n\t\n\nCustom HTML newsletter editor \n\t\n\t\n\t\n\nAI writing assistant \n\t\n\t\n\t\n\nSmart sending \n\t\n\t\n\t\nAutomate your work\nEmail automation builder \n\t\n\t\n\t\n\nMultiple automation triggers \n\t\n\t\n\t\n\nEmail automation templates \n\t\n\tLimited\tLimited\nAutomation steps \n\t100\t100\t100\nRSS campaigns \n\t\n\t\n\t\n\nAPI documentation \n\t\n\t\n\t\nBuild Websites & Blogs\nWebsites \n\tUnlimited\tUnlimited\tOne website\nLanding page templates \n\t\n\t\n\t\n\nCreate your own landing page template \n\t\n\t\n\t\n\nCustom domains \n\t\n\t\n\t\n\nLanding page A/B split testing \n\t\n\t\n\t\n\nClick maps \n\t\n\t\n\t\n\nWebsite blogs \n\t\n\t\n\t\n\nPassword protected pages \n\t\n\t\n\t\n\nCustom code injection \n\t\n\t\n\t\n\nCustomizable favicon \n\t\n\t\n\t\nSell products\nSell digital products \n\t\n\t\n\t\n\nSend paid newsletters \n\t\n\t\n\t\n\nSell recurring subscriptions \n\t\n\t\n\t\n\nEcommerce integrations \n\t\n\t\n\t\nOptimize for audiences\nCustom variables \n\t\n\t\n\t\n\nEmail A/B split testing \n\t\n\t\n\t\n\nSurveys \n\t\n\t\n\t\n\nQuizzes \n\t\n\t\n\t\n\nPreview and send test emails \n\t\n\t\n\t\n\nDeliver emails by timezone \n\t\n\t\n\t\n\nDynamic email content \n\t\n\t\n\t\n\nAuto resend campaigns \n\t\n\t\n\t\n\nUnsubscribe page builder \n\t\n\t\n\t\n\nPop-up and embedded forms A/B split testing \n\t\n\t\n\t\n\nMultivariate testing \n\t\n\t\n\t\n\nPromotion pop-up A/B split testing \n\t\n\t\n\t\n\nPreference center \n\t\n\t\n\t\nAnalyze reports\nCustom date range reports \n\t\n\t\n\t\n\nComparative reporting \n\t\n\t\n\t\n\nList growth reporting \n\t\n\t\n\t\n\nIndividual subscriber profiles \n\t\n\t\n\t\n\nEmail click maps \n\t\n\t\n\t\n\nE-commerce sales tracking \n\t\n\t\n\t\n\nAutomation real-time reports \n\t\n\t\n\t\nGet support\nKnowledge base \n\t\n\t\n\t\n\nMailerLite Academy \n\t\n\t\n\t\n\nEmail support \n\t24/7 Priority\t24/7 Priority\tUp to 30 days\n24/7 Live chat support \n\t\n\t\n\tUp to 30 days\nKeeping it Lite\n\nWe don\u2019t just talk the talk, we walk the walk. MailerLite started out as a small business too! See how \u2018Keeping it Lite\u2019 has helped us build a product our customers love to use.\n\nThis is how we keep it Lite\nLeader\nFall 2024\nEasiest to Use\nFall 2024\nLeader\nSmall Business\nFall 2024\nHigh Performer\nFall 2024\nBest of 5 Email\nDeliverability\n2024\nFREQUENTLY ASKED QUESTIONS\nWhich plan is right for me?\nHow do I switch to a different plan?\nCan I stack multiple discounts or promotions?\nHow do you count subscribers?\nWhat happens when I outgrow my subscriber limit on my plan?\nWhich features will I be able to test during the 30-day full access period?\nWhat happens after the 30-day trial of premium features ends?\nHow do you protect your customer's data?\nWhere is MailerLite data stored?\nIs MailerLite GDPR compliant?\nDo you offer discounts for nonprofits?\nDo you offer any discounts for organizations seeking multiple accounts?\nI am a marketing agency/freelancer and I help small businesses. Do you have a reseller or referral program?\nI don\u2019t have much experience in marketing. Do you offer any services to help me get started?\nDo you provide assistance if I am starting an account with a large list of contacts?\nPRODUCT\nEmail marketing\nAutomations\nWebsites\nIntegrations\nCompare MailerLite\nCompare paid newsletters\nDeveloper API\nStatus\nWhat's new\nSUPPORT\nKnowledge base\nVideo tutorials\nAcademy\nHire an Expert\nMigrate to MailerLite\nSupport\nReport abuse\nCOMPANY\nAbout us\nWhy Lite\nCompany values\nJobs\nHiring\nBecome a partner\nContact us\nWall of love\nNewsroom\nLet's keep in touch\n\nSign up for our weekly email marketing newsletter and MailerLite updates.\n\nEnter your email\nSubscribe\nFor more details, review our Privacy Policy.\n2010 - 2025 \u00a9 MailerLite. All rights reserved.\nTerms of Service Privacy Policy Cookies Settings Brand Assets\n\nBUREAU VERITAS\nISO 27001 Certification\n\nGDPR Compliant\nYour data is safe with us\n\nMailerLite's pricing is straightforward, fair and affordable for all businesses. Compare the plans and choose the one that fits your needs the best!",
      "error": null,
      "pricing_data": {
        "app_id": "mailerlite",
        "app_name": "MailerLite",
        "app_slug": "mailerlite",
        "pricing_url": "https://www.mailerlite.com/pricing",
        "source_url": null,
        "all_pricing_urls": [
          "https://www.mailerlite.com/pricing"
        ],
        "price_model_type": [
          "PriceModelType.SUBSCRIPTION",
          "PriceModelType.FREE_TIER"
        ],
        "has_free_tier": true,
        "has_free_trial": true,
        "free_trial_period_days": 30,
        "currency": "USD",
        "is_pricing_public": true,
        "pricing_page_accessible": true,
        "pricing_notes": "Pricing is based on the number of subscribers, with additional features available in higher tiers.",
        "pricing_tiers": [
          {
            "tier_name": "Free",
            "tier_description": "Basic features for up to 1,000 subscribers.",
            "monthly_price": 0.0,
            "annual_price": 0.0,
            "annual_discount_percentage": null,
            "setup_fee": null,
            "features": [
              "12,000 monthly emails",
              "1 user seat",
              "24/7 Email & chat support for up to 30 days",
              "Drag & drop editor",
              "Email automation builder",
              "Websites",
              "10 landing pages",
              "Comparative reporting",
              "Signup forms & pop-ups"
            ],
            "limits": {
              "users": 1,
              "storage": null,
              "operations": "12,000 monthly emails",
              "api_calls": null,
              "integrations": null,
              "custom_limits": [
                {
                  "name": "Subscribers",
                  "value": 1000
                }
              ]
            }
          },
          {
            "tier_name": "Growing Business",
            "tier_description": "Enhanced features for growing businesses.",
            "monthly_price": 9.0,
            "annual_price": 108.0,
            "annual_discount_percentage": 10.0,
            "setup_fee": null,
            "features": [
              "Unlimited monthly emails",
              "3 user seats",
              "24/7 Email support",
              "Sell digital products",
              "Unlimited templates",
              "Dynamic emails",
              "Campaign auto-resend",
              "Multivariate testing",
              "Unlimited websites & blogs",
              "Unlimited landing pages",
              "Unsubscribe page builder"
            ],
            "limits": {
              "users": 3,
              "storage": null,
              "operations": "unlimited",
              "api_calls": null,
              "integrations": null,
              "custom_limits": [
                {
                  "name": "Subscribers",
                  "value": 500
                }
              ]
            }
          },
          {
            "tier_name": "Advanced",
            "tier_description": "Premium features for advanced needs.",
            "monthly_price": 18.0,
            "annual_price": 216.0,
            "annual_discount_percentage": 10.0,
            "setup_fee": null,
            "features": [
              "Unlimited monthly emails",
              "Unlimited user seats",
              "24/7 Live chat & email support",
              "Smart sending",
              "Facebook integration",
              "Custom HTML editor",
              "Promotion pop-ups",
              "Enhanced automations",
              "Preference center",
              "AI writing assistant",
              "Partner discounts"
            ],
            "limits": {
              "users": "unlimited",
              "storage": null,
              "operations": "unlimited",
              "api_calls": null,
              "integrations": null,
              "custom_limits": [
                {
                  "name": "Subscribers",
                  "value": 500
                }
              ]
            }
          },
          {
            "tier_name": "Enterprise",
            "tier_description": "Custom solutions for businesses with over 100K subscribers.",
            "monthly_price": null,
            "annual_price": null,
            "annual_discount_percentage": null,
            "setup_fee": null,
            "features": [
              "Unlimited user seats",
              "24/7 Live chat & email support",
              "Dedicated success manager",
              "Dedicated IP & deliverability consultation",
              "Onboarding consultation and training",
              "Account audit and performance improvements"
            ],
            "limits": {
              "users": "unlimited",
              "storage": null,
              "operations": "unlimited",
              "api_calls": null,
              "integrations": null,
              "custom_limits": [
                {
                  "name": "Subscribers",
                  "value": "over 100K"
                }
              ]
            }
          }
        ],
        "usage_based_pricing": null,
        "ai_specific_pricing": null,
        "promotional_offers": [
          {
            "offer_name": "Annual Billing Discount",
            "offer_description": "Save 10% by paying yearly.",
            "discount_percentage": 10.0,
            "offer_url": null,
            "valid_until": null
          }
        ],
        "additional_fees": null,
        "extraction_timestamp": "2025-04-15T09:10:30.622843",
        "schema_validated": true,
        "confidence_score": 100,
        "extraction_error": false,
        "json_repaired": false
      },
      "pricing_analyzed": true
    }
  ],
  "results_directory": "pricing_results\\mailerlite\\20250415_091031"
}