{
  "app_name": "Upnify",
  "app_slug": "upnify",
  "search_term": "Find the official pricing page URL for Upnify (upnify.com). Only provide the exact URL to the pricing page, not a summary of pricing information.",
  "timestamp": 1744711143.2443125,
  "response_text": [
    "The official pricing page for Upnify can be found at this URL: [https://upnify.com/en/crm/pricing.html](https://upnify.com/en/crm/pricing.html)\u30103:0\u2020source\u3011."
  ],
  "citations": [
    {
      "title": "Pricing of Upnify CRM",
      "url": "https://upnify.com/pricing-en.html"
    }
  ],
  "extracted_content": [
    {
      "url": "https://upnify.com/en/crm/pricing.html",
      "is_accessible": true,
      "content": "Blog de Upnify\n===============\n\n[![Image 2: Upnify CRM](https://upnify.com/img/logo-upnify-black.webp)](https://upnify.com/)\n\n*   Contact Us [+1 972 996 6199](tel:+19729966199) | [info@upnify.com](mailto:info@upnify.com)\n    \n*   [Language](https://upnify.com/en/crm/pricing.html#)\n    *   [Espa\u00f1ol](https://upnify.com/es/)\n    *   [English](https://upnify.com/)\n    *   [Portugu\u00eas](https://upnify.com/pt/)\n*   [Access](https://suite.upnify.com/?lang=en)\n\n*   [![Image 3: Upnify Suite](https://upnify.com/img/logo-upnify-black.webp)](https://upnify.com/)\n*   [Products](https://upnify.com/en/crm/pricing.html#)\n    *   [CRM](https://upnify.com/upnify-crm.html)\n    *   [Engage](https://upnify.com/upnify-engage.html)\n    *   [Connect](https://upnify.com/upnify-connect.html)\n*   [Industries](https://upnify.com/en/crm/pricing.html#)\n    *   [Real Estate](https://upnify.com/crm-real-estate.html)\n    *   [Education](https://upnify.com/crm-educational.html)\n    *   [Hospitality](https://upnify.com/crm-hospitality.html)\n    *   [Business servicess](https://upnify.com/crm-financial-legal-business-services.html)\n    *   [Non Profit Organizations (NGOs)](https://upnify.com/crm-non-governmental-organizations.html)\n*   [Pricing](https://upnify.com/pricing-en.html)\n*   [Resources](https://upnify.com/en/crm/pricing.html#)\n    *   [Blog](https://upnify.com/blog-en/)\n    *   [Sales Glossary](https://upnify.com/sales-glossary/)\n    *   [Marketing Glossary](https://upnify.com/marketing-glossary/)\n    *   [Success cases](https://upnify.com/success-cases-en.html)\n*   [About us](https://upnify.com/about-us.html)\n*   [Free Trial](https://upnify.com/en/crm/pricing.html#)\n*   [Language](https://upnify.com/en/crm/pricing.html#)\n    *   [Espa\u00f1ol](https://upnify.com/es/)\n    *   [English](https://upnify.com/)\n    *   [Portugu\u00eas](https://upnify.com/pt/)\n*   [Access](https://suite.upnify.com/?lang=en)\n*   [Free Trial](https://upnify.com/en/crm/pricing.html#)\n\n4 0 4\n\n![Image 4](https://upnify.com/img/error-404.png)\n\nThat's weird!\n\nWe couldn't find the page you're looking for\n\n[Back to home page](https://upnify.com/)\n\n![Image 5: salesUp](https://upnify.com/img/logo-salesup.png)\n\nJoin us to receive sales tips, free trainings and invitations to exclusive events.\n\n[](https://www.instagram.com/upnify/)\n\n[](https://www.facebook.com/UpnifyCRM)\n\nFeatures\n\n*   [CRM System](https://upnify.com/blog-en/what-should-a-crm-system-have.html)\n*   [CRM or ERP](https://upnify.com/blog-en/choosing-between-crm-and-erp.html)\n*   [Learn more about Upnify](https://upnify.com/blog-en/learn-more-about-upnify.html)\n*   [Suite functions](https://upnify.com/functions-en.html)\n*   [WhatsApp CRM](https://upnify.com/upnify-connect.html)\n*   [Live Chat Software](https://upnify.com/upnify-connect.html)\n\nResources\n\n*   [Automatically Update your CRM Exchange Rate](https://upnify.com/blog-en/automatically-update-your-crm-exchange-rate.html)\n*   [The advantages of a CRM](https://upnify.com/blog-en/the-advantages-of-a-crm-.html)\n*   [Advantages of Creating a Database](https://upnify.com/blog-en/advantages-of-creating-a-database.html)\n*   [Help Center](https://upnify.com/en/help/)\n*   [Sales Glossary](https://upnify.com/sales-glossary/)\n*   [Security Compliance](https://upnify.com/security-soc-2.html)\n\nDevelopers\n\n*   [Upnify Zapier integration](https://upnify.com/blog-en/upnify-zapier-integration.html)\n*   [Facebook Lead Ads integration](https://upnify.com/blog-en/facebook-lead-ads-integration.html)\n*   [How to use Webhooks with Upnify](https://upnify.com/blog-en/how-to-use-webhooks-with-upnify.html)\n*   [Upnify CRM Connectivity Recommendations](https://upnify.com/blog-en/upnify-crm-connectivity-recommendations.html)\n\nDownload Upnify App\n\n[![Image 6: app store](https://upnify.com/img/app-store.png)](https://apps.apple.com/us/app/upnify-crm/id1609287424)\n\n[![Image 7: google play](https://upnify.com/img/google-play.png)](https://play.google.com/store/apps/details?id=com.upnifyapp)\n\nContact us: [+1-972-996-6199](tel:+19729966199) | [info@upnify.com](mailto:info@upnify.com)\n\n\u00a9 2024 UPNIFY, LLC. All rights reserved.\n\nWe hate SPAM and love your [privacy](https://upnify.com/privacy-notice-en.html).\n\nSee our [terms and conditions](https://upnify.com/terms-conditions.html)\n\n##### Create your account!\n\nFirst Name \n\nLast Name \n\nCompany email \n\nMobile phone \n\nPassword\n\nThis account already exists.  \nPlease provide a different email or [login here](https://suite.upnify.com/).\n\nCreate account\n\nAn error has ocurred. Please, try again later.\n\nOne moment, please.\n\nOne moment...\n\nThe account associated with this email already exists.  \nPlease provide a different account or [login here](https://suite.upnify.com/).\n\nIf you like you can access through the following services:\n\n Continue with Microsoft Continue with Apple\n\nNo credit card needed.\n\n![Image 8](https://bat.bing.com/action/0?ti=97047137&Ver=2&mid=fe4f9478-9827-4906-b2c3-08c36fb890b5&bo=1&sid=45806c3019e011f0acb067248244213f&vid=4580739019e011f09ab5eb6aeb2304bf&vids=1&msclkid=N&pi=918639831&lg=en-US&sw=800&sh=600&sc=24&tl=Blog%20de%20Upnify&p=https%3A%2F%2Fupnify.com%2Fen%2Fcrm%2Fpricing.html&r=&lt=1052&evt=pageLoad&sv=1&cdb=AQAQ&rn=1089)",
      "error": null,
      "pricing_data": {
        "app_id": "upnify",
        "app_name": "Upnify",
        "app_slug": "upnify",
        "pricing_url": "https://upnify.com/pricing-en.html",
        "source_url": "https://upnify.com/en/crm/pricing.html",
        "all_pricing_urls": [
          "https://upnify.com/pricing-en.html",
          "https://upnify.com/en/crm/pricing.html"
        ],
        "price_model_type": [
          "PriceModelType.SUBSCRIPTION"
        ],
        "has_free_tier": false,
        "has_free_trial": true,
        "free_trial_period_days": null,
        "currency": "USD",
        "is_pricing_public": true,
        "pricing_page_accessible": true,
        "pricing_notes": "The pricing page was accessible but specific tier details were not provided.",
        "pricing_tiers": null,
        "usage_based_pricing": null,
        "ai_specific_pricing": null,
        "promotional_offers": null,
        "additional_fees": null,
        "extraction_timestamp": "2025-04-15T05:59:14.066614",
        "schema_validated": true,
        "confidence_score": 85,
        "extraction_error": false,
        "json_repaired": false
      },
      "pricing_analyzed": true
    },
    {
      "url": "https://upnify.com/pricing-en.html",
      "is_accessible": true,
      "content": "Contact Us\n+1 972 996 6199\n|\ninfo@upnify.com\nLanguage\nAccess\nProducts\nIndustries\nPricing\nResources\nAbout us\nFree Trial\nThe cost-effective all-in-one sales automation solution\n\nStreamline your operations effortlessly with our complete and integrated solution.\n\nRated 4.9/ 5\n\nBook a meeting\nAvailable Plans\n\nChoose the version that fits your business needs.\n\nMAX\n$35 USD\n\n$43 USD Save ~20%\n\nPer user per month, billed annually*\n\nAccess to multiple accounts\nAdvanced integrations\n5,000 emails per month **\n2,500 monthly credits for\nUpnify Engage\n250 monthly credits for\nUpnify Connect\n100 GB of storage\nspace\nPriority support\nAll PRO features\nBook a meeting\nMOST POPULAR\nPRO\n$20 USD\n\n$25 USD Save ~20%\n\nPer user per month, billed annually*\n\nAPI for developers\nAutomated quoting tools\nInvoicing\nEmail marketing\nCall recording\nAI Insights\nPhone support\nAll basic features\nBook a meeting\nBASIC\n$14 USD\n\n$17 USD Save ~20%\n\nPer user per month, billed annually*\n\nSales automation\nEmail templates\nBasic integrations\nCalendar and reminders\nBook a meeting\nJoin over 11,000 thriving businesses empowered by Upnify\u00ae\nGeneral\nFunctions\nMarketing\nAutomation\nMultichannel\nCommunication\nSales\nAutomation\nCustomized\nSupport\n\t\n\nMAX\n\n\t\n\nPOPULAR\n\nPRO\n\n\t\n\nBASIC\n\n\nCalendar, appointments, tasks, and reminders\t\t\t\nIntegration of your corporate email (Microsoft\u00ae Exchange, Google\u00ae GMail, IMAP)\t\t\tSend only\nFree app for Apple and Android devices\t\t\t\nStorage capacity for files\t100 GB\t50 GB\t10 GB\nPermission, access control, and user restrictions by level\t\t\t\nSupervision of commercial activities\t\t\t\nAutomation of quotations\t\t\t\nReports on sales, collections, conversions, geolocation, follow-ups, forecasts\t\t\t\nAPI for integration with external tools\t\t\t\nAdvanced integrations\t\t\t\nElectronic signature of documents\t\t\t\nAccess to multiple accounts\t\t\t\nUpnify\u00ae Connect\t\toptional\t\nUpnify\u00ae Engage\t\toptional\t\nFree Trial\n\nIf you purchased 1 to 3 licenses and require personalized assistance, please consult with your executive.\n* Optional services at additional cost.\n\nFrequently Asked Questions\n1. Do I have to install anything to use Upnify?\n2. Do you have a free trial period available?\n3. What happens once the free trial period ends?\n4. What is Upnify's account user limit?\n5. What kind of training does Upnify offer?\n6. Can I talk to a sales representative?\n7. Do you accept international payments?\n8. Can I pay monthly?\n9. Can I see a live demo?\n10. Is my information safe?\n11. What is the privacy policy and terms of service?\n12. What kind of computer do I need to run the Upnify CRM?\n13. Does Upnify offer refunds?\n\nWith Upnify, my organization (which operates with independent offices) has achieved a high level of customization in terms of image, communication points, action, and contact with prospects. We maintain consistency in our process, facilitating analysis, measurement, and decision-making. I consider it the most successful CRM in Latin America.\n\nPepe Villac\u00eds, Business Coach at Action Coach\u00ae\n\nJoin us to receive sales tips, free trainings and invitations to exclusive events.\n\nFeatures\n\nCRM System\nCRM or ERP\nLearn more about Upnify\nSuite functions\nWhatsApp CRM\nLive Chat Software\n\nResources\n\nAutomatically Update your CRM Exchange Rate\nThe advantages of a CRM\nAdvantages of Creating a Database\nHelp Center\nSales Glossary\nSecurity Compliance\n\nDevelopers\n\nUpnify Zapier integration\nFacebook Lead Ads integration\nHow to use Webhooks with Upnify\nUpnify CRM Connectivity Recommendations\n\nDownload Upnify App\n\nContact us: +1-972-996-6199 | info@upnify.com\n\n\u00a9 2024 UPNIFY, LLC. All rights reserved.\n\nWe hate SPAM and love your privacy.\n\nSee our terms and conditions\n\nPricing & versions of Upnify CRM.",
      "error": null,
      "pricing_data": {
        "app_id": "upnify",
        "app_name": "Upnify",
        "app_slug": "upnify",
        "pricing_url": null,
        "source_url": null,
        "all_pricing_urls": null,
        "price_model_type": [
          "PriceModelType.SUBSCRIPTION"
        ],
        "has_free_tier": false,
        "has_free_trial": true,
        "free_trial_period_days": null,
        "currency": "USD",
        "is_pricing_public": true,
        "pricing_page_accessible": true,
        "pricing_notes": "Pricing is per user per month, billed annually. Discounts are applied for annual billing.",
        "pricing_tiers": [
          {
            "tier_name": "MAX",
            "tier_description": "Advanced plan with priority support and all PRO features.",
            "monthly_price": 35.0,
            "annual_price": 420.0,
            "annual_discount_percentage": 20.0,
            "setup_fee": null,
            "features": [
              "Access to multiple accounts",
              "Advanced integrations",
              "5,000 emails per month",
              "2,500 monthly credits for Upnify Engage",
              "250 monthly credits for Upnify Connect",
              "100 GB of storage space",
              "Priority support",
              "All PRO features"
            ],
            "limits": {
              "users": "unlimited",
              "storage": "100 GB",
              "operations": null,
              "api_calls": null,
              "integrations": "unlimited",
              "custom_limits": null
            }
          },
          {
            "tier_name": "PRO",
            "tier_description": "Most popular plan with API access and AI insights.",
            "monthly_price": 20.0,
            "annual_price": 240.0,
            "annual_discount_percentage": 20.0,
            "setup_fee": null,
            "features": [
              "API for developers",
              "Automated quoting tools",
              "Invoicing",
              "Email marketing",
              "Call recording",
              "AI Insights",
              "Phone support",
              "All basic features"
            ],
            "limits": {
              "users": "unlimited",
              "storage": "50 GB",
              "operations": null,
              "api_calls": null,
              "integrations": "unlimited",
              "custom_limits": null
            }
          },
          {
            "tier_name": "BASIC",
            "tier_description": "Entry-level plan with essential sales automation features.",
            "monthly_price": 14.0,
            "annual_price": 168.0,
            "annual_discount_percentage": 20.0,
            "setup_fee": null,
            "features": [
              "Sales automation",
              "Email templates",
              "Basic integrations",
              "Calendar and reminders"
            ],
            "limits": {
              "users": "unlimited",
              "storage": "10 GB",
              "operations": null,
              "api_calls": null,
              "integrations": "limited",
              "custom_limits": null
            }
          }
        ],
        "usage_based_pricing": null,
        "ai_specific_pricing": null,
        "promotional_offers": null,
        "additional_fees": [
          {
            "fee_name": "Optional services",
            "fee_amount": null,
            "fee_description": "Optional services are available at additional cost."
          }
        ],
        "extraction_timestamp": "2025-04-15T05:59:26.771250",
        "schema_validated": true,
        "confidence_score": 100,
        "extraction_error": false,
        "json_repaired": false
      },
      "pricing_analyzed": true
    }
  ],
  "results_directory": "pricing_results\\upnify\\20250415_055927"
}