{
  "app_name": "Oneflow",
  "app_slug": "oneflow",
  "search_term": "Find the official pricing page URL for Oneflow (oneflow.com). Only provide the exact URL to the pricing page, not a summary of pricing information.",
  "timestamp": 1744707693.1499915,
  "response_text": [
    "The official pricing page for Oneflow can be found at: [https://oneflow.com/pricing](https://oneflow.com/pricing). \u30103:0\u2020source\u3011"
  ],
  "citations": [
    {
      "title": "Oneflow pricing guide - Find your flow with the right plan",
      "url": "https://oneflow.com/pricing/"
    }
  ],
  "extracted_content": [
    {
      "url": "https://oneflow.com/pricing",
      "is_accessible": true,
      "content": "Skip to content\nNEWIntroducing Oneflow AI - Join the waitlist\nGet a demo\nMenu\nProduct\n\nExplore\n\nProduct tour\nSecurity Center\nCustomer stories\nCompare\nProduct updates\n\nFeatures\n\nOneflow AI\nE-signatures\nTracking\nWorkspaces\nSolutions\n\nDepartments\n\nSales\nHR\nProcurement\nIT & Ops\n\nCompany size\n\nEnterprise\nScale\nStartup\n\nIndustry\n\nTech & Software\nConsulting\nRecruitment\nSee all\nIntegrations\n\nSales\n\nHubSpot\nSalesforce\nMicrosoft Dynamics 365\nPipedrive\nSee all\n\nHR & Recruitment\n\nTeamtailor\nHiBob\nJobylon\nSeven20\nSee all\n\nAutomation & Productivity\n\nSlack\nZapier\nPower Automate\nGoogle Workspace\nSee all\nResources\n\nGet inspired\n\nBlog\nEvents\nOneflow Creator Program\nPodcast\n\nLearn\n\nGlossary\nThe State of Contracts Report\nAcademy & Onboarding\nFAQ\n\nBusiness templates\n\nSales Agreement\nPurchase Agreement\nNon-Disclosure Agreement\nSee all\nPricing\n\ud83c\uddf3\ud83c\uddf4 Norsk\n\ud83c\uddeb\ud83c\uddee Suomi\n\ud83c\uddf8\ud83c\uddea Svenska\n\ud83c\udde9\ud83c\uddf0 Dansk\n\ud83c\uddeb\ud83c\uddf7 Fran\u00e7ais\n\ud83c\uddf3\ud83c\uddf1 Nederlands\n\ud83c\uddea\ud83c\uddf8 Espa\u00f1ol\n\ud83c\uddf5\ud83c\uddf9 Portugu\u00eas\n\ud83c\udde9\ud83c\uddea Deutsch\n\ud83c\uddec\ud83c\udde7 English (UK)\n\ud83c\uddfa\ud83c\uddf8 English (US)\nCompany\nSupport\nInvestors\nBuy now\nTry for free\n\nHome >\n\nGet started!\n\nFind your flow with the right plan.\n\nYearly\nMonthly\nSave up to 17% with annual plans\nINR\nDKK\nEUR\nGBP\nNOK\nSEK\nUSD\nAUD\nNZD\nCAD\nFree\n14 day access to premium features. After the trial expires the basic Oneflow features will remain.\nFree\nforever\n\ud83c\udf89 No payment card required\nTry Oneflow for free\nIncludes:\nPDF contracts\nUpload, send and e-sign PDF documents with legally binding e-signatures\nComments\nTrack activities and get notified of any comments or updates\nAudit trail\nSee all the updates made to a contract in one place\nData portability\nImport or export all your contracts in Oneflow\nDashboards\nSee important KPIs about your contracts on a dashboard\nEssentials\nFor those freeing themselves from the PDF friction. Be more effective with digital contracts. Work faster.\n$17\n\n\n/ month per user\nBook a demo\nIncludes Free plan plus:\nDigital contracts\nCreate, collaborate live, send and e-sign interactive web-based contracts with legally binding e-signatures\nContract templates\nCreate, share and manage templates for contracts you send over and over again\nContract insights\nTrack engagement in the contract such as visits, opens, and more\nStandard integrations\nPlug and play integrations with many systems\nContract calendar\nVisualize contracts based on their lifecycle events in a calendar view\nMost popular\nBusiness\nFor teams seeking the magic of flow. Unlock and use the data inside your contracts. All systems are in sync.\n$45\n\n\n/ month per user\nBook a demo\nIncludes Essentials plus:\nLifecycle\nConfigure lifecycle rules for your contracts and get notified on lifecycle events\nTags\nAdd tags to contracts and templates to make them easier to find\nData retention\nConfigure data retention policies to avoid any information being stored passed its allowed time\nPremium integrations ($)\nPlug and play integrations with Salesforce, HubSpot and Microsoft Dynamics\nEnterprise\nFor global teams with true digital ambitions. Scale the power of flow to all teams. Unleash contract magic.\nLet\u2019s talk\n\n\n\u00a0\nContact sales\nIncludes Business plus:\nShared templates\nShare templates across different workspaces\nGroups\nOrganize users in groups for better access management\nSingle sign-on (SSO)\nConnect Oneflow to your own identity provider and utilize your own authentication policies\nSCIM API\nIntegrate your identity provisioning processes with our integrations smoothly\nCompare Plans\nJoin these companies making business flow\nCan Oneflow help you save time and money?\n\nOneflow provides a range of benefits that can help organizations save time and money across the contract lifecycle.\n\nDiscover the ROI of Oneflow\nWe love startups!\nScale your business with digital contracts at startup-friendly prices. Tell us about your startup and we\u2019ll be in touch.\nTell us about your startup\nAPI and web forms\nUse our API to automate contract workflows across all your systems. Make contract data processable and useful.\nMessage our team\nCall +46 8 517 297 70\nStart using Oneflow\nIs Oneflow free?\n\nWe have a free plan that allows users to send, track and sign as many PDF contracts as possible. So if you\u2019re happy with just signing PDF contracts, the answer is yes, it\u2019s free. Forever.\n\nWhat is the difference between free and trial accounts?\n\nWith our free plan, you can upload, send, track, and sign unlimited PDF contracts. However, with the free plan, you\u2019ll not be able to enjoy the full experience of contract magic.\n\nThat\u2019s why we also provide a trial of the full Oneflow experience for 14 days with no charge. With a trial account, you can try all the features our paid users love. For example, our contract editor. You can create stunning web-based contracts and make edits live, even after you\u2019ve sent.\n\nWhat happens after my trial ends?\n\nYour trial account will expire automatically after 14 days. Don\u2019t worry, you\u2019ll still be able to log into your account or access your contracts. After the trial, you\u2019ll automatically be in our free plan.\n\n\nHow can I extend my trial?\n\nFeel free to do so in the Oneflow app on your own by clicking on \u201cUpgrade\u201d. You can also leave us a message here.\n\nWhat kind of onboarding support can I expect?\n\nEvery user starts by attending an onboarding session facilitated by our friendly customer care team to run through the basics. We also have a comprehensive Help Center with all the how tos and tutorials that you need to get started. And you can always email us with your questions. Depending on your tier, you may also get a dedicated customer success manager to help with any questions you may have.\n\nScale up or down\n\nThere\u2019s no need to commit to a huge investment for a perpetual license with our flexible SaaS platform and subscription-based pricing.\n\nSafer contracts\n\nIt all boils down to this. Managing your contracts on one platform, in one place, is way more secure than storing in binders or folders that are hard to keep track of.\n\nCustomer support\nEmail, chat and phone support\n\nGot questions, feedback, or want to bounce your ideas off us? Reach out to us anytime. We\u2019d love to hear from you.\u00a0\n\n\u00a0\n\nHelp and training\n\nJoin our weekly Oneflow Academy webinar or get a personalized training. Or, if you want to go at your own pace, find comprehensive resources on our Help Center.\u00a0\n\n\u00a0\n\nExperts on-hand\n\nOur skilled team of business and technical experts are passionate about solving your challenges. We\u2019ll make sure you get the help you need to be successful.\n\nHave other questions?\n\nIf you have more questions on our pricing and plans, contact us so we can help.\n\nContact us\nCall +46 8 517 297 70\nDon\u2019t just take our word for it\u2026\n\n\u201cFrom board meeting protocols to GDPR agreements, and approval of keycards \u2014 Oneflow has removed the pains we weren\u2019t even aware of.\u201d\n\nRead full story\n\nTor Myhrman\n\nHead of Indirect Sourcing\n\nSystembolaget\n\n\u201cThe fact that Oneflow is 100% digital makes it so simple and flexible. It gives us peace of mind by providing control and a complete overview of our contract process at all times.\u201d\n\nRead full story\n\nElin Skoglund\n\nHR Business Partner\n\nHedin Bil\n\n\u201cOneflow is secure and really easy to use. It just works and saves us so much time. But, most importantly, we trust Oneflow with our documents because it meets our high security requirements.\u201d\n\nRead full story\n\nTobias T\u00f6rnqvist\n\nHR Specialist\n\nL\u00e4nsf\u00f6rs\u00e4kringar \u00c4lvsborg\n\n\u201cIt took 12 minutes from calling the prospect to him receiving the proposal. I swear he \u2018almost fainted\u2019 when he saw how fast we could send a proposal.\u201d\n\nRead full story\n\nAnders Berghagen\n\nSales & Marketing Director\n\nDormakaba\n\n\u201cIt saves time and removes irritation. Before Oneflow, we spent a lot of time on coordinating, administrating, and booking time for signing. We immediately cut our lead times with this integration.\u201d\n\nRead full story\n\nPontus Esbo\n\nCEO\n\nMiddlepoint\n\n\u201cThe layout is really easy on the eye. When you want to work quickly and efficiently, you really want to avoid any kind of sensory overload and get distracted by a messy dashboard where you\u2019ll struggle to find features. In Oneflow, the placement of every feature makes sense.\u201d\n\nRead full story\n\nKholod Hindi\n\nSales and Business Developer\n\nTeamtailor\n\n\u201cIt speeds up my work in many ways. Before it could take forever to get a contract sent and signed. Now it\u2019s all done digitally and customers can sign right away on any device \u2014 laptop, mobile phone, iPad/tablet. Sooo easy.\u201d\n\nRead full story\n\nSanel Osmic\n\nTeam Lead\n\nBredband2\n\n\u201cIt\u2019s gone from monologue to dialogue. The two-way communication makes it more fun for the seller and the customer becomes more involved. Everyone wins!\u201d\n\nRead full story\n\nPetter Lundqvist\n\nSales Manager\n\nFalck\n\n\u201cI\u2019d never thought it would be so easy. Oneflow saves me an incredible amount of time \u2013 there\u2019s nothing I dislike about it. As a consultant sending out offers repeatedly, this is the best tool I\u2019ve worked with.\u201d\n\nRead full story\n\nJ\u00f6rgen Persson\n\nConsulting Director\n\nLernia Bemanning\n\nRegistered name:\nOneflow AB (publ)\n\nHeadquarters:\nG\u00e4vlegatan 12a\n113 30 Stockholm, Sweden\n+46 8 517 297 70\n\nOrganisation number:\n556903-2989\n\nPlace where the board has its seat:\nStockholm\n\n\n\nProduct\nProduct tour\nDigital contract\nContract management\nElectronic signatures\nDigital signatures\nROI of Oneflow\nProduct Updates\nOneflow AI\nSolutions\nSales\nHR\nProcurement\nIT & Ops\nEnterprise\nScale\nStartup\nResources\nBlog\nCustomer stories\nAcademy\nGlossary\nThe State of Contracts Report\nFAQ\nDevelopers\nHelp Center\nCompare\nvs Docusign\nvs PandaDoc\nvs GetAccept\nvs Contractbook\nvs Juro\nvs Scrive\nAll alternatives\nSecurity\nSecurity Center\nReliability\nCompliance\nGDPR\nDORA\nSigning Methods\nAccessibility\nE-signatures legality\nIntegrations\nSalesforce\nHubspot\nMicrosoft Office 365\nTeamtailor\nGoogle Workspace\nZapier\nAll integrations\nCompany\nInvestor Relations\nPress releases\nPartners\nCareers\nAbout\nContact Oneflow\nOneflow Creator Program\nOneflow guest blog\nTemplates\nSales Agreement\nPurchase Agreement\nNon-Disclosure Agreement\nEmployment Agreement\nService level Agreement\nLicense Agreement\nSee all templates\nGet in the flow\nSend, track and sign your contracts free for the rest of your life. No trickery.\nTry Oneflow for free\nLogin\nPrivacy\nSitemap\nCookies statement\nStatus of Oneflow\n\nMade and hosted in the\n\nWe Care About Your Privacy\n\nWe use cookies to personalize content and ads, to provide social media features and to analyse our traffic. We also share information about your use of our site with social media, advertising and analytics partners who may combine it with other information that you've provided to them or that they've collected from your use of their services. You consent to our cookies if you continue to use our website. To change your preferences at any time, click on the \u201cChange cookie settings\u201d icon in the lower left corner.\n\nClose GDPR Cookie Banner\n\nStrictly necessary cookies\n\nMarketing cookies\n\nAccept Cookies\nUse necessary only\nMore information\nAccept selection\n\nGet started with Oneflow. There\u2019s no need to commit to a huge investment for a perpetual license with our flexible subscription-based pricing.",
      "error": null,
      "pricing_data": {
        "app_id": "oneflow",
        "app_name": "Oneflow",
        "app_slug": "oneflow",
        "pricing_url": "https://www.oneflow.com/pricing",
        "source_url": "https://www.oneflow.com/pricing",
        "all_pricing_urls": [
          "https://www.oneflow.com/pricing"
        ],
        "price_model_type": [
          "PriceModelType.SUBSCRIPTION",
          "PriceModelType.FREE_TIER"
        ],
        "has_free_tier": true,
        "has_free_trial": true,
        "free_trial_period_days": 14,
        "currency": "USD",
        "is_pricing_public": true,
        "pricing_page_accessible": true,
        "pricing_notes": "Pricing is subscription-based with a free tier and a free trial available.",
        "pricing_tiers": [
          {
            "tier_name": "Free",
            "tier_description": "Basic features for free forever.",
            "monthly_price": 0.0,
            "annual_price": 0.0,
            "annual_discount_percentage": null,
            "setup_fee": null,
            "features": [
              "PDF contracts",
              "Comments",
              "Audit trail",
              "Data portability",
              "Dashboards"
            ],
            "limits": {
              "users": "unlimited",
              "storage": "unlimited",
              "operations": "unlimited",
              "api_calls": null,
              "integrations": null,
              "custom_limits": null
            }
          },
          {
            "tier_name": "Essentials",
            "tier_description": "For those freeing themselves from the PDF friction.",
            "monthly_price": 17.0,
            "annual_price": null,
            "annual_discount_percentage": null,
            "setup_fee": null,
            "features": [
              "Digital contracts",
              "Contract templates",
              "Contract insights",
              "Standard integrations",
              "Contract calendar"
            ],
            "limits": {
              "users": "unlimited",
              "storage": "unlimited",
              "operations": "unlimited",
              "api_calls": null,
              "integrations": null,
              "custom_limits": null
            }
          },
          {
            "tier_name": "Business",
            "tier_description": "For teams seeking the magic of flow.",
            "monthly_price": 45.0,
            "annual_price": null,
            "annual_discount_percentage": null,
            "setup_fee": null,
            "features": [
              "Lifecycle",
              "Tags",
              "Data retention",
              "Premium integrations"
            ],
            "limits": {
              "users": "unlimited",
              "storage": "unlimited",
              "operations": "unlimited",
              "api_calls": null,
              "integrations": null,
              "custom_limits": null
            }
          },
          {
            "tier_name": "Enterprise",
            "tier_description": "For global teams with true digital ambitions.",
            "monthly_price": null,
            "annual_price": null,
            "annual_discount_percentage": null,
            "setup_fee": null,
            "features": [
              "Shared templates",
              "Groups",
              "Single sign-on (SSO)",
              "SCIM API"
            ],
            "limits": {
              "users": "unlimited",
              "storage": "unlimited",
              "operations": "unlimited",
              "api_calls": null,
              "integrations": null,
              "custom_limits": null
            }
          }
        ],
        "usage_based_pricing": null,
        "ai_specific_pricing": null,
        "promotional_offers": null,
        "additional_fees": null,
        "extraction_timestamp": "2025-04-15T05:01:50.645326",
        "schema_validated": true,
        "confidence_score": 100,
        "extraction_error": false,
        "json_repaired": false
      },
      "pricing_analyzed": true
    },
    {
      "url": "https://oneflow.com/pricing/",
      "is_accessible": true,
      "content": " \n  Skip to content    \n NEWIntroducing Oneflow AI - Join the waitlist  \n \n \n  \n NEWIntroducing Oneflow AI - Join the waitlist  \n   Company   Support   Investors   Login    \n   \n \n \n   \ud83c\uddf3\ud83c\uddf4  Norsk   \n   \ud83c\uddeb\ud83c\uddee  Suomi   \n   \ud83c\uddf8\ud83c\uddea  Svenska   \n   \ud83c\udde9\ud83c\uddf0  Dansk   \n   \ud83c\uddeb\ud83c\uddf7  Fran\u00e7ais   \n   \ud83c\uddf3\ud83c\uddf1  Nederlands   \n   \ud83c\uddea\ud83c\uddf8  Espa\u00f1ol   \n   \ud83c\uddf5\ud83c\uddf9  Portugu\u00eas   \n   \ud83c\udde9\ud83c\uddea  Deutsch   \n   \ud83c\uddec\ud83c\udde7  English (UK)   \n   \ud83c\uddfa\ud83c\uddf8  English (US)         \n \n    \n  \n \n \n Product  \n \n  \n \nExplore \n \n  \n Product tour  \n    \n  \n Security Center  \n    \n  \n Customer stories  \n    \n  \n Compare  \n    \n  \n Product updates  \n      \n \nFeatures \n \n  \n  Oneflow AI  \n    \n  \n E-signatures  \n    \n  \n Tracking  \n    \n  \n Workspaces  \n      \n \n \n \nPre-sign, sign and post-sign  \nA single platform for every part of the contract process  \n    \n \n  Explore        \n \n Solutions  \n \n  \n \nDepartments \n \n  \n Sales  \n    \n  \n HR  \n    \n  \n Procurement  \n    \n  \n IT & Ops  \n      \n \nCompany size \n \n  \n Enterprise  \n    \n  \n Scale  \n    \n  \n Startup  \n      \n \nIndustry \n \n  \n Tech & Software  \n    \n  \n Consulting  \n    \n  \n Recruitment  \n    \n  \n See all  \n      \n \n \n \nCustomer stories \nLearn how other companies have used Oneflow to level up their businesses.  \n    \n \n  All stories        \n \n Integrations  \n \n  \n \nSales \n \n  \n HubSpot  \n    \n  \n Salesforce  \n    \n  \n Microsoft Dynamics 365  \n    \n  \n Pipedrive  \n    \n  \n See all  \n      \n \nHR & Recruitment \n \n  \n Teamtailor  \n    \n  \n HiBob  \n    \n  \n Jobylon  \n    \n  \n Seven20  \n    \n  \n See all  \n      \n \nAutomation & Productivity \n \n  \n Slack  \n    \n  \n Zapier  \n    \n  \n Power Automate  \n    \n  \n Google Workspace  \n    \n  \n See all  \n      \n \n \n \nIntegrations  \n Connect your favorite tools with Oneflow and automate contracts effortlessly.  \n   \n \n  See all        \n \n Resources  \n \n  \n \nGet inspired \n \n  \n Blog  \n    \n  \n Events  \n    \n  \n Oneflow Creator Program  \n    \n  \n Podcast  \n      \n \nLearn \n \n  \n Glossary  \n    \n  \n The State of Contracts Report  \n    \n  \n Academy & Onboarding  \n    \n  \n FAQ  \n      \n \nBusiness templates \n \n  \n Sales Agreement  \n    \n  \n Purchase Agreement  \n    \n  \n Non-Disclosure Agreement  \n    \n  \n See all  \n      \n \n \n \nFree template library \nInstant access to our most popular contract templates.  \n    \n \n  Start free trial        \n  Pricing      \n \n  Get a demo       \n \n  Get a demo     \n \n  Get a demo    \n \nMenu        \n \n  Product  \n \n  \n \nExplore \n \n  \n Product tour  \n    \n  \n Security Center  \n    \n  \n Customer stories  \n    \n  \n Compare  \n    \n  \n Product updates  \n      \n \nFeatures \n \n  \n  Oneflow AI  \n    \n  \n E-signatures  \n    \n  \n Tracking  \n    \n  \n Workspaces  \n      \n \n \n \nPre-sign, sign and post-sign  \nA single platform for every part of the contract process  \n    \n \n  Explore        \n  Solutions  \n \n  \n \nDepartments \n \n  \n Sales  \n    \n  \n HR  \n    \n  \n Procurement  \n    \n  \n IT & Ops  \n      \n \nCompany size \n \n  \n Enterprise  \n    \n  \n Scale  \n    \n  \n Startup  \n      \n \nIndustry \n \n  \n Tech & Software  \n    \n  \n Consulting  \n    \n  \n Recruitment  \n    \n  \n See all  \n      \n \n \n \nCustomer stories \nLearn how other companies have used Oneflow to level up their businesses.  \n    \n \n  All stories        \n  Integrations  \n \n  \n \nSales \n \n  \n HubSpot  \n    \n  \n Salesforce  \n    \n  \n Microsoft Dynamics 365  \n    \n  \n Pipedrive  \n    \n  \n See all  \n      \n \nHR & Recruitment \n \n  \n Teamtailor  \n    \n  \n HiBob  \n    \n  \n Jobylon  \n    \n  \n Seven20  \n    \n  \n See all  \n      \n \nAutomation & Productivity \n \n  \n Slack  \n    \n  \n Zapier  \n    \n  \n Power Automate  \n    \n  \n Google Workspace  \n    \n  \n See all  \n      \n \n \n \nIntegrations  \n Connect your favorite tools with Oneflow and automate contracts effortlessly.  \n   \n \n  See all        \n  Resources  \n \n  \n \nGet inspired \n \n  \n Blog  \n    \n  \n Events  \n    \n  \n Oneflow Creator Program  \n    \n  \n Podcast  \n      \n \nLearn \n \n  \n Glossary  \n    \n  \n The State of Contracts Report  \n    \n  \n Academy & Onboarding  \n    \n  \n FAQ  \n      \n \nBusiness templates \n \n  \n Sales Agreement  \n    \n  \n Purchase Agreement  \n    \n  \n Non-Disclosure Agreement  \n    \n  \n See all  \n      \n \n \n \nFree template library \nInstant access to our most popular contract templates.  \n    \n \n  Start free trial        \n  Pricing     \n   \n \n \n   \ud83c\uddf3\ud83c\uddf4  Norsk   \n   \ud83c\uddeb\ud83c\uddee  Suomi   \n   \ud83c\uddf8\ud83c\uddea  Svenska   \n   \ud83c\udde9\ud83c\uddf0  Dansk   \n   \ud83c\uddeb\ud83c\uddf7  Fran\u00e7ais   \n   \ud83c\uddf3\ud83c\uddf1  Nederlands   \n   \ud83c\uddea\ud83c\uddf8  Espa\u00f1ol   \n   \ud83c\uddf5\ud83c\uddf9  Portugu\u00eas   \n   \ud83c\udde9\ud83c\uddea  Deutsch   \n   \ud83c\uddec\ud83c\udde7  English (UK)   \n   \ud83c\uddfa\ud83c\uddf8  English (US)       \n \n  Company   \n  Support   \n  Investors   \n  Login      \n \n  Login    \n \n  Buy now    \n \n  Try for free       \n    \n \n \n \nHome > Oneflow Pricing \nGet started! \nFind your flow with the right plan. \n   \n       \n \n \n  Yearly  Monthly  \n  Save up to 17% with annual plans   INR DKK EUR GBP NOK SEK USD AUD NZD CAD   \n \n \n \nFree \n14 day access to premium features. After the trial expires the basic Oneflow features will remain. \nFree \n forever forever \ud83c\udf89 No payment card required \ud83c\udf89 No payment card required   \n \n  Try Oneflow for free    \nIncludes: \n \n  PDF contracts \n Upload, send and e-sign PDF documents with legally binding e-signatures   \n  Comments \n Track activities and get notified of any comments or updates   \n  Audit trail \n See all the updates made to a contract in one place   \n  Data portability \n Import or export all your contracts in Oneflow   \n  Dashboards \n See important KPIs about your contracts on a dashboard     \n \n \nEssentials \nFor those freeing themselves from the PDF friction. Be more effective with digital contracts. Work faster. \n$17 \n \n/ month per user / month per user   \n \n  Book a demo    \nIncludes Free plan plus: \n \n  Digital contracts \n Create, collaborate live, send and e-sign interactive web-based contracts with legally binding e-signatures   \n  Contract templates \n Create, share and manage templates for contracts you send over and over again   \n  Contract insights \n Track engagement in the contract such as visits, opens, and more   \n  Standard integrations \n Plug and play integrations with many systems   \n  Contract calendar \n Visualize contracts based on their lifecycle events in a calendar view     \n \n \n Most popular  \nBusiness \nFor teams seeking the magic of flow. Unlock and use the data inside your contracts. All systems are in sync. \n$45 \n \n/ month per user / month per user   \n \n  Book a demo    \nIncludes Essentials plus: \n \n  Lifecycle \n Configure lifecycle rules for your contracts and get notified on lifecycle events   \n  Tags \n Add tags to contracts and templates to make them easier to find   \n  Data retention \n Configure data retention policies to avoid any information being stored passed its allowed time   \n  Premium integrations ($) \n Plug and play integrations with Salesforce, HubSpot and Microsoft Dynamics     \n \n \nEnterprise \nFor global teams with true digital ambitions. Scale the power of flow to all teams. Unleash contract magic. \nLet\u2019s talk \n \n      \n \n  Contact sales    \nIncludes Business plus: \n \n  Shared templates \n Share templates across different workspaces   \n  Groups \n Organize users in groups for better access management   \n  Single sign-on (SSO) \n Connect Oneflow to your own identity provider and utilize your own authentication policies   \n  SCIM API \n Integrate your identity provisioning processes with our integrations smoothly      \nCompare Plans      \n \n \n              \n \nFeaturesFreeEssentialsBusinessEnterprise \nCreate \nPDF contracts Upload, send and e-sign PDF documents with legally binding e-signaturesDigital contracts Create, collaborate live, send and e-sign interactive web-based contracts with legally binding e-signaturesContract templates Create, share and manage templates for contracts you send over and over againTemplate library Use a template from the library and adjust them to your own liking, instead of starting from scratchMessage templates Save and manage email messages as templates to save time the next time you send similar messagesShared templates Share templates across different workspaces($)Replace contract Create a new contract with a different template using existing content($)Batch sending Send contracts in bulk($)($) \nCollaborate \nComments Track activities and get notified of any comments or updatesAudit trail See all the updates made to a contract in one placeFields on PDF Add fields on PDF documentsSign later Share an offer and activate sign when readyVideo & screen recording Record, upload and share videos or screen recordingsInline comments Highlight text to comment directly in the contract, and sort by active or resolved commentsTwo-step authentication View contracts with two-step authentication to prevent unauthorized accessInternal approval workflow Add an internal approval step before signingSuggestions Add suggestions directly in the contract($)Section Rules Reveal or conceal specific sections based on rules and triggers($)Send contract over SMS Send invitation to contract as an SMS with a link to the contract($)($)Custom email domain Send Oneflow documents from any (sub)domain($)($) \nSign \nPremium signature Sign with an externally verifiable qualified seal through Oneflow with a clickHandwritten signature Sign using a wet ink signature by drawing or writing your signatureSign on same device Let signatories sign a contract on the same device as you use to create/send the contractSigning order Reorder the signatories so that it complies with your workflowSMS signature Let signatories verify their identity via SMS before signing your contracts($)($)eID signature Let signatories sign a contract using eID($)($) \nOneflow AI \nAI Assist Enable faster contract work, uncover blind spots and eliminate human errorsAI Import Upcoming Onboard Oneflow by instantly importing and organizing existing contracts into Oneflow platformAI Review Review individual contracts and receive recommendations to ensure compliance and get more favorable terms in the contracts you send and receive($)($)AI Insights Review your contracts in bulk to receive an instant due-diligence and compliance report across your entire portfolio($)($)AI Search Upcoming Perform intuitive and effective searches across all contracts($)($) \nManage \nData portability Export all your contracts in OneflowContract calendar Visualize contracts based on their lifecycle events in a calendar viewAdvanced filters Find contracts using granular filters such as tags, users, date range, etc.Data retention Configure data retention policies to avoid any information being stored passed its allowed timeAddress book Import or export all your contracts in OneflowMultiple Workspaces Organize your account and contracts to fit your organization structureTags Add tags to contracts and templates to make them easier to findLifecycle Configure lifecycle rules for your contracts and get notified on lifecycle eventsWorkspace branding Brand your Workspaces according to different affiliatesFolders Keep your Workspace structured. Create folders and subfolders in the specific document archive of a Workspace.Contract links Link related contracts together (e.g. subcontract, replacement, amendment)Custom reminders Create reminders with custom messages in the notification \nAnalyze \nDashboard See important KPIs about your contracts on a dashboardContract insights Track engagement in the contract such as visits, opens, and more \nIntegrate \nStandard integrations Plug and play integrations with many systemsAPI access Access to Oneflow API to build powerful integrations with any system of your choiceWebhooks Use Oneflow Webhooks to subscribe to notifications for contract events or updatesWeb form as a service Automate contract creation with data from web forms of your choice($)($)Premium integrations Plug and play integrations with Salesforce and Microsoft Dynamics($)($) \nSecurity  \nTwo-step authentication Log into the Oneflow account with two-step authenticationAccount audit log Keep track of user access, timestamps, and everything that happens in your account \nUser management \nUser management Add and manage active usersCustom workspace rolesManage what users can do within each workspaceSingle sign-on Connect Oneflow to your own identity provider and utilize your own authentication policies($)Custom admin roles Manage which account level admin controls a user can change($)GroupsOrganize users in groups for better access management($)Limited usersAdd users with limited access($)($)SCIM Integrate your user identity provisioning($) \nCertifications \nISO 27001 Oneflow\u2019s commitment to protecting sensitive data and providing best-in-class information security management systemISO 9001 Oneflow\u2019s commitment to excellence in delivering quality product and servicesISO 14001 Oneflow\u2019s commitment to reducing its environmental impacts \nSupport \nHelp center + Getting started Find helpful articles, guides and videos at our Help CenterEmail support Get help via email with our support team anytime, anywhereChat support Get help via chat with our support team anytime, anywherePhone support Get help via phone with our support team during office hoursDedicated Success Manager Get personalized onboarding and success plans from a designated success manager($)($)Premium SLA Add an SLA to your plan($)($)        \n \n \nJoin these companies making business flow  \n  \n \n   \n   \n   \n   \n   \n   \n   \n   \n   \n   \n   \n   \n   \n   \n   \n   \n    \n    \n    \n    \n    \n    \n    \n    \n    \n    \n    \n    \n    \n    \n    \n    \n    \n        \n \n    \n \nCan Oneflow help you save time and money? \nOneflow provides a range of benefits that can help organizations save time and money across the contract lifecycle. \n \nDiscover the ROI of Oneflow     \n \n \n \nWe love startups! \n Scale your business with digital contracts at startup-friendly prices. Tell us about your startup and we\u2019ll be in touch.  \n \n  Tell us about your startup     \n \nAPI and web forms \n Use our API to automate contract workflows across all your systems. Make contract data processable and useful.  \n \n  Message our team   \n  Call +46 8 517 297 70         \n \nStart using Oneflow \n \n \n Is Oneflow free?   \n \n \nWe have a free plan that allows users to send, track and sign as many PDF contracts as possible. So if you\u2019re happy with just signing PDF contracts, the answer is yes, it\u2019s free. Forever.    \n \n What is the difference between free and trial accounts?   \n \n \nWith our free plan, you can upload, send, track, and sign unlimited PDF contracts. However, with the free plan, you\u2019ll not be able to enjoy the full experience of contract magic. \nThat\u2019s why we also provide a trial of the full Oneflow experience for 14 days with no charge. With a trial account, you can try all the features our paid users love. For example, our contract editor. You can create stunning web-based contracts and make edits live, even after you\u2019ve sent.    \n \n What happens after my trial ends?   \n \n \nYour trial account will expire automatically after 14 days. Don\u2019t worry, you\u2019ll still be able to log into your account or access your contracts. After the trial, you\u2019ll automatically be in our free plan.\n     \n \n How can I extend my trial?   \n \n \nFeel free to do so in the Oneflow app on your own by clicking on \u201cUpgrade\u201d. You can also leave us a message here.    \n \n What kind of onboarding support can I expect?   \n \n \nEvery user starts by attending an onboarding session facilitated by our friendly customer care team to run through the basics. We also have a comprehensive Help Center with all the how tos and tutorials that you need to get started. And you can always email us with your questions. Depending on your tier, you may also get a dedicated customer success manager to help with any questions you may have.        \n \n \n  \nScale up or down \n \nThere\u2019s no need to commit to a huge investment for a perpetual license with our flexible SaaS platform and subscription-based pricing.   \n  \nSafer contracts \n \nIt all boils down to this. Managing your contracts on one platform, in one place, is way more secure than storing in binders or folders that are hard to keep track of.       \n \nCustomer support \n \n  \nEmail, chat and phone support \n \nGot questions, feedback, or want to bounce your ideas off us? Reach out to us anytime. We\u2019d love to hear from you.  \n    \n  \nHelp and training \n \nJoin our weekly Oneflow Academy webinar or get a personalized training. Or, if you want to go at your own pace, find comprehensive resources on our Help Center.  \n    \n  \nExperts on-hand \n \nOur skilled team of business and technical experts are passionate about solving your challenges. We\u2019ll make sure you get the help you need to be successful.       \n \n    \n \nHave other questions? \nIf you have more questions on our pricing and plans, contact us so we can help. \n \nContact us \nCall +46 8 517 297 70     \n \n \nDon\u2019t just take our word for it\u2026  \n \n \n \n \n \n \n \n \n\u201cFrom board meeting protocols to GDPR agreements, and approval of keycards \u2014 Oneflow has removed the pains we weren\u2019t even aware of.\u201d  Read full story   \n \n   \n \n Tor Myhrman  \n Head of Indirect Sourcing  \n Systembolaget         \n \n \n \n \n \n \n\u201cThe fact that Oneflow is 100% digital makes it so simple and flexible. It gives us peace of mind by providing control and a complete overview of our contract process at all times.\u201d  Read full story   \n \n   \n \n Elin Skoglund  \n HR Business Partner  \n Hedin Bil         \n \n \n \n \n \n \n\u201cOneflow is secure and really easy to use. It just works and saves us so much time. But, most importantly, we trust Oneflow with our documents because it meets our high security requirements.\u201d  Read full story   \n \n   \n \n Tobias T\u00f6rnqvist  \n HR Specialist  \n L\u00e4nsf\u00f6rs\u00e4kringar \u00c4lvsborg         \n \n \n \n \n \n \n\u201cIt took 12 minutes from calling the prospect to him receiving the proposal. I swear he \u2018almost fainted\u2019 when he saw how fast we could send a proposal.\u201d  Read full story   \n \n   \n \n Anders Berghagen  \n Sales & Marketing Director  \n Dormakaba         \n \n \n \n \n \n \n\u201cIt saves time and removes irritation. Before Oneflow, we spent a lot of time on coordinating, administrating, and booking time for signing. We immediately cut our lead times with this integration.\u201d  Read full story   \n \n   \n \n Pontus Esbo  \n CEO  \n Middlepoint         \n \n \n \n \n \n \n\u201cThe layout is really easy on the eye. When you want to work quickly and efficiently, you really want to avoid any kind of sensory overload and get distracted by a messy dashboard where you\u2019ll struggle to find features. In Oneflow, the placement of every feature makes sense.\u201d  Read full story   \n \n   \n \n Kholod Hindi  \n Sales and Business Developer  \n Teamtailor         \n \n \n \n \n \n \n\u201cIt speeds up my work in many ways. Before it could take forever to get a contract sent and signed. Now it\u2019s all done digitally and customers can sign right away on any device \u2014 laptop, mobile phone, iPad/tablet. Sooo easy.\u201d  Read full story   \n \n   \n \n Sanel Osmic  \n Team Lead  \n Bredband2         \n \n \n \n \n \n \n\u201cIt\u2019s gone from monologue to dialogue. The two-way communication makes it more fun for the seller and the customer becomes more involved. Everyone wins!\u201d  Read full story   \n \n   \n \n Petter Lundqvist  \n Sales Manager  \n Falck         \n \n \n \n \n \n \n\u201cI\u2019d never thought it would be so easy. Oneflow saves me an incredible amount of time \u2013 there\u2019s nothing I dislike about it. As a consultant sending out offers repeatedly, this is the best tool I\u2019ve worked with.\u201d   Read full story   \n \n   \n \n J\u00f6rgen Persson  \n Consulting Director  \n Lernia Bemanning          \n \n \n \n \n        \n \n \n \n    Registered name:\n Oneflow AB (publ)\n \n Headquarters:\n G\u00e4vlegatan 12a\n 113 30 Stockholm, Sweden\n +46 8 517 297 70\n \n Organisation number:\n 556903-2989\n \n Place where the board has its seat:\n Stockholm\n \n \n  \n                   \n    \n   \n \n  Product   \n  Product tour   \n  Digital contract   \n  Contract management   \n  Electronic signatures   \n  Digital signatures   \n  ROI of Oneflow   \n  Product Updates   \n  Oneflow AI      \n \n  Solutions   \n  Sales   \n  HR   \n  Procurement   \n  IT & Ops   \n  Enterprise   \n  Scale   \n  Startup       \n   \n \n  Resources   \n  Blog   \n  Customer stories   \n  Academy   \n  Glossary   \n  The State of Contracts Report   \n  FAQ   \n  Developers   \n  Help Center      \n \n  Compare   \n  vs Docusign   \n  vs PandaDoc   \n  vs GetAccept   \n  vs Contractbook   \n  vs Juro   \n  vs Scrive   \n  All alternatives       \n   \n \n  Security   \n  Security Center   \n  Reliability   \n  Compliance   \n  GDPR   \n  DORA   \n  Signing Methods   \n  Accessibility   \n  E-signatures legality      \n \n  Integrations   \n  Salesforce   \n  Hubspot   \n  Microsoft Office 365   \n  Teamtailor   \n  Google Workspace   \n  Zapier   \n  All integrations       \n   \n \n  Company   \n  Investor Relations   \n  Press releases   \n  Partners   \n  Careers   \n  About   \n  Contact Oneflow   \n  Oneflow Creator Program   \n  Oneflow guest blog      \n \n  Templates   \n  Sales Agreement   \n  Purchase Agreement   \n  Non-Disclosure Agreement   \n  Employment Agreement   \n  Service level Agreement   \n  License Agreement   \n  See all templates         Registered name:\n Oneflow AB (publ)\n \n Headquarters:\n G\u00e4vlegatan 12a\n 113 30 Stockholm, Sweden\n +46 8 517 297 70\n \n Organisation number:\n 556903-2989\n \n Place where the board has its seat:\n Stockholm\n \n \n  \n                   \n    \n \n \n \n Get in the flow   Send, track and sign your contracts free for the rest of your life. No trickery.   \n  Try Oneflow for free   \n     \n \n \n  Login   \n  Privacy   \n  Sitemap   \n  Cookies statement   \n  Status of Oneflow     \n   \n \n \n   \ud83c\uddf3\ud83c\uddf4  Norsk   \n   \ud83c\uddeb\ud83c\uddee  Suomi   \n   \ud83c\uddf8\ud83c\uddea  Svenska   \n   \ud83c\udde9\ud83c\uddf0  Dansk   \n   \ud83c\uddeb\ud83c\uddf7  Fran\u00e7ais   \n   \ud83c\uddf3\ud83c\uddf1  Nederlands   \n   \ud83c\uddea\ud83c\uddf8  Espa\u00f1ol   \n   \ud83c\uddf5\ud83c\uddf9  Portugu\u00eas   \n   \ud83c\udde9\ud83c\uddea  Deutsch   \n   \ud83c\uddec\ud83c\udde7  English (UK)   \n   \ud83c\uddfa\ud83c\uddf8  English (US)      \n \nMade and hosted in the   \n \n \nMade and hosted in the          \n \n \n \n \nWe Care About Your Privacy \nWe use cookies to personalize content and ads, to provide social media features and to analyse our traffic. We also share information about your use of our site with social media, advertising and analytics partners who may combine it with other information that you've provided to them or that they've collected from your use of their services. You consent to our cookies if you continue to use our website. To change your preferences at any time, click on the \u201cChange cookie settings\u201d icon in the lower left corner. \n Close GDPR Cookie Banner    \n  \n \n       \n \nStrictly necessary cookies     \n \n       \n \nMarketing cookies       \n \nAccept Cookies \nUse necessary only \nMore information \n Close GDPR Cookie Banner   \nAccept selection                 \n    Change cookie settings     \n \n \n Close GDPR Cookie Settings   \n \n \n \n Privacy overview   \n \n Strictly necessary cookies   \n \n Marketing cookies   \n \n Cookie Policy      \n \n \n Privacy overview  \n      \n \n \n \n \nThis website uses cookies so that we can provide you with the best user experience possible. Cookie information is stored in your browser and performs functions such as recognizing you when you return to our website and helping our team to understand which sections of the website you find most interesting and useful.     \n Strictly necessary cookies \n \nStrictly necessary cookies are enabled to save your preferences for cookie settings and other important core functionality. You may disable these by changing your browser settings, but this may affect how the website functions. To change your preferences at any time, click on the \u201cChange cookie settings\u201d icon in the lower left corner to access this page. \n \n \n  Enable or Disable Cookies              \n Marketing cookies \n \nCookies set by third party services or by us to track performance metrics, usage and marketing analytics to help us to personalize content and ads which improves your experience visiting Oneflow. We also share information about your use of our site with our analytics and advertising partners. \n \n \n  Enable or Disable Cookies          \n \nPlease enable Strictly Necessary Cookies first so that we can save your preferences!    Show details   \n    Name Provider Purpose Expiration      Facebook   Meta   Marketing   180 days     LinkedIn   LinkedIn   Marketing   30 days     Capterra   Capterra   Marketing   Persistent     Customer.io   Customer.io   Marketing   Persistent     Kameleoon   Kameleoon   Marketing Website Optimization   Persistent     Youtube   Youtube   Marketing   179 days     Google Ads   Alphabet Inc.   Marketing   30 days     Mouseflow mf_[website-id]   Mouseflow   Website analytics   This cookie is deleted when the session ends     Mouseflow mf_user   Mouseflow   Website analytics   90 days     Reddit   Reddit   Marketing   90 days     Amplitude   Amplitude   Analytics   365 days           \n Cookie Policy \n \nMore information about our Cookie Policy        \n \n \nAccept All \nReject All \nAccept selection\n\nGet started with Oneflow. There\u2019s no need to commit to a huge investment for a perpetual license with our flexible subscription-based pricing.",
      "error": null,
      "pricing_data": {
        "app_id": "oneflow",
        "app_name": "Oneflow",
        "app_slug": "oneflow",
        "pricing_url": "https://www.oneflow.com/pricing",
        "source_url": null,
        "all_pricing_urls": [
          "https://www.oneflow.com/pricing"
        ],
        "price_model_type": [
          "PriceModelType.SUBSCRIPTION",
          "PriceModelType.FREE_TIER"
        ],
        "has_free_tier": true,
        "has_free_trial": true,
        "free_trial_period_days": 14,
        "currency": "USD",
        "is_pricing_public": true,
        "pricing_page_accessible": true,
        "pricing_notes": "The free tier allows unlimited PDF contract handling, while paid tiers add advanced features like digital contracts and integrations.",
        "pricing_tiers": [
          {
            "tier_name": "Free",
            "tier_description": "Basic features for handling PDF contracts.",
            "monthly_price": 0.0,
            "annual_price": 0.0,
            "annual_discount_percentage": null,
            "setup_fee": null,
            "features": [
              "PDF contracts",
              "Comments",
              "Audit trail",
              "Data portability",
              "Dashboards"
            ],
            "limits": {
              "users": "unlimited",
              "storage": "unlimited",
              "operations": "unlimited",
              "api_calls": null,
              "integrations": null,
              "custom_limits": null
            }
          },
          {
            "tier_name": "Essentials",
            "tier_description": "For users transitioning to digital contracts.",
            "monthly_price": 17.0,
            "annual_price": null,
            "annual_discount_percentage": null,
            "setup_fee": null,
            "features": [
              "Digital contracts",
              "Contract templates",
              "Contract insights",
              "Standard integrations",
              "Contract calendar"
            ],
            "limits": {
              "users": "unlimited",
              "storage": "unlimited",
              "operations": "unlimited",
              "api_calls": null,
              "integrations": "standard",
              "custom_limits": null
            }
          },
          {
            "tier_name": "Business",
            "tier_description": "For teams requiring advanced contract management.",
            "monthly_price": 45.0,
            "annual_price": null,
            "annual_discount_percentage": null,
            "setup_fee": null,
            "features": [
              "Lifecycle management",
              "Tags",
              "Data retention",
              "Premium integrations"
            ],
            "limits": {
              "users": "unlimited",
              "storage": "unlimited",
              "operations": "unlimited",
              "api_calls": null,
              "integrations": "premium",
              "custom_limits": null
            }
          },
          {
            "tier_name": "Enterprise",
            "tier_description": "For large organizations with complex needs.",
            "monthly_price": null,
            "annual_price": null,
            "annual_discount_percentage": null,
            "setup_fee": null,
            "features": [
              "Shared templates",
              "Groups",
              "Single sign-on (SSO)",
              "SCIM API"
            ],
            "limits": {
              "users": "unlimited",
              "storage": "unlimited",
              "operations": "unlimited",
              "api_calls": null,
              "integrations": "custom",
              "custom_limits": null
            }
          }
        ],
        "usage_based_pricing": null,
        "ai_specific_pricing": null,
        "promotional_offers": null,
        "additional_fees": null,
        "extraction_timestamp": "2025-04-15T05:02:00.158119",
        "schema_validated": true,
        "confidence_score": 100,
        "extraction_error": false,
        "json_repaired": false
      },
      "pricing_analyzed": true
    }
  ],
  "results_directory": "pricing_results\\oneflow\\20250415_050200"
}