{
  "app_name": "Track-POD",
  "app_slug": "track-pod",
  "search_term": "Find the official pricing page URL for Track-POD (track-pod.com). Only provide the exact URL to the pricing page, not a summary of pricing information.",
  "timestamp": 1744721089.457582,
  "response_text": [
    "The official pricing page for Track-POD is [https://www.track-pod.com/pricing](https://www.track-pod.com/pricing)\u30103:0\u2020source\u3011."
  ],
  "citations": [
    {
      "title": "Pricing - Free Delivery App for Android / iOS \u00bb Track-POD",
      "url": "https://www.track-pod.com/pricing-delivery-app/"
    }
  ],
  "extracted_content": [
    {
      "url": "https://www.track-pod.com/pricing-delivery-app/",
      "is_accessible": true,
      "content": "Pricing - Free Delivery App for Android / iOS | Track-POD\n===============\n                                 \n\n [![Image 1: Track-POD company logo](https://www.track-pod.com/TrackPOD_logo.svg) ![Image 2: Track-POD company small logo](https://www.track-pod.com/TrackPOD_logo_small.svg)](https://www.track-pod.com/)\n\n*   [Home](https://www.track-pod.com/) chevron\\_right\n    \n*   [Solutions](https://www.track-pod.com/pricing-delivery-app/#) chevron\\_right\n    \n    [Route Planning Software](https://www.track-pod.com/route-planning-software/)\n    \n    [Last-Mile Logistics Software](https://www.track-pod.com/last-mile-logistics-software/)\n    \n    [Delivery Driver App](https://www.track-pod.com/delivery-driver-app/)\n    \n    [Transportation Management System](https://www.track-pod.com/transportation-management-system/)\n    \n    [Courier Dispatch Software](https://www.track-pod.com/courier-software/)\n    \n    [Vehicle Check & Safety Management](https://www.track-pod.com/vehicle-check-app/)\n    \n*   [Features](https://www.track-pod.com/pricing-delivery-app/#) chevron\\_right\n    \n    **Web-dashboard**\n    \n    [Planning and optimization](https://www.track-pod.com/blog/plan-track/)\n    \n    [Electronic proof of delivery](https://www.track-pod.com/blog/electronic-signature-capture/)\n    \n    [Delivery tracking](https://www.track-pod.com/blog/last-mile-delivery-tracking/)\n    \n    [Order fulfillment](https://www.track-pod.com/blog/mastering-order-lifecycle-on-track-pod/)\n    \n    [Branded live tracking](https://www.track-pod.com/blog/live-tracking-branding/)\n    \n    [Custom fields for delivery](https://www.track-pod.com/blog/new-custom-fields-for-the-delivery-live-tracking-page/)\n    \n    [Delivery notifications](https://www.track-pod.com/blog/when-to-send-shipping-notifications/)\n    \n    [Shipping Labels](https://www.track-pod.com/blog/shipping-label-template/)\n    \n    [Analytics & Reports](https://www.track-pod.com/blog/analytics-reports/)\n    \n    **Driver app**\n    \n    [ePOD & Delivery confirmation](https://www.track-pod.com/blog/what-is-proof-of-delivery/)\n    \n    [QR/Barcode scanner](https://www.track-pod.com/blog/free-barcode-scanner-app/)\n    \n    [Cash on delivery](https://www.track-pod.com/blog/cash-on-delivery/)\n    \n    [Vehicle check](https://www.track-pod.com/blog/safety-management/)\n    \n    [Geofencing](https://www.track-pod.com/blog/logistics-management-with-geofencing/)\n    \n    [Route management & navigation](https://www.track-pod.com/blog/route-manager-app/)\n    \n*   [Pricing](https://www.track-pod.com/pricing-delivery-app/) chevron\\_right\n    \n*   [Resources](https://www.track-pod.com/pricing-delivery-app/#) chevron\\_right\n    \n    [Blog](https://www.track-pod.com/blog/)\n    \n    [Case Studies](https://www.track-pod.com/case-studies/)\n    \n    [Industries](https://www.track-pod.com/blog/category/industries/)\n    \n    [Help Center](https://track-pod.freshdesk.com/support/home)\n    \n    [API](https://api.track-pod.com/index.html)\n    \n    [Security](https://www.track-pod.com/blog/customer-data-security/)\n    \n    [![Image 3](https://www.track-pod.com/assets/How+to+Route+optimization+using+map+zones+28129__FillWzIyMCwyMjBd.webp)](https://www.track-pod.com/blog/route-optimization-using-map-zones/)\n    \n    **Track-POD feature - MAP ZONES**\n    \n    [How To: Route Optimization Using Map Zones. New at Logistics](https://www.track-pod.com/blog/route-optimization-using-map-zones/)\n    \n    [**Read More**](https://www.track-pod.com/blog/route-optimization-using-map-zones/)\n    \n*   [Contact Us](https://www.track-pod.com/contact-us/) chevron\\_right\n    \n\n[Home](https://www.track-pod.com/)[Solutions chevron\\_right](https://www.track-pod.com/pricing-delivery-app/#)[Features chevron\\_right](https://www.track-pod.com/pricing-delivery-app/#)[Pricing](https://www.track-pod.com/pricing-delivery-app/)[Resources chevron\\_right](https://www.track-pod.com/pricing-delivery-app/#)[Contact Us](https://www.track-pod.com/contact-us/)\n\n[Log In](https://identity.track-pod.com/account/login/)[Try for Free](https://identity.track-pod.com/account/register/)\n\nchevron\\_left\n\n[Route Planning Software](https://www.track-pod.com/route-planning-software/)\n\n[Last-Mile Logistics Software](https://www.track-pod.com/last-mile-logistics-software/)\n\n[Delivery Driver App](https://www.track-pod.com/delivery-driver-app/)\n\n[Transportation Management System](https://www.track-pod.com/transportation-management-system/)\n\n[Courier Dispatch Software](https://www.track-pod.com/courier-software/)\n\n[Vehicle Check & Safety Management](https://www.track-pod.com/vehicle-check-app/)\n\n**Web-dashboard**\n\nchevron\\_right\n\n[Planning and optimization](https://www.track-pod.com/blog/plan-track/)\n\n[Electronic proof of delivery](https://www.track-pod.com/blog/electronic-signature-capture/)\n\n[Delivery tracking](https://www.track-pod.com/blog/last-mile-delivery-tracking/)\n\n[Order fulfillment](https://www.track-pod.com/blog/mastering-order-lifecycle-on-track-pod/)\n\n[Branded live tracking](https://www.track-pod.com/blog/live-tracking-branding/)\n\n[Custom fields for delivery](https://www.track-pod.com/blog/new-custom-fields-for-the-delivery-live-tracking-page/)\n\n[Delivery notifications](https://www.track-pod.com/blog/when-to-send-shipping-notifications/)\n\n[Shipping Labels](https://www.track-pod.com/blog/shipping-label-template/)\n\n[Analytics & Reports](https://www.track-pod.com/blog/analytics-reports/)\n\n**Driver app**\n\nchevron\\_right\n\n[ePOD & Delivery confirmation](https://www.track-pod.com/blog/what-is-proof-of-delivery/)\n\n[QR/Barcode scanner](https://www.track-pod.com/blog/free-barcode-scanner-app/)\n\n[Cash on delivery](https://www.track-pod.com/blog/cash-on-delivery/)\n\n[Vehicle check](https://www.track-pod.com/blog/safety-management/)\n\n[Geofencing](https://www.track-pod.com/blog/logistics-management-with-geofencing/)\n\n[Route management & navigation](https://www.track-pod.com/blog/route-manager-app/)\n\n[Blog](https://www.track-pod.com/blog/)\n\n[Case Studies](https://www.track-pod.com/case-studies/)\n\n[Industries](https://www.track-pod.com/blog/category/industries/)\n\n[Help Center](https://track-pod.freshdesk.com/support/home)\n\n[API](https://api.track-pod.com/index.html)\n\n[Security](https://www.track-pod.com/blog/customer-data-security/)\n\n[![Image 4](https://www.track-pod.com/assets/How+to+Route+optimization+using+map+zones+28129__FillWzcwMCw0MDBd.webp)](https://www.track-pod.com/blog/route-optimization-using-map-zones/)\n\n**Track-POD feature - MAP ZONES**\n\n[How To: Route Optimization Using Map Zones. New at Logistics](https://www.track-pod.com/blog/route-optimization-using-map-zones/)\n\n[**Read More**](https://www.track-pod.com/blog/route-optimization-using-map-zones/)\n\n[Log In](https://identity.track-pod.com/account/login/)[Try for Free](https://identity.track-pod.com/account/register/)\n\n[EN](https://www.track-pod.com/pricing-delivery-app/#)\n\n*   [EN](https://www.track-pod.com/pricing-delivery-app/)\n*   [DE](https://www.track-pod.com/de/preise/)\n*   [FR](https://www.track-pod.com/fr/tarifs/)\n*   [ES](https://www.track-pod.com/es/precios/)\n*   [PT](https://www.track-pod.com/pt/precos/)\n*   [NL](https://www.track-pod.com/nl/prijzen/)\n*   [PL](https://www.track-pod.com/pl/ceny/)\n*   [LT](https://www.track-pod.com/lt/kainos/)\n*   [RU](https://www.track-pod.com/ru/ceny/)\n\nmenu\n\nBest pricing for teams and enterprises\n======================================\n\nPER DRIVER PER ORDER\n\nStandard\n--------\n\n$29\n\na month per driver/vehicle billed annually\n\nor $35 month-to-month, \\*min 3 drivers\n\n[Get your free trial](https://identity.track-pod.com/account/register/)Included features\n\nIncluded featureAdditional cost\n\n### User Management\n\n*   #### Dashboard web-users\n    \n*   #### Roles and permissions for web-users\n    \n*   #### Web customer access\n    \n*   #### Minimum number of drivers\n    \n\n### Order Management\n\n*   #### Orders per month\n    \n*   #### Several type of orders\n    \n*   #### Bulk order editing\n    \n\n### iPhone & Android Delivery App\n\n*   #### Delivery confirmation\n    \n*   #### Live chat\n    \n*   #### Cash on Delivery (COD)\n    \n*   #### Navigation\n    \n*   #### Order transfer\n    \n\n### Proof of Delivery\n\n*   #### Signature capture\n    \n*   #### Picture taking\n    \n*   #### Geotags & Timestamps\n    \n*   #### QR / Barcode scanning\n    \n*   #### Custom POD template\n    \n*   #### Static map on POD template\n    \n\n### Live Tracking\n\n*   #### Vehicle tracking in real time\n    \n*   #### Recording GPS tracks\n    \n*   #### Delivery tracking\n    \n*   #### Live Tracking for your customer\n    \n\n### Route Planning\n\n*   #### Map-based planning tool\n    \n*   #### Route optimization with ETA\n    \n\n### Email and Push Notifications\n\n*   #### Delivery notification by email\n    \n*   #### Notification with Live Tracking link\n    \n*   #### Advance notification by email\n    \n*   #### All above notifications by SMS\\*\n    \n\n### Geofencing\n\n### Analytics & Reports\n\n*   #### Powerful Analysis Tool\n    \n*   #### Route sheet\n    \n*   #### Vehicle load plan\n    \n*   #### Shipping label\n    \n*   #### Analytics & Data history\n    \n\n### Integration and PDF reports\n\n*   #### Over 5,000 integrations to business apps\n    \n*   #### Published web services API\n    \n\n### Support\n\n*   #### Standard support plan\n    \n*   #### Free Onboarding Session\\*\n    \n\nMOST POPULAR\n\nAdvanced\n--------\n\n$49\n\na month per driver/vehicle billed annually\n\nor $59 month-to-month, \\*min 3 drivers\n\n[start free trial](https://identity.track-pod.com/account/register/)Included features\n\nIncluded featureAdditional cost\n\n### User Management\n\n*   #### Dashboard web-users\n    \n*   #### Roles and permissions for web-users\n    \n*   #### Web customer access\n    \n*   #### Minimum number of drivers\n    \n\n### Order Management\n\n*   #### Orders per month\n    \n*   #### Several type of orders\n    \n*   #### Custom objects creation\n    \n*   #### Bulk order editing\n    \n\n### iPhone & Android Delivery App\n\n*   #### Delivery confirmation\n    \n*   #### Live chat\n    \n*   #### Cash on Delivery (COD)\n    \n*   #### Navigation\n    \n*   #### Order transfer\n    \n*   #### Load check\n    \n*   #### Vehicle check\n    \n\n### Proof of Delivery\n\n*   #### Signature capture\n    \n*   #### Picture taking\n    \n*   #### Geotags & Timestamps\n    \n*   #### QR / Barcode scanning\n    \n*   #### Custom POD template\n    \n*   #### Static map on POD template\n    \n\n### Live Tracking\n\n*   #### Vehicle tracking in real time\n    \n*   #### Recording GPS tracks\n    \n*   #### Delivery tracking\n    \n*   #### Live Tracking for your customer\n    \n*   #### ETA live updates\n    \n\n### Route Planning\n\n*   #### Map-based planning tool\n    \n*   #### Route optimization with ETA\n    \n*   #### Advanced routing\n    \n*   #### Time slots\n    \n*   #### Service time\n    \n*   #### Priorities\n    \n*   #### Driver\u2019s breaks\n    \n*   #### Fleet optimization\n    \n*   #### Scheduling by capacities\n    \n*   #### Several types of routes\n    \n*   #### Dynamic departure time\n    \n*   #### Multiple trips\n    \n*   #### Recurring routes\n    \n\n### Email and Push Notifications\n\n*   #### Delivery notification by email\n    \n*   #### Notification with Live Tracking link\n    \n*   #### Notification with Live Tracking link & ETA\n    \n*   #### Advance notification by email\n    \n*   #### All above notifications by SMS\\*\n    \n*   #### Branded email configuration\n    \n\n### Geofencing\n\n### Analytics & Reports\n\n*   #### Powerful Analysis Tool\n    \n*   #### Route sheet\n    \n*   #### Vehicle load plan\n    \n*   #### Shipping label\n    \n*   #### Driver statistics\n    \n*   #### Trip summary by routes\n    \n*   #### Custom reports\n    \n*   #### Analytics & Data history\n    \n\n### Integration and PDF reports\n\n*   #### Over 5,000 integrations to business apps\n    \n*   #### Published web services API\n    \n\n### Support\n\n*   #### Standard support plan\n    \n*   #### Free Onboarding Session\\*\n    \n\nMORE VALUE\n\nAdvanced Plus\n-------------\n\n$69\n\na month per driver/vehicle billed annually\n\nor $79 month-to-month, \\*min 3 drivers\n\n[Try it for free](https://identity.track-pod.com/account/register/)Included features\n\nIncluded featureAdditional cost\n\n### User Management\n\n*   #### Dashboard web-users\n    \n*   #### Roles and permissions for web-users\n    \n*   #### Web customer access\n    \n*   #### Minimum number of drivers\n    \n\n### Order Management\n\n*   #### Orders per month\n    \n*   #### Several type of orders\n    \n*   #### Custom objects creation\n    \n*   #### Bulk order editing\n    \n\n### iPhone & Android Delivery App\n\n*   #### Delivery confirmation\n    \n*   #### Live chat\n    \n*   #### Cash on Delivery (COD)\n    \n*   #### Navigation\n    \n*   #### Order transfer\n    \n*   #### Load check\n    \n*   #### Vehicle check\n    \n*   #### Add new orders\n    \n\n### Proof of Delivery\n\n*   #### Signature capture\n    \n*   #### Picture taking\n    \n*   #### Geotags & Timestamps\n    \n*   #### QR / Barcode scanning\n    \n*   #### Custom POD template\n    \n*   #### Static map on POD template\n    \n*   #### PIN code confirmation\n    \n\n### Live Tracking\n\n*   #### Vehicle tracking in real time\n    \n*   #### Recording GPS tracks\n    \n*   #### Delivery tracking\n    \n*   #### Live Tracking for your customer\n    \n*   #### ETA live updates\n    \n*   #### Live tracking page with updated ETA\n    \n*   #### Live tracking customization\n    \n*   #### Live tracking page with updated ETA\n    \n\n### Route Planning\n\n*   #### Map-based planning tool\n    \n*   #### Route optimization with ETA\n    \n*   #### Advanced routing\n    \n*   #### Time slots\n    \n*   #### Service time\n    \n*   #### Priorities\n    \n*   #### Driver\u2019s breaks\n    \n*   #### Fleet optimization\n    \n*   #### Fleet optimization\n    \n*   #### Scheduling by capacities\n    \n*   #### Several types of routes\n    \n*   #### Dynamic departure time\n    \n*   #### Multiple trips\n    \n*   #### Recurring routes\n    \n*   #### Updating route start time and ETA\n    \n*   #### Updating and displaying ETA en route\n    \n*   #### Updating and displaying new stop sequence\n    \n\n### Email and Push Notifications\n\n*   #### Delivery notification by email\n    \n*   #### Notification with Live Tracking link\n    \n*   #### Notification with Live Tracking link & ETA\n    \n*   #### Advance notification by email\n    \n*   #### All above notifications by SMS\\*\n    \n*   #### Branded email configuration\n    \n\n### Geofencing\n\n*   #### Automatic check-in & check-out\n    \n*   #### Extended triggers for delivery confirmation\n    \n\n### Analytics & Reports\n\n*   #### Powerful Analysis Tool\n    \n*   #### Route sheet\n    \n*   #### Vehicle load plan\n    \n*   #### Shipping label\n    \n*   #### Driver statistics\n    \n*   #### Trip summary by routes\n    \n*   #### Custom reports\n    \n*   #### Analytics & Data history\n    \n\n### Integration and PDF reports\n\n*   #### Over 5,000 integrations to business apps\n    \n*   #### Published web services API\n    \n*   #### Generating PDF reports via API\n    \n*   #### Custom Integration\n    \n\n### Support\n\n*   #### Standard support plan\n    \n*   #### Developer API support\n    \n*   #### Free Onboarding Session\\*\n    \n\nEnterprise\n----------\n\nLet's talk\n\na month per driver/vehicle billed annually\n\nor month-to-month, \\*min 40 drivers\n\n[Book a demo](https://www.track-pod.com/evaluate-now/)Included features\n\nIncluded featureAdditional cost\n\n### User Management\n\n*   #### Dashboard web-users\n    \n*   #### Roles and permissions for web-users\n    \n*   #### Web customer access\n    \n*   #### Minimum number of drivers\n    \n\n### Order Management\n\n*   #### Orders per month\n    \n*   #### Several type of orders\n    \n*   #### Custom objects creation\n    \n*   #### Bulk order editing\n    \n\n### iPhone & Android Delivery App\n\n*   #### Delivery confirmation\n    \n*   #### Live chat\n    \n*   #### Cash on Delivery (COD)\n    \n*   #### Navigation\n    \n*   #### Order transfer\n    \n*   #### Load check\n    \n*   #### Vehicle check\n    \n*   #### Add new orders\n    \n\n### Proof of Delivery\n\n*   #### Signature capture\n    \n*   #### Picture taking\n    \n*   #### Geotags & Timestamps\n    \n*   #### QR / Barcode scanning\n    \n*   #### Custom POD template\n    \n*   #### Static map on POD template\n    \n*   #### PIN code confirmation\n    \n\n### Live Tracking\n\n*   #### Vehicle tracking in real time\n    \n*   #### Recording GPS tracks\n    \n*   #### Delivery tracking\n    \n*   #### Live Tracking for your customer\n    \n*   #### ETA live updates\n    \n*   #### Live tracking page with updated ETA\n    \n*   #### Live tracking customization\n    \n*   #### Live tracking page with updated ETA\n    \n\n### Route Planning\n\n*   #### Map-based planning tool\n    \n*   #### Route optimization with ETA\n    \n*   #### Advanced routing\n    \n*   #### Time slots\n    \n*   #### Service time\n    \n*   #### Priorities\n    \n*   #### Driver\u2019s breaks\n    \n*   #### Fleet optimization\n    \n*   #### Scheduling by capacities\n    \n*   #### Several types of routes\n    \n*   #### Dynamic departure time\n    \n*   #### Multiple trips\n    \n*   #### Recurring routes\n    \n*   #### Updating route start time and ETA\n    \n*   #### Updating and displaying ETA en route\n    \n*   #### Updating and displaying new stop sequence\n    \n\n### Email and Push Notifications\n\n*   #### Delivery notification by email\n    \n*   #### Notification with Live Tracking link\n    \n*   #### Notification with Live Tracking link & ETA\n    \n*   #### Advance notification by email\n    \n*   #### All above notifications by SMS\\*\n    \n*   #### Branded email configuration\n    \n\n### Geofencing\n\n*   #### Automatic check-in & check-out\n    \n*   #### Extended triggers for delivery confirmation\n    \n\n### Analytics & Reports\n\n*   #### Powerful Analysis Tool\n    \n*   #### Route sheet\n    \n*   #### Vehicle load plan\n    \n*   #### Shipping label\n    \n*   #### Driver statistics\n    \n*   #### Trip summary by routes\n    \n*   #### Custom reports\n    \n*   #### Analytics & Data history\n    \n\n### Integration and PDF reports\n\n*   #### Over 5,000 integrations to business apps\n    \n*   #### Published web services API\n    \n*   #### Generating PDF reports via API\n    \n*   #### Custom Integration\n    \n\n### Support\n\n*   #### Standard support plan\n    \n*   #### Developer API support\n    \n*   #### Customized Support & Services Plan\n    \n*   #### Free Onboarding Session\\*\n    \n\nS Plan\n------\n\n$285\n\na month per 1500 orders\n\n**$0.19 per order/task**\n\n[get your free trial](https://identity.track-pod.com/account/register/)Included features\n\nIncluded featureAdditional cost\n\n### User Management\n\n*   #### Allowed vehicles and drivers\n    \n*   #### Dashboard web-users\n    \n*   #### Roles and permissions for web-users\n    \n*   #### Web customer access\n    \n*   #### Roles y permisos para los usuarios de la web\n    \n\n### Order Management\n\n*   #### Orders per month\n    \n*   #### Several type of orders\n    \n*   #### Custom objects creation\n    \n*   #### Bulk order editing\n    \n\n### iPhone & Android Delivery App\n\n*   #### Delivery confirmation\n    \n*   #### Live chat\n    \n*   #### Cash on Delivery (COD)\n    \n*   #### Navigation\n    \n*   #### Load check\n    \n*   #### Vehicle check\n    \n*   #### Add new orders\n    \n*   #### Order transfer\n    \n*   #### Add new orders\n    \n*   #### Order transfer\n    \n\n### Proof of Delivery\n\n*   #### Signature capture\n    \n*   #### Picture taking\n    \n*   #### Geotags & Timestamps\n    \n*   #### QR / Barcode scanning\n    \n*   #### Custom POD template\n    \n*   #### Static map on POD template\n    \n*   #### PIN code confirmation\n    \n\n### Live Tracking\n\n*   #### Vehicle tracking in real time\n    \n*   #### Recording GPS tracks\n    \n*   #### Delivery tracking\n    \n*   #### Live Tracking for your customer\n    \n*   #### ETA live updates\n    \n*   #### Live tracking customization\n    \n\n### Route Planning\n\n*   #### Map-based planning tool\n    \n*   #### Route optimization with ETA\n    \n*   #### Advanced routing\n    \n*   #### Time slots\n    \n*   #### Service time\n    \n*   #### Priorities\n    \n*   #### Driver\u2019s breaks\n    \n*   #### Fleet optimization\n    \n*   #### Scheduling by capacities\n    \n*   #### Several types of routes\n    \n*   #### Dynamic departure time\n    \n*   #### Multiple trips\n    \n*   #### Recurring routes\n    \n*   #### Update route start time and ETA\n    \n*   #### Update and display ETA en route\n    \n*   #### Updating and displaying new stop sequence\n    \n*   #### Updating and displaying new stop sequence\n    \n\n### Email and Push Notifications\n\n*   #### Delivery notification by email\n    \n*   #### Notification with Live Tracking link\n    \n*   #### Notification with Live Tracking link & ETA\n    \n*   #### Advance notification by email\n    \n*   #### All above notifications by SMS\\*\n    \n*   #### Branded email configuration\n    \n*   #### Branded email configuration\n    \n\n### Geofencing\n\n*   #### Automatic check-in & check-out\n    \n*   #### Automatic check-in & check-out\n    \n*   #### Extended triggers for delivery confirmation\n    \n\n### Analytics & Reports\n\n*   #### Powerful Analysis Tool\n    \n*   #### Route sheet\n    \n*   #### Vehicle load plan\n    \n*   #### Shipping label\n    \n*   #### Driver statistics\n    \n*   #### Trip summary by routes\n    \n*   #### Analytics & Data history\n    \n*   #### Custom reports\n    \n*   #### Custom reports\n    \n\n### Integration and PDF reports\n\n*   #### Over 5,000 integrations to business apps\n    \n*   #### Published web services API\n    \n*   #### Generating PDF reports via API\n    \n*   #### Custom integration\n    \n*   #### Custom integration\n    \n\n### Support\n\n*   #### Standard support plan\n    \n*   #### Free Onboarding Session\\*\n    \n\nMOST POPULAR\n\nM Plan\n------\n\n$510\n\na month per 3000 orders\n\n**$0.17 per order/task**\n\n[start free trial](https://identity.track-pod.com/account/register/)Included features\n\nIncluded featureAdditional cost\n\n### User Management\n\n*   #### Allowed vehicles and drivers\n    \n*   #### Dashboard web-users\n    \n*   #### Roles and permissions for web-users\n    \n*   #### Web customer access\n    \n*   #### Roles y permisos para los usuarios de la web\n    \n\n### Order Management\n\n*   #### Orders per month\n    \n*   #### Several type of orders\n    \n*   #### Custom objects creation\n    \n*   #### Bulk order editing\n    \n\n### iPhone & Android Delivery App\n\n*   #### Delivery confirmation\n    \n*   #### Live chat\n    \n*   #### Cash on Delivery (COD)\n    \n*   #### Navigation\n    \n*   #### Load check\n    \n*   #### Vehicle check\n    \n*   #### Add new orders\n    \n*   #### Order transfer\n    \n*   #### Add new orders\n    \n*   #### Order transfer\n    \n\n### Proof of Delivery\n\n*   #### Signature capture\n    \n*   #### Picture taking\n    \n*   #### Geotags & Timestamps\n    \n*   #### QR / Barcode scanning\n    \n*   #### Custom POD template\n    \n*   #### Static map on POD template\n    \n*   #### PIN code confirmation\n    \n\n### Live Tracking\n\n*   #### Vehicle tracking in real time\n    \n*   #### Recording GPS tracks\n    \n*   #### Delivery tracking\n    \n*   #### Live Tracking for your customer\n    \n*   #### ETA live updates\n    \n*   #### Live tracking customization\n    \n\n### Route Planning\n\n*   #### Map-based planning tool\n    \n*   #### Route optimization with ETA\n    \n*   #### Advanced routing\n    \n*   #### Time slots\n    \n*   #### Service time\n    \n*   #### Priorities\n    \n*   #### Driver\u2019s breaks\n    \n*   #### Fleet optimization\n    \n*   #### Scheduling by capacities\n    \n*   #### Several types of routes\n    \n*   #### Dynamic departure time\n    \n*   #### Multiple trips\n    \n*   #### Recurring routes\n    \n*   #### Update route start time and ETA\n    \n*   #### Update and display ETA en route\n    \n*   #### Updating and displaying new stop sequence\n    \n*   #### Updating and displaying new stop sequence\n    \n\n### Email and Push Notifications\n\n*   #### Delivery notification by email\n    \n*   #### Notification with Live Tracking link\n    \n*   #### Notification with Live Tracking link & ETA\n    \n*   #### Advance notification by email\n    \n*   #### All above notifications by SMS\\*\n    \n*   #### Branded email configuration\n    \n*   #### Branded email configuration\n    \n\n### Geofencing\n\n*   #### Automatic check-in & check-out\n    \n*   #### Automatic check-in & check-out\n    \n*   #### Extended triggers for delivery confirmation\n    \n\n### Analytics & Reports\n\n*   #### Powerful Analysis Tool\n    \n*   #### Route sheet\n    \n*   #### Vehicle load plan\n    \n*   #### Shipping label\n    \n*   #### Driver statistics\n    \n*   #### Trip summary by routes\n    \n*   #### Analytics & Data history\n    \n*   #### Custom reports\n    \n*   #### Custom reports\n    \n\n### Integration and PDF reports\n\n*   #### Over 5,000 integrations to business apps\n    \n*   #### Published web services API\n    \n*   #### Generating PDF reports via API\n    \n*   #### Custom integration\n    \n*   #### Custom integration\n    \n\n### Support\n\n*   #### Standard support plan\n    \n*   #### Free Onboarding Session\\*\n    \n\nMORE VALUE\n\nL Plan\n------\n\n$900\n\na month per 6000 orders\n\n**$0.15 per order/task**\n\n[Try it for free](https://identity.track-pod.com/account/register/)Included features\n\nIncluded featureAdditional cost\n\n### User Management\n\n*   #### Allowed vehicles and drivers\n    \n*   #### Dashboard web-users\n    \n*   #### Roles and permissions for web-users\n    \n*   #### Web customer access\n    \n*   #### Roles y permisos para los usuarios de la web\n    \n\n### Order Management\n\n*   #### Orders per month\n    \n*   #### Several type of orders\n    \n*   #### Custom objects creation\n    \n*   #### Bulk order editing\n    \n\n### iPhone & Android Delivery App\n\n*   #### Delivery confirmation\n    \n*   #### Live chat\n    \n*   #### Cash on Delivery (COD)\n    \n*   #### Navigation\n    \n*   #### Load check\n    \n*   #### Vehicle check\n    \n*   #### Add new orders\n    \n*   #### Order transfer\n    \n*   #### Add new orders\n    \n*   #### Order transfer\n    \n\n### Proof of Delivery\n\n*   #### Signature capture\n    \n*   #### Picture taking\n    \n*   #### Geotags & Timestamps\n    \n*   #### QR / Barcode scanning\n    \n*   #### Custom POD template\n    \n*   #### Static map on POD template\n    \n*   #### PIN code confirmation\n    \n\n### Live Tracking\n\n*   #### Vehicle tracking in real time\n    \n*   #### Recording GPS tracks\n    \n*   #### Delivery tracking\n    \n*   #### Live Tracking for your customer\n    \n*   #### ETA live updates\n    \n*   #### Live tracking page with updated ETA\n    \n*   #### Live tracking customization\n    \n\n### Route Planning\n\n*   #### Map-based planning tool\n    \n*   #### Route optimization with ETA\n    \n*   #### Advanced routing\n    \n*   #### Time slots\n    \n*   #### Service time\n    \n*   #### Priorities\n    \n*   #### Driver\u2019s breaks\n    \n*   #### Fleet optimization\n    \n*   #### Scheduling by capacities\n    \n*   #### Several types of routes\n    \n*   #### Dynamic departure time\n    \n*   #### Multiple trips\n    \n*   #### Recurring routes\n    \n*   #### Update route start time and ETA\n    \n*   #### Update and display ETA en route\n    \n*   #### Updating and displaying new stop sequence\n    \n*   #### Updating and displaying new stop sequence\n    \n\n### Email and Push Notifications\n\n*   #### Delivery notification by email\n    \n*   #### Notification with Live Tracking link\n    \n*   #### Notification with Live Tracking link & ETA\n    \n*   #### Advance notification by email\n    \n*   #### All above notifications by SMS\\*\n    \n*   #### Branded email configuration\n    \n*   #### Branded email configuration\n    \n\n### Geofencing\n\n*   #### Automatic check-in & check-out\n    \n*   #### Automatic check-in & check-out\n    \n*   #### Extended triggers for delivery confirmation\n    \n\n### Analytics & Reports\n\n*   #### Powerful Analysis Tool\n    \n*   #### Route sheet\n    \n*   #### Vehicle load plan\n    \n*   #### Shipping label\n    \n*   #### Driver statistics\n    \n*   #### Trip summary by routes\n    \n*   #### Analytics & Data history\n    \n*   #### Custom reports\n    \n*   #### Custom reports\n    \n\n### Integration and PDF reports\n\n*   #### Over 5,000 integrations to business apps\n    \n*   #### Published web services API\n    \n*   #### Generating PDF reports via API\n    \n*   #### Custom integration\n    \n*   #### Custom integration\n    \n\n### Support\n\n*   #### Standard support plan\n    \n*   #### Developer API support\n    \n*   #### Customized Support & Services Plan\n    \n*   #### Free Onboarding Session\\*\n    \n\nXL Plan\n-------\n\n$1440\n\na month per 12000 orders\n\n**$0.12 per order/task**\n\n[Book a demo](https://www.track-pod.com/evaluate-now/)Included features\n\nIncluded featureAdditional cost\n\n### User Management\n\n*   #### Allowed vehicles and drivers\n    \n*   #### Dashboard web-users\n    \n*   #### Roles and permissions for web-users\n    \n*   #### Web customer access\n    \n*   #### Roles y permisos para los usuarios de la web\n    \n\n### Order Management\n\n*   #### Orders per month\n    \n*   #### Several type of orders\n    \n*   #### Custom objects creation\n    \n*   #### Bulk order editing\n    \n\n### iPhone & Android Delivery App\n\n*   #### Delivery confirmation\n    \n*   #### Live chat\n    \n*   #### Cash on Delivery (COD)\n    \n*   #### Navigation\n    \n*   #### Load check\n    \n*   #### Vehicle check\n    \n*   #### Add new orders\n    \n*   #### Order transfer\n    \n*   #### Add new orders\n    \n*   #### Order transfer\n    \n\n### Proof of Delivery\n\n*   #### Signature capture\n    \n*   #### Picture taking\n    \n*   #### Geotags & Timestamps\n    \n*   #### QR / Barcode scanning\n    \n*   #### Custom POD template\n    \n*   #### Static map on POD template\n    \n*   #### PIN code confirmation\n    \n\n### Live Tracking\n\n*   #### Vehicle tracking in real time\n    \n*   #### Recording GPS tracks\n    \n*   #### Delivery tracking\n    \n*   #### Live Tracking for your customer\n    \n*   #### ETA live updates\n    \n*   #### Live tracking page with updated ETA\n    \n*   #### Live tracking customization\n    \n\n### Route Planning\n\n*   #### Map-based planning tool\n    \n*   #### Route optimization with ETA\n    \n*   #### Advanced routing\n    \n*   #### Time slots\n    \n*   #### Service time\n    \n*   #### Priorities\n    \n*   #### Driver\u2019s breaks\n    \n*   #### Fleet optimization\n    \n*   #### Scheduling by capacities\n    \n*   #### Several types of routes\n    \n*   #### Dynamic departure time\n    \n*   #### Multiple trips\n    \n*   #### Recurring routes\n    \n*   #### Update route start time and ETA\n    \n*   #### Update and display ETA en route\n    \n*   #### Updating and displaying new stop sequence\n    \n*   #### Updating and displaying new stop sequence\n    \n\n### Email and Push Notifications\n\n*   #### Delivery notification by email\n    \n*   #### Notification with Live Tracking link\n    \n*   #### Notification with Live Tracking link & ETA\n    \n*   #### Advance notification by email\n    \n*   #### All above notifications by SMS\\*\n    \n*   #### Branded email configuration\n    \n*   #### Branded email configuration\n    \n\n### Geofencing\n\n*   #### Automatic check-in & check-out\n    \n*   #### Automatic check-in & check-out\n    \n*   #### Extended triggers for delivery confirmation\n    \n\n### Analytics & Reports\n\n*   #### Powerful Analysis Tool\n    \n*   #### Route sheet\n    \n*   #### Vehicle load plan\n    \n*   #### Shipping label\n    \n*   #### Driver statistics\n    \n*   #### Trip summary by routes\n    \n*   #### Analytics & Data history\n    \n*   #### Custom reports\n    \n*   #### Custom reports\n    \n\n### Integration and PDF reports\n\n*   #### Over 5,000 integrations to business apps\n    \n*   #### Published web services API\n    \n*   #### Generating PDF reports via API\n    \n*   #### Custom integration\n    \n*   #### Custom integration\n    \n\n### Support\n\n*   #### Standard support plan\n    \n*   #### Developer API support\n    \n*   #### Customized Support & Services Plan\n    \n*   #### Free Onboarding Session\\*\n    \n\n[Request a demo](https://www.track-pod.com/evaluate-now/) \\* You can easily book an online meeting now\n\nExpand all All features Some features Additional cost\n\nCompare Plans\n-------------\n\n### Standard\n\n### Advanced\n\n### Advanced Plus\n\n### Enterprise\n\n### User Management\n\n*   #### Minimum number of driversConsider the importance of purchasing the minimum number of driver/vehicle accounts.\n    \n    3 3 3 40\n    \n*   #### Dashboard web-usersThe number of Track-POD back-office users, e.g. dispatchers, salespersons, managers included in the Pricing Plan regardless the number of drivers/vehicles\n    \n    3 7 50 UNLIMITED\n    \n*   #### Roles and permissions for web-usersAbility to set up roles and permissions for dashboard web-users\n    \n*   #### Web customer accessProviding access to the Track-POD dashboard to verified customers/shippers for adding and tracking their deliveries\n    \n\n### Order Management\n\n*   #### Orders per monthThe maximum number of orders per month included in the Pricing Plan regardless the number of drivers/vehicles\n    \n    3000 6000 UNLIMITED UNLIMITED\n    \n*   #### Several type of ordersDelivery, Collection, Pickup&Delivery, Pickup-Hub-Delivery\n    \n*   #### Custom objects creationCreating custom fields to add more data to your order\n    \n    \u2014\n    \n*   #### Bulk order editingEdit orders in bulk by selecting multiple orders in your Plan & Track dashboard.\n    \n\n### iPhone & Android Delivery App\n\n*   #### Delivery confirmationConfirm a delivery with an electronic Proof of Delivery featuring time and geo stamps, pictures, customers\u2019 signatures\n    \n*   #### Live chatUse inbuilt messenger for communication with your field staff in real time\n    \n*   #### Cash on Delivery (COD)Let your driver collect cash from recipients, enter the COD to collect and the actual amount of collected\n    \n*   #### NavigationTrack-POD mobile app supports the most popular navigation and mapping tools, including Google Maps, Waze, TomTom, Here Map, Sygic and more\n    \n*   #### Order transferDrivers can transfer orders to each other to ensure on-time delivery in case of force majeure\n    \n*   #### Load checkAbility to scan packages onto a vehicle for a route in a sequence of delivery and to check that all have been scanned/loaded. Make sure that nothing has been left behind\n    \n    \u2014\n    \n*   #### Vehicle checkSome companies have mandatory requirements for checking a car to get it done before a driver starts a route. We created our Vehicle Check module to help you with this\n    \n    \u2014\n    \n*   #### Add new ordersEnable drivers to add new delivery and collection orders to active routes.\n    \n    \u2014 \u2014\n    \n\n### Proof of Delivery\n\n*   #### Signature captureGet a recipient\u2019s electronic signature with our Sign-on-Glass app\n    \n*   #### Picture takingTake a picture for any issue or location within the mobile app, use it as proof\n    \n*   #### Geotags & TimestampsCapture geotags & timestamps to know when/where orders are delivered\n    \n*   #### QR / Barcode scanningUse a mobile phone to scan order or item QR / barcodes, or capture ID from printed labels\n    \n*   #### Custom POD templateCustomize digital delivery note, put your logo, text on it\n    \n*   #### Static map on POD templateInsert a picture with a location pin in your POD template\n    \n*   #### PIN code confirmationShare a PIN code with customers for additional verification.\n    \n    \u2014 \u2014\n    \n\n### Live Tracking\n\n*   #### Vehicle tracking in real timeTrack your vehicle location on the map and monitor drop times in real time\n    \n*   #### Recording GPS tracksRecord route tracks, compare an actual track with the planned one\n    \n*   #### Delivery trackingTrack deliveries in real time, know the delivery status once the driver services the stop\n    \n*   #### Live Tracking for your customerLet your Customers track their deliveries on the map in real time with our Live Tracking Notifications\n    \n*   #### ETA live updatesInform your customers of their delivery ETA en route with our smart ETA Notifications\n    \n    \u2014\n    \n*   #### Live tracking page with updated ETALive tracking page displays updated ETA and provides you the possibility to set the time windows for updated ETA\n    \n    \u2014 \u2014\n    \n*   #### Live tracking customizationCustom brand your live tracking page by changing elements, colors, and logo.\n    \n    \u2014 \u2014\n    \n\n### Route Planning\n\n*   #### Map-based planning toolPlan your routes right on the map, first select on the map, then drag&drop into the route\n    \n*   #### Route optimization with ETAMultiple stop route planner calculating ETA and ATD per each stop/site\n    \n    UP TO 24 STOPS\n    \n*   #### Advanced routingOrders and routes are automatically assigned to drivers with no need for manual input. Support pickup&delivery orders optimisation\n    \n    \u2014\n    \n*   #### Time slotsRoutes are built to fit into customers\u2019 time windows\n    \n    \u2014\n    \n*   #### Service timeThe system considers service duration at each stop to provide the best routing solution\n    \n    \u2014\n    \n*   #### PrioritiesCreating routes with account for priorities given to customers, addresses, orders\n    \n    \u2014\n    \n*   #### Driver\u2019s breaksThe system considers drivers\u2019rest breaks when creating long-distance and multi-stop routes\n    \n    \u2014\n    \n*   #### Fleet optimizationFleet optimization\n    \n    \u2014\n    \n*   #### Scheduling by capacitiesCreating routes with regard to Loading, Volume, Pallets capacities\n    \n    \u2014\n    \n*   #### Several types of routesWe support all routing strategies: round trips, outbound, and inbound routes\n    \n    \u2014\n    \n*   #### Dynamic departure timeCalculating dynamic departure time to fit into time slots\n    \n    \u2014\n    \n*   #### Multiple tripsAutomatic assigning several routes per driver per day\n    \n    \u2014\n    \n*   #### Recurring routesCreate all kinds of scenarios for regular events/deliveries scheduled on a daily, weekly, monthly as well as quarterly basis\n    \n    \u2014\n    \n*   #### Updating route start time and ETAThe route start time will be updated to the actual driver's route start time. The planned ETA will be recalculated tacking into account the actual route start time and displayed in the ETA column of the Sites section\n    \n    \u2014 \u2014\n    \n*   #### Updating and displaying ETA en routeETA will be dynamically recalculated every 5 minutes according to the driver's GPS track. The updated ETA will be displayed with a slash in the Sites section in addition to the planned ETA and in the Analytics\n    \n    \u2014 \u2014\n    \n*   #### Updating and displaying new stop sequenceIf the driver rearranges the sequence of stops in a route, the new order of stops will appear in the web-dashboard. The web dispatcher screen will match the driver app screen\n    \n    \u2014 \u2014\n    \n\n### Email and Push Notifications\n\n*   #### Delivery notification by emailNotification sent to a customer once a job is completed with a PDF delivery confirmation\n    \n*   #### Notification with Live Tracking linkNotification with a live tracking link for your customers\n    \n*   #### Notification with Live Tracking link & ETANotification with a live tracking link for your customers and ETA updated in real time\n    \n    \u2014\n    \n*   #### Advance notification by emailEmail notification to a customer a day prior to a scheduled delivery\n    \n*   #### All above notifications by SMS\\*Text message confirming delivery. Charged for additionally for all countries\n    \n*   #### Branded email configurationYou can configure a custom SMTP server for your customers to receive notifications from your email domain address\n    \n    \u2014\n    \n\n### Geofencing\n\n*   #### Automatic check-in & check-outYou will not have the usual Arrived and Departed buttons, because these actions will occur automatically as soon as you enter or exit the geofence zone.\n    \n    \u2014 \u2014\n    \n*   #### Extended triggers for delivery confirmationThis option allows you to restrict your drivers to not be able to confirm the order only if they are not within the specified radius from your client's point or geofence zone\n    \n    \u2014 \u2014\n    \n\n### Analytics & Reports\n\n*   #### Powerful Analysis ToolAnalyze your data, drivers\u2019 KPI, delivery statuses, etc, create various analytics reports\n    \n*   #### Route sheetPrint out or save route sheets for the selected routes\n    \n*   #### Vehicle load planPrint out and view vehicle loading plans for each route\n    \n*   #### Shipping labelPrint out shipping labels generated by Track-POD per each route\n    \n*   #### Driver statisticsView your drivers\u2019 completed jobs in one report\n    \n    \u2014\n    \n*   #### Trip summary by routesCreate an Excel summary for a specified period of time\n    \n    \u2014\n    \n*   #### Custom reportsCreate your own reports figuring the data that matters for your business\n    \n    \u2014\n    \n*   #### Analytics & Data historyHow long will your data be stored in the cloud?\n    \n    1Y 2Y 2Y UNLIMITED\n    \n\n### Integration and PDF reports\n\n*   #### Over 5,000 integrations to business appsTrack-POD integrates to 5,000+ apps with Zapier\n    \n*   #### Published web services APIAccess our comprehensive REST API at no additional cost\n    \n*   #### Generating PDF reports via APIDownloading PDF proof of delivery reports using API call\n    \n    \u2014 \u2014\n    \n*   #### Custom IntegrationContact our Technical Team for integration assistance\n    \n    \u2014 \u2014\n    \n\n### Support\n\n*   #### Standard support planWe render on-time and comprehensive support to all customers no matter the size of the company\n    \n*   #### Free Onboarding Session\\*Individual video online session with our Customer Success Manager for 1-2h to help you GO LIVE as soon as possible, starting from 3+ drivers\n    \n*   #### Developer API supportConnect Track-POD to any app or system with the help of our Developer support plans\n    \n    \u2014 \u2014\n    \n*   #### Customized Support & Services PlanContact us with your specific requirements for support and services and we will work it out for you\n    \n    \u2014 \u2014 \u2014\n    \n\nExpand all All features Some features Additional cost\n\nCompare Plans\n-------------\n\n### S Plan\n\n### M Plan\n\n### L Plan\n\n### XL Plan\n\n### User Management\n\n*   #### Allowed vehicles and driversThe number of Track-POD mobile users for drivers or couriers\n    \n    UNLIMITED UNLIMITED UNLIMITED UNLIMITED\n    \n*   #### Dashboard web-usersThe number of Track-POD back-office users, e.g. dispatchers, included in the Pricing Plan regardless the number of drivers/vehicles\n    \n    50 50 50 50\n    \n*   #### Roles and permissions for web-usersAbility to set up roles and permissions for dashboard web-users\n    \n*   #### Web customer accessProviding access to the Track-POD dashboard to verified customers/shippers for adding and tracking their deliveries\n    \n*   #### Roles y permisos para los usuarios de la webPosibilidad de configurar roles y permisos para los usuarios de la web del panel de control\n    \n\n### Order Management\n\n*   #### Orders per monthThe maximum number of orders per month included in the Pricing Plan regardless the number of drivers/vehicles\n    \n    1500 3000 6000 12000\n    \n*   #### Several type of ordersDelivery, Collection, Pickup&Delivery, Pickup-Hub-Delivery\n    \n*   #### Custom objects creationDelivery, Collection, Pickup&Delivery, Pickup-Hub-Delivery\n    \n*   #### Bulk order editingEdit orders in bulk by selecting multiple orders in your Plan & Track dashboard.\n    \n\n### iPhone & Android Delivery App\n\n*   #### Delivery confirmationConfirm a delivery with an electronic Proof of Delivery featuring time and geo stamps, pictures, customers\u2019 signatures\n    \n*   #### Live chatUse inbuilt messenger for communication with your field staff in real time\n    \n*   #### Cash on Delivery (COD)Let your driver collect cash from recipients, enter the COD to collect and the actual amount of collected\n    \n*   #### NavigationTrack-POD mobile app supports the most popular navigation and mapping tools, including Google Maps, Waze, TomTom, Here Map, Sygic and more\n    \n*   #### Load checkAbility to scan packages onto a vehicle for a route in a sequence of delivery and to check that all have been scanned/loaded. Make sure that nothing has been left behind\n    \n*   #### Vehicle checkSome companies have mandatory requirements for checking a car to get it done before a driver starts a route. We created our Vehicle Check module to help you with this\n    \n*   #### Add new ordersEnable drivers to add new delivery and collection orders to active routes.\n    \n*   #### Order transferDrivers can transfer orders to each other to ensure on-time delivery in case of force majeure\n    \n\n### Proof of Delivery\n\n*   #### Signature captureGet a recipient\u2019s electronic signature with our Sign-on-Glass app\n    \n*   #### Picture takingTake a picture for any issue or location within the mobile app, use it as proof\n    \n*   #### Geotags & TimestampsCapture geotags & timestamps to know when/where orders are delivered\n    \n*   #### QR / Barcode scanningUse a mobile phone to scan order or item QR / barcodes, or capture ID from printed labels\n    \n*   #### Custom POD templateCustomize digital delivery note, put your logo, text on it\n    \n*   #### Static map on POD templateInsert a picture with a location pin in your POD template\n    \n*   #### PIN code confirmationShare a PIN code with customers for additional verification.\n    \n\n### Live Tracking\n\n*   #### Vehicle tracking in real timeTrack your vehicle location on the map and monitor drop times in real time\n    \n*   #### Recording GPS tracksRecord route tracks, compare an actual track with the planned one\n    \n*   #### Delivery trackingTrack deliveries in real time, know the delivery status once the driver services the stop\n    \n*   #### Live Tracking for your customerLet your Customers track their deliveries on the map in real time with our Live Tracking Notifications\n    \n*   #### ETA live updatesInform your customers of their delivery ETA en route with our smart ETA Notifications\n    \n*   #### Live tracking page with updated ETALive tracking page displays updated ETA and provides you the possibility to set the time windows for updated ETA\n    \n*   #### Live tracking customizationCustom brand your live tracking page by changing elements, colors, and logo.\n    \n\n### Route Planning\n\n*   #### Map-based planning toolPlan your routes right on the map, first select on the map, then drag&drop into the route\n    \n*   #### Route optimization with ETAMultiple stop route planner calculating ETA and ATD per each stop/site\n    \n*   #### Advanced routingOrders and routes are automatically assigned to drivers with no need for manual input\n    \n*   #### Time slotsRoutes are built to fit into customers\u2019 time windows\n    \n*   #### Service timeThe system considers service duration at each stop to provide the best routing solution\n    \n*   #### PrioritiesCreating routes with account for priorities given to customers, addresses, orders\n    \n*   #### Driver\u2019s breaksThe system considers drivers\u2019rest breaks when creating long-distance and multi-stop routes\n    \n*   #### Scheduling by capacitiesCreating routes with regard to Loading, Volume, Pallets capacities\n    \n*   #### Fleet optimizationOptimize your fleet of vehicles, make sure your trucks work to the full\n    \n*   #### Several types of routesWe support all routing strategies: round trips, outbound, and inbound routes\n    \n*   #### Dynamic departure timeCalculating dynamic departure time to fit into time slots\n    \n*   #### Multiple tripsAutomatic assigning several routes per driver per day\n    \n*   #### Recurring routesCreate all kinds of scenarios for regular events/deliveries scheduled on a daily, weekly, monthly as well as quarterly basis\n    \n*   #### Update route start time and ETAThe route start time will be updated to the actual driver's route start time. The planed ETA will be recalculated tacking into account the actual route start time and displayed in the ETA column of the Sites section\n    \n*   #### Update and display ETA en routeETA will be dynamically recalculated every 5 minutes according to the driver's GPS track. The updated ETA will be displayed with a slash in the Sites section in addition to the planned ETA and in the Analytics\n    \n*   #### Updating and displaying new stop sequenceIf the driver rearranges the sequence of stops in a route, the new order of stops will appear in the web-dashboard. The web dispatcher screen will match the driver app screen\n    \n\n### Email and Push Notifications\n\n*   #### Delivery notification by emailNotification sent to a customer once a job is completed with a PDF delivery confirmation\n    \n*   #### Notification with Live Tracking linkNotification with a live tracking link for your customers\n    \n*   #### Notification with Live Tracking link & ETANotification with a live tracking link for your customers and ETA updated in real time\n    \n*   #### Advance notification by emailEmail notification to a customer a day prior to a scheduled delivery\n    \n*   #### All above notifications by SMS\\*Text message confirming delivery. Charged for additionally for all countries\n    \n*   #### Branded email configurationYou can configure a custom SMTP server for your customers to receive notifications from your email domain address\n    \n\n### Geofencing\n\n*   #### Automatic check-in & check-outYou will not have the usual Arrived and Departed buttons, because these actions will occur automatically as soon as you enter or exit the geofence zone.\n    \n*   #### Extended triggers for delivery confirmationThis option allows you to restrict your drivers to not be able to confirm the order only if they are not within the specified radius from your client's point or geofence zone\n    \n\n### Analytics & Reports\n\n*   #### Powerful Analysis ToolAnalyze your data, drivers\u2019 KPI, delivery statuses, etc, create various analytics reports\n    \n*   #### Route sheetPrint out or save route sheets for the selected routes\n    \n*   #### Vehicle load planPrint out and view vehicle loading plans for each route\n    \n*   #### Shipping labelPrint out shipping labels generated by Track-POD per each route\n    \n*   #### Driver statisticsView your drivers\u2019 completed jobs in one report\n    \n*   #### Trip summary by routesCreate an Excel summary for a specified period of time\n    \n*   #### Analytics & Data historyHow long will your data be stored in the cloud?\n    \n    2Y 2Y 2Y UNLIMITED\n    \n*   #### Custom reportsCreate your own reports figuring the data that matters for your business\n    \n\n### Integration and PDF reports\n\n*   #### Over 5,000 integrations to business appsTrack-POD integrates to 5,000+ apps with Zapier\n    \n*   #### Published web services APIAccess our comprehensive REST API at no additional cost\n    \n*   #### Generating PDF reports via APIDownloading PDF proof of delivery reports using API call\n    \n*   #### Custom integrationContact our Technical Team for integration assistance\n    \n\n### Support\n\n*   #### Standard support planWe render on-time and comprehensive support to all customers no matter the size of the company\n    \n*   #### Free Onboarding Session\\*Individual video online session with our Customer Success Manager for 1-2h to help you GO LIVE as soon as possible, starting from 3+ drivers\n    \n*   #### Developer API supportConnect Track-POD to any app or system with the help of our Developer support plans\n    \n    \u2014 \u2014\n    \n*   #### Customized Support & Services PlanContact us with your specific requirements for support and services and we will work it out for you\n    \n    \u2014 \u2014\n    \n\nSTART INCREASING YOUR PROFIT TODAY\n----------------------------------\n\nCurrently, we are offering a free trial to test-run our software that works globally (US, UK, Europe, Australia, Canada, South Africa, Asia etc.). Signing up is simple and easy. You can try out Track-POD solution without any risks and start enjoying the immense benefits that it offers (No Credit Card Required).\n\n[Start it for free today](https://identity.track-pod.com/account/register/)\n\n###### Product\n\n*   [Features](https://www.track-pod.com/features/)\n*   [Pricing](https://www.track-pod.com/pricing-delivery-app/)\n*   [FAQ](https://www.track-pod.com/faq-delivery-system/)\n*   [Status](https://status.track-pod.com/787336601/)\n*   [Industries](https://www.track-pod.com/blog/category/industries/)\n\n###### Solutions\n\n*   [Route planning software](https://www.track-pod.com/route-planning-software/)\n*   [Last-mile logistics software](https://www.track-pod.com/last-mile-logistics-software/)\n*   [Delivery driver app](https://www.track-pod.com/delivery-driver-app/)\n*   [Transportation management system](https://www.track-pod.com/transportation-management-system/)\n*   [Vehicle check & safety management](https://www.track-pod.com/vehicle-check-app/)\n*   [Courier dispatch software](https://www.track-pod.com/courier-software/)\n\n###### Resources\n\n*   [Blog](https://www.track-pod.com/blog/)\n*   [Case studies](https://www.track-pod.com/case-studies/)\n*   [Help center](https://track-pod.freshdesk.com/support/home)\n*   [API Developer](https://www.track-pod.com/api-integration/)\n*   [Terms of Use](https://www.track-pod.com/terms-of-use/)\n*   [Privacy Policy & GDPR](https://www.track-pod.com/privacy-policy/)\n*   [Cookie Policy](https://www.track-pod.com/cookies-policy/)\n\n###### Company\n\n*   [About us](https://www.track-pod.com/about-us/)\n*   [Careers](https://www.linkedin.com/company/track-pod/jobs/)\n*   [Contact us](https://www.track-pod.com/contact-us/)\n\n###### Certified Service Provider\n\n*   [![Image 5: SOC badge](https://www.track-pod.com/_resources/themes/track/pictures/SOC_badge.svg?m=1708882225)](https://www.track-pod.com/blog/customer-data-security/)\n\nCopyright 2024 (c) | Track-POD. All Rights reserved.\n\n*   Follow Track-POD:\n*   [![Image 6: twitter sharing](https://www.track-pod.com/_resources/themes/track/pictures/twitter.svg?m=1701983083)](https://twitter.com/track_pod)\n*   [![Image 7: facebook sharing](https://www.track-pod.com/_resources/themes/track/pictures/facebook.svg?m=1672759102)](https://www.facebook.com/TrackPOD.delivery)\n*   [![Image 8: youtube sharing](https://www.track-pod.com/_resources/themes/track/pictures/youtube.svg?m=1677614387)](https://www.youtube.com/@get-track-pod)\n*   [![Image 9: linkedin sharing](https://www.track-pod.com/_resources/themes/track/pictures/linkedin.svg?m=1672759102)](https://www.linkedin.com/company/track-pod/)\n\n     \n\n![Image 11](https://bat.bing.com/action/0?ti=148009083&Ver=2&mid=d365d44f-1ed6-47c3-81e1-518fc2c711e1&bo=1&sid=6c44ec4019f711f0a730e5e3788df3e1&vid=6c44f5b019f711f08cfe631cf7bd59cb&vids=1&msclkid=N&pi=918639831&lg=en-US&sw=800&sh=600&sc=24&tl=Pricing%20-%20Free%20Delivery%20App%20for%20Android%20%2F%20iOS%20%7C%20Track-POD&p=https%3A%2F%2Fwww.track-pod.com%2Fpricing-delivery-app%2F&r=&lt=683&evt=pageLoad&sv=1&cdb=AQAQ&rn=833381)\n\n [![Image 12](blob:https://www.track-pod.com/c82e1687fcc86b84dde9d3121f4a1a4b)](https://consent.studio/?utm_source=banner&utm_medium=title-icon)**Our website uses cookies**\n\nOverview\n\nIn order to personalise content and ads, to remember your preferences, to enable social media features and to measure the traffic to our site, we use cookies. We also share information about your use of our website with our social media, analytics and advertising partners, who may combine that information with data they have already collected from your use of their services.\n\nMore information about the use of cookies on our website [can be found in our privacy policy](https://www.track-pod.com/privacy-policy/).\n\n*    Functional\n*    Analytics\n*    Marketing\n\nReject all Allow selection Accept all\n\n**Track-pod.com Cookies**\n\n**Functional**\n\nCloudflare\n\nCloudflare\n\n[Privacy Portal](https://www.cloudflare.com/privacypolicy/)\n\n\\_\\_cf\\_bm\n\nCloudflare's bot products identify and mitigate automated traffic to protect your site from bad bots. Cloudflare places the \\_\\_cf\\_bm cookie on End User devices that access Customer sites that are protected by Bot Management or Bot Fight Mode. The \\_\\_cf\\_bm cookie is necessary for the proper functioning of these bot solutions.\n\nsession\n\n\\_cfuvid\n\nThe \\_cfuvid cookie is only set when a site uses this option in a Rate Limiting Rule, and is only used to allow the Cloudflare WAF to distinguish individual users who share the same IP address.\n\nsession\n\nGoogle\n\nGoogle\n\n[Privacy Portal](https://business.safety.google/privacy/)\n\n\\_\\_Secure-ENID\n\nUsed by Google to prevent fraudulent login attempts. This also contains a Google user ID which can be used for statistics and marketing purposes following a successful login\n\n11 Months\n\ntest\\_cookie\n\nThis cookie is set by DoubleClick (which is owned by Google) to determine if the website visitor's browser supports cookies.\n\n1 year\n\nDoubleClick/Google Marketing\n\n[Privacy Portal](https://business.safety.google/privacy/)\n\nLinkedIn\n\nLinkedIn\n\n[Privacy Portal](https://www.linkedin.com/legal/privacy-policy)\n\nli\\_gc\n\nUsed to store guest consent to the use of cookies for non-essential purposes\n\n2 years\n\nVallonic B.V.\n\nConsent Studio CMP\n\nconsent-studio\\_\\_consent-id\n\nID of the proof of consent storage within the Consent Studio platform.\n\n30 days\n\nconsent-studio\\_\\_storage\n\nLocal storage for the consent given by the user for certain categories of cookies.\n\n30 days\n\nconsent-studio\\_\\_seen\n\nBoolean that keeps track of whether the user has seen the cookie banner at least once.\n\n30 days\n\nconsent-studio\\_\\_implicit-consent-triggered\n\nWhen a website has implicit consent configured, this cookie stores whether or not it has been triggered or not.\n\n30 days\n\n**Analytics**\n\nGoogle\n\nGoogle Analytics\n\n[Privacy Portal](https://business.safety.google/privacy/)\n\n\\_ga\\_\n\nID used to identify users\n\n2 years\n\n\\_ga\n\nID used to identify users\n\n2 years\n\n**Marketing**\n\nHubSpot\n\nHubspot\n\n[Privacy Portal](https://legal.hubspot.com/privacy-policy)\n\n\\_\\_hstc\n\nThe main cookie for tracking visitors.\n\n13 months\n\nhubspotutk\n\nThis cookie keeps track of a visitor's identity. It is passed to HubSpot on form submission and used when deduplicating contacts.\n\n13 months\n\n\\_\\_hssrc\n\nWhenever HubSpot changes the session cookie, this cookie is also set to determine if the visitor has restarted their browser.\n\nsession\n\n\\_\\_hssc\n\nThis cookie keeps track of sessions.\n\n30 minutes\n\nGoogle\n\nGoogle\n\n[Privacy Portal](https://business.safety.google/privacy/)\n\n\\_gcl\\_au\n\nUsed by Google AdSense for experimenting with advertisement efficiency across websites using their services.\n\n3 months\n\nFacebook\n\nFacebook\n\n[Privacy Portal](https://www.facebook.com/about/privacy/)\n\n\\_fbp\n\nUsed by Facebook to deliver a series of advertisement products such as real time bidding from third party advertisers\n\n4 months\n\nMicrosoft\n\nBing / Microsoft\n\n[Privacy Portal](https://account.microsoft.com/privacy)\n\nMUID\n\nIdentifies unique web browsers visiting Microsoft sites. These cookies are used for advertising, site analytics, and other operational purposes.\n\n1 year\n\n\\_uetsid\n\nThis cookie is used by Bing to determine what ads should be shown that may be relevant to the end user perusing the site.\n\n30 minutes\n\n\\_uetvid\n\nThis is a cookie utilised by Microsoft Bing Ads and is a tracking cookie. It allows us to engage with a user that has previously visited our website.\n\n16 days\n\nLinkedIn\n\nLinkedIn\n\n[Privacy Portal](https://www.linkedin.com/legal/privacy-policy)\n\nbcookie\n\nUsed by LinkedIn to track the use of embedded services.\n\n1 year\n\nlidc\n\nUsed by the social networking service, LinkedIn, for tracking the use of embedded services.\n\n1 day\n\n**\u2014**\n\nUnknown\n\nUnknown\n\ngaconnector\\_GA\\_Measurement\\_ID\n\n3 months\n\ngaconnector\\_pages\\_visited\\_list\n\n3 months\n\ngaconnector\\_page\\_visits\n\n3 months\n\ngaconnector\\_GA\\_Client\\_ID\n\n3 months\n\ngaconnector\\_GA\\_Session\\_ID\n\n3 months\n\ngaconnector\\_gclid\n\n3 months\n\ngaconnector\\_fc\\_source\n\n3 months\n\ngaconnector\\_lc\\_source\n\n3 months\n\ngaconnector\\_fc\\_medium\n\n3 months\n\ngaconnector\\_lc\\_medium\n\n3 months\n\ngaconnector\\_fc\\_campaign\n\n3 months\n\ngaconnector\\_lc\\_campaign\n\n3 months\n\ngaconnector\\_fc\\_term\n\n3 months\n\ngaconnector\\_lc\\_term\n\n3 months\n\ngaconnector\\_fc\\_content\n\n3 months\n\ngaconnector\\_lc\\_content\n\n3 months\n\ngaconnector\\_fc\\_landing\n\n3 months\n\ngaconnector\\_lc\\_landing\n\n3 months\n\ngaconnector\\_fc\\_referrer\n\n3 months\n\ngaconnector\\_lc\\_referrer\n\n3 months\n\ngaconnector\\_fc\\_channel\n\n3 months\n\ngaconnector\\_lc\\_channel\n\n3 months\n\ngaconnector\\_ip\\_address\n\n3 months\n\ngaconnector\\_OS\n\n3 months\n\ngaconnector\\_device\n\n3 months\n\ngaconnector\\_browser\n\n3 months\n\ngaconnector\\_city\n\n3 months\n\ngaconnector\\_country\n\n3 months\n\ngaconnector\\_country\\_code\n\n3 months\n\ngaconnector\\_region\n\n3 months\n\ngaconnector\\_time\\_zone\n\n3 months\n\ngaconnector\\_latitude\n\n3 months\n\ngaconnector\\_longitude\n\n3 months\n\ngaconnector\\_all\\_traffic\\_sources\n\n3 months\n\ngaconnector\\_fc\\_timestamp\n\n3 months\n\ngaconnector\\_lc\\_timestamp\n\n3 months\n\ngaconnector\\_time\\_passed\n\n3 months\n\nFlexible licensing. Pay per driver or per number of orders a month. #1 best delivery app for Android / iOS. Try for free.",
      "error": null,
      "pricing_data": {
        "app_id": "track_pod",
        "app_name": "Track-POD",
        "app_slug": "track-pod",
        "pricing_url": "https://www.track-pod.com/pricing-delivery-app/",
        "source_url": "https://www.track-pod.com/pricing-delivery-app/",
        "all_pricing_urls": [
          "https://www.track-pod.com/pricing-delivery-app/"
        ],
        "price_model_type": [
          "PriceModelType.SUBSCRIPTION",
          "PriceModelType.USAGE_BASED"
        ],
        "has_free_tier": false,
        "has_free_trial": true,
        "free_trial_period_days": null,
        "currency": "USD",
        "is_pricing_public": true,
        "pricing_page_accessible": true,
        "pricing_notes": "Pricing is based on per driver/vehicle or per order/task with minimum driver requirements.",
        "pricing_tiers": [
          {
            "tier_name": "Standard",
            "tier_description": "Basic plan for small teams.",
            "monthly_price": 35.0,
            "annual_price": 29.0,
            "annual_discount_percentage": 17.14,
            "setup_fee": null,
            "features": [
              "Dashboard web-users",
              "Roles and permissions for web-users",
              "Web customer access",
              "Orders per month",
              "Several type of orders",
              "Bulk order editing",
              "Delivery confirmation",
              "Live chat",
              "Cash on Delivery (COD)",
              "Navigation",
              "Order transfer",
              "Signature capture",
              "Picture taking",
              "Geotags & Timestamps",
              "QR / Barcode scanning",
              "Custom POD template",
              "Static map on POD template",
              "Vehicle tracking in real time",
              "Recording GPS tracks",
              "Delivery tracking",
              "Live Tracking for your customer",
              "Map-based planning tool",
              "Route optimization with ETA",
              "Delivery notification by email",
              "Notification with Live Tracking link",
              "Advance notification by email",
              "Powerful Analysis Tool",
              "Route sheet",
              "Vehicle load plan",
              "Shipping label",
              "Analytics & Data history",
              "Over 5,000 integrations to business apps",
              "Published web services API",
              "Standard support plan",
              "Free Onboarding Session"
            ],
            "limits": {
              "users": null,
              "storage": null,
              "operations": null,
              "api_calls": null,
              "integrations": "5000",
              "custom_limits": [
                {
                  "name": "Minimum drivers",
                  "value": 3
                }
              ]
            }
          },
          {
            "tier_name": "Advanced",
            "tier_description": "Most popular plan with additional features.",
            "monthly_price": 59.0,
            "annual_price": 49.0,
            "annual_discount_percentage": 16.95,
            "setup_fee": null,
            "features": [
              "Custom objects creation",
              "Load check",
              "Vehicle check",
              "ETA live updates",
              "Advanced routing",
              "Time slots",
              "Service time",
              "Priorities",
              "Driver\u2019s breaks",
              "Fleet optimization",
              "Scheduling by capacities",
              "Several types of routes",
              "Dynamic departure time",
              "Multiple trips",
              "Recurring routes",
              "Notification with Live Tracking link & ETA",
              "Branded email configuration",
              "Driver statistics",
              "Trip summary by routes",
              "Custom reports",
              "Analytics & Data history",
              "Generating PDF reports via API"
            ],
            "limits": {
              "users": null,
              "storage": null,
              "operations": null,
              "api_calls": null,
              "integrations": "5000",
              "custom_limits": [
                {
                  "name": "Minimum drivers",
                  "value": 3
                }
              ]
            }
          },
          {
            "tier_name": "Advanced Plus",
            "tier_description": "Enhanced plan for larger teams.",
            "monthly_price": 79.0,
            "annual_price": 69.0,
            "annual_discount_percentage": 12.66,
            "setup_fee": null,
            "features": [
              "Add new orders",
              "PIN code confirmation",
              "Live tracking page with updated ETA",
              "Live tracking customization",
              "Updating route start time and ETA",
              "Updating and displaying ETA en route",
              "Updating and displaying new stop sequence",
              "Automatic check-in & check-out",
              "Extended triggers for delivery confirmation",
              "Custom Integration",
              "Developer API support"
            ],
            "limits": {
              "users": null,
              "storage": null,
              "operations": null,
              "api_calls": null,
              "integrations": "5000",
              "custom_limits": [
                {
                  "name": "Minimum drivers",
                  "value": 3
                }
              ]
            }
          },
          {
            "tier_name": "Enterprise",
            "tier_description": "Custom plan for large enterprises.",
            "monthly_price": null,
            "annual_price": null,
            "annual_discount_percentage": null,
            "setup_fee": null,
            "features": [
              "Customized Support & Services Plan"
            ],
            "limits": {
              "users": null,
              "storage": null,
              "operations": null,
              "api_calls": null,
              "integrations": "5000",
              "custom_limits": [
                {
                  "name": "Minimum drivers",
                  "value": 40
                }
              ]
            }
          },
          {
            "tier_name": "S Plan",
            "tier_description": "Usage-based pricing for small order volumes.",
            "monthly_price": 285.0,
            "annual_price": null,
            "annual_discount_percentage": null,
            "setup_fee": null,
            "features": [
              "$0.19 per order/task"
            ],
            "limits": {
              "users": null,
              "storage": null,
              "operations": 1500,
              "api_calls": null,
              "integrations": "5000",
              "custom_limits": null
            }
          },
          {
            "tier_name": "M Plan",
            "tier_description": "Usage-based pricing for medium order volumes.",
            "monthly_price": 510.0,
            "annual_price": null,
            "annual_discount_percentage": null,
            "setup_fee": null,
            "features": [
              "$0.17 per order/task"
            ],
            "limits": {
              "users": null,
              "storage": null,
              "operations": 3000,
              "api_calls": null,
              "integrations": "5000",
              "custom_limits": null
            }
          }
        ],
        "usage_based_pricing": [
          {
            "metric_name": "Orders",
            "unit": "per order/task",
            "base_price": 0.19,
            "tiers": [
              {
                "min": 1.0,
                "max": 1500.0,
                "price": 285.0
              },
              {
                "min": 1501.0,
                "max": 3000.0,
                "price": 510.0
              }
            ]
          }
        ],
        "ai_specific_pricing": null,
        "promotional_offers": null,
        "additional_fees": null,
        "extraction_timestamp": "2025-04-15T08:45:07.458906",
        "schema_validated": true,
        "confidence_score": 95,
        "extraction_error": false,
        "json_repaired": false
      },
      "pricing_analyzed": true
    },
    {
      "url": "https://www.track-pod.com/pricing",
      "is_accessible": true,
      "content": "Page not found | Track-POD\n===============\n                                 \n\n [![Image 1: Track-POD company logo](https://www.track-pod.com/TrackPOD_logo.svg) ![Image 2: Track-POD company small logo](https://www.track-pod.com/TrackPOD_logo_small.svg)](https://www.track-pod.com/)\n\n*   [Home](https://www.track-pod.com/) chevron\\_right\n    \n*   [Solutions](https://www.track-pod.com/pricing/#) chevron\\_right\n    \n    [Route Planning Software](https://www.track-pod.com/route-planning-software/)\n    \n    [Last-Mile Logistics Software](https://www.track-pod.com/last-mile-logistics-software/)\n    \n    [Delivery Driver App](https://www.track-pod.com/delivery-driver-app/)\n    \n    [Transportation Management System](https://www.track-pod.com/transportation-management-system/)\n    \n    [Courier Dispatch Software](https://www.track-pod.com/courier-software/)\n    \n    [Vehicle Check & Safety Management](https://www.track-pod.com/vehicle-check-app/)\n    \n*   [Features](https://www.track-pod.com/pricing/#) chevron\\_right\n    \n    **Web-dashboard**\n    \n    [Planning and optimization](https://www.track-pod.com/blog/plan-track/)\n    \n    [Electronic proof of delivery](https://www.track-pod.com/blog/electronic-signature-capture/)\n    \n    [Delivery tracking](https://www.track-pod.com/blog/last-mile-delivery-tracking/)\n    \n    [Order fulfillment](https://www.track-pod.com/blog/mastering-order-lifecycle-on-track-pod/)\n    \n    [Branded live tracking](https://www.track-pod.com/blog/live-tracking-branding/)\n    \n    [Custom fields for delivery](https://www.track-pod.com/blog/new-custom-fields-for-the-delivery-live-tracking-page/)\n    \n    [Delivery notifications](https://www.track-pod.com/blog/when-to-send-shipping-notifications/)\n    \n    [Shipping Labels](https://www.track-pod.com/blog/shipping-label-template/)\n    \n    [Analytics & Reports](https://www.track-pod.com/blog/analytics-reports/)\n    \n    **Driver app**\n    \n    [ePOD & Delivery confirmation](https://www.track-pod.com/blog/what-is-proof-of-delivery/)\n    \n    [QR/Barcode scanner](https://www.track-pod.com/blog/free-barcode-scanner-app/)\n    \n    [Cash on delivery](https://www.track-pod.com/blog/cash-on-delivery/)\n    \n    [Vehicle check](https://www.track-pod.com/blog/safety-management/)\n    \n    [Geofencing](https://www.track-pod.com/blog/logistics-management-with-geofencing/)\n    \n    [Route management & navigation](https://www.track-pod.com/blog/route-manager-app/)\n    \n*   [Pricing](https://www.track-pod.com/pricing-delivery-app/) chevron\\_right\n    \n*   [Resources](https://www.track-pod.com/pricing/#) chevron\\_right\n    \n    [Blog](https://www.track-pod.com/blog/)\n    \n    [Case Studies](https://www.track-pod.com/case-studies/)\n    \n    [Industries](https://www.track-pod.com/blog/category/industries/)\n    \n    [Help Center](https://track-pod.freshdesk.com/support/home)\n    \n    [API](https://api.track-pod.com/index.html)\n    \n    [Security](https://www.track-pod.com/blog/customer-data-security/)\n    \n    [![Image 3](https://www.track-pod.com/assets/How+to+Route+optimization+using+map+zones+28129__FillWzIyMCwyMjBd.webp)](https://www.track-pod.com/blog/route-optimization-using-map-zones/)\n    \n    **Track-POD feature - MAP ZONES**\n    \n    [How To: Route Optimization Using Map Zones. New at Logistics](https://www.track-pod.com/blog/route-optimization-using-map-zones/)\n    \n    [**Read More**](https://www.track-pod.com/blog/route-optimization-using-map-zones/)\n    \n*   [Contact Us](https://www.track-pod.com/contact-us/) chevron\\_right\n    \n\n[Home](https://www.track-pod.com/)[Solutions chevron\\_right](https://www.track-pod.com/pricing/#)[Features chevron\\_right](https://www.track-pod.com/pricing/#)[Pricing](https://www.track-pod.com/pricing-delivery-app/)[Resources chevron\\_right](https://www.track-pod.com/pricing/#)[Contact Us](https://www.track-pod.com/contact-us/)\n\n[Log In](https://identity.track-pod.com/account/login/)[Try for Free](https://identity.track-pod.com/account/register/)\n\nchevron\\_left\n\n[Route Planning Software](https://www.track-pod.com/route-planning-software/)\n\n[Last-Mile Logistics Software](https://www.track-pod.com/last-mile-logistics-software/)\n\n[Delivery Driver App](https://www.track-pod.com/delivery-driver-app/)\n\n[Transportation Management System](https://www.track-pod.com/transportation-management-system/)\n\n[Courier Dispatch Software](https://www.track-pod.com/courier-software/)\n\n[Vehicle Check & Safety Management](https://www.track-pod.com/vehicle-check-app/)\n\n**Web-dashboard**\n\nchevron\\_right\n\n[Planning and optimization](https://www.track-pod.com/blog/plan-track/)\n\n[Electronic proof of delivery](https://www.track-pod.com/blog/electronic-signature-capture/)\n\n[Delivery tracking](https://www.track-pod.com/blog/last-mile-delivery-tracking/)\n\n[Order fulfillment](https://www.track-pod.com/blog/mastering-order-lifecycle-on-track-pod/)\n\n[Branded live tracking](https://www.track-pod.com/blog/live-tracking-branding/)\n\n[Custom fields for delivery](https://www.track-pod.com/blog/new-custom-fields-for-the-delivery-live-tracking-page/)\n\n[Delivery notifications](https://www.track-pod.com/blog/when-to-send-shipping-notifications/)\n\n[Shipping Labels](https://www.track-pod.com/blog/shipping-label-template/)\n\n[Analytics & Reports](https://www.track-pod.com/blog/analytics-reports/)\n\n**Driver app**\n\nchevron\\_right\n\n[ePOD & Delivery confirmation](https://www.track-pod.com/blog/what-is-proof-of-delivery/)\n\n[QR/Barcode scanner](https://www.track-pod.com/blog/free-barcode-scanner-app/)\n\n[Cash on delivery](https://www.track-pod.com/blog/cash-on-delivery/)\n\n[Vehicle check](https://www.track-pod.com/blog/safety-management/)\n\n[Geofencing](https://www.track-pod.com/blog/logistics-management-with-geofencing/)\n\n[Route management & navigation](https://www.track-pod.com/blog/route-manager-app/)\n\n[Blog](https://www.track-pod.com/blog/)\n\n[Case Studies](https://www.track-pod.com/case-studies/)\n\n[Industries](https://www.track-pod.com/blog/category/industries/)\n\n[Help Center](https://track-pod.freshdesk.com/support/home)\n\n[API](https://api.track-pod.com/index.html)\n\n[Security](https://www.track-pod.com/blog/customer-data-security/)\n\n[![Image 4](https://www.track-pod.com/assets/How+to+Route+optimization+using+map+zones+28129__FillWzcwMCw0MDBd.webp)](https://www.track-pod.com/blog/route-optimization-using-map-zones/)\n\n**Track-POD feature - MAP ZONES**\n\n[How To: Route Optimization Using Map Zones. New at Logistics](https://www.track-pod.com/blog/route-optimization-using-map-zones/)\n\n[**Read More**](https://www.track-pod.com/blog/route-optimization-using-map-zones/)\n\n[Log In](https://identity.track-pod.com/account/login/)[Try for Free](https://identity.track-pod.com/account/register/)\n\n[EN](https://www.track-pod.com/pricing/#)\n\n*   [EN](https://www.track-pod.com/page-not-found/)\n*   [DE](https://www.track-pod.com/de/)\n*   [FR](https://www.track-pod.com/fr/)\n*   [ES](https://www.track-pod.com/es/)\n*   [PT](https://www.track-pod.com/pt/)\n*   [NL](https://www.track-pod.com/nl/)\n*   [PL](https://www.track-pod.com/pl/)\n*   [LT](https://www.track-pod.com/lt/)\n*   [RU](https://www.track-pod.com/ru/)\n\nmenu\n\nSorry, it seems you were trying to access a page that doesn't exist.\n\nPlease check the spelling of the URL you were trying to access and try again.\n\n###### Product\n\n*   [Features](https://www.track-pod.com/features/)\n*   [Pricing](https://www.track-pod.com/pricing-delivery-app/)\n*   [FAQ](https://www.track-pod.com/faq-delivery-system/)\n*   [Status](https://status.track-pod.com/787336601/)\n*   [Industries](https://www.track-pod.com/blog/category/industries/)\n\n###### Solutions\n\n*   [Route planning software](https://www.track-pod.com/route-planning-software/)\n*   [Last-mile logistics software](https://www.track-pod.com/last-mile-logistics-software/)\n*   [Delivery driver app](https://www.track-pod.com/delivery-driver-app/)\n*   [Transportation management system](https://www.track-pod.com/transportation-management-system/)\n*   [Vehicle check & safety management](https://www.track-pod.com/vehicle-check-app/)\n*   [Courier dispatch software](https://www.track-pod.com/courier-software/)\n\n###### Resources\n\n*   [Blog](https://www.track-pod.com/blog/)\n*   [Case studies](https://www.track-pod.com/case-studies/)\n*   [Help center](https://track-pod.freshdesk.com/support/home)\n*   [API Developer](https://www.track-pod.com/api-integration/)\n*   [Terms of Use](https://www.track-pod.com/terms-of-use/)\n*   [Privacy Policy & GDPR](https://www.track-pod.com/privacy-policy/)\n*   [Cookie Policy](https://www.track-pod.com/cookies-policy/)\n\n###### Company\n\n*   [About us](https://www.track-pod.com/about-us/)\n*   [Careers](https://www.linkedin.com/company/track-pod/jobs/)\n*   [Contact us](https://www.track-pod.com/contact-us/)\n\n###### Certified Service Provider\n\n*   [![Image 5: SOC badge](https://www.track-pod.com/_resources/themes/track/pictures/SOC_badge.svg?m=1708882225)](https://www.track-pod.com/blog/customer-data-security/)\n\nCopyright 2024 (c) | Track-POD. All Rights reserved.\n\n*   Follow Track-POD:\n*   [![Image 6: twitter sharing](https://www.track-pod.com/_resources/themes/track/pictures/twitter.svg?m=1701983083)](https://twitter.com/track_pod)\n*   [![Image 7: facebook sharing](https://www.track-pod.com/_resources/themes/track/pictures/facebook.svg?m=1672759102)](https://www.facebook.com/TrackPOD.delivery)\n*   [![Image 8: youtube sharing](https://www.track-pod.com/_resources/themes/track/pictures/youtube.svg?m=1677614387)](https://www.youtube.com/@get-track-pod)\n*   [![Image 9: linkedin sharing](https://www.track-pod.com/_resources/themes/track/pictures/linkedin.svg?m=1672759102)](https://www.linkedin.com/company/track-pod/)\n\n     \n\n![Image 11](https://bat.bing.com/action/0?ti=148009083&Ver=2&mid=6ffff30b-53dc-4706-8f37-2555c57bfa24&bo=1&sid=7b7a3ef019f711f084d1bd93f4b27356&vid=7b7a772019f711f085c1edaee73677bf&vids=1&msclkid=N&pi=918639831&lg=en-US&sw=800&sh=600&sc=24&tl=Page%20not%20found%20%7C%20Track-POD&p=https%3A%2F%2Fwww.track-pod.com%2Fpricing%2F&r=&lt=597&evt=pageLoad&sv=1&cdb=AQAQ&rn=759868)\n\n [![Image 12](blob:https://www.track-pod.com/c82e1687fcc86b84dde9d3121f4a1a4b)](https://consent.studio/?utm_source=banner&utm_medium=title-icon)**Our website uses cookies**\n\nOverview\n\nIn order to personalise content and ads, to remember your preferences, to enable social media features and to measure the traffic to our site, we use cookies. We also share information about your use of our website with our social media, analytics and advertising partners, who may combine that information with data they have already collected from your use of their services.\n\nMore information about the use of cookies on our website [can be found in our privacy policy](https://www.track-pod.com/privacy-policy/).\n\n*    Functional\n*    Analytics\n*    Marketing\n\nReject all Allow selection Accept all\n\n**Track-pod.com Cookies**\n\n**Functional**\n\nCloudflare\n\nCloudflare\n\n[Privacy Portal](https://www.cloudflare.com/privacypolicy/)\n\n\\_\\_cf\\_bm\n\nCloudflare's bot products identify and mitigate automated traffic to protect your site from bad bots. Cloudflare places the \\_\\_cf\\_bm cookie on End User devices that access Customer sites that are protected by Bot Management or Bot Fight Mode. The \\_\\_cf\\_bm cookie is necessary for the proper functioning of these bot solutions.\n\nsession\n\n\\_cfuvid\n\nThe \\_cfuvid cookie is only set when a site uses this option in a Rate Limiting Rule, and is only used to allow the Cloudflare WAF to distinguish individual users who share the same IP address.\n\nsession\n\nGoogle\n\nGoogle\n\n[Privacy Portal](https://business.safety.google/privacy/)\n\n\\_\\_Secure-ENID\n\nUsed by Google to prevent fraudulent login attempts. This also contains a Google user ID which can be used for statistics and marketing purposes following a successful login\n\n11 Months\n\ntest\\_cookie\n\nThis cookie is set by DoubleClick (which is owned by Google) to determine if the website visitor's browser supports cookies.\n\n1 year\n\nDoubleClick/Google Marketing\n\n[Privacy Portal](https://business.safety.google/privacy/)\n\nLinkedIn\n\nLinkedIn\n\n[Privacy Portal](https://www.linkedin.com/legal/privacy-policy)\n\nli\\_gc\n\nUsed to store guest consent to the use of cookies for non-essential purposes\n\n2 years\n\nVallonic B.V.\n\nConsent Studio CMP\n\nconsent-studio\\_\\_consent-id\n\nID of the proof of consent storage within the Consent Studio platform.\n\n30 days\n\nconsent-studio\\_\\_storage\n\nLocal storage for the consent given by the user for certain categories of cookies.\n\n30 days\n\nconsent-studio\\_\\_seen\n\nBoolean that keeps track of whether the user has seen the cookie banner at least once.\n\n30 days\n\nconsent-studio\\_\\_implicit-consent-triggered\n\nWhen a website has implicit consent configured, this cookie stores whether or not it has been triggered or not.\n\n30 days\n\n**Analytics**\n\nGoogle\n\nGoogle Analytics\n\n[Privacy Portal](https://business.safety.google/privacy/)\n\n\\_ga\\_\n\nID used to identify users\n\n2 years\n\n\\_ga\n\nID used to identify users\n\n2 years\n\n**Marketing**\n\nHubSpot\n\nHubspot\n\n[Privacy Portal](https://legal.hubspot.com/privacy-policy)\n\n\\_\\_hstc\n\nThe main cookie for tracking visitors.\n\n13 months\n\nhubspotutk\n\nThis cookie keeps track of a visitor's identity. It is passed to HubSpot on form submission and used when deduplicating contacts.\n\n13 months\n\n\\_\\_hssrc\n\nWhenever HubSpot changes the session cookie, this cookie is also set to determine if the visitor has restarted their browser.\n\nsession\n\n\\_\\_hssc\n\nThis cookie keeps track of sessions.\n\n30 minutes\n\nGoogle\n\nGoogle\n\n[Privacy Portal](https://business.safety.google/privacy/)\n\n\\_gcl\\_au\n\nUsed by Google AdSense for experimenting with advertisement efficiency across websites using their services.\n\n3 months\n\nFacebook\n\nFacebook\n\n[Privacy Portal](https://www.facebook.com/about/privacy/)\n\n\\_fbp\n\nUsed by Facebook to deliver a series of advertisement products such as real time bidding from third party advertisers\n\n4 months\n\nMicrosoft\n\nBing / Microsoft\n\n[Privacy Portal](https://account.microsoft.com/privacy)\n\nMUID\n\nIdentifies unique web browsers visiting Microsoft sites. These cookies are used for advertising, site analytics, and other operational purposes.\n\n1 year\n\n\\_uetsid\n\nThis cookie is used by Bing to determine what ads should be shown that may be relevant to the end user perusing the site.\n\n30 minutes\n\n\\_uetvid\n\nThis is a cookie utilised by Microsoft Bing Ads and is a tracking cookie. It allows us to engage with a user that has previously visited our website.\n\n16 days\n\nLinkedIn\n\nLinkedIn\n\n[Privacy Portal](https://www.linkedin.com/legal/privacy-policy)\n\nbcookie\n\nUsed by LinkedIn to track the use of embedded services.\n\n1 year\n\nlidc\n\nUsed by the social networking service, LinkedIn, for tracking the use of embedded services.\n\n1 day\n\n**\u2014**\n\nUnknown\n\nUnknown\n\ngaconnector\\_GA\\_Measurement\\_ID\n\n3 months\n\ngaconnector\\_pages\\_visited\\_list\n\n3 months\n\ngaconnector\\_page\\_visits\n\n3 months\n\ngaconnector\\_GA\\_Client\\_ID\n\n3 months\n\ngaconnector\\_GA\\_Session\\_ID\n\n3 months\n\ngaconnector\\_gclid\n\n3 months\n\ngaconnector\\_fc\\_source\n\n3 months\n\ngaconnector\\_lc\\_source\n\n3 months\n\ngaconnector\\_fc\\_medium\n\n3 months\n\ngaconnector\\_lc\\_medium\n\n3 months\n\ngaconnector\\_fc\\_campaign\n\n3 months\n\ngaconnector\\_lc\\_campaign\n\n3 months\n\ngaconnector\\_fc\\_term\n\n3 months\n\ngaconnector\\_lc\\_term\n\n3 months\n\ngaconnector\\_fc\\_content\n\n3 months\n\ngaconnector\\_lc\\_content\n\n3 months\n\ngaconnector\\_fc\\_landing\n\n3 months\n\ngaconnector\\_lc\\_landing\n\n3 months\n\ngaconnector\\_fc\\_referrer\n\n3 months\n\ngaconnector\\_lc\\_referrer\n\n3 months\n\ngaconnector\\_fc\\_channel\n\n3 months\n\ngaconnector\\_lc\\_channel\n\n3 months\n\ngaconnector\\_ip\\_address\n\n3 months\n\ngaconnector\\_OS\n\n3 months\n\ngaconnector\\_device\n\n3 months\n\ngaconnector\\_browser\n\n3 months\n\ngaconnector\\_city\n\n3 months\n\ngaconnector\\_country\n\n3 months\n\ngaconnector\\_country\\_code\n\n3 months\n\ngaconnector\\_region\n\n3 months\n\ngaconnector\\_time\\_zone\n\n3 months\n\ngaconnector\\_latitude\n\n3 months\n\ngaconnector\\_longitude\n\n3 months\n\ngaconnector\\_all\\_traffic\\_sources\n\n3 months\n\ngaconnector\\_fc\\_timestamp\n\n3 months\n\ngaconnector\\_lc\\_timestamp\n\n3 months\n\ngaconnector\\_time\\_passed\n\n3 months\n\nSorry, it seems you were trying to access a page that doesn't exist.Please check the spelling of the URL you were trying to access and try again.",
      "error": null,
      "pricing_data": {
        "app_id": "track_pod",
        "app_name": "Track-POD",
        "app_slug": "track-pod",
        "pricing_url": "https://www.track-pod.com/pricing-delivery-app/",
        "source_url": "https://www.track-pod.com/pricing-delivery-app/",
        "all_pricing_urls": [
          "https://www.track-pod.com/pricing-delivery-app/"
        ],
        "price_model_type": [
          "PriceModelType.SUBSCRIPTION"
        ],
        "has_free_tier": false,
        "has_free_trial": true,
        "free_trial_period_days": null,
        "currency": "USD",
        "is_pricing_public": false,
        "pricing_page_accessible": true,
        "pricing_notes": "The pricing page was not accessible, and detailed pricing information could not be extracted.",
        "pricing_tiers": null,
        "usage_based_pricing": null,
        "ai_specific_pricing": null,
        "promotional_offers": null,
        "additional_fees": null,
        "extraction_timestamp": "2025-04-15T08:45:24.412771",
        "schema_validated": true,
        "confidence_score": 90,
        "extraction_error": false,
        "json_repaired": false
      },
      "pricing_analyzed": true
    }
  ],
  "results_directory": "pricing_results\\track-pod\\20250415_084524"
}