{
  "app_name": "BugHerd",
  "app_slug": "bugherd",
  "search_term": "Find the official pricing page URL for BugHerd (bugherd.com). Only provide the exact URL to the pricing page, not a summary of pricing information.",
  "timestamp": 1744722127.741438,
  "response_text": [
    "The URL to the official pricing page for BugHerd is: [https://www.bugherd.com/pricing](https://www.bugherd.com/pricing)\u30103:0\u2020source\u3011."
  ],
  "citations": [
    {
      "title": "BugHerd Pricing - Flexible Plans for Seamless Website Feedback Management",
      "url": "https://bugherd.com/pricing"
    }
  ],
  "extracted_content": [
    {
      "url": "https://www.bugherd.com/pricing",
      "is_accessible": true,
      "content": "Simple, straightforward plans for every team.\n---------------------------------------------\n\n**Whether you're a freelancer, a boutique agency or a large team, we have a plan for you.** \u2028  \nAll BugHerd plans include unlimited feedback, powerful integrations, and a customizable project board to streamline your workflow. Upgrade for more users, enhanced security, and dedicated support to ensure project success.\n\n**Monthly**\n\n**Yearly** **(2 months free!)**\n\n![Image 1](https://cdn.prod.website-files.com/5f348cefc28f736422d5b00d/66cd588c8fb71f885606e0bc_ic-plan-01%20standard-outline.svg)\n\n##### Standard\n\n$49\n\n$49\n\n**/ mo**\n\n##### Members:\n\n##### 5\n\n**Ideal for freelancers and small teams.**\n\n*   Unlimited Client users\n*   Unlimited Projects\n*   Feedback on websites, Figma designs, PDFs, images\n*   Capture screenshots & technical metadata\n*   Video feedback\n*   Standard integrations (Trello, Slack, GitHub + 12 more)\n\n##### POPULAR \ud83d\udd25\n\n![Image 2: red pin icon](https://cdn.prod.website-files.com/5f348cefc28f73bfbed5b00a/666fdaeb587fa0982ec0a678_pattern-pin-red.svg)\n\n![Image 3](https://cdn.prod.website-files.com/5f348cefc28f736422d5b00d/66cd589dc3cc86196a210904_ic-plan-02%20studio-outline.svg)\n\n##### Studio\n\n$79\n\n$79\n\n**/ mo**\n\n##### Members:\n\n##### 10\n\n**Perfect for growing agencies needing to manage multiple projects and clients effectively.**\n\nEverything in **Standard**, plus:\n\n*   More Members\n*   More storage\n\n##### POPULAR \ud83d\udd25\n\n![Image 4: red pin icon](https://cdn.prod.website-files.com/5f348cefc28f73bfbed5b00a/666fdaeb587fa0982ec0a678_pattern-pin-red.svg)\n\n![Image 5](https://cdn.prod.website-files.com/5f348cefc28f736422d5b00d/66cd58aa15067c3c944f5374_ic-plan-03%20premium-outline.svg)\n\n##### Premium\n\n$149\n\n$149\n\n**/ mo**\n\n##### Members:\n\n##### 25\n\n**Tailored for agencies and larger teams who want to deliver an exceptional project experience for clients.**\n\nEverything in **Studio**, plus:\n\n*   Custom branding\n*   Enhanced client collaboration\n*   Share member feedback with clients\n*   Private Team commenting\n*   Client project board\n*   Premium integrations (Jira, Asana, Linear, ClickUp, Monday.com)\n\n##### POPULAR \ud83d\udd25\n\n![Image 6: red pin icon](https://cdn.prod.website-files.com/5f348cefc28f73bfbed5b00a/666fdaeb587fa0982ec0a678_pattern-pin-red.svg)\n\n![Image 7](https://cdn.prod.website-files.com/5f348cefc28f736422d5b00d/66cd58b59c68e38126217fcb_ic-plan-04%20deluxe-outline.svg)\n\n##### Custom\n\nCustom pricing\n\nCustom pricing\n\n**/ mo**\n\n##### Members:\n\n##### Custom\n\n**Designed for enterprises with complex workflows and dedicated support needs.**\n\nEverything in **Premium**, plus:\n\n*   Custom limit on Members\n*   Dedicated Success Manager\n*   Onboarding & Training Support\n*   Secure single sign-on (SSO)\n\n##### POPULAR \ud83d\udd25\n\n![Image 8: red pin icon](https://cdn.prod.website-files.com/5f348cefc28f73bfbed5b00a/666fdaeb587fa0982ec0a678_pattern-pin-red.svg)\n\n![Image 9](https://cdn.prod.website-files.com/5f348cefc28f736422d5b00d/66cd588c8fb71f885606e0bc_ic-plan-01%20standard-outline.svg)\n\n##### Standard\n\n$49\n\n$41\n\n**/ mo**\n\n##### Members:\n\n##### 5\n\n**Ideal for freelancers and small teams.**\n\n*   Unlimited Client users\n*   Unlimited Projects\n*   Feedback on websites, Figma designs, PDFs, images\n*   Capture screenshots & technical metadata\n*   Video feedback\n*   Standard integrations (Trello, Slack, GitHub + 12 more)\n\n##### POPULAR\n\n![Image 10: red pin icon](https://cdn.prod.website-files.com/5f348cefc28f73bfbed5b00a/666fdaeb587fa0982ec0a678_pattern-pin-red.svg)\n\n![Image 11](https://cdn.prod.website-files.com/5f348cefc28f736422d5b00d/66cd589dc3cc86196a210904_ic-plan-02%20studio-outline.svg)\n\n##### Studio\n\n$79\n\n$66\n\n**/ mo**\n\n##### Members:\n\n##### 10\n\n**Perfect for growing agencies needing to manage multiple projects and clients effectively.**\n\nEverything in **Standard**, plus:\n\n*   More Members\n*   More storage\n\n##### POPULAR\n\n![Image 12: red pin icon](https://cdn.prod.website-files.com/5f348cefc28f73bfbed5b00a/666fdaeb587fa0982ec0a678_pattern-pin-red.svg)\n\n![Image 13](https://cdn.prod.website-files.com/5f348cefc28f736422d5b00d/66cd58aa15067c3c944f5374_ic-plan-03%20premium-outline.svg)\n\n##### Premium\n\n$149\n\n$124\n\n**/ mo**\n\n##### Members:\n\n##### 25\n\n**Tailored for agencies and larger teams who want to deliver an exceptional project experience for clients.**\n\nEverything in **Studio**, plus:\n\n*   Custom branding\n*   Enhanced client collaboration\n*   Share member feedback with clients\n*   Private Team commenting\n*   Client project board\n*   Premium integrations (Jira, Asana, Linear, ClickUp, Monday.com)\n\n##### POPULAR\n\n![Image 14: red pin icon](https://cdn.prod.website-files.com/5f348cefc28f73bfbed5b00a/666fdaeb587fa0982ec0a678_pattern-pin-red.svg)\n\n![Image 15](https://cdn.prod.website-files.com/5f348cefc28f736422d5b00d/66cd58b59c68e38126217fcb_ic-plan-04%20deluxe-outline.svg)\n\n##### Custom\n\nCustom pricing\n\nCustom pricing\n\n**/ mo**\n\n##### Members:\n\n##### Custom\n\n**Designed for enterprises with complex workflows and dedicated support needs.**\n\nEverything in **Premium**, plus:\n\n*   Custom limit on Members\n*   Dedicated Success Manager\n*   Onboarding & Training Support\n*   Secure single sign-on (SSO)\n\n##### POPULAR\n\n![Image 16: red pin icon](https://cdn.prod.website-files.com/5f348cefc28f73bfbed5b00a/666fdaeb587fa0982ec0a678_pattern-pin-red.svg)\n\nPrices shown are in US dollars and exclude applicable taxes.\n\n### Need more seats?\n\nAdd additional members for just $80/year for each additional user.  \nSelect a plan and enter how many additional members you require.\n\n### Compare features  \n\u200d\n\n##### USAGE\n\n##### Members\n\n(Devs, designers, PMs, QAs)\n\nAdditional member(s) available for $6.60 per user (billed annually).\n\n##### Clients\n\n(Clients, stakeholders)\n\n5\n\nUnlimited\n\nUnlimited\n\n10GB\n\n10\n\nUnlimited\n\nUnlimited\n\n25GB\n\n25\n\nUnlimited\n\nUnlimited\n\n50GB\n\nCustom\n\nUnlimited\n\nUnlimited\n\nUnlimited\n\n##### FEEDBACK FEATURES\n\n##### Capture screenshots & technical data\n\nExtension required on Standard and Studio.\n\n##### Annotating screenshots\n\nExtension required on Standard and Studio.\n\n![Image 17: icon of figma logo](https://cdn.prod.website-files.com/5f348cefc28f73bfbed5b00a/653891c5105ef6247fd2711e_ic-figma.svg)\n\n![Image 18: icon of pdf](https://cdn.prod.website-files.com/5f348cefc28f73bfbed5b00a/653891c6beb999d9c5766be6_ic-pdf.svg)\n\n![Image 19: icon of image](https://cdn.prod.website-files.com/5f348cefc28f73bfbed5b00a/653891c6d33bd473fb0480af_ic-images.svg)\n\n\u2705\n\n\u274c\n\n\u2705\n\n\u274c\n\n\u2705\n\n\u274c\n\n\u2705\n\n\u274c\n\n\u2705\n\n\u274c\n\n\u2705\n\n\u274c\n\n\u2705\n\n\u274c\n\n\u2705\n\n\u274c\n\n\u2705\n\n\u274c\n\n\u2705\n\n\u274c\n\n\u2705\n\n\u274c\n\n\u2705\n\n\u274c\n\n\u2705\n\n\u274c\n\n\u2705\n\n\u274c\n\n\u2705\n\n\u274c\n\n\u2705\n\n\u274c\n\n\u2705\n\n\u274c\n\n\u2705\n\n\u274c\n\n\u2705\n\n\u274c\n\n\u2705\n\n\u274c\n\n\u2705\n\n\u274c\n\n\u2705\n\n\u274c\n\n\u2705\n\n\u274c\n\n\u2705\n\n\u274c\n\n\u2705\n\n\u274c\n\n\u2705\n\n\u274c\n\n\u2705\n\n\u274c\n\n\u2705\n\n\u274c\n\n##### CLIENT EXPERIENCE\n\n\u2705\n\n\u274c\n\n\u2705\n\n\u274c\n\n\u2705\n\n\u274c\n\n\u2705\n\n\u274c\n\n\u2705\n\n\u274c\n\n\u2705\n\n\u274c\n\n\u2705\n\n\u274c\n\n\u2705\n\n\u274c\n\n\u2705\n\n\u274c\n\n\u2705\n\n\u274c\n\n\u2705\n\n\u274c\n\n\u2705\n\n\u274c\n\n\u2705\n\n\u274c\n\n\u2705\n\n\u274c\n\n\u2705\n\n\u274c\n\n\u2705\n\n\u274c\n\n##### WHITE LABELLING\n\n\u2705\n\n\u274c\n\n\u2705\n\n\u274c\n\n\u2705\n\n\u274c\n\n\u2705\n\n\u274c\n\n##### SECURITY & SUPPORT\n\n\u2705\n\n\u274c\n\n\u2705\n\n\u274c\n\n\u2705\n\n\u274c\n\n\u2705\n\n\u274c\n\n\u2705\n\n\u274c\n\n\u2705\n\n\u274c\n\n\u2705\n\n\u274c\n\n\u2705\n\n\u274c\n\n\u2705\n\n\u274c\n\n\u2705\n\n\u274c\n\n\u2705\n\n\u274c\n\n\u2705\n\n\u274c\n\n\u2705\n\n\u274c\n\n\u2705\n\n\u274c\n\n\u2705\n\n\u274c\n\n\u2705\n\n\u274c\n\n##### INTEGRATIONS\n\n![Image 20: icon - integration - slack](https://cdn.prod.website-files.com/5f348cefc28f73bfbed5b00a/6347bfaeb292a35c6799cb89_ic-integration-slack%403x.png)\n\n![Image 21: ms teams icon](https://cdn.prod.website-files.com/5f348cefc28f73bfbed5b00a/66ac2e1e1f22c1d767fc1b82_ic-integration-ms%20teams.svg)\n\n![Image 22: icon - integration - zapier](https://cdn.prod.website-files.com/5f348cefc28f73bfbed5b00a/6347bfae3a6b0d86062e660e_ic-integration-zapier%403x.png)\n\n![Image 23: make logo](https://cdn.prod.website-files.com/5f348cefc28f73bfbed5b00a/662cbb5fd0e9217e80a38b48_ic-integration-make.svg)\n\n![Image 24: icon - integration - github](https://cdn.prod.website-files.com/5f348cefc28f73bfbed5b00a/6348986a247ff343d97f8e57_ic-integration-github%403x.png)\n\n![Image 25: fullstory icon](https://cdn.prod.website-files.com/5f348cefc28f73bfbed5b00a/6685f72407e35c78b9decfab_ic-integration-fullstory-high%20res.png)\n\n![Image 26: logrocket icon](https://cdn.prod.website-files.com/5f348cefc28f73bfbed5b00a/668f4f21dc9fbbc3a66bfe0e_ic-integration-logrocket-high%20res.png)\n\n![Image 27: harvest logo](https://cdn.prod.website-files.com/5f348cefc28f73bfbed5b00a/66f4e0e5bfc12ceb1feead06_ic-integration-harvest.png)\n\n![Image 28: integration - timedoctor](https://cdn.prod.website-files.com/5f348cefc28f73bfbed5b00a/654d7d1a37ce3fa4801b2ab4_ic-integration-timedoctor%403x.png)\n\n![Image 29: integration - firmao](https://cdn.prod.website-files.com/5f348cefc28f73bfbed5b00a/654d7d1a058b6fd5b3e8d673_ic-integration-firmao%403x.png)\n\n![Image 30: lambdatest icon](https://cdn.prod.website-files.com/5f348cefc28f73bfbed5b00a/649e2b277c9c43cccf2aa309_ic-integration-lambdatest%403x.png)\n\n![Image 31: icon - integration - trello](https://cdn.prod.website-files.com/5f348cefc28f73bfbed5b00a/6347bfaee6e3d7f21d524446_ic-integration-trello%403x.png)\n\n![Image 32: integration productive logo](https://cdn.prod.website-files.com/5f348cefc28f73bfbed5b00a/66e8da263360505ceebd4c51_ic-integration-productive.svg)\n\n![Image 33: icon - integration - jira](https://cdn.prod.website-files.com/5f348cefc28f73bfbed5b00a/6347bfade07b280feee811c8_ic-integration-jira%403x.png)\n\n![Image 34: icon - integration - asana](https://cdn.prod.website-files.com/5f348cefc28f73bfbed5b00a/6347bfb6f870e5700ee694d6_ic-integration-asana%403x.png)\n\n![Image 35: linear logo](https://cdn.prod.website-files.com/5f348cefc28f73bfbed5b00a/661f685df697e589a62d0f99_ic-integration-linear.svg)\n\n![Image 36: clickup logo](https://cdn.prod.website-files.com/5f348cefc28f73bfbed5b00a/66344df594ef00243d905505_ic-integration-clickup.svg)\n\n![Image 37: monday.com logo](https://cdn.prod.website-files.com/5f348cefc28f73bfbed5b00a/66344df59dba56c96bedd604_ic-integration-monday.svg)\n\n![Image 38: integration logo teamwork](https://cdn.prod.website-files.com/5f348cefc28f73bfbed5b00a/6750f32660f2a8cc7d9a7068_ic-integration-teamwork.svg)\n\n\u2705\n\n\u274c\n\n\u2705\n\n\u274c\n\n\u2705\n\n\u274c\n\n\u2705\n\n\u274c\n\n\u2705\n\n\u274c\n\n\u2705\n\n\u274c\n\n\u2705\n\n\u274c\n\n\u2705\n\n\u274c\n\n\u2705\n\n\u274c\n\n\u2705\n\n\u274c\n\n\u2705\n\n\u274c\n\n\u2705\n\n\u274c\n\n\u2705\n\n\u274c\n\n\u2705\n\n\u274c\n\n\u2705\n\n\u274c\n\n\u2705\n\n\u274c\n\n\u2705\n\n\u274c\n\n\u2705\n\n\u274c\n\n\u2705\n\n\u274c\n\n\u2705\n\n\u274c\n\n\u2705\n\n\u274c\n\n\u2705\n\n\u274c\n\n\u2705\n\n\u274c\n\n\u2705\n\n\u274c\n\n\u2705\n\n\u274c\n\n\u2705\n\n\u274c\n\n\u2705\n\n\u274c\n\n\u2705\n\n\u274c\n\n\u2705\n\n\u274c\n\n\u2705\n\n\u274c\n\n\u2705\n\n\u274c\n\n\u2705\n\n\u274c\n\n\u2705\n\n\u274c\n\n\u2705\n\n\u274c\n\n\u2705\n\n\u274c\n\n\u2705\n\n\u274c\n\n\u2705\n\n\u274c\n\n\u2705\n\n\u274c\n\n\u2705\n\n\u274c\n\n\u2705\n\n\u274c\n\n\u2705\n\n\u274c\n\n\u2705\n\n\u274c\n\n\u2705\n\n\u274c\n\n\u2705\n\n\u274c\n\n\u2705\n\n\u274c\n\n\u2705\n\n\u274c\n\n\u2705\n\n\u274c\n\n\u2705\n\n\u274c\n\n\u2705\n\n\u274c\n\n\u2705\n\n\u274c\n\n\u2705\n\n\u274c\n\n\u2705\n\n\u274c\n\n\u2705\n\n\u274c\n\n\u2705\n\n\u274c\n\n\u2705\n\n\u274c\n\n\u2705\n\n\u274c\n\n\u2705\n\n\u274c\n\n\u2705\n\n\u274c\n\n\u2705\n\n\u274c\n\n\u2705\n\n\u274c\n\n\u2705\n\n\u274c\n\n\u2705\n\n\u274c\n\n\u2705\n\n\u274c\n\n\u2705\n\n\u274c\n\n\u2705\n\n\u274c\n\n\u2705\n\n\u274c\n\n\u2705\n\n\u274c\n\n\u2705\n\n\u274c\n\n\u2705\n\n\u274c\n\n\u2705\n\n\u274c\n\n\u2705\n\n\u274c\n\n\u2705\n\n\u274c\n\n\u2705\n\n\u274c\n\n\u2705\n\n\u274c\n\n\u2705\n\n\u274c\n\n\u2705\n\n\u274c\n\n##### USAGE\n\n##### Members\n\n(Devs, designers, PMs, QAs)\n\nAdditional member(s) available for $8 per user (billed monthly).\n\nStandard\n\n5 members\n\nStudio\n\n10 members\n\nPremium\n\n25 members\n\nEnterprise\n\nCustom limit\n\n##### Guests\n\n(Clients, stakeholders)\n\nStandard\n\n\u221e Unlimited\n\nStudio\n\n\u221e Unlimited\n\nPremium\n\n\u221e Unlimited\n\nEnterprise\n\n\u221e Unlimited\n\nStandard\n\n10 GB\n\nStudio\n\n25 GB\n\nPremium\n\n50 GB\n\nEnterprise\n\n\u221e Unlimited\n\nStandard\n\n\u221e Unlimited\n\nStudio\n\n\u221e Unlimited\n\nPremium\n\n\u221e Unlimited\n\nEnterprise\n\n\u221e Unlimited\n\n##### FEEDBACK FEATURES\n\n##### Capture screenshots & technical data\n\nBrowser, OS, screen size & more\n\nStandard\n\n\u2705\n\nStudio\n\n\u2705\n\nPremium\n\n\u2705\n\nEnterprise\n\n\u2705\n\nStandard\n\n\u2705\n\nStudio\n\n\u2705\n\nPremium\n\n\u2705\n\nEnterprise\n\n\u2705\n\n![Image 39: icon of figma logo](https://cdn.prod.website-files.com/5f348cefc28f73bfbed5b00a/653891c5105ef6247fd2711e_ic-figma.svg)\n\nStandard\n\n\u2705\n\nStudio\n\n\u2705\n\nPremium\n\n\u2705\n\nEnterprise\n\n\u2705\n\nStandard\n\n\u2705\n\nStudio\n\n\u2705\n\nPremium\n\n\u2705\n\nEnterprise\n\n\u2705\n\nStandard\n\n\u2705\n\nStudio\n\n\u2705\n\nPremium\n\n\u2705\n\nEnterprise\n\n\u2705\n\n##### WHITE LABELLING\n\nStandard\n\n\u274c\n\nStudio\n\n\u274c\n\nPremium\n\n\u2705\n\nEnterprise\n\n\u2705\n\n##### GUEST EXPERIENCE\n\nStandard\n\n\u274c\n\nStudio\n\n\u274c\n\nPremium\n\n\u2705\n\nEnterprise\n\n\u2705\n\nStandard\n\n\u274c\n\nStudio\n\n\u274c\n\nPremium\n\n\u2705\n\nEnterprise\n\n\u2705\n\nStandard\n\n\u274c\n\nStudio\n\n\u274c\n\nPremium\n\n\u2705\n\nEnterprise\n\n\u2705\n\nStandard\n\n\u274c\n\nStudio\n\n\u274c\n\nPremium\n\n\u2705\n\nEnterprise\n\n\u2705\n\n##### SECURITY & SUPPORT\n\nStandard\n\n\u274c\n\nStudio\n\n\u274c\n\nPremium\n\n\u274c\n\nEnterprise\n\n\u2705\n\nStandard\n\n\u274c\n\nStudio\n\n\u274c\n\nPremium\n\n\u274c\n\nEnterprise\n\n\u2705\n\nStandard\n\n\u274c\n\nStudio\n\n\u274c\n\nPremium\n\n\u274c\n\nEnterprise\n\n\u2705\n\nStandard\n\n\u274c\n\nStudio\n\n\u274c\n\nPremium\n\n\u274c\n\nEnterprise\n\n\u2705\n\n##### INTEGRATIONS\n\nFrequently asked questions\n--------------------------\n\nDo I need to install anything?\n\nWhere possible we recommend installing BugHerd via a simple one line JavaScript tag. If you are unable to install any code on your website BugHerd can also be accessed via our browser extension.\n\nIs BugHerd mobile friendly?\n\nThe BugHerd sidebar is fully responsive working on mobile websites allowing you to log/close tasks and manage your workflow.\n\nDo you offer annual discounts?\n\nYes. Select a yearly plan for BugHerd and get two months free.\n\nCan I export my data?\n\nYes. All BugHerd plans support data export via CSV, XML & JSON. If you're feeling more technical you can also access your tasks via the BugHerd API.\n\nTry BugHerd free for 7 days. No credit card required. Explore flexible pricing plans designed to make managing client feedback on websites ridiculously easy.",
      "error": null,
      "pricing_data": {
        "app_id": "bugherd",
        "app_name": "BugHerd",
        "app_slug": "bugherd",
        "pricing_url": null,
        "source_url": null,
        "all_pricing_urls": null,
        "price_model_type": [
          "PriceModelType.SUBSCRIPTION",
          "PriceModelType.USAGE_BASED",
          "PriceModelType.FREE_TIER"
        ],
        "has_free_tier": false,
        "has_free_trial": true,
        "free_trial_period_days": 7,
        "currency": "USD",
        "is_pricing_public": true,
        "pricing_page_accessible": true,
        "pricing_notes": "Annual plans offer a discount equivalent to two months free.",
        "pricing_tiers": [
          {
            "tier_name": "Standard",
            "tier_description": "Ideal for freelancers and small teams.",
            "monthly_price": 49.0,
            "annual_price": 41.0,
            "annual_discount_percentage": 16.33,
            "setup_fee": null,
            "features": [
              "Unlimited Client users",
              "Unlimited Projects",
              "Feedback on websites, Figma designs, PDFs, images",
              "Capture screenshots & technical metadata",
              "Video feedback",
              "Standard integrations (Trello, Slack, GitHub + 12 more)"
            ],
            "limits": {
              "users": 5,
              "storage": "10GB",
              "operations": "unlimited",
              "api_calls": "unlimited",
              "integrations": "unlimited",
              "custom_limits": null
            }
          },
          {
            "tier_name": "Studio",
            "tier_description": "Perfect for growing agencies needing to manage multiple projects and clients effectively.",
            "monthly_price": 79.0,
            "annual_price": 66.0,
            "annual_discount_percentage": 16.46,
            "setup_fee": null,
            "features": [
              "Everything in Standard",
              "More Members",
              "More storage"
            ],
            "limits": {
              "users": 10,
              "storage": "25GB",
              "operations": "unlimited",
              "api_calls": "unlimited",
              "integrations": "unlimited",
              "custom_limits": null
            }
          },
          {
            "tier_name": "Premium",
            "tier_description": "Tailored for agencies and larger teams who want to deliver an exceptional project experience for clients.",
            "monthly_price": 149.0,
            "annual_price": 124.0,
            "annual_discount_percentage": 16.78,
            "setup_fee": null,
            "features": [
              "Everything in Studio",
              "Custom branding",
              "Enhanced client collaboration",
              "Share member feedback with clients",
              "Private Team commenting",
              "Client project board",
              "Premium integrations (Jira, Asana, Linear, ClickUp, Monday.com)"
            ],
            "limits": {
              "users": 25,
              "storage": "50GB",
              "operations": "unlimited",
              "api_calls": "unlimited",
              "integrations": "unlimited",
              "custom_limits": null
            }
          },
          {
            "tier_name": "Custom",
            "tier_description": "Designed for enterprises with complex workflows and dedicated support needs.",
            "monthly_price": null,
            "annual_price": null,
            "annual_discount_percentage": null,
            "setup_fee": null,
            "features": [
              "Everything in Premium",
              "Custom limit on Members",
              "Dedicated Success Manager",
              "Onboarding & Training Support",
              "Secure single sign-on (SSO)"
            ],
            "limits": {
              "users": "custom",
              "storage": "unlimited",
              "operations": "unlimited",
              "api_calls": "unlimited",
              "integrations": "unlimited",
              "custom_limits": null
            }
          }
        ],
        "usage_based_pricing": [
          {
            "metric_name": "Additional members",
            "unit": "per user",
            "base_price": 80.0,
            "tiers": null
          }
        ],
        "ai_specific_pricing": null,
        "promotional_offers": null,
        "additional_fees": null,
        "extraction_timestamp": "2025-04-15T09:02:16.977265",
        "schema_validated": true,
        "confidence_score": 100,
        "extraction_error": false,
        "json_repaired": false
      },
      "pricing_analyzed": true
    },
    {
      "url": "https://bugherd.com/pricing",
      "is_accessible": true,
      "content": "Simple, straightforward plans for every team.\n---------------------------------------------\n\n**Whether you're a freelancer, a boutique agency or a large team, we have a plan for you.** \u2028  \nAll BugHerd plans include unlimited feedback, powerful integrations, and a customizable project board to streamline your workflow. Upgrade for more users, enhanced security, and dedicated support to ensure project success.\n\n**Monthly**\n\n**Yearly** **(2 months free!)**\n\n![Image 1](https://cdn.prod.website-files.com/5f348cefc28f736422d5b00d/66cd588c8fb71f885606e0bc_ic-plan-01%20standard-outline.svg)\n\n##### Standard\n\n$49\n\n$49\n\n**/ mo**\n\n##### Members:\n\n##### 5\n\n**Ideal for freelancers and small teams.**\n\n*   Unlimited Client users\n*   Unlimited Projects\n*   Feedback on websites, Figma designs, PDFs, images\n*   Capture screenshots & technical metadata\n*   Video feedback\n*   Standard integrations (Trello, Slack, GitHub + 12 more)\n\n##### POPULAR \ud83d\udd25\n\n![Image 2: red pin icon](https://cdn.prod.website-files.com/5f348cefc28f73bfbed5b00a/666fdaeb587fa0982ec0a678_pattern-pin-red.svg)\n\n![Image 3](https://cdn.prod.website-files.com/5f348cefc28f736422d5b00d/66cd589dc3cc86196a210904_ic-plan-02%20studio-outline.svg)\n\n##### Studio\n\n$79\n\n$79\n\n**/ mo**\n\n##### Members:\n\n##### 10\n\n**Perfect for growing agencies needing to manage multiple projects and clients effectively.**\n\nEverything in **Standard**, plus:\n\n*   More Members\n*   More storage\n\n##### POPULAR \ud83d\udd25\n\n![Image 4: red pin icon](https://cdn.prod.website-files.com/5f348cefc28f73bfbed5b00a/666fdaeb587fa0982ec0a678_pattern-pin-red.svg)\n\n![Image 5](https://cdn.prod.website-files.com/5f348cefc28f736422d5b00d/66cd58aa15067c3c944f5374_ic-plan-03%20premium-outline.svg)\n\n##### Premium\n\n$149\n\n$149\n\n**/ mo**\n\n##### Members:\n\n##### 25\n\n**Tailored for agencies and larger teams who want to deliver an exceptional project experience for clients.**\n\nEverything in **Studio**, plus:\n\n*   Custom branding\n*   Enhanced client collaboration\n*   Share member feedback with clients\n*   Private Team commenting\n*   Client project board\n*   Premium integrations (Jira, Asana, Linear, ClickUp, Monday.com)\n\n##### POPULAR \ud83d\udd25\n\n![Image 6: red pin icon](https://cdn.prod.website-files.com/5f348cefc28f73bfbed5b00a/666fdaeb587fa0982ec0a678_pattern-pin-red.svg)\n\n![Image 7](https://cdn.prod.website-files.com/5f348cefc28f736422d5b00d/66cd58b59c68e38126217fcb_ic-plan-04%20deluxe-outline.svg)\n\n##### Custom\n\nCustom pricing\n\nCustom pricing\n\n**/ mo**\n\n##### Members:\n\n##### Custom\n\n**Designed for enterprises with complex workflows and dedicated support needs.**\n\nEverything in **Premium**, plus:\n\n*   Custom limit on Members\n*   Dedicated Success Manager\n*   Onboarding & Training Support\n*   Secure single sign-on (SSO)\n\n##### POPULAR \ud83d\udd25\n\n![Image 8: red pin icon](https://cdn.prod.website-files.com/5f348cefc28f73bfbed5b00a/666fdaeb587fa0982ec0a678_pattern-pin-red.svg)\n\n![Image 9](https://cdn.prod.website-files.com/5f348cefc28f736422d5b00d/66cd588c8fb71f885606e0bc_ic-plan-01%20standard-outline.svg)\n\n##### Standard\n\n$49\n\n$41\n\n**/ mo**\n\n##### Members:\n\n##### 5\n\n**Ideal for freelancers and small teams.**\n\n*   Unlimited Client users\n*   Unlimited Projects\n*   Feedback on websites, Figma designs, PDFs, images\n*   Capture screenshots & technical metadata\n*   Video feedback\n*   Standard integrations (Trello, Slack, GitHub + 12 more)\n\n##### POPULAR\n\n![Image 10: red pin icon](https://cdn.prod.website-files.com/5f348cefc28f73bfbed5b00a/666fdaeb587fa0982ec0a678_pattern-pin-red.svg)\n\n![Image 11](https://cdn.prod.website-files.com/5f348cefc28f736422d5b00d/66cd589dc3cc86196a210904_ic-plan-02%20studio-outline.svg)\n\n##### Studio\n\n$79\n\n$66\n\n**/ mo**\n\n##### Members:\n\n##### 10\n\n**Perfect for growing agencies needing to manage multiple projects and clients effectively.**\n\nEverything in **Standard**, plus:\n\n*   More Members\n*   More storage\n\n##### POPULAR\n\n![Image 12: red pin icon](https://cdn.prod.website-files.com/5f348cefc28f73bfbed5b00a/666fdaeb587fa0982ec0a678_pattern-pin-red.svg)\n\n![Image 13](https://cdn.prod.website-files.com/5f348cefc28f736422d5b00d/66cd58aa15067c3c944f5374_ic-plan-03%20premium-outline.svg)\n\n##### Premium\n\n$149\n\n$124\n\n**/ mo**\n\n##### Members:\n\n##### 25\n\n**Tailored for agencies and larger teams who want to deliver an exceptional project experience for clients.**\n\nEverything in **Studio**, plus:\n\n*   Custom branding\n*   Enhanced client collaboration\n*   Share member feedback with clients\n*   Private Team commenting\n*   Client project board\n*   Premium integrations (Jira, Asana, Linear, ClickUp, Monday.com)\n\n##### POPULAR\n\n![Image 14: red pin icon](https://cdn.prod.website-files.com/5f348cefc28f73bfbed5b00a/666fdaeb587fa0982ec0a678_pattern-pin-red.svg)\n\n![Image 15](https://cdn.prod.website-files.com/5f348cefc28f736422d5b00d/66cd58b59c68e38126217fcb_ic-plan-04%20deluxe-outline.svg)\n\n##### Custom\n\nCustom pricing\n\nCustom pricing\n\n**/ mo**\n\n##### Members:\n\n##### Custom\n\n**Designed for enterprises with complex workflows and dedicated support needs.**\n\nEverything in **Premium**, plus:\n\n*   Custom limit on Members\n*   Dedicated Success Manager\n*   Onboarding & Training Support\n*   Secure single sign-on (SSO)\n\n##### POPULAR\n\n![Image 16: red pin icon](https://cdn.prod.website-files.com/5f348cefc28f73bfbed5b00a/666fdaeb587fa0982ec0a678_pattern-pin-red.svg)\n\nPrices shown are in US dollars and exclude applicable taxes.\n\n### Need more seats?\n\nAdd additional members for just $80/year for each additional user.  \nSelect a plan and enter how many additional members you require.\n\n### Compare features  \n\u200d\n\n##### USAGE\n\n##### Members\n\n(Devs, designers, PMs, QAs)\n\nAdditional member(s) available for $6.60 per user (billed annually).\n\n##### Clients\n\n(Clients, stakeholders)\n\n5\n\nUnlimited\n\nUnlimited\n\n10GB\n\n10\n\nUnlimited\n\nUnlimited\n\n25GB\n\n25\n\nUnlimited\n\nUnlimited\n\n50GB\n\nCustom\n\nUnlimited\n\nUnlimited\n\nUnlimited\n\n##### FEEDBACK FEATURES\n\n##### Capture screenshots & technical data\n\nExtension required on Standard and Studio.\n\n##### Annotating screenshots\n\nExtension required on Standard and Studio.\n\n![Image 17: icon of figma logo](https://cdn.prod.website-files.com/5f348cefc28f73bfbed5b00a/653891c5105ef6247fd2711e_ic-figma.svg)\n\n![Image 18: icon of pdf](https://cdn.prod.website-files.com/5f348cefc28f73bfbed5b00a/653891c6beb999d9c5766be6_ic-pdf.svg)\n\n![Image 19: icon of image](https://cdn.prod.website-files.com/5f348cefc28f73bfbed5b00a/653891c6d33bd473fb0480af_ic-images.svg)\n\n\u2705\n\n\u274c\n\n\u2705\n\n\u274c\n\n\u2705\n\n\u274c\n\n\u2705\n\n\u274c\n\n\u2705\n\n\u274c\n\n\u2705\n\n\u274c\n\n\u2705\n\n\u274c\n\n\u2705\n\n\u274c\n\n\u2705\n\n\u274c\n\n\u2705\n\n\u274c\n\n\u2705\n\n\u274c\n\n\u2705\n\n\u274c\n\n\u2705\n\n\u274c\n\n\u2705\n\n\u274c\n\n\u2705\n\n\u274c\n\n\u2705\n\n\u274c\n\n\u2705\n\n\u274c\n\n\u2705\n\n\u274c\n\n\u2705\n\n\u274c\n\n\u2705\n\n\u274c\n\n\u2705\n\n\u274c\n\n\u2705\n\n\u274c\n\n\u2705\n\n\u274c\n\n\u2705\n\n\u274c\n\n\u2705\n\n\u274c\n\n\u2705\n\n\u274c\n\n\u2705\n\n\u274c\n\n\u2705\n\n\u274c\n\n##### CLIENT EXPERIENCE\n\n\u2705\n\n\u274c\n\n\u2705\n\n\u274c\n\n\u2705\n\n\u274c\n\n\u2705\n\n\u274c\n\n\u2705\n\n\u274c\n\n\u2705\n\n\u274c\n\n\u2705\n\n\u274c\n\n\u2705\n\n\u274c\n\n\u2705\n\n\u274c\n\n\u2705\n\n\u274c\n\n\u2705\n\n\u274c\n\n\u2705\n\n\u274c\n\n\u2705\n\n\u274c\n\n\u2705\n\n\u274c\n\n\u2705\n\n\u274c\n\n\u2705\n\n\u274c\n\n##### WHITE LABELLING\n\n\u2705\n\n\u274c\n\n\u2705\n\n\u274c\n\n\u2705\n\n\u274c\n\n\u2705\n\n\u274c\n\n##### SECURITY & SUPPORT\n\n\u2705\n\n\u274c\n\n\u2705\n\n\u274c\n\n\u2705\n\n\u274c\n\n\u2705\n\n\u274c\n\n\u2705\n\n\u274c\n\n\u2705\n\n\u274c\n\n\u2705\n\n\u274c\n\n\u2705\n\n\u274c\n\n\u2705\n\n\u274c\n\n\u2705\n\n\u274c\n\n\u2705\n\n\u274c\n\n\u2705\n\n\u274c\n\n\u2705\n\n\u274c\n\n\u2705\n\n\u274c\n\n\u2705\n\n\u274c\n\n\u2705\n\n\u274c\n\n##### INTEGRATIONS\n\n![Image 20: icon - integration - slack](https://cdn.prod.website-files.com/5f348cefc28f73bfbed5b00a/6347bfaeb292a35c6799cb89_ic-integration-slack%403x.png)\n\n![Image 21: ms teams icon](https://cdn.prod.website-files.com/5f348cefc28f73bfbed5b00a/66ac2e1e1f22c1d767fc1b82_ic-integration-ms%20teams.svg)\n\n![Image 22: icon - integration - zapier](https://cdn.prod.website-files.com/5f348cefc28f73bfbed5b00a/6347bfae3a6b0d86062e660e_ic-integration-zapier%403x.png)\n\n![Image 23: make logo](https://cdn.prod.website-files.com/5f348cefc28f73bfbed5b00a/662cbb5fd0e9217e80a38b48_ic-integration-make.svg)\n\n![Image 24: icon - integration - github](https://cdn.prod.website-files.com/5f348cefc28f73bfbed5b00a/6348986a247ff343d97f8e57_ic-integration-github%403x.png)\n\n![Image 25: fullstory icon](https://cdn.prod.website-files.com/5f348cefc28f73bfbed5b00a/6685f72407e35c78b9decfab_ic-integration-fullstory-high%20res.png)\n\n![Image 26: logrocket icon](https://cdn.prod.website-files.com/5f348cefc28f73bfbed5b00a/668f4f21dc9fbbc3a66bfe0e_ic-integration-logrocket-high%20res.png)\n\n![Image 27: harvest logo](https://cdn.prod.website-files.com/5f348cefc28f73bfbed5b00a/66f4e0e5bfc12ceb1feead06_ic-integration-harvest.png)\n\n![Image 28: integration - timedoctor](https://cdn.prod.website-files.com/5f348cefc28f73bfbed5b00a/654d7d1a37ce3fa4801b2ab4_ic-integration-timedoctor%403x.png)\n\n![Image 29: integration - firmao](https://cdn.prod.website-files.com/5f348cefc28f73bfbed5b00a/654d7d1a058b6fd5b3e8d673_ic-integration-firmao%403x.png)\n\n![Image 30: lambdatest icon](https://cdn.prod.website-files.com/5f348cefc28f73bfbed5b00a/649e2b277c9c43cccf2aa309_ic-integration-lambdatest%403x.png)\n\n![Image 31: icon - integration - trello](https://cdn.prod.website-files.com/5f348cefc28f73bfbed5b00a/6347bfaee6e3d7f21d524446_ic-integration-trello%403x.png)\n\n![Image 32: integration productive logo](https://cdn.prod.website-files.com/5f348cefc28f73bfbed5b00a/66e8da263360505ceebd4c51_ic-integration-productive.svg)\n\n![Image 33: icon - integration - jira](https://cdn.prod.website-files.com/5f348cefc28f73bfbed5b00a/6347bfade07b280feee811c8_ic-integration-jira%403x.png)\n\n![Image 34: icon - integration - asana](https://cdn.prod.website-files.com/5f348cefc28f73bfbed5b00a/6347bfb6f870e5700ee694d6_ic-integration-asana%403x.png)\n\n![Image 35: linear logo](https://cdn.prod.website-files.com/5f348cefc28f73bfbed5b00a/661f685df697e589a62d0f99_ic-integration-linear.svg)\n\n![Image 36: clickup logo](https://cdn.prod.website-files.com/5f348cefc28f73bfbed5b00a/66344df594ef00243d905505_ic-integration-clickup.svg)\n\n![Image 37: monday.com logo](https://cdn.prod.website-files.com/5f348cefc28f73bfbed5b00a/66344df59dba56c96bedd604_ic-integration-monday.svg)\n\n![Image 38: integration logo teamwork](https://cdn.prod.website-files.com/5f348cefc28f73bfbed5b00a/6750f32660f2a8cc7d9a7068_ic-integration-teamwork.svg)\n\n\u2705\n\n\u274c\n\n\u2705\n\n\u274c\n\n\u2705\n\n\u274c\n\n\u2705\n\n\u274c\n\n\u2705\n\n\u274c\n\n\u2705\n\n\u274c\n\n\u2705\n\n\u274c\n\n\u2705\n\n\u274c\n\n\u2705\n\n\u274c\n\n\u2705\n\n\u274c\n\n\u2705\n\n\u274c\n\n\u2705\n\n\u274c\n\n\u2705\n\n\u274c\n\n\u2705\n\n\u274c\n\n\u2705\n\n\u274c\n\n\u2705\n\n\u274c\n\n\u2705\n\n\u274c\n\n\u2705\n\n\u274c\n\n\u2705\n\n\u274c\n\n\u2705\n\n\u274c\n\n\u2705\n\n\u274c\n\n\u2705\n\n\u274c\n\n\u2705\n\n\u274c\n\n\u2705\n\n\u274c\n\n\u2705\n\n\u274c\n\n\u2705\n\n\u274c\n\n\u2705\n\n\u274c\n\n\u2705\n\n\u274c\n\n\u2705\n\n\u274c\n\n\u2705\n\n\u274c\n\n\u2705\n\n\u274c\n\n\u2705\n\n\u274c\n\n\u2705\n\n\u274c\n\n\u2705\n\n\u274c\n\n\u2705\n\n\u274c\n\n\u2705\n\n\u274c\n\n\u2705\n\n\u274c\n\n\u2705\n\n\u274c\n\n\u2705\n\n\u274c\n\n\u2705\n\n\u274c\n\n\u2705\n\n\u274c\n\n\u2705\n\n\u274c\n\n\u2705\n\n\u274c\n\n\u2705\n\n\u274c\n\n\u2705\n\n\u274c\n\n\u2705\n\n\u274c\n\n\u2705\n\n\u274c\n\n\u2705\n\n\u274c\n\n\u2705\n\n\u274c\n\n\u2705\n\n\u274c\n\n\u2705\n\n\u274c\n\n\u2705\n\n\u274c\n\n\u2705\n\n\u274c\n\n\u2705\n\n\u274c\n\n\u2705\n\n\u274c\n\n\u2705\n\n\u274c\n\n\u2705\n\n\u274c\n\n\u2705\n\n\u274c\n\n\u2705\n\n\u274c\n\n\u2705\n\n\u274c\n\n\u2705\n\n\u274c\n\n\u2705\n\n\u274c\n\n\u2705\n\n\u274c\n\n\u2705\n\n\u274c\n\n\u2705\n\n\u274c\n\n\u2705\n\n\u274c\n\n\u2705\n\n\u274c\n\n\u2705\n\n\u274c\n\n\u2705\n\n\u274c\n\n\u2705\n\n\u274c\n\n\u2705\n\n\u274c\n\n\u2705\n\n\u274c\n\n\u2705\n\n\u274c\n\n\u2705\n\n\u274c\n\n\u2705\n\n\u274c\n\n\u2705\n\n\u274c\n\n##### USAGE\n\n##### Members\n\n(Devs, designers, PMs, QAs)\n\nAdditional member(s) available for $8 per user (billed monthly).\n\nStandard\n\n5 members\n\nStudio\n\n10 members\n\nPremium\n\n25 members\n\nEnterprise\n\nCustom limit\n\n##### Guests\n\n(Clients, stakeholders)\n\nStandard\n\n\u221e Unlimited\n\nStudio\n\n\u221e Unlimited\n\nPremium\n\n\u221e Unlimited\n\nEnterprise\n\n\u221e Unlimited\n\nStandard\n\n10 GB\n\nStudio\n\n25 GB\n\nPremium\n\n50 GB\n\nEnterprise\n\n\u221e Unlimited\n\nStandard\n\n\u221e Unlimited\n\nStudio\n\n\u221e Unlimited\n\nPremium\n\n\u221e Unlimited\n\nEnterprise\n\n\u221e Unlimited\n\n##### FEEDBACK FEATURES\n\n##### Capture screenshots & technical data\n\nBrowser, OS, screen size & more\n\nStandard\n\n\u2705\n\nStudio\n\n\u2705\n\nPremium\n\n\u2705\n\nEnterprise\n\n\u2705\n\nStandard\n\n\u2705\n\nStudio\n\n\u2705\n\nPremium\n\n\u2705\n\nEnterprise\n\n\u2705\n\n![Image 39: icon of figma logo](https://cdn.prod.website-files.com/5f348cefc28f73bfbed5b00a/653891c5105ef6247fd2711e_ic-figma.svg)\n\nStandard\n\n\u2705\n\nStudio\n\n\u2705\n\nPremium\n\n\u2705\n\nEnterprise\n\n\u2705\n\nStandard\n\n\u2705\n\nStudio\n\n\u2705\n\nPremium\n\n\u2705\n\nEnterprise\n\n\u2705\n\nStandard\n\n\u2705\n\nStudio\n\n\u2705\n\nPremium\n\n\u2705\n\nEnterprise\n\n\u2705\n\n##### WHITE LABELLING\n\nStandard\n\n\u274c\n\nStudio\n\n\u274c\n\nPremium\n\n\u2705\n\nEnterprise\n\n\u2705\n\n##### GUEST EXPERIENCE\n\nStandard\n\n\u274c\n\nStudio\n\n\u274c\n\nPremium\n\n\u2705\n\nEnterprise\n\n\u2705\n\nStandard\n\n\u274c\n\nStudio\n\n\u274c\n\nPremium\n\n\u2705\n\nEnterprise\n\n\u2705\n\nStandard\n\n\u274c\n\nStudio\n\n\u274c\n\nPremium\n\n\u2705\n\nEnterprise\n\n\u2705\n\nStandard\n\n\u274c\n\nStudio\n\n\u274c\n\nPremium\n\n\u2705\n\nEnterprise\n\n\u2705\n\n##### SECURITY & SUPPORT\n\nStandard\n\n\u274c\n\nStudio\n\n\u274c\n\nPremium\n\n\u274c\n\nEnterprise\n\n\u2705\n\nStandard\n\n\u274c\n\nStudio\n\n\u274c\n\nPremium\n\n\u274c\n\nEnterprise\n\n\u2705\n\nStandard\n\n\u274c\n\nStudio\n\n\u274c\n\nPremium\n\n\u274c\n\nEnterprise\n\n\u2705\n\nStandard\n\n\u274c\n\nStudio\n\n\u274c\n\nPremium\n\n\u274c\n\nEnterprise\n\n\u2705\n\n##### INTEGRATIONS\n\nFrequently asked questions\n--------------------------\n\nDo I need to install anything?\n\nWhere possible we recommend installing BugHerd via a simple one line JavaScript tag. If you are unable to install any code on your website BugHerd can also be accessed via our browser extension.\n\nIs BugHerd mobile friendly?\n\nThe BugHerd sidebar is fully responsive working on mobile websites allowing you to log/close tasks and manage your workflow.\n\nDo you offer annual discounts?\n\nYes. Select a yearly plan for BugHerd and get two months free.\n\nCan I export my data?\n\nYes. All BugHerd plans support data export via CSV, XML & JSON. If you're feeling more technical you can also access your tasks via the BugHerd API.\n\nTry BugHerd free for 7 days. No credit card required. Explore flexible pricing plans designed to make managing client feedback on websites ridiculously easy.",
      "error": null,
      "pricing_data": {
        "app_id": "bugherd",
        "app_name": "BugHerd",
        "app_slug": "bugherd",
        "pricing_url": null,
        "source_url": null,
        "all_pricing_urls": null,
        "price_model_type": [
          "PriceModelType.SUBSCRIPTION",
          "PriceModelType.USAGE_BASED"
        ],
        "has_free_tier": false,
        "has_free_trial": true,
        "free_trial_period_days": 7,
        "currency": "USD",
        "is_pricing_public": true,
        "pricing_page_accessible": true,
        "pricing_notes": "Annual plans offer a discount equivalent to two months free.",
        "pricing_tiers": [
          {
            "tier_name": "Standard",
            "tier_description": "Ideal for freelancers and small teams.",
            "monthly_price": 49.0,
            "annual_price": 41.0,
            "annual_discount_percentage": 16.67,
            "setup_fee": null,
            "features": [
              "Unlimited Client users",
              "Unlimited Projects",
              "Feedback on websites, Figma designs, PDFs, images",
              "Capture screenshots & technical metadata",
              "Video feedback",
              "Standard integrations (Trello, Slack, GitHub + 12 more)"
            ],
            "limits": {
              "users": 5,
              "storage": "10GB",
              "operations": "unlimited",
              "api_calls": "unlimited",
              "integrations": "unlimited",
              "custom_limits": null
            }
          },
          {
            "tier_name": "Studio",
            "tier_description": "Perfect for growing agencies needing to manage multiple projects and clients effectively.",
            "monthly_price": 79.0,
            "annual_price": 66.0,
            "annual_discount_percentage": 16.46,
            "setup_fee": null,
            "features": [
              "Everything in Standard",
              "More Members",
              "More storage"
            ],
            "limits": {
              "users": 10,
              "storage": "25GB",
              "operations": "unlimited",
              "api_calls": "unlimited",
              "integrations": "unlimited",
              "custom_limits": null
            }
          },
          {
            "tier_name": "Premium",
            "tier_description": "Tailored for agencies and larger teams who want to deliver an exceptional project experience for clients.",
            "monthly_price": 149.0,
            "annual_price": 124.0,
            "annual_discount_percentage": 16.78,
            "setup_fee": null,
            "features": [
              "Everything in Studio",
              "Custom branding",
              "Enhanced client collaboration",
              "Share member feedback with clients",
              "Private Team commenting",
              "Client project board",
              "Premium integrations (Jira, Asana, Linear, ClickUp, Monday.com)"
            ],
            "limits": {
              "users": 25,
              "storage": "50GB",
              "operations": "unlimited",
              "api_calls": "unlimited",
              "integrations": "unlimited",
              "custom_limits": null
            }
          },
          {
            "tier_name": "Custom",
            "tier_description": "Designed for enterprises with complex workflows and dedicated support needs.",
            "monthly_price": null,
            "annual_price": null,
            "annual_discount_percentage": null,
            "setup_fee": null,
            "features": [
              "Everything in Premium",
              "Custom limit on Members",
              "Dedicated Success Manager",
              "Onboarding & Training Support",
              "Secure single sign-on (SSO)"
            ],
            "limits": {
              "users": "custom",
              "storage": "unlimited",
              "operations": "unlimited",
              "api_calls": "unlimited",
              "integrations": "unlimited",
              "custom_limits": null
            }
          }
        ],
        "usage_based_pricing": [
          {
            "metric_name": "Additional members",
            "unit": "per user",
            "base_price": 80.0,
            "tiers": null
          }
        ],
        "ai_specific_pricing": null,
        "promotional_offers": null,
        "additional_fees": null,
        "extraction_timestamp": "2025-04-15T09:02:26.521128",
        "schema_validated": true,
        "confidence_score": 100,
        "extraction_error": false,
        "json_repaired": false
      },
      "pricing_analyzed": true
    }
  ],
  "results_directory": "pricing_results\\bugherd\\20250415_090226"
}