{
  "app_name": "HelpDesk",
  "app_slug": "helpdesk",
  "search_term": "Find the official pricing page URL for HelpDesk (helpdesk.com). Only provide the exact URL to the pricing page, not a summary of pricing information.",
  "timestamp": 1744722948.6222298,
  "response_text": [
    "The official URL for the HelpDesk pricing page is: [https://www.helpdesk.com/pricing](https://www.helpdesk.com/pricing)\u30103:0\u2020source\u3011."
  ],
  "citations": [
    {
      "title": "HelpDesk Pricing and Plans",
      "url": "https://www.helpdesk.com/pricing/"
    }
  ],
  "extracted_content": [
    {
      "url": "https://www.helpdesk.com/pricing",
      "is_accessible": true,
      "content": "Team\n----\n\nFor growing teams with entry-level needs.\n\n$ 29 /mo\n\nper agent billed annually **(save 15%)** or $34 billed monthly\n\n*   Paid users with admin or agent roles\n*   Unlimited free viewers\n*   5 teams\n*   5 forwarding addresses\n*   5 reply addresses\n*   One custom domain\n*   5 email templates\n*   5 active rules\n*   5 activated custom fields\n\nBusiness\n--------\n\nFor businesses with multi-brand operations.\n\n$ 50 /mo\n\nper agent billed annually **(save 15%)** or $59 billed monthly\n\n*   Paid users with admin or agent roles\n*   Unlimited free viewers\n*   100 teams\n*   100 forwarding addresses\n*   100 reply addresses\n*   100 custom domains\n*   100 email templates\n*   50 active rules\n*   20 activated custom fields\n\nEnterprise\n----------\n\nFor corporations requiring an individual approach.\n\nFill form to talk to Sales\n\n![Image 1](https://www.helpdesk.com/images/sqf/decor-left.svg)\n\nindividual contract, [learn more](https://www.helpdesk.com/enterprise-help-desk-software/)\n\n*   Everything from the Business plan with no limits\n*   Dedicated account manager\n*   Product training\n*   Software engineer support\n*   Security assistance\n*   White label\n\nWhat makes HelpDesk stand out?\n------------------------------\n\nSee how users value our simple ticket system for everyday tasks.\n\n![Image 2](https://www.helpdesk.com/icons/drawn/active/lifebouy.svg)\n\n### 24/7/365 support\n\nFeel free to reach out to us anytime you need support or guidance, no matter what!\n\n![Image 3](https://www.helpdesk.com/icons/drawn/active/shield-password.svg)\n\n### Data safety\n\nMake sure you\u2019re secure with GDPR compliance and Privacy-Shield certification.\n\n![Image 4](https://www.helpdesk.com/icons/drawn/active/ticket-multichannel-2.svg)\n\n### Extensive marketplace\n\nSeamlessly integrate HelpDesk with other apps and systems to boost your productivity.\n\nHow does the free trial work?\n-----------------------------\n\n**Try HelpDesk with a free 14-day trial of our Business plan without any commitment.** After your trial, you can choose to continue with the Team plan at $29 per month per agent (billed annually), the Business plan at $50 per month per agent (billed annually), or a tailored Enterprise solution based on your needs. Find the plan that suits you best.\n\nCompare HelpDesk plans\n----------------------\n\nPricing (all prices in USD)\n\nPrice / month (billed annually)\n\nPrice / month (billed monthly)\n\nMessaging\n\nMultiple inboxes\n\nManage different company inboxes in one place. ![Image 5: ?](https://www.helpdesk.com/icons/bold/question-circle.svg)\n\nManage different company inboxes in one place.\n\nTeam reply address\n\nAdjust the email address for outgoing messages to match your brand. ![Image 6: ?](https://www.helpdesk.com/icons/bold/question-circle.svg)\n\nAdjust the email address for outgoing messages to match your brand.\n\nMultiple email templates\n\nCreate multiple email templates for your teams to organize response processes better. ![Image 7: ?](https://www.helpdesk.com/icons/bold/question-circle.svg)\n\nCreate multiple email templates for your teams to organize response processes better.\n\nContact form\n\nPublish the contact form on your website and get submissions as tickets directly to HelpDesk. ![Image 8: ?](https://www.helpdesk.com/icons/bold/question-circle.svg)\n\nPublish the contact form on your website and get submissions as tickets directly to HelpDesk.\n\nRecipient details\n\nGet detailed information about your recipients, such as customers, prospects, business partners, employees, vendors, or investors, to improve communication and tailor interactions. ![Image 9: ?](https://www.helpdesk.com/icons/bold/question-circle.svg)\n\nGet detailed information about your recipients, such as customers, prospects, business partners, employees, vendors, or investors, to improve communication and tailor interactions.\n\nActivated custom fields\n\nCreate custom fields to specify your tickets with additional helpful information for your work. ![Image 10: ?](https://www.helpdesk.com/icons/bold/question-circle.svg)\n\n![Image 11](https://www.helpdesk.com/pricing/database.svg) Data collection\n\nCreate custom fields to specify your tickets with additional helpful information for your work.\n\nCanned responses\n\nPrepare ready-made messages based on your communication best practices and trigger them with a single click. ![Image 12: ?](https://www.helpdesk.com/icons/bold/question-circle.svg)\n\n![Image 13](https://www.helpdesk.com/pricing/rotate-clockwise-2.svg) Time saver\n\nPrepare ready-made messages based on your communication best practices and trigger them with a single click.\n\nPrivate notes\n\nLeave confidential notes attached to your tickets that will only be visible to you and your team. ![Image 14: ?](https://www.helpdesk.com/icons/bold/question-circle.svg)\n\n![Image 15](https://www.helpdesk.com/pricing/circles.svg) Loved by teams\n\nLeave confidential notes attached to your tickets that will only be visible to you and your team.\n\nTags\n\nCategorize tickets with tags to filter and identify similar cases later. ![Image 16: ?](https://www.helpdesk.com/icons/bold/question-circle.svg)\n\nCategorize tickets with tags to filter and identify similar cases later.\n\nPriorities\n\nPrioritize tickets and highlight urgent cases to better organize and plan your work. ![Image 17: ?](https://www.helpdesk.com/icons/bold/question-circle.svg)\n\nPrioritize tickets and highlight urgent cases to better organize and plan your work.\n\nStatuses\n\nUse Open, Pending, On hold, Solved, or Closed statuses to stay on top of your tickets. ![Image 18: ?](https://www.helpdesk.com/icons/bold/question-circle.svg)\n\nUse Open, Pending, On hold, Solved, or Closed statuses to stay on top of your tickets.\n\nFile sharing\n\nShare files with team members or recipients without leaving the HelpDesk app. ![Image 19: ?](https://www.helpdesk.com/icons/bold/question-circle.svg)\n\nShare files with team members or recipients without leaving the HelpDesk app.\n\nTicket merging\n\nMerge many requester's tickets into one main ticket. ![Image 20: ?](https://www.helpdesk.com/icons/bold/question-circle.svg)\n\n![Image 21](https://www.helpdesk.com/pricing/route.svg) Organized ticketing\n\nMerge many requester's tickets into one main ticket.\n\nMessage delivery tracking\n\nVerify that the message has been read by the recipient and prepare the next steps. ![Image 22: ?](https://www.helpdesk.com/icons/bold/question-circle.svg)\n\nVerify that the message has been read by the recipient and prepare the next steps.\n\nAgent rating\n\nGrow from feedback and allow your recipients to assess your performance and the quality of your assistance. ![Image 23: ?](https://www.helpdesk.com/icons/bold/question-circle.svg)\n\n![Image 24](https://www.helpdesk.com/pricing/smile.svg) Customer feedback\n\nGrow from feedback and allow your recipients to assess your performance and the quality of your assistance.\n\nAutomation\n\nAutomated assignment\n\nAutomatically assign tickets to appropriate team members and teams. ![Image 25: ?](https://www.helpdesk.com/icons/bold/question-circle.svg)\n\nAutomatically assign tickets to appropriate team members and teams.\n\nCustom active rules\n\nCreate custom rules according to your requirements. ![Image 26: ?](https://www.helpdesk.com/icons/bold/question-circle.svg)\n\n![Image 27](https://www.helpdesk.com/pricing/user-check.svg) Managers' favorite\n\nCreate custom rules according to your requirements.\n\nPreset rules\n\nUse ready-made rule templates to automate any tasks in seconds. ![Image 28: ?](https://www.helpdesk.com/icons/bold/question-circle.svg)\n\n![Image 29](https://www.helpdesk.com/pricing/pig-money.svg) Money saver\n\nUse ready-made rule templates to automate any tasks in seconds.\n\nPrivate macros\n\nCreate private macros for personal use only. Then, apply them and update a ticket with a pre-set series of actions. ![Image 30: ?](https://www.helpdesk.com/icons/bold/question-circle.svg)\n\nCreate private macros for personal use only. Then, apply them and update a ticket with a pre-set series of actions.\n\nShared macros\n\nCreate shared macros for use by multiple users. Then, apply them and update a ticket with a pre-set series of actions. ![Image 31: ?](https://www.helpdesk.com/icons/bold/question-circle.svg)\n\nCreate shared macros for use by multiple users. Then, apply them and update a ticket with a pre-set series of actions.\n\nBulk actions\n\nUse bulk actions to perform ticket-related tasks quicker and on a large scale. ![Image 32: ?](https://www.helpdesk.com/icons/bold/question-circle.svg)\n\n![Image 33](https://www.helpdesk.com/pricing/rotate-clockwise-2.svg) Time saver\n\nUse bulk actions to perform ticket-related tasks quicker and on a large scale.\n\nScreen recording\n\nRecord your screen using the video response feature in HelpDesk to guide your recipients in solving their issues. ![Image 34: ?](https://www.helpdesk.com/icons/bold/question-circle.svg)\n\nRecord your screen using the video response feature in HelpDesk to guide your recipients in solving their issues.\n\nAI\n\nText enhancements\n\nExtend, correct, or make your text more polite, formal, or casual in seconds. ![Image 35: ?](https://www.helpdesk.com/icons/bold/question-circle.svg)\n\nExtend, correct, or make your text more polite, formal, or casual in seconds.\n\nTicket summary\n\nUse the ticket summary feature to automatically generate a brief and information-rich overview of the ticket and its conversation history. ![Image 36: ?](https://www.helpdesk.com/icons/bold/question-circle.svg)\n\n![Image 37](https://www.helpdesk.com/pricing/rotate-clockwise-2.svg) Time saver\n\nUse the ticket summary feature to automatically generate a brief and information-rich overview of the ticket and its conversation history.\n\nLanguage detection\n\nRecognize languages instantly and automate ticket routing, responses, and teamwork across multiple languages. ![Image 38: ?](https://www.helpdesk.com/icons/bold/question-circle.svg)\n\nRecognize languages instantly and automate ticket routing, responses, and teamwork across multiple languages.\n\nReply suggestions\n\nQuick, context-aware responses powered by AI to streamline ticket replies. ![Image 39: ?](https://www.helpdesk.com/icons/bold/question-circle.svg)\n\n![Image 40](https://www.helpdesk.com/pricing/coming-soon.svg) Coming soon\n\nQuick, context-aware responses powered by AI to streamline ticket replies.\n\nSimilar ticket suggestions\n\nAutomatically find and display past tickets related to the current case for quick resolutions. ![Image 41: ?](https://www.helpdesk.com/icons/bold/question-circle.svg)\n\n![Image 42](https://www.helpdesk.com/pricing/star-unfilled.svg) New feature\n\nAutomatically find and display past tickets related to the current case for quick resolutions.\n\nTag suggestions\n\nGet recommendations on relevant tags for tickets to improve your organizational and search capabilities. ![Image 43: ?](https://www.helpdesk.com/icons/bold/question-circle.svg)\n\n![Image 44](https://www.helpdesk.com/pricing/star-unfilled.svg) New feature\n\nGet recommendations on relevant tags for tickets to improve your organizational and search capabilities.\n\nWork management\n\nMultiple teams\n\nCreate multiple teams with different goals and daily tasks, such as sales, marketing, customer service, finance, legal, and tech. ![Image 45: ?](https://www.helpdesk.com/icons/bold/question-circle.svg)\n\n![Image 46](https://www.helpdesk.com/pricing/user-check.svg) Managers' favorite\n\nCreate multiple teams with different goals and daily tasks, such as sales, marketing, customer service, finance, legal, and tech.\n\nAgent and admin roles\n\nGive one of three roles: Admin, Agent, and Viewer. Admins have all the permission, Agents can work with tickets, and Viewers can only browse and read tickets. ![Image 47: ?](https://www.helpdesk.com/icons/bold/question-circle.svg)\n\n![Image 48](https://www.helpdesk.com/pricing/lock.svg) Fully secure\n\nGive one of three roles: Admin, Agent, and Viewer. Admins have all the permission, Agents can work with tickets, and Viewers can only browse and read tickets.\n\nFree viewer role\n\nGive Viewer roles to allow browsing and reading of tickets without modification. ![Image 49: ?](https://www.helpdesk.com/icons/bold/question-circle.svg)\n\n![Image 50](https://www.helpdesk.com/pricing/rotate-clockwise-2.svg) Time saver\n\nGive Viewer roles to allow browsing and reading of tickets without modification.\n\nSuspending users\n\nUse viewer role for temporarily suspending an agent\u2019s status to pause billing without extra charges. ![Image 51: ?](https://www.helpdesk.com/icons/bold/question-circle.svg)\n\nUse viewer role for temporarily suspending an agent\u2019s status to pause billing without extra charges.\n\nCollaboration\n\nAgent mentioning\n\nMention an agent or admin in a private note who can assist you in solving the ticket. ![Image 52: ?](https://www.helpdesk.com/icons/bold/question-circle.svg)\n\nMention an agent or admin in a private note who can assist you in solving the ticket.\n\nTicket following\n\nBecome the ticket follower and be notified of any updates in it. ![Image 53: ?](https://www.helpdesk.com/icons/bold/question-circle.svg)\n\nBecome the ticket follower and be notified of any updates in it.\n\nCollision detection\n\nDetect key activities performed in a ticket, such as browsing or typing by another agent. ![Image 54: ?](https://www.helpdesk.com/icons/bold/question-circle.svg)\n\n![Image 55](https://www.helpdesk.com/pricing/circles.svg) Loved by teams\n\nDetect key activities performed in a ticket, such as browsing or typing by another agent.\n\nShared ticket views\n\nShare ticket views with your team to work on them together. ![Image 56: ?](https://www.helpdesk.com/icons/bold/question-circle.svg)\n\nShare ticket views with your team to work on them together.\n\nAllowed domains\n\nAllow teammates to join Text products without invitations by setting up allowed domains. ![Image 57: ?](https://www.helpdesk.com/icons/bold/question-circle.svg)\n\nAllow teammates to join Text products without invitations by setting up allowed domains.\n\nCustomization\n\nAgent signatures\n\nAdd your own signature to messages sent from HelpDesk. ![Image 58: ?](https://www.helpdesk.com/icons/bold/question-circle.svg)\n\nAdd your own signature to messages sent from HelpDesk.\n\nVisual email template builder\n\nFreely customize email templates for each team using a no-code visual builder. Create different looks for the messages sent to recipients. ![Image 59: ?](https://www.helpdesk.com/icons/bold/question-circle.svg)\n\n![Image 60](https://www.helpdesk.com/pricing/drag-drop.svg) No code feature\n\nFreely customize email templates for each team using a no-code visual builder. Create different looks for the messages sent to recipients.\n\nCustom domains\n\nAdd one or more custom domains and send messages from HelpDesk using your own email address. ![Image 61: ?](https://www.helpdesk.com/icons/bold/question-circle.svg)\n\nAdd one or more custom domains and send messages from HelpDesk using your own email address.\n\nCustom reply address\n\nAdjust the email address for your outgoing messages to match your brand. ![Image 62: ?](https://www.helpdesk.com/icons/bold/question-circle.svg)\n\nAdjust the email address for your outgoing messages to match your brand.\n\nCustomizable ticket views\n\nSave filtering settings as ticket views for easy access on a daily basis. ![Image 63: ?](https://www.helpdesk.com/icons/bold/question-circle.svg)\n\n![Image 64](https://www.helpdesk.com/pricing/trending-up.svg) Work booster\n\nSave filtering settings as ticket views for easy access on a daily basis.\n\nCustomizable message rating\n\nAsk recipients for feedback with a simple message sent automatically. ![Image 65: ?](https://www.helpdesk.com/icons/bold/question-circle.svg)\n\nAsk recipients for feedback with a simple message sent automatically.\n\nCustomizable automated reply\n\nAutomate responses by adding ticket confirmations or other updates to keep recipients informed and improve satisfaction without manual effort. ![Image 66: ?](https://www.helpdesk.com/icons/bold/question-circle.svg)\n\n![Image 67](https://www.helpdesk.com/pricing/rotate-clockwise-2.svg) Time saver\n\nAutomate responses by adding ticket confirmations or other updates to keep recipients informed and improve satisfaction without manual effort.\n\nDark mode\n\nSwitch to a dark-themed interface for reduced eye strain and a sleek look during low-light or late hours. ![Image 68: ?](https://www.helpdesk.com/icons/bold/question-circle.svg)\n\nSwitch to a dark-themed interface for reduced eye strain and a sleek look during low-light or late hours.\n\nWhite label\n\nRemove the \"This email is delivered by HelpDesk\" branding. Available on demand. ![Image 69: ?](https://www.helpdesk.com/icons/bold/question-circle.svg)\n\nRemove the \"This email is delivered by HelpDesk\" branding. Available on demand.\n\nPerformance and reports\n\nLast 7 days\n\nReview ticket activity over the past 7 days. ![Image 70: ?](https://www.helpdesk.com/icons/bold/question-circle.svg)\n\nReview ticket activity over the past 7 days.\n\nNew tickets\n\nLearn more about new tickets that reach HelpDesk. ![Image 71: ?](https://www.helpdesk.com/icons/bold/question-circle.svg)\n\nLearn more about new tickets that reach HelpDesk.\n\nNew tickets heatmap in last 7 days\n\nDiscover peak times with more tickets than usual. ![Image 72: ?](https://www.helpdesk.com/icons/bold/question-circle.svg)\n\nDiscover peak times with more tickets than usual.\n\nTickets sources\n\nCompare the number of manually created tickets to those from other channels. ![Image 73: ?](https://www.helpdesk.com/icons/bold/question-circle.svg)\n\nCompare the number of manually created tickets to those from other channels.\n\nTicket satisfaction\n\nVerify how well recipients rate your assistance. ![Image 74: ?](https://www.helpdesk.com/icons/bold/question-circle.svg)\n\nVerify how well recipients rate your assistance.\n\nFirst response time\n\nFind out how quickly you respond to tickets on average. ![Image 75: ?](https://www.helpdesk.com/icons/bold/question-circle.svg)\n\n![Image 76](https://www.helpdesk.com/pricing/user-check.svg) Managers' favorite\n\nFind out how quickly you respond to tickets on average.\n\nResolution time\n\nLearn the average time since a ticket's creation and since an agent started working on it. ![Image 77: ?](https://www.helpdesk.com/icons/bold/question-circle.svg)\n\nLearn the average time since a ticket's creation and since an agent started working on it.\n\nHandling time by status\n\nBreak down the time tickets spend across statuses. ![Image 78: ?](https://www.helpdesk.com/icons/bold/question-circle.svg)\n\nBreak down the time tickets spend across statuses.\n\nSolved and closed\n\nCompare the number of solved and closed tickets. ![Image 79: ?](https://www.helpdesk.com/icons/bold/question-circle.svg)\n\nCompare the number of solved and closed tickets.\n\nTeams performance\n\nCompare how different teams are performing. ![Image 80: ?](https://www.helpdesk.com/icons/bold/question-circle.svg)\n\n![Image 81](https://www.helpdesk.com/pricing/heart-rate-monitor.svg) Detailed data\n\nCompare how different teams are performing.\n\nAgents performance\n\nCompare how different agents are performing. ![Image 82: ?](https://www.helpdesk.com/icons/bold/question-circle.svg)\n\nCompare how different agents are performing.\n\nReports export\n\nExport ticket metadata within the specified date range. ![Image 83: ?](https://www.helpdesk.com/icons/bold/question-circle.svg)\n\nExport ticket metadata within the specified date range.\n\nSecurity\n\n256-bit SSL secure connection\n\nKeep you data safe with the SSL encryption protocol. ![Image 84: ?](https://www.helpdesk.com/icons/bold/question-circle.svg)\n\nKeep you data safe with the SSL encryption protocol.\n\nBuilt-in antispam protection\n\nGet advanced spam prevention mechanisms with an explanation of why the message was marked as spam. ![Image 85: ?](https://www.helpdesk.com/icons/bold/question-circle.svg)\n\n![Image 86](https://www.helpdesk.com/pricing/barrier-block.svg) Spam blocker\n\nGet advanced spam prevention mechanisms with an explanation of why the message was marked as spam.\n\nLog in with Google\n\nUse your Google Account details to log in to HelpDesk. ![Image 87: ?](https://www.helpdesk.com/icons/bold/question-circle.svg)\n\nUse your Google Account details to log in to HelpDesk.\n\nCustom SSO\n\nConfigure Custom SSO in the Enterprise plan to align with your security protocols. ![Image 88: ?](https://www.helpdesk.com/icons/bold/question-circle.svg)\n\nConfigure Custom SSO in the Enterprise plan to align with your security protocols.\n\nTwo-Factor Authentication\n\nEnable two-factor authentication (2FA) to enhance account security by requiring a password and an authentication app code. ![Image 89: ?](https://www.helpdesk.com/icons/bold/question-circle.svg)\n\nEnable two-factor authentication (2FA) to enhance account security by requiring a password and an authentication app code.\n\nLog in with Microsoft\n\nUse your Microsoft Account details to log in to HelpDesk. ![Image 90: ?](https://www.helpdesk.com/icons/bold/question-circle.svg)\n\nUse your Microsoft Account details to log in to HelpDesk.\n\nLog in with Apple\n\nUse your Apple Account details to log in to HelpDesk. ![Image 91: ?](https://www.helpdesk.com/icons/bold/question-circle.svg)\n\nUse your Apple Account details to log in to HelpDesk.\n\nAudit log\n\nGet a list of changes made in the app settings. ![Image 92: ?](https://www.helpdesk.com/icons/bold/question-circle.svg)\n\n![Image 93](https://www.helpdesk.com/pricing/star-unfilled.svg) New feature\n\nGet a list of changes made in the app settings.\n\nSecurity assistance\n\nGet tailored security advice from our specialists. ![Image 94: ?](https://www.helpdesk.com/icons/bold/question-circle.svg)\n\nGet tailored security advice from our specialists.\n\nProduct support\n\nSelf-service help center\n\nRead step-by-step articles on all HelpDesk features. ![Image 95: ?](https://www.helpdesk.com/icons/bold/question-circle.svg)\n\nRead step-by-step articles on all HelpDesk features.\n\n24/7/365 support\n\nConnect with our support team on chat to get instant assistance. ![Image 96: ?](https://www.helpdesk.com/icons/bold/question-circle.svg)\n\n![Image 97](https://www.helpdesk.com/pricing/brand-wechat.svg) Proactive support\n\nConnect with our support team on chat to get instant assistance.\n\nProduct training\n\nGet a one-on-one product training session with one of our Support Heroes. ![Image 98: ?](https://www.helpdesk.com/icons/bold/question-circle.svg)\n\n![Image 99](https://www.helpdesk.com/pricing/users.svg) End-to-end training\n\nGet a one-on-one product training session with one of our Support Heroes.\n\nSoftware engineer support\n\nTalk to our tech team to get support even on the most complicated issues. ![Image 100: ?](https://www.helpdesk.com/icons/bold/question-circle.svg)\n\nTalk to our tech team to get support even on the most complicated issues.\n\nLegal assistance\n\nGet help from our legal team to analyze or prepare the documentation needed to start using HelpDesk. ![Image 101: ?](https://www.helpdesk.com/icons/bold/question-circle.svg)\n\nGet help from our legal team to analyze or prepare the documentation needed to start using HelpDesk.\n\nYearly PO & invoicing\n\nPurchase orders to pay for HelpDesk, and get annual invoices. ![Image 102: ?](https://www.helpdesk.com/icons/bold/question-circle.svg)\n\nPurchase orders to pay for HelpDesk, and get annual invoices.\n\nKey Account Manager\n\nGet premium support and one-on-one product training sessions. ![Image 103: ?](https://www.helpdesk.com/icons/bold/question-circle.svg)\n\nGet premium support and one-on-one product training sessions.\n\nAlternative payment terms\n\nAs an alternative to using your company card, you can pay for HelpDesk with purchase orders and annual invoices. ![Image 104: ?](https://www.helpdesk.com/icons/bold/question-circle.svg)\n\nAs an alternative to using your company card, you can pay for HelpDesk with purchase orders and annual invoices.\n\nPay with crypto\n\nUse cryptocurrencies like USDC on Ethereum, Solana, or Polygon to purchase your HelpDesk license. ![Image 105: ?](https://www.helpdesk.com/icons/bold/question-circle.svg)\n\nUse cryptocurrencies like USDC on Ethereum, Solana, or Polygon to purchase your HelpDesk license.\n\nMaintenance\n\nArchive, Spam, and Trash folders\n\nUse the Archive, Trash, and Spam folders to categorize and organize your tickets. ![Image 106: ?](https://www.helpdesk.com/icons/bold/question-circle.svg)\n\nUse the Archive, Trash, and Spam folders to categorize and organize your tickets.\n\nTicket history\n\nReview the ticket history to learn more about the context of the messages. ![Image 107: ?](https://www.helpdesk.com/icons/bold/question-circle.svg)\n\n![Image 108](https://www.helpdesk.com/pricing/cloud-data-connection.svg) CRM capability\n\nReview the ticket history to learn more about the context of the messages.\n\nRecord storage\n\nStore screen recordings prepared for recipients securely for 30 days. ![Image 109: ?](https://www.helpdesk.com/icons/bold/question-circle.svg)\n\nStore screen recordings prepared for recipients securely for 30 days.\n\nCustom data retention period\n\nSpecify a custom retention period to control data retention time, ensuring compliance with the organization's policies and regulations. ![Image 110: ?](https://www.helpdesk.com/icons/bold/question-circle.svg)\n\nSpecify a custom retention period to control data retention time, ensuring compliance with the organization's policies and regulations.\n\nIntegrations\n\nData migration\n\nMigrate data from another ticketing system with our support, including cost details and possible coverage. If you\u2019re interested, please contact us through chat. ![Image 111: ?](https://www.helpdesk.com/icons/bold/question-circle.svg)\n\nMigrate data from another ticketing system with our support, including cost details and possible coverage. If you\u2019re interested, please contact us through chat.\n\nAPI\n\nCustomize HelpDesk to meet your needs and improve performance with personalized integrations and API services. ![Image 112: ?](https://www.helpdesk.com/icons/bold/question-circle.svg)\n\nCustomize HelpDesk to meet your needs and improve performance with personalized integrations and API services.\n\nMarketplace apps\n\nBrowse marketplace apps and extend your HelpDesk freely. ![Image 113: ?](https://www.helpdesk.com/icons/bold/question-circle.svg)\n\nBrowse marketplace apps and extend your HelpDesk freely.\n\nLiveChat\n\nConnect HelpDesk with your LiveChat account. ![Image 114: ?](https://www.helpdesk.com/icons/bold/question-circle.svg)\n\nConnect HelpDesk with your LiveChat account.\n\nZapier\n\nConnect HelpDesk with 3000+ web apps with Zapier. ![Image 115: ?](https://www.helpdesk.com/icons/bold/question-circle.svg)\n\nConnect HelpDesk with 3000+ web apps with Zapier.\n\nShopify\n\nIntegrate Shopify with HelpDesk to sync order details and communication history, making ticket creation seamless and providing real-time updates. ![Image 116: ?](https://www.helpdesk.com/icons/bold/question-circle.svg)\n\nIntegrate Shopify with HelpDesk to sync order details and communication history, making ticket creation seamless and providing real-time updates.\n\nWordPress\n\nEmbed the HelpDesk contact form into your WordPress website as another ticket source. ![Image 117: ?](https://www.helpdesk.com/icons/bold/question-circle.svg)\n\nEmbed the HelpDesk contact form into your WordPress website as another ticket source.\n\nWebflow\n\nCreate a Webflow contact form and forward all submitted forms to HelpDesk. ![Image 118: ?](https://www.helpdesk.com/icons/bold/question-circle.svg)\n\n![Image 119](https://www.helpdesk.com/pricing/star-unfilled.svg) New feature\n\nCreate a Webflow contact form and forward all submitted forms to HelpDesk.\n\nSwitching to HelpDesk from other providers is\u00a0simple\n----------------------------------------------------\n\nMigration feels like an effortless upgrade \u2013 it's that intuitive!\n\n![Image 120](https://www.helpdesk.com/icons/steps/1.662a7f3b8e49b36ac0bff87be2ca4175f0f06b273e393265750543d19593db0b.svg)\n\nUse your existing HelpDesk account or create a new one.\n\n![Image 121](https://www.helpdesk.com/icons/steps/2.31253ce384e5c5a9e83375beb92e4a6d545cc47e461ad91565817226649d50a5.svg)\n\nSpecify the data you want to move from another ticketing system.\n\n![Image 122](https://www.helpdesk.com/icons/steps/3.9beee459af1318b20a915c2aab73b729386cec1f5438a00b6eab59c9e0be7625.svg)\n\nChat with us to get our support in\u00a0the migration process, offer information about any related costs and, if possible, cover them for\u00a0you.\n\n![Image 123: HelpDesk Partner Program](https://www.helpdesk.com/images/helpdesk-partner-program.jpg)\n\n### Opening a HelpDesk account for a client?\n\nBecome a Solution Partner and set up clients' accounts in no time directly in the Partner App.\n\n[Go to Partner Program](https://partners.livechat.com/solution-program/?utm_source=helpdesk.com/pricing&utm_medium=referral&utm_content=pricing_agency_section)\n\n### We're here for you 24/7/365\n\nAny time you need help, you can count on our Support Heroes. They are strong, they are fast, and they will help you - no matter the time!\n\nChat with us\n\n![Image 124: HelpDesk support](https://www.helpdesk.com/company/support/support-team.32bb80088669660524a05e0d7fd1021adf66a80bc38a09e2532e60a257050201.png)\n\nYou're one step away from empowering your team and delighting your customers\n\nFree 14-day trial Core ticketing features No credit card required\n\nYou'll be in  \ngood\u00a0company\n\n![Image 125](https://www.helpdesk.com/images/happy-customers.3abd905fe8d7b8555194b183a241defb71af2e49133597006148afc0b10844a2.png)\n\n![Image 126: Tickets that are created with Shopify, Salesforce, LiveChat, and Messenger](https://www.helpdesk.com/images/help-desk.79e548c3ea5a705be5adc9845f58af6bbde2445c7f29b82d107aa8add6655130.png)\n\nCheck out HelpDesk's easy-to-read offer and choose the plan that fits you best. Start your free 14-day trial.",
      "error": null,
      "pricing_data": {
        "app_id": "helpdesk",
        "app_name": "HelpDesk",
        "app_slug": "helpdesk",
        "pricing_url": "https://www.helpdesk.com/pricing",
        "source_url": "https://www.helpdesk.com/pricing",
        "all_pricing_urls": [
          "https://www.helpdesk.com/pricing"
        ],
        "price_model_type": [
          "PriceModelType.SUBSCRIPTION",
          "PriceModelType.QUOTE_BASED",
          "PriceModelType.FREE_TIER"
        ],
        "has_free_tier": false,
        "has_free_trial": true,
        "free_trial_period_days": 14,
        "currency": "USD",
        "is_pricing_public": true,
        "pricing_page_accessible": true,
        "pricing_notes": "Pricing includes options for annual and monthly billing with discounts for annual payments. Enterprise tier requires custom pricing.",
        "pricing_tiers": [
          {
            "tier_name": "Team",
            "tier_description": "For growing teams with entry-level needs.",
            "monthly_price": 34.0,
            "annual_price": 29.0,
            "annual_discount_percentage": 15.0,
            "setup_fee": null,
            "features": [
              "Paid users with admin or agent roles",
              "Unlimited free viewers",
              "5 teams",
              "5 forwarding addresses",
              "5 reply addresses",
              "One custom domain",
              "5 email templates",
              "5 active rules",
              "5 activated custom fields"
            ],
            "limits": {
              "users": "unlimited",
              "storage": null,
              "operations": null,
              "api_calls": null,
              "integrations": null,
              "custom_limits": null
            }
          },
          {
            "tier_name": "Business",
            "tier_description": "For businesses with multi-brand operations.",
            "monthly_price": 59.0,
            "annual_price": 50.0,
            "annual_discount_percentage": 15.0,
            "setup_fee": null,
            "features": [
              "Paid users with admin or agent roles",
              "Unlimited free viewers",
              "100 teams",
              "100 forwarding addresses",
              "100 reply addresses",
              "100 custom domains",
              "100 email templates",
              "50 active rules",
              "20 activated custom fields"
            ],
            "limits": {
              "users": "unlimited",
              "storage": null,
              "operations": null,
              "api_calls": null,
              "integrations": null,
              "custom_limits": null
            }
          },
          {
            "tier_name": "Enterprise",
            "tier_description": "For corporations requiring an individual approach.",
            "monthly_price": null,
            "annual_price": null,
            "annual_discount_percentage": null,
            "setup_fee": null,
            "features": [
              "Everything from the Business plan with no limits",
              "Dedicated account manager",
              "Product training",
              "Software engineer support",
              "Security assistance",
              "White label"
            ],
            "limits": {
              "users": "unlimited",
              "storage": "unlimited",
              "operations": "unlimited",
              "api_calls": "unlimited",
              "integrations": "unlimited",
              "custom_limits": null
            }
          }
        ],
        "usage_based_pricing": null,
        "ai_specific_pricing": null,
        "promotional_offers": null,
        "additional_fees": null,
        "extraction_timestamp": "2025-04-15T09:15:59.453389",
        "schema_validated": true,
        "confidence_score": 100,
        "extraction_error": false,
        "json_repaired": false
      },
      "pricing_analyzed": true
    },
    {
      "url": "https://www.helpdesk.com/pricing/",
      "is_accessible": true,
      "content": "Team\n----\n\nFor growing teams with entry-level needs.\n\n$ 29 /mo\n\nper agent billed annually **(save 15%)** or $34 billed monthly\n\n*   Paid users with admin or agent roles\n*   Unlimited free viewers\n*   5 teams\n*   5 forwarding addresses\n*   5 reply addresses\n*   One custom domain\n*   5 email templates\n*   5 active rules\n*   5 activated custom fields\n\nBusiness\n--------\n\nFor businesses with multi-brand operations.\n\n$ 50 /mo\n\nper agent billed annually **(save 15%)** or $59 billed monthly\n\n*   Paid users with admin or agent roles\n*   Unlimited free viewers\n*   100 teams\n*   100 forwarding addresses\n*   100 reply addresses\n*   100 custom domains\n*   100 email templates\n*   50 active rules\n*   20 activated custom fields\n\nEnterprise\n----------\n\nFor corporations requiring an individual approach.\n\nFill form to talk to Sales\n\n![Image 1](https://www.helpdesk.com/images/sqf/decor-left.svg)\n\nindividual contract, [learn more](https://www.helpdesk.com/enterprise-help-desk-software/)\n\n*   Everything from the Business plan with no limits\n*   Dedicated account manager\n*   Product training\n*   Software engineer support\n*   Security assistance\n*   White label\n\nWhat makes HelpDesk stand out?\n------------------------------\n\nSee how users value our simple ticket system for everyday tasks.\n\n![Image 2](https://www.helpdesk.com/icons/drawn/active/lifebouy.svg)\n\n### 24/7/365 support\n\nFeel free to reach out to us anytime you need support or guidance, no matter what!\n\n![Image 3](https://www.helpdesk.com/icons/drawn/active/shield-password.svg)\n\n### Data safety\n\nMake sure you\u2019re secure with GDPR compliance and Privacy-Shield certification.\n\n![Image 4](https://www.helpdesk.com/icons/drawn/active/ticket-multichannel-2.svg)\n\n### Extensive marketplace\n\nSeamlessly integrate HelpDesk with other apps and systems to boost your productivity.\n\nHow does the free trial work?\n-----------------------------\n\n**Try HelpDesk with a free 14-day trial of our Business plan without any commitment.** After your trial, you can choose to continue with the Team plan at $29 per month per agent (billed annually), the Business plan at $50 per month per agent (billed annually), or a tailored Enterprise solution based on your needs. Find the plan that suits you best.\n\nCompare HelpDesk plans\n----------------------\n\nPricing (all prices in USD)\n\nPrice / month (billed annually)\n\nPrice / month (billed monthly)\n\nMessaging\n\nMultiple inboxes\n\nManage different company inboxes in one place. ![Image 5: ?](https://www.helpdesk.com/icons/bold/question-circle.svg)\n\nManage different company inboxes in one place.\n\nTeam reply address\n\nAdjust the email address for outgoing messages to match your brand. ![Image 6: ?](https://www.helpdesk.com/icons/bold/question-circle.svg)\n\nAdjust the email address for outgoing messages to match your brand.\n\nMultiple email templates\n\nCreate multiple email templates for your teams to organize response processes better. ![Image 7: ?](https://www.helpdesk.com/icons/bold/question-circle.svg)\n\nCreate multiple email templates for your teams to organize response processes better.\n\nContact form\n\nPublish the contact form on your website and get submissions as tickets directly to HelpDesk. ![Image 8: ?](https://www.helpdesk.com/icons/bold/question-circle.svg)\n\nPublish the contact form on your website and get submissions as tickets directly to HelpDesk.\n\nRecipient details\n\nGet detailed information about your recipients, such as customers, prospects, business partners, employees, vendors, or investors, to improve communication and tailor interactions. ![Image 9: ?](https://www.helpdesk.com/icons/bold/question-circle.svg)\n\nGet detailed information about your recipients, such as customers, prospects, business partners, employees, vendors, or investors, to improve communication and tailor interactions.\n\nActivated custom fields\n\nCreate custom fields to specify your tickets with additional helpful information for your work. ![Image 10: ?](https://www.helpdesk.com/icons/bold/question-circle.svg)\n\n![Image 11](https://www.helpdesk.com/pricing/database.svg) Data collection\n\nCreate custom fields to specify your tickets with additional helpful information for your work.\n\nCanned responses\n\nPrepare ready-made messages based on your communication best practices and trigger them with a single click. ![Image 12: ?](https://www.helpdesk.com/icons/bold/question-circle.svg)\n\n![Image 13](https://www.helpdesk.com/pricing/rotate-clockwise-2.svg) Time saver\n\nPrepare ready-made messages based on your communication best practices and trigger them with a single click.\n\nPrivate notes\n\nLeave confidential notes attached to your tickets that will only be visible to you and your team. ![Image 14: ?](https://www.helpdesk.com/icons/bold/question-circle.svg)\n\n![Image 15](https://www.helpdesk.com/pricing/circles.svg) Loved by teams\n\nLeave confidential notes attached to your tickets that will only be visible to you and your team.\n\nTags\n\nCategorize tickets with tags to filter and identify similar cases later. ![Image 16: ?](https://www.helpdesk.com/icons/bold/question-circle.svg)\n\nCategorize tickets with tags to filter and identify similar cases later.\n\nPriorities\n\nPrioritize tickets and highlight urgent cases to better organize and plan your work. ![Image 17: ?](https://www.helpdesk.com/icons/bold/question-circle.svg)\n\nPrioritize tickets and highlight urgent cases to better organize and plan your work.\n\nStatuses\n\nUse Open, Pending, On hold, Solved, or Closed statuses to stay on top of your tickets. ![Image 18: ?](https://www.helpdesk.com/icons/bold/question-circle.svg)\n\nUse Open, Pending, On hold, Solved, or Closed statuses to stay on top of your tickets.\n\nFile sharing\n\nShare files with team members or recipients without leaving the HelpDesk app. ![Image 19: ?](https://www.helpdesk.com/icons/bold/question-circle.svg)\n\nShare files with team members or recipients without leaving the HelpDesk app.\n\nTicket merging\n\nMerge many requester's tickets into one main ticket. ![Image 20: ?](https://www.helpdesk.com/icons/bold/question-circle.svg)\n\n![Image 21](https://www.helpdesk.com/pricing/route.svg) Organized ticketing\n\nMerge many requester's tickets into one main ticket.\n\nMessage delivery tracking\n\nVerify that the message has been read by the recipient and prepare the next steps. ![Image 22: ?](https://www.helpdesk.com/icons/bold/question-circle.svg)\n\nVerify that the message has been read by the recipient and prepare the next steps.\n\nAgent rating\n\nGrow from feedback and allow your recipients to assess your performance and the quality of your assistance. ![Image 23: ?](https://www.helpdesk.com/icons/bold/question-circle.svg)\n\n![Image 24](https://www.helpdesk.com/pricing/smile.svg) Customer feedback\n\nGrow from feedback and allow your recipients to assess your performance and the quality of your assistance.\n\nAutomation\n\nAutomated assignment\n\nAutomatically assign tickets to appropriate team members and teams. ![Image 25: ?](https://www.helpdesk.com/icons/bold/question-circle.svg)\n\nAutomatically assign tickets to appropriate team members and teams.\n\nCustom active rules\n\nCreate custom rules according to your requirements. ![Image 26: ?](https://www.helpdesk.com/icons/bold/question-circle.svg)\n\n![Image 27](https://www.helpdesk.com/pricing/user-check.svg) Managers' favorite\n\nCreate custom rules according to your requirements.\n\nPreset rules\n\nUse ready-made rule templates to automate any tasks in seconds. ![Image 28: ?](https://www.helpdesk.com/icons/bold/question-circle.svg)\n\n![Image 29](https://www.helpdesk.com/pricing/pig-money.svg) Money saver\n\nUse ready-made rule templates to automate any tasks in seconds.\n\nPrivate macros\n\nCreate private macros for personal use only. Then, apply them and update a ticket with a pre-set series of actions. ![Image 30: ?](https://www.helpdesk.com/icons/bold/question-circle.svg)\n\nCreate private macros for personal use only. Then, apply them and update a ticket with a pre-set series of actions.\n\nShared macros\n\nCreate shared macros for use by multiple users. Then, apply them and update a ticket with a pre-set series of actions. ![Image 31: ?](https://www.helpdesk.com/icons/bold/question-circle.svg)\n\nCreate shared macros for use by multiple users. Then, apply them and update a ticket with a pre-set series of actions.\n\nBulk actions\n\nUse bulk actions to perform ticket-related tasks quicker and on a large scale. ![Image 32: ?](https://www.helpdesk.com/icons/bold/question-circle.svg)\n\n![Image 33](https://www.helpdesk.com/pricing/rotate-clockwise-2.svg) Time saver\n\nUse bulk actions to perform ticket-related tasks quicker and on a large scale.\n\nScreen recording\n\nRecord your screen using the video response feature in HelpDesk to guide your recipients in solving their issues. ![Image 34: ?](https://www.helpdesk.com/icons/bold/question-circle.svg)\n\nRecord your screen using the video response feature in HelpDesk to guide your recipients in solving their issues.\n\nAI\n\nText enhancements\n\nExtend, correct, or make your text more polite, formal, or casual in seconds. ![Image 35: ?](https://www.helpdesk.com/icons/bold/question-circle.svg)\n\nExtend, correct, or make your text more polite, formal, or casual in seconds.\n\nTicket summary\n\nUse the ticket summary feature to automatically generate a brief and information-rich overview of the ticket and its conversation history. ![Image 36: ?](https://www.helpdesk.com/icons/bold/question-circle.svg)\n\n![Image 37](https://www.helpdesk.com/pricing/rotate-clockwise-2.svg) Time saver\n\nUse the ticket summary feature to automatically generate a brief and information-rich overview of the ticket and its conversation history.\n\nLanguage detection\n\nRecognize languages instantly and automate ticket routing, responses, and teamwork across multiple languages. ![Image 38: ?](https://www.helpdesk.com/icons/bold/question-circle.svg)\n\nRecognize languages instantly and automate ticket routing, responses, and teamwork across multiple languages.\n\nReply suggestions\n\nQuick, context-aware responses powered by AI to streamline ticket replies. ![Image 39: ?](https://www.helpdesk.com/icons/bold/question-circle.svg)\n\n![Image 40](https://www.helpdesk.com/pricing/coming-soon.svg) Coming soon\n\nQuick, context-aware responses powered by AI to streamline ticket replies.\n\nSimilar ticket suggestions\n\nAutomatically find and display past tickets related to the current case for quick resolutions. ![Image 41: ?](https://www.helpdesk.com/icons/bold/question-circle.svg)\n\n![Image 42](https://www.helpdesk.com/pricing/star-unfilled.svg) New feature\n\nAutomatically find and display past tickets related to the current case for quick resolutions.\n\nTag suggestions\n\nGet recommendations on relevant tags for tickets to improve your organizational and search capabilities. ![Image 43: ?](https://www.helpdesk.com/icons/bold/question-circle.svg)\n\n![Image 44](https://www.helpdesk.com/pricing/star-unfilled.svg) New feature\n\nGet recommendations on relevant tags for tickets to improve your organizational and search capabilities.\n\nWork management\n\nMultiple teams\n\nCreate multiple teams with different goals and daily tasks, such as sales, marketing, customer service, finance, legal, and tech. ![Image 45: ?](https://www.helpdesk.com/icons/bold/question-circle.svg)\n\n![Image 46](https://www.helpdesk.com/pricing/user-check.svg) Managers' favorite\n\nCreate multiple teams with different goals and daily tasks, such as sales, marketing, customer service, finance, legal, and tech.\n\nAgent and admin roles\n\nGive one of three roles: Admin, Agent, and Viewer. Admins have all the permission, Agents can work with tickets, and Viewers can only browse and read tickets. ![Image 47: ?](https://www.helpdesk.com/icons/bold/question-circle.svg)\n\n![Image 48](https://www.helpdesk.com/pricing/lock.svg) Fully secure\n\nGive one of three roles: Admin, Agent, and Viewer. Admins have all the permission, Agents can work with tickets, and Viewers can only browse and read tickets.\n\nFree viewer role\n\nGive Viewer roles to allow browsing and reading of tickets without modification. ![Image 49: ?](https://www.helpdesk.com/icons/bold/question-circle.svg)\n\n![Image 50](https://www.helpdesk.com/pricing/rotate-clockwise-2.svg) Time saver\n\nGive Viewer roles to allow browsing and reading of tickets without modification.\n\nSuspending users\n\nUse viewer role for temporarily suspending an agent\u2019s status to pause billing without extra charges. ![Image 51: ?](https://www.helpdesk.com/icons/bold/question-circle.svg)\n\nUse viewer role for temporarily suspending an agent\u2019s status to pause billing without extra charges.\n\nCollaboration\n\nAgent mentioning\n\nMention an agent or admin in a private note who can assist you in solving the ticket. ![Image 52: ?](https://www.helpdesk.com/icons/bold/question-circle.svg)\n\nMention an agent or admin in a private note who can assist you in solving the ticket.\n\nTicket following\n\nBecome the ticket follower and be notified of any updates in it. ![Image 53: ?](https://www.helpdesk.com/icons/bold/question-circle.svg)\n\nBecome the ticket follower and be notified of any updates in it.\n\nCollision detection\n\nDetect key activities performed in a ticket, such as browsing or typing by another agent. ![Image 54: ?](https://www.helpdesk.com/icons/bold/question-circle.svg)\n\n![Image 55](https://www.helpdesk.com/pricing/circles.svg) Loved by teams\n\nDetect key activities performed in a ticket, such as browsing or typing by another agent.\n\nShared ticket views\n\nShare ticket views with your team to work on them together. ![Image 56: ?](https://www.helpdesk.com/icons/bold/question-circle.svg)\n\nShare ticket views with your team to work on them together.\n\nAllowed domains\n\nAllow teammates to join Text products without invitations by setting up allowed domains. ![Image 57: ?](https://www.helpdesk.com/icons/bold/question-circle.svg)\n\nAllow teammates to join Text products without invitations by setting up allowed domains.\n\nCustomization\n\nAgent signatures\n\nAdd your own signature to messages sent from HelpDesk. ![Image 58: ?](https://www.helpdesk.com/icons/bold/question-circle.svg)\n\nAdd your own signature to messages sent from HelpDesk.\n\nVisual email template builder\n\nFreely customize email templates for each team using a no-code visual builder. Create different looks for the messages sent to recipients. ![Image 59: ?](https://www.helpdesk.com/icons/bold/question-circle.svg)\n\n![Image 60](https://www.helpdesk.com/pricing/drag-drop.svg) No code feature\n\nFreely customize email templates for each team using a no-code visual builder. Create different looks for the messages sent to recipients.\n\nCustom domains\n\nAdd one or more custom domains and send messages from HelpDesk using your own email address. ![Image 61: ?](https://www.helpdesk.com/icons/bold/question-circle.svg)\n\nAdd one or more custom domains and send messages from HelpDesk using your own email address.\n\nCustom reply address\n\nAdjust the email address for your outgoing messages to match your brand. ![Image 62: ?](https://www.helpdesk.com/icons/bold/question-circle.svg)\n\nAdjust the email address for your outgoing messages to match your brand.\n\nCustomizable ticket views\n\nSave filtering settings as ticket views for easy access on a daily basis. ![Image 63: ?](https://www.helpdesk.com/icons/bold/question-circle.svg)\n\n![Image 64](https://www.helpdesk.com/pricing/trending-up.svg) Work booster\n\nSave filtering settings as ticket views for easy access on a daily basis.\n\nCustomizable message rating\n\nAsk recipients for feedback with a simple message sent automatically. ![Image 65: ?](https://www.helpdesk.com/icons/bold/question-circle.svg)\n\nAsk recipients for feedback with a simple message sent automatically.\n\nCustomizable automated reply\n\nAutomate responses by adding ticket confirmations or other updates to keep recipients informed and improve satisfaction without manual effort. ![Image 66: ?](https://www.helpdesk.com/icons/bold/question-circle.svg)\n\n![Image 67](https://www.helpdesk.com/pricing/rotate-clockwise-2.svg) Time saver\n\nAutomate responses by adding ticket confirmations or other updates to keep recipients informed and improve satisfaction without manual effort.\n\nDark mode\n\nSwitch to a dark-themed interface for reduced eye strain and a sleek look during low-light or late hours. ![Image 68: ?](https://www.helpdesk.com/icons/bold/question-circle.svg)\n\nSwitch to a dark-themed interface for reduced eye strain and a sleek look during low-light or late hours.\n\nWhite label\n\nRemove the \"This email is delivered by HelpDesk\" branding. Available on demand. ![Image 69: ?](https://www.helpdesk.com/icons/bold/question-circle.svg)\n\nRemove the \"This email is delivered by HelpDesk\" branding. Available on demand.\n\nPerformance and reports\n\nLast 7 days\n\nReview ticket activity over the past 7 days. ![Image 70: ?](https://www.helpdesk.com/icons/bold/question-circle.svg)\n\nReview ticket activity over the past 7 days.\n\nNew tickets\n\nLearn more about new tickets that reach HelpDesk. ![Image 71: ?](https://www.helpdesk.com/icons/bold/question-circle.svg)\n\nLearn more about new tickets that reach HelpDesk.\n\nNew tickets heatmap in last 7 days\n\nDiscover peak times with more tickets than usual. ![Image 72: ?](https://www.helpdesk.com/icons/bold/question-circle.svg)\n\nDiscover peak times with more tickets than usual.\n\nTickets sources\n\nCompare the number of manually created tickets to those from other channels. ![Image 73: ?](https://www.helpdesk.com/icons/bold/question-circle.svg)\n\nCompare the number of manually created tickets to those from other channels.\n\nTicket satisfaction\n\nVerify how well recipients rate your assistance. ![Image 74: ?](https://www.helpdesk.com/icons/bold/question-circle.svg)\n\nVerify how well recipients rate your assistance.\n\nFirst response time\n\nFind out how quickly you respond to tickets on average. ![Image 75: ?](https://www.helpdesk.com/icons/bold/question-circle.svg)\n\n![Image 76](https://www.helpdesk.com/pricing/user-check.svg) Managers' favorite\n\nFind out how quickly you respond to tickets on average.\n\nResolution time\n\nLearn the average time since a ticket's creation and since an agent started working on it. ![Image 77: ?](https://www.helpdesk.com/icons/bold/question-circle.svg)\n\nLearn the average time since a ticket's creation and since an agent started working on it.\n\nHandling time by status\n\nBreak down the time tickets spend across statuses. ![Image 78: ?](https://www.helpdesk.com/icons/bold/question-circle.svg)\n\nBreak down the time tickets spend across statuses.\n\nSolved and closed\n\nCompare the number of solved and closed tickets. ![Image 79: ?](https://www.helpdesk.com/icons/bold/question-circle.svg)\n\nCompare the number of solved and closed tickets.\n\nTeams performance\n\nCompare how different teams are performing. ![Image 80: ?](https://www.helpdesk.com/icons/bold/question-circle.svg)\n\n![Image 81](https://www.helpdesk.com/pricing/heart-rate-monitor.svg) Detailed data\n\nCompare how different teams are performing.\n\nAgents performance\n\nCompare how different agents are performing. ![Image 82: ?](https://www.helpdesk.com/icons/bold/question-circle.svg)\n\nCompare how different agents are performing.\n\nReports export\n\nExport ticket metadata within the specified date range. ![Image 83: ?](https://www.helpdesk.com/icons/bold/question-circle.svg)\n\nExport ticket metadata within the specified date range.\n\nSecurity\n\n256-bit SSL secure connection\n\nKeep you data safe with the SSL encryption protocol. ![Image 84: ?](https://www.helpdesk.com/icons/bold/question-circle.svg)\n\nKeep you data safe with the SSL encryption protocol.\n\nBuilt-in antispam protection\n\nGet advanced spam prevention mechanisms with an explanation of why the message was marked as spam. ![Image 85: ?](https://www.helpdesk.com/icons/bold/question-circle.svg)\n\n![Image 86](https://www.helpdesk.com/pricing/barrier-block.svg) Spam blocker\n\nGet advanced spam prevention mechanisms with an explanation of why the message was marked as spam.\n\nLog in with Google\n\nUse your Google Account details to log in to HelpDesk. ![Image 87: ?](https://www.helpdesk.com/icons/bold/question-circle.svg)\n\nUse your Google Account details to log in to HelpDesk.\n\nCustom SSO\n\nConfigure Custom SSO in the Enterprise plan to align with your security protocols. ![Image 88: ?](https://www.helpdesk.com/icons/bold/question-circle.svg)\n\nConfigure Custom SSO in the Enterprise plan to align with your security protocols.\n\nTwo-Factor Authentication\n\nEnable two-factor authentication (2FA) to enhance account security by requiring a password and an authentication app code. ![Image 89: ?](https://www.helpdesk.com/icons/bold/question-circle.svg)\n\nEnable two-factor authentication (2FA) to enhance account security by requiring a password and an authentication app code.\n\nLog in with Microsoft\n\nUse your Microsoft Account details to log in to HelpDesk. ![Image 90: ?](https://www.helpdesk.com/icons/bold/question-circle.svg)\n\nUse your Microsoft Account details to log in to HelpDesk.\n\nLog in with Apple\n\nUse your Apple Account details to log in to HelpDesk. ![Image 91: ?](https://www.helpdesk.com/icons/bold/question-circle.svg)\n\nUse your Apple Account details to log in to HelpDesk.\n\nAudit log\n\nGet a list of changes made in the app settings. ![Image 92: ?](https://www.helpdesk.com/icons/bold/question-circle.svg)\n\n![Image 93](https://www.helpdesk.com/pricing/star-unfilled.svg) New feature\n\nGet a list of changes made in the app settings.\n\nSecurity assistance\n\nGet tailored security advice from our specialists. ![Image 94: ?](https://www.helpdesk.com/icons/bold/question-circle.svg)\n\nGet tailored security advice from our specialists.\n\nProduct support\n\nSelf-service help center\n\nRead step-by-step articles on all HelpDesk features. ![Image 95: ?](https://www.helpdesk.com/icons/bold/question-circle.svg)\n\nRead step-by-step articles on all HelpDesk features.\n\n24/7/365 support\n\nConnect with our support team on chat to get instant assistance. ![Image 96: ?](https://www.helpdesk.com/icons/bold/question-circle.svg)\n\n![Image 97](https://www.helpdesk.com/pricing/brand-wechat.svg) Proactive support\n\nConnect with our support team on chat to get instant assistance.\n\nProduct training\n\nGet a one-on-one product training session with one of our Support Heroes. ![Image 98: ?](https://www.helpdesk.com/icons/bold/question-circle.svg)\n\n![Image 99](https://www.helpdesk.com/pricing/users.svg) End-to-end training\n\nGet a one-on-one product training session with one of our Support Heroes.\n\nSoftware engineer support\n\nTalk to our tech team to get support even on the most complicated issues. ![Image 100: ?](https://www.helpdesk.com/icons/bold/question-circle.svg)\n\nTalk to our tech team to get support even on the most complicated issues.\n\nLegal assistance\n\nGet help from our legal team to analyze or prepare the documentation needed to start using HelpDesk. ![Image 101: ?](https://www.helpdesk.com/icons/bold/question-circle.svg)\n\nGet help from our legal team to analyze or prepare the documentation needed to start using HelpDesk.\n\nYearly PO & invoicing\n\nPurchase orders to pay for HelpDesk, and get annual invoices. ![Image 102: ?](https://www.helpdesk.com/icons/bold/question-circle.svg)\n\nPurchase orders to pay for HelpDesk, and get annual invoices.\n\nKey Account Manager\n\nGet premium support and one-on-one product training sessions. ![Image 103: ?](https://www.helpdesk.com/icons/bold/question-circle.svg)\n\nGet premium support and one-on-one product training sessions.\n\nAlternative payment terms\n\nAs an alternative to using your company card, you can pay for HelpDesk with purchase orders and annual invoices. ![Image 104: ?](https://www.helpdesk.com/icons/bold/question-circle.svg)\n\nAs an alternative to using your company card, you can pay for HelpDesk with purchase orders and annual invoices.\n\nPay with crypto\n\nUse cryptocurrencies like USDC on Ethereum, Solana, or Polygon to purchase your HelpDesk license. ![Image 105: ?](https://www.helpdesk.com/icons/bold/question-circle.svg)\n\nUse cryptocurrencies like USDC on Ethereum, Solana, or Polygon to purchase your HelpDesk license.\n\nMaintenance\n\nArchive, Spam, and Trash folders\n\nUse the Archive, Trash, and Spam folders to categorize and organize your tickets. ![Image 106: ?](https://www.helpdesk.com/icons/bold/question-circle.svg)\n\nUse the Archive, Trash, and Spam folders to categorize and organize your tickets.\n\nTicket history\n\nReview the ticket history to learn more about the context of the messages. ![Image 107: ?](https://www.helpdesk.com/icons/bold/question-circle.svg)\n\n![Image 108](https://www.helpdesk.com/pricing/cloud-data-connection.svg) CRM capability\n\nReview the ticket history to learn more about the context of the messages.\n\nRecord storage\n\nStore screen recordings prepared for recipients securely for 30 days. ![Image 109: ?](https://www.helpdesk.com/icons/bold/question-circle.svg)\n\nStore screen recordings prepared for recipients securely for 30 days.\n\nCustom data retention period\n\nSpecify a custom retention period to control data retention time, ensuring compliance with the organization's policies and regulations. ![Image 110: ?](https://www.helpdesk.com/icons/bold/question-circle.svg)\n\nSpecify a custom retention period to control data retention time, ensuring compliance with the organization's policies and regulations.\n\nIntegrations\n\nData migration\n\nMigrate data from another ticketing system with our support, including cost details and possible coverage. If you\u2019re interested, please contact us through chat. ![Image 111: ?](https://www.helpdesk.com/icons/bold/question-circle.svg)\n\nMigrate data from another ticketing system with our support, including cost details and possible coverage. If you\u2019re interested, please contact us through chat.\n\nAPI\n\nCustomize HelpDesk to meet your needs and improve performance with personalized integrations and API services. ![Image 112: ?](https://www.helpdesk.com/icons/bold/question-circle.svg)\n\nCustomize HelpDesk to meet your needs and improve performance with personalized integrations and API services.\n\nMarketplace apps\n\nBrowse marketplace apps and extend your HelpDesk freely. ![Image 113: ?](https://www.helpdesk.com/icons/bold/question-circle.svg)\n\nBrowse marketplace apps and extend your HelpDesk freely.\n\nLiveChat\n\nConnect HelpDesk with your LiveChat account. ![Image 114: ?](https://www.helpdesk.com/icons/bold/question-circle.svg)\n\nConnect HelpDesk with your LiveChat account.\n\nZapier\n\nConnect HelpDesk with 3000+ web apps with Zapier. ![Image 115: ?](https://www.helpdesk.com/icons/bold/question-circle.svg)\n\nConnect HelpDesk with 3000+ web apps with Zapier.\n\nShopify\n\nIntegrate Shopify with HelpDesk to sync order details and communication history, making ticket creation seamless and providing real-time updates. ![Image 116: ?](https://www.helpdesk.com/icons/bold/question-circle.svg)\n\nIntegrate Shopify with HelpDesk to sync order details and communication history, making ticket creation seamless and providing real-time updates.\n\nWordPress\n\nEmbed the HelpDesk contact form into your WordPress website as another ticket source. ![Image 117: ?](https://www.helpdesk.com/icons/bold/question-circle.svg)\n\nEmbed the HelpDesk contact form into your WordPress website as another ticket source.\n\nWebflow\n\nCreate a Webflow contact form and forward all submitted forms to HelpDesk. ![Image 118: ?](https://www.helpdesk.com/icons/bold/question-circle.svg)\n\n![Image 119](https://www.helpdesk.com/pricing/star-unfilled.svg) New feature\n\nCreate a Webflow contact form and forward all submitted forms to HelpDesk.\n\nSwitching to HelpDesk from other providers is\u00a0simple\n----------------------------------------------------\n\nMigration feels like an effortless upgrade \u2013 it's that intuitive!\n\n![Image 120](https://www.helpdesk.com/icons/steps/1.662a7f3b8e49b36ac0bff87be2ca4175f0f06b273e393265750543d19593db0b.svg)\n\nUse your existing HelpDesk account or create a new one.\n\n![Image 121](https://www.helpdesk.com/icons/steps/2.31253ce384e5c5a9e83375beb92e4a6d545cc47e461ad91565817226649d50a5.svg)\n\nSpecify the data you want to move from another ticketing system.\n\n![Image 122](https://www.helpdesk.com/icons/steps/3.9beee459af1318b20a915c2aab73b729386cec1f5438a00b6eab59c9e0be7625.svg)\n\nChat with us to get our support in\u00a0the migration process, offer information about any related costs and, if possible, cover them for\u00a0you.\n\n![Image 123: HelpDesk Partner Program](https://www.helpdesk.com/images/helpdesk-partner-program.jpg)\n\n### Opening a HelpDesk account for a client?\n\nBecome a Solution Partner and set up clients' accounts in no time directly in the Partner App.\n\n[Go to Partner Program](https://partners.livechat.com/solution-program/?utm_source=helpdesk.com/pricing&utm_medium=referral&utm_content=pricing_agency_section)\n\n### We're here for you 24/7/365\n\nAny time you need help, you can count on our Support Heroes. They are strong, they are fast, and they will help you - no matter the time!\n\nChat with us\n\n![Image 124: HelpDesk support](https://www.helpdesk.com/company/support/support-team.32bb80088669660524a05e0d7fd1021adf66a80bc38a09e2532e60a257050201.png)\n\nYou're one step away from empowering your team and delighting your customers\n\nFree 14-day trial Core ticketing features No credit card required\n\nYou'll be in  \ngood\u00a0company\n\n![Image 125](https://www.helpdesk.com/images/happy-customers.3abd905fe8d7b8555194b183a241defb71af2e49133597006148afc0b10844a2.png)\n\n![Image 126: Tickets that are created with Shopify, Salesforce, LiveChat, and Messenger](https://www.helpdesk.com/images/help-desk.79e548c3ea5a705be5adc9845f58af6bbde2445c7f29b82d107aa8add6655130.png)\n\nCheck out HelpDesk's easy-to-read offer and choose the plan that fits you best. Start your free 14-day trial.",
      "error": null,
      "pricing_data": {
        "app_id": "helpdesk",
        "app_name": "HelpDesk",
        "app_slug": "helpdesk",
        "pricing_url": "https://www.helpdesk.com/pricing",
        "source_url": "https://www.helpdesk.com/pricing",
        "all_pricing_urls": [
          "https://www.helpdesk.com/pricing"
        ],
        "price_model_type": [
          "PriceModelType.SUBSCRIPTION",
          "PriceModelType.QUOTE_BASED",
          "PriceModelType.FREE_TIER"
        ],
        "has_free_tier": false,
        "has_free_trial": true,
        "free_trial_period_days": 14,
        "currency": "USD",
        "is_pricing_public": true,
        "pricing_page_accessible": true,
        "pricing_notes": "Pricing includes per-agent costs with annual and monthly billing options. Enterprise plan requires custom quotation.",
        "pricing_tiers": [
          {
            "tier_name": "Team",
            "tier_description": "For growing teams with entry-level needs.",
            "monthly_price": 34.0,
            "annual_price": 348.0,
            "annual_discount_percentage": 15.0,
            "setup_fee": null,
            "features": [
              "Paid users with admin or agent roles",
              "Unlimited free viewers",
              "5 teams",
              "5 forwarding addresses",
              "5 reply addresses",
              "One custom domain",
              "5 email templates",
              "5 active rules",
              "5 activated custom fields"
            ],
            "limits": {
              "users": "unlimited",
              "storage": null,
              "operations": null,
              "api_calls": null,
              "integrations": null,
              "custom_limits": [
                {
                  "name": "teams",
                  "value": 5
                },
                {
                  "name": "forwarding addresses",
                  "value": 5
                },
                {
                  "name": "reply addresses",
                  "value": 5
                },
                {
                  "name": "email templates",
                  "value": 5
                },
                {
                  "name": "active rules",
                  "value": 5
                },
                {
                  "name": "activated custom fields",
                  "value": 5
                }
              ]
            }
          },
          {
            "tier_name": "Business",
            "tier_description": "For businesses with multi-brand operations.",
            "monthly_price": 59.0,
            "annual_price": 600.0,
            "annual_discount_percentage": 15.0,
            "setup_fee": null,
            "features": [
              "Paid users with admin or agent roles",
              "Unlimited free viewers",
              "100 teams",
              "100 forwarding addresses",
              "100 reply addresses",
              "100 custom domains",
              "100 email templates",
              "50 active rules",
              "20 activated custom fields"
            ],
            "limits": {
              "users": "unlimited",
              "storage": null,
              "operations": null,
              "api_calls": null,
              "integrations": null,
              "custom_limits": [
                {
                  "name": "teams",
                  "value": 100
                },
                {
                  "name": "forwarding addresses",
                  "value": 100
                },
                {
                  "name": "reply addresses",
                  "value": 100
                },
                {
                  "name": "custom domains",
                  "value": 100
                },
                {
                  "name": "email templates",
                  "value": 100
                },
                {
                  "name": "active rules",
                  "value": 50
                },
                {
                  "name": "activated custom fields",
                  "value": 20
                }
              ]
            }
          },
          {
            "tier_name": "Enterprise",
            "tier_description": "For corporations requiring an individual approach.",
            "monthly_price": null,
            "annual_price": null,
            "annual_discount_percentage": null,
            "setup_fee": null,
            "features": [
              "Everything from the Business plan with no limits",
              "Dedicated account manager",
              "Product training",
              "Software engineer support",
              "Security assistance",
              "White label"
            ],
            "limits": {
              "users": "unlimited",
              "storage": "unlimited",
              "operations": "unlimited",
              "api_calls": "unlimited",
              "integrations": "unlimited",
              "custom_limits": null
            }
          }
        ],
        "usage_based_pricing": null,
        "ai_specific_pricing": null,
        "promotional_offers": null,
        "additional_fees": null,
        "extraction_timestamp": "2025-04-15T09:16:08.477292",
        "schema_validated": true,
        "confidence_score": 100,
        "extraction_error": false,
        "json_repaired": false
      },
      "pricing_analyzed": true
    }
  ],
  "results_directory": "pricing_results\\helpdesk\\20250415_091609"
}