{
  "app_name": "HeyGen",
  "app_slug": "heygen",
  "search_term": "Find the official pricing page URL for HeyGen (heygen.com). Only provide the exact URL to the pricing page, not a summary of pricing information.",
  "timestamp": 1744692405.4107533,
  "response_text": [
    "The official pricing page URL for HeyGen is: [https://www.heygen.com/pricing](https://www.heygen.com/pricing)\u30103:0\u2020source\u3011."
  ],
  "citations": [
    {
      "title": "HeyGen Pricing | Free & Paid Plans from $24/mo | HeyGen",
      "url": "https://www.heygen.com/pricing"
    }
  ],
  "extracted_content": [
    {
      "url": "https://www.heygen.com/pricing",
      "is_accessible": true,
      "content": "HeyGen Pricing | Free & Paid Plans from $24/mo | HeyGen\n===============\n\nJoin weekly webinars in the community\n\n[Register Now](https://community.heygen.com/public/events)\n\n[![Image 2: heygen](https://www.heygen.com/images/heygen-logo.svg)](https://www.heygen.com/)\n\n[Platform](https://www.heygen.com/pricing#)\n\n#### PRODUCTS\n\n[Video Avatars](https://www.heygen.com/avatars/ai-video-avatar)[Photo Avatars](https://www.heygen.com/avatars/ai-photo-avatar)[Generative Avatars](https://www.heygen.com/avatars/generative-avatar)[Avatar Looks](https://www.heygen.com/avatars/avatar-looks)[Video Translation](https://www.heygen.com/translate)[Localization](https://www.heygen.com/translate/language-localization)[Avatar Video](https://www.heygen.com/create-avatar-video)[Personalized Video](https://www.heygen.com/personalized-video)[Interactive Avatar](https://www.heygen.com/interactive-avatar)\n\n#### FEATURES\n\n[Stock Avatars](https://www.heygen.com/avatars/stock-avatars)[API](https://www.heygen.com/api)\n\n> ![Image 3: a purple background with the words all our latest drops on it](https://www.heygen.com/_next/image?url=https%3A%2F%2Fcdn.sanity.io%2Fimages%2Fpdhqcmb1%2Fproduction%2F858b69b410690dacf077c87b116caec1347d9d47-640x481.webp%3Frect%3D0%2C7%2C640%2C469%26w%3D15%26h%3D11%26fit%3Dcrop%26auto%3Dformat&w=1280&q=75)![Image 4: a purple background with the words all our latest drops on it](https://www.heygen.com/_next/image?url=https%3A%2F%2Fcdn.sanity.io%2Fimages%2Fpdhqcmb1%2Fproduction%2F858b69b410690dacf077c87b116caec1347d9d47-640x481.webp%3Fw%3D640%26h%3D481%26fit%3Dcrop%26auto%3Dformat&w=1536&q=75)\n\n[Check out our latest drops](https://www.heygen.com/latest-drops/fall-2024)\n\n[Solutions](https://www.heygen.com/pricing#)\n\n#### INDUSTRY\n\n[Agencies](https://www.heygen.com/agencies)[E-Learning](https://www.heygen.com/e-learning)\n\n#### TEAMS\n\n[Marketing](https://www.heygen.com/marketing)[Learning & Development](https://www.heygen.com/learning-and-development)[Localization](https://www.heygen.com/translate)[Sales Enablement](https://www.heygen.com/sales)\n\n#### USE CASES\n\n[Video Ads](https://www.heygen.com/use-cases/ai-video-ads)[Social Media](https://www.heygen.com/use-cases/social-media)[Product Explainers](https://www.heygen.com/use-cases/product-explainers)[How-to Videos](https://www.heygen.com/use-cases/how-to-videos)[Learning Courses](https://www.heygen.com/use-cases/learning-courses)[All Use Cases](https://www.heygen.com/use-cases)\n\n> ![Image 5: a man is standing in front of a cell phone in a hotel room](https://www.heygen.com/_next/image?url=https%3A%2F%2Fcdn.sanity.io%2Fimages%2Fpdhqcmb1%2Fproduction%2Ffaa0cfea3823d81b5c7bbd6d8f7327496315d5ad-2000x1153.webp%3Frect%3D39%2C0%2C1922%2C1153%26w%3D15%26h%3D9%26fit%3Dcrop%26auto%3Dformat&w=1536&q=75)![Image 6: a man is standing in front of a cell phone in a hotel room](https://www.heygen.com/_next/image?url=https%3A%2F%2Fcdn.sanity.io%2Fimages%2Fpdhqcmb1%2Fproduction%2Ffaa0cfea3823d81b5c7bbd6d8f7327496315d5ad-2000x1153.webp%3Fw%3D2000%26h%3D1153%26fit%3Dcrop%26auto%3Dformat&w=1536&q=75)\n\n[See how Trivago is creating with HeyGen](https://www.heygen.com/customer-stories/trivago)\n\n[Resources](https://www.heygen.com/pricing#)\n\n[Blog](https://www.heygen.com/blog)[Customer Stories](https://www.heygen.com/customer-stories)[Affiliate Program](https://www.heygen.com/affiliate-program?sid=no_sid)[Community](https://community.heygen.com/)[App Integrations](https://www.heygen.com/integrations)\n\n[Webinars](https://community.heygen.com/public/events)[Help Center](https://help.heygen.com/en/?sid=no_sid)[API Docs](https://docs.heygen.com/)[How To Guides](https://community.heygen.com/public/content)\n\n> ![Image 7: Create Innovative](https://www.heygen.com/_next/image?url=https%3A%2F%2Fcdn.sanity.io%2Fimages%2Fpdhqcmb1%2Fproduction%2F86929bc2752d8e9061c79af5447a4cb9f23d9bfd-640x480.png%3Frect%3D0%2C6%2C640%2C469%26w%3D15%26h%3D11%26fit%3Dcrop%26auto%3Dformat&w=1280&q=75)![Image 8: Create Innovative](https://www.heygen.com/_next/image?url=https%3A%2F%2Fcdn.sanity.io%2Fimages%2Fpdhqcmb1%2Fproduction%2F86929bc2752d8e9061c79af5447a4cb9f23d9bfd-640x480.png%3Fw%3D640%26h%3D480%26fit%3Dcrop%26auto%3Dformat&w=1536&q=75)\n\n[Stay updated with HeyGen\u2019s latest news](https://www.heygen.com/whats-new/)\n\n[Pricing](https://www.heygen.com/pricing#)\n\n[Pricing Plans](https://www.heygen.com/pricing)[API Pricing](https://www.heygen.com/api-pricing)\n\n> ![Image 9: a man is standing in front of a cell phone in a hotel room](https://www.heygen.com/_next/image?url=https%3A%2F%2Fcdn.sanity.io%2Fimages%2Fpdhqcmb1%2Fproduction%2Ffaa0cfea3823d81b5c7bbd6d8f7327496315d5ad-2000x1153.webp%3Frect%3D39%2C0%2C1922%2C1153%26w%3D15%26h%3D9%26fit%3Dcrop%26auto%3Dformat&w=1536&q=75)![Image 10: a man is standing in front of a cell phone in a hotel room](https://www.heygen.com/_next/image?url=https%3A%2F%2Fcdn.sanity.io%2Fimages%2Fpdhqcmb1%2Fproduction%2Ffaa0cfea3823d81b5c7bbd6d8f7327496315d5ad-2000x1153.webp%3Fw%3D2000%26h%3D1153%26fit%3Dcrop%26auto%3Dformat&w=1536&q=75)\n\n[See how Trivago is creating with HeyGen](https://www.heygen.com/customer-stories/trivago)\n\n[Enterprise](https://www.heygen.com/enterprise)\n\n[Company](https://www.heygen.com/pricing#)\n\n[About Us](https://www.heygen.com/about)[Careers](https://job-boards.greenhouse.io/heygen?sid=no_sid)[Trust & Safety](https://www.heygen.com/trust-and-safety)[AI Research](https://www.heygen.com/ai-research)\n\n> ![Image 11: a man is standing in front of a cell phone in a hotel room](https://www.heygen.com/_next/image?url=https%3A%2F%2Fcdn.sanity.io%2Fimages%2Fpdhqcmb1%2Fproduction%2Ffaa0cfea3823d81b5c7bbd6d8f7327496315d5ad-2000x1153.webp%3Frect%3D39%2C0%2C1922%2C1153%26w%3D15%26h%3D9%26fit%3Dcrop%26auto%3Dformat&w=1536&q=75)![Image 12: a man is standing in front of a cell phone in a hotel room](https://www.heygen.com/_next/image?url=https%3A%2F%2Fcdn.sanity.io%2Fimages%2Fpdhqcmb1%2Fproduction%2Ffaa0cfea3823d81b5c7bbd6d8f7327496315d5ad-2000x1153.webp%3Fw%3D2000%26h%3D1153%26fit%3Dcrop%26auto%3Dformat&w=1536&q=75)\n\n[See how Trivago is creating with HeyGen](https://www.heygen.com/customer-stories/trivago)\n\n[Login](https://app.heygen.com/login)\n\n[Sign up for free](https://app.heygen.com/signup)\n\n[Login](https://app.heygen.com/login)\n\n[Sign up for free](https://app.heygen.com/signup)\n\nOpen main menu\n\nFastest Growing Product by G2\n\nFlexible Plans Built for\n\nEvery Creator, Marketer, and Team\n\n\n=============================================================\n\nHeyGen powers 85,000+ businesses to create, scale, and collaborate on video content without a camera or crew and was named G2\u2019s #1 Fastest Growing Product of 2025.\n\nPay MonthlyPay Yearly (Save 22%)\n\n### Free\n\n$0/mo\n\nStart creating on HeyGen at no cost\n\n[Get Started](https://app.heygen.com/signup)\n\nVideo Generation:\n\n*   3 videos per month\n*   Videos up to 3-mins\n*   720p video export\n*   Standard video processing\n\nFeatures You\u2019ll Love:\n\n*   1 Custom Video Avatar\n*   500+ Stock Video Avatars\n*   30+ languages\n*   Share & download videos\n\n### Creator\n\n$29/mo\n\nUnlimited short-form videos for creators\n\n[Get Started](https://app.heygen.com/signup)\n\nVideo Generation:\n\n*   Unlimited videos\n*   Videos up to 5-mins\n*   1080p video export\n*   Fast video processing\n\nEverything in Free, plus:\n\n*   1+ Custom Video Avatar\n*   1+ Custom Interactive Avatar\n*   700+ Stock Video Avatars\n*   Voice cloning\n*   175+ languages and dialects\n*   Generate Looks\n*   Look Packs\n*   Watermark removal\n*   Brand Kit\n\nMost Popular\n\n### Team\n\n$39/seat/mo\n\nSupercharge video creation (minimum 2 seats)\n\n[Get Started](https://app.heygen.com/signup)\n\nVideo Generation:\n\n*   Unlimited videos\n*   Videos up to 30-mins\n*   1080p video export\n*   Faster video processing\n\nEverything in Creator, plus:\n\n*   1 Custom Video Avatar/ seat\n*   1 Custom Interactive Avatar/ seat\n*   Unlimited Photo Avatars\n*   Translation Proofread\n*   Invites & team management\n*   Collaborative workspace\n*   Pay as you grow\n*   Scale your brand and centralize assets\n\n### Enterprise\n\nLet\u2019s Talk\n\nStudio-quality custom video creation\n\n[Contact Sales](https://www.heygen.com/contact-us)\n\nVideo Generation:\n\n*   Unlimited videos\n*   No video duration max\n*   4k video export\n*   Fastest video processing\n\nEverything in Team, plus:\n\n*   Centrally manage roles and access\n*   SAML/SSO\n*   Enterprise-grade security & privacy\n*   Commercial terms\n*   Priority customer support\n*   Dedicated customer success manager\n\n[Explore Our API Pricing](https://www.heygen.com/api-pricing)\n\nFeatures\n\nCompare Plans  \nAnd Features.\n\n\n-------------------------------\n\n|  | \nFree\n\n$0/mo\n\n[Get Started For Free](https://app.heygen.com/signup) | \n\nCreator\n\n$29/mo\n\n[Get Started For Free](https://app.heygen.com/signup) | \n\nTeam\n\n$39/seat/mo\n\n[Get Started For Free](https://app.heygen.com/signup) | \n\nEnterprise\n\nLet\u2019s Talk\n\n[Let's talk](https://www.heygen.com/contact-us) |\n| --- | --- | --- | --- | --- |\n| Video Creation |\n| \n\nAI studio editor\n\n | Full access | Full access | Full access | Full access |\n| \n\nMax duration per video\n\n | 3 minutes | 5 minutes | 30 minutes | No video duration max |\n| \n\nVideo processing speed\n\n | Standard | Fast | Faster | Fastest |\n| \n\nExport resolution\n\n | 720P | Up to 1080P | Up to 1080P | Up to 4K |\n| \n\nVideo templates\n\n | 75+ | 75+ | 75+ | 75+ |\n| \n\nScreen recorder\n\n | \n\n | \n\n | \n\n | \n\n |\n| \n\nPowerPoint & PDF Imports\n\n | \n\n | \n\n | \n\n | \n\n |\n| \n\nAudio input\n\n | \n\n | \n\n | \n\n | \n\n |\n| \n\nSave designs as templates\n\n |  | \n\n | \n\n | \n\n |\n| \n\nWatermark removal\n\n |  |  |  | \n\n |\n| AI Avatars & Voices |\n| \n\nStock Video Avatars\n\n | 700+ | 1000+ | 1000+ | 1000+ |\n| \n\nCustom Video Avatars\n\n | 1 | 1+ | 1+/ seat | 3+ |\n| \n\nCustom Video Avatar Looks\n\n | 100 | 100+ | 100+ | 300+ |\n| \n\nAI Voice\n\n | 1000+ | 1000+ | 1000+ | 1000+ |\n| \n\nVoice Cloning\n\n | 1 voice clone | Unlimited | Unlimited | Unlimited |\n| \n\nPhoto Avatars\n\n | Up to 3 | Up to 10 | Unlimited | Unlimited |\n| \n\nMotion / Gesture Control\n\n | 3 uses / month | 100 uses / month | Unlimited | Unlimited |\n| \n\nGenerate Looks\n\n |  | \n\n | \n\n | \n\n |\n| \n\nAI Model Training\n\n |  | \n\n | \n\n | \n\n |\n| \n\nLook Packs\n\n |  | \n\n | \n\n | \n\n |\n| \n\nProduct Placement\n\n |  | \n\n | \n\n | \n\n |\n| \n\nCustom Voice Emotion\n\n |  | \n\n | \n\n | \n\n |\n| \n\nAdditional Custom Avatars\n\n |  | Add-on | Add-on | Add-on |\n| \n\nAI background removal\n\n |  | \n\n | \n\n | \n\n |\n| \n\n4K Custom Video Avatars\n\n |  |  |  | \n\n |\n| \n\nCustom Studio Avatar Shoot\n\n |  |  |  | Add-on |\n| Video Translation & Languages |\n| \n\nMax duration per video\n\n | 3 minutes | 5 minutes | 30 minutes | No video duration max |\n| \n\nVideo processing speed\n\n | Standard | Fast | Faster | Fastest |\n| \n\nGlobal Language Suite\n\n | 30+ languages | 175 languages and dialects | 175 languages and dialects | 175 languages and dialects |\n| \n\nBrand voice translation\n\n |  | \n\n | \n\n | \n\n |\n| \n\nTranslation proofread & editing\n\n |  |  | \n\n | \n\n |\n| \n\nProofreading collaboration\n\n |  |  |  | \n\n |\n| \n\nSRT upload\n\n |  |  |  | \n\n |\n| \n\nAudio upload\n\n |  |  |  | \n\n |\n| Workspace & Collaboration |\n| \n\nUser seats\n\n | 1 | 1 | 2+ | 3+ |\n| \n\nCommenting\n\n | \n\n | \n\n | \n\n | \n\n |\n| \n\nBrand kit\n\n |  | \n\n | \n\n | \n\n |\n| \n\nBranded share page\n\n |  |  | \n\n | \n\n |\n| \n\nCollaborative workspace\n\n |  |  | \n\n | \n\n |\n| \n\nTeam templates\n\n |  |  | \n\n | \n\n |\n| \n\nRole controls\n\n |  |  | \n\n | \n\n |\n| \n\nContent access controls\n\n |  |  | \n\n | \n\n |\n| \n\nGranular content access controls\n\n |  |  | \n\n | \n\n |\n| HeyGen Interactive Avatars |\n| \n\nStock Interactive Avatars\n\n | \n\n | \n\n | \n\n | \n\n |\n| \n\nKnowledge base\n\n | \n\n | \n\n | \n\n | \n\n |\n| \n\nJoin Zoom meetings\n\n | \n\n | \n\n | \n\n | \n\n |\n| \n\nShare /HTML embed\n\n | \n\n | \n\n | \n\n | \n\n |\n| \n\nStreaming session duration limit\n\n | 10 min / session | Unlimited | Unlimited | Unlimited |\n| \n\nCustom Interactive Avatars\n\n |  | 1 | 1/ seat | 3+ |\n| \n\nAdditional Custom Interactive Avatars\n\n |  | Add-on | Add-on | Add-on |\n| \n\nWatermark removal\n\n |  |  |  | \n\n |\n| Privacy & Security |\n| \n\nPassword Protected URLs\n\n | \n\n | \n\n | \n\n | \n\n |\n| \n\nMulti-factor authentication (MFA)\n\n | \n\n | \n\n | \n\n | \n\n |\n| \n\nSAML/SSO\n\n |  |  |  | \n\n |\n| \n\nAudit Log\n\n |  |  |  | \n\n |\n| Support & Resources |\n| \n\nLive chat support\n\n |  | \n\n | \n\n | \n\n |\n| \n\nPriority support\n\n |  |  |  | \n\n |\n| \n\nCustomer Success Manager\n\n |  |  |  | \n\n |\n\n![Image 13: the word hubspot is written in white on a black background .](https://www.heygen.com/_next/image?url=https%3A%2F%2Fcdn.sanity.io%2Fimages%2Fpdhqcmb1%2Fproduction%2F60974c7b7e3aad774b68d54e0957d50104c71129-294x86.png&w=320&q=75)\n\n![Image 14: open-ai-logo\n](https://cdn.sanity.io/images/pdhqcmb1/production/2c22ca7ec5d49061352dbc0e83df993e91aa257e-160x43.svg)\n\n![Image 15: the word ogilvy is written in white on a black background .](https://www.heygen.com/_next/image?url=https%3A%2F%2Fcdn.sanity.io%2Fimages%2Fpdhqcmb1%2Fproduction%2F25f98986ef8b42cf1dd69e31f005d320b4a09486-204x86.png&w=320&q=75)\n\n![Image 16: the word klarna is written in white on a black background](https://www.heygen.com/_next/image?url=https%3A%2F%2Fcdn.sanity.io%2Fimages%2Fpdhqcmb1%2Fproduction%2F0c5eb502270fe85cb6145b98a50baff112cbc14f-276x86.png&w=320&q=75)\n\n![Image 17: a black and white image of the shopify logo on a black background .](https://www.heygen.com/_next/image?url=https%3A%2F%2Fcdn.sanity.io%2Fimages%2Fpdhqcmb1%2Fproduction%2Fd3d3163ab9d9884e85c8b6a721378826451d007b-290x92.png&w=320&q=75)\n\n![Image 18: the word komatsu is written in white letters on a black background .](https://www.heygen.com/_next/image?url=https%3A%2F%2Fcdn.sanity.io%2Fimages%2Fpdhqcmb1%2Fproduction%2Ffd2b4d0c7be094ea8ca0b58be9f2a5cae488e43e-430x86.png&w=320&q=75)\n\n![Image 19: univision-logo](https://cdn.sanity.io/images/pdhqcmb1/production/4fff6d2f130e99c72808ea572629a2d2d874b433-152x30.svg)\n\n![Image 20: a pixel art drawing of a cloud with a black background .](https://www.heygen.com/_next/image?url=https%3A%2F%2Fcdn.sanity.io%2Fimages%2Fpdhqcmb1%2Fproduction%2F0f7a4773634ae459f5ca9612663ef2386a9222da-130x115.png&w=320&q=75)\n\n![Image 21: the harvarrd university logo is shown on a black background](https://www.heygen.com/_next/image?url=https%3A%2F%2Fcdn.sanity.io%2Fimages%2Fpdhqcmb1%2Fproduction%2Ffddcec19c3a450f213c17b7973dcf421a0e957c8-312x86.png&w=320&q=75)\n\n![Image 22: a black and white logo for a company called docusign](https://www.heygen.com/_next/image?url=https%3A%2F%2Fcdn.sanity.io%2Fimages%2Fpdhqcmb1%2Fproduction%2F9b557562450c6d3df7e926494eaa28bf2e46c361-312x64.png&w=320&q=75)\n\n![Image 23: a black and white logo for pepsico with a globe in the middle](https://www.heygen.com/_next/image?url=https%3A%2F%2Fcdn.sanity.io%2Fimages%2Fpdhqcmb1%2Fproduction%2Fc3555269141ee461f096730235ffb709a987b11b-336x86.png&w=320&q=75)\n\n![Image 24: a black and white image of the pwc logo](https://www.heygen.com/_next/image?url=https%3A%2F%2Fcdn.sanity.io%2Fimages%2Fpdhqcmb1%2Fproduction%2F340f20eec6c6ebb43f9d9888008732ac8c1a2555-120x86.png&w=320&q=75)\n\n![Image 25: the word samsung is written in white letters on a black background .](https://www.heygen.com/_next/image?url=https%3A%2F%2Fcdn.sanity.io%2Fimages%2Fpdhqcmb1%2Fproduction%2F149ce7189a4d6a68ef380468dfe2d5489edfacf1-392x86.png&w=320&q=75)\n\n![Image 26: a black and white logo for james river church](https://www.heygen.com/_next/image?url=https%3A%2F%2Fcdn.sanity.io%2Fimages%2Fpdhqcmb1%2Fproduction%2F13c7b410d1cc73557a954516e3ad0f72cd354d86-296x86.png&w=320&q=75)\n\n![Image 27: the word hubspot is written in white on a black background .](https://www.heygen.com/_next/image?url=https%3A%2F%2Fcdn.sanity.io%2Fimages%2Fpdhqcmb1%2Fproduction%2F60974c7b7e3aad774b68d54e0957d50104c71129-294x86.png&w=320&q=75)\n\n![Image 28: open-ai-logo\n](https://cdn.sanity.io/images/pdhqcmb1/production/2c22ca7ec5d49061352dbc0e83df993e91aa257e-160x43.svg)\n\n![Image 29: the word ogilvy is written in white on a black background .](https://www.heygen.com/_next/image?url=https%3A%2F%2Fcdn.sanity.io%2Fimages%2Fpdhqcmb1%2Fproduction%2F25f98986ef8b42cf1dd69e31f005d320b4a09486-204x86.png&w=320&q=75)\n\n![Image 30: the word klarna is written in white on a black background](https://www.heygen.com/_next/image?url=https%3A%2F%2Fcdn.sanity.io%2Fimages%2Fpdhqcmb1%2Fproduction%2F0c5eb502270fe85cb6145b98a50baff112cbc14f-276x86.png&w=320&q=75)\n\n![Image 31: a black and white image of the shopify logo on a black background .](https://www.heygen.com/_next/image?url=https%3A%2F%2Fcdn.sanity.io%2Fimages%2Fpdhqcmb1%2Fproduction%2Fd3d3163ab9d9884e85c8b6a721378826451d007b-290x92.png&w=320&q=75)\n\n![Image 32: the word komatsu is written in white letters on a black background .](https://www.heygen.com/_next/image?url=https%3A%2F%2Fcdn.sanity.io%2Fimages%2Fpdhqcmb1%2Fproduction%2Ffd2b4d0c7be094ea8ca0b58be9f2a5cae488e43e-430x86.png&w=320&q=75)\n\n![Image 33: univision-logo](https://cdn.sanity.io/images/pdhqcmb1/production/4fff6d2f130e99c72808ea572629a2d2d874b433-152x30.svg)\n\n![Image 34: a pixel art drawing of a cloud with a black background .](https://www.heygen.com/_next/image?url=https%3A%2F%2Fcdn.sanity.io%2Fimages%2Fpdhqcmb1%2Fproduction%2F0f7a4773634ae459f5ca9612663ef2386a9222da-130x115.png&w=320&q=75)\n\n![Image 35: the harvarrd university logo is shown on a black background](https://www.heygen.com/_next/image?url=https%3A%2F%2Fcdn.sanity.io%2Fimages%2Fpdhqcmb1%2Fproduction%2Ffddcec19c3a450f213c17b7973dcf421a0e957c8-312x86.png&w=320&q=75)\n\n![Image 36: a black and white logo for a company called docusign](https://www.heygen.com/_next/image?url=https%3A%2F%2Fcdn.sanity.io%2Fimages%2Fpdhqcmb1%2Fproduction%2F9b557562450c6d3df7e926494eaa28bf2e46c361-312x64.png&w=320&q=75)\n\n![Image 37: a black and white logo for pepsico with a globe in the middle](https://www.heygen.com/_next/image?url=https%3A%2F%2Fcdn.sanity.io%2Fimages%2Fpdhqcmb1%2Fproduction%2Fc3555269141ee461f096730235ffb709a987b11b-336x86.png&w=320&q=75)\n\n![Image 38: a black and white image of the pwc logo](https://www.heygen.com/_next/image?url=https%3A%2F%2Fcdn.sanity.io%2Fimages%2Fpdhqcmb1%2Fproduction%2F340f20eec6c6ebb43f9d9888008732ac8c1a2555-120x86.png&w=320&q=75)\n\n![Image 39: the word samsung is written in white letters on a black background .](https://www.heygen.com/_next/image?url=https%3A%2F%2Fcdn.sanity.io%2Fimages%2Fpdhqcmb1%2Fproduction%2F149ce7189a4d6a68ef380468dfe2d5489edfacf1-392x86.png&w=320&q=75)\n\n![Image 40: a black and white logo for james river church](https://www.heygen.com/_next/image?url=https%3A%2F%2Fcdn.sanity.io%2Fimages%2Fpdhqcmb1%2Fproduction%2F13c7b410d1cc73557a954516e3ad0f72cd354d86-296x86.png&w=320&q=75)\n\n![Image 41: the word hubspot is written in white on a black background .](https://www.heygen.com/_next/image?url=https%3A%2F%2Fcdn.sanity.io%2Fimages%2Fpdhqcmb1%2Fproduction%2F60974c7b7e3aad774b68d54e0957d50104c71129-294x86.png&w=320&q=75)\n\n![Image 42: open-ai-logo\n](https://cdn.sanity.io/images/pdhqcmb1/production/2c22ca7ec5d49061352dbc0e83df993e91aa257e-160x43.svg)\n\n![Image 43: the word ogilvy is written in white on a black background .](https://www.heygen.com/_next/image?url=https%3A%2F%2Fcdn.sanity.io%2Fimages%2Fpdhqcmb1%2Fproduction%2F25f98986ef8b42cf1dd69e31f005d320b4a09486-204x86.png&w=320&q=75)\n\n![Image 44: the word klarna is written in white on a black background](https://www.heygen.com/_next/image?url=https%3A%2F%2Fcdn.sanity.io%2Fimages%2Fpdhqcmb1%2Fproduction%2F0c5eb502270fe85cb6145b98a50baff112cbc14f-276x86.png&w=320&q=75)\n\n![Image 45: a black and white image of the shopify logo on a black background .](https://www.heygen.com/_next/image?url=https%3A%2F%2Fcdn.sanity.io%2Fimages%2Fpdhqcmb1%2Fproduction%2Fd3d3163ab9d9884e85c8b6a721378826451d007b-290x92.png&w=320&q=75)\n\n![Image 46: the word komatsu is written in white letters on a black background .](https://www.heygen.com/_next/image?url=https%3A%2F%2Fcdn.sanity.io%2Fimages%2Fpdhqcmb1%2Fproduction%2Ffd2b4d0c7be094ea8ca0b58be9f2a5cae488e43e-430x86.png&w=320&q=75)\n\n![Image 47: univision-logo](https://cdn.sanity.io/images/pdhqcmb1/production/4fff6d2f130e99c72808ea572629a2d2d874b433-152x30.svg)\n\n![Image 48: a pixel art drawing of a cloud with a black background .](https://www.heygen.com/_next/image?url=https%3A%2F%2Fcdn.sanity.io%2Fimages%2Fpdhqcmb1%2Fproduction%2F0f7a4773634ae459f5ca9612663ef2386a9222da-130x115.png&w=320&q=75)\n\n![Image 49: the harvarrd university logo is shown on a black background](https://www.heygen.com/_next/image?url=https%3A%2F%2Fcdn.sanity.io%2Fimages%2Fpdhqcmb1%2Fproduction%2Ffddcec19c3a450f213c17b7973dcf421a0e957c8-312x86.png&w=320&q=75)\n\n![Image 50: a black and white logo for a company called docusign](https://www.heygen.com/_next/image?url=https%3A%2F%2Fcdn.sanity.io%2Fimages%2Fpdhqcmb1%2Fproduction%2F9b557562450c6d3df7e926494eaa28bf2e46c361-312x64.png&w=320&q=75)\n\n![Image 51: a black and white logo for pepsico with a globe in the middle](https://www.heygen.com/_next/image?url=https%3A%2F%2Fcdn.sanity.io%2Fimages%2Fpdhqcmb1%2Fproduction%2Fc3555269141ee461f096730235ffb709a987b11b-336x86.png&w=320&q=75)\n\n![Image 52: a black and white image of the pwc logo](https://www.heygen.com/_next/image?url=https%3A%2F%2Fcdn.sanity.io%2Fimages%2Fpdhqcmb1%2Fproduction%2F340f20eec6c6ebb43f9d9888008732ac8c1a2555-120x86.png&w=320&q=75)\n\n![Image 53: the word samsung is written in white letters on a black background .](https://www.heygen.com/_next/image?url=https%3A%2F%2Fcdn.sanity.io%2Fimages%2Fpdhqcmb1%2Fproduction%2F149ce7189a4d6a68ef380468dfe2d5489edfacf1-392x86.png&w=320&q=75)\n\n![Image 54: a black and white logo for james river church](https://www.heygen.com/_next/image?url=https%3A%2F%2Fcdn.sanity.io%2Fimages%2Fpdhqcmb1%2Fproduction%2F13c7b410d1cc73557a954516e3ad0f72cd354d86-296x86.png&w=320&q=75)\n\n![Image 55: the word hubspot is written in white on a black background .](https://www.heygen.com/_next/image?url=https%3A%2F%2Fcdn.sanity.io%2Fimages%2Fpdhqcmb1%2Fproduction%2F60974c7b7e3aad774b68d54e0957d50104c71129-294x86.png&w=320&q=75)\n\n![Image 56: open-ai-logo\n](https://cdn.sanity.io/images/pdhqcmb1/production/2c22ca7ec5d49061352dbc0e83df993e91aa257e-160x43.svg)\n\n![Image 57: the word ogilvy is written in white on a black background .](https://www.heygen.com/_next/image?url=https%3A%2F%2Fcdn.sanity.io%2Fimages%2Fpdhqcmb1%2Fproduction%2F25f98986ef8b42cf1dd69e31f005d320b4a09486-204x86.png&w=320&q=75)\n\n![Image 58: the word klarna is written in white on a black background](https://www.heygen.com/_next/image?url=https%3A%2F%2Fcdn.sanity.io%2Fimages%2Fpdhqcmb1%2Fproduction%2F0c5eb502270fe85cb6145b98a50baff112cbc14f-276x86.png&w=320&q=75)\n\n![Image 59: a black and white image of the shopify logo on a black background .](https://www.heygen.com/_next/image?url=https%3A%2F%2Fcdn.sanity.io%2Fimages%2Fpdhqcmb1%2Fproduction%2Fd3d3163ab9d9884e85c8b6a721378826451d007b-290x92.png&w=320&q=75)\n\n![Image 60: the word komatsu is written in white letters on a black background .](https://www.heygen.com/_next/image?url=https%3A%2F%2Fcdn.sanity.io%2Fimages%2Fpdhqcmb1%2Fproduction%2Ffd2b4d0c7be094ea8ca0b58be9f2a5cae488e43e-430x86.png&w=320&q=75)\n\n![Image 61: univision-logo](https://cdn.sanity.io/images/pdhqcmb1/production/4fff6d2f130e99c72808ea572629a2d2d874b433-152x30.svg)\n\n![Image 62: a pixel art drawing of a cloud with a black background .](https://www.heygen.com/_next/image?url=https%3A%2F%2Fcdn.sanity.io%2Fimages%2Fpdhqcmb1%2Fproduction%2F0f7a4773634ae459f5ca9612663ef2386a9222da-130x115.png&w=320&q=75)\n\n![Image 63: the harvarrd university logo is shown on a black background](https://www.heygen.com/_next/image?url=https%3A%2F%2Fcdn.sanity.io%2Fimages%2Fpdhqcmb1%2Fproduction%2Ffddcec19c3a450f213c17b7973dcf421a0e957c8-312x86.png&w=320&q=75)\n\n![Image 64: a black and white logo for a company called docusign](https://www.heygen.com/_next/image?url=https%3A%2F%2Fcdn.sanity.io%2Fimages%2Fpdhqcmb1%2Fproduction%2F9b557562450c6d3df7e926494eaa28bf2e46c361-312x64.png&w=320&q=75)\n\n![Image 65: a black and white logo for pepsico with a globe in the middle](https://www.heygen.com/_next/image?url=https%3A%2F%2Fcdn.sanity.io%2Fimages%2Fpdhqcmb1%2Fproduction%2Fc3555269141ee461f096730235ffb709a987b11b-336x86.png&w=320&q=75)\n\n![Image 66: a black and white image of the pwc logo](https://www.heygen.com/_next/image?url=https%3A%2F%2Fcdn.sanity.io%2Fimages%2Fpdhqcmb1%2Fproduction%2F340f20eec6c6ebb43f9d9888008732ac8c1a2555-120x86.png&w=320&q=75)\n\n![Image 67: the word samsung is written in white letters on a black background .](https://www.heygen.com/_next/image?url=https%3A%2F%2Fcdn.sanity.io%2Fimages%2Fpdhqcmb1%2Fproduction%2F149ce7189a4d6a68ef380468dfe2d5489edfacf1-392x86.png&w=320&q=75)\n\n![Image 68: a black and white logo for james river church](https://www.heygen.com/_next/image?url=https%3A%2F%2Fcdn.sanity.io%2Fimages%2Fpdhqcmb1%2Fproduction%2F13c7b410d1cc73557a954516e3ad0f72cd354d86-296x86.png&w=320&q=75)\n\nTrusted by over\n\n85,000+ customers\n\n![Image 69: background image](https://www.heygen.com/_next/image?url=https%3A%2F%2Fcdn.sanity.io%2Fimages%2Fpdhqcmb1%2Fproduction%2F042653d89df99494fcd36c94f58e82dad6b32bc2-3760x2116.png&w=1536&q=75)\n\nPricing FAQs\n------------\n\nHow much does HeyGen cost?\n\nWhat happens when I cancel my subscription?\n\nWhat Is the difference between a monthly and yearly subscriptio?\n\nHow do I switch plans?\n\nAm I allowed to use videos to promote services to clients?\n\nWhat payment methods do you offer?\n\nHow can I cancel my plan?\n\nTestimonials\n\nWhat Customers Say About Us\n\n\n-----------------------------\n\n[Get Started For Free](https://app.heygen.com/signup)\n\n5 out of 5 Stars\n\n\"A great resource for instructors to easily create content\"\n\n\"This tool is very user-friendly with helpful step-by-step instructions. The custom AI video avatar works flawlessly, and even the free plan meets my needs.\" - Kwan S. on G2\n\n5 out of 5 Stars\n\n\"Innovative and easy-to-use AI video creation tool\"\n\n\"HeyGen is incredibly intuitive and user-friendly for AI video content. I was impressed by the quality of the avatars and lip-sync, making videos look very natural.\" - Javier M. on G2\n\n5 out of 5 Stars\n\n\"My Digital AI Twin Does My Market Update Videos\"\n\n\"This is now achieved in much less time and no travel. Now I can sit in my casual clothes and produce all my videos in one take, saving many hours each week.\" - Eriks D. on G2\n\n5 out of 5 Stars\n\n\"Effective way to share your message.\"\n\n\"It keeps my students engaged, and the best part is that it takes almost no time to produce high-quality content. With HeyGen, I can prepare a lesson in under two hours \u2013 it has transformed how I teach!\" - Ella K. on G2\n\n5 out of 5 Stars\n\n\"An engaging filmmaking adventure for an amateur\"\n\n\"As an amateur filmmaker, I benefited greatly from HeyGen. It helped me effortlessly create my first video and manage my professional YouTube channel, which seemed successful due to the captivating avatars it offered.\" - Mohammad A. on G2\n\n5 out of 5 Stars\n\n\"Awesome tool for busy founders and creators\"\n\n\"I can create hundreds of videos without physically being present. I've taken control of my time and increased my productivity more than ever.\" - Sujit K. on G2\n\n5 out of 5 Stars\n\n\"Unbelievably realistic avatars\"\n\n\"The avatars are unbelievably realistic. The lip-sync and expressions are spot on. My clients thought it was a real presenter!\" - Brenda K. on Product Hunt\n\n5 out of 5 Stars\n\n\"Game changer for content creation\"\n\n\"HeyGen is a game changer! It's incredibly easy to create videos now. The AI avatars look real and I can produce content so much faster.\" - Alec L. on Product Hunt\n\n5 out of 5 Stars\n\n\"Competition creates the best - HeyGen\"\n\n\"Only HeyGen provides high-quality translation, dubbing, and lip-syncing. At this stage, it's the best service for video translation and dubbing.\" - Pavel G. on G2\n\n5 out of 5 Stars\n\n\"Huge time saver\"\n\n\"What used to take me days now takes hours. HeyGen speeds up video production like nothing else, with zero compromise on quality.\" - Carlos M. on Product Hunt\n\n5 out of 5 Stars\n\n\"So easy to use!\"\n\n\"I am not very tech-savvy, but HeyGen is so easy to use. I made a professional video on my first try. Absolutely love it.\"  \n\\- Diana P. on Product Hunt\n\n5 out of 5 Stars\n\n\"Impressive AI quality\"\n\n\"I was skeptical, but the AI quality impressed me. The voices and avatars are top-notch. It definitely makes our workflow more efficient.\" - Ethan W. on Product Hunt\n\n5 out of 5 Stars\n\n\"Make your life easier with HeyGen!\"\n\n\"HeyGen has made our video content creation much easier and faster. It's a dynamic tool with huge potential.\" - Hannah L. on Capterra\n\n5 out of 5 Stars\n\n\"Constantly adding innovative features\"\n\n\"HeyGen's avatars are incredibly lifelike, with natural movements and expressions. I was blown away by the seamless lip-sync. I can input my script and generate a polished video in no time.\" - Joseph S. on G2\n\n5 out of 5 Stars\n\n\"The best on the market\"\n\n\"The quality of the results, especially the voice generation, is so high that it's very difficult to distinguish the avatar from a real person.\" - Nina P. on Capterra\n\n5 out of 5 Stars\n\n\"Remarkable video creations\"\n\n\"This has been such a great experience. Coming from image generation, I was amazed at how easy video creation is with HeyGen.\" - Anna R. on G2\n\n5 out of 5 Stars\n\n\"Transforms our content creation\"\n\n\"HeyGen helps us create professional videos at a fraction of the time and cost of traditional methods. It's a game-changer for our team.\" - Allison G. on Capterra\n\n5 out of 5 Stars\n\n\"Impressive AI video generation\"\n\n\"I was skeptical at first, but HeyGen impressed me with its realistic avatars and easy workflow. It's now a go-to tool for our projects.\" - Omar V. on Capterra\n\n5 out of 5 Stars\n\n\"Highly recommend for marketers\"\n\n\"As a marketer, HeyGen has saved me so much time. It's easy to use and the videos look highly professional.\" - Rebecca S. on Capterra\n\n5 out of 5 Stars\n\n\"Super impressive and very easy to use\"\n\n\"Took minimal time and effort to get set up, and the output quality is fantastic.\" - Kevin L. on G2\n\n5 out of 5 Stars\n\n\"Simple and straightforward\"\n\n\"It\u2019s simple and offers various options to make videos look good and engaging.\" - Brian T. on G2\n\n5 out of 5 Stars\n\n\"Fast and intuitive\"\n\n\"I can churn out videos incredibly fast with HeyGen. The intuitive interface means there's virtually no learning curve.\" - Phil C. on Capterra\n\n5 out of 5 Stars\n\n\"Ideal for e-learning\"\n\n\"We've incorporated HeyGen into our e-learning creation. The avatars and voices make lessons engaging, and it's extremely easy to use.\" - Quinn H. on Capterra\n\n5 out of 5 Stars\n\n\"Cuts down production time\"\n\n\"HeyGen significantly cuts down our video production time. We can create training videos much faster without compromising on quality.\" - Samuel E. on Capterra\n\n5 out of 5 Stars\n\n\"Exceeded my expectations\"\n\n\"The realism of the avatars exceeded my expectations. It\u2019s easy to use and the end product looks professional.\" - Alex W. on G2\n\n5 out of 5 Stars\n\n\"Terrific for multilingual videos\"\n\n\"HeyGen's translation features are terrific. We can easily create multilingual videos. The dubbed voices sound excellent.\" - Kim L. on Capterra\n\n5 out of 5 Stars\n\n\"Great support and quality\"\n\n\"I had an issue and their support responded within minutes. The avatar quality is amazing, and overall it's a valuable tool.\" - Danielle U. on Capterra\n\n5 out of 5 Stars\n\n\"Revolutionary technology\"\n\n\"This is revolutionary for our content creation. It saves time, money, and the results are highly professional. Truly impressive.\" - Manuel R. on Capterra\n\n5 out of 5 Stars\n\n\"Makes video creation a breeze\"\n\n\"The interface is extremely user-friendly, making video creation a breeze even with no editing skills.\" - Mark C. on G2\n\n5 out of 5 Stars\n\n\"Huge time-saver\"\n\n\"HeyGen saves me hours on video production. I can generate a polished video in minutes without a camera or crew.\" - Sophia L. on G2\n\n5 out of 5 Stars\n\n\"Quality results in minutes\"\n\n\"I can produce professional-quality videos in just minutes. The avatars and voices are so realistic.\" - Derek P. on G2\n\n5 out of 5 Stars\n\n\"Lifelike avatars, simple UI\"\n\n\"I love the lifelike avatars and how simple the UI is. Even our non-designers can create great videos with HeyGen.\" - Thomas V. on Product Hunt\n\n5 out of 5 Stars\n\n\"Versatile and intuitive\"\n\n\"The versatility of this tool is impressive. We make everything from ads to tutorials. HeyGen is intuitive and requires minimal effort.\" - Umair B. on Product Hunt\n\n5 out of 5 Stars\n\n\"Exceeded expectations\"\n\n\"HeyGen exceeded my expectations in every way. The speed, the quality, the ease of use \u2014 it's all top-notch.\" - Valerie C. on Product Hunt\n\n5 out of 5 Stars\n\n\"No camera needed!\"\n\n\"I love that I don't need any camera or crew now. I just type my script and get a video. It's incredibly convenient and the results are great.\" - Wendy D. on Product Hunt\n\n5 out of 5 Stars\n\n\"Perfect for global audience\"\n\n\"HeyGen\u2019s multi-language support is perfect for reaching a global audience. The translations and voice overs sound very natural.\" - Xiao L. on Product Hunt\n\n5 out of 5 Stars\n\n\"Remarkable video creations\"\n\n\"Coming from image generation, I found the video creation experience with HeyGen to be outstanding. It unlocks so much creativity with ease.\" - Bella M. on Capterra\n\n5 out of 5 Stars\n\n\"Great for entrepreneurs\"\n\n\"As a solo entrepreneur, HeyGen helps me create professional content without any production team. It's very straightforward and effective.\" - Alexis N. on Product Hunt\n\n5 out of 5 Stars\n\n\"Simplifies video creation\"\n\n\"Video creation is so much simpler now. HeyGen turned a complicated process into something anyone can do in a short time.\" - Ben T. on Product Hunt\n\n5 out of 5 Stars\n\n\"Loving the AI avatars\"\n\n\"I am loving the AI avatars. They look real and deliver my message effectively. Plus, I can churn out content much faster.\" - Cynthia L. on Product Hunt\n\n5 out of 5 Stars\n\n\"High quality, low effort\"\n\n\"The quality of videos is high while the effort required is low. It's exactly what I needed to boost my content output.\" - Devon R. on Product Hunt\n\n5 out of 5 Stars\n\n\"Worth the investment\"\n\n\"We decided to invest in HeyGen and it paid off. Our videos are more engaging and we're producing them faster than ever.\" - Elena C. on Capterra\n\n5 out of 5 Stars\n\n\"Great support\"\n\n\"The customer support is excellent. They helped me quickly when I had questions. The tool itself is fantastic and easy to use.\" - Ravi T. on Product Hunt\n\n5 out of 5 Stars\n\n\"Easy for a tech idiot like me!\"\n\n\"I'm every day using HeyGen and making videos for my social media! I like this! (It\u2019s very easy to use, even for a non-tech person.)\" - Ippazio D. on Capterra\n\n5 out of 5 Stars\n\n\"Brilliant for marketing\"\n\n\"We use HeyGen for marketing videos. It's brilliant! Our content output increased and the videos look very professional and engaging.\" - Sofia M. on Product Hunt\n\n5 out of 5 Stars\n\n\"Perfect lip-sync technology\"\n\n\"HeyGen powers our human-like avatars with perfect lip-sync. It's less complex and more intuitive than other AI tools we tried.\" - Shivali G. on Product Hunt\n\n5 out of 5 Stars\n\n\"I am amazed\"\n\n\"Seeing what is possible now with AI is just mind blowing!\" - Allan F. on Capterra\n\n5 out of 5 Stars\n\n\"I freaking love it!\"\n\n\"I'm in love. It allows me to create content I could never have created on my own. It allows me to reach people in places I could never have reached before.\" - Ped on Capterra\n\n5 out of 5 Stars\n\n\"Stop hesitating\"\n\n\"WOW! It is crazy what the future of AI and video generation looks like with HeyGen.\" - Lena C. on Product Hunt\n\n5 out of 5 Stars\n\n\"A great resource for instructors to easily create content\"\n\n\"This tool is very user-friendly with helpful step-by-step instructions. The custom AI video avatar works flawlessly, and even the free plan meets my needs.\" - Kwan S. on G2\n\n5 out of 5 Stars\n\n\"Innovative and easy-to-use AI video creation tool\"\n\n\"HeyGen is incredibly intuitive and user-friendly for AI video content. I was impressed by the quality of the avatars and lip-sync, making videos look very natural.\" - Javier M. on G2\n\n5 out of 5 Stars\n\n\"My Digital AI Twin Does My Market Update Videos\"\n\n\"This is now achieved in much less time and no travel. Now I can sit in my casual clothes and produce all my videos in one take, saving many hours each week.\" - Eriks D. on G2\n\n5 out of 5 Stars\n\n\"Effective way to share your message.\"\n\n\"It keeps my students engaged, and the best part is that it takes almost no time to produce high-quality content. With HeyGen, I can prepare a lesson in under two hours \u2013 it has transformed how I teach!\" - Ella K. on G2\n\n5 out of 5 Stars\n\n\"An engaging filmmaking adventure for an amateur\"\n\n\"As an amateur filmmaker, I benefited greatly from HeyGen. It helped me effortlessly create my first video and manage my professional YouTube channel, which seemed successful due to the captivating avatars it offered.\" - Mohammad A. on G2\n\n5 out of 5 Stars\n\n\"Awesome tool for busy founders and creators\"\n\n\"I can create hundreds of videos without physically being present. I've taken control of my time and increased my productivity more than ever.\" - Sujit K. on G2\n\n5 out of 5 Stars\n\n\"Unbelievably realistic avatars\"\n\n\"The avatars are unbelievably realistic. The lip-sync and expressions are spot on. My clients thought it was a real presenter!\" - Brenda K. on Product Hunt\n\n5 out of 5 Stars\n\n\"Game changer for content creation\"\n\n\"HeyGen is a game changer! It's incredibly easy to create videos now. The AI avatars look real and I can produce content so much faster.\" - Alec L. on Product Hunt\n\n5 out of 5 Stars\n\n\"Competition creates the best - HeyGen\"\n\n\"Only HeyGen provides high-quality translation, dubbing, and lip-syncing. At this stage, it's the best service for video translation and dubbing.\" - Pavel G. on G2\n\n5 out of 5 Stars\n\n\"Huge time saver\"\n\n\"What used to take me days now takes hours. HeyGen speeds up video production like nothing else, with zero compromise on quality.\" - Carlos M. on Product Hunt\n\n5 out of 5 Stars\n\n\"So easy to use!\"\n\n\"I am not very tech-savvy, but HeyGen is so easy to use. I made a professional video on my first try. Absolutely love it.\"  \n\\- Diana P. on Product Hunt\n\n5 out of 5 Stars\n\n\"Impressive AI quality\"\n\n\"I was skeptical, but the AI quality impressed me. The voices and avatars are top-notch. It definitely makes our workflow more efficient.\" - Ethan W. on Product Hunt\n\n5 out of 5 Stars\n\n\"Make your life easier with HeyGen!\"\n\n\"HeyGen has made our video content creation much easier and faster. It's a dynamic tool with huge potential.\" - Hannah L. on Capterra\n\n5 out of 5 Stars\n\n\"Constantly adding innovative features\"\n\n\"HeyGen's avatars are incredibly lifelike, with natural movements and expressions. I was blown away by the seamless lip-sync. I can input my script and generate a polished video in no time.\" - Joseph S. on G2\n\n5 out of 5 Stars\n\n\"The best on the market\"\n\n\"The quality of the results, especially the voice generation, is so high that it's very difficult to distinguish the avatar from a real person.\" - Nina P. on Capterra\n\n5 out of 5 Stars\n\n\"Remarkable video creations\"\n\n\"This has been such a great experience. Coming from image generation, I was amazed at how easy video creation is with HeyGen.\" - Anna R. on G2\n\n5 out of 5 Stars\n\n\"Transforms our content creation\"\n\n\"HeyGen helps us create professional videos at a fraction of the time and cost of traditional methods. It's a game-changer for our team.\" - Allison G. on Capterra\n\n5 out of 5 Stars\n\n\"Impressive AI video generation\"\n\n\"I was skeptical at first, but HeyGen impressed me with its realistic avatars and easy workflow. It's now a go-to tool for our projects.\" - Omar V. on Capterra\n\n5 out of 5 Stars\n\n\"Highly recommend for marketers\"\n\n\"As a marketer, HeyGen has saved me so much time. It's easy to use and the videos look highly professional.\" - Rebecca S. on Capterra\n\n5 out of 5 Stars\n\n\"Super impressive and very easy to use\"\n\n\"Took minimal time and effort to get set up, and the output quality is fantastic.\" - Kevin L. on G2\n\n5 out of 5 Stars\n\n\"Simple and straightforward\"\n\n\"It\u2019s simple and offers various options to make videos look good and engaging.\" - Brian T. on G2\n\n5 out of 5 Stars\n\n\"Fast and intuitive\"\n\n\"I can churn out videos incredibly fast with HeyGen. The intuitive interface means there's virtually no learning curve.\" - Phil C. on Capterra\n\n5 out of 5 Stars\n\n\"Ideal for e-learning\"\n\n\"We've incorporated HeyGen into our e-learning creation. The avatars and voices make lessons engaging, and it's extremely easy to use.\" - Quinn H. on Capterra\n\n5 out of 5 Stars\n\n\"Cuts down production time\"\n\n\"HeyGen significantly cuts down our video production time. We can create training videos much faster without compromising on quality.\" - Samuel E. on Capterra\n\n5 out of 5 Stars\n\n\"Exceeded my expectations\"\n\n\"The realism of the avatars exceeded my expectations. It\u2019s easy to use and the end product looks professional.\" - Alex W. on G2\n\n5 out of 5 Stars\n\n\"Terrific for multilingual videos\"\n\n\"HeyGen's translation features are terrific. We can easily create multilingual videos. The dubbed voices sound excellent.\" - Kim L. on Capterra\n\n5 out of 5 Stars\n\n\"Great support and quality\"\n\n\"I had an issue and their support responded within minutes. The avatar quality is amazing, and overall it's a valuable tool.\" - Danielle U. on Capterra\n\n5 out of 5 Stars\n\n\"Revolutionary technology\"\n\n\"This is revolutionary for our content creation. It saves time, money, and the results are highly professional. Truly impressive.\" - Manuel R. on Capterra\n\n5 out of 5 Stars\n\n\"Makes video creation a breeze\"\n\n\"The interface is extremely user-friendly, making video creation a breeze even with no editing skills.\" - Mark C. on G2\n\n5 out of 5 Stars\n\n\"Huge time-saver\"\n\n\"HeyGen saves me hours on video production. I can generate a polished video in minutes without a camera or crew.\" - Sophia L. on G2\n\n5 out of 5 Stars\n\n\"Quality results in minutes\"\n\n\"I can produce professional-quality videos in just minutes. The avatars and voices are so realistic.\" - Derek P. on G2\n\n5 out of 5 Stars\n\n\"Lifelike avatars, simple UI\"\n\n\"I love the lifelike avatars and how simple the UI is. Even our non-designers can create great videos with HeyGen.\" - Thomas V. on Product Hunt\n\n5 out of 5 Stars\n\n\"Versatile and intuitive\"\n\n\"The versatility of this tool is impressive. We make everything from ads to tutorials. HeyGen is intuitive and requires minimal effort.\" - Umair B. on Product Hunt\n\n5 out of 5 Stars\n\n\"Exceeded expectations\"\n\n\"HeyGen exceeded my expectations in every way. The speed, the quality, the ease of use \u2014 it's all top-notch.\" - Valerie C. on Product Hunt\n\n5 out of 5 Stars\n\n\"No camera needed!\"\n\n\"I love that I don't need any camera or crew now. I just type my script and get a video. It's incredibly convenient and the results are great.\" - Wendy D. on Product Hunt\n\n5 out of 5 Stars\n\n\"Perfect for global audience\"\n\n\"HeyGen\u2019s multi-language support is perfect for reaching a global audience. The translations and voice overs sound very natural.\" - Xiao L. on Product Hunt\n\n5 out of 5 Stars\n\n\"Remarkable video creations\"\n\n\"Coming from image generation, I found the video creation experience with HeyGen to be outstanding. It unlocks so much creativity with ease.\" - Bella M. on Capterra\n\n5 out of 5 Stars\n\n\"Great for entrepreneurs\"\n\n\"As a solo entrepreneur, HeyGen helps me create professional content without any production team. It's very straightforward and effective.\" - Alexis N. on Product Hunt\n\n5 out of 5 Stars\n\n\"Simplifies video creation\"\n\n\"Video creation is so much simpler now. HeyGen turned a complicated process into something anyone can do in a short time.\" - Ben T. on Product Hunt\n\n5 out of 5 Stars\n\n\"Loving the AI avatars\"\n\n\"I am loving the AI avatars. They look real and deliver my message effectively. Plus, I can churn out content much faster.\" - Cynthia L. on Product Hunt\n\n5 out of 5 Stars\n\n\"High quality, low effort\"\n\n\"The quality of videos is high while the effort required is low. It's exactly what I needed to boost my content output.\" - Devon R. on Product Hunt\n\n5 out of 5 Stars\n\n\"Worth the investment\"\n\n\"We decided to invest in HeyGen and it paid off. Our videos are more engaging and we're producing them faster than ever.\" - Elena C. on Capterra\n\n5 out of 5 Stars\n\n\"Great support\"\n\n\"The customer support is excellent. They helped me quickly when I had questions. The tool itself is fantastic and easy to use.\" - Ravi T. on Product Hunt\n\n5 out of 5 Stars\n\n\"Easy for a tech idiot like me!\"\n\n\"I'm every day using HeyGen and making videos for my social media! I like this! (It\u2019s very easy to use, even for a non-tech person.)\" - Ippazio D. on Capterra\n\n5 out of 5 Stars\n\n\"Brilliant for marketing\"\n\n\"We use HeyGen for marketing videos. It's brilliant! Our content output increased and the videos look very professional and engaging.\" - Sofia M. on Product Hunt\n\n5 out of 5 Stars\n\n\"Perfect lip-sync technology\"\n\n\"HeyGen powers our human-like avatars with perfect lip-sync. It's less complex and more intuitive than other AI tools we tried.\" - Shivali G. on Product Hunt\n\n5 out of 5 Stars\n\n\"I am amazed\"\n\n\"Seeing what is possible now with AI is just mind blowing!\" - Allan F. on Capterra\n\n5 out of 5 Stars\n\n\"I freaking love it!\"\n\n\"I'm in love. It allows me to create content I could never have created on my own. It allows me to reach people in places I could never have reached before.\" - Ped on Capterra\n\n5 out of 5 Stars\n\n\"Stop hesitating\"\n\n\"WOW! It is crazy what the future of AI and video generation looks like with HeyGen.\" - Lena C. on Product Hunt\n\n[Home](https://www.heygen.com/)\n\nPricing\n\n![Image 70: logo](https://www.heygen.com/images/heygen-logo.svg)[Sign up for free](https://app.heygen.com/signup)[Login](https://app.heygen.com/login)\n\nPricing\n\n[Pricing Plans](https://www.heygen.com/pricing)[API Pricing](https://www.heygen.com/api-pricing)\n\nHeyGen for Enterprise\n\n[Enterprise](https://www.heygen.com/enterprise)[Contact Sales](https://www.heygen.com/contact-us)\n\nProducts\n\n[Video Avatars](https://www.heygen.com/avatars/ai-video-avatar)[Photo Avatars](https://www.heygen.com/avatars/ai-photo-avatar)[Generative Avatars](https://www.heygen.com/avatars/generative-avatar)[Stock Avatars](https://www.heygen.com/avatars/stock-avatars)[Avatar Looks](https://www.heygen.com/avatars/avatar-looks)[Avatar Video](https://www.heygen.com/create-avatar-video)[API](https://docs.heygen.com/)[Video Translation](https://www.heygen.com/translate)[Localization](https://www.heygen.com/translate/language-localization)[Personalized Video](https://www.heygen.com/personalized-video)[Interactive Avatar](https://www.heygen.com/interactive-avatar)[AI Tools](https://www.heygen.com/ai-tools)\n\nIndustry\n\n[Agencies](https://www.heygen.com/agencies)[E-Learning](https://www.heygen.com/e-learning)\n\nResources\n\n[Blog](https://www.heygen.com/blog)[Customer Stories](https://www.heygen.com/customer-stories)[Affiliate Program](https://www.heygen.com/affiliate-program)[Webinars](https://community.heygen.com/public/events)[Help Center](https://help.heygen.com/en/)[Community](https://community.heygen.com/)[How To Guides](https://community.heygen.com/public/content)[API Docs](https://docs.heygen.com/)[FAQ](https://www.heygen.com/faq)[Tutorials](https://www.heygen.com/tutorial)\n\nTeams\n\n[Marketing](https://www.heygen.com/marketing)[Learning & Development](https://www.heygen.com/learning-and-development)[Localization](https://www.heygen.com/translate)[Sales Enablement](https://www.heygen.com/sales)\n\nCompany\n\n[About Us](https://www.heygen.com/about)[Careers](https://job-boards.greenhouse.io/heygen)[Competitors](https://www.heygen.com/alternatives)[Trust & Safety](https://www.heygen.com/trust-and-safety)[AI Research](https://www.heygen.com/ai-research)[Security Portal](https://security.heygen.com/)[Privacy Policy](https://www.heygen.com/policy)[Terms of Service](https://www.heygen.com/terms)[Moderation Policy](https://www.heygen.com/moderation-policy)Cookie Preference\n\n@Copyright HeyGen12130 Millennium Drive Suite 300, Los Angeles, CA 90094\n\n![Image 71: Content Authentication Logo](https://www.heygen.com/_next/image?url=%2Fassets_2025%2F_next%2Fstatic%2Fmedia%2Fcontent-auth.d8f8f229.webp&w=128&q=75)![Image 72: C2PA Certification Logo](https://www.heygen.com/_next/image?url=%2Fassets_2025%2F_next%2Fstatic%2Fmedia%2Fc2-pa.76720745.webp&w=64&q=75)\n\n[](https://www.linkedin.com/company/heygen)[](https://www.youtube.com/@heygen_official)[](https://x.com/heygen_official?mx=2)\n\n     ![Image 74](https://t.co/1/i/adsct?bci=4&dv=UTC%26en-US%26Google%20Inc.%26Linux%20x86_64%26255%26800%26600%264%2624%26800%26600%260%26na&eci=3&event=%7B%7D&event_id=2f60106e-a1aa-466f-b7e9-24a0f72ba5ed&integration=advertiser&p_id=Twitter&p_user_id=0&pl_id=59d2ecae-8f7a-403e-9740-e8c3802d7631&tw_document_href=https%3A%2F%2Fwww.heygen.com%2Fpricing&tw_iframe_status=0&txn_id=of0u6&type=javascript&version=2.3.31)![Image 75](https://analytics.twitter.com/1/i/adsct?bci=4&dv=UTC%26en-US%26Google%20Inc.%26Linux%20x86_64%26255%26800%26600%264%2624%26800%26600%260%26na&eci=3&event=%7B%7D&event_id=2f60106e-a1aa-466f-b7e9-24a0f72ba5ed&integration=advertiser&p_id=Twitter&p_user_id=0&pl_id=59d2ecae-8f7a-403e-9740-e8c3802d7631&tw_document_href=https%3A%2F%2Fwww.heygen.com%2Fpricing&tw_iframe_status=0&txn_id=of0u6&type=javascript&version=2.3.31)\n\nExplore HeyGen pricing with a free plan and paid options from $24/mo (billed yearly). Compare features, AI video tools, and API plans to find the best fit for you.",
      "error": null,
      "pricing_data": {
        "app_id": "heygen",
        "app_name": "HeyGen",
        "app_slug": "heygen",
        "pricing_url": "https://www.heygen.com/pricing",
        "source_url": "https://www.heygen.com/pricing",
        "all_pricing_urls": [
          "https://www.heygen.com/pricing",
          "https://www.heygen.com/api-pricing"
        ],
        "price_model_type": [
          "PriceModelType.SUBSCRIPTION",
          "PriceModelType.FREE_TIER",
          "PriceModelType.QUOTE_BASED"
        ],
        "has_free_tier": true,
        "has_free_trial": false,
        "free_trial_period_days": null,
        "currency": "USD",
        "is_pricing_public": true,
        "pricing_page_accessible": true,
        "pricing_notes": "Pricing includes a free tier and multiple subscription options with varying features.",
        "pricing_tiers": [
          {
            "tier_name": "Free",
            "tier_description": "Start creating on HeyGen at no cost",
            "monthly_price": 0.0,
            "annual_price": 0.0,
            "annual_discount_percentage": null,
            "setup_fee": null,
            "features": [
              "3 videos per month",
              "Videos up to 3-mins",
              "720p video export",
              "Standard video processing",
              "1 Custom Video Avatar",
              "500+ Stock Video Avatars",
              "30+ languages",
              "Share & download videos"
            ],
            "limits": {
              "users": 1,
              "storage": null,
              "operations": 3,
              "api_calls": null,
              "integrations": null,
              "custom_limits": [
                {
                  "name": "Max video duration",
                  "value": "3 minutes"
                }
              ]
            }
          },
          {
            "tier_name": "Creator",
            "tier_description": "Unlimited short-form videos for creators",
            "monthly_price": 29.0,
            "annual_price": null,
            "annual_discount_percentage": 22.0,
            "setup_fee": null,
            "features": [
              "Unlimited videos",
              "Videos up to 5-mins",
              "1080p video export",
              "Fast video processing",
              "1+ Custom Video Avatar",
              "1+ Custom Interactive Avatar",
              "700+ Stock Video Avatars",
              "Voice cloning",
              "175+ languages and dialects",
              "Generate Looks",
              "Look Packs",
              "Watermark removal",
              "Brand Kit"
            ],
            "limits": {
              "users": 1,
              "storage": null,
              "operations": "unlimited",
              "api_calls": null,
              "integrations": null,
              "custom_limits": [
                {
                  "name": "Max video duration",
                  "value": "5 minutes"
                }
              ]
            }
          },
          {
            "tier_name": "Team",
            "tier_description": "Supercharge video creation (minimum 2 seats)",
            "monthly_price": 39.0,
            "annual_price": null,
            "annual_discount_percentage": null,
            "setup_fee": null,
            "features": [
              "Unlimited videos",
              "Videos up to 30-mins",
              "1080p video export",
              "Faster video processing",
              "1 Custom Video Avatar/ seat",
              "1 Custom Interactive Avatar/ seat",
              "Unlimited Photo Avatars",
              "Translation Proofread",
              "Invites & team management",
              "Collaborative workspace",
              "Pay as you grow",
              "Scale your brand and centralize assets"
            ],
            "limits": {
              "users": "2+",
              "storage": null,
              "operations": "unlimited",
              "api_calls": null,
              "integrations": null,
              "custom_limits": [
                {
                  "name": "Max video duration",
                  "value": "30 minutes"
                }
              ]
            }
          },
          {
            "tier_name": "Enterprise",
            "tier_description": "Studio-quality custom video creation",
            "monthly_price": null,
            "annual_price": null,
            "annual_discount_percentage": null,
            "setup_fee": null,
            "features": [
              "Unlimited videos",
              "No video duration max",
              "4k video export",
              "Fastest video processing",
              "Centrally manage roles and access",
              "SAML/SSO",
              "Enterprise-grade security & privacy",
              "Commercial terms",
              "Priority customer support",
              "Dedicated customer success manager"
            ],
            "limits": {
              "users": "3+",
              "storage": null,
              "operations": "unlimited",
              "api_calls": null,
              "integrations": null,
              "custom_limits": [
                {
                  "name": "Max video duration",
                  "value": "No limit"
                }
              ]
            }
          }
        ],
        "usage_based_pricing": null,
        "ai_specific_pricing": null,
        "promotional_offers": null,
        "additional_fees": null,
        "extraction_timestamp": "2025-04-15T00:47:03.255223",
        "schema_validated": true,
        "confidence_score": 95,
        "extraction_error": false,
        "json_repaired": false
      },
      "pricing_analyzed": true
    }
  ],
  "results_directory": "pricing_results\\heygen\\20250415_004703"
}