{
  "app_name": "Kartra",
  "app_slug": "kartra",
  "search_term": "Find the official pricing page URL for Kartra (kartra.com). Only provide the exact URL to the pricing page, not a summary of pricing information.",
  "timestamp": 1744708476.8301704,
  "response_text": [
    "The official pricing page for Kartra can be found at: [https://www.kartra.com/plans](https://www.kartra.com/plans)\u30103:0\u2020source\u3011."
  ],
  "citations": [
    {
      "title": "Kartra Plans and Pricing",
      "url": "https://kartra.com/plans-and-pricing/"
    }
  ],
  "extracted_content": [
    {
      "url": "https://www.kartra.com/plans",
      "is_accessible": true,
      "content": "We value your privacy\n\nWe use cookies to enhance your browsing experience, serve personalized ads or content, and analyze our traffic. By clicking \"Accept All\", you consent to our use of cookies.\n\nCustomize\nReject All\nAccept All\nSkip to content\nOpen toolbar\n\nAccessibility Tools\n\nIncrease Text\nDecrease Text\nGrayscale\nHigh Contrast\nNegative Contrast\nLight Background\nLinks Underline\nReadable Font\n Reset\nSkip to content\nFeatures\n Plans and Pricing \nResources\nLogin\nGet Started\nSPRING SALE\nSave $552 on Kartra Growth\nComplimentary 1:1 onboarding call with any plan. 30-day money back guarantee.\nMonthly\nYearly\nSTARTER\nSave $180\n$89/mo $119/mo\nBilled monthly\nClaim Spring Sale \u2013 $89/mo\n0% transaction fees\nUnlimited email & SMS\n2,500 contacts\n1 custom domain\nWhat\u2019s included on Starter:\nUnlimited products\nUnlimited funnels\nUnlimited pages & forms\nUnlimited memberships & courses\nDrag-and-drop page builder\nFully integrated e-commerce\nCalendar booking\nKartra AI features\n100 pre-built campaigns\n$89/mo for the first 6 months, then $119/mo afterwards. New customers only. Terms apply.\nGROWTH\nBest Value | Save $552\n$137/mo $229/mo\nBilled monthly\nClaim Spring Sale \u2013 $137/mo\n0% transaction fees\nUnlimited email & SMS\n12,500 contacts\n3 custom domains\nEverything on Starter, plus:\nFunnel simulation\nWebinars \u2013 300 attendees\nAdvanced automations\nAffiliate management\nSurveys & quizzes\nHelpdesk\n$137/mo for the first 6 months, then $229/mo afterwards. New customers only. Terms apply.\nPROFESSIONAL\nAdvanced Tools\n$549/mo\nBilled monthly\nGet Professional Plan\n0% transaction fees\nUnlimited email & SMS\n25,000 contacts\n5 custom domains\nEverything on Growth, plus:\nReal-time funnel analytics\nWebinars \u2013 1,000 attendees\nHelpdesk live chat\nENTERPRISE\n$999/mo\nIncludes all Professional features, plus:\n250,000 contacts\n50 team members\n50 custom domains\nWebinars \u2013 5,000 attendees\nGet Started\nCompare features\nSTARTER\n$89/mo\nGet Starter\nGROWTH\n$137/mo\nGet Growth\nPROFESSIONAL\n$549/mo\nGet Professional\nCreation tools - Easily build Your course, web pages, emails & more!\nUnlimited products\t\n\t\n\t\n\nMemberships and courses\t\n\t\n\t\n\nFunnel mapping\t\n\t\n\t\n\nForms\t\n\t\n\t\n\nKartra AI\t\n\t\n\t\n\nSurveys & quizzes\t--\t\n\t\n\nWebinars\t--\t\n\t\n\nWebinar presenters\t--\t6\t6\nMarketing tools - Engage with your audience and leads and turn them into customers!\nFunnels and campaigns\t\n\t\n\t\n\nUnlimited email & SMS\t\n\t\n\t\n\nCheckouts\t\n\t\n\t\n\nLead capture\t\n\t\n\t\n\nLead & sales management\t\n\t\n\t\n\nCalendars\t\n\t\n\t\n\nFunnel simulations\t\n\t\n\t\n\nLanguages\t1\tUnlimited\tUnlimited\n\nScaling tools - Launch automated campaigns & funnels to accelerate your growth!\nAdvanced Analytics\t\n\t\n\t\n\nAutomated Sequences\t\n\t\n\t\n\nAffiliate management\t--\t\n\t\n\nHelpdesk support\t--\t\n\t\n\nHelpdesk live chat\t--\t--\t\n\nReal-time analytics\t--\t--\t\nAdvanced tools - Analyze your customers behavior, learn what drives them to purchase.\nTeam members\t5\t10\t20\nAgency capacity\t--\t\n\t\n\nAPI access\t--\t\n\t\n\nCustom code page\t--\t\n\t\n\nAdvanced automations\t--\t\n\t\nCreators use Kartra to do and earn more.\n60K\nKartra customers\n718K\nPages launched\n3.4M\nCourses sold\n$1.5B\nEarned by creators\nYou can make sales even when you're sleeping or when you're out for dinner with your BFFs.\nLouise Henry\nTech Expert & Online Business Strategist\nOnce I saw what Kartra could do, I realized that this is going to be something that can take me very far with my business.\nRyan Turner\nBusiness Consultant\n[Kartra helped me] to spread the word and reach as many tennis players and coaches as I possibly can through my online tennis courses and programs.\nCosmin Miholca\nTennis Coach\nYou can make sales even when you're sleeping or when you're out for dinner with your BFFs.\nLouise Henry\nTech Expert & Online Business Strategist\nOnce I saw what Kartra could do, I realized that this is going to be something that can take me very far with my business.\nRyan Turner\nBusiness Consultant\nOne platform to market and grow your online business.\nKartra Pages\n\nUtilize our drag-and-drop page builder with hundreds of ready-to-launch designed templates. 100% mobile optimized.\n\n\nKartra Leads\n\nBuild your leads, prospects, and customer database. Organize them in theme groups via lists and custom tags.\n\nKartra Funnels & Campaigns\n\nQuickly launch a multi-page funnel flow to convert visitors into leads, leads into customers, and customers into recurrent clients!\n\nKartra Webinars\n\nBoost your sales while interacting with your audience. Automate your webinar funnel and generate more leads.\n\n\nKartra Videos\n\nVideo marketers rejoice! Pop offers mid-way through your video, inject lead capture forms and much more.\n\nKartra Mail\n\nCreate live or automated email/SMS marketing campaigns to communicate and engage with your user base.\n\nKartra Checkouts\n\nSell products or services online through our secure and gorgeous checkout forms for both credit card and PayPal payments.\n\n\nKartra Memberships\n\nDeliver your content, course, or training material with our professionally designed, drag-and-drop membership portal builder.\n\nAnd so much more\u2026\n\nSurveys & Quizzes, Calendars & Appointments, Funnel Mapper, Affiliates, Agency, Marketplace, and Helpdesk\n\n\nGot questions?\nWe've got answers!\n\nWhat platforms and services does Kartra replace?\nHow secure is Kartra?\nCan I cancel or change plans anytime?\nDo I need coding skills?\nWhat languages are available in Kartra?\nWhat currencies are available in Kartra?\nIs there a support team that can help assist me if I have more questions?\nIs Kartra HIPAA compliant\nDoes Kartra have any extra fees?\nCan I pay for my subscription in my own currency?\nCan I pay with PayPal?\nWhat happens if I reach the limits of my plan?\n\u00a0I need more domains for my account. Is there an add-on I can buy?\n   \n\nGenesis Digital LLC\n4730 S. Fort Apache Rd. Suite 300\nLas Vegas, NV 89147-7947\n+1 (858) 869-9533\n\nProduct Support\nPlans and Pricing\nSupport Helpdesk\nKartra Status\nUser Login\nCompliance\nCookie Preferences\nTerms & Conditions\nDMCA\nGDPR\nPrivacy Policy\nAcceptable Use\nBilling Policy\nEULA\nDPA\nCompany\nAffiliate Program\nCompany\nLeadership\n\u00a9 Copyright, Genesis Digital LLC. All Rights Reserved.\n\nGrow your business with Kartra's all-in-one marketing platform.",
      "error": null,
      "pricing_data": {
        "app_id": "kartra",
        "app_name": "Kartra",
        "app_slug": "kartra",
        "pricing_url": "https://www.kartra.com/pricing",
        "source_url": null,
        "all_pricing_urls": [
          "https://www.kartra.com/pricing"
        ],
        "price_model_type": [
          "PriceModelType.SUBSCRIPTION"
        ],
        "has_free_tier": false,
        "has_free_trial": true,
        "free_trial_period_days": 30,
        "currency": "USD",
        "is_pricing_public": true,
        "pricing_page_accessible": true,
        "pricing_notes": "Promotional pricing is available for the first 6 months for new customers.",
        "pricing_tiers": [
          {
            "tier_name": "Starter",
            "tier_description": null,
            "monthly_price": 89.0,
            "annual_price": null,
            "annual_discount_percentage": null,
            "setup_fee": null,
            "features": [
              "Unlimited products",
              "Unlimited funnels",
              "Unlimited pages & forms",
              "Unlimited memberships & courses",
              "Drag-and-drop page builder",
              "Fully integrated e-commerce",
              "Calendar booking",
              "Kartra AI features",
              "100 pre-built campaigns"
            ],
            "limits": {
              "users": null,
              "storage": null,
              "operations": null,
              "api_calls": null,
              "integrations": null,
              "custom_limits": [
                {
                  "name": "Contacts",
                  "value": 2500
                },
                {
                  "name": "Custom Domains",
                  "value": 1
                }
              ]
            }
          },
          {
            "tier_name": "Growth",
            "tier_description": "Best Value",
            "monthly_price": 137.0,
            "annual_price": null,
            "annual_discount_percentage": null,
            "setup_fee": null,
            "features": [
              "Everything on Starter",
              "Funnel simulation",
              "Webinars \u2013 300 attendees",
              "Advanced automations",
              "Affiliate management",
              "Surveys & quizzes",
              "Helpdesk"
            ],
            "limits": {
              "users": null,
              "storage": null,
              "operations": null,
              "api_calls": null,
              "integrations": null,
              "custom_limits": [
                {
                  "name": "Contacts",
                  "value": 12500
                },
                {
                  "name": "Custom Domains",
                  "value": 3
                }
              ]
            }
          },
          {
            "tier_name": "Professional",
            "tier_description": "Advanced Tools",
            "monthly_price": 549.0,
            "annual_price": null,
            "annual_discount_percentage": null,
            "setup_fee": null,
            "features": [
              "Everything on Growth",
              "Real-time funnel analytics",
              "Webinars \u2013 1,000 attendees",
              "Helpdesk live chat"
            ],
            "limits": {
              "users": null,
              "storage": null,
              "operations": null,
              "api_calls": null,
              "integrations": null,
              "custom_limits": [
                {
                  "name": "Contacts",
                  "value": 25000
                },
                {
                  "name": "Custom Domains",
                  "value": 5
                }
              ]
            }
          },
          {
            "tier_name": "Enterprise",
            "tier_description": null,
            "monthly_price": 999.0,
            "annual_price": null,
            "annual_discount_percentage": null,
            "setup_fee": null,
            "features": [
              "Includes all Professional features",
              "250,000 contacts",
              "50 team members",
              "50 custom domains",
              "Webinars \u2013 5,000 attendees"
            ],
            "limits": {
              "users": 50,
              "storage": null,
              "operations": null,
              "api_calls": null,
              "integrations": null,
              "custom_limits": [
                {
                  "name": "Contacts",
                  "value": 250000
                },
                {
                  "name": "Custom Domains",
                  "value": 50
                }
              ]
            }
          }
        ],
        "usage_based_pricing": null,
        "ai_specific_pricing": null,
        "promotional_offers": [
          {
            "offer_name": "Spring Sale",
            "offer_description": "Save $552 on Kartra Growth. Complimentary 1:1 onboarding call with any plan.",
            "discount_percentage": null,
            "offer_url": null,
            "valid_until": null
          }
        ],
        "additional_fees": null,
        "extraction_timestamp": "2025-04-15T05:14:54.679791",
        "schema_validated": true,
        "confidence_score": 100,
        "extraction_error": false,
        "json_repaired": false
      },
      "pricing_analyzed": true
    },
    {
      "url": "https://kartra.com/plans-and-pricing/",
      "is_accessible": true,
      "content": "Skip to content\nOpen toolbar\n\nAccessibility Tools\n\nIncrease Text\nDecrease Text\nGrayscale\nHigh Contrast\nNegative Contrast\nLight Background\nLinks Underline\nReadable Font\n Reset\nSkip to content\nFeatures\n Plans and Pricing \nResources\nLogin\nGet Started\nSPRING SALE\nSave $552 on Kartra Growth\nComplimentary 1:1 onboarding call with any plan. 30-day money back guarantee.\nMonthly\nYearly\nSTARTER\nSave $180\n$89/mo $119/mo\nBilled monthly\nClaim Spring Sale \u2013 $89/mo\n0% transaction fees\nUnlimited email & SMS\n2,500 contacts\n1 custom domain\nWhat\u2019s included on Starter:\nUnlimited products\nUnlimited funnels\nUnlimited pages & forms\nUnlimited memberships & courses\nDrag-and-drop page builder\nFully integrated e-commerce\nCalendar booking\nKartra AI features\n100 pre-built campaigns\n$89/mo for the first 6 months, then $119/mo afterwards. New customers only. Terms apply.\nGROWTH\nBest Value | Save $552\n$137/mo $229/mo\nBilled monthly\nClaim Spring Sale \u2013 $137/mo\n0% transaction fees\nUnlimited email & SMS\n12,500 contacts\n3 custom domains\nEverything on Starter, plus:\nFunnel simulation\nWebinars \u2013 300 attendees\nAdvanced automations\nAffiliate management\nSurveys & quizzes\nHelpdesk\n$137/mo for the first 6 months, then $229/mo afterwards. New customers only. Terms apply.\nPROFESSIONAL\nAdvanced Tools\n$549/mo\nBilled monthly\nGet Professional Plan\n0% transaction fees\nUnlimited email & SMS\n25,000 contacts\n5 custom domains\nEverything on Growth, plus:\nReal-time funnel analytics\nWebinars \u2013 1,000 attendees\nHelpdesk live chat\nENTERPRISE\n$999/mo\nIncludes all Professional features, plus:\n250,000 contacts\n50 team members\n50 custom domains\nWebinars \u2013 5,000 attendees\nGet Started\nCompare features\nSTARTER\n$89/mo\nGet Starter\nGROWTH\n$137/mo\nGet Growth\nPROFESSIONAL\n$549/mo\nGet Professional\nCreation tools - Easily build Your course, web pages, emails & more!\nUnlimited products\t\n\t\n\t\n\nMemberships and courses\t\n\t\n\t\n\nFunnel mapping\t\n\t\n\t\n\nForms\t\n\t\n\t\n\nKartra AI\t\n\t\n\t\n\nSurveys & quizzes\t--\t\n\t\n\nWebinars\t--\t\n\t\n\nWebinar presenters\t--\t6\t6\nMarketing tools - Engage with your audience and leads and turn them into customers!\nFunnels and campaigns\t\n\t\n\t\n\nUnlimited email & SMS\t\n\t\n\t\n\nCheckouts\t\n\t\n\t\n\nLead capture\t\n\t\n\t\n\nLead & sales management\t\n\t\n\t\n\nCalendars\t\n\t\n\t\n\nFunnel simulations\t\n\t\n\t\n\nLanguages\t1\tUnlimited\tUnlimited\n\nScaling tools - Launch automated campaigns & funnels to accelerate your growth!\nAdvanced Analytics\t\n\t\n\t\n\nAutomated Sequences\t\n\t\n\t\n\nAffiliate management\t--\t\n\t\n\nHelpdesk support\t--\t\n\t\n\nHelpdesk live chat\t--\t--\t\n\nReal-time analytics\t--\t--\t\nAdvanced tools - Analyze your customers behavior, learn what drives them to purchase.\nTeam members\t5\t10\t20\nAgency capacity\t--\t\n\t\n\nAPI access\t--\t\n\t\n\nCustom code page\t--\t\n\t\n\nAdvanced automations\t--\t\n\t\nCreators use Kartra to do and earn more.\n60K\nKartra customers\n718K\nPages launched\n3.4M\nCourses sold\n$1.5B\nEarned by creators\nYou can make sales even when you're sleeping or when you're out for dinner with your BFFs.\nLouise Henry\nTech Expert & Online Business Strategist\nOnce I saw what Kartra could do, I realized that this is going to be something that can take me very far with my business.\nRyan Turner\nBusiness Consultant\n[Kartra helped me] to spread the word and reach as many tennis players and coaches as I possibly can through my online tennis courses and programs.\nCosmin Miholca\nTennis Coach\nYou can make sales even when you're sleeping or when you're out for dinner with your BFFs.\nLouise Henry\nTech Expert & Online Business Strategist\nOnce I saw what Kartra could do, I realized that this is going to be something that can take me very far with my business.\nRyan Turner\nBusiness Consultant\nOne platform to market and grow your online business.\nKartra Pages\n\nUtilize our drag-and-drop page builder with hundreds of ready-to-launch designed templates. 100% mobile optimized.\n\n\nKartra Leads\n\nBuild your leads, prospects, and customer database. Organize them in theme groups via lists and custom tags.\n\nKartra Funnels & Campaigns\n\nQuickly launch a multi-page funnel flow to convert visitors into leads, leads into customers, and customers into recurrent clients!\n\nKartra Webinars\n\nBoost your sales while interacting with your audience. Automate your webinar funnel and generate more leads.\n\n\nKartra Videos\n\nVideo marketers rejoice! Pop offers mid-way through your video, inject lead capture forms and much more.\n\nKartra Mail\n\nCreate live or automated email/SMS marketing campaigns to communicate and engage with your user base.\n\nKartra Checkouts\n\nSell products or services online through our secure and gorgeous checkout forms for both credit card and PayPal payments.\n\n\nKartra Memberships\n\nDeliver your content, course, or training material with our professionally designed, drag-and-drop membership portal builder.\n\nAnd so much more\u2026\n\nSurveys & Quizzes, Calendars & Appointments, Funnel Mapper, Affiliates, Agency, Marketplace, and Helpdesk\n\n\nGot questions?\nWe've got answers!\n\nWhat platforms and services does Kartra replace?\nHow secure is Kartra?\nCan I cancel or change plans anytime?\nDo I need coding skills?\nWhat languages are available in Kartra?\nWhat currencies are available in Kartra?\nIs there a support team that can help assist me if I have more questions?\nIs Kartra HIPAA compliant\nDoes Kartra have any extra fees?\nCan I pay for my subscription in my own currency?\nCan I pay with PayPal?\nWhat happens if I reach the limits of my plan?\n\u00a0I need more domains for my account. Is there an add-on I can buy?\n   \n\nGenesis Digital LLC\n4730 S. Fort Apache Rd. Suite 300\nLas Vegas, NV 89147-7947\n+1 (858) 869-9533\n\nProduct Support\nPlans and Pricing\nSupport Helpdesk\nKartra Status\nUser Login\nCompliance\nCookie Preferences\nTerms & Conditions\nDMCA\nGDPR\nPrivacy Policy\nAcceptable Use\nBilling Policy\nEULA\nDPA\nCompany\nAffiliate Program\nCompany\nLeadership\n\u00a9 Copyright, Genesis Digital LLC. All Rights Reserved.\n\nGrow your business with Kartra's all-in-one marketing platform.",
      "error": null,
      "pricing_data": {
        "app_id": "kartra",
        "app_name": "Kartra",
        "app_slug": "kartra",
        "pricing_url": "https://www.kartra.com/pricing",
        "source_url": null,
        "all_pricing_urls": [
          "https://www.kartra.com/pricing"
        ],
        "price_model_type": [
          "PriceModelType.SUBSCRIPTION"
        ],
        "has_free_tier": false,
        "has_free_trial": false,
        "free_trial_period_days": null,
        "currency": "USD",
        "is_pricing_public": true,
        "pricing_page_accessible": true,
        "pricing_notes": "Promotional pricing is available for the first 6 months for new customers.",
        "pricing_tiers": [
          {
            "tier_name": "Starter",
            "tier_description": "Basic plan for small businesses.",
            "monthly_price": 89.0,
            "annual_price": null,
            "annual_discount_percentage": null,
            "setup_fee": null,
            "features": [
              "Unlimited products",
              "Unlimited funnels",
              "Unlimited pages & forms",
              "Unlimited memberships & courses",
              "Drag-and-drop page builder",
              "Fully integrated e-commerce",
              "Calendar booking",
              "Kartra AI features",
              "100 pre-built campaigns"
            ],
            "limits": {
              "users": null,
              "storage": null,
              "operations": null,
              "api_calls": null,
              "integrations": null,
              "custom_limits": [
                {
                  "name": "Contacts",
                  "value": 2500
                },
                {
                  "name": "Custom Domains",
                  "value": 1
                }
              ]
            }
          },
          {
            "tier_name": "Growth",
            "tier_description": "Best value plan for growing businesses.",
            "monthly_price": 137.0,
            "annual_price": null,
            "annual_discount_percentage": null,
            "setup_fee": null,
            "features": [
              "Everything on Starter",
              "Funnel simulation",
              "Webinars \u2013 300 attendees",
              "Advanced automations",
              "Affiliate management",
              "Surveys & quizzes",
              "Helpdesk"
            ],
            "limits": {
              "users": null,
              "storage": null,
              "operations": null,
              "api_calls": null,
              "integrations": null,
              "custom_limits": [
                {
                  "name": "Contacts",
                  "value": 12500
                },
                {
                  "name": "Custom Domains",
                  "value": 3
                }
              ]
            }
          },
          {
            "tier_name": "Professional",
            "tier_description": "Advanced tools for professionals.",
            "monthly_price": 549.0,
            "annual_price": null,
            "annual_discount_percentage": null,
            "setup_fee": null,
            "features": [
              "Everything on Growth",
              "Real-time funnel analytics",
              "Webinars \u2013 1,000 attendees",
              "Helpdesk live chat"
            ],
            "limits": {
              "users": null,
              "storage": null,
              "operations": null,
              "api_calls": null,
              "integrations": null,
              "custom_limits": [
                {
                  "name": "Contacts",
                  "value": 25000
                },
                {
                  "name": "Custom Domains",
                  "value": 5
                }
              ]
            }
          },
          {
            "tier_name": "Enterprise",
            "tier_description": "Comprehensive plan for large enterprises.",
            "monthly_price": 999.0,
            "annual_price": null,
            "annual_discount_percentage": null,
            "setup_fee": null,
            "features": [
              "Everything on Professional",
              "Webinars \u2013 5,000 attendees"
            ],
            "limits": {
              "users": 50,
              "storage": null,
              "operations": null,
              "api_calls": null,
              "integrations": null,
              "custom_limits": [
                {
                  "name": "Contacts",
                  "value": 250000
                },
                {
                  "name": "Custom Domains",
                  "value": 50
                }
              ]
            }
          }
        ],
        "usage_based_pricing": null,
        "ai_specific_pricing": null,
        "promotional_offers": [
          {
            "offer_name": "Spring Sale",
            "offer_description": "Save $552 on Kartra Growth plan for the first 6 months.",
            "discount_percentage": null,
            "offer_url": null,
            "valid_until": null
          }
        ],
        "additional_fees": null,
        "extraction_timestamp": "2025-04-15T05:15:14.302459",
        "schema_validated": true,
        "confidence_score": 100,
        "extraction_error": false,
        "json_repaired": false
      },
      "pricing_analyzed": true
    }
  ],
  "results_directory": "pricing_results\\kartra\\20250415_051514"
}