{
  "app_name": "Chatbase",
  "app_slug": "chatbase",
  "search_term": "Find the official pricing page URL for Chatbase (chatbase.com). Only provide the exact URL to the pricing page, not a summary of pricing information.",
  "timestamp": 1744691306.2885673,
  "response_text": [
    "The official pricing page URL for Chatbase is: [https://www.chatbase.com/pricing](https://www.chatbase.com/pricing) ."
  ],
  "citations": [],
  "extracted_content": [
    {
      "url": "https://www.chatbase.com/pricing",
      "is_accessible": true,
      "content": "Predictable pricingscalable plans\n---------------------------------\n\nDesigned for every stage of your journey.\n\n### ![Image 1: Free plan icon](https://www.chatbase.com/_next/static/media/star-1.789b840b.svg)Free\n\n$0\n\nper month\n\n*   Access to fast models*   100 message credits/month\n*   400 KB per AI agent\n*   1 team member\n*   1 AI agent\n*   Limit of 10 links to train on\n*   Embed on unlimited websites\nAI agents get deleted after 14 days of inactivity on the free plan.\n\n### ![Image 2: Hobby plan icon](https://www.chatbase.com/_next/static/media/star-2.b9628ce6.svg)Hobby\n\n$40\n\nper month\n\nEverything in Free +*   Access to advanced models*   2,000 message credits/month\n*   1 AI agent\n*   5 AI Actions per AI agent\n*   33 MB per AI agent\n*   Unlimited links to train on\n*   API access\n*   Integrations*   Basic analytics\n\n### ![Image 3: Standard plan icon](https://www.chatbase.com/_next/static/media/star-3.e8fb0576.svg)Standard\n\nPopular\n\n$150\n\nper month\n\n[](https://www.chatbase.com/dashboard?next=/settings/plans)\n\nEverything in Hobby +*   12,000 message credits/month\n*   10 AI Actions per AI agent\n*   3 team members\n*   2 AI agents\n\nTrusted by 9000+ business worldwide\n\nAdd-ons\n\nFine-tune your plan with powerful add-ons\n-----------------------------------------\n\n### Auto recharge credits\n\nWhen your credits fall below the threshold you set, we'll automatically add credits that don't expire to your account, ensuring uninterrupted service.\n\n$14Total per 1000 message credits\n\n### Extra message credits\n\n$12 per 1000 credits / month\n\n$12Total per month\n\n### Extra agents\n\n$7 per AI agent / month\n\n$7Total per month\n\n### Custom domains\n\nUse your own custom domains for the AI agent's embed script, iframe, and shareable link.\n\n$59Total per month\n\n### Remove 'Powered By Chatbase'\n\nRemove the Chatbase branding from the iframe and widget\n\n$39Total per month\n\nCompare\n\nCompare all our plans\n---------------------\n\nFree\n\n$0\n\nper month\n\nHobby\n\n$40\n\nper month\n\nStandard\n\nPopular\n\n$150\n\nper month\n\n[](https://www.chatbase.com/dashboard?next=/settings/plans)\n\nPro\n\n$500\n\nper month\n\nConfigurationMessage credits (monthly)AgentsAI Actions per agentAgent size (characters)Team membersEmbed on unlimited websites\n\nTrainingLinks to train on\n\nActivityBasic analyticsAdvanced analytics\n\nIntegrations & APIAPI accessZapierSlackWordpressWhatsAppMessengerInstagram\n\nModelFast modelsAdvanced OpenAI modelsAdvanced Anthropic modelsAdvanced Gemini modelsAdvanced Cohere modelsAdvanced DeepSeek modelsAdvanced Meta models\n\n10010400 KB1\n\n10 Links\n\n20001533 MB1\n\nUnlimited links\n\n12,00021033 MB3\n\nUnlimited links\n\n40,00031533 MB\n\n5+\n\n/ extra member per month\n\nUnlimited links\n\n$0\n\n/ month\n\nConfiguration\n\nMessage credits (monthly)100\n\nAgents1\n\nAI Actions per agent0\n\nAgent size (characters)400 KB\n\nTeam members1\n\nEmbed on unlimited websites\n\nTraining\n\nLinks to train on10 Links\n\nActivity\n\nBasic analytics\n\nAdvanced analytics\n\nIntegrations & API\n\nAPI access\n\nZapier\n\nSlack\n\nWordpress\n\nWhatsApp\n\nMessenger\n\nInstagram\n\nModel\n\nFast models\n\nAdvanced OpenAI models\n\nAdvanced Anthropic models\n\nAdvanced Gemini models\n\nAdvanced Cohere models\n\nAdvanced DeepSeek models\n\nAdvanced Meta models\n\nFAQ\n\nGet answers to the most commonly asked questions\n------------------------------------------------\n\nTestimonials\n\nWhat people say\n---------------\n\nWith over 9000 clients served, here's what they have to say\n\n\"Chatbase is a strong signal of how customer support will evolve. It is an early adopter of the agentic approach, which will become increasingly effective, trusted, and prominent.\"\n\n![Image 4: Marc Manara](https://www.chatbase.com/_next/image?url=https%3A%2F%2Fbackend.chatbase.co%2Fstorage%2Fv1%2Fobject%2Fpublic%2Fchatbase%2Flanding%2Ftestimonials%2Fmarc-manara.webp&w=828&q=75&dpl=dpl_716rZ14Y2Gm1Kdvy97RWDkGkHvRx)\n\nMarc Manara\n\nOpenAI\n\n\"This is awesome, thanks for building it!\"\n\n![Image 5: Logan Kilpatrick](https://www.chatbase.com/_next/image?url=https%3A%2F%2Fbackend.chatbase.co%2Fstorage%2Fv1%2Fobject%2Fpublic%2Fchatbase%2Flanding%2Ftestimonials%2Flogan-kilpatrick.webp&w=828&q=75&dpl=dpl_716rZ14Y2Gm1Kdvy97RWDkGkHvRx)\n\nLogan Kilpatrick\n\nGoogle\n\n![Image 6: abstract image](https://www.chatbase.com/_next/image?url=%2F_next%2Fstatic%2Fmedia%2Fabstract-2.ce7e024b.png&w=640&q=75&dpl=dpl_716rZ14Y2Gm1Kdvy97RWDkGkHvRx)\n\n9000+\n\nbusinesses trust Chatbase\n\n![Image 7: abstract image](https://www.chatbase.com/_next/image?url=%2F_next%2Fstatic%2Fmedia%2Fabstract-1.9639a07f.png&w=640&q=75&dpl=dpl_716rZ14Y2Gm1Kdvy97RWDkGkHvRx)\n\n140+\n\ncountries served\n\n\"I want to express how impressed we are with the talent behind such an excellent product like Chatbase. we at Zain Cash truly appreciate and enjoy using your platform.\"\n\n![Image 8: Yazen Altimimi](https://www.chatbase.com/_next/image?url=https%3A%2F%2Fbackend.chatbase.co%2Fstorage%2Fv1%2Fobject%2Fpublic%2Fchatbase%2Flanding%2Ftestimonials%2Fyazen-altimimi.webp&w=828&q=75&dpl=dpl_716rZ14Y2Gm1Kdvy97RWDkGkHvRx)\n\nYazen Altimimi\n\nZain Cash\n\n\"Our chatbot has been great. Answers questions it knows, delegates to our talent when its stuck, knows how to push clients to the funnel. Chatbase is what we use, 10/10 recommend.\"\n\n![Image 9: Martin Terskin](https://www.chatbase.com/_next/image?url=https%3A%2F%2Fbackend.chatbase.co%2Fstorage%2Fv1%2Fobject%2Fpublic%2Fchatbase%2Flanding%2Ftestimonials%2Fmartin-terskin.webp&w=828&q=75&dpl=dpl_716rZ14Y2Gm1Kdvy97RWDkGkHvRx)\n\nMartin Terskin\n\nOfferMarket\n\n\"Chatbase is a strong signal of how customer support will evolve. It is an early adopter of the agentic approach, which will become increasingly effective, trusted, and prominent.\"\n\n![Image 10: Marc Manara](https://www.chatbase.com/_next/image?url=https%3A%2F%2Fbackend.chatbase.co%2Fstorage%2Fv1%2Fobject%2Fpublic%2Fchatbase%2Flanding%2Ftestimonials%2Fmarc-manara.webp&w=828&q=75&dpl=dpl_716rZ14Y2Gm1Kdvy97RWDkGkHvRx)\n\nMarc Manara\n\nOpenAI\n\n\"This is awesome, thanks for building it!\"\n\n![Image 11: Logan Kilpatrick](https://www.chatbase.com/_next/image?url=https%3A%2F%2Fbackend.chatbase.co%2Fstorage%2Fv1%2Fobject%2Fpublic%2Fchatbase%2Flanding%2Ftestimonials%2Flogan-kilpatrick.webp&w=828&q=75&dpl=dpl_716rZ14Y2Gm1Kdvy97RWDkGkHvRx)\n\nLogan Kilpatrick\n\nGoogle\n\n![Image 12: abstract image](https://www.chatbase.com/_next/image?url=%2F_next%2Fstatic%2Fmedia%2Fabstract-2.ce7e024b.png&w=640&q=75&dpl=dpl_716rZ14Y2Gm1Kdvy97RWDkGkHvRx)\n\n9000+\n\nbusinesses trust Chatbase\n\n![Image 13: abstract image](https://www.chatbase.com/_next/image?url=%2F_next%2Fstatic%2Fmedia%2Fabstract-1.9639a07f.png&w=640&q=75&dpl=dpl_716rZ14Y2Gm1Kdvy97RWDkGkHvRx)\n\n140+\n\ncountries served\n\n\"I want to express how impressed we are with the talent behind such an excellent product like Chatbase. we at Zain Cash truly appreciate and enjoy using your platform.\"\n\n![Image 14: Yazen Altimimi](https://www.chatbase.com/_next/image?url=https%3A%2F%2Fbackend.chatbase.co%2Fstorage%2Fv1%2Fobject%2Fpublic%2Fchatbase%2Flanding%2Ftestimonials%2Fyazen-altimimi.webp&w=828&q=75&dpl=dpl_716rZ14Y2Gm1Kdvy97RWDkGkHvRx)\n\nYazen Altimimi\n\nZain Cash\n\n\"Our chatbot has been great. Answers questions it knows, delegates to our talent when its stuck, knows how to push clients to the funnel. Chatbase is what we use, 10/10 recommend.\"\n\n![Image 15: Martin Terskin](https://www.chatbase.com/_next/image?url=https%3A%2F%2Fbackend.chatbase.co%2Fstorage%2Fv1%2Fobject%2Fpublic%2Fchatbase%2Flanding%2Ftestimonials%2Fmartin-terskin.webp&w=828&q=75&dpl=dpl_716rZ14Y2Gm1Kdvy97RWDkGkHvRx)\n\nMartin Terskin\n\nOfferMarket\n\n\"Chatbase is a strong signal of how customer support will evolve. It is an early adopter of the agentic approach, which will become increasingly effective, trusted, and prominent.\"\n\n![Image 16: Marc Manara](https://www.chatbase.com/_next/image?url=https%3A%2F%2Fbackend.chatbase.co%2Fstorage%2Fv1%2Fobject%2Fpublic%2Fchatbase%2Flanding%2Ftestimonials%2Fmarc-manara.webp&w=828&q=75&dpl=dpl_716rZ14Y2Gm1Kdvy97RWDkGkHvRx)\n\nMarc Manara\n\nOpenAI\n\n\"This is awesome, thanks for building it!\"\n\n![Image 17: Logan Kilpatrick](https://www.chatbase.com/_next/image?url=https%3A%2F%2Fbackend.chatbase.co%2Fstorage%2Fv1%2Fobject%2Fpublic%2Fchatbase%2Flanding%2Ftestimonials%2Flogan-kilpatrick.webp&w=828&q=75&dpl=dpl_716rZ14Y2Gm1Kdvy97RWDkGkHvRx)\n\nLogan Kilpatrick\n\nGoogle\n\n![Image 18: abstract image](https://www.chatbase.com/_next/image?url=%2F_next%2Fstatic%2Fmedia%2Fabstract-2.ce7e024b.png&w=640&q=75&dpl=dpl_716rZ14Y2Gm1Kdvy97RWDkGkHvRx)\n\n9000+\n\nbusinesses trust Chatbase\n\n![Image 19: abstract image](https://www.chatbase.com/_next/image?url=%2F_next%2Fstatic%2Fmedia%2Fabstract-1.9639a07f.png&w=640&q=75&dpl=dpl_716rZ14Y2Gm1Kdvy97RWDkGkHvRx)\n\n140+\n\ncountries served\n\n\"I want to express how impressed we are with the talent behind such an excellent product like Chatbase. we at Zain Cash truly appreciate and enjoy using your platform.\"\n\n![Image 20: Yazen Altimimi](https://www.chatbase.com/_next/image?url=https%3A%2F%2Fbackend.chatbase.co%2Fstorage%2Fv1%2Fobject%2Fpublic%2Fchatbase%2Flanding%2Ftestimonials%2Fyazen-altimimi.webp&w=828&q=75&dpl=dpl_716rZ14Y2Gm1Kdvy97RWDkGkHvRx)\n\nYazen Altimimi\n\nZain Cash\n\n\"Our chatbot has been great. Answers questions it knows, delegates to our talent when its stuck, knows how to push clients to the funnel. Chatbase is what we use, 10/10 recommend.\"\n\n![Image 21: Martin Terskin](https://www.chatbase.com/_next/image?url=https%3A%2F%2Fbackend.chatbase.co%2Fstorage%2Fv1%2Fobject%2Fpublic%2Fchatbase%2Flanding%2Ftestimonials%2Fmartin-terskin.webp&w=828&q=75&dpl=dpl_716rZ14Y2Gm1Kdvy97RWDkGkHvRx)\n\nMartin Terskin\n\nOfferMarket\n\nMake customer experience your competitive edge\n\nUse Chatbase to deliver exceptional support experiences that set you apart from the competition.\n\n[](https://www.chatbase.com/dashboard?next=create-new-chatbot)\n\nNo credit card required\n\n![Image 22: cta](https://www.chatbase.com/_next/image?url=https%3A%2F%2Fbackend.chatbase.co%2Fstorage%2Fv1%2Fobject%2Fpublic%2Fchatbase%2Flanding%2Fcta%2Fcta.png&w=3840&q=75&dpl=dpl_716rZ14Y2Gm1Kdvy97RWDkGkHvRx)\n\nInstantly assist customers with an AI-chatbot for quick, accurate answers. Build your chatbot today!",
      "error": null,
      "pricing_data": {
        "app_id": "chatbase",
        "app_name": "Chatbase",
        "app_slug": "chatbase",
        "pricing_url": "https://www.chatbase.com/pricing",
        "source_url": "https://www.chatbase.com/pricing",
        "all_pricing_urls": [
          "https://www.chatbase.com/pricing"
        ],
        "price_model_type": [
          "PriceModelType.SUBSCRIPTION",
          "PriceModelType.USAGE_BASED",
          "PriceModelType.FREE_TIER"
        ],
        "has_free_tier": true,
        "has_free_trial": false,
        "free_trial_period_days": null,
        "currency": "USD",
        "is_pricing_public": true,
        "pricing_page_accessible": true,
        "pricing_notes": "Add-ons are available for customization of plans.",
        "pricing_tiers": [
          {
            "tier_name": "Free",
            "tier_description": null,
            "monthly_price": 0.0,
            "annual_price": null,
            "annual_discount_percentage": null,
            "setup_fee": null,
            "features": [
              "Access to fast models",
              "100 message credits/month",
              "400 KB per AI agent",
              "1 team member",
              "1 AI agent",
              "Limit of 10 links to train on",
              "Embed on unlimited websites"
            ],
            "limits": {
              "users": 1,
              "storage": "400 KB",
              "operations": null,
              "api_calls": null,
              "integrations": null,
              "custom_limits": [
                {
                  "name": "message credits",
                  "value": 100
                },
                {
                  "name": "AI agents",
                  "value": 1
                },
                {
                  "name": "links to train on",
                  "value": 10
                }
              ]
            }
          },
          {
            "tier_name": "Hobby",
            "tier_description": null,
            "monthly_price": 40.0,
            "annual_price": null,
            "annual_discount_percentage": null,
            "setup_fee": null,
            "features": [
              "Access to advanced models",
              "2,000 message credits/month",
              "1 AI agent",
              "5 AI Actions per AI agent",
              "33 MB per AI agent",
              "Unlimited links to train on",
              "API access",
              "Integrations",
              "Basic analytics"
            ],
            "limits": {
              "users": 1,
              "storage": "33 MB",
              "operations": null,
              "api_calls": null,
              "integrations": "unlimited",
              "custom_limits": [
                {
                  "name": "message credits",
                  "value": 2000
                },
                {
                  "name": "AI agents",
                  "value": 1
                },
                {
                  "name": "AI Actions per AI agent",
                  "value": 5
                }
              ]
            }
          },
          {
            "tier_name": "Standard",
            "tier_description": "Popular",
            "monthly_price": 150.0,
            "annual_price": null,
            "annual_discount_percentage": null,
            "setup_fee": null,
            "features": [
              "12,000 message credits/month",
              "10 AI Actions per AI agent",
              "3 team members",
              "2 AI agents"
            ],
            "limits": {
              "users": 3,
              "storage": "33 MB",
              "operations": null,
              "api_calls": null,
              "integrations": "unlimited",
              "custom_limits": [
                {
                  "name": "message credits",
                  "value": 12000
                },
                {
                  "name": "AI agents",
                  "value": 2
                },
                {
                  "name": "AI Actions per AI agent",
                  "value": 10
                }
              ]
            }
          },
          {
            "tier_name": "Pro",
            "tier_description": null,
            "monthly_price": 500.0,
            "annual_price": null,
            "annual_discount_percentage": null,
            "setup_fee": null,
            "features": [
              "40,000 message credits/month",
              "Advanced analytics",
              "5+ team members",
              "Unlimited links to train on"
            ],
            "limits": {
              "users": "5+",
              "storage": "33 MB",
              "operations": null,
              "api_calls": null,
              "integrations": "unlimited",
              "custom_limits": [
                {
                  "name": "message credits",
                  "value": 40000
                },
                {
                  "name": "AI agents",
                  "value": "unlimited"
                }
              ]
            }
          }
        ],
        "usage_based_pricing": [
          {
            "metric_name": "message credits",
            "unit": "per 1000 credits",
            "base_price": 12.0,
            "tiers": null
          },
          {
            "metric_name": "extra agents",
            "unit": "per AI agent",
            "base_price": 7.0,
            "tiers": null
          }
        ],
        "ai_specific_pricing": {
          "has_token_based_pricing": false,
          "input_token_price": null,
          "output_token_price": null,
          "models_pricing": null,
          "has_inference_pricing": false,
          "has_fine_tuning_pricing": true,
          "has_training_pricing": false,
          "ai_addon_available": true
        },
        "promotional_offers": null,
        "additional_fees": [
          {
            "fee_name": "Custom domains",
            "fee_amount": 59.0,
            "fee_description": "Use your own custom domains for the AI agent's embed script, iframe, and shareable link."
          },
          {
            "fee_name": "Remove 'Powered By Chatbase'",
            "fee_amount": 39.0,
            "fee_description": "Remove the Chatbase branding from the iframe and widget."
          }
        ],
        "extraction_timestamp": "2025-04-15T00:28:36.321613",
        "schema_validated": true,
        "confidence_score": 100,
        "extraction_error": false,
        "json_repaired": false
      },
      "pricing_analyzed": true
    }
  ],
  "results_directory": "pricing_results\\chatbase\\20250415_002836"
}