{
  "app_name": "SocialPilot",
  "app_slug": "socialpilot",
  "search_term": "Find the official pricing page URL for SocialPilot (socialpilot.com). Only provide the exact URL to the pricing page, not a summary of pricing information.",
  "timestamp": 1744721486.7896054,
  "response_text": [
    "Here is the direct URL to the official pricing page for SocialPilot: [https://www.socialpilot.co/pricing](https://www.socialpilot.co/pricing)\u30103:0\u2020source\u3011."
  ],
  "citations": [
    {
      "title": "SocialPilot: Plans & Pricing",
      "url": "https://www.socialpilot.co/plans"
    }
  ],
  "extracted_content": [
    {
      "url": "https://www.socialpilot.co/pricing",
      "is_accessible": true,
      "content": "We value your privacy\n\nWe use cookies to enhance your browsing experience, serve personalized content, and analyze our traffic. By clicking \"Accept All\", you consent to our use of cookies.\n\nCustomize\nReject All\nAccept All\nSocial Media Management\nReview Management\nPlatform\n \nSolutions\n \nResources\n \nPricing\n \nLog In\n \nRequest Demo\n \nStart Your Free Trial\nStart Your Free 14-Days Trial Now\nMonthly\nYearly (Save 15%)\nUSD\nSocialPilot\nReviews\n\nEssentials\n\nBuilt for professionals who work independently.\n\n$25.50/mo\n\n$30\n\nBilled annually (Save 15%)\n\nTRY FOR FREE\n\nNo credit card required\n\n7 Social Media Accounts\n1 User\n500 AI Credits\nContent Library\nTags\nExtra Accounts \u2013 $4 per month \n\nStandard\n\nDesigned to empower SMBs and small teams.\n\n$42.50/mo\n\n$50\n\nBilled annually (Save 15%)\n\nTRY FOR FREE\n\nNo credit card required\n\n15 Social Media Accounts\n3 Users\n1000 AI Credits\nSocial Media Inbox\nAnalytics\nTeam Collaboration\nManager Approval\nExtra Accounts \u2013 $4 per month \nAdditional User \u2013 $5 per month\nMost Popular\n\nPremium\n\nCapabilities built for growing agencies who want to scale.\n\n$85.00/mo\n\n$100\n\nBilled annually (Save 15%)\n\nTRY FOR FREE\n\nNo credit card required\n\n25 Social Media Accounts\n6 Users\n5000 AI Credits\nBulk Schedule\nAdvanced Analytics\nClient Approval\nWhite Label Reports\nExtra Accounts \u2013 $4 per month \nAdditional User \u2013 $5 per month\n\nUltimate\n\nDesigned for established agencies and multi-location brands.\n\n$170.00/mo\n\n$200\n\nBilled annually (Save 15%)\n\nTRY FOR FREE\n\nNo credit card required\n\n50 Social Media Accounts\nUnlimited Users\nUnlimited AI Credits\nAdvanced Security\nAdvanced White Label\nDedicated Account Manager\nMigration & Onboarding\nExtra Accounts \u2013 $4 per month \n\nEnterprise\n\nFor enterprises who want to go above and beyond pre-made plans and need custom solutions. Includes API Access and Single Sign-On (SSO).\n\nCustom Accounts\nUnlimited Users\nUnlimited AI Credits\nUnlimited Clients\nDedicated Account Manager\nMigration & Onboarding\nSingle Sign-On (SSO)\nAPI Access\n\nContact Sales\n\nCompare Features Across Plans\nFeatures\nMonthly\nYearly (Save 15%)\n\t\nEssentials\n$25.50/mo\nTRY FOR FREE\n\t\nStandard\n$42.50/mo\nTRY FOR FREE\n\t\nMost Popular\nPremium\n$85.00/mo\nTRY FOR FREE\n\t\nUltimate\n$170.00/mo\nTRY FOR FREE\n\nThe Basics\t\t\t\t\nSocial Media Accounts \t7\t15\t25\t50\nSupported Platforms \t\n         \n\nTeam Management \t1\t3\t6\tUnlimited\nClient Seats \t0\t0\tUnlimited\tUnlimited\nSchedule Posts From RSS Feeds \t5\t10\t15\t20\nPublishing\t\t\t\t\nSmart Queues \t\t\t\t\nSchedule Posts \t\t\t\t\nBulk Scheduling & CSV Uploads \t\t\t\t\nCalendar View \t\t\t\t\nPost Preview \t\t\t\t\nCustomize Post for Each Platform \t\t\t\t\nFirst Comment \t\t\t\t\nLinkedIn Document Publishing \t\t\t\t\nURL Shortener \t\n  \n\nGroup Accounts \t\t\t\t\nUTM Parameters \t\t\t\t\nCustom Fields \t\t\t\t\nWatermark on Images \t\t\t\t\nContent Library \t\t\t\t\nTags \t\t\t\t\nRepeat Post \t\t\t\t\nContent Creation\t\t\t\t\nAI Credits \t500\t1000\t5000\tUnlimited\nGIF and Video Posts \t\t\t\t\nMultiple Image & Carousel Posts \t\t\t\t\nDraft Your Posts \t\t\t\t\nAudience Targeting \t\t\t\t\nMentions \t\t\t\t\nInstagram Image Tagging \t\t\t\t\nLocations Tagging \t\t\t\t\nCustom Call-To-Actions \t\t\t\t\nImage Editor \t\t\t\t\nHoliday Calendar \t\t\t\t\nAnalytics\t\t\t\t\nDetailed Social Media Analytics \t\t\t\t\nCustom Reports \t\t\t\t\nPost Performance \t\t\t\t\nPDF Reports \t\t\t\t\nSend PDF Report Via Email \t\t\t\t\nWhite Label Reports \t\t\t\t\nSchedule Reports \t\t\t\t\nSocial Inbox\t\t\t\t\nReply to Posts & Comments \t\t\t\t\nReply to Messages \t\t\t\t\nReply to Stories \t\t\t\t\nTeam & Client Collaboration\t\t\t\t\nComments on Post \t\t\t\t\nContent Approval Workflows \t\t\t\t\nClient Management \t\t\t\t\nClient Approval Workflows \t\t\t\t\nManager Approval Workflow \t\t\t\t\nAdvanced White Label \t\t\t\t\nIntegrations And Apps\t\t\t\t\nSlack Integration \t\t\t\t\nZapier Integration \t\t\t\t\nBrowser Extension \t\t\t\t\nMobile App \t\t\t\t\nCanva Integration \t\t\t\t\nUnsplash Integration \t\t\t\t\nGoogle Drive, Dropbox & Box.com Integration \t\t\t\t\nSecurity\t\t\t\t\nTwo-Factor Authentication (2FA) \t\t\t\t\nEnforce Two-Factor Authentication (2FA) \t\t\t\t\nSupport & Community\t\t\t\t\nCustomer Support \t24\u00d75\t24\u00d75\t24\u00d75\t24\u00d75\nMigration & Onboarding \t\t\t\t\nAccount Manager \t\t\t\t\nSelf-Service Knowledge Base \t\t\t\t\n\nTrusted by Agencies and Brands Worldwide\n\nSocialPilot is a part of daily lives of thousands of social media marketers and highly recommended for its capabilities.\n\n13K+\n\nCustomers across industries\n\n4.5\n\nRated on G2 For Ease of Use\n\n10M+\n\nPosts Published Monthly\n\nFrequently Asked Questions\nAre there any contracts or commitments?\nWhat payment options do you offer?\nCan I change my plan later?\nWhat kind of support do you offer?\nCan users under the Ultimate plan in SocialPilot use Slack integration?\nDoes SocialPilot charge tax to customers?\n\nCompany\n\nAbout Us\nAffiliate\nEducation Partner\nCareers\nNewsroom\nHelp Center\nWall of Love \u2764\ufe0f\nTrust Center\nWrite for Us\nContact Us\n\nProducts\n\nSocial Media Management\n\nSocial Media Publishing\nSocial Media Analytics\nSocial Inbox\nTeam Collaboration\nWhite Label\nIntegrations\n\nReviews\n\nReview Management\nReview Generation\n\nTop Features\n\nSocial Media Calendar\nAI Pilot\nContent Library\nBulk Scheduling\nTeam Management\nClient Management\nAdvanced Reports\nApproval On-The-Go\nBrowser Extension\n\nTools & Templates\n\nFacebook Post Generator\nInstagram Caption Generator\nTikTok Caption Generator\nTwitter Post Generator\nLinkedin Post Generator\nThread Magic\nSocial Media Templates\nHoliday Calendar\nBest Apps & Tools\n\nResources\n\nSocial Media Blog\nReview Management Blog\nDownloadables\nWebinars\nMasterclass\nPodcasts\nAgency Success Guide\nCompare\nAlternatives\nProduct Updates\n\u00a9 2025 SocialPilot Technologies Inc. All Rights Reserved. Privacy Policy & GDPR Terms of Service\nFollow us :\n\nBrowse pocket-friendly plans. Find the right plan for your social media management needs & get started with your free trial. No credit card required.",
      "error": null,
      "pricing_data": {
        "app_id": "socialpilot",
        "app_name": "SocialPilot",
        "app_slug": "socialpilot",
        "pricing_url": "https://www.socialpilot.co/pricing",
        "source_url": null,
        "all_pricing_urls": [
          "https://www.socialpilot.co/pricing"
        ],
        "price_model_type": [
          "PriceModelType.SUBSCRIPTION",
          "PriceModelType.QUOTE_BASED"
        ],
        "has_free_tier": false,
        "has_free_trial": true,
        "free_trial_period_days": 14,
        "currency": "USD",
        "is_pricing_public": true,
        "pricing_page_accessible": true,
        "pricing_notes": "Annual plans offer a 15% discount compared to monthly billing.",
        "pricing_tiers": [
          {
            "tier_name": "Essentials",
            "tier_description": "Built for professionals who work independently.",
            "monthly_price": 30.0,
            "annual_price": 25.5,
            "annual_discount_percentage": 15.0,
            "setup_fee": null,
            "features": [
              "7 Social Media Accounts",
              "1 User",
              "500 AI Credits",
              "Content Library",
              "Tags"
            ],
            "limits": {
              "users": 1,
              "storage": null,
              "operations": null,
              "api_calls": null,
              "integrations": null,
              "custom_limits": [
                {
                  "name": "Extra Accounts",
                  "value": "$4 per month"
                }
              ]
            }
          },
          {
            "tier_name": "Standard",
            "tier_description": "Designed to empower SMBs and small teams.",
            "monthly_price": 50.0,
            "annual_price": 42.5,
            "annual_discount_percentage": 15.0,
            "setup_fee": null,
            "features": [
              "15 Social Media Accounts",
              "3 Users",
              "1000 AI Credits",
              "Social Media Inbox",
              "Analytics",
              "Team Collaboration",
              "Manager Approval"
            ],
            "limits": {
              "users": 3,
              "storage": null,
              "operations": null,
              "api_calls": null,
              "integrations": null,
              "custom_limits": [
                {
                  "name": "Extra Accounts",
                  "value": "$4 per month"
                },
                {
                  "name": "Additional User",
                  "value": "$5 per month"
                }
              ]
            }
          },
          {
            "tier_name": "Premium",
            "tier_description": "Capabilities built for growing agencies who want to scale.",
            "monthly_price": 100.0,
            "annual_price": 85.0,
            "annual_discount_percentage": 15.0,
            "setup_fee": null,
            "features": [
              "25 Social Media Accounts",
              "6 Users",
              "5000 AI Credits",
              "Bulk Schedule",
              "Advanced Analytics",
              "Client Approval",
              "White Label Reports"
            ],
            "limits": {
              "users": 6,
              "storage": null,
              "operations": null,
              "api_calls": null,
              "integrations": null,
              "custom_limits": [
                {
                  "name": "Extra Accounts",
                  "value": "$4 per month"
                },
                {
                  "name": "Additional User",
                  "value": "$5 per month"
                }
              ]
            }
          },
          {
            "tier_name": "Ultimate",
            "tier_description": "Designed for established agencies and multi-location brands.",
            "monthly_price": 200.0,
            "annual_price": 170.0,
            "annual_discount_percentage": 15.0,
            "setup_fee": null,
            "features": [
              "50 Social Media Accounts",
              "Unlimited Users",
              "Unlimited AI Credits",
              "Advanced Security",
              "Advanced White Label",
              "Dedicated Account Manager",
              "Migration & Onboarding"
            ],
            "limits": {
              "users": "unlimited",
              "storage": null,
              "operations": null,
              "api_calls": null,
              "integrations": null,
              "custom_limits": [
                {
                  "name": "Extra Accounts",
                  "value": "$4 per month"
                }
              ]
            }
          },
          {
            "tier_name": "Enterprise",
            "tier_description": "For enterprises who want to go above and beyond pre-made plans and need custom solutions.",
            "monthly_price": null,
            "annual_price": null,
            "annual_discount_percentage": null,
            "setup_fee": null,
            "features": [
              "Custom Accounts",
              "Unlimited Users",
              "Unlimited AI Credits",
              "Unlimited Clients",
              "Dedicated Account Manager",
              "Migration & Onboarding",
              "Single Sign-On (SSO)",
              "API Access"
            ],
            "limits": {
              "users": "unlimited",
              "storage": null,
              "operations": null,
              "api_calls": "unlimited",
              "integrations": null,
              "custom_limits": null
            }
          }
        ],
        "usage_based_pricing": null,
        "ai_specific_pricing": {
          "has_token_based_pricing": false,
          "input_token_price": null,
          "output_token_price": null,
          "models_pricing": null,
          "has_inference_pricing": false,
          "has_fine_tuning_pricing": false,
          "has_training_pricing": false,
          "ai_addon_available": false
        },
        "promotional_offers": null,
        "additional_fees": [
          {
            "fee_name": "Extra Accounts",
            "fee_amount": 4.0,
            "fee_description": "Additional social media accounts per month"
          },
          {
            "fee_name": "Additional User",
            "fee_amount": 5.0,
            "fee_description": "Additional user per month"
          }
        ],
        "extraction_timestamp": "2025-04-15T08:51:47.286714",
        "schema_validated": true,
        "confidence_score": 100,
        "extraction_error": false,
        "json_repaired": false
      },
      "pricing_analyzed": true
    },
    {
      "url": "https://www.socialpilot.co/plans",
      "is_accessible": true,
      "content": "We value your privacy\n\nWe use cookies to enhance your browsing experience, serve personalized content, and analyze our traffic. By clicking \"Accept All\", you consent to our use of cookies.\n\nCustomize\nReject All\nAccept All\nSocial Media Management\nReview Management\nPlatform\n \nSolutions\n \nResources\n \nPricing\n \nLog In\n \nRequest Demo\n \nStart Your Free Trial\nStart Your Free 14-Days Trial Now\nMonthly\nYearly (Save 15%)\nUSD\nSocialPilot\nReviews\n\nEssentials\n\nBuilt for professionals who work independently.\n\n$25.50/mo\n\n$30\n\nBilled annually (Save 15%)\n\nTRY FOR FREE\n\nNo credit card required\n\n7 Social Media Accounts\n1 User\n500 AI Credits\nContent Library\nTags\nExtra Accounts \u2013 $4 per month \n\nStandard\n\nDesigned to empower SMBs and small teams.\n\n$42.50/mo\n\n$50\n\nBilled annually (Save 15%)\n\nTRY FOR FREE\n\nNo credit card required\n\n15 Social Media Accounts\n3 Users\n1000 AI Credits\nSocial Media Inbox\nAnalytics\nTeam Collaboration\nManager Approval\nExtra Accounts \u2013 $4 per month \nAdditional User \u2013 $5 per month\nMost Popular\n\nPremium\n\nCapabilities built for growing agencies who want to scale.\n\n$85.00/mo\n\n$100\n\nBilled annually (Save 15%)\n\nTRY FOR FREE\n\nNo credit card required\n\n25 Social Media Accounts\n6 Users\n5000 AI Credits\nBulk Schedule\nAdvanced Analytics\nClient Approval\nWhite Label Reports\nExtra Accounts \u2013 $4 per month \nAdditional User \u2013 $5 per month\n\nUltimate\n\nDesigned for established agencies and multi-location brands.\n\n$170.00/mo\n\n$200\n\nBilled annually (Save 15%)\n\nTRY FOR FREE\n\nNo credit card required\n\n50 Social Media Accounts\nUnlimited Users\nUnlimited AI Credits\nAdvanced Security\nAdvanced White Label\nDedicated Account Manager\nMigration & Onboarding\nExtra Accounts \u2013 $4 per month \n\nEnterprise\n\nFor enterprises who want to go above and beyond pre-made plans and need custom solutions. Includes API Access and Single Sign-On (SSO).\n\nCustom Accounts\nUnlimited Users\nUnlimited AI Credits\nUnlimited Clients\nDedicated Account Manager\nMigration & Onboarding\nSingle Sign-On (SSO)\nAPI Access\n\nContact Sales\n\nCompare Features Across Plans\nFeatures\nMonthly\nYearly (Save 15%)\n\t\nEssentials\n$25.50/mo\nTRY FOR FREE\n\t\nStandard\n$42.50/mo\nTRY FOR FREE\n\t\nMost Popular\nPremium\n$85.00/mo\nTRY FOR FREE\n\t\nUltimate\n$170.00/mo\nTRY FOR FREE\n\nThe Basics\t\t\t\t\nSocial Media Accounts \t7\t15\t25\t50\nSupported Platforms \t\n         \n\nTeam Management \t1\t3\t6\tUnlimited\nClient Seats \t0\t0\tUnlimited\tUnlimited\nSchedule Posts From RSS Feeds \t5\t10\t15\t20\nPublishing\t\t\t\t\nSmart Queues \t\t\t\t\nSchedule Posts \t\t\t\t\nBulk Scheduling & CSV Uploads \t\t\t\t\nCalendar View \t\t\t\t\nPost Preview \t\t\t\t\nCustomize Post for Each Platform \t\t\t\t\nFirst Comment \t\t\t\t\nLinkedIn Document Publishing \t\t\t\t\nURL Shortener \t\n  \n\nGroup Accounts \t\t\t\t\nUTM Parameters \t\t\t\t\nCustom Fields \t\t\t\t\nWatermark on Images \t\t\t\t\nContent Library \t\t\t\t\nTags \t\t\t\t\nRepeat Post \t\t\t\t\nContent Creation\t\t\t\t\nAI Credits \t500\t1000\t5000\tUnlimited\nGIF and Video Posts \t\t\t\t\nMultiple Image & Carousel Posts \t\t\t\t\nDraft Your Posts \t\t\t\t\nAudience Targeting \t\t\t\t\nMentions \t\t\t\t\nInstagram Image Tagging \t\t\t\t\nLocations Tagging \t\t\t\t\nCustom Call-To-Actions \t\t\t\t\nImage Editor \t\t\t\t\nHoliday Calendar \t\t\t\t\nAnalytics\t\t\t\t\nDetailed Social Media Analytics \t\t\t\t\nCustom Reports \t\t\t\t\nPost Performance \t\t\t\t\nPDF Reports \t\t\t\t\nSend PDF Report Via Email \t\t\t\t\nWhite Label Reports \t\t\t\t\nSchedule Reports \t\t\t\t\nSocial Inbox\t\t\t\t\nReply to Posts & Comments \t\t\t\t\nReply to Messages \t\t\t\t\nReply to Stories \t\t\t\t\nTeam & Client Collaboration\t\t\t\t\nComments on Post \t\t\t\t\nContent Approval Workflows \t\t\t\t\nClient Management \t\t\t\t\nClient Approval Workflows \t\t\t\t\nManager Approval Workflow \t\t\t\t\nAdvanced White Label \t\t\t\t\nIntegrations And Apps\t\t\t\t\nSlack Integration \t\t\t\t\nZapier Integration \t\t\t\t\nBrowser Extension \t\t\t\t\nMobile App \t\t\t\t\nCanva Integration \t\t\t\t\nUnsplash Integration \t\t\t\t\nGoogle Drive, Dropbox & Box.com Integration \t\t\t\t\nSecurity\t\t\t\t\nTwo-Factor Authentication (2FA) \t\t\t\t\nEnforce Two-Factor Authentication (2FA) \t\t\t\t\nSupport & Community\t\t\t\t\nCustomer Support \t24\u00d75\t24\u00d75\t24\u00d75\t24\u00d75\nMigration & Onboarding \t\t\t\t\nAccount Manager \t\t\t\t\nSelf-Service Knowledge Base \t\t\t\t\n\nTrusted by Agencies and Brands Worldwide\n\nSocialPilot is a part of daily lives of thousands of social media marketers and highly recommended for its capabilities.\n\n13K+\n\nCustomers across industries\n\n4.5\n\nRated on G2 For Ease of Use\n\n10M+\n\nPosts Published Monthly\n\nFrequently Asked Questions\nAre there any contracts or commitments?\nWhat payment options do you offer?\nCan I change my plan later?\nWhat kind of support do you offer?\nCan users under the Ultimate plan in SocialPilot use Slack integration?\nDoes SocialPilot charge tax to customers?\n\nCompany\n\nAbout Us\nAffiliate\nEducation Partner\nCareers\nNewsroom\nHelp Center\nWall of Love \u2764\ufe0f\nTrust Center\nWrite for Us\nContact Us\n\nProducts\n\nSocial Media Management\n\nSocial Media Publishing\nSocial Media Analytics\nSocial Inbox\nTeam Collaboration\nWhite Label\nIntegrations\n\nReviews\n\nReview Management\nReview Generation\n\nTop Features\n\nSocial Media Calendar\nAI Pilot\nContent Library\nBulk Scheduling\nTeam Management\nClient Management\nAdvanced Reports\nApproval On-The-Go\nBrowser Extension\n\nTools & Templates\n\nFacebook Post Generator\nInstagram Caption Generator\nTikTok Caption Generator\nTwitter Post Generator\nLinkedin Post Generator\nThread Magic\nSocial Media Templates\nHoliday Calendar\nBest Apps & Tools\n\nResources\n\nSocial Media Blog\nReview Management Blog\nDownloadables\nWebinars\nMasterclass\nPodcasts\nAgency Success Guide\nCompare\nAlternatives\nProduct Updates\n\u00a9 2025 SocialPilot Technologies Inc. All Rights Reserved. Privacy Policy & GDPR Terms of Service\nFollow us :\n\nBrowse pocket-friendly plans. Find the right plan for your social media management needs & get started with your free trial. No credit card required.",
      "error": null,
      "pricing_data": {
        "app_id": "socialpilot",
        "app_name": "SocialPilot",
        "app_slug": "socialpilot",
        "pricing_url": "https://www.socialpilot.co/pricing",
        "source_url": null,
        "all_pricing_urls": [
          "https://www.socialpilot.co/pricing"
        ],
        "price_model_type": [
          "PriceModelType.SUBSCRIPTION",
          "PriceModelType.FREE_TIER"
        ],
        "has_free_tier": false,
        "has_free_trial": true,
        "free_trial_period_days": 14,
        "currency": "USD",
        "is_pricing_public": true,
        "pricing_page_accessible": true,
        "pricing_notes": "Annual billing offers a 15% discount compared to monthly billing.",
        "pricing_tiers": [
          {
            "tier_name": "Essentials",
            "tier_description": "Built for professionals who work independently.",
            "monthly_price": 30.0,
            "annual_price": 25.5,
            "annual_discount_percentage": 15.0,
            "setup_fee": null,
            "features": [
              "7 Social Media Accounts",
              "1 User",
              "500 AI Credits",
              "Content Library",
              "Tags"
            ],
            "limits": {
              "users": 1,
              "storage": null,
              "operations": null,
              "api_calls": null,
              "integrations": null,
              "custom_limits": [
                {
                  "name": "Social Media Accounts",
                  "value": 7
                },
                {
                  "name": "AI Credits",
                  "value": 500
                }
              ]
            }
          },
          {
            "tier_name": "Standard",
            "tier_description": "Designed to empower SMBs and small teams.",
            "monthly_price": 50.0,
            "annual_price": 42.5,
            "annual_discount_percentage": 15.0,
            "setup_fee": null,
            "features": [
              "15 Social Media Accounts",
              "3 Users",
              "1000 AI Credits",
              "Social Media Inbox",
              "Analytics",
              "Team Collaboration",
              "Manager Approval"
            ],
            "limits": {
              "users": 3,
              "storage": null,
              "operations": null,
              "api_calls": null,
              "integrations": null,
              "custom_limits": [
                {
                  "name": "Social Media Accounts",
                  "value": 15
                },
                {
                  "name": "AI Credits",
                  "value": 1000
                }
              ]
            }
          },
          {
            "tier_name": "Premium",
            "tier_description": "Capabilities built for growing agencies who want to scale.",
            "monthly_price": 100.0,
            "annual_price": 85.0,
            "annual_discount_percentage": 15.0,
            "setup_fee": null,
            "features": [
              "25 Social Media Accounts",
              "6 Users",
              "5000 AI Credits",
              "Bulk Schedule",
              "Advanced Analytics",
              "Client Approval",
              "White Label Reports"
            ],
            "limits": {
              "users": 6,
              "storage": null,
              "operations": null,
              "api_calls": null,
              "integrations": null,
              "custom_limits": [
                {
                  "name": "Social Media Accounts",
                  "value": 25
                },
                {
                  "name": "AI Credits",
                  "value": 5000
                }
              ]
            }
          },
          {
            "tier_name": "Ultimate",
            "tier_description": "Designed for established agencies and multi-location brands.",
            "monthly_price": 200.0,
            "annual_price": 170.0,
            "annual_discount_percentage": 15.0,
            "setup_fee": null,
            "features": [
              "50 Social Media Accounts",
              "Unlimited Users",
              "Unlimited AI Credits",
              "Advanced Security",
              "Advanced White Label",
              "Dedicated Account Manager",
              "Migration & Onboarding"
            ],
            "limits": {
              "users": "unlimited",
              "storage": null,
              "operations": null,
              "api_calls": null,
              "integrations": null,
              "custom_limits": [
                {
                  "name": "Social Media Accounts",
                  "value": 50
                },
                {
                  "name": "AI Credits",
                  "value": "unlimited"
                }
              ]
            }
          },
          {
            "tier_name": "Enterprise",
            "tier_description": "For enterprises who want to go above and beyond pre-made plans and need custom solutions.",
            "monthly_price": null,
            "annual_price": null,
            "annual_discount_percentage": null,
            "setup_fee": null,
            "features": [
              "Custom Accounts",
              "Unlimited Users",
              "Unlimited AI Credits",
              "Unlimited Clients",
              "Dedicated Account Manager",
              "Migration & Onboarding",
              "Single Sign-On (SSO)",
              "API Access"
            ],
            "limits": {
              "users": "unlimited",
              "storage": null,
              "operations": null,
              "api_calls": null,
              "integrations": null,
              "custom_limits": [
                {
                  "name": "AI Credits",
                  "value": "unlimited"
                }
              ]
            }
          }
        ],
        "usage_based_pricing": null,
        "ai_specific_pricing": {
          "has_token_based_pricing": false,
          "input_token_price": null,
          "output_token_price": null,
          "models_pricing": null,
          "has_inference_pricing": false,
          "has_fine_tuning_pricing": false,
          "has_training_pricing": false,
          "ai_addon_available": false
        },
        "promotional_offers": null,
        "additional_fees": [
          {
            "fee_name": "Extra Accounts",
            "fee_amount": 4.0,
            "fee_description": "Additional social media accounts per month."
          },
          {
            "fee_name": "Additional User",
            "fee_amount": 5.0,
            "fee_description": "Additional user per month for Standard and Premium plans."
          }
        ],
        "extraction_timestamp": "2025-04-15T08:52:10.157100",
        "schema_validated": true,
        "confidence_score": 100,
        "extraction_error": false,
        "json_repaired": false
      },
      "pricing_analyzed": true
    }
  ],
  "results_directory": "pricing_results\\socialpilot\\20250415_085210"
}