{
  "app_name": "DealMachine",
  "app_slug": "dealmachine",
  "search_term": "Find the official pricing page URL for DealMachine (dealmachine.com). Only provide the exact URL to the pricing page, not a summary of pricing information.",
  "timestamp": 1744726033.6973875,
  "response_text": [
    "The official pricing page URL for DealMachine is: [https://dealmachine.com/pricing](https://dealmachine.com/pricing)\u30103:0\u2020source\u3011."
  ],
  "citations": [
    {
      "title": "DealMachine Pricing - Compare Plans and Try For Free",
      "url": "https://www.dealmachine.com/pricing"
    }
  ],
  "extracted_content": [
    {
      "url": "https://www.dealmachine.com/pricing",
      "is_accessible": true,
      "content": "Product\nkeyboard_arrow_down\nProduct:\ndirections_car\nDriving For Dollars\nFind off-market deals by driving.\nkeyboard_arrow_right\nplaylist_add\nList Builder\nAutomate lead generation with smart lists.\nkeyboard_arrow_right\nperson_search\nUnlimited Contact Info\nLook up contact information for property owners.\nkeyboard_arrow_right\ncall\nAI-Powered Dialer\nCall with confidence with AI by your side.\nkeyboard_arrow_right\nmail\nMarketing Automation\nSend direct mail to property owners with automated follow-ups.\nkeyboard_arrow_right\nforum\nReal Estate AI Assistant\nLet our AI assistant guide you on your journey.\nkeyboard_arrow_right\nSee All Features\narrow_right_alt\nLearn\nkeyboard_arrow_down\nLearn:\nFREE\narticle\nBlog\nSubscribe to our newsletter for the latest info on real estate investing.\nkeyboard_arrow_right\ngroups\nCommunity\nDiscuss real estate with other on the journey.\nkeyboard_arrow_right\nfast_forward\nMedia\nWatch, listen and engage with our media library.\nkeyboard_arrow_right\nsupport\nHelp\nLearn how to use DealMachine through our help center and live chat support.\nkeyboard_arrow_right\nDealMachine Masterclass\nPAID\nJoin an intimate group of likeminded individuals weekly. Part of your DealMachine subscription.\nkeyboard_arrow_right\nLatest From Blog:\nSee All\narrow_right_alt\nCreative Real Estate Deals That Built 250 Properties\nkeyboard_arrow_right\nTop 5 Ways to Find Off-Market Real Estate Investments\nkeyboard_arrow_right\nHow Karl Spielvogel Turns Messy Properties into Big Profits\nkeyboard_arrow_right\nPricing\nLogin\nGet Started\narrow_right_alt\nClose More Deals. Start Free.\nChoose a plan that works for you.\ntoggle_on\nSave 17% with annual\nStarter\n$99 /mo $1190 billed annually\nJust getting started? Want to try things out? Start here.\ncheck\n1 user\ncheck\nUnlimited contact info, phone numbers, and email addresses\ncheck\nUp to 20,000 leads\ncheck\n10,000 leads exported per month\ncheck\nDriving for dollars\ncheck\nAI-Powered Dialer access\ncheck\nAI Voicemail drops\ncheck\n1 call tracking number\ncheck\nMLS & county comps\ncheck\nDaily data updates\ncheck\nMail as low as 67\u00a2\nGet Started\narrow_right_alt\nPro\nBest Value!\n$149 /mo $1790 billed annually\nBuilt for small teams with big goals.\ncheck\nEverything included in Starter\ncheck\n3 users\ncheck\nUp to 60,000 leads\ncheck\n30,000 exported leads per month exports\n\n\ncheck\n3 call tracking numbers\ncheck\nReal estate AI assistant\ncheck\nRoute planning\ncheck\nMail sequences\ncheck\nCustom mail designer\ncheck\nCurbside view of properties from Google street view on your mail.\ncheck\n10 Custom Fields\n\n\ncheck\nMail as low as 62\u00a2\nGet Started\narrow_right_alt\nPro Plus\n$232 /mo $2790 billed annually\nBuilt for pros who need that extra edge to win.\ncheck\nEverything included in Pro\ncheck\n6 users\ncheck\nUp to 120,000 leads\ncheck\n60,000 exported leads per month\n\n\ncheck\n6 call tracking number\ncheck\nDriver recruitment tools\ncheck\nCustom deal pipeline\u00a0\ncheck\n25 custom fields\n\n\ncheck\nMail as low as 57\u00a2\nGet Started\narrow_right_alt\nNeed more data? Have a larger team?\u00a0\n\nContact us for custom pricing for larger scale operations.\n\nContact Sales\narrow_right_alt\nSave cash with Unlimited Licenses.\n\nYour DealMachine plan gives you access to our AI-powered dialer through per-minute pricing. You can buy a license for every caller on your team and get unlimited minutes and AI voicemails.\n\nDialer License\n$99 /mo\nStop paying buy the minute and get an unlimited license. 1 team member per license.\ncheck\nUnlimited dialer minutes\nGet Started\narrow_right_alt\nAI Voicemail License\n$99 /mo\nDrop till you can't stop. Get unlimited AI voicemail drops. 1 team member per license.\ncheck\nUnlimited AI Voicemail drops\nGet Started\narrow_right_alt\nJoin over 150,000 people on the path to financial freedom.\nChoose a plan that works for you.\n\n\u00a0\n\n\u00a0\tStarter\tPro\tPro Plus\nTeam members\t1\t3\t6\nLeads with live data updates\t20,000\t60,000\t120,000\nMonthly exports\t10,000\t30,000\t60,000\nMail pricing\tas low as 64\u00a2\tas low as 62\u00a2\tas low as 57\u00a2\nBallpoint Letter pricing\tas low as $1.99\tas low as $1.75\tas low as $1.47\nSkip trace pricing\tFREE\tFREE\tFREE\nCorporate skip trace pricing\tFREE\tFREE\tFREE\nDialer\tcheck\tcheck\tcheck\nDialer price per minute\nTry our Unlimited Dialer License\n$99/mo per seat!\n\t$0.06\t$0.05\t$0.04\nAI Voicemail Drop\nTry our Unlimited AI Voicemail License!\n$99/mo per seat!\n\t$0.08\t$0.07\t$0.06\nTake incoming calls/texts\tFREE\tFREE\tFREE\nCall Pool SPAM monitoring\tcheck\tcheck\tcheck\nLitigator Scrub\tcheck\tcheck\tcheck\nLive Transcription\tcheck\tcheck\tcheck\nAI Call Summarization\tcheck\tcheck\tcheck\nAI Call Suggestions\tcheck\tcheck\tcheck\nAutomated Follow-Up Queue\tcheck\tcheck\tcheck\nCall Reporting\tcheck\tcheck\tcheck\nCall Tracking Numbers\t1\t3\t6\nRoute planning\t--\tcheck\tcheck\nCustom mail designs\t--\tcheck\tcheck\nStreet pic\t--\tcheck\tcheck\nMail sequences\t--\tcheck\tcheck\nCustom pipeline\t--\t--\tcheck\n\n\u00a0\n\n\u2709\ufe0f Interested in Bulk Mail? You could receive mail for as low as $.50\n\nClick here to schedule a call with our Head of Customer Success\n\nkeyboard_arrow_right\n\u00a0\n$10,000 Bulk Mail Deposit\n\n\u00a0\n\nSize\n\n\t\n\nPricing\n\n\n\n\n4x6\n\n\t\n\n$0.54\n\n\n\n\n6x9\n\n\t\n\n$0.69\n\n\n\n\n6x11\n\n\t\n\n$0.76\n\n\u00a0\n$15,000 Bulk Mail Deposit\n\n\u00a0\n\nSize\n\n\t\n\nPricing\n\n\n\n\n4x6\n\n\t\n\n$0.52\n\n\n\n\n6x9\n\n\t\n\n$0.67\n\n\n\n\n6x11\n\n\t\n\n$0.76\n\n\u00a0\n$20,000 Bulk Mail Deposit\n\n\u00a0\n\nSize\n\n\t\n\nPricing\n\n\n\n\n4x6\n\n\t\n\n$0.50\n\n\n\n\n6x9\n\n\t\n\n$0.65\n\n\n\n\n6x11\n\n\t\n\n$0.76\n\nYou have questions? We have answers.\n\n\u00a0\n\nadd\n\nWhat is driving for dollars?\n\nadd\n\nWhat is List Builder?\n\nadd\n\nWhat makes DealMachine unique?\n\nadd\n\nWhat is DealMachine Masterclass?\n\nadd\n\nCan I track my routes?\n\nadd\n\nCan I add team members on my account?\n\nadd\n\nCan I control my team members abilities?\n\nadd\n\nWhat does route planning do?\n\nadd\n\nWhere does DealMachine get data from? Is It accurate?\n\nadd\n\nHow often do you update your data?\n\nadd\n\nCan I import my leads into DealMachine?\n\nadd\n\nCan I export or pull data out of DealMachine?\n\nadd\n\nDo I need a CRM to go with DealMachine?\n\nadd\n\nDoes DealMachine support Zapier?\n\nadd\n\nWhat are comps?\n\nadd\n\nWhy do you need my billing info for a free trial?\n\nadd\n\nHow do I cancel? (refund policy)\n\nadd\n\nHow can I contact DealMachine support?\n\nInvest with confidence using the highest-rated real estate investing app.\nBest value investor app ever!6 months ago\nstar\nstar\nstar\nstar\nstar\nThis real estate investment app is top-notch. The live chat support, expert classes, and weekly online meetings are amazing! I'm hooked. Great work!\nUser6 months ago\nstar\nstar\nstar\nstar\nstar\nGreat App. Lots of potential to make $$$\nAccuracy and support6 months ago\nstar\nstar\nstar\nstar\nstar\nDeal machine is the best software for wholesalers, flipper and real estate investors. All information about the home and owners is very accurate and when having any issue their support team is just a click away and take care of questions and issues quickly. I highly recommend Deal Machine!\nReview3 months ago\nstar\nstar\nstar\nstar\nstar\nAre you tired of getting out of your car to locate addresses of vacant houses? I know I was. That\u2019s how I knew deal machine was for me. Now I get to add houses from the comfort of my car! Thank you so much deal machine.\nGreen, seasoned, stuck and wanna grow?? This app will get you where you want to be!!3 months ago\nstar\nstar\nstar\nstar\nstar\nAbsolutely amazing application for investors wholesalers anybody in real estate in all stages of their career weather you\u2019re just getting started like myself or if you already have an up and running business, and wanna take it to the next level. Of course I\u2019m not there yet, but I can\u2019t help to think about the possibilities once I do get there that this app or this tool well allow me to do I could write 10 pages about all the different functions in applications that DealMachine has available, but just on the surface it allows you to To find thousands of leads efficiently, organize them them gives you all the information on the spot about each Property their owner Records Skiptracing cops then gives you the option to do all the marketing in terms of mailers Cold calling. If you\u2019re like me and getting started, I need to drive for dollars you can literally do it from your couch virtually, You can plan out routes so that way you can focus more on the properties as opposed to your route you could do it free I mean, I can go on and on about how awesome this app is if you were able to give 10 stars I would give 11\nDeal Machine is the real deal3 months ago\nstar\nstar\nstar\nstar\nstar\nDeal Machine really makes gathering information about properties very efficient and easy. I\u2019m just starting on the real estate investing journey and between the program and podcast my learning curve has been shortened significantly.\nGreat for Real Estate Investors!!3 months ago\nstar\nstar\nstar\nstar\nstar\nDealmachine makes finding properties for real estate investing easy and fast! It only took minutes to compile a list and send a mailing campaign. The list is neatly organized for me and can be further updated as the lead process goes forward. Support was super helpful in getting me started. Very user friendly!\nEasy to use3 months ago\nstar\nstar\nstar\nstar\nstar\nEasy to use and accurate information!!\nDeal Machine is Great3 months ago\nstar\nstar\nstar\nstar\nstar\nDeal machine is very user friendly and it speeds up the wholesaling process by a large margin. Totally worth the subscription, I recommend to all!\nVery user friendly4 months ago\nstar\nstar\nstar\nstar\nstar\nVery user friendly and customer support responds quickly.\nGreat customer service!4 months ago\nstar\nstar\nstar\nstar\nstar\nReally happy with my experience so far. They are very responsive and helpful!\nDriving for dollars4 months ago\nstar\nstar\nstar\nstar\nstar\nI truly love this app how simple it\u2019s made things like driving for dollars. Find myself pulling over and then tagging a house or neighborhood. Then starting mail and easy follow up later when I get home.\nRevolutionary Real Estate App4 months ago\nstar\nstar\nstar\nstar\nstar\nDeal Machine free skiptracing, accurate ability to filter properties, its intuitive feature and design make it a no brainer compared to other property apps like propstream. We\u2019ve been searching for an all in one software that listens to its users and has support for all user features. Best real estate app for my team!\nInvestor4 months ago\nstar\nstar\nstar\nstar\nstar\nGreat all in one tool\nAmazing App for RE4 months ago\nstar\nstar\nstar\nstar\nstar\nThis app is easy to use and even more features than I have used yet. Driving for dollars is invaluable to have all the info saved in the app as you go!\nReliable Information4 months ago\nstar\nstar\nstar\nstar\nstar\nRecently introduced to Deal Machine. I\u2019m new to real estate investing and this app came highly recommended from various people! Love that the information is so up to date.\nAmazing Starter Resource4 months ago\nstar\nstar\nstar\nstar\nstar\nI\u2019m new to real estate investing but this is such an amazing resource so far! I\u2019ve checked out other platforms and did not like any of them as much as Deal Machine. The information is pretty up to date and accurate, I didn\u2019t find this kind of reliability on other platforms.\nThe Best!4 months ago\nstar\nstar\nstar\nstar\nstar\nBest REI app out there :)\nGreat Tool4 months ago\nstar\nstar\nstar\nstar\nstar\nJust subscribed for the new year and excited about the new features\nGreat4 months ago\nstar\nstar\nstar\nstar\nstar\nGreat tool and great customer support !\nExcellent Application5 months ago\nstar\nstar\nstar\nstar\nstar\nI was recently introduced to this app and love it!! Highly recommend.\nEasy to use5 months ago\nstar\nstar\nstar\nstar\nstar\nThis software offers a lot of options while remaining easy to use. Thank you!\nEverything I need to run my business5 months ago\nstar\nstar\nstar\nstar\nstar\nMyself and other investors in my network all use Deal Machine to run our real estate businesses. Deal machine offers everything I need - lists, slip testing, Driving for Dollars, AI Assisted Dialing - you name it. It\u2019s super convenient to have everything I need one platform that\u2019s simple and easy to use. On top of that, their customer service is unmatched, and they are always innovating to improve the user experience. Thank you Deal Machine!\nGreat app5 months ago\nstar\nstar\nstar\nstar\nstar\nGreat app, I use it both for driving for dollars and for finding property leads using the integrative map feature.\n5 stars5 months ago\nstar\nstar\nstar\nstar\nstar\nGreat tool\nDealMachine rocks!5 months ago\nstar\nstar\nstar\nstar\nstar\nThe guys have it dialed in! Software works great and customer service is top notch.\nLove this app5 months ago\nstar\nstar\nstar\nstar\nstar\nIt\u2019s great\nBy far the best driving for dollars app5 months ago\nstar\nstar\nstar\nstar\nstar\nI love using this app to drive for dollars and send mailers. Automates my marketing and brings me inbound leads without harassing people.\nGreat Technology for Real Estate5 months ago\nstar\nstar\nstar\nstar\nstar\nI have been a real estate investor for a handful of years and have used DealMachine for the past year. In my opinion, DealMachine is becoming the most comprehensive data/skip trace/dialer/CRM is one.\nAmazing app!5 months ago\nstar\nstar\nstar\nstar\nstar\nDeal machine is a one stop shop. From lead details, lead management, and dialer I couldn\u2019t be happier!\nDriving 4 $$$5 months ago\nstar\nstar\nstar\nstar\nstar\nThis is the best app to be created.\nDeal Machine App5 months ago\nstar\nstar\nstar\nstar\nstar\nThis is a great app to use!!It has same me time and energy. Thank you Deal Machine for such a great product!!\nAmazing5 months ago\nstar\nstar\nstar\nstar\nstar\nThis shortens the time spent looking for needed info, and the unlimited leads is much less expensive than other lead sources. well done.\nGreat app5 months ago\nstar\nstar\nstar\nstar\nstar\nGreat app!\nMoney Machine5 months ago\nstar\nstar\nstar\nstar\nstar\nDeal machine is a money making platform for Wholesalers when used correctly. The Skip-tracing is the best with very accurate data. The D4$ is a great tool.\nDealMachine Is Adding New Things!5 months ago\nstar\nstar\nstar\nstar\nstar\nI am excited to have upgraded to the DealMachine Pro Version. Although I haven\u2019t used all of the features yet, I was able to cancel 2 other programs that I was paying for. Nearly everything I needed, is in this program. James (in Support) is great. Ryan & Elise are good teachers. One of the best decisions I have ever made, for a real estate software program.\nLots of tools at your disposal5 months ago\nstar\nstar\nstar\nstar\nstar\nI absolutely love the AI dailer. Helps you keep track of your conversation and leads. The post cards are a great addition so far haven\u2019t had much luck yet but I will \ud83d\udc4d\ud83c\udffd\ud83d\udc4d\ud83c\udffd\nGreat for analyzing and cold calling5 months ago\nstar\nstar\nstar\nstar\nstar\nI have been really happy with this app for the last year. They have now added an AI dialer, which is really cool. I like the driving for dollars feature as well.\nGreat app but few bugs5 months ago\nstar\nstar\nstar\nstar\nstar\nI love this app and its most definitely my favorite software to use. But the only thing is that it has a few bugs that I and maybe some others don\u2019t enjoy. It sometimes lags out and I have to keep refreshing the app. It won\u2019t let me press the buttons to call nor copy the address. Please fix this problem for the future and fix it for us. Thank you deal machine. Yall are great. \ud83e\udd19\ud83e\udd19\nDeal machine rocks6 months ago\nstar\nstar\nstar\nstar\nstar\nGreat service user friendly and awesome tech support\nEasy to use6 months ago\nstar\nstar\nstar\nstar\nstar\nFull of great information and very user friendly.\nEasy Using App6 months ago\nstar\nstar\nstar\nstar\nstar\nActually enjoy using the app. Very user friendly. What\u2019s even better is that the customer service is really responsive if you need help with anything. Definitely worth getting.\nGreat program !!6 months ago\nstar\nstar\nstar\nstar\nstar\nLove this program!! It does everything you can think of !!\nThe DealMachine for real estate investors6 months ago\nstar\nstar\nstar\nstar\nstar\nThe DealMachine is the greatest piece of equipment. I could\u2019ve added to my investment journey. It\u2019s an all-in-one tool that is easy to use. Once you have the DealMachine, you don\u2019t have to use any other platform in real estate. David Leko has made this so simple for you. If if it was any simpler, he\u2019d be doing it for you. The only way you won\u2019t be successful with the DealMachine is if you don\u2019t use it.\nFirst appointment6 months ago\nstar\nstar\nstar\nstar\nstar\nI used PropStream for about a month and was receiving a lot of wrong numbers. I then switched to DealMachine and within the first week I set my first wholesale appointment. I made an offer to the seller and waiting for her acceptance, which hopefully will happen tomorrow. Highly recommended DealMachine over PropStream.\nBest value investor app ever!6 months ago\nstar\nstar\nstar\nstar\nstar\nThis real estate investment app is top-notch. The live chat support, expert classes, and weekly online meetings are amazing! I'm hooked. Great work!\nUser6 months ago\nstar\nstar\nstar\nstar\nstar\nGreat App. Lots of potential to make $$$\nAccuracy and support6 months ago\nstar\nstar\nstar\nstar\nstar\nDeal machine is the best software for wholesalers, flipper and real estate investors. All information about the home and owners is very accurate and when having any issue their support team is just a click away and take care of questions and issues quickly. I highly recommend Deal Machine!\nReview3 months ago\nstar\nstar\nstar\nstar\nstar\nAre you tired of getting out of your car to locate addresses of vacant houses? I know I was. That\u2019s how I knew deal machine was for me. Now I get to add houses from the comfort of my car! Thank you so much deal machine.\nGreen, seasoned, stuck and wanna grow?? This app will get you where you want to be!!3 months ago\nstar\nstar\nstar\nstar\nstar\nAbsolutely amazing application for investors wholesalers anybody in real estate in all stages of their career weather you\u2019re just getting started like myself or if you already have an up and running business, and wanna take it to the next level. Of course I\u2019m not there yet, but I can\u2019t help to think about the possibilities once I do get there that this app or this tool well allow me to do I could write 10 pages about all the different functions in applications that DealMachine has available, but just on the surface it allows you to To find thousands of leads efficiently, organize them them gives you all the information on the spot about each Property their owner Records Skiptracing cops then gives you the option to do all the marketing in terms of mailers Cold calling. If you\u2019re like me and getting started, I need to drive for dollars you can literally do it from your couch virtually, You can plan out routes so that way you can focus more on the properties as opposed to your route you could do it free I mean, I can go on and on about how awesome this app is if you were able to give 10 stars I would give 11\nDeal Machine is the real deal3 months ago\nstar\nstar\nstar\nstar\nstar\nDeal Machine really makes gathering information about properties very efficient and easy. I\u2019m just starting on the real estate investing journey and between the program and podcast my learning curve has been shortened significantly.\nGreat for Real Estate Investors!!3 months ago\nstar\nstar\nstar\nstar\nstar\nDealmachine makes finding properties for real estate investing easy and fast! It only took minutes to compile a list and send a mailing campaign. The list is neatly organized for me and can be further updated as the lead process goes forward. Support was super helpful in getting me started. Very user friendly!\nEasy to use3 months ago\nstar\nstar\nstar\nstar\nstar\nEasy to use and accurate information!!\nDeal Machine is Great3 months ago\nstar\nstar\nstar\nstar\nstar\nDeal machine is very user friendly and it speeds up the wholesaling process by a large margin. Totally worth the subscription, I recommend to all!\nVery user friendly4 months ago\nstar\nstar\nstar\nstar\nstar\nVery user friendly and customer support responds quickly.\nGreat customer service!4 months ago\nstar\nstar\nstar\nstar\nstar\nReally happy with my experience so far. They are very responsive and helpful!\nDriving for dollars4 months ago\nstar\nstar\nstar\nstar\nstar\nI truly love this app how simple it\u2019s made things like driving for dollars. Find myself pulling over and then tagging a house or neighborhood. Then starting mail and easy follow up later when I get home.\nRevolutionary Real Estate App4 months ago\nstar\nstar\nstar\nstar\nstar\nDeal Machine free skiptracing, accurate ability to filter properties, its intuitive feature and design make it a no brainer compared to other property apps like propstream. We\u2019ve been searching for an all in one software that listens to its users and has support for all user features. Best real estate app for my team!\nInvestor4 months ago\nstar\nstar\nstar\nstar\nstar\nGreat all in one tool\nAmazing App for RE4 months ago\nstar\nstar\nstar\nstar\nstar\nThis app is easy to use and even more features than I have used yet. Driving for dollars is invaluable to have all the info saved in the app as you go!\nReliable Information4 months ago\nstar\nstar\nstar\nstar\nstar\nRecently introduced to Deal Machine. I\u2019m new to real estate investing and this app came highly recommended from various people! Love that the information is so up to date.\nAmazing Starter Resource4 months ago\nstar\nstar\nstar\nstar\nstar\nI\u2019m new to real estate investing but this is such an amazing resource so far! I\u2019ve checked out other platforms and did not like any of them as much as Deal Machine. The information is pretty up to date and accurate, I didn\u2019t find this kind of reliability on other platforms.\nThe Best!4 months ago\nstar\nstar\nstar\nstar\nstar\nBest REI app out there :)\nGreat Tool4 months ago\nstar\nstar\nstar\nstar\nstar\nJust subscribed for the new year and excited about the new features\nGreat4 months ago\nstar\nstar\nstar\nstar\nstar\nGreat tool and great customer support !\nExcellent Application5 months ago\nstar\nstar\nstar\nstar\nstar\nI was recently introduced to this app and love it!! Highly recommend.\nEasy to use5 months ago\nstar\nstar\nstar\nstar\nstar\nThis software offers a lot of options while remaining easy to use. Thank you!\nEverything I need to run my business5 months ago\nstar\nstar\nstar\nstar\nstar\nMyself and other investors in my network all use Deal Machine to run our real estate businesses. Deal machine offers everything I need - lists, slip testing, Driving for Dollars, AI Assisted Dialing - you name it. It\u2019s super convenient to have everything I need one platform that\u2019s simple and easy to use. On top of that, their customer service is unmatched, and they are always innovating to improve the user experience. Thank you Deal Machine!\nGreat app5 months ago\nstar\nstar\nstar\nstar\nstar\nGreat app, I use it both for driving for dollars and for finding property leads using the integrative map feature.\n5 stars5 months ago\nstar\nstar\nstar\nstar\nstar\nGreat tool\nDealMachine rocks!5 months ago\nstar\nstar\nstar\nstar\nstar\nThe guys have it dialed in! Software works great and customer service is top notch.\nLove this app5 months ago\nstar\nstar\nstar\nstar\nstar\nIt\u2019s great\nBy far the best driving for dollars app5 months ago\nstar\nstar\nstar\nstar\nstar\nI love using this app to drive for dollars and send mailers. Automates my marketing and brings me inbound leads without harassing people.\nGreat Technology for Real Estate5 months ago\nstar\nstar\nstar\nstar\nstar\nI have been a real estate investor for a handful of years and have used DealMachine for the past year. In my opinion, DealMachine is becoming the most comprehensive data/skip trace/dialer/CRM is one.\nAmazing app!5 months ago\nstar\nstar\nstar\nstar\nstar\nDeal machine is a one stop shop. From lead details, lead management, and dialer I couldn\u2019t be happier!\nDriving 4 $$$5 months ago\nstar\nstar\nstar\nstar\nstar\nThis is the best app to be created.\nDeal Machine App5 months ago\nstar\nstar\nstar\nstar\nstar\nThis is a great app to use!!It has same me time and energy. Thank you Deal Machine for such a great product!!\nAmazing5 months ago\nstar\nstar\nstar\nstar\nstar\nThis shortens the time spent looking for needed info, and the unlimited leads is much less expensive than other lead sources. well done.\nGreat app5 months ago\nstar\nstar\nstar\nstar\nstar\nGreat app!\nMoney Machine5 months ago\nstar\nstar\nstar\nstar\nstar\nDeal machine is a money making platform for Wholesalers when used correctly. The Skip-tracing is the best with very accurate data. The D4$ is a great tool.\nDealMachine Is Adding New Things!5 months ago\nstar\nstar\nstar\nstar\nstar\nI am excited to have upgraded to the DealMachine Pro Version. Although I haven\u2019t used all of the features yet, I was able to cancel 2 other programs that I was paying for. Nearly everything I needed, is in this program. James (in Support) is great. Ryan & Elise are good teachers. One of the best decisions I have ever made, for a real estate software program.\nLots of tools at your disposal5 months ago\nstar\nstar\nstar\nstar\nstar\nI absolutely love the AI dailer. Helps you keep track of your conversation and leads. The post cards are a great addition so far haven\u2019t had much luck yet but I will \ud83d\udc4d\ud83c\udffd\ud83d\udc4d\ud83c\udffd\nGreat for analyzing and cold calling5 months ago\nstar\nstar\nstar\nstar\nstar\nI have been really happy with this app for the last year. They have now added an AI dialer, which is really cool. I like the driving for dollars feature as well.\nGreat app but few bugs5 months ago\nstar\nstar\nstar\nstar\nstar\nI love this app and its most definitely my favorite software to use. But the only thing is that it has a few bugs that I and maybe some others don\u2019t enjoy. It sometimes lags out and I have to keep refreshing the app. It won\u2019t let me press the buttons to call nor copy the address. Please fix this problem for the future and fix it for us. Thank you deal machine. Yall are great. \ud83e\udd19\ud83e\udd19\nDeal machine rocks6 months ago\nstar\nstar\nstar\nstar\nstar\nGreat service user friendly and awesome tech support\nEasy to use6 months ago\nstar\nstar\nstar\nstar\nstar\nFull of great information and very user friendly.\nEasy Using App6 months ago\nstar\nstar\nstar\nstar\nstar\nActually enjoy using the app. Very user friendly. What\u2019s even better is that the customer service is really responsive if you need help with anything. Definitely worth getting.\nGreat program !!6 months ago\nstar\nstar\nstar\nstar\nstar\nLove this program!! It does everything you can think of !!\nThe DealMachine for real estate investors6 months ago\nstar\nstar\nstar\nstar\nstar\nThe DealMachine is the greatest piece of equipment. I could\u2019ve added to my investment journey. It\u2019s an all-in-one tool that is easy to use. Once you have the DealMachine, you don\u2019t have to use any other platform in real estate. David Leko has made this so simple for you. If if it was any simpler, he\u2019d be doing it for you. The only way you won\u2019t be successful with the DealMachine is if you don\u2019t use it.\nFirst appointment6 months ago\nstar\nstar\nstar\nstar\nstar\nI used PropStream for about a month and was receiving a lot of wrong numbers. I then switched to DealMachine and within the first week I set my first wholesale appointment. I made an offer to the seller and waiting for her acceptance, which hopefully will happen tomorrow. Highly recommended DealMachine over PropStream.\nBest value investor app ever!6 months ago\nstar\nstar\nstar\nstar\nstar\nThis real estate investment app is top-notch. The live chat support, expert classes, and weekly online meetings are amazing! I'm hooked. Great work!\nUser6 months ago\nstar\nstar\nstar\nstar\nstar\nGreat App. Lots of potential to make $$$\nAccuracy and support6 months ago\nstar\nstar\nstar\nstar\nstar\nDeal machine is the best software for wholesalers, flipper and real estate investors. All information about the home and owners is very accurate and when having any issue their support team is just a click away and take care of questions and issues quickly. I highly recommend Deal Machine!\nReal Estate At Your Fingertips.\n\nUnlock your full potential and build generational wealth with the app that gives you the power of real estate.\n\nGet Started\narrow_right_alt\n\nCompany\n\nAbout Us\nRelease Notes\nFeature Request\nBrand\nStatus\n\nResources\n\nHelp Docs\nContact Us\nImport Leads\nAPI\nPartners\nMedia\n\nTools\n\nBRRRR Calculator\nReal Estate Comps Tool\n\nFeatures\n\nDriving For Dollars\nList Builder\nUnlimited Contact Info\nAI-Powered Dialer\nMarketing Automation\nReal Estate AI Assistant\nSee All Features\nDemo\n\nSolutions\n\nWholesaling\nFix & Flip\n\nCompare\n\nvs Propstream\nvs BatchLeads\n\nLearn\n\nCommunity\nBlog\nMasterclass\n@ 2025 DealMachine Holdings L.L.C.\nPrivacy Policy\nTerms of Service\n801 Shelby St, Indianapolis, IN 46203\n\nFind your perfect real estate plan with DealMachine. Get a free 7-day trial and achieve your investment goals with the right plan for your journey.",
      "error": null,
      "pricing_data": {
        "app_id": "dealmachine",
        "app_name": "DealMachine",
        "app_slug": "dealmachine",
        "pricing_url": "https://dealmachine.com/pricing",
        "source_url": "https://dealmachine.com/pricing",
        "all_pricing_urls": [
          "https://dealmachine.com/pricing"
        ],
        "price_model_type": [
          "PriceModelType.SUBSCRIPTION",
          "PriceModelType.USAGE_BASED",
          "PriceModelType.QUOTE_BASED"
        ],
        "has_free_tier": false,
        "has_free_trial": true,
        "free_trial_period_days": null,
        "currency": "USD",
        "is_pricing_public": true,
        "pricing_page_accessible": true,
        "pricing_notes": "DealMachine offers subscription-based pricing with additional usage-based options for AI-powered dialer and voicemail services.",
        "pricing_tiers": [
          {
            "tier_name": "Starter",
            "tier_description": "Just getting started? Want to try things out? Start here.",
            "monthly_price": 99.0,
            "annual_price": 1190.0,
            "annual_discount_percentage": 17.0,
            "setup_fee": null,
            "features": [
              "1 user",
              "Unlimited contact info, phone numbers, and email addresses",
              "Up to 20,000 leads",
              "10,000 leads exported per month",
              "Driving for dollars",
              "AI-Powered Dialer access",
              "AI Voicemail drops",
              "1 call tracking number",
              "MLS & county comps",
              "Daily data updates",
              "Mail as low as 67\u00a2"
            ],
            "limits": {
              "users": 1,
              "storage": null,
              "operations": null,
              "api_calls": null,
              "integrations": null,
              "custom_limits": [
                {
                  "name": "Leads",
                  "value": 20000
                },
                {
                  "name": "Monthly Exports",
                  "value": 10000
                }
              ]
            }
          },
          {
            "tier_name": "Pro",
            "tier_description": "Built for small teams with big goals.",
            "monthly_price": 149.0,
            "annual_price": 1790.0,
            "annual_discount_percentage": 17.0,
            "setup_fee": null,
            "features": [
              "Everything included in Starter",
              "3 users",
              "Up to 60,000 leads",
              "30,000 exported leads per month exports",
              "3 call tracking numbers",
              "Real estate AI assistant",
              "Route planning",
              "Mail sequences",
              "Custom mail designer",
              "Curbside view of properties from Google street view on your mail.",
              "10 Custom Fields",
              "Mail as low as 62\u00a2"
            ],
            "limits": {
              "users": 3,
              "storage": null,
              "operations": null,
              "api_calls": null,
              "integrations": null,
              "custom_limits": [
                {
                  "name": "Leads",
                  "value": 60000
                },
                {
                  "name": "Monthly Exports",
                  "value": 30000
                }
              ]
            }
          },
          {
            "tier_name": "Pro Plus",
            "tier_description": "Built for pros who need that extra edge to win.",
            "monthly_price": 232.0,
            "annual_price": 2790.0,
            "annual_discount_percentage": 17.0,
            "setup_fee": null,
            "features": [
              "Everything included in Pro",
              "6 users",
              "Up to 120,000 leads",
              "60,000 exported leads per month",
              "6 call tracking number",
              "Driver recruitment tools",
              "Custom deal pipeline",
              "25 custom fields",
              "Mail as low as 57\u00a2"
            ],
            "limits": {
              "users": 6,
              "storage": null,
              "operations": null,
              "api_calls": null,
              "integrations": null,
              "custom_limits": [
                {
                  "name": "Leads",
                  "value": 120000
                },
                {
                  "name": "Monthly Exports",
                  "value": 60000
                }
              ]
            }
          }
        ],
        "usage_based_pricing": [
          {
            "metric_name": "Dialer minutes",
            "unit": "per minute",
            "base_price": 0.06,
            "tiers": [
              {
                "min": 0.0,
                "max": null,
                "price": 0.06
              }
            ]
          },
          {
            "metric_name": "AI Voicemail Drop",
            "unit": "per drop",
            "base_price": 0.08,
            "tiers": [
              {
                "min": 0.0,
                "max": null,
                "price": 0.08
              }
            ]
          }
        ],
        "ai_specific_pricing": {
          "has_token_based_pricing": false,
          "input_token_price": null,
          "output_token_price": null,
          "models_pricing": null,
          "has_inference_pricing": false,
          "has_fine_tuning_pricing": false,
          "has_training_pricing": false,
          "ai_addon_available": true
        },
        "promotional_offers": [
          {
            "offer_name": "Save 17% with annual billing",
            "offer_description": "Discount applied for annual billing.",
            "discount_percentage": 17.0,
            "offer_url": "https://dealmachine.com/pricing",
            "valid_until": null
          }
        ],
        "additional_fees": [
          {
            "fee_name": "Dialer License",
            "fee_amount": 99.0,
            "fee_description": "Unlimited dialer minutes for one team member per license."
          },
          {
            "fee_name": "AI Voicemail License",
            "fee_amount": 99.0,
            "fee_description": "Unlimited AI voicemail drops for one team member per license."
          }
        ],
        "extraction_timestamp": "2025-04-15T10:07:36.800546",
        "schema_validated": true,
        "confidence_score": 95,
        "extraction_error": false,
        "json_repaired": false
      },
      "pricing_analyzed": true
    },
    {
      "url": "https://dealmachine.com/pricing",
      "is_accessible": true,
      "content": "Product\nkeyboard_arrow_down\nProduct:\ndirections_car\nDriving For Dollars\nFind off-market deals by driving.\nkeyboard_arrow_right\nplaylist_add\nList Builder\nAutomate lead generation with smart lists.\nkeyboard_arrow_right\nperson_search\nUnlimited Contact Info\nLook up contact information for property owners.\nkeyboard_arrow_right\ncall\nAI-Powered Dialer\nCall with confidence with AI by your side.\nkeyboard_arrow_right\nmail\nMarketing Automation\nSend direct mail to property owners with automated follow-ups.\nkeyboard_arrow_right\nforum\nReal Estate AI Assistant\nLet our AI assistant guide you on your journey.\nkeyboard_arrow_right\nSee All Features\narrow_right_alt\nLearn\nkeyboard_arrow_down\nLearn:\nFREE\narticle\nBlog\nSubscribe to our newsletter for the latest info on real estate investing.\nkeyboard_arrow_right\ngroups\nCommunity\nDiscuss real estate with other on the journey.\nkeyboard_arrow_right\nfast_forward\nMedia\nWatch, listen and engage with our media library.\nkeyboard_arrow_right\nsupport\nHelp\nLearn how to use DealMachine through our help center and live chat support.\nkeyboard_arrow_right\nDealMachine Masterclass\nPAID\nJoin an intimate group of likeminded individuals weekly. Part of your DealMachine subscription.\nkeyboard_arrow_right\nLatest From Blog:\nSee All\narrow_right_alt\nCreative Real Estate Deals That Built 250 Properties\nkeyboard_arrow_right\nTop 5 Ways to Find Off-Market Real Estate Investments\nkeyboard_arrow_right\nHow Karl Spielvogel Turns Messy Properties into Big Profits\nkeyboard_arrow_right\nPricing\nLogin\nGet Started\narrow_right_alt\nClose More Deals. Start Free.\nChoose a plan that works for you.\ntoggle_on\nSave 17% with annual\nStarter\n$99 /mo $1190 billed annually\nJust getting started? Want to try things out? Start here.\ncheck\n1 user\ncheck\nUnlimited contact info, phone numbers, and email addresses\ncheck\nUp to 20,000 leads\ncheck\n10,000 leads exported per month\ncheck\nDriving for dollars\ncheck\nAI-Powered Dialer access\ncheck\nAI Voicemail drops\ncheck\n1 call tracking number\ncheck\nMLS & county comps\ncheck\nDaily data updates\ncheck\nMail as low as 67\u00a2\nGet Started\narrow_right_alt\nPro\nBest Value!\n$149 /mo $1790 billed annually\nBuilt for small teams with big goals.\ncheck\nEverything included in Starter\ncheck\n3 users\ncheck\nUp to 60,000 leads\ncheck\n30,000 exported leads per month exports\n\n\ncheck\n3 call tracking numbers\ncheck\nReal estate AI assistant\ncheck\nRoute planning\ncheck\nMail sequences\ncheck\nCustom mail designer\ncheck\nCurbside view of properties from Google street view on your mail.\ncheck\n10 Custom Fields\n\n\ncheck\nMail as low as 62\u00a2\nGet Started\narrow_right_alt\nPro Plus\n$232 /mo $2790 billed annually\nBuilt for pros who need that extra edge to win.\ncheck\nEverything included in Pro\ncheck\n6 users\ncheck\nUp to 120,000 leads\ncheck\n60,000 exported leads per month\n\n\ncheck\n6 call tracking number\ncheck\nDriver recruitment tools\ncheck\nCustom deal pipeline\u00a0\ncheck\n25 custom fields\n\n\ncheck\nMail as low as 57\u00a2\nGet Started\narrow_right_alt\nNeed more data? Have a larger team?\u00a0\n\nContact us for custom pricing for larger scale operations.\n\nContact Sales\narrow_right_alt\nSave cash with Unlimited Licenses.\n\nYour DealMachine plan gives you access to our AI-powered dialer through per-minute pricing. You can buy a license for every caller on your team and get unlimited minutes and AI voicemails.\n\nDialer License\n$99 /mo\nStop paying buy the minute and get an unlimited license. 1 team member per license.\ncheck\nUnlimited dialer minutes\nGet Started\narrow_right_alt\nAI Voicemail License\n$99 /mo\nDrop till you can't stop. Get unlimited AI voicemail drops. 1 team member per license.\ncheck\nUnlimited AI Voicemail drops\nGet Started\narrow_right_alt\nJoin over 150,000 people on the path to financial freedom.\nChoose a plan that works for you.\n\n\u00a0\n\n\u00a0\tStarter\tPro\tPro Plus\nTeam members\t1\t3\t6\nLeads with live data updates\t20,000\t60,000\t120,000\nMonthly exports\t10,000\t30,000\t60,000\nMail pricing\tas low as 64\u00a2\tas low as 62\u00a2\tas low as 57\u00a2\nBallpoint Letter pricing\tas low as $1.99\tas low as $1.75\tas low as $1.47\nSkip trace pricing\tFREE\tFREE\tFREE\nCorporate skip trace pricing\tFREE\tFREE\tFREE\nDialer\tcheck\tcheck\tcheck\nDialer price per minute\nTry our Unlimited Dialer License\n$99/mo per seat!\n\t$0.06\t$0.05\t$0.04\nAI Voicemail Drop\nTry our Unlimited AI Voicemail License!\n$99/mo per seat!\n\t$0.08\t$0.07\t$0.06\nTake incoming calls/texts\tFREE\tFREE\tFREE\nCall Pool SPAM monitoring\tcheck\tcheck\tcheck\nLitigator Scrub\tcheck\tcheck\tcheck\nLive Transcription\tcheck\tcheck\tcheck\nAI Call Summarization\tcheck\tcheck\tcheck\nAI Call Suggestions\tcheck\tcheck\tcheck\nAutomated Follow-Up Queue\tcheck\tcheck\tcheck\nCall Reporting\tcheck\tcheck\tcheck\nCall Tracking Numbers\t1\t3\t6\nRoute planning\t--\tcheck\tcheck\nCustom mail designs\t--\tcheck\tcheck\nStreet pic\t--\tcheck\tcheck\nMail sequences\t--\tcheck\tcheck\nCustom pipeline\t--\t--\tcheck\n\n\u00a0\n\n\u2709\ufe0f Interested in Bulk Mail? You could receive mail for as low as $.50\n\nClick here to schedule a call with our Head of Customer Success\n\nkeyboard_arrow_right\n\u00a0\n$10,000 Bulk Mail Deposit\n\n\u00a0\n\nSize\n\n\t\n\nPricing\n\n\n\n\n4x6\n\n\t\n\n$0.54\n\n\n\n\n6x9\n\n\t\n\n$0.69\n\n\n\n\n6x11\n\n\t\n\n$0.76\n\n\u00a0\n$15,000 Bulk Mail Deposit\n\n\u00a0\n\nSize\n\n\t\n\nPricing\n\n\n\n\n4x6\n\n\t\n\n$0.52\n\n\n\n\n6x9\n\n\t\n\n$0.67\n\n\n\n\n6x11\n\n\t\n\n$0.76\n\n\u00a0\n$20,000 Bulk Mail Deposit\n\n\u00a0\n\nSize\n\n\t\n\nPricing\n\n\n\n\n4x6\n\n\t\n\n$0.50\n\n\n\n\n6x9\n\n\t\n\n$0.65\n\n\n\n\n6x11\n\n\t\n\n$0.76\n\nYou have questions? We have answers.\n\n\u00a0\n\nadd\n\nWhat is driving for dollars?\n\nadd\n\nWhat is List Builder?\n\nadd\n\nWhat makes DealMachine unique?\n\nadd\n\nWhat is DealMachine Masterclass?\n\nadd\n\nCan I track my routes?\n\nadd\n\nCan I add team members on my account?\n\nadd\n\nCan I control my team members abilities?\n\nadd\n\nWhat does route planning do?\n\nadd\n\nWhere does DealMachine get data from? Is It accurate?\n\nadd\n\nHow often do you update your data?\n\nadd\n\nCan I import my leads into DealMachine?\n\nadd\n\nCan I export or pull data out of DealMachine?\n\nadd\n\nDo I need a CRM to go with DealMachine?\n\nadd\n\nDoes DealMachine support Zapier?\n\nadd\n\nWhat are comps?\n\nadd\n\nWhy do you need my billing info for a free trial?\n\nadd\n\nHow do I cancel? (refund policy)\n\nadd\n\nHow can I contact DealMachine support?\n\nInvest with confidence using the highest-rated real estate investing app.\nBest value investor app ever!6 months ago\nstar\nstar\nstar\nstar\nstar\nThis real estate investment app is top-notch. The live chat support, expert classes, and weekly online meetings are amazing! I'm hooked. Great work!\nUser6 months ago\nstar\nstar\nstar\nstar\nstar\nGreat App. Lots of potential to make $$$\nAccuracy and support6 months ago\nstar\nstar\nstar\nstar\nstar\nDeal machine is the best software for wholesalers, flipper and real estate investors. All information about the home and owners is very accurate and when having any issue their support team is just a click away and take care of questions and issues quickly. I highly recommend Deal Machine!\nReview3 months ago\nstar\nstar\nstar\nstar\nstar\nAre you tired of getting out of your car to locate addresses of vacant houses? I know I was. That\u2019s how I knew deal machine was for me. Now I get to add houses from the comfort of my car! Thank you so much deal machine.\nGreen, seasoned, stuck and wanna grow?? This app will get you where you want to be!!3 months ago\nstar\nstar\nstar\nstar\nstar\nAbsolutely amazing application for investors wholesalers anybody in real estate in all stages of their career weather you\u2019re just getting started like myself or if you already have an up and running business, and wanna take it to the next level. Of course I\u2019m not there yet, but I can\u2019t help to think about the possibilities once I do get there that this app or this tool well allow me to do I could write 10 pages about all the different functions in applications that DealMachine has available, but just on the surface it allows you to To find thousands of leads efficiently, organize them them gives you all the information on the spot about each Property their owner Records Skiptracing cops then gives you the option to do all the marketing in terms of mailers Cold calling. If you\u2019re like me and getting started, I need to drive for dollars you can literally do it from your couch virtually, You can plan out routes so that way you can focus more on the properties as opposed to your route you could do it free I mean, I can go on and on about how awesome this app is if you were able to give 10 stars I would give 11\nDeal Machine is the real deal3 months ago\nstar\nstar\nstar\nstar\nstar\nDeal Machine really makes gathering information about properties very efficient and easy. I\u2019m just starting on the real estate investing journey and between the program and podcast my learning curve has been shortened significantly.\nGreat for Real Estate Investors!!3 months ago\nstar\nstar\nstar\nstar\nstar\nDealmachine makes finding properties for real estate investing easy and fast! It only took minutes to compile a list and send a mailing campaign. The list is neatly organized for me and can be further updated as the lead process goes forward. Support was super helpful in getting me started. Very user friendly!\nEasy to use3 months ago\nstar\nstar\nstar\nstar\nstar\nEasy to use and accurate information!!\nDeal Machine is Great3 months ago\nstar\nstar\nstar\nstar\nstar\nDeal machine is very user friendly and it speeds up the wholesaling process by a large margin. Totally worth the subscription, I recommend to all!\nVery user friendly4 months ago\nstar\nstar\nstar\nstar\nstar\nVery user friendly and customer support responds quickly.\nGreat customer service!4 months ago\nstar\nstar\nstar\nstar\nstar\nReally happy with my experience so far. They are very responsive and helpful!\nDriving for dollars4 months ago\nstar\nstar\nstar\nstar\nstar\nI truly love this app how simple it\u2019s made things like driving for dollars. Find myself pulling over and then tagging a house or neighborhood. Then starting mail and easy follow up later when I get home.\nRevolutionary Real Estate App4 months ago\nstar\nstar\nstar\nstar\nstar\nDeal Machine free skiptracing, accurate ability to filter properties, its intuitive feature and design make it a no brainer compared to other property apps like propstream. We\u2019ve been searching for an all in one software that listens to its users and has support for all user features. Best real estate app for my team!\nInvestor4 months ago\nstar\nstar\nstar\nstar\nstar\nGreat all in one tool\nAmazing App for RE4 months ago\nstar\nstar\nstar\nstar\nstar\nThis app is easy to use and even more features than I have used yet. Driving for dollars is invaluable to have all the info saved in the app as you go!\nReliable Information4 months ago\nstar\nstar\nstar\nstar\nstar\nRecently introduced to Deal Machine. I\u2019m new to real estate investing and this app came highly recommended from various people! Love that the information is so up to date.\nAmazing Starter Resource4 months ago\nstar\nstar\nstar\nstar\nstar\nI\u2019m new to real estate investing but this is such an amazing resource so far! I\u2019ve checked out other platforms and did not like any of them as much as Deal Machine. The information is pretty up to date and accurate, I didn\u2019t find this kind of reliability on other platforms.\nThe Best!4 months ago\nstar\nstar\nstar\nstar\nstar\nBest REI app out there :)\nGreat Tool4 months ago\nstar\nstar\nstar\nstar\nstar\nJust subscribed for the new year and excited about the new features\nGreat4 months ago\nstar\nstar\nstar\nstar\nstar\nGreat tool and great customer support !\nExcellent Application5 months ago\nstar\nstar\nstar\nstar\nstar\nI was recently introduced to this app and love it!! Highly recommend.\nEasy to use5 months ago\nstar\nstar\nstar\nstar\nstar\nThis software offers a lot of options while remaining easy to use. Thank you!\nEverything I need to run my business5 months ago\nstar\nstar\nstar\nstar\nstar\nMyself and other investors in my network all use Deal Machine to run our real estate businesses. Deal machine offers everything I need - lists, slip testing, Driving for Dollars, AI Assisted Dialing - you name it. It\u2019s super convenient to have everything I need one platform that\u2019s simple and easy to use. On top of that, their customer service is unmatched, and they are always innovating to improve the user experience. Thank you Deal Machine!\nGreat app5 months ago\nstar\nstar\nstar\nstar\nstar\nGreat app, I use it both for driving for dollars and for finding property leads using the integrative map feature.\n5 stars5 months ago\nstar\nstar\nstar\nstar\nstar\nGreat tool\nDealMachine rocks!5 months ago\nstar\nstar\nstar\nstar\nstar\nThe guys have it dialed in! Software works great and customer service is top notch.\nLove this app5 months ago\nstar\nstar\nstar\nstar\nstar\nIt\u2019s great\nBy far the best driving for dollars app5 months ago\nstar\nstar\nstar\nstar\nstar\nI love using this app to drive for dollars and send mailers. Automates my marketing and brings me inbound leads without harassing people.\nGreat Technology for Real Estate5 months ago\nstar\nstar\nstar\nstar\nstar\nI have been a real estate investor for a handful of years and have used DealMachine for the past year. In my opinion, DealMachine is becoming the most comprehensive data/skip trace/dialer/CRM is one.\nAmazing app!5 months ago\nstar\nstar\nstar\nstar\nstar\nDeal machine is a one stop shop. From lead details, lead management, and dialer I couldn\u2019t be happier!\nDriving 4 $$$5 months ago\nstar\nstar\nstar\nstar\nstar\nThis is the best app to be created.\nDeal Machine App5 months ago\nstar\nstar\nstar\nstar\nstar\nThis is a great app to use!!It has same me time and energy. Thank you Deal Machine for such a great product!!\nAmazing5 months ago\nstar\nstar\nstar\nstar\nstar\nThis shortens the time spent looking for needed info, and the unlimited leads is much less expensive than other lead sources. well done.\nGreat app5 months ago\nstar\nstar\nstar\nstar\nstar\nGreat app!\nMoney Machine5 months ago\nstar\nstar\nstar\nstar\nstar\nDeal machine is a money making platform for Wholesalers when used correctly. The Skip-tracing is the best with very accurate data. The D4$ is a great tool.\nDealMachine Is Adding New Things!5 months ago\nstar\nstar\nstar\nstar\nstar\nI am excited to have upgraded to the DealMachine Pro Version. Although I haven\u2019t used all of the features yet, I was able to cancel 2 other programs that I was paying for. Nearly everything I needed, is in this program. James (in Support) is great. Ryan & Elise are good teachers. One of the best decisions I have ever made, for a real estate software program.\nLots of tools at your disposal5 months ago\nstar\nstar\nstar\nstar\nstar\nI absolutely love the AI dailer. Helps you keep track of your conversation and leads. The post cards are a great addition so far haven\u2019t had much luck yet but I will \ud83d\udc4d\ud83c\udffd\ud83d\udc4d\ud83c\udffd\nGreat for analyzing and cold calling5 months ago\nstar\nstar\nstar\nstar\nstar\nI have been really happy with this app for the last year. They have now added an AI dialer, which is really cool. I like the driving for dollars feature as well.\nGreat app but few bugs5 months ago\nstar\nstar\nstar\nstar\nstar\nI love this app and its most definitely my favorite software to use. But the only thing is that it has a few bugs that I and maybe some others don\u2019t enjoy. It sometimes lags out and I have to keep refreshing the app. It won\u2019t let me press the buttons to call nor copy the address. Please fix this problem for the future and fix it for us. Thank you deal machine. Yall are great. \ud83e\udd19\ud83e\udd19\nDeal machine rocks6 months ago\nstar\nstar\nstar\nstar\nstar\nGreat service user friendly and awesome tech support\nEasy to use6 months ago\nstar\nstar\nstar\nstar\nstar\nFull of great information and very user friendly.\nEasy Using App6 months ago\nstar\nstar\nstar\nstar\nstar\nActually enjoy using the app. Very user friendly. What\u2019s even better is that the customer service is really responsive if you need help with anything. Definitely worth getting.\nGreat program !!6 months ago\nstar\nstar\nstar\nstar\nstar\nLove this program!! It does everything you can think of !!\nThe DealMachine for real estate investors6 months ago\nstar\nstar\nstar\nstar\nstar\nThe DealMachine is the greatest piece of equipment. I could\u2019ve added to my investment journey. It\u2019s an all-in-one tool that is easy to use. Once you have the DealMachine, you don\u2019t have to use any other platform in real estate. David Leko has made this so simple for you. If if it was any simpler, he\u2019d be doing it for you. The only way you won\u2019t be successful with the DealMachine is if you don\u2019t use it.\nFirst appointment6 months ago\nstar\nstar\nstar\nstar\nstar\nI used PropStream for about a month and was receiving a lot of wrong numbers. I then switched to DealMachine and within the first week I set my first wholesale appointment. I made an offer to the seller and waiting for her acceptance, which hopefully will happen tomorrow. Highly recommended DealMachine over PropStream.\nBest value investor app ever!6 months ago\nstar\nstar\nstar\nstar\nstar\nThis real estate investment app is top-notch. The live chat support, expert classes, and weekly online meetings are amazing! I'm hooked. Great work!\nUser6 months ago\nstar\nstar\nstar\nstar\nstar\nGreat App. Lots of potential to make $$$\nAccuracy and support6 months ago\nstar\nstar\nstar\nstar\nstar\nDeal machine is the best software for wholesalers, flipper and real estate investors. All information about the home and owners is very accurate and when having any issue their support team is just a click away and take care of questions and issues quickly. I highly recommend Deal Machine!\nReview3 months ago\nstar\nstar\nstar\nstar\nstar\nAre you tired of getting out of your car to locate addresses of vacant houses? I know I was. That\u2019s how I knew deal machine was for me. Now I get to add houses from the comfort of my car! Thank you so much deal machine.\nGreen, seasoned, stuck and wanna grow?? This app will get you where you want to be!!3 months ago\nstar\nstar\nstar\nstar\nstar\nAbsolutely amazing application for investors wholesalers anybody in real estate in all stages of their career weather you\u2019re just getting started like myself or if you already have an up and running business, and wanna take it to the next level. Of course I\u2019m not there yet, but I can\u2019t help to think about the possibilities once I do get there that this app or this tool well allow me to do I could write 10 pages about all the different functions in applications that DealMachine has available, but just on the surface it allows you to To find thousands of leads efficiently, organize them them gives you all the information on the spot about each Property their owner Records Skiptracing cops then gives you the option to do all the marketing in terms of mailers Cold calling. If you\u2019re like me and getting started, I need to drive for dollars you can literally do it from your couch virtually, You can plan out routes so that way you can focus more on the properties as opposed to your route you could do it free I mean, I can go on and on about how awesome this app is if you were able to give 10 stars I would give 11\nDeal Machine is the real deal3 months ago\nstar\nstar\nstar\nstar\nstar\nDeal Machine really makes gathering information about properties very efficient and easy. I\u2019m just starting on the real estate investing journey and between the program and podcast my learning curve has been shortened significantly.\nGreat for Real Estate Investors!!3 months ago\nstar\nstar\nstar\nstar\nstar\nDealmachine makes finding properties for real estate investing easy and fast! It only took minutes to compile a list and send a mailing campaign. The list is neatly organized for me and can be further updated as the lead process goes forward. Support was super helpful in getting me started. Very user friendly!\nEasy to use3 months ago\nstar\nstar\nstar\nstar\nstar\nEasy to use and accurate information!!\nDeal Machine is Great3 months ago\nstar\nstar\nstar\nstar\nstar\nDeal machine is very user friendly and it speeds up the wholesaling process by a large margin. Totally worth the subscription, I recommend to all!\nVery user friendly4 months ago\nstar\nstar\nstar\nstar\nstar\nVery user friendly and customer support responds quickly.\nGreat customer service!4 months ago\nstar\nstar\nstar\nstar\nstar\nReally happy with my experience so far. They are very responsive and helpful!\nDriving for dollars4 months ago\nstar\nstar\nstar\nstar\nstar\nI truly love this app how simple it\u2019s made things like driving for dollars. Find myself pulling over and then tagging a house or neighborhood. Then starting mail and easy follow up later when I get home.\nRevolutionary Real Estate App4 months ago\nstar\nstar\nstar\nstar\nstar\nDeal Machine free skiptracing, accurate ability to filter properties, its intuitive feature and design make it a no brainer compared to other property apps like propstream. We\u2019ve been searching for an all in one software that listens to its users and has support for all user features. Best real estate app for my team!\nInvestor4 months ago\nstar\nstar\nstar\nstar\nstar\nGreat all in one tool\nAmazing App for RE4 months ago\nstar\nstar\nstar\nstar\nstar\nThis app is easy to use and even more features than I have used yet. Driving for dollars is invaluable to have all the info saved in the app as you go!\nReliable Information4 months ago\nstar\nstar\nstar\nstar\nstar\nRecently introduced to Deal Machine. I\u2019m new to real estate investing and this app came highly recommended from various people! Love that the information is so up to date.\nAmazing Starter Resource4 months ago\nstar\nstar\nstar\nstar\nstar\nI\u2019m new to real estate investing but this is such an amazing resource so far! I\u2019ve checked out other platforms and did not like any of them as much as Deal Machine. The information is pretty up to date and accurate, I didn\u2019t find this kind of reliability on other platforms.\nThe Best!4 months ago\nstar\nstar\nstar\nstar\nstar\nBest REI app out there :)\nGreat Tool4 months ago\nstar\nstar\nstar\nstar\nstar\nJust subscribed for the new year and excited about the new features\nGreat4 months ago\nstar\nstar\nstar\nstar\nstar\nGreat tool and great customer support !\nExcellent Application5 months ago\nstar\nstar\nstar\nstar\nstar\nI was recently introduced to this app and love it!! Highly recommend.\nEasy to use5 months ago\nstar\nstar\nstar\nstar\nstar\nThis software offers a lot of options while remaining easy to use. Thank you!\nEverything I need to run my business5 months ago\nstar\nstar\nstar\nstar\nstar\nMyself and other investors in my network all use Deal Machine to run our real estate businesses. Deal machine offers everything I need - lists, slip testing, Driving for Dollars, AI Assisted Dialing - you name it. It\u2019s super convenient to have everything I need one platform that\u2019s simple and easy to use. On top of that, their customer service is unmatched, and they are always innovating to improve the user experience. Thank you Deal Machine!\nGreat app5 months ago\nstar\nstar\nstar\nstar\nstar\nGreat app, I use it both for driving for dollars and for finding property leads using the integrative map feature.\n5 stars5 months ago\nstar\nstar\nstar\nstar\nstar\nGreat tool\nDealMachine rocks!5 months ago\nstar\nstar\nstar\nstar\nstar\nThe guys have it dialed in! Software works great and customer service is top notch.\nLove this app5 months ago\nstar\nstar\nstar\nstar\nstar\nIt\u2019s great\nBy far the best driving for dollars app5 months ago\nstar\nstar\nstar\nstar\nstar\nI love using this app to drive for dollars and send mailers. Automates my marketing and brings me inbound leads without harassing people.\nGreat Technology for Real Estate5 months ago\nstar\nstar\nstar\nstar\nstar\nI have been a real estate investor for a handful of years and have used DealMachine for the past year. In my opinion, DealMachine is becoming the most comprehensive data/skip trace/dialer/CRM is one.\nAmazing app!5 months ago\nstar\nstar\nstar\nstar\nstar\nDeal machine is a one stop shop. From lead details, lead management, and dialer I couldn\u2019t be happier!\nDriving 4 $$$5 months ago\nstar\nstar\nstar\nstar\nstar\nThis is the best app to be created.\nDeal Machine App5 months ago\nstar\nstar\nstar\nstar\nstar\nThis is a great app to use!!It has same me time and energy. Thank you Deal Machine for such a great product!!\nAmazing5 months ago\nstar\nstar\nstar\nstar\nstar\nThis shortens the time spent looking for needed info, and the unlimited leads is much less expensive than other lead sources. well done.\nGreat app5 months ago\nstar\nstar\nstar\nstar\nstar\nGreat app!\nMoney Machine5 months ago\nstar\nstar\nstar\nstar\nstar\nDeal machine is a money making platform for Wholesalers when used correctly. The Skip-tracing is the best with very accurate data. The D4$ is a great tool.\nDealMachine Is Adding New Things!5 months ago\nstar\nstar\nstar\nstar\nstar\nI am excited to have upgraded to the DealMachine Pro Version. Although I haven\u2019t used all of the features yet, I was able to cancel 2 other programs that I was paying for. Nearly everything I needed, is in this program. James (in Support) is great. Ryan & Elise are good teachers. One of the best decisions I have ever made, for a real estate software program.\nLots of tools at your disposal5 months ago\nstar\nstar\nstar\nstar\nstar\nI absolutely love the AI dailer. Helps you keep track of your conversation and leads. The post cards are a great addition so far haven\u2019t had much luck yet but I will \ud83d\udc4d\ud83c\udffd\ud83d\udc4d\ud83c\udffd\nGreat for analyzing and cold calling5 months ago\nstar\nstar\nstar\nstar\nstar\nI have been really happy with this app for the last year. They have now added an AI dialer, which is really cool. I like the driving for dollars feature as well.\nGreat app but few bugs5 months ago\nstar\nstar\nstar\nstar\nstar\nI love this app and its most definitely my favorite software to use. But the only thing is that it has a few bugs that I and maybe some others don\u2019t enjoy. It sometimes lags out and I have to keep refreshing the app. It won\u2019t let me press the buttons to call nor copy the address. Please fix this problem for the future and fix it for us. Thank you deal machine. Yall are great. \ud83e\udd19\ud83e\udd19\nDeal machine rocks6 months ago\nstar\nstar\nstar\nstar\nstar\nGreat service user friendly and awesome tech support\nEasy to use6 months ago\nstar\nstar\nstar\nstar\nstar\nFull of great information and very user friendly.\nEasy Using App6 months ago\nstar\nstar\nstar\nstar\nstar\nActually enjoy using the app. Very user friendly. What\u2019s even better is that the customer service is really responsive if you need help with anything. Definitely worth getting.\nGreat program !!6 months ago\nstar\nstar\nstar\nstar\nstar\nLove this program!! It does everything you can think of !!\nThe DealMachine for real estate investors6 months ago\nstar\nstar\nstar\nstar\nstar\nThe DealMachine is the greatest piece of equipment. I could\u2019ve added to my investment journey. It\u2019s an all-in-one tool that is easy to use. Once you have the DealMachine, you don\u2019t have to use any other platform in real estate. David Leko has made this so simple for you. If if it was any simpler, he\u2019d be doing it for you. The only way you won\u2019t be successful with the DealMachine is if you don\u2019t use it.\nFirst appointment6 months ago\nstar\nstar\nstar\nstar\nstar\nI used PropStream for about a month and was receiving a lot of wrong numbers. I then switched to DealMachine and within the first week I set my first wholesale appointment. I made an offer to the seller and waiting for her acceptance, which hopefully will happen tomorrow. Highly recommended DealMachine over PropStream.\nBest value investor app ever!6 months ago\nstar\nstar\nstar\nstar\nstar\nThis real estate investment app is top-notch. The live chat support, expert classes, and weekly online meetings are amazing! I'm hooked. Great work!\nUser6 months ago\nstar\nstar\nstar\nstar\nstar\nGreat App. Lots of potential to make $$$\nAccuracy and support6 months ago\nstar\nstar\nstar\nstar\nstar\nDeal machine is the best software for wholesalers, flipper and real estate investors. All information about the home and owners is very accurate and when having any issue their support team is just a click away and take care of questions and issues quickly. I highly recommend Deal Machine!\nReal Estate At Your Fingertips.\n\nUnlock your full potential and build generational wealth with the app that gives you the power of real estate.\n\nGet Started\narrow_right_alt\n\nCompany\n\nAbout Us\nRelease Notes\nFeature Request\nBrand\nStatus\n\nResources\n\nHelp Docs\nContact Us\nImport Leads\nAPI\nPartners\nMedia\n\nTools\n\nBRRRR Calculator\nReal Estate Comps Tool\n\nFeatures\n\nDriving For Dollars\nList Builder\nUnlimited Contact Info\nAI-Powered Dialer\nMarketing Automation\nReal Estate AI Assistant\nSee All Features\nDemo\n\nSolutions\n\nWholesaling\nFix & Flip\n\nCompare\n\nvs Propstream\nvs BatchLeads\n\nLearn\n\nCommunity\nBlog\nMasterclass\n@ 2025 DealMachine Holdings L.L.C.\nPrivacy Policy\nTerms of Service\n801 Shelby St, Indianapolis, IN 46203\n\nFind your perfect real estate plan with DealMachine. Get a free 7-day trial and achieve your investment goals with the right plan for your journey.",
      "error": null,
      "pricing_data": {
        "app_id": "dealmachine",
        "app_name": "DealMachine",
        "app_slug": "dealmachine",
        "pricing_url": "https://dealmachine.com/pricing",
        "source_url": null,
        "all_pricing_urls": [
          "https://dealmachine.com/pricing"
        ],
        "price_model_type": [
          "PriceModelType.SUBSCRIPTION",
          "PriceModelType.USAGE_BASED"
        ],
        "has_free_tier": false,
        "has_free_trial": true,
        "free_trial_period_days": null,
        "currency": "USD",
        "is_pricing_public": true,
        "pricing_page_accessible": true,
        "pricing_notes": "Annual billing offers a 17% discount. Additional licenses for AI Dialer and Voicemail are available at $99/month each.",
        "pricing_tiers": [
          {
            "tier_name": "Starter",
            "tier_description": "Just getting started? Want to try things out? Start here.",
            "monthly_price": 99.0,
            "annual_price": 1190.0,
            "annual_discount_percentage": 17.0,
            "setup_fee": null,
            "features": [
              "1 user",
              "Unlimited contact info, phone numbers, and email addresses",
              "Up to 20,000 leads",
              "10,000 leads exported per month",
              "Driving for dollars",
              "AI-Powered Dialer access",
              "AI Voicemail drops",
              "1 call tracking number",
              "MLS & county comps",
              "Daily data updates",
              "Mail as low as 67\u00a2"
            ],
            "limits": {
              "users": 1,
              "storage": null,
              "operations": null,
              "api_calls": null,
              "integrations": null,
              "custom_limits": [
                {
                  "name": "Leads",
                  "value": 20000
                },
                {
                  "name": "Exported Leads per Month",
                  "value": 10000
                }
              ]
            }
          },
          {
            "tier_name": "Pro",
            "tier_description": "Built for small teams with big goals.",
            "monthly_price": 149.0,
            "annual_price": 1790.0,
            "annual_discount_percentage": 17.0,
            "setup_fee": null,
            "features": [
              "Everything included in Starter",
              "3 users",
              "Up to 60,000 leads",
              "30,000 exported leads per month exports",
              "3 call tracking numbers",
              "Real estate AI assistant",
              "Route planning",
              "Mail sequences",
              "Custom mail designer",
              "Curbside view of properties from Google street view on your mail.",
              "10 Custom Fields",
              "Mail as low as 62\u00a2"
            ],
            "limits": {
              "users": 3,
              "storage": null,
              "operations": null,
              "api_calls": null,
              "integrations": null,
              "custom_limits": [
                {
                  "name": "Leads",
                  "value": 60000
                },
                {
                  "name": "Exported Leads per Month",
                  "value": 30000
                }
              ]
            }
          },
          {
            "tier_name": "Pro Plus",
            "tier_description": "Built for pros who need that extra edge to win.",
            "monthly_price": 232.0,
            "annual_price": 2790.0,
            "annual_discount_percentage": 17.0,
            "setup_fee": null,
            "features": [
              "Everything included in Pro",
              "6 users",
              "Up to 120,000 leads",
              "60,000 exported leads per month",
              "6 call tracking number",
              "Driver recruitment tools",
              "Custom deal pipeline",
              "25 custom fields",
              "Mail as low as 57\u00a2"
            ],
            "limits": {
              "users": 6,
              "storage": null,
              "operations": null,
              "api_calls": null,
              "integrations": null,
              "custom_limits": [
                {
                  "name": "Leads",
                  "value": 120000
                },
                {
                  "name": "Exported Leads per Month",
                  "value": 60000
                }
              ]
            }
          }
        ],
        "usage_based_pricing": [
          {
            "metric_name": "AI Dialer",
            "unit": "per minute",
            "base_price": 0.06,
            "tiers": [
              {
                "min": 0.0,
                "max": 1000.0,
                "price": 0.06
              },
              {
                "min": 1001.0,
                "max": 5000.0,
                "price": 0.05
              },
              {
                "min": 5001.0,
                "max": "unlimited",
                "price": 0.04
              }
            ]
          },
          {
            "metric_name": "AI Voicemail Drop",
            "unit": "per drop",
            "base_price": 0.08,
            "tiers": [
              {
                "min": 0.0,
                "max": 1000.0,
                "price": 0.08
              },
              {
                "min": 1001.0,
                "max": 5000.0,
                "price": 0.07
              },
              {
                "min": 5001.0,
                "max": "unlimited",
                "price": 0.06
              }
            ]
          }
        ],
        "ai_specific_pricing": {
          "has_token_based_pricing": false,
          "input_token_price": null,
          "output_token_price": null,
          "models_pricing": null,
          "has_inference_pricing": false,
          "has_fine_tuning_pricing": false,
          "has_training_pricing": false,
          "ai_addon_available": true
        },
        "promotional_offers": null,
        "additional_fees": [
          {
            "fee_name": "Bulk Mail Deposit",
            "fee_amount": 10000.0,
            "fee_description": "Deposit for bulk mail services, pricing varies by size."
          }
        ],
        "extraction_timestamp": "2025-04-15T10:07:59.432943",
        "schema_validated": true,
        "confidence_score": 95,
        "extraction_error": false,
        "json_repaired": false
      },
      "pricing_analyzed": true
    }
  ],
  "results_directory": "pricing_results\\dealmachine\\20250415_100759"
}