{
  "app_name": "OneSignal",
  "app_slug": "onesignal",
  "search_term": "Find the official pricing page URL for OneSignal (onesignal.com). Only provide the exact URL to the pricing page, not a summary of pricing information.",
  "timestamp": 1744712082.6749938,
  "response_text": [
    "The official pricing page for OneSignal is: [https://onesignal.com/pricing](https://onesignal.com/pricing)\u30103:0\u2020source\u3011."
  ],
  "citations": [
    {
      "title": "Pricing - OneSignal",
      "url": "https://onesignal.com/pricing"
    }
  ],
  "extracted_content": [
    {
      "url": "https://onesignal.com/pricing",
      "is_accessible": true,
      "content": "Skip to Content\nProduct\nMessaging Channels\nMobile Push Notifications\nDirect, highly visible, mobile-first\nWeb Push Notifications\nDirect, reach any browser visit\nEmail\nPowerful composer, accessible anywhere\nIn-App Messaging\nVisual, customizable, reach all app users\nSMS\nEffective, fast, mobile-first\nLive Activities\nHighlight real-time app updates\nFeatures\nJourneys \nPersonalization\nSegmentation\nAnalytics\nAPI\nSDKs\nIntegrations Directory\nView More Features \nIndustries\nGaming\nNews/Media\neCommerce\nMobile Apps\nFintech/Financial\nResources\nResources\neBooks\nCustomer Case Studies\nVideos\nPodcasts\nTools & Templates\nEvents\nView All Resources \nMore to Explore\nBlog\nUse Cases\nDemo Videos\nNotification Preview Tool\nSignal Boosters Community\nOneSignal Solution Partners\nGlossary\nDocumentation\nPricing\nLog in\nTalk to sales\nGet started now\nTransparent pricing for every stage of growth\n\nChoose the right plan for your business\n\nFree\nPowerful essentials for\nsmall businesses\n$0 / Month\nFree access to all channels\nMessage limits may apply\nGet Started Now\nFree access to:\n10,000/mth Free Email Sends\nUnlimited Mobile Push Sends\nJourneys Workflows\nGDPR Compliant\nA/B Testing\nGrowth\nFundamentals to help\nstartups scale\nStarts at $9 / Month\nPlus usage costs by channel\nEstimate your monthly cost\nGet Started Now\nAll features from Free +\n20,000/mth Free Email Sends\nAdvanced In-App Messaging\nJourneys Branching\nIntelligent Delivery\nExpanded Integrations\nProfessional\nAdvanced features to\ndrive conversions\nCustom\nPricing by channel\nVolume-based discounting available\nContact Sales\nAll features from Growth +\n24/7 Prioritized Support\nCSV Exports\nAdvanced Journeys\nAdvanced Personalization\nCustom Outcome Tracking\nEnterprise\nUltimate control and support\nfor businesses\nCustom\nTailored contract & features\nVolume-based discounting available\nContact Sales\nAll features from Professional +\nFrequency Capping\nFull Live Activities Access\nSecurity/Legal Package + SLA\nDedicated Success Manager\nAdvanced User Permissions\nComprehensive feature breakdown\n\nCompare the features and benefits of each plan\n\nDeveloper Friendly Pricing\n\t\nFree\n$0 / Month\nGet Started Now\n\t\nGrowth\nStarts at $9 / Month\nGet Started Now\n\t\nProfessional\nCustom\nContact Sales\n\t\nEnterprise\nCustom\nContact Sales\nMessaging channels\nMobile Push Notifications\nUnlimited mobile push\n$0.012 per monthly active user\nCustom\nCustom\nWeb Push Notifications\nMax 10,000 subscribers per send\n$0.004 per web push subscriber\nCustom\nCustom\nIn-App Messaging\n1 active message\nUnlimited, included with mobile push\nCustom\nCustom\nEmail\n10,000 free sends / month\n20,000 free sends / month, then $2 / 1,000 sends\nCustom\nCustom\nSMS\nTalk to Sales to discuss trial or pricing.\nLive Activities\nMax 10,000 total push subscribers\nMax 100,000 total push subscribers\nCustom\nCustom\nJourneys\nActive Journeys\n1\n3\n20\nCustom\nMessage Steps\n2\n6\n50\nCustom\nBranching\n\u2014\nCross-channel flows\nQuickstart Journeys\nTag users\nVisual workflow builder\nNo-code and HTML message builders\nWebhooks Steps\nAvailable on annual plans. Talk to Sales to discuss pricing.\nMessage personalization\nAudience Segments\n6\n10\n20\nCustom\nData Tags\n2\n10\n100\nCustom\nProduct features\nContacts\nUnlimited\nUnlimited\nUnlimited\nUnlimited\nAPI Send Access\nUnlimited\nUnlimited\nUnlimited\nUnlimited\nA/B Testing\nBasic\nBasic\nAdvanced\nAdvanced\nPersonalized Notifications\nTimezone Delivery\nCategory Opt In Prompt\nHTML Editor\nCustom Data Uploads\nEmail Auto Warm Up\nDynamic Content\nIntelligent Delivery\n\u2014\nTime Delayed Sends\n\u2014\nConfirmed Deliveries\n\u2014\nMessage Throttling\n\u2014\nPush & SMS Retargeting\n\u2014\nIn-App Carousel Messages\n\u2014\nAdvanced Analytics\n\u2014\n\u2014\nCustom Outcome Tracking\n\u2014\n\u2014\nNotification Data Exports (CSV)\n\u2014\n\u2014\nNotification History API\n\u2014\n\u2014\nUser Activity Timeline\n\u2014\n\u2014\nFrequency Capping\n\u2014\n\u2014\n\u2014\nEmail IPs\nShared IP Only\nShared IP Only\nDedicated IP available based on volume\nDedicated IP available based on volume\nEvent Streams\nLimited\nEssential\nCustom\nCustom\nIntegrations\n30+ Core\n30+ Core plus\n   \n30+ Core plus\n   \n30+ Core plus\n   \nPremium Integrations\n\u2014\n\u2014\nAvailable for Purchase\n  \nAvailable for Purchase\n  \nSecurity & compliance\nUser Permissions\nAdmin\nAdmin + Viewer\nAll roles\nAll roles\nData Retention\nLimited\nFull\nFull\nFull\nGDPR Compliance\nCompliant\nCompliant w/ DPA\nCompliant w/ DPA\nCompliant w/ DPA\nData Protection\nTwo-Factor Authentication\nCustom Security & Legal Package\n\u2014\n\u2014\nTalk to Sales\nService Level Agreement (SLA)\n\u2014\n\u2014\n\u2014\nAvailable\nCustomer support\nOngoing Support\nEmail\nPrioritized Email\n24/7 Prioritized Email\n24/7 Prioritized Email & SRE On Call Support\nJump Start Onboarding Support\n\u2014\n\u2014\nTalk to Sales\nTalk to Sales\nDedicated Success Manager\n\u2014\n\u2014\n\u2014\nGrowth plan cost calculator\nMobile push notifications\nMobile users active in the last 30 days\nWeb push notifications\nWeb push subscribers\nEmail\nEmail campaigns per month\nTarget audience size for email campaigns\nNumber of email sends\n0\nIn-app messaging\n\nFree and unlimited w/ mobile push\n\nSMS\n\nTalk to sales\n\nYour cost breakdown\nGrowth plan\n\nPlatform cost\n\n$9.00\nMessaging channels\n\nMobile push notifications\n\n$0.00\n\nWeb push notifications\n\n$0.00\n\nEmail\n\n$0.00\n\nIn-app messaging\n\nIncluded w/ mobile push\n\nSMS\n\nTalk to sales\n\nTotal estimated cost per month\n\n$9.00\nFrequently asked questions\nWhich plan should I choose?\nHow do you charge?\nWhat is a monthly active user (MAU) for mobile push?\nWhat is a web push subscriber?\nHow do I upgrade my plan?\nHow can I pay?\nCan I pay in my local currency?\nWhat if I decide to downgrade or cancel?\nWhat is your data retention policy?\nWhat is an in-app message impression?\nGet started today for free with our platform\n\nGet going in a matter of minutes\n\nGet started now Talk to sales\n\nProduct\nMobile Push Notifications\nWeb Push Notifications\nEmail\nIn-App Messaging\nSMS\nLive Activities\nJourneys\nIntegrations Directory\nPricing\nResources\nResources Library\nCustomer Case Studies\nBlog\nNotification Preview Tool\nSignal Boosters Community\nGlossary\nDevelopers\nDocumentation\nGitHub\nCode Samples\nDeveloper Community\nBeta Program\nStatus\nCompany\nAbout Us\nCareers\nWhy OneSignal?\nContact Sales\nNewsroom\nPartner Program\nCustomer Referral Program\n\nOneSignal is the market leading customer engagement solution for push notifications, email, SMS, in-app messaging, and Live Activities\n\nPrivacy\nTerms of Use\nAcceptable Use Policy\nSoftware Lifecycle Policy\nBack to top\n\nStart with 10,000 free emails, free unlimited mobile push, and 10,000 free web push. Let\u2019s find a plan that\u2019s right for you.",
      "error": null,
      "pricing_data": {
        "app_id": "onesignal",
        "app_name": "OneSignal",
        "app_slug": "onesignal",
        "pricing_url": "https://onesignal.com/pricing",
        "source_url": null,
        "all_pricing_urls": [
          "https://onesignal.com/pricing"
        ],
        "price_model_type": [
          "PriceModelType.SUBSCRIPTION",
          "PriceModelType.USAGE_BASED",
          "PriceModelType.FREE_TIER",
          "PriceModelType.QUOTE_BASED"
        ],
        "has_free_tier": true,
        "has_free_trial": false,
        "free_trial_period_days": null,
        "currency": "USD",
        "is_pricing_public": true,
        "pricing_page_accessible": true,
        "pricing_notes": "Pricing includes free tier, subscription plans, and usage-based costs for specific features.",
        "pricing_tiers": [
          {
            "tier_name": "Free",
            "tier_description": "Powerful essentials for small businesses",
            "monthly_price": 0.0,
            "annual_price": null,
            "annual_discount_percentage": null,
            "setup_fee": null,
            "features": [
              "Free access to all channels",
              "10,000/mth Free Email Sends",
              "Unlimited Mobile Push Sends",
              "Journeys Workflows",
              "GDPR Compliant",
              "A/B Testing"
            ],
            "limits": {
              "users": "unlimited",
              "storage": "unlimited",
              "operations": "unlimited",
              "api_calls": "unlimited",
              "integrations": "30+ Core",
              "custom_limits": [
                {
                  "name": "Email Sends",
                  "value": "10,000/mth"
                },
                {
                  "name": "Mobile Push Sends",
                  "value": "unlimited"
                }
              ]
            }
          },
          {
            "tier_name": "Growth",
            "tier_description": "Fundamentals to help startups scale",
            "monthly_price": 9.0,
            "annual_price": null,
            "annual_discount_percentage": null,
            "setup_fee": null,
            "features": [
              "All features from Free",
              "20,000/mth Free Email Sends",
              "Advanced In-App Messaging",
              "Journeys Branching",
              "Intelligent Delivery",
              "Expanded Integrations"
            ],
            "limits": {
              "users": "unlimited",
              "storage": "unlimited",
              "operations": "unlimited",
              "api_calls": "unlimited",
              "integrations": "30+ Core plus",
              "custom_limits": [
                {
                  "name": "Email Sends",
                  "value": "20,000/mth"
                }
              ]
            }
          },
          {
            "tier_name": "Professional",
            "tier_description": "Advanced features to drive conversions",
            "monthly_price": null,
            "annual_price": null,
            "annual_discount_percentage": null,
            "setup_fee": null,
            "features": [
              "All features from Growth",
              "24/7 Prioritized Support",
              "CSV Exports",
              "Advanced Journeys",
              "Advanced Personalization",
              "Custom Outcome Tracking"
            ],
            "limits": {
              "users": "unlimited",
              "storage": "unlimited",
              "operations": "unlimited",
              "api_calls": "unlimited",
              "integrations": "30+ Core plus",
              "custom_limits": null
            }
          },
          {
            "tier_name": "Enterprise",
            "tier_description": "Ultimate control and support for businesses",
            "monthly_price": null,
            "annual_price": null,
            "annual_discount_percentage": null,
            "setup_fee": null,
            "features": [
              "All features from Professional",
              "Frequency Capping",
              "Full Live Activities Access",
              "Security/Legal Package + SLA",
              "Dedicated Success Manager",
              "Advanced User Permissions"
            ],
            "limits": {
              "users": "unlimited",
              "storage": "unlimited",
              "operations": "unlimited",
              "api_calls": "unlimited",
              "integrations": "30+ Core plus",
              "custom_limits": null
            }
          }
        ],
        "usage_based_pricing": [
          {
            "metric_name": "Mobile Push Notifications",
            "unit": "per monthly active user",
            "base_price": 0.012,
            "tiers": null
          },
          {
            "metric_name": "Web Push Notifications",
            "unit": "per web push subscriber",
            "base_price": 0.004,
            "tiers": null
          },
          {
            "metric_name": "Email",
            "unit": "per 1,000 sends",
            "base_price": 2.0,
            "tiers": null
          }
        ],
        "ai_specific_pricing": null,
        "promotional_offers": null,
        "additional_fees": null,
        "extraction_timestamp": "2025-04-15T06:15:02.432499",
        "schema_validated": true,
        "confidence_score": 100,
        "extraction_error": false,
        "json_repaired": false
      },
      "pricing_analyzed": true
    }
  ],
  "results_directory": "pricing_results\\onesignal\\20250415_061502"
}