{
  "app_name": "Lawmatics",
  "app_slug": "lawmatics",
  "search_term": "Find the official pricing page URL for Lawmatics (lawmatics.com). Only provide the exact URL to the pricing page, not a summary of pricing information.",
  "timestamp": 1744714442.5872698,
  "response_text": [
    "The official pricing page for Lawmatics is available at: [https://www.lawmatics.com/pricing](https://www.lawmatics.com/pricing)\u30103:0\u2020source\u3011."
  ],
  "citations": [
    {
      "title": "Pricing - Lawmatics",
      "url": "https://www.lawmatics.com/pricing/"
    }
  ],
  "extracted_content": [
    {
      "url": "https://www.lawmatics.com/pricing",
      "is_accessible": true,
      "content": "Your practice, your\u00a0pricing\n---------------------------\n\nLet's find your perfect fit.\n\n*   Essential\n    ---------\n    \n    For firms striving to boost client capacity while operating at peak efficiency.\n    \n    [Get pricing](https://www.lawmatics.com/demo-essential/)\n    \n    ### What's included:\n    \n    *   Client intake\n        \n    *   Lead management\n        \n    *   Calendaring\n        \n    *   Custom forms\n        \n    *   Task management\n        \n    *   2,500 contacts\\*\n        \n    *   50 e-signatures\n        \n    *   250 text messages\\*\n        \n    \n*   Most popular\n    \n    Premium\n    -------\n    \n    For firms targeting rapid growth, record high profitability, and market leadership.\n    \n    [Get pricing](https://www.lawmatics.com/demo-premium/)\n    \n    ### What's included:\n    \n    *   Every feature in Essential\n        \n    *   Unlimited automations\n        \n    *   Email marketing campaigns\n        \n    *   Advanced conflict checking\n        \n    *   ROI tracking &\u00a0analysis\n        \n    *   Custom dashboards\n        \n    *   Event management\n        \n    *   10,000 contacts\\*\n        \n    *   Unlimited e-signatures\n        \n    *   750 text messages\\*\n        \n    \n*   Enterprise\n    ----------\n    \n    Talk to us for a comprehensive solution that meets all your large-scale cross\u2011functional needs.\n    \n    [Get pricing](https://www.lawmatics.com/demo-enterprise/)\n    \n    ### What's included:\n    \n    *   Custom pricing\n        \n    *   Full access to all features\n        \n    *   Dedicated account manager\n        \n    \n    Time & Billing\n    \n    Time tracking, data insights, client management, payment processing, and invoicing \u2014 applicable to any plan.\n    \n    [Contact sales](https://www.lawmatics.com/demo)\n    \n\n\\*Additional contacts and texts sold separately.\n\nLawmatics integrates with the apps you use every day  \n\n-------------------------------------------------------\n\n![Image 1: David Lehr](blob:http://localhost/e8a57f4972516a1d3218894eabc89576)\n\n\u201c\n\n### \u201c\n\n### The one thing you can't buy as a lawyer is more time. Lawmatics gets you more time. It breaks that rule.\u201d\n\nDavid Lehr  \n  \nManaging Attorney,\u00a0Strongest Defense\n\nWe've got your back.\n--------------------\n\n### Personalized onboarding\n\nOur award-winning Customer Success Team will work directly with your team to develop a tailored plan suited to your firm\u2019s business goals.\n\n### Phone & email support\n\nWhatever your firm may need, ouraward-winning Support Team is here to help so you can focus on what you do best: practicing law.\n\n### Training documentation\n\nWhether you have a question or just want to dive headfirst into Lawmatics features, our extensive Resource Center has the articles and tutorials you need.\n\n![Image 2: Conti Moore Smith](blob:http://localhost/e8a57f4972516a1d3218894eabc89576)\n\n\u201c\n\n### \u201c\n\n### Lawmatics pays for itself. Now my staff can focus on profit-generating tasks rather than manual processes related to client follow up.\u201c  \n\nConti Moore Smith  \n  \nManaging Partner,\u00a0Conti Moore Law Divorce Lawyers, PLLC\n\nCompare plans side by\u00a0side\n--------------------------\n\n##### User minimum\n\nGrant your staff access to Lawmatics with dedicated user seats for strong collaboration.\n\n##### User roles\n\nCustomize user access for security and efficient collaboration within Lawmatics.\n\n##### Automations\n\nPlan, measure, and manage all of your marketing campaigns.\n\n##### Custom forms\n\nCollect the intake information you need: notes, details, signatures, appointments, and whatever else you can imagine\n\n##### Appointment booking\n\nLet your clients pick and schedule an available time slot with you or any of your associates\n\n##### E-signatures\n\nComplete contracts, approvals, and other agreements in minutes.\n\n##### Document automation\n\nBuild custom and advanced documents like fee agreements with reusable and personalizable features.\n\n##### File requests\n\nUse file requests to collect and receive files from anyone\n\n##### Contacts\n\nThe sum of all contacts (Matters, Clients, etc.) available for the firm.\n\n##### Client relationship  \nmanagement\n\nManage the relationship with all current and potential clients in one place. Take advantage of tasks, lists, and calendar to make keeping in touch a breeze.\n\n##### Conflict checking\n\nSearch any term in all of your firm's matters, and approve, deny, or flag as a possible conflict manually or via automation.\n\n##### Calendaring\n\nManage appointments and send automated reminders from within Lawmatics.\n\n##### Round-robin scheduling\n\nDistributed appointments evenly among team members.\n\n##### Pipelines\n\nManage, prioritize, and nurture your prospective clients from initial inquiry to invoice.\n\n##### Task management\n\nPrioritize and organize your team's to-dos.\n\n##### Two-way SMS / text\u00a0messaging\n\nCommunicate more efficiently by sending and receiving text messages to and from your client's phone.\n\n##### MMS\n\nReceive photos and documents from clients via text\n\n##### Event management\n\nManage registration for events of any size, from webinars to networking luncheons.\n\n##### LMPay\n\nCollect online payments from your clients directly from within Lawmatics.\n\n##### Client portal\n\nA simple, secure, and efficient way to communicate with your clients and keep them in the know on the status of their case.\n\n##### HTML email builder\n\nBuild beautiful, responsive emails quickly and easily with our fully featured email builder.\n\n##### LM\\[AI\\]\n\nGenerate fresh and professional email copy that resonates with prospective clients.\n\n##### Email sends\n\nReach your prospects and clients effectively with a high allocation of email sends.\n\n##### Audiences\n\nBuild audiences to better target your messaging.\n\n##### Custom email domain\n\nHave your automated emails come from your personal domain email address.\n\n##### Analytics & dashboard\n\nMeasure, manage, and analyze marketing performance. Be more efficient and minimize wasted marketing dollars.\n\n##### Custom reports\n\nSlice and dice your data to get the answers to your most important business decisions.\n\n##### Custom dashboards\n\nConsolidate your critical intake, marketing, and financial metrics into an easy-to-use interface.\n\n##### Source reporting\n\nCollect data perinent to where your leads are coming from to better understand your marketing efficiency.\n\n##### ROI tracking & analysis\n\nMaximize marketing spending effectiveness and optimize return on investment (ROI) with key marketing data.\n\n##### URL UTM tracking\n\nTrack the exact location your leads came into your funnel.\n\n##### SAML SSO\n\nLawmatics offers enhanced security and seamless access with single sign-on authentication.\n\n##### Comprehensive integrations\n\nSeamlessly integrate with your preferred software tools for easy workflow optimization.\n\n##### API access\n\nLawmatics' Open API will allow you to customize your app even further. Extensive documentation available.\n\n##### Billing & invoicing\n\nSend invoices and trust fund requests to collect payment from your matters.\n\n##### Time & expense tracking\n\nRecord billable time and expenses to generate and send invoices.\n\n##### Online payments\n\nUse LMPay to allow clients to pay invoices online and on your custom forms.\n\n\\*Additional contacts and texts sold separately.\n\n![Image 3: Matthew Sullivan](blob:http://localhost/e8a57f4972516a1d3218894eabc89576)\n\n\u201c\n\n### \u201c\n\n### Lawmatics is a great platform for small and solo practices \u2014 and it's a great platform for very large, AM Law 100 firms.\u201c  \n\nMatthew Sullivan  \n  \nExecutive Director of Finance and Operations,\u00a0Sullivan Law & Associates\n\nLaw firms love Lawmatics\n------------------------\n\nOur customers give their clients the client-focused experience they deserve. Learn how they do it all with Lawmatics.\n\nReady to grow your law firm with Lawmatics?\n-------------------------------------------\n\nSchedule a demo of legal's #1 growth platform.\n\n[Get a demo](https://www.lawmatics.com/demo/)\n\n[![Image 4: Lawmatics Dashboard](blob:http://localhost/37070fe43939e5a69fcfc127a9675d8e)](https://www.lawmatics.com/demo-pricing/)\n\nNot sure which plan is right for your firm?  \n\n----------------------------------------------\n\nOur experts can help.\n\n[Get a demo](https://www.lawmatics.com/demo-pricing/)\n\nStart streamlining your practice's intake and marketing today!",
      "error": null,
      "pricing_data": {
        "app_id": "lawmatics",
        "app_name": "Lawmatics",
        "app_slug": "lawmatics",
        "pricing_url": "https://www.lawmatics.com/demo-pricing/",
        "source_url": "https://www.lawmatics.com/demo-pricing/",
        "all_pricing_urls": [
          "https://www.lawmatics.com/demo-essential/",
          "https://www.lawmatics.com/demo-premium/",
          "https://www.lawmatics.com/demo-enterprise/"
        ],
        "price_model_type": [
          "PriceModelType.SUBSCRIPTION",
          "PriceModelType.QUOTE_BASED"
        ],
        "has_free_tier": false,
        "has_free_trial": false,
        "free_trial_period_days": null,
        "currency": "USD",
        "is_pricing_public": false,
        "pricing_page_accessible": true,
        "pricing_notes": "Pricing details are not publicly disclosed; users are directed to contact sales or schedule a demo for specific pricing information.",
        "pricing_tiers": [
          {
            "tier_name": "Essential",
            "tier_description": "For firms striving to boost client capacity while operating at peak efficiency.",
            "monthly_price": null,
            "annual_price": null,
            "annual_discount_percentage": null,
            "setup_fee": null,
            "features": [
              "Client intake",
              "Lead management",
              "Calendaring",
              "Custom forms",
              "Task management",
              "2,500 contacts",
              "50 e-signatures",
              "250 text messages"
            ],
            "limits": {
              "users": null,
              "storage": null,
              "operations": null,
              "api_calls": null,
              "integrations": null,
              "custom_limits": [
                {
                  "name": "contacts",
                  "value": "2,500"
                },
                {
                  "name": "e-signatures",
                  "value": "50"
                },
                {
                  "name": "text messages",
                  "value": "250"
                }
              ]
            }
          },
          {
            "tier_name": "Premium",
            "tier_description": "For firms targeting rapid growth, record high profitability, and market leadership.",
            "monthly_price": null,
            "annual_price": null,
            "annual_discount_percentage": null,
            "setup_fee": null,
            "features": [
              "Every feature in Essential",
              "Unlimited automations",
              "Email marketing campaigns",
              "Advanced conflict checking",
              "ROI tracking & analysis",
              "Custom dashboards",
              "Event management",
              "10,000 contacts",
              "Unlimited e-signatures",
              "750 text messages"
            ],
            "limits": {
              "users": null,
              "storage": null,
              "operations": null,
              "api_calls": null,
              "integrations": null,
              "custom_limits": [
                {
                  "name": "contacts",
                  "value": "10,000"
                },
                {
                  "name": "e-signatures",
                  "value": "unlimited"
                },
                {
                  "name": "text messages",
                  "value": "750"
                }
              ]
            }
          },
          {
            "tier_name": "Enterprise",
            "tier_description": "Talk to us for a comprehensive solution that meets all your large-scale cross-functional needs.",
            "monthly_price": null,
            "annual_price": null,
            "annual_discount_percentage": null,
            "setup_fee": null,
            "features": [
              "Custom pricing",
              "Full access to all features",
              "Dedicated account manager"
            ],
            "limits": null
          }
        ],
        "usage_based_pricing": null,
        "ai_specific_pricing": null,
        "promotional_offers": null,
        "additional_fees": [
          {
            "fee_name": "Additional contacts and texts",
            "fee_amount": null,
            "fee_description": "Sold separately"
          }
        ],
        "extraction_timestamp": "2025-04-15T06:54:13.609382",
        "schema_validated": null,
        "confidence_score": null,
        "extraction_error": null,
        "json_repaired": null
      },
      "pricing_analyzed": true
    },
    {
      "url": "https://www.lawmatics.com/pricing/",
      "is_accessible": true,
      "content": "Your practice, your\u00a0pricing\n---------------------------\n\nLet's find your perfect fit.\n\n*   Essential\n    ---------\n    \n    For firms striving to boost client capacity while operating at peak efficiency.\n    \n    [Get pricing](https://www.lawmatics.com/demo-essential/)\n    \n    ### What's included:\n    \n    *   Client intake\n        \n    *   Lead management\n        \n    *   Calendaring\n        \n    *   Custom forms\n        \n    *   Task management\n        \n    *   2,500 contacts\\*\n        \n    *   50 e-signatures\n        \n    *   250 text messages\\*\n        \n    \n*   Most popular\n    \n    Premium\n    -------\n    \n    For firms targeting rapid growth, record high profitability, and market leadership.\n    \n    [Get pricing](https://www.lawmatics.com/demo-premium/)\n    \n    ### What's included:\n    \n    *   Every feature in Essential\n        \n    *   Unlimited automations\n        \n    *   Email marketing campaigns\n        \n    *   Advanced conflict checking\n        \n    *   ROI tracking &\u00a0analysis\n        \n    *   Custom dashboards\n        \n    *   Event management\n        \n    *   10,000 contacts\\*\n        \n    *   Unlimited e-signatures\n        \n    *   750 text messages\\*\n        \n    \n*   Enterprise\n    ----------\n    \n    Talk to us for a comprehensive solution that meets all your large-scale cross\u2011functional needs.\n    \n    [Get pricing](https://www.lawmatics.com/demo-enterprise/)\n    \n    ### What's included:\n    \n    *   Custom pricing\n        \n    *   Full access to all features\n        \n    *   Dedicated account manager\n        \n    \n    Time & Billing\n    \n    Time tracking, data insights, client management, payment processing, and invoicing \u2014 applicable to any plan.\n    \n    [Contact sales](https://www.lawmatics.com/demo)\n    \n\n\\*Additional contacts and texts sold separately.\n\nLawmatics integrates with the apps you use every day  \n\n-------------------------------------------------------\n\n![Image 1: David Lehr](https://www.lawmatics.com/wp-content/uploads/2022/06/David-Lehr_Headshot_Square.webp)\n\n\u201c\n\n### \u201c\n\n### The one thing you can't buy as a lawyer is more time. Lawmatics gets you more time. It breaks that rule.\u201d\n\nDavid Lehr  \n  \nManaging Attorney,\u00a0Strongest Defense\n\nWe've got your back.\n--------------------\n\n### Personalized onboarding\n\nOur award-winning Customer Success Team will work directly with your team to develop a tailored plan suited to your firm\u2019s business goals.\n\n### Phone & email support\n\nWhatever your firm may need, ouraward-winning Support Team is here to help so you can focus on what you do best: practicing law.\n\n### Training documentation\n\nWhether you have a question or just want to dive headfirst into Lawmatics features, our extensive Resource Center has the articles and tutorials you need.\n\n![Image 2: Conti Moore Smith](https://www.lawmatics.com/wp-content/uploads/2021/07/lawyer-conti.webp)\n\n\u201c\n\n### \u201c\n\n### Lawmatics pays for itself. Now my staff can focus on profit-generating tasks rather than manual processes related to client follow up.\u201c  \n\nConti Moore Smith  \n  \nManaging Partner,\u00a0Conti Moore Law Divorce Lawyers, PLLC\n\nCompare plans side by\u00a0side\n--------------------------\n\n##### User minimum\n\nGrant your staff access to Lawmatics with dedicated user seats for strong collaboration.\n\n##### User roles\n\nCustomize user access for security and efficient collaboration within Lawmatics.\n\n##### Automations\n\nPlan, measure, and manage all of your marketing campaigns.\n\n##### Custom forms\n\nCollect the intake information you need: notes, details, signatures, appointments, and whatever else you can imagine\n\n##### Appointment booking\n\nLet your clients pick and schedule an available time slot with you or any of your associates\n\n##### E-signatures\n\nComplete contracts, approvals, and other agreements in minutes.\n\n##### Document automation\n\nBuild custom and advanced documents like fee agreements with reusable and personalizable features.\n\n##### File requests\n\nUse file requests to collect and receive files from anyone\n\n##### Contacts\n\nThe sum of all contacts (Matters, Clients, etc.) available for the firm.\n\n##### Client relationship  \nmanagement\n\nManage the relationship with all current and potential clients in one place. Take advantage of tasks, lists, and calendar to make keeping in touch a breeze.\n\n##### Conflict checking\n\nSearch any term in all of your firm's matters, and approve, deny, or flag as a possible conflict manually or via automation.\n\n##### Calendaring\n\nManage appointments and send automated reminders from within Lawmatics.\n\n##### Round-robin scheduling\n\nDistributed appointments evenly among team members.\n\n##### Pipelines\n\nManage, prioritize, and nurture your prospective clients from initial inquiry to invoice.\n\n##### Task management\n\nPrioritize and organize your team's to-dos.\n\n##### Two-way SMS / text\u00a0messaging\n\nCommunicate more efficiently by sending and receiving text messages to and from your client's phone.\n\n##### MMS\n\nReceive photos and documents from clients via text\n\n##### Event management\n\nManage registration for events of any size, from webinars to networking luncheons.\n\n##### LMPay\n\nCollect online payments from your clients directly from within Lawmatics.\n\n##### Client portal\n\nA simple, secure, and efficient way to communicate with your clients and keep them in the know on the status of their case.\n\n##### HTML email builder\n\nBuild beautiful, responsive emails quickly and easily with our fully featured email builder.\n\n##### LM\\[AI\\]\n\nGenerate fresh and professional email copy that resonates with prospective clients.\n\n##### Email sends\n\nReach your prospects and clients effectively with a high allocation of email sends.\n\n##### Audiences\n\nBuild audiences to better target your messaging.\n\n##### Custom email domain\n\nHave your automated emails come from your personal domain email address.\n\n##### Analytics & dashboard\n\nMeasure, manage, and analyze marketing performance. Be more efficient and minimize wasted marketing dollars.\n\n##### Custom reports\n\nSlice and dice your data to get the answers to your most important business decisions.\n\n##### Custom dashboards\n\nConsolidate your critical intake, marketing, and financial metrics into an easy-to-use interface.\n\n##### Source reporting\n\nCollect data perinent to where your leads are coming from to better understand your marketing efficiency.\n\n##### ROI tracking & analysis\n\nMaximize marketing spending effectiveness and optimize return on investment (ROI) with key marketing data.\n\n##### URL UTM tracking\n\nTrack the exact location your leads came into your funnel.\n\n##### SAML SSO\n\nLawmatics offers enhanced security and seamless access with single sign-on authentication.\n\n##### Comprehensive integrations\n\nSeamlessly integrate with your preferred software tools for easy workflow optimization.\n\n##### API access\n\nLawmatics' Open API will allow you to customize your app even further. Extensive documentation available.\n\n##### Billing & invoicing\n\nSend invoices and trust fund requests to collect payment from your matters.\n\n##### Time & expense tracking\n\nRecord billable time and expenses to generate and send invoices.\n\n##### Online payments\n\nUse LMPay to allow clients to pay invoices online and on your custom forms.\n\n\\*Additional contacts and texts sold separately.\n\n![Image 3: Matthew Sullivan](https://www.lawmatics.com/wp-content/uploads/2023/03/matthew-sullivan_headshot.webp)\n\n\u201c\n\n### \u201c\n\n### Lawmatics is a great platform for small and solo practices \u2014 and it's a great platform for very large, AM Law 100 firms.\u201c  \n\nMatthew Sullivan  \n  \nExecutive Director of Finance and Operations,\u00a0Sullivan Law & Associates\n\nLaw firms love Lawmatics\n------------------------\n\nOur customers give their clients the client-focused experience they deserve. Learn how they do it all with Lawmatics.\n\nReady to grow your law firm with Lawmatics?\n-------------------------------------------\n\nSchedule a demo of legal's #1 growth platform.\n\n[Get a demo](https://www.lawmatics.com/demo/)\n\n[![Image 4: Lawmatics Dashboard](https://www.lawmatics.com/wp-content/uploads/2021/09/app-shot.webp)](https://www.lawmatics.com/demo-pricing/)\n\nNot sure which plan is right for your firm?  \n\n----------------------------------------------\n\nOur experts can help.\n\n[Get a demo](https://www.lawmatics.com/demo-pricing/)\n\nStart streamlining your practice's intake and marketing today!",
      "error": null,
      "pricing_data": {
        "app_id": "lawmatics",
        "app_name": "Lawmatics",
        "app_slug": "lawmatics",
        "pricing_url": "https://www.lawmatics.com/demo-pricing/",
        "source_url": "https://www.lawmatics.com/demo-pricing/",
        "all_pricing_urls": [
          "https://www.lawmatics.com/demo-essential/",
          "https://www.lawmatics.com/demo-premium/",
          "https://www.lawmatics.com/demo-enterprise/"
        ],
        "price_model_type": [
          "PriceModelType.SUBSCRIPTION",
          "PriceModelType.QUOTE_BASED"
        ],
        "has_free_tier": false,
        "has_free_trial": false,
        "free_trial_period_days": null,
        "currency": "USD",
        "is_pricing_public": false,
        "pricing_page_accessible": true,
        "pricing_notes": "Pricing details are not directly listed on the website; users are directed to contact sales for specific pricing information.",
        "pricing_tiers": [
          {
            "tier_name": "Essential",
            "tier_description": "For firms striving to boost client capacity while operating at peak efficiency.",
            "monthly_price": null,
            "annual_price": null,
            "annual_discount_percentage": null,
            "setup_fee": null,
            "features": [
              "Client intake",
              "Lead management",
              "Calendaring",
              "Custom forms",
              "Task management",
              "2,500 contacts",
              "50 e-signatures",
              "250 text messages"
            ],
            "limits": {
              "users": null,
              "storage": null,
              "operations": null,
              "api_calls": null,
              "integrations": null,
              "custom_limits": [
                {
                  "name": "contacts",
                  "value": 2500
                },
                {
                  "name": "e-signatures",
                  "value": 50
                },
                {
                  "name": "text messages",
                  "value": 250
                }
              ]
            }
          },
          {
            "tier_name": "Premium",
            "tier_description": "For firms targeting rapid growth, record high profitability, and market leadership.",
            "monthly_price": null,
            "annual_price": null,
            "annual_discount_percentage": null,
            "setup_fee": null,
            "features": [
              "Every feature in Essential",
              "Unlimited automations",
              "Email marketing campaigns",
              "Advanced conflict checking",
              "ROI tracking & analysis",
              "Custom dashboards",
              "Event management",
              "10,000 contacts",
              "Unlimited e-signatures",
              "750 text messages"
            ],
            "limits": {
              "users": null,
              "storage": null,
              "operations": null,
              "api_calls": null,
              "integrations": null,
              "custom_limits": [
                {
                  "name": "contacts",
                  "value": 10000
                },
                {
                  "name": "e-signatures",
                  "value": "unlimited"
                },
                {
                  "name": "text messages",
                  "value": 750
                }
              ]
            }
          },
          {
            "tier_name": "Enterprise",
            "tier_description": "Comprehensive solution for large-scale cross-functional needs.",
            "monthly_price": null,
            "annual_price": null,
            "annual_discount_percentage": null,
            "setup_fee": null,
            "features": [
              "Custom pricing",
              "Full access to all features",
              "Dedicated account manager"
            ],
            "limits": null
          }
        ],
        "usage_based_pricing": null,
        "ai_specific_pricing": null,
        "promotional_offers": null,
        "additional_fees": [
          {
            "fee_name": "Additional contacts",
            "fee_amount": null,
            "fee_description": "Additional contacts sold separately."
          },
          {
            "fee_name": "Additional texts",
            "fee_amount": null,
            "fee_description": "Additional texts sold separately."
          }
        ],
        "extraction_timestamp": "2025-04-15T06:54:24.171767",
        "schema_validated": null,
        "confidence_score": null,
        "extraction_error": null,
        "json_repaired": null
      },
      "pricing_analyzed": true
    }
  ],
  "results_directory": "pricing_results\\lawmatics\\20250415_065432"
}