{
  "app_name": "Rev",
  "app_slug": "rev",
  "search_term": "Find the official pricing page URL for Rev (rev.com). Only provide the exact URL to the pricing page, not a summary of pricing information.",
  "timestamp": 1744702511.232519,
  "response_text": [
    "The official pricing page for Rev can be found at: [https://www.rev.com/pricing](https://www.rev.com/pricing)\u30103:0\u2020source\u3011."
  ],
  "citations": [
    {
      "title": "Pricing for Caption, Transcription, and VoiceHub Services | Rev",
      "url": "https://www.rev.com/pricing"
    }
  ],
  "extracted_content": [
    {
      "url": "https://www.rev.com/pricing",
      "is_accessible": true,
      "content": "Free\n----\n\nBest for getting started with Rev  \nfor free\n\nFeatures:\n\n45 minutes of AI transcription per month6x more! Get 300 minutes now \u2013 offer ends soon!\n\nAccess to pay-per-minute 99% accurate human transcripts, captions, and subtitles\n\nAI Notetaker for Google, Teams, and Zoom\n\nRev Mobile App for recording and editing on the go\n\nInteractive transcript editor\n\nBasic\n-----\n\nBuilt for productivity in individuals and small teams\n\nFeatures\n\n20 hours of AI transcription per month; 90 minutes per recording\n\n3% discount on 99% accurate human transcripts, caption, and subtitlesUpgrade to human transcripts or captions for $1.93/min (reg price $1.99) or global subtitles for $6.30 to $15.51 (reg price $6.49 to $15.99)\n\nAI Notetaker for Google, Teams, and Zoom\n\nRev Mobile App for recording and editing on the go\n\nInteractive transcript editor\n\nUnlimited use of AI Assistant & AI Summary Templates\n\nRecommended\n\nPro\n---\n\nBuilt for larger teams who need advanced features and collaboration\n\nFeatures\n\n100 hours of AI transcription per month; no limit on file length\n\nAI captions in 37+ languages included in 100 monthly hours\n\n5% discount on 99% accurate human transcripts, caption, and subtitlesUpgrade to human transcripts or captions for $1.89/min (reg price $1.99) or global subtitles for $6.17 to $15.19 (reg price $6.49 to $15.99)\n\nAI Notetaker for Google, Teams, and Zoom\n\nRev Mobile App for recording and editing on the go\n\nInteractive transcript editor\n\nUnlimited use of AI Assistant & AI Summary Templates\n\nInteractive captions editor\n\nCustomizable AI Summary Templates\n\nEnterprise\n----------\n\nBuilt for organizations needing security, management, and customized features\n\nFeatures\n\n100 hours of AI transcription per month; no limit on file length\n\nAI captions in 37+ languages included in 100 monthly hours\n\nCustom discounts on 99% accurate human transcripts, captions, and subtitles\n\nAI Notetaker for Google, Teams, and Zoom\n\nRev Mobile App for recording and editing on the go\n\nInteractive transcript editor\n\nUnlimited use of AI Assistant & AI Summary Templates\n\nInteractive captions editor\n\nUnlimited customizable AI templates tailored just for you\n\nEnterprise-grade privacy; HIPAA and SOC 2 Type II compliance\n\nSSO & Domain Claiming\n\nFree\n\nBest for getting started with Rev  \n\u200dfor free\n\nFeatures:\n\n45 minutes of AI transcription per month6x more! Get 300 minutes now \u2013 offer ends soon!\n\nAccess to pay-per-minute 99% accurate human transcripts, captions, and subtitles\n\nAI Notetaker for Google, Teams, and Zoom\n\nRev Mobile App for recording and editing on the go\n\nInteractive transcript editor\n\nBasic\n\nBuilt for productivity in individuals and small teams\n\n$9.99 per user/month\n\nBilled annually Save 33%\n\n[Get Started](https://www.rev.com/subscription/signup/groups/17/plans/76)\n\nFeatures:\n\n20 hours of AI transcription per month; 90 minutes per recording\n\n15% discount on 99% accurate human transcripts Upgrade to human transcripts or captions for $1.70/min (regular price $1.99) or global subtitles for $5.52 to $13.59 (reg price $6.49 to $15.99)\n\nAI Notetaker for Google, Teams, and Zoom\n\nRev Mobile App for recording and editing on the go\n\nInteractive transcript editor\n\nUnlimited use of AI Assistant & AI Summary Templates\n\nRecommended\n\nPro\n\nBuilt for larger teams who need advanced features and collaboration\n\n$20.99 per user/month\n\nBilled annually Save 40%\n\n[Get Started](https://www.rev.com/subscription/signup/groups/17/plans/77)\n\nFeatures:\n\n100 hours of AI transcription per month; no limit on file length\n\nAI captions in 37+ languages included in 100 monthly hours\n\n30% discount on 99% accurate human transcripts, captions, and subtitles Upgrade to human transcripts or captions for $1.39/min (reg price $1.99) or global subtitles for $4.54 to $11.19 (reg price $6.49 to $15.99)\n\nAI Notetaker for Google, Teams, and Zoom\n\nRev Mobile App for recording and editing on the go\n\nInteractive transcript editor\n\nUnlimited use of AI Assistant & AI Summary Templates\n\nInteractive captions editor\n\nCustomizable AI Summary Templates\n\nEnterprise\n\nBuilt for organizations needing security, management, and customized features\n\nFeatures\n\n100 hours of AI transcription per month; no limit on file length\n\nAI captions in 37+ languages included in 100 monthly hours\n\nCustom discounts on 99% accurate human transcripts, captions, and subtitles\n\nAI Notetaker for Google, Teams, and Zoom\n\nRev Mobile App for recording and editing on the go\n\nInteractive transcript editor\n\nUnlimited use of AI Assistant & AI Summary Templates\n\nInteractive captions editor\n\nUnlimited customizable AI templates tailored just for you\n\nEnterprise-grade privacy; HIPAA and SOC 2 Type II compliance\n\nSSO & Domain Claiming\n\nHuman Transcription\n-------------------\n\nOur expert transcriptionists turn speech to text in 12 hours or less, 99% accuracy guaranteed.\n\n$1.99 /minute\n\nWhat's included:\n\n99% accuracy, fully formatted with timestamps in 12 hours or less\n\nFree audio recording on Rev\u2019s mobile app\n\nCustomize and edit your transcripts in our interactive editor\n\nAutomatically integrates with Dropbox\n\nTranscribe video and audio to text in minutes with AI-powered automatic speech recognition.\n\n$0.25 /minute\n\nWhat's included:\n\n95%+ accuracy in five minutes or less\n\nAvailable in 37 languages coming soon\n\nFree audio recording on Rev\u2019s mobile app\n\nCustomize and edit your transcripts in our interactive editor\n\nAutomatically integrates with Dropbox\n\nHuman Captions\n--------------\n\nReach a wider audience with human-generated captions in English or Spanish.\n\nStarting at\n\n$1.99 /minute\n\nWhat's included:\n\n99% accuracy in 12 hours or less\n\nFree audio recording on Rev\u2019s mobile app\n\nFCC and ADA compliant in all major file formats\n\nCustomize and edit your captions in our interactive editor\n\nAutomatically integrates with YouTube, Vimeo, Zoom, Dropbox, and Google Drive\n\nAI\u00a0Captions\n-----------\n\nBoost your engagement by adding AI generated captions in 38 languages.\n\nPrice\n\n$0.25 /minute\n\nWhat's included:\n\n95%+ accuracy in five minutes or less\n\nAvailable in 37 languages coming soon\n\nDownload caption files in all major formats\n\nCustomize and edit your captions in our interactive editor\n\nAutomatically integrates with YouTube, Vimeo, Zoom, Dropbox, and Google Drive\n\nGlobal Subtitles\n----------------\n\nCreate globally accessible videos with fluent, human-translated subtitles in 17 languages.\n\n$6.49 to $15.99 /minute\n\nWhat's included:\n\nTranslated subtitles by fluent speakers in 17 languages\n\n99% accuracy in 48 hours or less\n\nDownload files in all major formats with free English captions\n\nCustomize and edit your subtitles in our interactive editor\n\nAutomatic integration with YouTube, Vimeo, and Dropbox\n\nAI\u00a0Subtitles\n\nBoost your engagement by adding AI generated subtitles to your videos in 38 languages.\n\nWhat's included:\n\n90+% accuracy in five minutes or less\n\nAvailable in 38 languages\n\nDownload caption files in all major formats\n\nInteractive editor for easy collaboration\n\nAutomatically integrates with YouTube, Vimeo, Zoom, Dropbox, and Google Drive\n\nFree\n----\n\nBest for getting started with Rev  \nfor free\n\nFeatures:\n\n45 minutes of AI transcription per month6x more! Get 300 minutes now \u2013 offer ends soon!\n\nAccess to pay-per-minute 99% accurate human transcripts, captions, and subtitles\n\nAI Notetaker for Google, Teams, and Zoom\n\nRev Mobile App for recording and editing on the go\n\nInteractive transcript editor\n\nBasic\n-----\n\nBuilt for productivity in individuals and small teams\n\nFeatures\n\n20 hours of AI transcription per month; 90 minutes per recording\n\n3% discount on 99% accurate human transcripts, caption, and subtitlesUpgrade to human transcripts or captions for $1.93/min (reg price $1.99) or global subtitles for $6.30 to $15.51 (reg price $6.49 to $15.99)\n\nAI Notetaker for Google, Teams, and Zoom\n\nRev Mobile App for recording and editing on the go\n\nInteractive transcript editor\n\nUnlimited use of AI Assistant & AI Summary Templates\n\nRecommended\n\nPro\n---\n\nBuilt for larger teams who need advanced features and collaboration\n\nFeatures\n\n100 hours of AI transcription per month; no limit on file length\n\nAI captions in 37+ languages included in 100 monthly hours\n\n5% discount on 99% accurate human transcripts, caption, and subtitlesUpgrade to human transcripts or captions for $1.89/min (reg price $1.99) or global subtitles for $6.17 to $15.19 (reg price $6.49 to $15.99)\n\nAI Notetaker for Google, Teams, and Zoom\n\nRev Mobile App for recording and editing on the go\n\nInteractive transcript editor\n\nUnlimited use of AI Assistant & AI Summary Templates\n\nInteractive captions editor\n\nCustomizable AI Summary Templates\n\nEnterprise\n----------\n\nBuilt for organizations needing security, management, and customized features\n\nFeatures\n\n100 hours of AI transcription per month; no limit on file length\n\nAI captions in 37+ languages included in 100 monthly hours\n\nCustom discounts on 99% accurate human transcripts, captions, and subtitles\n\nAI Notetaker for Google, Teams, and Zoom\n\nRev Mobile App for recording and editing on the go\n\nInteractive transcript editor\n\nUnlimited use of AI Assistant & AI Summary Templates\n\nInteractive captions editor\n\nUnlimited customizable AI templates tailored just for you\n\nEnterprise-grade privacy; HIPAA and SOC 2 Type II compliance\n\nSSO & Domain Claiming\n\nFree\n\nBest for getting started with Rev  \n\u200dfor free\n\nFeatures:\n\n45 minutes of AI transcription per month6x more! Get 300 minutes now \u2013 offer ends soon!\n\nAccess to pay-per-minute 99% accurate human transcripts, captions, and subtitles\n\nAI Notetaker for Google, Teams, and Zoom\n\nRev Mobile App for recording and editing on the go\n\nInteractive transcript editor\n\nBasic\n\nBuilt for productivity in individuals and small teams\n\n$9.99 per user/month\n\nBilled annually Save 33%\n\n[Get Started](https://www.rev.com/subscription/signup/groups/17/plans/76)\n\nFeatures:\n\n20 hours of AI transcription per month; 90 minutes per recording\n\n15% discount on 99% accurate human transcripts Upgrade to human transcripts or captions for $1.70/min (regular price $1.99) or global subtitles for $5.52 to $13.59 (reg price $6.49 to $15.99)\n\nAI Notetaker for Google, Teams, and Zoom\n\nRev Mobile App for recording and editing on the go\n\nInteractive transcript editor\n\nUnlimited use of AI Assistant & AI Summary Templates\n\nRecommended\n\nPro\n\nBuilt for larger teams who need advanced features and collaboration\n\n$20.99 per user/month\n\nBilled annually Save 40%\n\n[Get Started](https://www.rev.com/subscription/signup/groups/17/plans/77)\n\nFeatures:\n\n100 hours of AI transcription per month; no limit on file length\n\nAI captions in 37+ languages included in 100 monthly hours\n\n30% discount on 99% accurate human transcripts, captions, and subtitles Upgrade to human transcripts or captions for $1.39/min (reg price $1.99) or global subtitles for $4.54 to $11.19 (reg price $6.49 to $15.99)\n\nAI Notetaker for Google, Teams, and Zoom\n\nRev Mobile App for recording and editing on the go\n\nInteractive transcript editor\n\nUnlimited use of AI Assistant & AI Summary Templates\n\nInteractive captions editor\n\nCustomizable AI Summary Templates\n\nEnterprise\n\nBuilt for organizations needing security, management, and customized features\n\nFeatures\n\n100 hours of AI transcription per month; no limit on file length\n\nAI captions in 37+ languages included in 100 monthly hours\n\nCustom discounts on 99% accurate human transcripts, captions, and subtitles\n\nAI Notetaker for Google, Teams, and Zoom\n\nRev Mobile App for recording and editing on the go\n\nInteractive transcript editor\n\nUnlimited use of AI Assistant & AI Summary Templates\n\nInteractive captions editor\n\nUnlimited customizable AI templates tailored just for you\n\nEnterprise-grade privacy; HIPAA and SOC 2 Type II compliance\n\nSSO & Domain Claiming\n\nTrusted by 1M+ Users and 125K+ Organizations\n--------------------------------------------\n\n![Image 1: CBS Logo](https://cdn.prod.website-files.com/65dd0e80788a2f545d95cd65/65e3687f92a2687a5ed60cbc_CBS.svg)\n\n![Image 2: LegalZoom logo](https://cdn.prod.website-files.com/65dd0e80788a2f545d95cd65/65e3687ffce524f7b7f48ab8_LegalZoom.svg)\n\n![Image 3: Standford university logo](https://cdn.prod.website-files.com/65dd0e80788a2f545d95cd65/65e3687f7632a225efe60876_Stanford%20University.svg)\n\n![Image 4: PBS logo](https://cdn.prod.website-files.com/65dd0e80788a2f545d95cd65/65e3687fc1644f760b0fe882_PBS.svg)\n\n![Image 5: TCM Logo](https://cdn.prod.website-files.com/65dd0e80788a2f545d95cd65/65e3687fb448ad3c53dadd41_TCM.svg)\n\n![Image 6: Viacom logo](https://cdn.prod.website-files.com/65dd0e80788a2f545d95cd65/65e3687fe6faceda6078d620_viacom.svg)\n\n![Image 7](https://cdn.prod.website-files.com/65dd0e80788a2f545d95cd65/66d747e0cf6166cce07a3238_logo_atlantic.svg)\n\n![Image 8: Vimeo](https://cdn.prod.website-files.com/65dd0e80788a2f545d95cd65/66228ad06f81ba9d74f78161_logo_vimeo.svg)\n\n![Image 9: Skadden logo](https://cdn.prod.website-files.com/65dd0e80788a2f545d95cd65/65e3687f9e2ce4ad8745e35e_Skadden.svg)\n\n![Image 10: Jones Day](https://cdn.prod.website-files.com/65dd0e80788a2f545d95cd65/65e3687f07c381b94f941cf4_Jones%20Day.svg)\n\nCompare Our Plans\n-----------------\n\nFree\n\nBasic\n\n[Get Started](https://www.rev.com/subscription/signup/groups/17/plans/76)\n\n$9.99 per user/month\n\nBilled annually Save 33%\n\n$14.99 per user/month\n\nPro\n\n$20.99 per user/month\n\nBilled annually Save 40%\n\n$34.99 per user/month\n\nEnterprise\n\nUsage\n\nAI Minutes (per user per month) Min. accrue per seat, drawn from account-wide pool\n\n45 minutes\n\n20 hours\n\n100 hours\n\n100 hours\n\nAI Transcription Languages English (UK), English, Arabic, Bulgarian, Catalan, Croatian, Czech, Danish, Dutch, Farsi (Persian), Finnish, French, German, Greek, Hebrew, Hindi, Hungarian, Indonesian, Italian, Japanese, Korean, Lithuanian, Latvian, Malay, Mandarin, Norwegian, Polish, Portuguese, Romanian, Russian, Slovak, Slovenian, Spanish, Swedish, Tamil, Telugu, Turkish\n\nEnglish\n\n37 languages\n\n37 languages\n\n37 languages\n\nAI Captions\n\n37 languages\n\n37 languages\n\nMaximum minutes you can transcribe in one recording\n\n45 minutes\n\n90 minutes\n\nUnlimited\n\nUnlimited\n\nDiscounts on Human Transcription, Captions, and Subtitles\n\n15% discount\n\n30% discount\n\nCustom\n\nPlatform Features\n\nWorkspaces Workspaces allow you to create different projects and team member access within your organization.\n\n1\n\nUnlimited\n\nUnlimited\n\nUnlimited\n\nMeeting Notetaker Joins, records, and transcribes your meetings.\n\nGlossary Terms Submit your glossary to improve accuracy.\n\nUnlimited\n\nUnlimited\n\nUnlimited\n\nUnlimited\n\nTranscript Editor Edit, highlight & comment on your transcripts.\n\nCaption Editor Free & Basic: Get captions through .srt download.\n\nAI Assistant Pull insights from transcripts using our chatbot.\n\nUp to 5\\* queries/month\n\nTranscript Summarization \\*5 across Transcript Summarization and AI Assistant\n\nUp to 5\\* summaries/month\n\nAI Summary TemplatesPull AI summaries, key insights, and more.\n\nDefault Templates\n\nPre-built Template Library\n\nPre-built Template Library\n\nUnlimited Customizable Templates\n\nAI Template Builder Create custom summary templates with AI Blocks.\n\nAI Block Builder AI blocks form the basis of AI Templates.\n\nMulti-File Summaries Pull insights from multiple files at once.\n\nClip Sharing\n\nUsage Dashboards See how your team is using VoiceHub.\n\nAPI Access\n\nIntegrations Zoom, Google Meet, Microsoft Teams, Slack, & more.\n\nSecurity & User Management\n\nSSO\n\nDomain Claiming\n\nFile Viewer ModeShare files with privacy controls.\n\nFile Sharing ControlChoose access levels for transcripts.\n\nConfigurable\n\nHIPAA Compliance\n\nADA Compliant Captions\n\nFCC Compliant Captions\n\nSupport & Billing\n\nFAQ\n\nEmail\n\nPhone\n\nDedicated Account Manager\n\nImplementation Engineer\n\n[Button text](https://www.rev.com/pricing#)\n\n$9.99 per user/month\n\nBilled annually Save 33%\n\n$20.99 per user/month\n\nBilled annually Save 40%\n\n$14.99 per user/month\n\n$34.99 per user/month\n\n### Usage\n\nAI Minutes (per user per month) Min. accrue per seat, drawn from account-wide pool\n\n45 minutes\n\nAI Transcription Languages English (UK), English, Arabic, Bulgarian, Catalan, Croatian, Czech, Danish, Dutch, Farsi (Persian), Finnish, French, German, Greek, Hebrew, Hindi, Hungarian, Indonesian, Italian, Japanese, Korean, Lithuanian, Latvian, Malay, Mandarin, Norwegian, Polish, Portuguese, Romanian, Russian, Slovak, Slovenian, Spanish, Swedish, Tamil, Telugu, Turkish\n\nEnglish\n\nAI Captions\n\nMaximum minutes you can transcribe in one recording\n\n45 minutes\n\nMaximum Meeting Transcription Per Conversation\n\nDiscounts on Human Transcription, Captions, and Subtitles\n\n### Platform Features\n\nWorkspaces Workspaces allow you to create different projects and team member access within your organization.\n\n1\n\nMeeting Notetaker Joins, records, and transcribes your meetings.\n\nGlossary Terms Submit your glossary to improve accuracy.\n\nUnlimited\n\nTranscript Editor Edit, highlight & comment on your transcripts.\n\nCaption Editor Free & Basic: Get captions through .srt download.\n\nAI Assistant Pull insights from transcripts using our chatbot.\n\nUp to 5\\* queries/month\n\nTranscript Summarization \\*5 across Transcript Summarization and AI Assistant\n\nUp to 5\\* summaries/month\n\nAI Summary TemplatesPull AI summaries, key insights, and more.\n\nDefault Templates\n\nAI Template Builder Create custom summary templates with AI Blocks.\n\nAI Block Builder AI blocks form the basis of AI Templates.\n\nMulti-File SummariesPull insights from multiple files at once.\n\nClip Sharing\n\nUsage Dashboards See how your team is using VoiceHub.\n\nAPI Access\n\nIntegrations Zoom, Google Meet, Microsoft Teams, Slack, & more.\n\n### Security & User Management\n\nSSO\n\nDomain Claiming\n\nFile Viewer ModeShare files with privacy controls.\n\nFile Sharing ControlChoose access levels for transcripts.\n\nHIPAA Compliance\n\nADA Compliant Captions\n\nFCC Compliant Captions\n\n### Support & Billing\n\nFAQ\n\nEmail\n\nPhone\n\nDedicated Account Manager\n\nImplementation Engineer\n\n### Usage\n\nAI Minutes (per user per month) Min. accrue per seat, drawn from account-wide pool\n\n20 hours\n\nAI Transcription Languages English (UK), English, Arabic, Bulgarian, Catalan, Croatian, Czech, Danish, Dutch, Farsi (Persian), Finnish, French, German, Greek, Hebrew, Hindi, Hungarian, Indonesian, Italian, Japanese, Korean, Lithuanian, Latvian, Malay, Mandarin, Norwegian, Polish, Portuguese, Romanian, Russian, Slovak, Slovenian, Spanish, Swedish, Tamil, Telugu, Turkish\n\n37 languages\n\nAI Captions\n\nMaximum minutes you can transcribe in one recording\n\n90 minutes\n\nDiscounts on Human Transcription, Captions, and Subtitles\n\n15% discount\n\n### Platform Features\n\nWorkspaces Workspaces allow you to create different projects and team member access within your organization.\n\nUnlimited\n\nMeeting Notetaker Joins, records, and transcribes your meetings.\n\nGlossary Terms Submit your glossary to improve accuracy.\n\nUnlimited\n\nTranscript Editor Edit, highlight & comment on your transcripts.\n\nCaption Editor Free & Basic: Get captions through .srt download.\n\nAI Assistant Pull insights from transcripts using our chatbot.\n\nTranscript Summarization \\*5 across Transcript Summarization and AI Assistant\n\nAI Summary TemplatesPull AI summaries, key insights, and more.\n\nPre-built Template Library\n\nAI Template Builder Create custom summary templates with AI Blocks.\n\nAI Block Builder AI blocks form the basis of AI Templates.\n\nMulti-File SummariesPull insights from multiple files at once.\n\nClip Sharing\n\nUsage Dashboards See how your team is using VoiceHub.\n\nAPI Access\n\nIntegrations Zoom, Google Meet, Microsoft Teams, Slack, & more.\n\n### Security & User Management\n\nSSO\n\nDomain Claiming\n\nFile Viewer ModeShare files with privacy controls.\n\nFile Sharing ControlChoose access levels for transcripts.\n\nHIPAA\u00a0Compliance\n\nADA Compliant Captions\n\nFCC Compliant Captions\n\n### Support & Billing\n\nFAQ\n\nEmail\n\nPhone\n\nDedicated Account Manager\n\nImplementation Engineer\n\n### Usage\n\nAI Minutes (per user per month) Min. accrue per seat, drawn from account-wide pool\n\n100 hours\n\nAI Transcription Languages English (UK), English, Arabic, Bulgarian, Catalan, Croatian, Czech, Danish, Dutch, Farsi (Persian), Finnish, French, German, Greek, Hebrew, Hindi, Hungarian, Indonesian, Italian, Japanese, Korean, Lithuanian, Latvian, Malay, Mandarin, Norwegian, Polish, Portuguese, Romanian, Russian, Slovak, Slovenian, Spanish, Swedish, Tamil, Telugu, Turkish\n\n37 languages\n\nAI Captions\n\n37 languages\n\nMaximum minutes you can transcribe in one recording\n\nUnlimited\n\nDiscounts on Human Transcription, Captions, and Subtitles\n\n30% discount\n\n### Platform Features\n\nWorkspaces Workspaces allow you to create different projects and team member access within your organization.\n\nUnlimited\n\nMeeting Notetaker Joins, records, and transcribes your meetings.\n\nGlossary Terms Submit your glossary to improve accuracy.\n\nUnlimited\n\nTranscript Editor Edit, highlight & comment on your transcripts.\n\nCaption Editor Free & Basic: Get captions through .srt download.\n\nAI Assistant Pull insights from transcripts using our chatbot.\n\nTranscript Summarization \\*5 across Transcript Summarization and AI Assistant\n\nAI Summary TemplatesPull AI summaries, key insights, and more.\n\nCustomizable Templates\n\nAI Template Builder Create custom summary templates with AI Blocks.\n\nAI Block Builder AI blocks form the basis of AI Templates.\n\nMulti-File SummariesPull insights from multiple files at once.\n\nClip Sharing\n\nUsage Dashboards See how your team is using VoiceHub.\n\nAPI Access\n\nIntegrations Zoom, Google Meet, Microsoft Teams, Slack, & more.\n\n### Security & User Management\n\nSSO\n\nDomain Claiming\n\nFile Viewer ModeShare files with privacy controls.\n\nFile Sharing ControlChoose access levels for transcripts.\n\nHIPAA Compliance\n\nADA Compliant Captions\n\nFCC Compliant Captions\n\n### Support & Billing\n\nFAQ\n\nEmail\n\nPhone\n\nDedicated Account Manager\n\nImplementation Engineer\n\n### Usage\n\nAI Minutes (per user per month) Min. accrue per seat, drawn from account-wide pool\n\n100 hours\n\nAI Transcription Languages English (UK), English, Arabic, Bulgarian, Catalan, Croatian, Czech, Danish, Dutch, Farsi (Persian), Finnish, French, German, Greek, Hebrew, Hindi, Hungarian, Indonesian, Italian, Japanese, Korean, Lithuanian, Latvian, Malay, Mandarin, Norwegian, Polish, Portuguese, Romanian, Russian, Slovak, Slovenian, Spanish, Swedish, Tamil, Telugu, Turkish\n\nAll 37 languages\n\nAI Captions\n\nAll 37 languages\n\nMaximum minutes you can transcribe in one recording\n\nUnlimited\n\nDiscounts on Human Transcription, Captions, and Subtitles\n\nCustom\n\n### Platform Features\n\nWorkspaces Workspaces allow you to create different projects and team member access within your organization.\n\nUnlimited\n\nMeeting Notetaker Joins, records, and transcribes your meetings.\n\nGlossary Terms Submit your glossary to improve accuracy.\n\nUnlimited\n\nTranscript Editor Edit, highlight & comment on your transcripts.\n\nCaption Editor Free & Basic: Get captions through .srt download.\n\nAI Assistant Pull insights from transcripts using our chatbot.\n\nTranscript Summarization \\*5 across Transcript Summarization and AI Assistant\n\nAI Summary TemplatesPull AI summaries, key insights, and more.\n\nUnlimited Customizable Templates\n\nAI Template Builder Create custom summary templates with AI Blocks.\n\nAI Block Builder AI blocks form the basis of AI Templates.\n\nMulti-File SummariesPull insights from multiple files at once.\n\nClip Sharing\n\nUsage Dashboards See how your team is using VoiceHub.\n\nAPI Access\n\nIntegrations Zoom, Google Meet, Microsoft Teams, Slack, & more.\n\n### Security & User Management\n\nSSO\n\nDomain Claiming\n\nFile Viewer ModeShare files with privacy controls.\n\nFile Sharing ControlChoose access levels for transcripts.\n\nConfigurable\n\nHIPAA Compliance\n\nADA Compliant Captions\n\nFCC Compliant Captions\n\n### Support & Billing\n\nFAQ\n\nEmail\n\nPhone\n\nDedicated Account Manager\n\nImplementation Engineer\n\nFAQ for Transcripts, Captions, and Subtitles\n--------------------------------------------\n\nYes, you can subscribe to VoiceHub to receive discounts on Human Transcription. As a paid subscriber, you can get discounts depending on what plan you subscribe to \u2013 3% for those on the monthly Basic plan, 15% for those on the annual Basic plan, 5% for those on the monthly Pro plan, 30% for those on the annual Pro plan, and custom discounts for those on the Enterprise plan. Subscribe [here](https://www.rev.com/pricing).\n\nWe offer the following transcription formats: Microsoft Word (.docx), PDF (.pdf), Plain Text (.txt). When you order transcription, all of our transcription file formats are available to you at no additional cost.\n\nWe offer captions and subtitles in every major format, including but not limited to SubRip (.srt), Scenarist (.scc), MacCaption (.mcc), Timed Text (.ttml), Quicktime Timed Text (.qt.txt), Transcript (.txt), WebVTT (.vtt), DFXP (.dfxp), Cheetah .CAP (.cap), Spruce Subtitle File (.stl), Avid DS Subtitle File (.txt), Avid DVD Subtitle File (.txt), Scenarist 23.98 fps (.23p.scc), and burned-in captions.\n\nYes, we timestamp every new paragraph in a transcript for an additional $0.30 per minute. Your transcript is synced with audio, so you can click on any word and instantly hear that point in the audio\u2014no scrubbing required.\n\nWe accept audio and video recordings in MP3, MP4, WMV, AIF, M4A, MOV, AVI, VOB, AMR, WMA, OGG, AAC, and WAV. We also accept streaming video and audio files available on the web, plus seamless integration with YouTube, Vimeo, Zoom, Dropbox, and other major apps.\n\nThe average turnaround time for Human Transcription and Human Captions for a 30-60 minute file is 12 hours. If you have a tight deadline, you may be interested in our Rush service that delivers your files back up to 5x faster. The average turnaround time for Global Subtitles for a 30-60 minute file is 96 hours.\n\n\u200d\n\nSubscription FAQ\n----------------\n\nNo, you can cancel your subscription at any time without any penalty. Simply go to the \u201cManage Subscription\u201d page to cancel your subscription. If you are on a shared account, only the Admin and Billing Manager can access this page. You can click on your name in the top right corner and select \u201cManage Subscription\u201d from the dropdown menu to navigate to your Plan Management page. Here you can view the current details of your plan, change to a different plan, update your payment method, and cancel your paid subscription.\n\nYes. Entitlements within seat subscriptions are pooled at the account level. If an individual user goes over their allotted seat entitlements they simply start consuming from the account's pooled available entitlement.\n\nFree and Basic subscribers can access [AI transcripts](https://www.rev.com/services/ai-transcription) as part of their monthly AI minutes. Pro and Enterprise subscribers can access both AI transcripts and AI captions as part of their monthly AI minutes. As a paid subscriber, you also get a discount on Human Transcription \u2013 3% for those on the monthly Basic plan, 15% for those on the annual Basic plan, 5% for those on the monthly Pro plan, 30% for those on the annual Pro plan, and custom discounts for those on the Enterprise plan.\n\nWhether you\u2019re a content creator, a Fortune 500 company, or something in between, our speech-to-text solutions and subscription plans are priced for all.",
      "error": null,
      "pricing_data": {
        "app_id": "rev",
        "app_name": "Rev",
        "app_slug": "rev",
        "pricing_url": "https://www.rev.com/pricing",
        "source_url": "https://www.rev.com/pricing",
        "all_pricing_urls": [
          "https://www.rev.com/pricing"
        ],
        "price_model_type": [
          "PriceModelType.SUBSCRIPTION",
          "PriceModelType.USAGE_BASED",
          "PriceModelType.FREE_TIER"
        ],
        "has_free_tier": true,
        "has_free_trial": false,
        "free_trial_period_days": null,
        "currency": "USD",
        "is_pricing_public": true,
        "pricing_page_accessible": true,
        "pricing_notes": "Rev offers a combination of subscription-based tiers and usage-based pricing for additional services.",
        "pricing_tiers": [
          {
            "tier_name": "Free",
            "tier_description": "Best for getting started with Rev for free",
            "monthly_price": 0.0,
            "annual_price": 0.0,
            "annual_discount_percentage": null,
            "setup_fee": null,
            "features": [
              "45 minutes of AI transcription per month",
              "Access to pay-per-minute 99% accurate human transcripts, captions, and subtitles",
              "AI Notetaker for Google, Teams, and Zoom",
              "Rev Mobile App for recording and editing on the go",
              "Interactive transcript editor"
            ],
            "limits": {
              "users": "unlimited",
              "storage": "unlimited",
              "operations": "unlimited",
              "api_calls": null,
              "integrations": "unlimited",
              "custom_limits": [
                {
                  "name": "AI transcription minutes",
                  "value": 45
                }
              ]
            }
          },
          {
            "tier_name": "Basic",
            "tier_description": "Built for productivity in individuals and small teams",
            "monthly_price": 14.99,
            "annual_price": 9.99,
            "annual_discount_percentage": 33.0,
            "setup_fee": null,
            "features": [
              "20 hours of AI transcription per month",
              "90 minutes per recording",
              "15% discount on human transcripts",
              "AI Notetaker for Google, Teams, and Zoom",
              "Rev Mobile App for recording and editing on the go",
              "Interactive transcript editor",
              "Unlimited use of AI Assistant & AI Summary Templates"
            ],
            "limits": {
              "users": "unlimited",
              "storage": "unlimited",
              "operations": "unlimited",
              "api_calls": null,
              "integrations": "unlimited",
              "custom_limits": [
                {
                  "name": "AI transcription minutes",
                  "value": "20 hours"
                }
              ]
            }
          },
          {
            "tier_name": "Pro",
            "tier_description": "Built for larger teams who need advanced features and collaboration",
            "monthly_price": 34.99,
            "annual_price": 20.99,
            "annual_discount_percentage": 40.0,
            "setup_fee": null,
            "features": [
              "100 hours of AI transcription per month",
              "No limit on file length",
              "30% discount on human transcripts",
              "AI captions in 37+ languages",
              "AI Notetaker for Google, Teams, and Zoom",
              "Rev Mobile App for recording and editing on the go",
              "Interactive transcript editor",
              "Unlimited use of AI Assistant & AI Summary Templates",
              "Interactive captions editor",
              "Customizable AI Summary Templates"
            ],
            "limits": {
              "users": "unlimited",
              "storage": "unlimited",
              "operations": "unlimited",
              "api_calls": null,
              "integrations": "unlimited",
              "custom_limits": [
                {
                  "name": "AI transcription minutes",
                  "value": "100 hours"
                }
              ]
            }
          },
          {
            "tier_name": "Enterprise",
            "tier_description": "Built for organizations needing security, management, and customized features",
            "monthly_price": null,
            "annual_price": null,
            "annual_discount_percentage": null,
            "setup_fee": null,
            "features": [
              "100 hours of AI transcription per month",
              "No limit on file length",
              "Custom discounts on human transcripts",
              "AI captions in 37+ languages",
              "AI Notetaker for Google, Teams, and Zoom",
              "Rev Mobile App for recording and editing on the go",
              "Interactive transcript editor",
              "Unlimited use of AI Assistant & AI Summary Templates",
              "Interactive captions editor",
              "Unlimited customizable AI templates tailored just for you",
              "Enterprise-grade privacy",
              "HIPAA and SOC 2 Type II compliance",
              "SSO & Domain Claiming"
            ],
            "limits": {
              "users": "unlimited",
              "storage": "unlimited",
              "operations": "unlimited",
              "api_calls": null,
              "integrations": "unlimited",
              "custom_limits": [
                {
                  "name": "AI transcription minutes",
                  "value": "100 hours"
                }
              ]
            }
          }
        ],
        "usage_based_pricing": [
          {
            "metric_name": "Human Transcription",
            "unit": "per minute",
            "base_price": 1.99,
            "tiers": null
          },
          {
            "metric_name": "AI Transcription",
            "unit": "per minute",
            "base_price": 0.25,
            "tiers": null
          },
          {
            "metric_name": "Human Captions",
            "unit": "per minute",
            "base_price": 1.99,
            "tiers": null
          },
          {
            "metric_name": "AI Captions",
            "unit": "per minute",
            "base_price": 0.25,
            "tiers": null
          },
          {
            "metric_name": "Global Subtitles",
            "unit": "per minute",
            "base_price": 6.49,
            "tiers": [
              {
                "min": null,
                "max": null,
                "price": 15.99
              }
            ]
          }
        ],
        "ai_specific_pricing": {
          "has_token_based_pricing": false,
          "input_token_price": null,
          "output_token_price": null,
          "models_pricing": null,
          "has_inference_pricing": false,
          "has_fine_tuning_pricing": false,
          "has_training_pricing": false,
          "ai_addon_available": true
        },
        "promotional_offers": [
          {
            "offer_name": "Free Tier Promotion",
            "offer_description": "Get 300 minutes of AI transcription for free.",
            "discount_percentage": null,
            "offer_url": "https://www.rev.com/pricing",
            "valid_until": null
          }
        ],
        "additional_fees": null,
        "extraction_timestamp": "2025-04-15T03:35:23.489929",
        "schema_validated": true,
        "confidence_score": 95,
        "extraction_error": false,
        "json_repaired": false
      },
      "pricing_analyzed": true
    }
  ],
  "results_directory": "pricing_results\\rev\\20250415_033523"
}