{
  "app_name": "GivingFuel",
  "app_slug": "givingfuel",
  "search_term": "Find the official pricing page URL for GivingFuel (givingfuel.com). Only provide the exact URL to the pricing page, not a summary of pricing information.",
  "timestamp": 1744723392.6545951,
  "response_text": [
    "The official pricing page for GivingFuel can be found at: [https://www.givingfuel.com/pricing](https://www.givingfuel.com/pricing)\u30103:1\u2020source\u3011."
  ],
  "citations": [
    {
      "title": "Pricing Plans - GivingFuel",
      "url": "https://www.givingfuel.com/plans"
    }
  ],
  "extracted_content": [
    {
      "url": "https://www.givingfuel.com/pricing",
      "is_accessible": true,
      "content": "Sales Questions\n\nSupport Questions\n\n![Image 1](https://cdn.prod.website-files.com/5fb2eb1d9d0b44ee7d07fb39/5fb2eb1d9d0b44d82807fcd3_x.svg)\n\n[![Image 2](https://cdn.prod.website-files.com/6099a69bddeacc2dbbd0761e/60a29e74101c41a7247c6b05_givingfuel-logo.png)](https://www.givingfuel.com/)\n\nEverything Your Organization Needs to Fundraise\n-----------------------------------------------\n\nFree to You,  \nRespectful to Your Donors\n\nAll-In Plan\n\n$0/month\n\n[Get Started](https://www.givingfuel.com/sign-up)**Optional transaction fees  \n****for** **donors****:  \n**\n\nPlatform Fee (1.5%)  \n+\n\nStandard Credit Card Fees\n\n**\ud83c\udfaf Your Success is Our Priority**\n-----------------------------------\n\nMost donors (~80%) choose to cover the fees\n\nWhen they do, 100% of their gift goes to your mission\n\nIf they don't, you \\*only\\* pay the credit card fees\n\n**What is Included?**\n---------------------\n\nEverything GivingFuel\u00a0Offers\n\n![Image 3](https://cdn.prod.website-files.com/6099a69bddeacc2dbbd0761e/60db6f4986410aee6c28ad8c_Icon%20Drag%20%26%20Drop.png)\n\n### Donation Form / Page Builder\n\nCreate powerful customization tools that handle your most **complex fundraising needs**, and sophisticated donation forms that **match your brand** perfectly.\n\n![Image 4](https://cdn.prod.website-files.com/6099a69bddeacc2dbbd0761e/60dc6f8a2513617832cfa598_Icon%20Dynamic%20Data%20Capture.png)\n\n### Donor Management & CRM\n\nYour complete view of donor relationships in one place. Track giving history, manage recurring donations, segment donors, and get the insights you need to strengthen donor relationships and increase retention.\n\n![Image 5](https://cdn.prod.website-files.com/6099a69bddeacc2dbbd0761e/60be820296f53a09aedfd0f2_comm-icon.png)\n\n### Marketing & Donor Engagement\n\nConnect with donors where they are. Send targeted emails, set up **automated emails** and **text messages**, and personalized communications that keep supporters engaged with your mission and inspire them to give again.\n\n![Image 6](https://cdn.prod.website-files.com/6099a69bddeacc2dbbd0761e/60be925fab1d98264aaab232_Icon%20Funding.png)\n\n### Payment Processing for Nonprofits\n\nBuilt specifically for nonprofit needs with enhanced **fraud protection**, **simple reconciliation**, and complete control over your donations. Accept **ACH** payments, enable donors to cover fees, and get detailed transaction reporting.\n\n![Image 7](https://cdn.prod.website-files.com/6099a69bddeacc2dbbd0761e/60be8135c977beabdff72f69_t2g-icon.png)\n\n### Digital Payments (Coming Soon)\n\nMake giving frictionless with **Apple Pay** and **Google Pay** support. Let donors give instantly using their preferred digital payment method, increasing conversion rates and donation amounts.\n\n![Image 8](https://cdn.prod.website-files.com/6099a69bddeacc2dbbd0761e/60be825c99c2716563eeff8f_rec-icon.png)\n\n#### Recurring Payment Auto Updater (Coming Soon)\n\nNever lose a recurring donation to an expired card again. Automatically update expired or canceled cards with new payment information, maintaining your consistent revenue stream without manual intervention.  \n\u200d\n\n![Image 9](https://cdn.prod.website-files.com/6099a69bddeacc2dbbd0761e/616f36f9e0a9d280ab3f92a9_icon-grow.png)\n\n### Customizable Reporting & Analytics\n\nGet the insights you need with flexible reporting tools. Create custom reports, track key metrics, and export data in the format you need - all with just a few clicks.\n\n![Image 10](https://cdn.prod.website-files.com/6099a69bddeacc2dbbd0761e/60e7a4dd3857075356e339b7_icon-close.png)\n\n### Events, Registration & Ticketing\n\nEverything you need to run successful fundraising events. Manage registrations, assign seating, process tickets, and track attendance while maximizing donations through integrated fundraising tools.\n\n![Image 11](https://cdn.prod.website-files.com/6099a69bddeacc2dbbd0761e/60be9336b385ab553e5bf309_crm-icon.png)\n\n### Integrations\n\nConnect GivingFuel with your favorite tools. Seamlessly sync data with popular CRM, email, accounting, and other platforms to streamline your operations and save time.\n\nSee All Features\n----------------\n\nDiscover everything you can build with our flexible donation tools.\n\n[Learn More](https://www.givingfuel.com/features)\n\n**FAQ**\n-------\n\n### No contracts? Seriously?  \n\nIt\u2019s true - no contracts. For organizations doing impactful work in their communities or around the world, we didn\u2019t like the idea of anyone feeling stuck in a contract they didn\u2019t want. With GivingFuel you can leave at any time. No hard feelings. Your donor data belongs to you and we\u2019ll even help you move it.\n\n### Can I migrate recurring donations to keep them processing?  \n\nYou can! If you have recurring donors on another platform, our team can help you keep recurring gifts flowing as you switch to GivingFuel. Fees discussed during onboarding. [Learn more about the process](https://help.givingfuel.com/en/articles/2587000-migrate-and-import-your-recurring-donations-from-another-payment-processor). Questions? [Email us](mailto:team@givingfuel.com).\n\n### Can I migrate my historic donation data into GivingFuel?  \n\nYou can!\u00a0More info on this is provided in the onboarding process.\n\n### What payment gateways can I use?  \n\nGivingFuel by default works with our in house payment processor called Webconnex Payments. If you are processing $500,000 or more in online donations annually and are hesitant to switch payment processors we can discuss migrating you and keeping your current payment processor. [Contact Sales](https://www.givingfuel.com/sign-up).\n\n### Is your pricing \u201cper contact\u201d?  \n\nNo. GivingFuel has one simple plan that doesn\u2019t change based on the amount of contacts, donors, or records you use on the platform.\n\n### Do we have to be a nonprofit to use GivingFuel?  \n\nNope. While most of our customers are nonprofit organizations, any type of business or sole proprietorship can use GivingFuel.\n\n### Can you do whitelabelling, domain masking, or logo removal?  \n\nYes, [email us](mailto:team@givingfuel.com) for options and pricing.\n\nTake the Next Step\n------------------\n\nBook a call with our team to see if GivingFuel could be right for you.\n\n[Get Started](https://www.givingfuel.com/sign-up)\n\nNo hidden fees, no surprises, no shenanigans. Just an affordable monthly fee, basic credit card processing, and free & friendly support.",
      "error": null,
      "pricing_data": {
        "app_id": "givingfuel",
        "app_name": "GivingFuel",
        "app_slug": "givingfuel",
        "pricing_url": "https://www.givingfuel.com/pricing",
        "source_url": "https://www.givingfuel.com/",
        "all_pricing_urls": [
          "https://www.givingfuel.com/pricing"
        ],
        "price_model_type": [
          "PriceModelType.FREE_TIER",
          "PriceModelType.USAGE_BASED"
        ],
        "has_free_tier": true,
        "has_free_trial": false,
        "free_trial_period_days": null,
        "currency": "USD",
        "is_pricing_public": true,
        "pricing_page_accessible": true,
        "pricing_notes": "GivingFuel offers a free tier with optional transaction fees for donors.",
        "pricing_tiers": [
          {
            "tier_name": "All-In Plan",
            "tier_description": "Includes all features offered by GivingFuel.",
            "monthly_price": 0.0,
            "annual_price": null,
            "annual_discount_percentage": null,
            "setup_fee": null,
            "features": [
              "Donation Form / Page Builder",
              "Donor Management & CRM",
              "Marketing & Donor Engagement",
              "Payment Processing for Nonprofits",
              "Digital Payments (Coming Soon)",
              "Recurring Payment Auto Updater (Coming Soon)",
              "Customizable Reporting & Analytics",
              "Events, Registration & Ticketing",
              "Integrations"
            ],
            "limits": {
              "users": "unlimited",
              "storage": "unlimited",
              "operations": "unlimited",
              "api_calls": "unlimited",
              "integrations": "unlimited",
              "custom_limits": null
            }
          }
        ],
        "usage_based_pricing": [
          {
            "metric_name": "Platform Fee",
            "unit": "percentage",
            "base_price": 1.5,
            "tiers": null
          },
          {
            "metric_name": "Standard Credit Card Fees",
            "unit": "percentage",
            "base_price": null,
            "tiers": null
          }
        ],
        "ai_specific_pricing": null,
        "promotional_offers": null,
        "additional_fees": null,
        "extraction_timestamp": "2025-04-15T09:23:24.464058",
        "schema_validated": true,
        "confidence_score": 100,
        "extraction_error": false,
        "json_repaired": false
      },
      "pricing_analyzed": true
    },
    {
      "url": "https://www.givingfuel.com/plans",
      "is_accessible": true,
      "content": "Pricing Plans - GivingFuel\n===============\n    \n\n[![Image 1](https://cdn.prod.website-files.com/6099a69bddeacc2dbbd0761e/60a29e74101c41a7247c6b05_givingfuel-logo.png)](https://www.givingfuel.com/)\n\nChoose Your Plan To Get Started\n===============================\n\nCreate your GivingFuel account by selecting a plan below. Enjoy 3 months free with no contracts or credit card required at sign up.  \n\n### Starter  \n\nFor smaller orgs raising less than $25,000 online annually.\n\n### $0 / MONTH  \n\n2% per donation plus standard credit card rates of 2.9% + 30\u00a2.\n\nBasic fundraising\n\nDonor management\n\n[Sign Up](https://signup.givingfuel.com/?packageID=1&utm_cta=package-page)\n\n![Image 2](https://cdn.prod.website-files.com/6099a69bddeacc2dbbd0761e/60be905bec9a5362cfbb4abc_popular.png)\n\nMost popular\n\n### Pro  \n\nFor growing orgs looking to accelerate their fundraising.\n\n### $59 $0 / MONTH  \n\n3 months free, then $59 / month\n\n2.9% + 30\u00a2 credit card fee per donation\n\nText-to-give\n\nPeer-to-peer fundraising\n\n[Sign Up](https://signup.givingfuel.com/?packageID=2&utm_cta=package-page)\n\n### Enterprise  \n\nFor high impact orgs managing multiple campaigns and donor management tasks.\n\n### $99 $0 / MONTH  \n\n3 months free, then $99 / month\n\n2.9% + 30\u00a2 credit card fee per donation\n\nDonor accounts\n\nReduced text-to-give fees\n\n[Sign Up](https://signup.givingfuel.com/?packageID=3&utm_cta=package-page)\n\n### Enterprise Plus  \n\nFor larger orgs raising $1m+ annually online and requiring advanced onboarding and support.\n\n$149 / MONTH\n\n$1-3 million online annually\n\n$249 / MONTH\n\n$3-5 million online annually\n\n$349 / MONTH\n\n$5 million + online annually\n\n[Sign Up](https://signup.givingfuel.com/?packageID=3&utm_cta=package-page)\n\n[Support Center](https://help.givingfuel.com/en/)[Chat with support](https://www.givingfuel.com/help-support)[Schedule a support call](https://calendly.com/givingfuel/solutions?month=2021-07)[Leave a message for support: (888) 317-4539](tel:+18883174539)[Email support](mailto:team@givingfuel.com)\n\n[Features](https://www.givingfuel.com/features)[Pricing](https://www.givingfuel.com/pricing)[Demo](https://www.givingfuel.com/on-demand-demo---form)[](https://www.givingfuel.com/why-switch)[Blog](https://www.givingfuel.com/blog)\n\n[Sign Up](https://www.givingfuel.com/sign-up)[GivingFuel Academy](https://www.givingfuel.com/academy)[Sign In](https://auth.givingfuel.com/)[Security](https://www.givingfuel.com/security)[System status](http://status.webconnex.com/)\n\n\u00a9 Webconnex 2025\n\n[Terms](https://www.givingfuel.com/terms-of-service)[Privacy](https://www.givingfuel.com/privacy-policy)\n\nWe, like the rest of the internet, use cookies and similar tracking technologies that are essential to make our site function, improve your experience, and display personalized content. By continuing to use the site you agree to our [Privacy Policy](https://www.givingfuel.com/privacy-policy) and [Terms of Service.](https://www.givingfuel.com/terms-of-service)\n\nUnderstood\n\nCreate your GivingFuel account by selecting a plan below. Enjoy 3 months free with no contracts or credit card required at sign up.",
      "error": null,
      "pricing_data": {
        "app_id": "givingfuel",
        "app_name": "GivingFuel",
        "app_slug": "givingfuel",
        "pricing_url": "https://www.givingfuel.com/pricing",
        "source_url": "https://www.givingfuel.com/pricing",
        "all_pricing_urls": [
          "https://www.givingfuel.com/pricing"
        ],
        "price_model_type": [
          "PriceModelType.SUBSCRIPTION",
          "PriceModelType.USAGE_BASED"
        ],
        "has_free_tier": true,
        "has_free_trial": true,
        "free_trial_period_days": 90,
        "currency": "USD",
        "is_pricing_public": true,
        "pricing_page_accessible": true,
        "pricing_notes": "Pricing includes subscription fees and usage-based fees per donation.",
        "pricing_tiers": [
          {
            "tier_name": "Starter",
            "tier_description": "For smaller orgs raising less than $25,000 online annually.",
            "monthly_price": 0.0,
            "annual_price": null,
            "annual_discount_percentage": null,
            "setup_fee": null,
            "features": [
              "Basic fundraising",
              "Donor management"
            ],
            "limits": {
              "users": "unlimited",
              "storage": "unlimited",
              "operations": "unlimited",
              "api_calls": "unlimited",
              "integrations": "unlimited",
              "custom_limits": [
                {
                  "name": "Annual online fundraising limit",
                  "value": "$25,000"
                }
              ]
            }
          },
          {
            "tier_name": "Pro",
            "tier_description": "For growing orgs looking to accelerate their fundraising.",
            "monthly_price": 59.0,
            "annual_price": null,
            "annual_discount_percentage": null,
            "setup_fee": null,
            "features": [
              "Text-to-give",
              "Peer-to-peer fundraising"
            ],
            "limits": {
              "users": "unlimited",
              "storage": "unlimited",
              "operations": "unlimited",
              "api_calls": "unlimited",
              "integrations": "unlimited",
              "custom_limits": null
            }
          },
          {
            "tier_name": "Enterprise",
            "tier_description": "For high impact orgs managing multiple campaigns and donor management tasks.",
            "monthly_price": 99.0,
            "annual_price": null,
            "annual_discount_percentage": null,
            "setup_fee": null,
            "features": [
              "Donor accounts",
              "Reduced text-to-give fees"
            ],
            "limits": {
              "users": "unlimited",
              "storage": "unlimited",
              "operations": "unlimited",
              "api_calls": "unlimited",
              "integrations": "unlimited",
              "custom_limits": null
            }
          },
          {
            "tier_name": "Enterprise Plus",
            "tier_description": "For larger orgs raising $1m+ annually online and requiring advanced onboarding and support.",
            "monthly_price": 149.0,
            "annual_price": null,
            "annual_discount_percentage": null,
            "setup_fee": null,
            "features": [
              "Advanced onboarding",
              "Enhanced support"
            ],
            "limits": {
              "users": "unlimited",
              "storage": "unlimited",
              "operations": "unlimited",
              "api_calls": "unlimited",
              "integrations": "unlimited",
              "custom_limits": [
                {
                  "name": "Annual online fundraising limit",
                  "value": "$1-3 million"
                }
              ]
            }
          },
          {
            "tier_name": "Enterprise Plus",
            "tier_description": "For larger orgs raising $3-5 million online annually.",
            "monthly_price": 249.0,
            "annual_price": null,
            "annual_discount_percentage": null,
            "setup_fee": null,
            "features": [
              "Advanced onboarding",
              "Enhanced support"
            ],
            "limits": {
              "users": "unlimited",
              "storage": "unlimited",
              "operations": "unlimited",
              "api_calls": "unlimited",
              "integrations": "unlimited",
              "custom_limits": [
                {
                  "name": "Annual online fundraising limit",
                  "value": "$3-5 million"
                }
              ]
            }
          },
          {
            "tier_name": "Enterprise Plus",
            "tier_description": "For larger orgs raising $5 million+ online annually.",
            "monthly_price": 349.0,
            "annual_price": null,
            "annual_discount_percentage": null,
            "setup_fee": null,
            "features": [
              "Advanced onboarding",
              "Enhanced support"
            ],
            "limits": {
              "users": "unlimited",
              "storage": "unlimited",
              "operations": "unlimited",
              "api_calls": "unlimited",
              "integrations": "unlimited",
              "custom_limits": [
                {
                  "name": "Annual online fundraising limit",
                  "value": "$5 million+"
                }
              ]
            }
          }
        ],
        "usage_based_pricing": [
          {
            "metric_name": "Donation processing",
            "unit": "per donation",
            "base_price": 2.0,
            "tiers": [
              {
                "min": 0.0,
                "max": "unlimited",
                "price": 2.0
              }
            ]
          },
          {
            "metric_name": "Credit card processing",
            "unit": "per transaction",
            "base_price": 2.9,
            "tiers": [
              {
                "min": 0.0,
                "max": "unlimited",
                "price": 2.9
              }
            ]
          }
        ],
        "ai_specific_pricing": null,
        "promotional_offers": [
          {
            "offer_name": "3 Months Free",
            "offer_description": "Enjoy 3 months free with no contracts or credit card required at sign up.",
            "discount_percentage": 100.0,
            "offer_url": "https://www.givingfuel.com/pricing",
            "valid_until": null
          }
        ],
        "additional_fees": [
          {
            "fee_name": "Credit card processing fee",
            "fee_amount": 2.9,
            "fee_description": "Standard credit card rates of 2.9% + 30\u00a2 per transaction."
          }
        ],
        "extraction_timestamp": "2025-04-15T09:23:37.190894",
        "schema_validated": true,
        "confidence_score": 100,
        "extraction_error": false,
        "json_repaired": false
      },
      "pricing_analyzed": true
    }
  ],
  "results_directory": "pricing_results\\givingfuel\\20250415_092337"
}