{
  "app_name": "Vimeo",
  "app_slug": "vimeo",
  "search_term": "Find the official pricing page URL for Vimeo (vimeo.com). Only provide the exact URL to the pricing page, not a summary of pricing information.",
  "timestamp": 1744710149.800402,
  "response_text": [
    "The official pricing page for Vimeo is at: [https://vimeo.com/upgrade](https://vimeo.com/upgrade)\u30103:0\u2020source\u3011."
  ],
  "citations": [
    {
      "title": "Pricing plans | From free plans to enterprise solutions - Vimeo",
      "url": "https://vimeo.com/upgrade-plan"
    }
  ],
  "extracted_content": [
    {
      "url": "https://vimeo.com/upgrade-plan",
      "is_accessible": true,
      "content": "Choose a plan\n-------------\n\n### Free\n\nTry Vimeo for free\n\n### Starter\n\nGrow your business with essential video tools\n\n$12\n---\n\nper month, billed annually\n--------------------------\n\nor $20 billed monthly\n---------------------\n\n1+ seat\n\n100GB storage\n\nEverything in Free, plus:\n\n*   Privacy controls\n    \n*   Custom video player\n    \n*   Custom URLs\n    \n*   Review and collaboration tools\n    \n*   Auto closed captioning\n    \n\nRecommended\n-----------\n\n### Standard\n\nBoost your impact with premium creation\n\n$25\n---\n\nper month, billed annually\n--------------------------\n\nor $41 billed monthly\n---------------------\n\n5+ seats\n\n2TB storage\n\nEverything in Starter, plus:\n\n*   Brand kit\n    \n*   Teleprompter\n    \n*   Text-based video editing\n    \n*   AI script generator\n    \n*   Engagement and social analytics\n    \n\n### Advanced\n\nDrive engagement with Vimeo AI and events\n\n$75\n---\n\nper month, billed annually\n--------------------------\n\nor $125 billed monthly\n----------------------\n\n10+ seats\n\n7TB storage\n\nEverything in Standard, plus:\n\n*   AI-generated chapters and text summaries\n    \n*   Enable creators to ask questions on videos\n    \n*   Host live broadcasts and webinars\n    \n*   Stream to multiple destinations\n    \n*   Branded invite and reminder emails\n    \n*   Live chat, polls, and Q&A\n    \n\n### Enterprise\n\nMore security, control, and support\n\nTalk to our team for pricing\n----------------------------\n\nMore seats\n\nMore Storage & Bandwidth\n\nEverything in Advanced, plus:\n\n*   More storage and bandwidth\n    \n*   More seats\n    \n*   Custom permissions\n    \n*   Advanced AI capabilities\n    \n*   SSO (SAML) and SCIM (OKTA, AZURE)\n    \n*   Advanced analytics and marketing integrations\n    \n*   Events with breakout rooms and live Q&A\n    \n*   Quality events (backup streams, eCDN)\n    \n*   Dedicated support\n    \n\nThe best brands in the world trust Vimeo\n\n![Image 1](https://i.vimeocdn.com/custom_asset/092abed72dbe7f5dc1f73cb09b60c04c)\n\n![Image 2](https://i.vimeocdn.com/custom_asset/3498a05852d3a00f0c97d96dcc17b9c7)\n\n![Image 3](https://i.vimeocdn.com/custom_asset/41fb227d68ad883f2591e8d89396ec3d)\n\n![Image 4](https://i.vimeocdn.com/custom_asset/f4c9eef1ad28101635d4002615e56c48)\n\n![Image 5](https://i.vimeocdn.com/custom_asset/a19232ad45048c17575d09c9ef009553)\n\n![Image 6](https://i.vimeocdn.com/custom_asset/e8751f3c931697a7e5f5e3313b277de6)\n\n![Image 7](https://i.vimeocdn.com/custom_asset/8cdc134380a73439a6a9b17f9794552e)\n\n![Image 8](https://i.vimeocdn.com/custom_asset/17fbd9c2648e0a033b4f1f1d72649ddf)\n\n![Image 9](https://i.vimeocdn.com/custom_asset/092abed72dbe7f5dc1f73cb09b60c04c)\n\n![Image 10](https://i.vimeocdn.com/custom_asset/3498a05852d3a00f0c97d96dcc17b9c7)\n\n![Image 11](https://i.vimeocdn.com/custom_asset/41fb227d68ad883f2591e8d89396ec3d)\n\n![Image 12](https://i.vimeocdn.com/custom_asset/f4c9eef1ad28101635d4002615e56c48)\n\n![Image 13](https://i.vimeocdn.com/custom_asset/a19232ad45048c17575d09c9ef009553)\n\n![Image 14](https://i.vimeocdn.com/custom_asset/e8751f3c931697a7e5f5e3313b277de6)\n\n![Image 15](https://i.vimeocdn.com/custom_asset/8cdc134380a73439a6a9b17f9794552e)\n\n![Image 16](https://i.vimeocdn.com/custom_asset/17fbd9c2648e0a033b4f1f1d72649ddf)\n\n![Image 17](https://i.vimeocdn.com/custom_asset/092abed72dbe7f5dc1f73cb09b60c04c)\n\n![Image 18](https://i.vimeocdn.com/custom_asset/3498a05852d3a00f0c97d96dcc17b9c7)\n\n![Image 19](https://i.vimeocdn.com/custom_asset/41fb227d68ad883f2591e8d89396ec3d)\n\n![Image 20](https://i.vimeocdn.com/custom_asset/f4c9eef1ad28101635d4002615e56c48)\n\n![Image 21](https://i.vimeocdn.com/custom_asset/a19232ad45048c17575d09c9ef009553)\n\n![Image 22](https://i.vimeocdn.com/custom_asset/e8751f3c931697a7e5f5e3313b277de6)\n\n![Image 23](https://i.vimeocdn.com/custom_asset/8cdc134380a73439a6a9b17f9794552e)\n\n![Image 24](https://i.vimeocdn.com/custom_asset/17fbd9c2648e0a033b4f1f1d72649ddf)\n\nWhat's different about hosting videos on Vimeo?\n-----------------------------------------------\n\nVideos hosted on Vimeo can stream up to 4K Ultra HD so your viewers see your videos in the highest quality and unlike other platforms, we never put ads before, during, or after your videos - even on our Free plan.\n\nWill viewers see third-party ads on my videos?\n----------------------------------------------\n\nCan I cancel anytime?\n---------------------\n\nIs there a video limit?\n-----------------------\n\nWhat happens if I go over my storage limit?\n-------------------------------------------\n\nDo team members share the storage limit?\n----------------------------------------\n\nIs the Free plan just a free trial?\n-----------------------------------\n\nDo you have duration or file-size restrictions?\n-----------------------------------------------\n\nCan I stream live events with Vimeo?\n------------------------------------\n\nDo Vimeo's self-serve plans have a bandwidth limit?\n---------------------------------------------------\n\nWhere are the different types of seats or users I can have on my plan?\n----------------------------------------------------------------------\n\n[Go to Help Center](https://vimeo.com/help/contact)\n\nJoin the web\u2019s most supportive community of creators and get high-quality tools for hosting, sharing, and streaming videos in gorgeous HD and 4K with no ads.",
      "error": null,
      "pricing_data": {
        "app_id": "vimeo",
        "app_name": "Vimeo",
        "app_slug": "vimeo",
        "pricing_url": null,
        "source_url": null,
        "all_pricing_urls": null,
        "price_model_type": [
          "PriceModelType.SUBSCRIPTION",
          "PriceModelType.QUOTE_BASED",
          "PriceModelType.FREE_TIER"
        ],
        "has_free_tier": true,
        "has_free_trial": false,
        "free_trial_period_days": null,
        "currency": "USD",
        "is_pricing_public": true,
        "pricing_page_accessible": true,
        "pricing_notes": null,
        "pricing_tiers": [
          {
            "tier_name": "Free",
            "tier_description": "Try Vimeo for free",
            "monthly_price": 0.0,
            "annual_price": 0.0,
            "annual_discount_percentage": null,
            "setup_fee": null,
            "features": [
              "Stream videos up to 4K Ultra HD",
              "No ads before, during, or after videos"
            ],
            "limits": {
              "users": "unlimited",
              "storage": "limited",
              "operations": null,
              "api_calls": null,
              "integrations": null,
              "custom_limits": null
            }
          },
          {
            "tier_name": "Starter",
            "tier_description": "Grow your business with essential video tools",
            "monthly_price": 20.0,
            "annual_price": 144.0,
            "annual_discount_percentage": 40.0,
            "setup_fee": null,
            "features": [
              "Privacy controls",
              "Custom video player",
              "Custom URLs",
              "Review and collaboration tools",
              "Auto closed captioning"
            ],
            "limits": {
              "users": 1,
              "storage": "100GB",
              "operations": null,
              "api_calls": null,
              "integrations": null,
              "custom_limits": null
            }
          },
          {
            "tier_name": "Standard",
            "tier_description": "Boost your impact with premium creation",
            "monthly_price": 41.0,
            "annual_price": 300.0,
            "annual_discount_percentage": 39.0,
            "setup_fee": null,
            "features": [
              "Brand kit",
              "Teleprompter",
              "Text-based video editing",
              "AI script generator",
              "Engagement and social analytics"
            ],
            "limits": {
              "users": 5,
              "storage": "2TB",
              "operations": null,
              "api_calls": null,
              "integrations": null,
              "custom_limits": null
            }
          },
          {
            "tier_name": "Advanced",
            "tier_description": "Drive engagement with Vimeo AI and events",
            "monthly_price": 125.0,
            "annual_price": 900.0,
            "annual_discount_percentage": 40.0,
            "setup_fee": null,
            "features": [
              "AI-generated chapters and text summaries",
              "Enable creators to ask questions on videos",
              "Host live broadcasts and webinars",
              "Stream to multiple destinations",
              "Branded invite and reminder emails",
              "Live chat, polls, and Q&A"
            ],
            "limits": {
              "users": 10,
              "storage": "7TB",
              "operations": null,
              "api_calls": null,
              "integrations": null,
              "custom_limits": null
            }
          },
          {
            "tier_name": "Enterprise",
            "tier_description": "More security, control, and support",
            "monthly_price": null,
            "annual_price": null,
            "annual_discount_percentage": null,
            "setup_fee": null,
            "features": [
              "More storage and bandwidth",
              "More seats",
              "Custom permissions",
              "Advanced AI capabilities",
              "SSO (SAML) and SCIM (OKTA, AZURE)",
              "Advanced analytics and marketing integrations",
              "Events with breakout rooms and live Q&A",
              "Quality events (backup streams, eCDN)",
              "Dedicated support"
            ],
            "limits": {
              "users": "custom",
              "storage": "custom",
              "operations": null,
              "api_calls": null,
              "integrations": null,
              "custom_limits": null
            }
          }
        ],
        "usage_based_pricing": null,
        "ai_specific_pricing": null,
        "promotional_offers": null,
        "additional_fees": null,
        "extraction_timestamp": "2025-04-15T05:43:00.063358",
        "schema_validated": true,
        "confidence_score": 100,
        "extraction_error": false,
        "json_repaired": false
      },
      "pricing_analyzed": true
    },
    {
      "url": "https://vimeo.com/upgrade",
      "is_accessible": false,
      "content": null,
      "error": "Exception: HTTPSConnectionPool(host='r.jina.ai', port=443): Read timed out. (read timeout=15)"
    }
  ],
  "results_directory": "pricing_results\\vimeo\\20250415_054315"
}