{
  "app_name": "AccuLynx",
  "app_slug": "acculynx",
  "search_term": "Find the official pricing page URL for AccuLynx (acculynx.com). Only provide the exact URL to the pricing page, not a summary of pricing information.",
  "timestamp": 1744726435.2131798,
  "response_text": [
    "The official pricing page for AccuLynx can be found at: [https://www.acculynx.com/plans](https://www.acculynx.com/plans)\u30103:0\u2020source\u3011."
  ],
  "citations": [
    {
      "title": "Plan Options | AccuLynx Pro vs. Elite",
      "url": "https://acculynx.com/plan-options/"
    }
  ],
  "extracted_content": [
    {
      "url": "https://acculynx.com/plan-options/",
      "is_accessible": true,
      "content": "TALK TO SALES SIGN IN \nPRODUCT\nPRODUCT\n\nSALES/CRM\nStay on top of your sales pipeline and win more\u00a0jobs\n\nFINANCE\nHandle the financial side of the business with\u00a0ease\n\nPRODUCTION\nManage and streamline every aspect of\u00a0production\n\nBUSINESS MANAGEMENT\nSimplify your processes and improve\u00a0collaboration\n\nFIELD APP\nAccess AccuLynx on the go with our easy-to-use mobile app\n\nENHANCEMENTS\nACCUPAY\nAPPCONNECTIONS\nMOBILE CREW APP\nCUSTOMER PORTAL\nREPORTSPLUS\nSMART(ER) DOCS\nTEXT MESSAGING\nPLATFORM OVERVIEW\nPLAN OPTIONS\nNEW ACCULYNX FEATURES\n\nSee what we\u2019ve just added to AccuLynx, including new integrations, communication features, document design tools, and more!\n\nSEE DEMO\nINTEGRATIONS\nPOPULAR INTEGRATIONS\n\nBEACON\nAccess Beacon materials and send orders from AccuLynx\n\nSRS DISTRIBUTION\nSee SRS\u2019s catalog and place your order from AccuLynx\n\nABC SUPPLY\nGet pricing and submit orders to ABC from AccuLynx\n\nQUICKBOOKS\nSync accounting data with this two-way\u00a0integration\n\nQUICKMEASURE\nGet QuickMeasure reports straight to your job file\n\nEAGLEVIEW\nOrder EagleView measurements directly from AccuLynx\n\nALL INTEGRATIONS\n\nEarn up to $2,000 when you place orders to ABC Supply through AccuLynx!\n\nApril 14\u2013May 30, 2025\n\nSTART EARNING\nRESOURCES\nRESOURCES\n\nBLOG\nAccess industry tips, best practices, news and more\n\nFAQ\nGet answers to our most frequently asked questions\n\nWEBINARS\nLevel up your skills with our educational\u00a0webinars\n\nCOMPARE ACCULYNX\nFind out how AccuLynx stacks up against competition\n\nROI CALCULATOR\nCalculate the ROI you could realize using\u00a0AccuLynx\n\nPODCAST\nHear roofing industry experts share tips and stories\n\nALL RESOURCES\nDEMO VIDEO\nLIVE ACCULYNX INTERVIEW\n\nHow one PE-backed roofing company scaled 3X with the right tech.\n\nApril 15 at 12 PM CST\n\nREGISTER NOW\nCOMPANY\nABOUT US\nCOMPANY NEWS\nCUSTOMERS\nCAREERS\nCONTACT US\nSUPPORT\nCUSTOMER SUPPORT\nKNOWLEDGE BASE\nPRODUCT UPDATES\nSEE DEMO\nGET PRICING\nAccuLynx plan options\n\nEvery roofing company is unique, so we offer two different plans for roofing contractors to choose from. Our knowledgeable team will work with you to select the right plan and provide a customized price quote.\n\nSEE DEMO\nGET PRICING\nWhat you get with the best all-in-one roofing contractor\u00a0software\n\nEach AccuLynx plan includes the tools you need to streamline your work and grow your roofing business,\u00a0plus:\n\nNo contracts\n\nOur monthly subscription option gives you flexibility so you\u2019re not locked in.\n\nTraining anytime\n\nAccess training whenever your team needs it as long as you\u2019re a customer.\n\nFast implementation\n\nYou\u2019ll be guided through the setup process and onboarded quickly.\n\nLive help\n\nCall and speak to a live person whenever you have questions.\n\nBest Roofing App\nPlatinum Nominee\nCrozdesk Top\nRanked Solution\nCategory Leader\nRoofing Software\nCategory Leader\nConstruction Estimating\nFront Runner\nConstruction Estimating\nBest SaaS Product\nfor CRM\nGreat Place to Work\nCertified Company\nHigh Performer\nConstruction Software\nShortlist\nConstruction Estimating\nBest Roofing App\nPlatinum Nominee\nCrozdesk Top\nRanked Solution\nCategory Leader\nRoofing Software\nCategory Leader\nConstruction Estimating\nFront Runner\nConstruction Estimating\nBest SaaS Product\nfor CRM\nGreat Place to Work\nCertified Company\nHigh Performer\nConstruction Software\nShortlist\nConstruction Estimating\nBest Roofing App\nPlatinum Nominee\nAccuLynx Pro and Elite plan features\n\nSee what roofing software features each plan has to offer.\n\nBUSINESS MANAGEMENT\tPRO\tELITE\nAutomations manager\t\t\nCustom email templates\t\t\nCustom reporting\t\t\nCustom workflow manager\t\t\nJob milestone tracker\t\t\nLead API\t\t\nLive activity feed\t\t\nMultiple company location set-up\t\t\nPersonal or role-based dashboards\t\t\nTemplate manager\t\t\nUser permission & location settings\t\t\nSALES & PRODUCTION\tPRO\tELITE\nAerial measurement ordering\t\t\nAI-based automatic lead scoring\t\t\nCustom materials library\t\t\nEmbedded web forms\t\t\nEstimates and contracts\t\t\nInvoicing\t\t\nLabor management and work orders\t\t\nLeads/CRM\t\t\nMortgage check tracking\t\t\nPermits tracking\t\t\nProduction calendar\t\t\nProduction status and trade reports\t\t\nProspecting reports\t\t\nSales pipeline and closing percentage reports\t\t\nSupplement tracking\t\t\nSupplier direct ordering\t\t\nCOMMUNICATION & COLLABORATION\tPRO\tELITE\nJob messaging & communications history\t\t\nMobile field app\t\t\nNotes, tasks, reminders, and notifications\t\t\nPhoto/video management & storage\t\t\nShared appointment calendar\t\t\nTask manager\t\t\nUnlimited document storage and sharing\t\t\nFINANCIAL MANAGEMENT\tPRO\tELITE\nAdvances and paybacks tracking\t\t\nCommissions\t\t\nJob costs and A/R tracking\t\t\nJob profit forecasting\t\t\nMarketing expense tracking\t\t\nProfit & loss analysis\t\t\nAdditional tools to enrich your plan\n\nAccuPay\n\nCustomer Portal\n\nSmart(er) Docs\n\nAccuFi\n\nReportsPlus\n\nTexting\n\nMobile Crew App\n\nAppConnections\n\nGet AccuLynx pricing and demo\n\nWe\u2019ll contact you with demo information and a custom price quote.\n\nSEE DEMO\nGET PRICING\nPRODUCT\nSales/CRM\nFinance\nProduction\nBusiness Management\nField App\nAccuPay\nAppConnections\nMobile Crew App\nCustomer Portal\nReportsPlus\nSmart(er) Docs\nTexting\nPlatform Overview\nPlan Options\nINTEGRATIONS\nBeacon Building Products\nSRS Distribution\nABC Supply\nQuickBooks\nEagleView\nGAF QuickMeasure\nAll Integrations\nRESOURCES\nBlog\nFAQ\nWebinars\nPodcast\nCompare AccuLynx\nROI Calculator\nAll Resources\nDemo Video\nCOMPANY\nAbout AccuLynx\nCompany News\nCustomers\nCareers\nContact Us\nSUPPORT\nCustomer Support\nKnowledge Base\nProduct Updates\nSign In \n\nAccuLynx is the leading, all-in-one roofing software designed to streamline every aspect of a roofing business. Since 2008, thousands of roofing companies have turned to our award-winning software to save time, simplify production, and sell more\u00a0profitable\u00a0jobs.\n\n\u00a9 2025 ExactLogix, Inc. All Rights Reserved.\n\nTerms of Use\nPrivacy Policy\nCopyright Policy\n\nExplore AccuLynx software plan options for your roofing business: Compare AccuLynx Pro vs. AccuLynx Elite features here.",
      "error": null,
      "pricing_data": {
        "app_id": "acculynx",
        "app_name": "AccuLynx",
        "app_slug": "acculynx",
        "pricing_url": null,
        "source_url": null,
        "all_pricing_urls": null,
        "price_model_type": [
          "PriceModelType.SUBSCRIPTION",
          "PriceModelType.QUOTE_BASED"
        ],
        "has_free_tier": false,
        "has_free_trial": false,
        "free_trial_period_days": null,
        "currency": "USD",
        "is_pricing_public": true,
        "pricing_page_accessible": true,
        "pricing_notes": "Pricing is customized based on the roofing company's needs and requires contacting sales for a quote.",
        "pricing_tiers": [
          {
            "tier_name": "Pro",
            "tier_description": "Includes essential features for business management, sales, production, communication, and financial management.",
            "monthly_price": null,
            "annual_price": null,
            "annual_discount_percentage": null,
            "setup_fee": null,
            "features": [
              "Automations manager",
              "Custom email templates",
              "Custom reporting",
              "Custom workflow manager",
              "Job milestone tracker",
              "Lead API",
              "Live activity feed",
              "Multiple company location set-up",
              "Personal or role-based dashboards",
              "Template manager",
              "User permission & location settings",
              "Aerial measurement ordering",
              "AI-based automatic lead scoring",
              "Custom materials library",
              "Embedded web forms",
              "Estimates and contracts",
              "Invoicing",
              "Labor management and work orders",
              "Leads/CRM",
              "Mortgage check tracking",
              "Permits tracking",
              "Production calendar",
              "Production status and trade reports",
              "Prospecting reports",
              "Sales pipeline and closing percentage reports",
              "Supplement tracking",
              "Supplier direct ordering",
              "Job messaging & communications history",
              "Mobile field app",
              "Notes, tasks, reminders, and notifications",
              "Photo/video management & storage",
              "Shared appointment calendar",
              "Task manager",
              "Unlimited document storage and sharing",
              "Advances and paybacks tracking",
              "Commissions",
              "Job costs and A/R tracking",
              "Job profit forecasting",
              "Marketing expense tracking",
              "Profit & loss analysis"
            ],
            "limits": null
          },
          {
            "tier_name": "Elite",
            "tier_description": "Includes all features of Pro plus additional advanced tools.",
            "monthly_price": null,
            "annual_price": null,
            "annual_discount_percentage": null,
            "setup_fee": null,
            "features": [
              "All features in Pro",
              "Additional tools to enrich your plan such as AccuPay, Customer Portal, Smart(er) Docs, AccuFi, ReportsPlus, Texting, Mobile Crew App, AppConnections"
            ],
            "limits": null
          }
        ],
        "usage_based_pricing": null,
        "ai_specific_pricing": null,
        "promotional_offers": [
          {
            "offer_name": "ABC Supply Order Incentive",
            "offer_description": "Earn up to $2,000 when you place orders to ABC Supply through AccuLynx.",
            "discount_percentage": null,
            "offer_url": null,
            "valid_until": "2025-05-30"
          }
        ],
        "additional_fees": null,
        "extraction_timestamp": "2025-04-15T10:14:13.651116",
        "schema_validated": true,
        "confidence_score": 100,
        "extraction_error": false,
        "json_repaired": false
      },
      "pricing_analyzed": true
    },
    {
      "url": "https://www.acculynx.com/plans",
      "is_accessible": true,
      "content": "Page not found | AccuLynx\n===============\n\n[![Image 2: AccuLynx](https://acculynx.com/wp-content/uploads/2021/05/acculynx-logo.svg)](https://www.acculynx.com/)\n\n[Talk to Sales![Image 3](https://acculynx.com/wp-content/uploads/2018/12/email-icon.svg)](https://www.acculynx.com/plans#) [Sign In](https://my.acculynx.com/signin/)\n\n[(608) 473-3800](tel:(608) 473-3800)\n\n[See Demo](https://www.acculynx.com/demonstration-request/)[Get Pricing](https://www.acculynx.com/pricing-request/)\n\n![Image 4](https://acculynx.com/wp-content/uploads/2019/01/email-icon-dark.svg)\n\nSend us an email\n----------------\n\nGet your questions about AccuLynx answered here.\n------------------------------------------------\n\nPlease fill out the form below, and one of our product experts will respond to you directly. We look forward to hearing from you.\n\nFirst Name\\*\n\nLast Name\\*\n\nCompany Name\\*\n\nPhone Number\\*\n\nEmail\\*\n\nMessage\\*\n\nPriority Level\n\nutm\\_source\n\nutm\\_medium\n\nutm\\_campaign\n\nutm\\_content\n\nutm\\_term\n\n[![Image 5: AccuLynx](https://acculynx.com/wp-content/uploads/2021/05/acculynx-logo.svg)](https://www.acculynx.com/)\n\n[See Demo](https://acculynx.com/demonstration-request/ \"Demonstration Request\")\n\n[Get Pricing](https://acculynx.com/pricing-request/ \"Pricing Request\")\n\nProduct\n-------\n\n*   [Sales/CRM](https://acculynx.com/features/roofing-crm/)\n*   [Finance](https://acculynx.com/features/roofing-finance/)\n*   [Production](https://acculynx.com/features/roofing-production-management/)\n*   [Business Management](https://acculynx.com/features/roofing-business-management/)\n*   [Field App](https://acculynx.com/roofing-app/)\n*   [AccuPay](https://acculynx.com/accupay-payment-processing/)\n*   [AppConnections](https://acculynx.com/appconnections/)\n*   [Mobile Crew App](https://acculynx.com/mobile-crew-app/)\n*   [Customer Portal](https://acculynx.com/features/customer-portal-software/)\n*   [ReportsPlus](https://acculynx.com/reportsplus/)\n*   [Smart(er) Docs](https://acculynx.com/smarter-docs/)\n*   [Texting](https://acculynx.com/text-messaging/)\n*   [Platform Overview](https://acculynx.com/features/)\n*   [Plan Options](https://acculynx.com/plan-options/)\n\nIntegrations\n------------\n\n*   [Beacon Building Products](https://acculynx.com/integrations/beacon/)\n*   [SRS Distribution](https://acculynx.com/integrations/srs-distribution/)\n*   [ABC Supply](https://acculynx.com/integrations/abc-supply/)\n*   [QuickBooks](https://acculynx.com/integrations/quickbooks/)\n*   [EagleView](https://acculynx.com/integrations/eagleview/)\n*   [GAF QuickMeasure](https://acculynx.com/integrations/gaf-quickmeasure/)\n*   [All Integrations](https://acculynx.com/integrations/)\n\nResources\n---------\n\n*   [Blog](https://acculynx.com/blog/)\n*   [FAQ](https://acculynx.com/faq/)\n*   [Webinars](https://acculynx.com/resources/#webinars)\n*   [Podcast](https://acculynx.com/podcast/)\n*   [Compare AccuLynx](https://acculynx.com/compare-acculynx-roofing-software/)\n*   [ROI Calculator](https://acculynx.com/roi-calculator/)\n*   [All Resources](https://acculynx.com/resources/)\n*   [Demo Video](https://www.acculynx.com/plans#)\n\nCompany\n-------\n\n*   [About AccuLynx](https://acculynx.com/about-acculynx/)\n*   [Company News](https://acculynx.com/blog/#news)\n*   [Customers](https://acculynx.com/customers/)\n*   [Careers](https://acculynx.com/careers/)\n*   [Contact Us](https://acculynx.com/contact-us/)\n\nSupport\n-------\n\n*   [Customer Support](https://acculynx.com/support/)\n*   [Knowledge Base](https://support.acculynx.com/hc/en-us)\n*   [Product Updates](https://acculynx.com/blog/#product-updates)\n*   [Sign In](https://my.acculynx.com/signin/)\n\n[](https://www.acculynx.com/plans#)\n\n*   [Product](https://www.acculynx.com/plans#)\n    *   ##### Product\n        \n        [Sales/CRM Stay on top of your sales pipeline and win more jobs](https://acculynx.com/features/roofing-crm/)\n        \n        [Finance Handle the financial side of the business with ease](https://acculynx.com/features/roofing-finance/)\n        \n        [Production Manage and streamline every aspect of production](https://acculynx.com/features/roofing-production-management/)\n        \n        [Business Management Simplify your processes and improve collaboration](https://acculynx.com/features/roofing-business-management/)\n        \n        [Field App Access AccuLynx on the go with our easy-to-use mobile app](https://acculynx.com/roofing-app/)\n        \n        ##### Enhancements\n        \n        [](https://acculynx.com/accupay-payment-processing/ \"AccuPay\")\n        \n        [###### AccuPay](https://acculynx.com/accupay-payment-processing/ \"AccuPay\")\n        \n        [](https://acculynx.com/appconnections/ \"AppConnections\")\n        \n        [###### AppConnections](https://acculynx.com/appconnections/ \"AppConnections\")\n        \n        [![Image 6: Crew App_Crews Icon](https://acculynx.com/wp-content/uploads/2020/06/Logo_CrewApp.svg)](https://acculynx.com/mobile-crew-app/ \"Mobile Crew App\")\n        \n        [###### Mobile Crew App](https://acculynx.com/mobile-crew-app/ \"Mobile Crew App\")\n        \n        [](https://acculynx.com/features/customer-portal-software/ \"Customer Portal\")\n        \n        [###### Customer Portal](https://acculynx.com/features/customer-portal-software/ \"Customer Portal\")\n        \n        [![Image 7](https://acculynx.com/wp-content/uploads/2020/06/Icon-ReportsPlus-Dark-Icon.svg)](https://acculynx.com/reportsplus/ \"ReportsPlus\")\n        \n        [###### ReportsPlus](https://acculynx.com/reportsplus/ \"ReportsPlus\")\n        \n        [](https://acculynx.com/smarter-docs/ \"Smart(er) Docs\")\n        \n        [###### Smart(er) Docs](https://acculynx.com/smarter-docs/ \"Smart(er) Docs\")\n        \n        [![Image 8](https://acculynx.com/wp-content/uploads/2020/08/Icon_Texts-back-and-forth.svg)](https://acculynx.com/text-messaging/ \"Text Messaging\")\n        \n        [###### Text Messaging](https://acculynx.com/text-messaging/ \"Text Messaging\")\n        \n        ###### [Platform Overview](https://acculynx.com/features/ \"Platform Overview\")\n        \n        ###### [Plan Options](https://acculynx.com/plan-options/ \"Plan Options\")\n        \n        ##### NEW ACCULYNX FEATURES\n        \n        [![Image 9: AccuLynx New Features](https://acculynx.com/wp-content/uploads/2024/10/acculynx-new-features-350x229.png)](https://bit.ly/4bnO44x)\n        \n        See what we\u2019ve just added to AccuLynx, including new integrations, communication features, document design tools, and more!\n        \n        [See Demo](https://bit.ly/4bnO44x)\n        \n*   [Integrations](https://www.acculynx.com/plans#)\n    *   ##### Popular Integrations\n        \n        [![Image 10: Beacon Building Products](https://acculynx.com/wp-content/uploads/2023/02/logo-beacon-icon.jpg)](https://acculynx.com/integrations/beacon/ \"Beacon\")\n        \n        [Beacon Access Beacon materials and send orders from AccuLynx](https://acculynx.com/integrations/beacon/)\n        \n        [](https://acculynx.com/integrations/srs-distribution/ \"SRS Distribution\")\n        \n        [SRS Distribution See SRS\u2019s catalog and place your order from AccuLynx](https://acculynx.com/integrations/srs-distribution/)\n        \n        [](https://acculynx.com/integrations/abc-supply/ \"ABC Supply\")\n        \n        [ABC Supply Get pricing and submit orders to ABC from AccuLynx](https://acculynx.com/integrations/abc-supply/)\n        \n        [![Image 11](https://acculynx.com/wp-content/uploads/2018/12/Logo-Quickbooks-Mark.png)](https://acculynx.com/integrations/quickbooks/ \"QuickBooks\")\n        \n        [QuickBooks Sync accounting data with this two-way integration](https://acculynx.com/integrations/quickbooks/)\n        \n        [](https://acculynx.com/integrations/gaf-quickmeasure/ \"GAF\")\n        \n        [QuickMeasure Get QuickMeasure reports straight to your job file](https://acculynx.com/integrations/gaf-quickmeasure/)\n        \n        [![Image 12: EagleView Aerial Measurement Logo](https://acculynx.com/wp-content/uploads/2019/06/EagleView-Aerial-Measurement-Logo.png)](https://acculynx.com/integrations/eagleview/ \"EagleView\")\n        \n        [EagleView Order EagleView measurements directly from AccuLynx](https://acculynx.com/integrations/eagleview/)\n        \n        ###### [All Integrations](https://acculynx.com/integrations/ \"All Integrations\")\n        \n        ![Image 13: Spring Into Rewards - Sponsored by: ABC Supply Co. inc.](https://acculynx.com/wp-content/uploads/2025/04/Spring-Into-Rewards_Integrations-Dropdown-Graphic-274x300.png)\n        \n        Earn up to $2,000 when you place orders to ABC Supply through AccuLynx!\n        \n        April 14\u2013May 30, 2025\n        \n        [START EARNING](https://hubs.la/Q03gP7n50 \"START EARNING\")\n        \n*   [Resources](https://www.acculynx.com/plans#)\n    *   ##### Resources\n        \n        [![Image 14](https://acculynx.com/wp-content/uploads/2020/07/icon-star-check-dark.svg)](https://acculynx.com/blog/ \"Blog\")\n        \n        [Blog Access industry tips, best practices, news and more](https://acculynx.com/blog/)\n        \n        [](https://acculynx.com/faq/ \"FAQ\")\n        \n        [FAQ Get answers to our most frequently asked questions](https://acculynx.com/faq/)\n        \n        [](https://acculynx.com/resources/#webinars \"Webinars\")\n        \n        [Webinars Level up your skills with our educational webinars](https://acculynx.com/resources/#webinars)\n        \n        [](https://acculynx.com/compare-acculynx-roofing-software/ \"Compare AccuLynx\")\n        \n        [Compare AccuLynx Find out how AccuLynx stacks up against competition](https://acculynx.com/compare-acculynx-roofing-software/)\n        \n        [![Image 15](https://acculynx.com/wp-content/uploads/2021/02/icon-dollar-sign.svg)](https://acculynx.com/roi-calculator/ \"ROI Calculator\")\n        \n        [ROI Calculator Calculate the ROI you could realize using AccuLynx](https://acculynx.com/roi-calculator/)\n        \n        [](https://acculynx.com/podcast/ \"Webinars\")\n        \n        [Podcast Hear roofing industry experts share tips and stories](https://acculynx.com/podcast/)\n        \n        ###### [All Resources](https://acculynx.com/resources/ \"All Resources\")\n        \n        ###### [Demo Video](https://www.acculynx.com/plans#)\n        \n        ##### LIVE ACCULYNX INTERVIEW\n        \n        ![Image 16: AccuLynx + Ridgeline Roofing & Restoration](https://acculynx.com/wp-content/uploads/2025/04/Resources-Dropdown-Menu-Graphic_Ridgeline-Roofing-and-Restoration_Graphic_Dark-600x238.png)\n        \n        How one PE-backed roofing company scaled 3X with the right tech.\n        \n        April 15 at 12 PM CST\n        \n        [REGISTER NOW](https://hubs.la/Q03dBbyw0 \"REGISTER NOW\")\n        \n*   [Company](https://www.acculynx.com/plans#)\n    *   [About Us](https://acculynx.com/about-acculynx/)\n    *   [Company News](https://acculynx.com/blog/#news)\n    *   [Customers](https://acculynx.com/customers/)\n    *   [Careers](https://acculynx.com/careers/)\n    *   [Contact Us](https://acculynx.com/contact-us/)\n*   [Support](https://www.acculynx.com/plans#)\n    *   [Customer Support](https://acculynx.com/support/)\n    *   [Knowledge Base](https://support.acculynx.com/hc/en-us)\n    *   [Product Updates](https://acculynx.com/blog/#product-updates)\n\n[See Demo](https://www.acculynx.com/demonstration-request/)[Get Pricing](https://www.acculynx.com/pricing-request/)\n\n[![Image 17: AccuLynx](https://acculynx.com/wp-content/uploads/2021/05/acculynx-logo.svg)](https://www.acculynx.com/)\n\n[See Demo](https://acculynx.com/demonstration-request/ \"Demonstration Request\")\n\n[Get Pricing](https://acculynx.com/pricing-request/ \"Pricing Request\")\n\nProduct\n-------\n\n*   [Sales/CRM](https://acculynx.com/features/roofing-crm/)\n*   [Finance](https://acculynx.com/features/roofing-finance/)\n*   [Production](https://acculynx.com/features/roofing-production-management/)\n*   [Business Management](https://acculynx.com/features/roofing-business-management/)\n*   [Field App](https://acculynx.com/roofing-app/)\n*   [AccuPay](https://acculynx.com/accupay-payment-processing/)\n*   [AppConnections](https://acculynx.com/appconnections/)\n*   [Mobile Crew App](https://acculynx.com/mobile-crew-app/)\n*   [Customer Portal](https://acculynx.com/features/customer-portal-software/)\n*   [ReportsPlus](https://acculynx.com/reportsplus/)\n*   [Smart(er) Docs](https://acculynx.com/smarter-docs/)\n*   [Texting](https://acculynx.com/text-messaging/)\n*   [Platform Overview](https://acculynx.com/features/)\n*   [Plan Options](https://acculynx.com/plan-options/)\n\nIntegrations\n------------\n\n*   [Beacon Building Products](https://acculynx.com/integrations/beacon/)\n*   [SRS Distribution](https://acculynx.com/integrations/srs-distribution/)\n*   [ABC Supply](https://acculynx.com/integrations/abc-supply/)\n*   [QuickBooks](https://acculynx.com/integrations/quickbooks/)\n*   [EagleView](https://acculynx.com/integrations/eagleview/)\n*   [GAF QuickMeasure](https://acculynx.com/integrations/gaf-quickmeasure/)\n*   [All Integrations](https://acculynx.com/integrations/)\n\nResources\n---------\n\n*   [Blog](https://acculynx.com/blog/)\n*   [FAQ](https://acculynx.com/faq/)\n*   [Webinars](https://acculynx.com/resources/#webinars)\n*   [Podcast](https://acculynx.com/podcast/)\n*   [Compare AccuLynx](https://acculynx.com/compare-acculynx-roofing-software/)\n*   [ROI Calculator](https://acculynx.com/roi-calculator/)\n*   [All Resources](https://acculynx.com/resources/)\n*   [Demo Video](https://www.acculynx.com/plans#)\n\nCompany\n-------\n\n*   [About AccuLynx](https://acculynx.com/about-acculynx/)\n*   [Company News](https://acculynx.com/blog/#news)\n*   [Customers](https://acculynx.com/customers/)\n*   [Careers](https://acculynx.com/careers/)\n*   [Contact Us](https://acculynx.com/contact-us/)\n\nSupport\n-------\n\n*   [Customer Support](https://acculynx.com/support/)\n*   [Knowledge Base](https://support.acculynx.com/hc/en-us)\n*   [Product Updates](https://acculynx.com/blog/#product-updates)\n*   [Sign In](https://my.acculynx.com/signin/)\n\nPage not found\n==============\n\nThe link you followed may be broken, or the page may have been removed.\n\nProduct\n-------\n\n*   [Sales/CRM](https://acculynx.com/features/roofing-crm/)\n*   [Finance](https://acculynx.com/features/roofing-finance/)\n*   [Production](https://acculynx.com/features/roofing-production-management/)\n*   [Business Management](https://acculynx.com/features/roofing-business-management/)\n*   [Field App](https://acculynx.com/roofing-app/)\n*   [AccuPay](https://acculynx.com/accupay-payment-processing/)\n*   [AppConnections](https://acculynx.com/appconnections/)\n*   [Mobile Crew App](https://acculynx.com/mobile-crew-app/)\n*   [Customer Portal](https://acculynx.com/features/customer-portal-software/)\n*   [ReportsPlus](https://acculynx.com/reportsplus/)\n*   [Smart(er) Docs](https://acculynx.com/smarter-docs/)\n*   [Texting](https://acculynx.com/text-messaging/)\n*   [Platform Overview](https://acculynx.com/features/)\n*   [Plan Options](https://acculynx.com/plan-options/)\n\nIntegrations\n------------\n\n*   [Beacon Building Products](https://acculynx.com/integrations/beacon/)\n*   [SRS Distribution](https://acculynx.com/integrations/srs-distribution/)\n*   [ABC Supply](https://acculynx.com/integrations/abc-supply/)\n*   [QuickBooks](https://acculynx.com/integrations/quickbooks/)\n*   [EagleView](https://acculynx.com/integrations/eagleview/)\n*   [GAF QuickMeasure](https://acculynx.com/integrations/gaf-quickmeasure/)\n*   [All Integrations](https://acculynx.com/integrations/)\n\nCompany\n-------\n\n*   [About AccuLynx](https://acculynx.com/about-acculynx/)\n*   [Company News](https://acculynx.com/blog/#news)\n*   [Customers](https://acculynx.com/customers/)\n*   [Careers](https://acculynx.com/careers/)\n*   [Contact Us](https://acculynx.com/contact-us/)\n\nResources\n---------\n\n*   [Blog](https://acculynx.com/blog/)\n*   [FAQ](https://acculynx.com/faq/)\n*   [Webinars](https://acculynx.com/resources/#webinars)\n*   [Podcast](https://acculynx.com/podcast/)\n*   [Compare AccuLynx](https://acculynx.com/compare-acculynx-roofing-software/)\n*   [ROI Calculator](https://acculynx.com/roi-calculator/)\n*   [All Resources](https://acculynx.com/resources/)\n*   [Demo Video](https://www.acculynx.com/plans#)\n\nSupport\n-------\n\n*   [Customer Support](https://acculynx.com/support/)\n*   [Knowledge Base](https://support.acculynx.com/hc/en-us)\n*   [Product Updates](https://acculynx.com/blog/#product-updates)\n*   [Sign In](https://my.acculynx.com/signin/)\n\nCompany\n-------\n\n*   [About AccuLynx](https://acculynx.com/about-acculynx/)\n*   [Company News](https://acculynx.com/blog/#news)\n*   [Customers](https://acculynx.com/customers/)\n*   [Careers](https://acculynx.com/careers/)\n*   [Contact Us](https://acculynx.com/contact-us/)\n\nSupport\n-------\n\n*   [Customer Support](https://acculynx.com/support/)\n*   [Knowledge Base](https://support.acculynx.com/hc/en-us)\n*   [Product Updates](https://acculynx.com/blog/#product-updates)\n*   [Sign In](https://my.acculynx.com/signin/)\n\n![Image 18: AccuLynx](https://acculynx.com/wp-content/uploads/2021/05/acculynx-logo.svg)\n\nAccuLynx is the leading, all-in-one roofing software designed to streamline every aspect of a roofing business. Since 2008, thousands of roofing companies have turned to our award-winning software to save time, simplify production, and sell more\u00a0profitable\u00a0jobs.\n\n[](https://www.facebook.com/acculynx/)\n\nFacebook\n\n[](https://x.com/acculynx/)\n\nX\n\n[](https://www.linkedin.com/company/acculynx/)\n\nLinkedIn\n\n[](https://www.instagram.com/acculynx/)\n\nInstagram\n\n[](https://www.youtube.com/user/acculynx/)\n\nYouTube\n\n[](https://podcasts.apple.com/us/podcast/acculynx-on-the-roof-a-residential-roofing-podcast/id1690203389)\n\nAccuLynx on the Roof Podcast\n\n\u00a9 2025 ExactLogix, Inc. All Rights Reserved.\n\n*   [Terms of Use](https://my.acculynx.com/signin/TermsView)\n*   [Privacy Policy](https://my.acculynx.com/privacy-policy)\n*   [Copyright Policy](https://acculynx.com/copyright-policy/)\n\nFirst Name\\*\n\nLast Name\\*\n\nEmail\\*\n\nCompany Name\\*\n\nPhone Number\n\nPriority Level\n\n\\*Indicates a required field. We respect your [privacy](https://www.acculynx.com/privacy-policy/).\n\nMenu",
      "error": null,
      "pricing_data": {
        "app_id": "acculynx",
        "app_name": "AccuLynx",
        "app_slug": "acculynx",
        "pricing_url": "https://www.acculynx.com/pricing-request/",
        "source_url": "https://www.acculynx.com/",
        "all_pricing_urls": [
          "https://www.acculynx.com/pricing-request/"
        ],
        "price_model_type": [
          "PriceModelType.QUOTE_BASED"
        ],
        "has_free_tier": false,
        "has_free_trial": false,
        "free_trial_period_days": null,
        "currency": "USD",
        "is_pricing_public": false,
        "pricing_page_accessible": true,
        "pricing_notes": "Pricing information requires a request form submission to access.",
        "pricing_tiers": null,
        "usage_based_pricing": null,
        "ai_specific_pricing": null,
        "promotional_offers": null,
        "additional_fees": null,
        "extraction_timestamp": "2025-04-15T10:14:30.226379",
        "schema_validated": true,
        "confidence_score": 95,
        "extraction_error": false,
        "json_repaired": false
      },
      "pricing_analyzed": true
    }
  ],
  "results_directory": "pricing_results\\acculynx\\20250415_101430"
}