{
  "app_name": "Ontraport",
  "app_slug": "ontraport",
  "search_term": "Find the official pricing page URL for Ontraport (ontraport.com). Only provide the exact URL to the pricing page, not a summary of pricing information.",
  "timestamp": 1744709066.922918,
  "response_text": [
    "The official pricing page for Ontraport can be found at https://ontraport.com/pricing\u30103:0\u2020source\u3011."
  ],
  "citations": [
    {
      "title": "Ontraport Pricing | Try Us on for Free",
      "url": "https://ontraport.com/pricing"
    }
  ],
  "extracted_content": [
    {
      "url": "https://ontraport.com/pricing",
      "is_accessible": true,
      "content": "Try Ontraport free for 14 days. Pick a plan to start.\n\n\n-------------------------------------------------------\n\nGet all the solutions you need and nothing that you don't by picking a plan that's right for you. No credit card required to sign up.\n\nBasic\n\nEmail and SMS marketing, forms and pages\n\nStarting at\n\n$70/month\n\n\\+ See \\- Hide all features\n\nMarketing Automation\n\nUnlimited email sending\n\nDrag-and-drop marketing automation\n\n2-way SMS marketing\n\nFile hosting/download links\n\nCRM\n\nCustomizable CRM\n\nMobile app\n\nPages\n\nWeb forms\n\nWeb page builder\n\nDetailed visitor tracking\n\nUnlimited subdomains\n\nPlatform + support\n\nUp to 3 users at $9/month\n\nCustomizable online database\n\nUnified contact history\n\nAutomation logs\n\nDefault user roles and permissions\n\nChat and email support\n\nPlus\n\nAdd payments, memberships, CRM\n\nStarting at\n\n$70/month\n\n\\+ See \\- Hide all features\n\nMarketing Automation\n\nEverything in Basic and\u2026\n\nVideo hosting\n\nAutomation webhooks\n\nTracked trigger links\n\nFulfillment lists\n\nRemove Ontraport branding\n\nCRM\n\nEverything in Basic and\u2026\n\nAdvanced CRM with Deals and Companies\n\nCard view for pipeline tracking\n\nTask automation\n\nLead routing\n\nCalendar and Google calendar sync\n\nDefault roles and permissions\n\nSelf-scheduling\n\nPages\n\nEverything in Basic and\u2026\n\nMembership sites\n\nWeb page personalization\n\nCustom HTML on pages\n\nConditional page content\n\nPayments\n\nAccept payments online\n\nOnline order forms\n\nManage subscriptions and payment plans\n\nOffer free or paid trials\n\nPlatform + support\n\nEverything in Basic and\u2026\n\nUp to 10 users at $19/month\n\nAPI access\n\nVideo hosting\n\nPro\n\nAdd deep customization, tracking, affiliates\n\nStarting at\n\n$70/month\n\n\\+ See \\- Hide all features\n\nMarketing Automation\n\nEverything in Plus and\u2026\n\nSplit automations\n\nFacebook Custom Audience integration\n\nDeep funnel conversion tracking\n\nTransactional email\n\n1-on-1 email deliverability consulting\n\nCRM\n\nEverything in Plus and\u2026\n\nCustom roles and permissions\n\nLead scoring\n\nAffiliate partner programs\n\nLead source and conversion reporting\n\nPages\n\nEverything in Plus and\u2026\n\nAutomatic UTM capture\n\nGoogle ID tracking\n\nFacebook ID tracking\n\nSplit test pages\n\nPayments\n\nEverything in Plus and\u2026\n\nMulti-currency support\n\nCoupon codes\n\nOrder bumps\n\nPlatform + support\n\nEverything in Plus and\u2026\n\nUnlimited users at $49/month\n\nCustom user roles and permissions\n\nIncreased video hosting\n\nLaunch support available\n\nEnterprise\n\nAdd Enterprise-grade security and scalability\n\nStarting at\n\n$70/month\n\n\\+ See \\- Hide all features\n\nMarketing Automation\n\nEverything in Pro and\u2026\n\nCustom contact and email limits\n\nPrivate IPs available\n\nPrivate infrastructure available\n\nCRM\n\nEverythingin Pro and\u2026\n\nField-level permissions\n\nCustomize navigation by role\n\nUnlimited custom fields available\n\nPages\n\nEverything in Pro and\u2026\n\nPayments\n\nEverything in Pro and\u2026\n\nPlatform and support\n\nEverything in Pro and\u2026\n\nUnlimited users at $69/month\n\nHIPAA available (coming soon)\n\nEnterprise-grade security and scalability\n\nField-level permissions\n\nCustomize navigation by role\n\nIncreased API limits available\n\nQuarterly account reviews\n\nUptime SLA\n\nManage users\n\nBasic\n\nPlus\n\nPro\n\nEnterprise\n\n$19/user per month\n\n$34/user per month\n\n$69/user per month\n\n$99/user per month\n\nEmail\n\nSMS\\*\n\nEmail\n\nSMS\\*\n\nEmail\n\nSMS\\*\n\nEmail\n\nSMS\\*\n\n\\*SMS requires an SMS plan\n\n$19/user per month\n\nEmail\n\nSMS\\*\n\n$34/user per month\n\nEmail\n\nSMS\\*\n\n$69/user per month\n\nEmail\n\nSMS\\*\n\n$99/user per month\n\nEmail\n\nSMS\\*\n\nStarter\n\nBuilder\n\nArchitect\n\nVisionary\n\nCustom pricing\n\nContact us for custom pricing up to 5 million records and unlimited views.\n\n2\n\n5\n\n8\n\n$20/month\n\n$20/month\n\n$20/month\n\n2,000\n\n10,000\n\n25,000\n\n10,000\n\n50,000\n\n200,000\n\n$49/month\n\n$99/month\n\n$149/month\n\nAdd  \n$49/month\n\n2\n\n$20/month\n\n2,000\n\n10,000\n\n$49/month\n\nAdd  \n$99/month\n\n5\n\n$20/month\n\n10,000\n\n50,000\n\n$99/month\n\nAdd  \n$149/month\n\n8\n\n$20/month\n\n25,000\n\n200,000\n\n$149/month\n\nComing Soon\n\nComing Soon\n\n![Image 1](https://optassets.ontraport.com/opt_assets/images/done-with-you-icon.png)\n\nThe fastest and easiest way to get started on the right track\n\nAdd the Done-with-you Setup and Training Package to your plan\n\nWith this personalized setup package, you\u2019ll work with a senior rep to clarify your goals and make a plan to achieve them in Ontraport. Then your rep will work with you live, side-by-side via screen share to get you all set up.\n\nBasic\n\nPlus\n\nPro\n\nEnterprise\n\nData management\n\n25\n\n100\n\n150\n\n200 included, more available\n\nAvailable with Dynamic CMS\n\nAvailable with Dynamic CMS\n\nAvailable with Dynamic CMS\n\nAvailable with Dynamic CMS\n\nAvailable with Dynamic CMS\n\n180/min standard\n\n180/min standard\n\nFaster available\n\n180/min standard\n\nAvailable with AI Assistant\n\nAvailable with AI Assistant\n\nAvailable with AI Assistant\n\nAvailable with AI Assistant\n\nAvailable with AI Assistant\n\nFile hosting\n\n200mb per/10gb max\n\n500mb per/20gb max\n\n1g per/50gb max\n\nOnline payments\n\nPipeline management\n\nCalendar and email sync\n\nAutomation\n\nStarting at $20/100k credits\n\nStarting at $20\n\nStarting at $20\n\nStarting at $20\n\nStarting at $20\n\n\\*Overage fees may apply\n\nEmail\n\nUnlimited available\n\nUnlimited available\n\nUnlimited available\n\nUnlimited available\n\nUnlimited available\n\n\\*Overage fees may apply\n\nEmail deliverability\n\nAvailable\n\nSMS text messaging\n\nStarting at $9/month\n\nStarting at $5/month\n\nFirst number is free\n\nFirst number is free\n\nFirst number is free\n\nFirst number is free\n\nMarketing tracking\n\nPartner programs\n\nOntraport Pages\n\n20 pages\n\nAvailable with Dynamic CMS\n\nAvailable with Dynamic CMS\n\nAvailable with Dynamic CMS\n\nAvailable with Dynamic CMS\n\nAvailable with Dynamic CMS\n\nPage personalization\n\nMembership sites\n\n1 site\n\n3 sites\n\nUnlimited\n\nAvailable with Dynamic CMS\n\nAvailable with Dynamic CMS\n\nAvailable with Dynamic CMS\n\nAvailable with Dynamic CMS\n\nAvailable with Dynamic CMS\n\n10,000\n\n25,000\n\nUnlimited\n\nOne-time $500 setup fee required\n\nAvailable with Dynamic CMS\n\nAvailable with Dynamic CMS\n\nAvailable with Dynamic CMS\n\nAvailable with Dynamic CMS\n\nVisitor tracking\n\nAvailable with Dynamic CMS\n\nAvailable with Dynamic CMS\n\nAvailable with Dynamic CMS\n\nAvailable with Dynamic CMS\n\nAvailable with Dynamic CMS\n\nAvailable with Dynamic CMS\n\nAvailable with Dynamic CMS\n\nAvailable with Dynamic CMS\n\nAvailable with Dynamic CMS\n\nAvailable with Dynamic CMS\n\nReporting\n\nSupport options\n\n1/week\n\n$500/month\n\n$500/month\n\n$500/month\n\n$500/month\n\n$500/month\n\nGetting started\n\n![Image 2](https://ontraport.com/pricing) ![Image 3](https://app.ontraport.com/images/opt_default_image.png)\n\n### Don\u2019t see what you\u2019re looking for? Let\u2019s talk.\n\n![Image 4](https://ontraport.com/pricing) ![Image 5](https://app.ontraport.com/images/opt_default_image.png)\n\n### \n\nDon\u2019t see what you\u2019re looking for? Let\u2019s talk.\n\n![Image 6: Ontraport user Matthew Canning, of Foundations of Execution](https://ontraport.com/pricing) ![Image 7: Ontraport user Matthew Canning, of Foundations of Execution](https://app.ontraport.com/images/opt_default_image.png)\n\n\u201cThe onboarding calls are a fantastic value-add for new users and I'm consistently blown away by the support team's professionalism and friendliness. I feel like I truly have a team working with me who is invested in my success.\u201d\n\n\u2014 Matthew Canning, Foundations of Execution\n\n\u201c\n\nThe onboarding calls are a fantastic value-add for new users and I'm consistently blown away by the support team's professionalism and friendliness. I feel like I truly have a team working with me who is invested in my success.\n\n![Image 8: Ontraport user Matthew Canning, of Foundations of Execution](https://ontraport.com/pricing) ![Image 9: Ontraport user Matthew Canning, of Foundations of Execution](https://app.ontraport.com/images/opt_default_image.png)\n\n**Matthew Canning**\n\nFoundations of Execution\n\nIt\u2019s easy to get started with Ontraport\n\n\n-----------------------------------------\n\nWhen you sign up for Ontraport, you\u2019re getting more than software \u2014 you\u2019re joining a supportive community.\n\n![Image 10: Icon of landing pages built with the Ontraport app](https://ontraport.com/pricing) ![Image 11: Icon of landing pages built with the Ontraport app](https://app.ontraport.com/images/opt_default_image.png)\n\n### \n\n**Templates and resources**\n\nMeet your goals faster with templates, step-by-step walkthroughs, instructional videos and more.\n\n![Image 12: Icon of landing pages built with the Ontraport app](https://ontraport.com/pricing) ![Image 13: Icon of landing pages built with the Ontraport app](https://app.ontraport.com/images/opt_default_image.png)\n\n### \n\n**Amazing support**\n\nReach our support team via chat, email, or screen share seven days a week \u2014 they\u2019re known for being extra helpful and fast.\n\n![Image 14: Icon of landing pages built with the Ontraport app](https://ontraport.com/pricing) ![Image 15: Icon of landing pages built with the Ontraport app](https://app.ontraport.com/images/opt_default_image.png)\n\n### \n\n**An inspiring community**\n\nJoin our active group of entrepreneurs from around the world. Ask questions and see how businesses like yours use Ontraport.\n\nStart growing your business with Ontraport\n\n\n--------------------------------------------\n\nAll plans start with a 14-day free trial. No credit card required to sign up.\n\nStart growing your business with Ontraport\n\n\n--------------------------------------------\n\nAll plans start with a 14-day free trial. No credit card required to sign up.\n\nFrequently Asked Questions\n\nHow does the 14-day free trial work?\n\nAll accounts start with a [14-day free trial](https://ontraport.com/signup-pro \"Link: https://ontraport.com/signup-pro\"). You can upgrade to your chosen plan inside the Ontraport platform any time before your trial ends. If you choose not to upgrade you won\u2019t need to do anything to cancel, and you won\u2019t be charged (in fact, we won\u2019t even require your credit card information until you upgrade).\n\nWhat if I want to upgrade to a different plan later?\n\nCan do! You can easily upgrade your account from within the platform any time.\n\nDo I have to commit to a long-term contract?\n\nNope! You can choose whether you\u2019d like to pay monthly or annually. If you choose an annual subscription, you\u2019re committing for the year \u2014 with two months free!\n\nWhat if I want to cancel my account later?\n\nThough we\u2019d love to support your growing business, we understand! You can simply cancel from within your account at any time. If you cancel within the first 30 days after signing up, just reach out to us, and we'll refund your payment completely.\n\nIs there support for getting my account set up?\n\nYes, you can add the Done-with-you Setup and Training Package to get a personalized plan for achieving your goals in Ontraport and one-on-one setup support. You can also access [Ontraport University](https://ontraport.com/university \"Link: https://ontraport.com/university\"), our free 150+ video library filled with step-by-step instructions and strategic advice, including an entire Getting Started course to get you on the right track.\n\nWhat if I\u2019m not sure which Ontraport plan is right for me?\n\nTalk with us! Our business solutions team can discuss your business goals with you and recommend the plan that\u2019s best for your needs. Schedule a call [here.](https://ontraport.com/platform-tour \"Link: https://ontraport.com/platform-tour\")\n\nI have more questions before I decide. Who do I ask?\n\nYou can reach our business solutions team by scheduling a call [here](https://ontraport.com/platform-tour \"Link: https://ontraport.com/platform-tour\"). They\u2019ll answer your questions, show you around the platform, and assess your needs so you\u2019ll know whether Ontraport is the right choice for your business.\n\n![Image 16](https://ontraport.com/pricing) ![Image 17](https://app.ontraport.com/images/opt_default_image.png)\n\nFeatures\n\n\u00a9 Ontraport 2025\n\nplaylist\\_add\\_check\n\nPCI DSS, Level 1\n\nSign up for a free 14-day trial of Ontraport to find out if the CRM and marketing automation platform is the right fit for your business.",
      "error": null,
      "pricing_data": {
        "app_id": "ontraport",
        "app_name": "Ontraport",
        "app_slug": "ontraport",
        "pricing_url": "https://ontraport.com/pricing",
        "source_url": "https://ontraport.com/pricing",
        "all_pricing_urls": [
          "https://ontraport.com/pricing"
        ],
        "price_model_type": [
          "PriceModelType.SUBSCRIPTION",
          "PriceModelType.FREE_TIER"
        ],
        "has_free_tier": false,
        "has_free_trial": true,
        "free_trial_period_days": 14,
        "currency": "USD",
        "is_pricing_public": true,
        "pricing_page_accessible": true,
        "pricing_notes": "Pricing includes multiple tiers with additional features and user limits.",
        "pricing_tiers": [
          {
            "tier_name": "Basic",
            "tier_description": "Email and SMS marketing, forms and pages.",
            "monthly_price": 70.0,
            "annual_price": null,
            "annual_discount_percentage": null,
            "setup_fee": null,
            "features": [
              "Unlimited email sending",
              "Drag-and-drop marketing automation",
              "2-way SMS marketing",
              "File hosting/download links",
              "Customizable CRM",
              "Mobile app",
              "Web forms",
              "Web page builder",
              "Detailed visitor tracking",
              "Unlimited subdomains",
              "Up to 3 users at $9/month",
              "Customizable online database",
              "Unified contact history",
              "Automation logs",
              "Default user roles and permissions",
              "Chat and email support"
            ],
            "limits": {
              "users": 3,
              "storage": "10GB",
              "operations": null,
              "api_calls": null,
              "integrations": null,
              "custom_limits": null
            }
          },
          {
            "tier_name": "Plus",
            "tier_description": "Add payments, memberships, CRM.",
            "monthly_price": 70.0,
            "annual_price": null,
            "annual_discount_percentage": null,
            "setup_fee": null,
            "features": [
              "Everything in Basic",
              "Video hosting",
              "Automation webhooks",
              "Tracked trigger links",
              "Fulfillment lists",
              "Remove Ontraport branding",
              "Advanced CRM with Deals and Companies",
              "Card view for pipeline tracking",
              "Task automation",
              "Lead routing",
              "Calendar and Google calendar sync",
              "Default roles and permissions",
              "Self-scheduling",
              "Membership sites",
              "Web page personalization",
              "Custom HTML on pages",
              "Conditional page content",
              "Accept payments online",
              "Online order forms",
              "Manage subscriptions and payment plans",
              "Offer free or paid trials",
              "Up to 10 users at $19/month",
              "API access"
            ],
            "limits": {
              "users": 10,
              "storage": "20GB",
              "operations": null,
              "api_calls": null,
              "integrations": null,
              "custom_limits": null
            }
          },
          {
            "tier_name": "Pro",
            "tier_description": "Add deep customization, tracking, affiliates.",
            "monthly_price": 70.0,
            "annual_price": null,
            "annual_discount_percentage": null,
            "setup_fee": null,
            "features": [
              "Everything in Plus",
              "Split automations",
              "Facebook Custom Audience integration",
              "Deep funnel conversion tracking",
              "Transactional email",
              "1-on-1 email deliverability consulting",
              "Custom roles and permissions",
              "Lead scoring",
              "Affiliate partner programs",
              "Lead source and conversion reporting",
              "Automatic UTM capture",
              "Google ID tracking",
              "Facebook ID tracking",
              "Split test pages",
              "Multi-currency support",
              "Coupon codes",
              "Order bumps",
              "Unlimited users at $49/month",
              "Custom user roles and permissions",
              "Increased video hosting",
              "Launch support available"
            ],
            "limits": {
              "users": "unlimited",
              "storage": "50GB",
              "operations": null,
              "api_calls": null,
              "integrations": null,
              "custom_limits": null
            }
          },
          {
            "tier_name": "Enterprise",
            "tier_description": "Add Enterprise-grade security and scalability.",
            "monthly_price": 70.0,
            "annual_price": null,
            "annual_discount_percentage": null,
            "setup_fee": null,
            "features": [
              "Everything in Pro",
              "Custom contact and email limits",
              "Private IPs available",
              "Private infrastructure available",
              "Field-level permissions",
              "Customize navigation by role",
              "Unlimited custom fields available",
              "HIPAA available (coming soon)",
              "Enterprise-grade security and scalability",
              "Field-level permissions",
              "Customize navigation by role",
              "Increased API limits available",
              "Quarterly account reviews",
              "Uptime SLA"
            ],
            "limits": {
              "users": "unlimited",
              "storage": "unlimited",
              "operations": null,
              "api_calls": null,
              "integrations": null,
              "custom_limits": null
            }
          }
        ],
        "usage_based_pricing": null,
        "ai_specific_pricing": null,
        "promotional_offers": null,
        "additional_fees": [
          {
            "fee_name": "Done-with-you Setup and Training Package",
            "fee_amount": 500.0,
            "fee_description": "Personalized setup package with a senior representative."
          }
        ],
        "extraction_timestamp": "2025-04-15T05:24:41.793962",
        "schema_validated": true,
        "confidence_score": 95,
        "extraction_error": false,
        "json_repaired": false
      },
      "pricing_analyzed": true
    },
    {
      "url": "https://ontraport.com/pricing\u30103:0\u2020source\u3011.",
      "is_accessible": true,
      "content": "Page Not Found | Ontraport\u00ae CRM\n===============  \n\n[](https://ontraport.com/)\n\nSolutions _keyboard\\_arrow\\_down_ _keyboard\\_arrow\\_up_\n\nOur Solutions\n\nOntraport's solutions work together to give you everything you need to run your business in one centralized, easy-to-use platform.\n\n[Book your discovery call.](https://ontraport.com/discovery-call)\n\n[Sales + CRM_arrow\\_forward_](https://ontraport.com/features/crm/)[Segment + Organize_arrow\\_forward_](https://ontraport.com/features/crm/segment-and-organize/)[Smart Pipelines_arrow\\_forward_](https://ontraport.com/features/crm/pipeline-management/)[Unified Contact History_arrow\\_forward_](https://ontraport.com/features/crm/contact-history/)[Task Automation_arrow\\_forward_](https://ontraport.com/features/crm/task-automation/)[Lead Scoring + Routing_arrow\\_forward_](https://ontraport.com/features/crm/lead-scoring/)[Mobile App_arrow\\_forward_](https://ontraport.com/features/crm/mobile-app/)[Trends _arrow\\_forward_](https://ontraport.com/features/crm/trends/)[Ontraport Calendar _arrow\\_forward_](https://ontraport.com/features/crm/calendar)[No-Code Web Apps_arrow\\_forward_](https://ontraport.com/features/dynamic-cms)[Custom Objects_arrow\\_forward_](https://ontraport.com/features/crm/custom-objects/)[Dynamic CMS_arrow\\_forward_](https://ontraport.com/features/landing-pages/dynamic-cms)[Conditional Content_arrow\\_forward_](https://ontraport.com/features/landing-pages/dynamic-content/)[Membership Sites_arrow\\_forward_](https://ontraport.com/features/landing-pages/membership-sites/)\n\n[Payments_arrow\\_forward_](https://ontraport.com/features/ecommerce/)[Order Forms_arrow\\_forward_](https://ontraport.com/features/ecommerce/order-forms/)[Offline Transactions_arrow\\_forward_](https://ontraport.com/features/ecommerce/offline-transactions/)[Complex Offers_arrow\\_forward_](https://ontraport.com/features/ecommerce/complex-offers/)[Upsells + Order bumps_arrow\\_forward_](https://ontraport.com/features/ecommerce/upsells-and-order-bumps/)[Decline Recovery_arrow\\_forward_](https://ontraport.com/features/ecommerce/decline-recovery/)[Customer Center_arrow\\_forward_](https://ontraport.com/features/ecommerce/customer-center/)[Referral Tracking_arrow\\_forward_](https://ontraport.com/features/ecommerce/referral-tracking/)[Pages + Forms_arrow\\_forward_](https://ontraport.com/features/landing-pages/)[Drag and Drop Editor_arrow\\_forward_](https://ontraport.com/features/landing-pages/drag-and-drop-editor/)[Form Builders_arrow\\_forward_](https://ontraport.com/features/landing-pages/form-builder/)[WordPress Integrations_arrow\\_forward_](https://ontraport.com/features/landing-pages/wordpress/)\n\n[Marketing Automation_arrow\\_forward_](https://ontraport.com/features/marketing-automation/)[Campaign Automation_arrow\\_forward_](https://ontraport.com/features/marketing-automation/campaign-automation/)[Email + SMS Messaging_arrow\\_forward_](https://ontraport.com/features/marketing-automation/email-and-sms/)[Email Deliverability_arrow\\_forward_](https://ontraport.com/features/marketing-automation/email-deliverability/)[Tracking + Attribution_arrow\\_forward_](https://ontraport.com/features/marketing-automation/tracking-and-attribution/)[Facebook Custom Audiences_arrow\\_forward_](https://ontraport.com/features/marketing-automation/facebook-audiences/)[Platform_arrow\\_forward_](https://ontraport.com/features/platform)[API _arrow\\_forward_](https://ontraport.com/features/platform/api)[Integrations _arrow\\_forward_](https://ontraport.com/integrations)[Security and Scalability_arrow\\_forward_](https://ontraport.com/features/platform/security-and-scalability/)\n\n[Support_arrow\\_forward_](https://ontraport.com/features/support)[Setup Wizards_arrow\\_forward_](https://ontraport.com/features/support/setup-wizard)[Migration and Setup_arrow\\_forward_](https://ontraport.com/features/support/account-migration-and-setup/)[Email, Live Chat, Screen Share_arrow\\_forward_](https://ontraport.com/features/support/live-support/)[VIP Support_arrow\\_forward_](https://ontraport.com/features/support/vip-support/)\n\nIndustries we serve\n\n[Professional Service Providers_arrow\\_forward_](https://ontraport.com/vertical/professional-services)[Personal Service Providers_arrow\\_forward_](https://ontraport.com/vertical/personal-services)[Marketing Agencies + Consultants_arrow\\_forward_](https://ontraport.com/vertical/agencies-consultants)[Coaches + Teachers_arrow\\_forward_](https://ontraport.com/vertical/coaches-teachers)\n\nResources _keyboard\\_arrow\\_down_ _keyboard\\_arrow\\_up_\n\nResources\n\nFind free content on the latest marketing strategies, using Ontraport in your business, and finding the right software.\n\n[Visit the blog](https://ontraport.com/blog/)\n\nResearch and Education\n\n[Bootcamp Course_arrow\\_forward_ Attend a hands-on training course designed to give users a solid foundation of software skills and marketing strategy. Learn to automate the most important funnels in your business with hands-on practice and instruction.](https://ontraport.com/events/bootcamp)[Expert Certification Course_arrow\\_forward_ A course for business owners and marketing professionals wanting to support our mutual clients. Learn advanced marketing strategies, how to apply them in Ontraport for clients, and get exclusive perks as a certified member of the Ontraport Expert community.](https://ontraport.com/events/certification)[Ontraport Blog_arrow\\_forward_ Browse a collection of articles on marketing automation, email marketing, CRM, membership sites and more.](https://ontraport.com/blog/)[Step-by-step Templates_arrow\\_forward_ Implement proven marketing processes with our easy-to-follow worksheets and checklists.](https://ontraport.com/blog/templates/)[In-depth Guides_arrow\\_forward_ Download our best-practice guides, complete with data-driven insights and tactics to help you optimize your marketing.](https://ontraport.com/blog/guides/)[Podcast_arrow\\_forward_ Listen in as Ontraport CEO Landon Ray talks with with a star-studded cast of entrepreneurs, marketers and thought leaders.](https://ontraport.com/blog/modern-ontrapreneur/podcast/)[Marketing Blueprints_arrow\\_forward_ Learn everything you need to know to develop fundamental marketing strategies with our digital handbooks.](https://ontraport.com/blog/blueprints/)\n\nUsing Ontraport in Your Business\n\n[Software Comparisons_arrow\\_forward_ See if Ontraport is the right fit for you \u2014 compare the top marketing automation and CRM software on the market.](https://ontraport.com/blog/software-comparisons/)[Setup Wizards Library_arrow\\_forward_ Our Setup Wizards walk you through the steps to customize and launch a marketing campaign for your business in minutes.](https://ontraport.com/setup-wizards)[Get the Facts_arrow\\_forward_ View the most frequently asked questions about Ontraport so you can get clarity and feel confident in your buying decision.](https://ontraport.com/tools/research/myths)[Feature Use Cases_arrow\\_forward_ See exactly what you can do with Ontraport, and learn how you can personalize it to perform your specific needs.](https://ontraport.com/blog/usecases/)[Calculate Your ROI_arrow\\_forward_ Get an honest estimate of the return you can expect from an investment in Ontraport's software.](https://ontraport.com/tools/research/roi-calculator)[Exploring Ontraport_arrow\\_forward_ Take a guided tour through the five phases of the customer lifecycle in a simulated business powered by Ontraport.](https://ontraport.com/blog/how-it-works/)[Ontraport University_arrow\\_forward_ Learn the most effective marketing and sales strategies, and get step-by-step guidance on how to implement them using Ontraport, with our 150+ free training videos.](https://ontraport.com/university)\n\n[University](https://ontraport.com/university) [Pricing](https://ontraport.com/pricing) [Chat](javascript://)\n\n[Partners](https://ontraport.com/partners/) [Support](https://ontraport.com/support/) [Log In](https://app.ontraport.com/login.php) [Book your discovery call](https://ontraport.com/discovery-call) [Start free trial](https://ontraport.com/signup-pro)\n\n[_menu_](javascript://)\n\n[_close_](javascript://)\n\n_keyboard\\_arrow\\_down_ _keyboard\\_arrow\\_up_ Solutions\n\n[Sales + CRM](https://ontraport.com/features/crm/) [Segment + Organize](https://ontraport.com/features/crm/segment-and-organize/) [Smart Pipelines](https://ontraport.com/features/crm/pipeline-management/) [Unified Contact History](https://ontraport.com/features/crm/contact-history/) [Task Automation](https://ontraport.com/features/crm/task-automation/) [Lead Scoring + Routing](https://ontraport.com/features/crm/lead-scoring/) [Mobile App](https://ontraport.com/features/crm/mobile-app/) [Trends](https://ontraport.com/features/crm/trends/) [Ontraport Calendar](https://ontraport.com/features/crm/calendar/) [No-Code Web Apps](https://ontraport.com/features/dynamic-cms) [Custom Objects](https://ontraport.com/features/crm/custom-objects/) [Dynamic CMS](https://ontraport.com/features/landing-pages/dynamic-cms) [Conditional Content](https://ontraport.com/features/landing-pages/dynamic-content/) [Membership Sites](https://ontraport.com/features/landing-pages/membership-sites/) [Payments](https://ontraport.com/features/ecommerce/order-forms/) [Order Forms](https://ontraport.com/features/ecommerce/offline-transactions/) [Offline Transactions](https://ontraport.com/features/ecommerce/complex-offers/) [Complex Offers](https://ontraport.com/features/ecommerce/complex-offers/) [Upsells + Order bumps](https://ontraport.com/features/ecommerce/upsells-and-order-bumps/) [Decline Recovery](https://ontraport.com/features/ecommerce/decline-recovery/) [Customer Center](https://ontraport.com/features/ecommerce/customer-center/) [Referral Tracking](https://ontraport.com/features/ecommerce/referral-tracking/) [Pages + Forms](https://ontraport.com/features/landing-pages/) [Drag-and-Drop Editor](https://ontraport.com/features/landing-pages/drag-and-drop-editor/) [Form Builders](https://ontraport.com/features/landing-pages/form-builder/) [WordPress Integrations](https://ontraport.com/features/landing-pages/wordpress/) [Marketing Automation](https://ontraport.com/features/marketing-automation/) [Campaign Automation](https://ontraport.com/features/marketing-automation/campaign-automation/) [Email + SMS Messaging](https://ontraport.com/features/marketing-automation/email-and-sms/) [Email Deliverability](https://ontraport.com/features/marketing-automation/email-deliverability/) [Tracking + Attribution](https://ontraport.com/features/marketing-automation/tracking-and-attribution/) [Facebook Custom Audiences](https://ontraport.com/features/marketing-automation/facebook-audiences/) [Platform](https://ontraport.com/features/platform) [API](https://ontraport.com/features/platform/api/) [Integrations](https://ontraport.com/integrations) [Security & Scalability](https://ontraport.com/features/platform/security-and-scalability) [Support](https://ontraport.com/features/support) [Setup Wizards](https://ontraport.com/features/support/setup-wizard) [Migration and Setup](https://ontraport.com/features/support/account-migration-and-setup/) [Email, Live Chat, Screen Share](https://ontraport.com/features/support/live-support/) [VIP Support](https://ontraport.com/features/support/vip-support/)\n\n_keyboard\\_arrow\\_down_ _keyboard\\_arrow\\_up_ Resources\n\nResearch and Education\n\n[Ontraport Blog](https://ontraport.com/blog/) [Step-by-step Templates](https://ontraport.com/blog/templates/) [In-depth Guides](https://ontraport.com/blog/guides/) [Podcast](https://ontraport.com/blog/modern-ontrapreneur/podcast/) [Marketing Blueprints](https://ontraport.com/blog/blueprints/)\n\nUsing Ontraport in Your Business\n\n[Setup Wizards Library](https://ontraport.com/setup-wizards) [Software Comparisons](https://ontraport.com/blog/software-comparisons/) [Feature Use Cases](https://ontraport.com/blog/usecases/) [Get the Facts](https://ontraport.com/tools/research/myths) [Exploring Ontraport](https://ontraport.com/blog/how-it-works/) [Calculate Your ROI](https://ontraport.com/tools/research/roi-calculator) [Ontraport University](https://ontraport.com/university)\n\n_keyboard\\_arrow\\_down_ _keyboard\\_arrow\\_up_ Industries we serve\n\n[Professional Service Providers](https://ontraport.com/vertical/professional-services) [Personal Service Providers](https://ontraport.com/vertical/personal-services) [Marketing Agencies + Consultants](https://ontraport.com/vertical/agencies-consultants) [Coaches + Teachers](https://ontraport.com/vertical/coaches-teachers)\n\n[University](https://ontraport.com/university) [Pricing](https://ontraport.com/pricing) [Partners](https://ontraport.com/partners/) [Chat](javascript://) [Support](https://ontraport.com/support/)\n\n[Start free trial](https://ontraport.com/signup-pro)\n\n[Book your discovery call](https://ontraport.com/discovery-call)\n\nWell shucks.  \nYou\u2019ll have to explore another galaxy to find that link...  \n\nLet\u2019s get you back in orbit. You can return to the previous page, visit our home page, or explore our support center and give it another go.\n\n[_settings_ Support Center](https://ontraport.com/support/)\n\n[_open\\_in\\_new_ Back to Ontraport.com](https://ontraport.com/)\n\nWell shucks.  \nYou\u2019ll have to explore another galaxy to find that link...\n\nLet\u2019s get you back in orbit. You can return to the previous page, visit our home page, or explore our support center and give it another go.\n\n[_settings_ Support Center](https://ontraport.com/support) \n\n[_open\\_in\\_new_ Back to Ontraport.com](https://ontraport.com/) \n\n[](https://www.facebook.com/ontraport)\n\n[](https://www.instagram.com/ontraport/)\n\n[](https://twitter.com/ontraport)\n\n[](https://www.youtube.com/c/ontraport)\n\n_settings_\n\nTurn your business on with Ontraport.\n\n[Terms & Conditions](https://ontraport.com/legal?#o7f1b12e528cb) \u00a0\u00a0\u00a0\u00a0\u00a0\u00a0 [Legal](https://ontraport.com/legal) \u00a0\u00a0\u00a0\u00a0\u00a0\u00a0 [Privacy Policy](https://ontraport.com/legal?#odb99feb709d7) \u00a0\u00a0\u00a0\u00a0\u00a0\u00a0 [Service Status](https://ontraport.com/service-status)\n\nAbout Ontraport\n\nPartners & Integrations\n\nResources\n\nGetting Started\n\n[![Image 1](https://optassets.ontraport.com/opt_assets/blocks/common/iconsets/monochromatic-white/facebook.png)](https://www.facebook.com/ontraport)\n\n[![Image 2](https://optassets.ontraport.com/opt_assets/blocks/common/iconsets/monochromatic-white/instagram.png)](https://www.instagram.com/ontraport/)\n\n[![Image 3](https://optassets.ontraport.com/opt_assets/blocks/common/iconsets/monochromatic-white/twitter.png)](https://twitter.com/ontraport)\n\n[![Image 4](https://optassets.ontraport.com/opt_assets/blocks/common/iconsets/monochromatic-white/youtube.png)](https://www.youtube.com/channel/UCeun0dpuidRiVXKPqQaAwug)\n\n[About Us](https://ontraport.com/about \"Link: https://ontraport.com/about\")\n\n[Pricing](https://ontraport.com/pricing \"Link: https://ontraport.com/pricing\")\n\n[Press](https://ontraport.com/press \"Link: https://ontraport.com/press\")\n\n[Careers](https://ontraport.com/careers \"Link: https://ontraport.com/careers\")\n\n[Service Status](https://ontraport.com/service-status \"Link: https://ontraport.com/service-status\")\n\n[Legal](https://ontraport.com/legal \"Link: https://ontraport.com/legal\")\n\n[Expert Directory](https://ontraport.com/partners/experts \"Link: https://ontraport.com/partners/experts\")\n\n[Partner Program](https://ontraport.com/partners \"Link: https://ontraport.com/partners\")\n\n[Integrations](https://ontraport.com/integrations \"Link: https://ontraport.com/integrations\")\n\n[API Documentation](https://api.ontraport.com/doc/ \"Link: https://api.ontraport.com/doc/\")\n\n[Partner Login](https://partners.ontraport.com/ \"Link: https://partners.ontraport.com/\")\n\n[Expert Login](https://partners.ontraport.com/certified-consultants-2/ \"Link: https://partners.ontraport.com/certified-consultants-2/\")\n\n[Blog](https://ontraport.com/blog/ \"Link: https://ontraport.com/blog/\")\n\n[Support Center](https://ontraport.com/support/ \"Link: https://ontraport.com/support/\")\n\n[Ontraport University](https://ontraport.com/university \"Link: https://ontraport.com/university\")\n\n[Postmaster Team](https://ontraport.com/postmaster \"Link: https://ontraport.com/postmaster\")\n\n[Free Trial](https://ontraport.com/signup-pro \"Link: https://ontraport.com/signup-pro\")\n\n[Discovery Call](https://ontraport.com/discovery-call \"Link: https://ontraport.com/discovery-call\")\n\n[Setup Wizards](https://ontraport.com/setup-wizards \"Link: https://ontraport.com/setup-wizards\")\n\n[Customer Love](https://ontraport.com/reviews \"Link: https://ontraport.com/reviews\")\n\n[Industries we serve](https://ontraport.com/select-your-industry \"Link: https://ontraport.com/select-your-industry\")\n\n\\[bot\\_catcher\\]\n\nThis page does not exist. You can return to the previous page, visit our home page, or explore our support center to give it another go.",
      "error": null,
      "pricing_data": {
        "app_id": "ontraport",
        "app_name": "Ontraport",
        "app_slug": "ontraport",
        "pricing_url": "https://ontraport.com/pricing",
        "source_url": "https://ontraport.com/",
        "all_pricing_urls": [
          "https://ontraport.com/pricing"
        ],
        "price_model_type": [
          "PriceModelType.SUBSCRIPTION"
        ],
        "has_free_tier": false,
        "has_free_trial": true,
        "free_trial_period_days": null,
        "currency": "USD",
        "is_pricing_public": false,
        "pricing_page_accessible": false,
        "pricing_notes": "The pricing page was not accessible, and detailed pricing information could not be extracted.",
        "pricing_tiers": null,
        "usage_based_pricing": null,
        "ai_specific_pricing": null,
        "promotional_offers": null,
        "additional_fees": null,
        "extraction_timestamp": "2025-04-15T05:24:50.925548",
        "schema_validated": true,
        "confidence_score": 90,
        "extraction_error": false,
        "json_repaired": false
      },
      "pricing_analyzed": true
    }
  ],
  "results_directory": "pricing_results\\ontraport\\20250415_052451"
}