{
  "app_name": "GitHub",
  "app_slug": "github",
  "search_term": "Find the official pricing page URL for GitHub (github.com). Only provide the exact URL to the pricing page, not a summary of pricing information.",
  "timestamp": 1744704877.543551,
  "response_text": [
    "The official GitHub pricing page URL is: [https://github.com/pricing](https://github.com/pricing)\u30103:0\u2020source\u3011."
  ],
  "citations": [
    {
      "title": "Pricing \u00b7 Plans for every developer - GitHub",
      "url": "https://github.com/pricing"
    }
  ],
  "extracted_content": [
    {
      "url": "https://github.com/pricing",
      "is_accessible": true,
      "content": "Pricing \u00b7 Plans for every developer \u00b7 GitHub\n===============                                       \n\n[Skip to content](https://github.com/pricing#start-of-content)  \n\nGitHub Copilot is now available for free. [Learn more](https://github.com/features/copilot/?utm_source=github&utm_medium=banner&utm_campaign=copilotfree-bannerheader-pricing)\n\nNavigation Menu\n---------------\n\nToggle navigation\n\n[](https://github.com/)\n\n[Sign in](https://github.com/login?return_to=https%3A%2F%2Fgithub.com%2Fpricing)\n\n*   Product\n    \n    *   [GitHub Copilot Write better code with AI](https://github.com/features/copilot)\n    *   [GitHub Advanced Security Find and fix vulnerabilities](https://github.com/security/advanced-security)\n    *   [Actions Automate any workflow](https://github.com/features/actions)\n    *   [Codespaces Instant dev environments](https://github.com/features/codespaces)\n    *   [Issues Plan and track work](https://github.com/features/issues)\n    *   [Code Review Manage code changes](https://github.com/features/code-review)\n    *   [Discussions Collaborate outside of code](https://github.com/features/discussions)\n    *   [Code Search Find more, search less](https://github.com/features/code-search)\n    \n    Explore\n    \n    *   [All features](https://github.com/features)\n    *   [Documentation](https://docs.github.com/)\n    *   [GitHub Skills](https://skills.github.com/)\n    *   [Blog](https://github.blog/)\n    \n*   Solutions\n    \n    By company size\n    \n    *   [Enterprises](https://github.com/enterprise)\n    *   [Small and medium teams](https://github.com/team)\n    *   [Startups](https://github.com/enterprise/startups)\n    *   [Nonprofits](https://github.com/solutions/industry/nonprofits)\n    \n    By use case\n    \n    *   [DevSecOps](https://github.com/solutions/use-case/devsecops)\n    *   [DevOps](https://github.com/solutions/use-case/devops)\n    *   [CI/CD](https://github.com/solutions/use-case/ci-cd)\n    *   [View all use cases](https://github.com/solutions/use-case)\n    \n    By industry\n    \n    *   [Healthcare](https://github.com/solutions/industry/healthcare)\n    *   [Financial services](https://github.com/solutions/industry/financial-services)\n    *   [Manufacturing](https://github.com/solutions/industry/manufacturing)\n    *   [Government](https://github.com/solutions/industry/government)\n    *   [View all industries](https://github.com/solutions/industry)\n    \n    [View all solutions](https://github.com/solutions)\n    \n*   Resources\n    \n    Topics\n    \n    *   [AI](https://github.com/resources/articles/ai)\n    *   [DevOps](https://github.com/resources/articles/devops)\n    *   [Security](https://github.com/resources/articles/security)\n    *   [Software Development](https://github.com/resources/articles/software-development)\n    *   [View all](https://github.com/resources/articles)\n    \n    Explore\n    \n    *   [Learning Pathways](https://resources.github.com/learn/pathways)\n    *   [Events & Webinars](https://resources.github.com/)\n    *   [Ebooks & Whitepapers](https://github.com/resources/whitepapers)\n    *   [Customer Stories](https://github.com/customer-stories)\n    *   [Partners](https://partner.github.com/)\n    *   [Executive Insights](https://github.com/solutions/executive-insights)\n    \n*   Open Source\n    \n    *   [GitHub Sponsors Fund open source developers](https://github.com/sponsors)\n    \n    *   [The ReadME Project GitHub community articles](https://github.com/readme)\n    \n    Repositories\n    \n    *   [Topics](https://github.com/topics)\n    *   [Trending](https://github.com/trending)\n    *   [Collections](https://github.com/collections)\n    \n*   Enterprise\n    \n    *   [Enterprise platform AI-powered developer platform](https://github.com/enterprise)\n    \n    Available add-ons\n    \n    *   [GitHub Advanced Security Enterprise-grade security features](https://github.com/security/advanced-security)\n    *   [Copilot for business Enterprise-grade AI features](https://github.com/features/copilot/copilot-business)\n    *   [Premium Support Enterprise-grade 24/7 support](https://github.com/premium-support)\n    \n*   [Pricing](https://github.com/pricing)\n\nSearch or jump to...\n\nSearch code, repositories, users, issues, pull requests...\n==========================================================\n\nSearch\n\nClear\n\n[Search syntax tips](https://docs.github.com/search-github/github-code-search/understanding-github-code-search-syntax)\n\nProvide feedback\n================\n\nWe read every piece of feedback, and take your input very seriously.\n\n Include my email address so I can be contacted\n\nCancel Submit feedback\n\nSaved searches\n==============\n\nUse saved searches to filter your results more quickly\n------------------------------------------------------\n\nName  \n\nQuery \n\nTo see all available qualifiers, see our [documentation](https://docs.github.com/search-github/github-code-search/understanding-github-code-search-syntax).\n\nCancel Create saved search\n\n[Sign in](https://github.com/login?return_to=https%3A%2F%2Fgithub.com%2Fpricing)\n\n[Sign up](https://github.com/signup?ref_cta=Sign+up&ref_loc=header+logged+out&ref_page=%2Fpricing&source=header) Reseting focus\n\nYou signed in with another tab or window. Reload to refresh your session. You signed out in another tab or window. Reload to refresh your session. You switched accounts on another tab or window. Reload to refresh your session. Dismiss alert\n\n{{ message }}\n\nTry the Copilot-powered platform\n================================\n\nWe get it, there's a lot you can do with GitHub. That\u2019s why we've packed all of it into a single risk-free trial that includes GitHub Enterprise, Copilot, and Advanced Security.\n\n[Start free for 30 days](https://github.com/organizations/enterprise_plan)\n\nFree\n----\n\nThe basics for individuals  \nand organizations\n\n### $ 0 USD per month\n\n### \n\n$ 0 USD\n\nper month forever\n\n[Join for free](https://github.com/join?plan=free&ref_cta=Join%2520for%2520free&ref_loc=cards&ref_page=%2Fpricing&source=pricing-card-free)\n\n*   Unlimited public/private repositories\n    \n    Host open source projects in public GitHub repositories, accessible via web or command line. Public repositories are accessible to anyone at GitHub.com.\n    \n*   Dependabot security and version updates\n    \n    Keep projects secure by automatically opening pull requests to update vulnerable dependencies and keep them up to date.\n    \n*   2,000 CI/CD minutes/month\n    \n    Free for public repositories\n    \n    Use execution minutes with GitHub Actions to automate your software development workflows. Write tasks and combine them to build, test, and deploy any code project on GitHub.\n    \n*   500MB of Packages storage\n    \n    Free for public repositories\n    \n    Host your own software packages or use them as dependencies in other projects. Both private and public hosting available.\n    \n*   Issues & Projects\n    \n    Give your developers flexible features for project management that adapts to any team, project, and workflow \u2014 all alongside your code.\n    \n*   Community support\n    \n    Get help with most of your GitHub questions and issues in our Community Forum.\n    \n\n#### Featured add-ons\n\n*   GitHub Copilot Access\n    \n    With [GitHub Copilot](https://github.com/features/copilot), get suggestions for whole lines or entire functions\u2014right inside your\u00a0editor.\n    \n*   GitHub Codespaces Access\n    \n    With [GitHub Codespaces](https://github.com/features/codespaces), get an instant dev environment in the cloud, so you can code anywhere on any device.\n    \n\nShow features\n\nMost popular\n\nTeam\n----\n\nAdvanced collaboration for  \nindividuals and organizations\n\n### $ 4 USD per user/month\n\n### \n\n$ 4 USD\n\nper user/month for the first 12 months\\*\n\n[Continue with Team](https://github.com/join?plan=business&pricing_exp=true&ref_cta=Continue%2520with%2520Team&ref_loc=cards&ref_page=%2Fpricing&setup_organization=true&source=pricing-card-team)\n\n*   Everything included in Free, plus...\n*   Access to GitHub Codespaces\n    \n    Blazing fast cloud developer environments with flexible compute and pre-configured containers, developers can code, collaborate, and debug from any browser. Pay only for what you use with compute fees starting at $0.18/hr and storage fees at $0.07/GB per month.\n    \n*   Protected branches\n    \n    Enforce restrictions on how code branches are merged, including requiring reviews by selected collaborators, or allowing only specific contributors to work on a particular branch.\n    \n*   Multiple reviewers in pull requests\n    \n    Assign multiple users or a team to review a pull request.\n    \n*   Draft pull requests\n    \n    Easily discuss and collaborate on pull requests before submitting to formal review.\n    \n*   Code owners\n    \n    Automatically request reviews\u2014or require approval\u2014by selected contributors when changes are made to sections of code that they own.\n    \n*   Required reviewers\n    \n    Ensure that pull requests have a specific number of approving reviews before collaborators can make changes to a protected branch.\n    \n*   Pages and Wikis\n    \n    Host documentation and simple websites for your project in a wiki format that contributors can easily edit either on the web or command line.\n    \n*   Environment deployment branches and secrets\n    \n    A job cannot access secrets that are defined in an environment unless it is running on the specified branch.\n    \n*   3,000 CI/CD minutes/month\n    \n    Free for public repositories\n    \n    Use execution minutes with GitHub Actions to automate your software development workflows. Write tasks and combine them to build, test, and deploy any code project on GitHub.\n    \n*   2GB of Packages storage\n    \n    Free for public repositories\n    \n    Host your own software packages or use them as dependencies in other projects. Both private and public hosting available.\n    \n*   Web-based support\n    \n    GitHub Support can help you troubleshoot issues you run into while using GitHub.\n    \n\n#### Featured add-ons\n\n*   GitHub Secret Protection\n    \n    Ensure your secrets stay secure. Mitigate risk associated with exposed secrets in your repositories, while preventing new leaks before they happen with push protection.\n    \n*   GitHub Code Security\n    \n    Find and fix vulnerabilities in your code before they reach production. Prioritize your Dependabot alerts with automated triage rules.\n    \n\nShow features\n\nRecommended\n\nEnterprise\n----------\n\nSecurity, compliance,  \nand flexible deployment\n\nStarting at\n\n### $ 21 USD per user/month\n\n### \n\n$ 21 USD\n\nper user/month for the first 12 months\\*\n\n[Start a free trial](https://github.com/organizations/enterprise_plan?ref_cta=Start%2520a%2520free%2520trial&ref_loc=card&ref_page=pricing)\n\n[Contact Sales](https://github.com/enterprise/contact?ref_page=/pricing&ref_cta=Contact%20Sales&ref_loc=cards)\n\n*   Everything included in Team, plus...\n*   Data residency\n    \n    GitHub Enterprise Cloud offers a multi-tenant enterprise SaaS solution on Microsoft Azure, allowing you to choose a regional cloud deployment for data residency, so your in-scope data is stored at rest in a designated location. This is available in the EU and Australia with additional regions coming soon. [Contact our sales team](https://github.com/enterprise/contact/data-residency) to learn more.\n    \n*   Enterprise Managed Users\n    \n    Own and control the user accounts of your enterprise members through your identity provider (IdP).\n    \n*   User provisioning through SCIM\n    \n    Automatically invite members to join your organization when you grant access on your IdP. If you remove a member's access to your GitHub organization on your SAML IdP, the member will be automatically removed from the GitHub organization.\n    \n*   Enterprise Account to centrally manage multiple organizations\n    \n    GitHub Enterprise Cloud includes the option to create an enterprise account, which enables collaboration between multiple organizations, gives administrators a single point of visibility and management and brings license cost savings for identical users in multiple organizations.\n    \n*   Environment protection rules\n    \n    When a workflow job references an environment, the job won't start until all of the environment's protection rules pass.\n    \n*   Repository rules\n    \n    Enforce branch and tag restrictions across your organization, ensuring branch and tag protection across your repositories. Evaluate rules to asses impact before enforcement.\n    \n*   Audit Log API\n    \n    As a GitHub Enterprise Cloud organization administrator, you can now access log events using our GraphQL API and monitor the activity in your organization.\n    \n*   SOC1, SOC2, type 2 reports annually\n    \n    GitHub offers AICPA System and Organization Controls (SOC) 1 Type 2 and SOC 2 Type 2 reports with IAASB International Standards on Assurance Engagements, ISAE 3000, and ISAE 3402.\n    \n*   FedRAMP Tailored Authority to Operate (ATO)\n    \n    Government users can host projects on GitHub Enterprise Cloud with the confidence that our platform meets the low impact software-as-a-service (SaaS) baseline of security standards set by our U.S. federal government partners.\n    \n*   SAML single sign-on\n    \n    Use an identity provider to manage the identities of GitHub users and applications.\n    \n*   Advanced auditing\n    \n    Quickly review the actions performed by members of your organization. Keep copies of audit log data to ensure secure IP and maintain compliance for your organization.\n    \n*   GitHub Connect\n    \n    Share features and workflows between your GitHub Enterprise Server instance and GitHub Enterprise Cloud.\n    \n*   50,000 CI/CD minutes/month\n    \n    Free for public repositories\n    \n    Use execution minutes with GitHub Actions to automate your software development workflows. Write tasks and combine them to build, test, and deploy any code project on GitHub.\n    \n*   50GB of Packages storage\n    \n    Free for public repositories\n    \n    Host your own software packages or use them as dependencies in other projects. Both private and public hosting available.\n    \n\n#### Exclusive add-on\n\n*   Premium support\n    \n    With Premium, get a 30-minute SLA on Urgent tickets and 24/7 web and phone support via callback request. With Premium Plus, get everything in Premium, assigned Customer Reliability Engineer and more.  \n      \n    [Learn more about Premium Support](https://github.com/premium-support)\n    \n\nShow features\n\nAdditional add-ons\n------------------\n\n[### GitHub Copilot Get started for free with up to 2,000 completions and 50 chat requests per month. Compare plans](https://github.com/features/copilot#pricing)\n\n[### GitHub Codespaces Starting at $0.18 per hour of compute and $0.07 per GB of storage. Learn more](https://github.com/features/codespaces)\n\n[### Git Large File Storage $5 per month for 50 GB bandwidth and 50 GB of storage. Learn more](https://docs.github.com/repositories/working-with-files/managing-large-files/about-git-large-file-storage)\n\n[### GitHub Advanced Security Secret Protection $19 per committer/ per month. Code Security $30 per committer/ per month Learn more](https://github.com/security/plans)\n\n[Compare all features](https://github.com/pricing#compare-features)\n\n ![Image 1: Trustpilot](https://github.githubassets.com/assets/trustpilot-946048c9ea8c.svg) ![Image 2: Netdata](https://github.githubassets.com/assets/netdata-402a6c7c5e1b.svg) ![Image 3: American Airlines](https://github.githubassets.com/assets/american-airlines-b2705b73b06a.svg) ![Image 4: SAP](https://github.githubassets.com/assets/sap-43859daae47d.svg) ![Image 5: Spotify](https://github.githubassets.com/assets/spotify-e11be014f9e8.svg) ![Image 6: Stripe](https://github.githubassets.com/assets/stripe-2ceb23f9d540.png) ![Image 7: Ford](https://github.githubassets.com/assets/ford-4fe02686f28c.png)![Image 8: Nubank](https://github.githubassets.com/assets/nubank-a2338da09cf7.png)\n\n  ![Image 9: Trustpilot office](https://github.githubassets.com/assets/trustpilot-be07df951cf3.jpg) ![Image 10: Netdata team](https://github.githubassets.com/assets/netdata-d87629cd8043.jpg)  ![Image 11: American Airlines office](https://github.githubassets.com/assets/american-airlines-27bc9b69249f.jpg)  ![Image 12: SAP meeting](https://github.githubassets.com/assets/sap-221410edcdae.jpeg)  ![Image 13: Spotify studio](https://github.githubassets.com/assets/spotify-4e8add4d1e17.jpg)  ![Image 14: Stripe office](https://github.githubassets.com/assets/stripe-887a7be6edbb.jpg)  ![Image 15: Ford car interior](https://github.githubassets.com/assets/ford-b1aa6cf2ef87.jpg)  ![Image 16: Nubank office](https://github.githubassets.com/assets/nubank-b168ffda4c13.jpg)\n\n\u201cGitHub is the world\u2019s mono repository, so sharing our open source there is natural.\u201d\n\n\u2014 Martin Andersen, VP of Engineering, Trustpilot\n\n[Read the case study](https://github.com/customer-stories/trustpilot)\n\n\u201cGitHub Advanced Security is there for every pull request and excels compared to other static analysis tools we have used.\u201d\n\n\u2014 Dimosthenis Kaponis, CTO, Netdata\n\n[Read the case study](https://github.com/customer-stories/netdata)\n\n\u201cGitHub keeps us up to speed with the industry\u2019s best tools. We want new hires to know GitHub is in our toolchain\u2014it makes them excited to join us.\u201d\n\n\u2014 Spencer Kaiser, Principal Architect of Emerging Tech, American Airlines\n\n[Read the case study](https://github.com/customer-stories/american-airlines)\n\n\u201cThis collaborative way of building software is unstoppable. It isn\u2019t going away\u2014and GitHub has its place in that. We can make the whole company rethink how they build software.\u201d\n\n\u2014 Ingo Sauerzapf, SAP Cloud Development Tools Manager\n\n[Read the case study](https://github.com/customer-stories/sap)\n\n\u201cPeople know what a pull request is because it\u2019s how they contribute to open source projects. We have many developers who are well-versed with GitHub, either for personal development or previous roles. With GitHub Enterprise, no one has to relearn the wheel.\u201d\n\n\u2014 Laurent Ploix, Product Manager, Spotify\n\n[Read the case study](https://github.com/customer-stories/spotify)\n\n\u201cI have seen some truly revolutionary actions happen in communities on GitHub. People are collaborating on code but they\u2019re also having foundational conversations on best practices and how software, as a whole, is built. More and more, GitHub is an internet archive. It\u2019s a deeply social and critical piece of our infrastructure.\u201d\n\n\u2014 Michael Glukhovsky, Developer, Stripe\n\n[Read the case study](https://github.com/customer-stories/stripe)\n\n\u201cWhen we started talking about code reuse, we felt like we already had the perfect platform in place: GitHub.\u201d\n\n\u2014 Timothy Carmean, Software Processes and Tools Supervisor, Ford\n\n[Read the case study](https://github.com/customer-stories/ford)\n\n\u201cUsing GitHub Enterprise Cloud removes the burden of managing infrastructure, and we don\u2019t need to worry about the availability of our versioning code, source code and versioning tools. It lets us focus on what\u2019s important for our business, and that\u2019s our customers.\u201d\n\n\u2014 Victor Gomes, Infosec Tech Manager, Nubank\n\n[Read the case study](https://github.com/customer-stories/nubank)\n\nCompare features\n================\n\nFeatures on team Switch plans\n\nSelect a plan to review its features\n\nFree Team Enterprise\n\nFeatures\n\nFree\n----\n\nTeam\n----\n\nEnterprise\n----------\n\nPricing\n\n$0 USD\n\nper month\n\n$0 USD\n\nper month forever\n\n$4 USD\n\nper user/month\n\n$4 USD\n\nper user/month for the first 12 months\\*\n\n$21 USD\n\nper user/month\n\n$21 USD\n\nper user/month for the first 12 months\\*\n\nHow to get started\n\n[Join for free](https://github.com/join?ref_cta=Join%2520for%2520free&ref_loc=pricing%2520comparison&ref_page=%2Fpricing&source=pricing-comparison-free)\n\n[Continue with Team](https://github.com/join?plan=business&ref_cta=Continue%2520with%2520Team&ref_loc=pricing-comparison&ref_page=%2Fpricing&setup_organization=true&source=pricing-comparison-team)\n\n[Start a free trial](https://github.com/organizations/enterprise_plan?ref_cta=Start%2520a%2520free%2520trial&ref_loc=card&ref_page=pricing) [Contact Sales](https://github.com/enterprise/contact?ref_page=/pricing&ref_cta=Contact%20Sales&ref_loc=pricing%20comparison)\n\n### Code management\n\nPublic repositories\n\nUnlimited\n\nUnlimited\n\nUnlimited\n\nHost open source projects in public GitHub repositories, accessible via web or command line. Public repositories are accessible to anyone at GitHub.com.\n\nUnlimited\n\nUnlimited\n\nUnlimited\n\nPrivate repositories\n\nUnlimited\n\nUnlimited\n\nUnlimited\n\nHost code in private GitHub repositories, accessible via appliance, web, and command line. Private repositories are only accessible to you and people you share them with.\n\nUnlimited\n\nUnlimited\n\nUnlimited\n\n### Code workflow\n\nGitHub Codespaces\n\n$0 spend limit  \nWith policies and controls\n\nAbility to increase spend limit\n\nAbility to increase spend limit\n\nSpin up fully configured dev environments in the cloud with the power of your favorite editor. A \"core hour\" denotes compute usage. On a 2-core machine, you would get 60 hours free. On a 4-core machine, you would get 30 hours free, etc. Free hours are assigned to personal accounts, rather than free organizations.\n\n$0 spend limit  \nWith policies and controls\n\nAbility to increase spend limit\n\nAbility to increase spend limit\n\nGitHub Actions\n\n2,000 minutes/monthFree for public repositories\n\n3,000 minutes/monthFree for public repositories\n\n50,000 minutes/monthFree for public repositories\n\nUse execution minutes with GitHub Actions to automate your software development workflows. Write tasks and combine them to build, test, and deploy any code project on GitHub. Minutes are free for public repositories.  \n  \n[Learn more about billing](https://docs.github.com/billing/managing-billing-for-github-actions/about-billing-for-github-actions)\n\n2,000 minutes/monthFree for public repositories\n\n3,000 minutes/monthFree for public repositories\n\n50,000 minutes/monthFree for public repositories\n\nGitHub Packages\n\n500 MBFree for public repositories\n\n2GBFree for public repositories\n\n50GBFree for public repositories\n\nHost your own software packages or use them as dependencies in other projects. Both private and public hosting available. Packages are free for public repositories.\n\n500 MBFree for public repositories\n\n2GBFree for public repositories\n\n50GBFree for public repositories\n\nCode reviews\n\nReview new code, see visual code changes, and confidently merge code changes with automated status checks.\n\nPull requests\n\nAllow contributors to easily notify you of changes they've pushed to a repository \u2013 with access limited to the contributors you specify. Easily merge changes you accept.\n\nProtected branches\n\nPublic repositories\n\nEnforce restrictions on how code branches are merged, including requiring reviews by selected collaborators, or allowing only specific contributors to work on a particular branch.\n\nPublic repositories\n\nCode owners\n\nPublic repositories\n\nAutomatically request reviews \u2013 or require approval \u2013 by selected contributors when changes are made to sections of code that they own.\n\nPublic repositories\n\nDraft pull requests\n\nPublic repositories\n\nEasily discuss and collaborate on pull requests before submitting to formal review.\n\nPublic repositories\n\nMultiple pull request assignees\n\nPublic repositories\n\nAssign more than one person to a pull request.\n\nPublic repositories\n\nRepository insights\n\nPublic repositories\n\nSee data about activity and contributions within your repositories, including trends. You can use this data to improve collaboration and make development faster and more effective.\n\nPublic repositories\n\nScheduled reminders\n\nPublic repositories\n\nSend scheduled messages to you or your team listing open pull requests.\n\nPublic repositories\n\nAutomatic code review assignment\n\nPublic repositories\n\nAutomatically assign code reviews to members of your team based on one of two algorithms.\n\nPublic repositories\n\nEnvironment protection rules\n\nPublic repositories\n\nPublic repositories\n\nWhen a workflow job references an environment, the job won't start until all of the environment's protection rules pass.\n\nPublic repositories\n\nPublic repositories\n\nEnvironment deployment branches and secrets\n\nPublic repositories\n\nA job cannot access secrets that are defined in an environment unless it is running on the specified branch.\n\nPublic repositories\n\n### Collaboration\n\nCollaborators for public repositories\n\nUnlimited\n\nUnlimited\n\nUnlimited\n\nInvite any GitHub member, or all GitHub members, to work with you on code in a public repository you control \u2013 including making changes and opening issues.\n\nUnlimited\n\nUnlimited\n\nUnlimited\n\nCollaborators for private repositories\n\nUnlimited\n\n$4\n\nper user/month\n\n$21\n\nper user/month\n\nInvite any GitHub member, or all GitHub members, to work with you on code in a private repository you control \u2013 including making changes and opening issues.\n\nUnlimited\n\n$4\n\nper user/month\n\n$21\n\nper user/month\n\nIssues\n\nTrack bugs, enhancements, and other requests, prioritize work, and communicate with stakeholders as changes are proposed and merged.\n\nProjects\n\nVisualize and manage issues and pull requests across tables, boards, and roadmaps with custom fields and views that you can arrange to suit your workflow.\n\nMilestones\n\nTrack progress on groups of issues or pull requests in a repository, and map groups to overall project goals.\n\nTeam discussions\n\nDiscuss any topic, unattached to a specific project or issue. Control who has access, notify discussion participants with updates, and link from anywhere.\n\nOrganization and team management\n\nManage access to projects on a team-by-team, or individual user, basis.\n\nPages and wikis\n\nPublic repositories\n\nHost documentation and simple websites for your project in a wiki format that contributors can easily edit either on the web or command line.\n\nPublic repositories\n\nMultiple issue assignees\n\nPublic repositories\n\nAssign more than one person to an issue.\n\nPublic repositories\n\n### GitHub Secret Protection\n\nPush protection\n\nPublic repositories\n\nPrevent secret exposures by proactively blocking secrets before they reach your code.\n\nPublic repositories\n\nSecret scanning\n\nPublic repositories\n\nDetect and manage exposed secrets across git history, pull requests, issues, and wikis.\n\nPublic repositories\n\nProvider patterns\n\nPublic repositories\n\nGitHub collaborates with AWS, Azure, and Google Cloud to detect secrets with high accuracy. This minimizes false positives, letting you focus on what matters.\n\nPublic repositories\n\nProvider notification\n\nPublic repositories\n\nPublic repositories\n\nPublic repositories\n\nProviders get real-time alerts when their tokens appear in public code, enabling them to notify, quarantine, or revoke secrets.\n\nPublic repositories\n\nPublic repositories\n\nPublic repositories\n\nValidity checks\n\nPrioritize active secrets with validity checks for provider patterns.\n\nCopilot secret scanning\n\nUse AI to detect unstructured like passwords\u2014without the noise.\n\nGeneric patterns\n\nDetect tokens from unknown providers, including HTTP authentication headers, connection strings, and private keys.\n\nCustom patterns\n\nCreate your own patterns and find organization-specific secrets.\n\nPush protection bypass controls\n\nManage who can bypass push protection and when.\n\nInsights in security overview\n\nUnderstand how risk is distributed across your organization with security metrics and insight dashboards.\n\nScan history API\n\nReview how and when GitHub scans your repositories for secrets.\n\n### Code Security\n\nCopilot Autofix\n\nPublic repositories\n\nPowered by GitHub Copilot, generate automatic fixes for 90% of alert types in JavaScript, Typescript, Java, and Python.\n\nPublic repositories\n\nThird party extensibility for code scanning alerts\n\nPublic repositories\n\nCentralize your findings across all your scanning tools via SARIF upload to GitHub.\n\nPublic repositories\n\nContextual vulnerability intelligence and advice\n\nPublic repositories\n\nQuickly remediate with context provided by Copilot Autofix.\n\nPublic repositories\n\nCodeQL\n\nPublic repositories\n\nUncover vulnerabilities in your code with our industry-leading semantic code analysis.\n\nPublic repositories\n\nSecurity campaigns\n\nReduce security debt and burn down your security backlog with security campaigns.\n\nDependency graph\n\nGet a clear view of your project\u2019s dependencies with a summary of manifest, lock files, and submitted dependencies via the API.\n\nDependency review action\n\nCatch insecure dependencies before adding them and get insights on licenses, dependents, and age.\n\nDependabot custom auto-triage rules\n\nDefine alert-centric policies to control how Dependabot handles alerts and pull requests.\n\nDependabot security updates with grouped updates\n\nAutomated pull requests that batch dependency updates for known vulnerabilities.\n\nDependabot version updates\n\nAutomated pull requests that keep your dependencies up to date.\n\nInsights in security overview\n\nGet a clear view of risk distribution with security metrics and dashboards.\n\n### Platform security and compliance\n\nRepository rulesets\n\nPublic repositories\n\nEnforce consistent code standards, security, and compliance across branches and tags.\n\nPublic repositories\n\nSBOMs\n\nExport a software bill of materials (SBOM) for your repository.\n\nArtifact attestations\n\nPublic repositories\n\nPublic repositories\n\nEnsure unfalsifiable provenance and integrity for your software.\n\nPublic repositories\n\nPublic repositories\n\nGitHub Security Advisories\n\nRole-based access control\n\nDefine users' level of access to your code, data and settings.\n\nRequired 2FA\n\nUse an extra layer of security with two factor authentication (2FA) when logging into GitHub.\n\nAudit log\n\nQuickly review the actions performed by members of your organization.\n\nAudit log API\n\nKeep copies of audit log data to ensure secure IP and maintain compliance for your organization.\n\nGitHub Connect\n\nShare features and workflows between your GitHub Enterprise Server instance and GitHub Enterprise Cloud.\n\nSAML single sign-on (SSO)\n\nUse an identity provider to manage the identities of GitHub users and applications.\n\nLDAP\n\nAccess GitHub Enterprise Server using your existing accounts and centrally manage repository access.\n\nIP allow list\n\nEnterprise Cloud\n\nLimit access to known allowed IP addresses.\n\nEnterprise Cloud\n\n### Marketplace and integrations\n\nGitHub Apps\n\nUnlimited\n\nUnlimited\n\nUnlimited\n\nInstall apps that integrate directly with GitHub's API to improve development workflows \u2013 or build your own for private use or publication in the GitHub Marketplace.\n\nUnlimited\n\nUnlimited\n\nUnlimited\n\nStatus checks\n\nDefine tests that GitHub automatically runs against code being committed to your repository, and get details about failures and what is causing them.\n\nPre-receive hooks\n\nEnterprise Server\n\nCreate requirements for automatically accepting or rejecting a push based on the contents of the push.\n\nEnterprise Server\n\n### Support and deployment\n\nCommunity Support\n\nGet help with most of your GitHub questions and issues in our Community Forum.\n\nStandard Support\n\nGitHub Support can help you troubleshoot issues you run into while using GitHub. Get support via the web.\n\nPremium and Premium Plus Support\n\nAvailable\n\nWith Premium, get a 30-minute SLA on Urgent tickets and 24/7 web and phone support via callback request. With Premium Plus, get everything in Premium, assigned Customer Reliability Engineer and more.  \n  \n[Learn more about Premium Support](https://github.com/premium-support)\n\nAvailable\n\nInvoice billing\n\nPay bills via invoice, rather than using your credit card.\n\nSelf-hosted deployment\n\nEnterprise Server\n\nSelf-hosted GitHub for on-prem appliances or self-managed cloud tenants.\n\nEnterprise Server\n\nData residency\n\nEnterprise Cloud\n\nMulti-tenant enterprise SaaS solution on Microsoft Azure, allowing you to choose a regional cloud deployment for data residency, so your in-scope data is stored at rest in a designated location. This is available in the EU and Australia with additional regions coming soon. [Contact our sales team](https://github.com/enterprise/contact/data-residency) to learn more.\n\nEnterprise Cloud\n\n![Image 17: GitHub Community Icon](https://github.githubassets.com/assets/icon-community-1ade392d94bd.svg)\n\nWe love people who are changing the\u00a0world\n-----------------------------------------\n\n[### Open source teams If you manage multiple contributors, there\u2019s a free option. We also run GitHub Sponsors, where we help fund your work. Learn more](https://github.com/team)\n\n[### Students and teachers We\u2019ve partnered with industry leaders to give students and teachers free access to the best developer tools\u2014for the school year and beyond. Learn more](https://education.github.com/)\n\n[### Nonprofits Work for a government-recognized nonprofit, association, or 501(c)(3)? Get a discounted Organization on us. Learn more](https://github.com/solutions/industry/nonprofits)\n\nSite-wide Links\n---------------\n\n[](https://github.com/)\n\n### Subscribe to our developer newsletter\n\nGet tips, technical guides, and best practices. Twice a month. Right in your inbox.\n\n[Subscribe](https://resources.github.com/newsletter/)\n\n### Product\n\n*   [Features](https://github.com/features)\n*   [Enterprise](https://github.com/enterprise)\n*   [Copilot](https://github.com/features/copilot)\n*   [Security](https://github.com/security)\n*   [Pricing](https://github.com/pricing)\n*   [Team](https://github.com/team)\n*   [Resources](https://resources.github.com/)\n*   [Roadmap](https://github.com/github/roadmap)\n*   [Compare GitHub](https://resources.github.com/devops/tools/compare)\n\n### Platform\n\n*   [Developer API](https://docs.github.com/get-started/exploring-integrations/about-building-integrations)\n*   [Partners](https://partner.github.com/)\n*   [Education](https://github.com/edu)\n*   [GitHub CLI](https://cli.github.com/)\n*   [GitHub Desktop](https://desktop.github.com/)\n*   [GitHub Mobile](https://github.com/mobile)\n\n### Support\n\n*   [Docs](https://docs.github.com/)\n*   [Community Forum](https://github.community/)\n*   [Professional Services](https://services.github.com/)\n*   [Premium Support](https://github.com/enterprise/premium-support)\n*   [Skills](https://skills.github.com/)\n*   [Status](https://www.githubstatus.com/)\n*   [Contact GitHub](https://support.github.com/?tags=dotcom-footer)\n\n### Company\n\n*   [About](https://github.com/about)\n*   [Customer stories](https://github.com/customer-stories?type=enterprise)\n*   [Blog](https://github.blog/)\n*   [The ReadME Project](https://github.com/readme)\n*   [Careers](https://github.careers/)\n*   [Newsroom](https://github.com/newsroom)\n*   [Inclusion](https://github.com/about/diversity)\n*   [Social Impact](https://socialimpact.github.com/)\n*   [Shop](https://shop.github.com/)\n\n*   \u00a9 2025 GitHub, Inc.\n*   [Terms](https://docs.github.com/site-policy/github-terms/github-terms-of-service)\n*   [Privacy](https://docs.github.com/site-policy/privacy-policies/github-privacy-statement) ([Updated 02/2024](https://github.com/github/site-policy/pull/582))\n*   [Sitemap](https://github.com/sitemap)\n*   [What is Git?](https://github.com/git-guides)\n*   Manage cookies\n*   Do not share my personal information\n\n*   [GitHub on LinkedIn](https://www.linkedin.com/company/github)\n*   [GitHub on Instagram](https://www.instagram.com/github)\n*   [GitHub on YouTube](https://www.youtube.com/github)\n*   [GitHub on X](https://x.com/github)\n*   [GitHub on TikTok](https://www.tiktok.com/@github)\n*   [GitHub on Twitch](https://www.twitch.tv/github)\n*   [GitHub\u2019s organization on GitHub](https://github.com/github)\n\nYou can\u2019t perform that action at this time.\n\nWhether you're starting an open source project or choosing new tools for your team, we\u2019ve got you covered.",
      "error": null,
      "pricing_data": {
        "app_id": "github",
        "app_name": "GitHub",
        "app_slug": "github",
        "pricing_url": "https://github.com/pricing",
        "source_url": "https://github.com/pricing",
        "all_pricing_urls": [
          "https://github.com/pricing"
        ],
        "price_model_type": [
          "PriceModelType.SUBSCRIPTION",
          "PriceModelType.FREE_TIER",
          "PriceModelType.USAGE_BASED"
        ],
        "has_free_tier": true,
        "has_free_trial": true,
        "free_trial_period_days": 30,
        "currency": "USD",
        "is_pricing_public": true,
        "pricing_page_accessible": true,
        "pricing_notes": "GitHub offers a free tier with unlimited repositories and limited CI/CD minutes and storage. Paid tiers include additional features and higher limits.",
        "pricing_tiers": [
          {
            "tier_name": "Free",
            "tier_description": "The basics for individuals and organizations",
            "monthly_price": 0.0,
            "annual_price": 0.0,
            "annual_discount_percentage": null,
            "setup_fee": null,
            "features": [
              "Unlimited public/private repositories",
              "Dependabot security and version updates",
              "2,000 CI/CD minutes/month",
              "500MB of Packages storage",
              "Issues & Projects",
              "Community support"
            ],
            "limits": {
              "users": "unlimited",
              "storage": "500MB",
              "operations": null,
              "api_calls": null,
              "integrations": null,
              "custom_limits": [
                {
                  "name": "CI/CD minutes",
                  "value": "2,000 per month"
                }
              ]
            }
          },
          {
            "tier_name": "Team",
            "tier_description": "Advanced collaboration for individuals and organizations",
            "monthly_price": 4.0,
            "annual_price": 48.0,
            "annual_discount_percentage": null,
            "setup_fee": null,
            "features": [
              "Everything included in Free",
              "Access to GitHub Codespaces",
              "Protected branches",
              "Multiple reviewers in pull requests",
              "Draft pull requests",
              "Code owners",
              "Required reviewers",
              "Pages and Wikis",
              "Environment deployment branches and secrets",
              "3,000 CI/CD minutes/month",
              "2GB of Packages storage",
              "Web-based support"
            ],
            "limits": {
              "users": "unlimited",
              "storage": "2GB",
              "operations": null,
              "api_calls": null,
              "integrations": null,
              "custom_limits": [
                {
                  "name": "CI/CD minutes",
                  "value": "3,000 per month"
                }
              ]
            }
          },
          {
            "tier_name": "Enterprise",
            "tier_description": "Security, compliance, and flexible deployment",
            "monthly_price": 21.0,
            "annual_price": 252.0,
            "annual_discount_percentage": null,
            "setup_fee": null,
            "features": [
              "Everything included in Team",
              "Data residency",
              "Enterprise Managed Users",
              "User provisioning through SCIM",
              "Enterprise Account to centrally manage multiple organizations",
              "Environment protection rules",
              "Repository rules",
              "Audit Log API",
              "SOC1, SOC2, type 2 reports annually",
              "FedRAMP Tailored Authority to Operate (ATO)",
              "SAML single sign-on",
              "Advanced auditing",
              "GitHub Connect",
              "50,000 CI/CD minutes/month",
              "50GB of Packages storage"
            ],
            "limits": {
              "users": "unlimited",
              "storage": "50GB",
              "operations": null,
              "api_calls": null,
              "integrations": null,
              "custom_limits": [
                {
                  "name": "CI/CD minutes",
                  "value": "50,000 per month"
                }
              ]
            }
          }
        ],
        "usage_based_pricing": [
          {
            "metric_name": "GitHub Codespaces",
            "unit": "per hour of compute",
            "base_price": 0.18,
            "tiers": null
          },
          {
            "metric_name": "Git Large File Storage",
            "unit": "per month",
            "base_price": 5.0,
            "tiers": [
              {
                "min": 0.0,
                "max": 50.0,
                "price": 5.0
              }
            ]
          },
          {
            "metric_name": "GitHub Advanced Security",
            "unit": "per committer per month",
            "base_price": 19.0,
            "tiers": null
          }
        ],
        "ai_specific_pricing": {
          "has_token_based_pricing": false,
          "input_token_price": null,
          "output_token_price": null,
          "models_pricing": null,
          "has_inference_pricing": false,
          "has_fine_tuning_pricing": false,
          "has_training_pricing": false,
          "ai_addon_available": true
        },
        "promotional_offers": null,
        "additional_fees": null,
        "extraction_timestamp": "2025-04-15T04:14:50.361532",
        "schema_validated": true,
        "confidence_score": 95,
        "extraction_error": false,
        "json_repaired": false
      },
      "pricing_analyzed": true
    }
  ],
  "results_directory": "pricing_results\\github\\20250415_041450"
}